Workbook

Sheet Read Me
A1: AI API / Infrastructure — 3-Year Financial Model
A2: 36-month integrated financial model — Read Me
A4: Overview
A5: A 36-month, formula-driven financial model for an AI API / infrastructure company with tiered customers, usage-based billing, and compute-heavy cost of revenue. Start on the Assumptions tab: set your Base / Upside / Downside inputs and pick a scenario. Every downstream tab recalculates automatically.
A7: How this workbook is organized
A8: Assumptions -> Headcount -> Revenue -> COGS & GM -> Opex -> Working Capital -> P&L -> Balance Sheet -> Cash Flow -> Cash & Runway -> Scenarios -> Visuals -> Checks. Data flows strictly left-to-right through that order: change an assumption, and every downstream tab recalculates automatically (workbook calculation mode is Automatic).
A10: Formatting legend
A11: Blue text on light-blue fill = an input you can edit (Assumptions tab, and scenario selector).
A12: Black text on white = a live formula. Do not hard-code over these cells.
A13: Cells on a light-gray band = a value linked in from another tab.
A15: Color palette
A16: Purple (#7B68EE)
... A35: 36 monthly periods, plus quarterly (12) and annual (3) roll-up columns on each schedule tab. Workbook calculation is set to Automatic — Excel recalculates on every edit. Deterministic, seeded default assumptions are provided so the model is internally consistent out of the box; replace them with your own numbers on the Assumptions tab.

Sheet Assumptions
A1: AI API / Infrastructure — 3-Year Financial Model — Assumptions
A2: Plain-language inputs. Edit the Base / Upside / Downside columns only — everything else in this workbook is a formula.
A4: Scenario selector: | C4: Base | D4: << Pick Base / Upside / Downside. This one cell drives every formula in the model.
A6: Assumption | B6: Unit | C6: Base | D6: Upside | E6: Downside | F6: Active (used in model) | G6: Notes / definition
A7: Company & Financial
A8: Starting cash balance | B8: $ | C8: 5000000 | D8: 5000000 | E8: 5000000 | F8: =CHOOSE(MATCH('Assumptions'!$C$4,{"Base","Upside","Downside"},0),C8,D8,E8) -> 0 | G8: Cash on hand at the start of month 1.
A9: Starting paid-in capital | B9: $ | C9: 6500000 | D9: 6500000 | E9: 6500000 | F9: =CHOOSE(MATCH('Assumptions'!$C$4,{"Base","Upside","Downside"},0),C9,D9,E9) -> 0 | G9: Cumulative equity raised before the modeled period.
A10: Income tax rate | B10: % | C10: 0 | D10: 0 | E10: 0 | F10: =CHOOSE(MATCH('Assumptions'!$C$4,{"Base","Upside","Downside"},0),C10,D10,E10) -> 0 | G10: Applied only when Earnings Before Tax is positive; no NOL schedule modeled.
A12: Customers & Volume
A13: Starter customers at month 1 start | B13: # | C13: 30 | D13: 34 | E13: 26 | F13: =CHOOSE(MATCH('Assumptions'!$C$4,{"Base","Upside","Downside"},0),C13,D13,E13) -> 0 | G13: Small self-serve / startup accounts.
A14: Starter new customers, month 1 | B14: # | C14: 6 | D14: 8 | E14: 4 | F14: =CHOOSE(MATCH('Assumptions'!$C$4,{"Base","Upside","Downside"},0),C14,D14,E14) -> 0 | G14: New Starter logos landed in month 1.
A15: Starter new-customer growth, month over month | B15: % | C15: 0.0314 | D15: 0.0535 | E15: 0.0031 | F15: =CHOOSE(MATCH('Assumptions'!$C$4,{"Base","Upside","Downside"},0),C15,D15,E15) -> 0 | G15: Compounding growth in monthly Starter logo adds.
A16: Starter monthly churn rate | B16: % | C16: 0.03 | D16: 0.02 | E16: 0.045 | F16: =CHOOSE(MATCH('Assumptions'!$C$4,{"Base","Upside","Downside"},0),C16,D16,E16) -> 0 | G16: Share of beginning Starter customers that churn each month.
A17: Starter usage per customer, month 1 | B17: M req/mo | C17: 4 | D17: 4.5 | E17: 3.5 | F17: =CHOOSE(MATCH('Assumptions'!$C$4,{"Base","Upside","Downside"},0),C17,D17,E17) -> 0 | G17: Average monthly inference request-equivalents per active Starter customer.
A18: Starter usage growth per customer, month over month | B18: % | C18: 0.04 | D18: 0.0645 | E18: 0.0143 | F18: =CHOOSE(MATCH('Assumptions'!$C$4,{"Base","Upside","Downside"},0),C18,D18,E18) -> 0 | G18: Growth in monthly usage intensity per Starter customer.
A19: Growth customers at month 1 start | B19: # | C19: 12 | D19: 14 | E19: 10 | F19: =CHOOSE(MATCH('Assumptions'!$C$4,{"Base","Upside","Downside"},0),C19,D19,E19) -> 0 | G19: Mid-market accounts on annual commits.
A20: Growth new customers, month 1 | B20: # | C20: 3 | D20: 4 | E20: 2 | F20: =CHOOSE(MATCH('Assumptions'!$C$4,{"Base","Upside","Downside"},0),C20,D20,E20) -> 0 | G20: New Growth customers landed in month 1.
A21: Growth new-customer growth, month over month | B21: % | C21: 0.0226 | D21: 0.0323 | E21: 0.0037 | F21: =CHOOSE(MATCH('Assumptions'!$C$4,{"Base","Upside","Downside"},0),C21,D21,E21) -> 0 | G21: Compounding growth in monthly Growth-customer adds.
A22: Growth monthly churn rate | B22: % | C22: 0.015 | D22: 0.01 | E22: 0.025 | F22: =CHOOSE(MATCH('Assumptions'!$C$4,{"Base","Upside","Downside"},0),C22,D22,E22) -> 0 | G22: Share of beginning Growth customers lost each month.
A23: Growth usage per customer, month 1 | B23: M req/mo | C23: 25 | D23: 28 | E23: 22 | F23: =CHOOSE(MATCH('Assumptions'!$C$4,{"Base","Upside","Downside"},0),C23,D23,E23) -> 0 | G23: Average monthly inference request-equivalents per active Growth customer.
A24: Growth usage growth per customer, month over month | B24: % | C24: 0.0307 | D24: 0.0596 | E24: 0.0119 | F24: =CHOOSE(MATCH('Assumptions'!$C$4,{"Base","Upside","Downside"},0),C24,D24,E24) -> 0 | G24: Growth in monthly usage intensity per Growth customer.
... A30: Enterprise usage growth per customer, month over month | B30: % | C30: 0.0282 | D30: 0.0471 | E30: 0.0131 | F30: =CHOOSE(MATCH('Assumptions'!$C$4,{"Base","Upside","Downside"},0),C30,D30,E30) -> 0 | G30: Growth in monthly usage intensity per Enterprise customer.
A32: Pricing & Unit Economics
A33: Standard-model list price per 1M requests | B33: $/M req | C33: 2200 | D33: 2350 | E33: 2050 | F33: =CHOOSE(MATCH('Assumptions'!$C$4,{"Base","Upside","Downside"},0),C33,D33,E33) -> 0 | G33: Realized before tier multipliers and discounting.
A34: Premium-model list price per 1M requests | B34: $/M req | C34: 5000 | D34: 5250 | E34: 4750 | F34: =CHOOSE(MATCH('Assumptions'!$C$4,{"Base","Upside","Downside"},0),C34,D34,E34) -> 0 | G34: Higher-value reasoning / multimodal request pricing.
A35: Premium-model mix, month 1 | B35: % | C35: 0.25 | D35: 0.32 | E35: 0.18 | F35: =CHOOSE(MATCH('Assumptions'!$C$4,{"Base","Upside","Downside"},0),C35,D35,E35) -> 0 | G35: Share of usage billed on premium models at the start of the model.
A36: Premium-model mix shift, month over month | B36: % | C36: 0.0038 | D36: 0.0057 | E36: 0.0009 | F36: =CHOOSE(MATCH('Assumptions'!$C$4,{"Base","Upside","Downside"},0),C36,D36,E36) -> 0 | G36: Monthly change in premium-model mix; capped inside the model.
A37: Starter realized price multiplier | B37: x | C37: 0.85 | D37: 0.88 | E37: 0.82 | F37: =CHOOSE(MATCH('Assumptions'!$C$4,{"Base","Upside","Downside"},0),C37,D37,E37) -> 0 | G37: Discounted vs blended list price due to lower ACV and promotional pricing.
A38: Growth realized price multiplier | B38: x | C38: 1 | D38: 1.03 | E38: 0.97 | F38: =CHOOSE(MATCH('Assumptions'!$C$4,{"Base","Upside","Downside"},0),C38,D38,E38) -> 0 | G38: Mid-market customers roughly at blended list price.
A39: Enterprise realized price multiplier | B39: x | C39: 1.18 | D39: 1.22 | E39: 1.12 | F39: =CHOOSE(MATCH('Assumptions'!$C$4,{"Base","Upside","Downside"},0),C39,D39,E39) -> 0 | G39: Premium for SLA, throughput, and higher-value workloads.
A40: Committed-use / volume discount rate | B40: % | C40: 0.08 | D40: 0.06 | E40: 0.12 | F40: =CHOOSE(MATCH('Assumptions'!$C$4,{"Base","Upside","Downside"},0),C40,D40,E40) -> 0 | G40: Blended discount off list price for annual commits and committed capacity.
A41: Cache hit rate | B41: % | C41: 0.18 | D41: 0.24 | E41: 0.1 | F41: =CHOOSE(MATCH('Assumptions'!$C$4,{"Base","Upside","Downside"},0),C41,D41,E41) -> 0 | G41: Share of gross requests satisfied by cache rather than fresh inference.
A42: Share of cache benefit passed back to customers | B42: % | C42: 0.35 | D42: 0.25 | E42: 0.45 | F42: =CHOOSE(MATCH('Assumptions'!$C$4,{"Base","Upside","Downside"},0),C42,D42,E42) -> 0 | G42: Portion of cache savings that lowers billable units / effective invoice volume.
A43: Batch / async discount rate | B43: % | C43: 0.07 | D43: 0.1 | E43: 0.03 | F43: =CHOOSE(MATCH('Assumptions'!$C$4,{"Base","Upside","Downside"},0),C43,D43,E43) -> 0 | G43: Effective unit reduction from customers opting into batched / async processing.
A44: Starter platform fee per customer | B44: $/mo | C44: 500 | D44: 600 | E44: 450 | F44: =CHOOSE(MATCH('Assumptions'!$C$4,{"Base","Upside","Downside"},0),C44,D44,E44) -> 0 | G44: Base platform / support fee billed monthly per Starter account.
... A46: Enterprise platform fee per customer | B46: $/mo | C46: 12000 | D46: 14000 | E46: 10000 | F46: =CHOOSE(MATCH('Assumptions'!$C$4,{"Base","Upside","Downside"},0),C46,D46,E46) -> 0 | G46: Base platform / SLA fee billed monthly per Enterprise account.
A48: COGS & Compute Costs
A49: Reserved capacity compute cost per 1M requests | B49: $/M req | C49: 900 | D49: 820 | E49: 1020 | F49: =CHOOSE(MATCH('Assumptions'!$C$4,{"Base","Upside","Downside"},0),C49,D49,E49) -> 0 | G49: At target utilization; actual effective cost is adjusted by utilization.
A50: On-demand compute cost per 1M requests | B50: $/M req | C50: 1500 | D50: 1380 | E50: 1700 | F50: =CHOOSE(MATCH('Assumptions'!$C$4,{"Base","Upside","Downside"},0),C50,D50,E50) -> 0 | G50: Pay-as-you-go compute cost for overflow / burst workloads.
A51: External model/API cost per 1M standard requests | B51: $/M req | C51: 400 | D51: 360 | E51: 470 | F51: =CHOOSE(MATCH('Assumptions'!$C$4,{"Base","Upside","Downside"},0),C51,D51,E51) -> 0 | G51: Third-party inference / foundation-model provider cost.
A52: External model/API cost per 1M premium requests | B52: $/M req | C52: 1500 | D52: 1350 | E52: 1700 | F52: =CHOOSE(MATCH('Assumptions'!$C$4,{"Base","Upside","Downside"},0),C52,D52,E52) -> 0 | G52: Higher-cost premium provider / model blend.
A53: Storage / vector index cost per 1M requests | B53: $/M req | C53: 45 | D53: 40 | E53: 55 | F53: =CHOOSE(MATCH('Assumptions'!$C$4,{"Base","Upside","Downside"},0),C53,D53,E53) -> 0 | G53: Storage, retrieval, and persistent context cost allocated by usage.
A54: Bandwidth / egress cost per 1M requests | B54: $/M req | C54: 60 | D54: 52 | E54: 72 | F54: =CHOOSE(MATCH('Assumptions'!$C$4,{"Base","Upside","Downside"},0),C54,D54,E54) -> 0 | G54: Network and delivery cost allocated by gross request volume.
A55: Reserved-capacity share of compute volume | B55: % | C55: 0.65 | D55: 0.75 | E55: 0.5 | F55: =CHOOSE(MATCH('Assumptions'!$C$4,{"Base","Upside","Downside"},0),C55,D55,E55) -> 0 | G55: Share of fresh inference volume routed to reserved capacity.
A56: Reserved capacity utilization, month 1 | B56: % | C56: 0.55 | D56: 0.62 | E56: 0.45 | F56: =CHOOSE(MATCH('Assumptions'!$C$4,{"Base","Upside","Downside"},0),C56,D56,E56) -> 0 | G56: Blended utilization of reserved GPU / inference clusters in month 1.
A57: Utilization improvement, month over month | B57: % | C57: 0.0031 | D57: 0.0079 | E57: 0.0017 | F57: =CHOOSE(MATCH('Assumptions'!$C$4,{"Base","Upside","Downside"},0),C57,D57,E57) -> 0 | G57: Monthly utilization ramp from better scheduling and fill-rate.
A59: Headcount — Cost of Revenue (COGS)
A60: Starting Infrastructure / SRE FTEs | B60: # | C60: 5 | D60: 5 | E60: 5 | F60: =CHOOSE(MATCH('Assumptions'!$C$4,{"Base","Upside","Downside"},0),C60,D60,E60) -> 0 | G60: Team operating inference clusters, reliability, and cost optimization.
A61: Infrastructure / SRE net adds per quarter | B61: # | C61: 1 | D61: 1.5 | E61: 0.5 | F61: =CHOOSE(MATCH('Assumptions'!$C$4,{"Base","Upside","Downside"},0),C61,D61,E61) -> 0
A62: Infrastructure / SRE fully-loaded cost per FTE | B62: $/mo | C62: 16000 | D62: 16000 | E62: 16000 | F62: =CHOOSE(MATCH('Assumptions'!$C$4,{"Base","Upside","Downside"},0),C62,D62,E62) -> 0 | G62: Salary + benefits + payroll tax, monthly.
A64: Headcount — R&D / Engineering (Opex)
A65: Starting Model Engineering / Applied Research FTEs | B65: # | C65: 4 | D65: 4 | E65: 4 | F65: =CHOOSE(MATCH('Assumptions'!$C$4,{"Base","Upside","Downside"},0),C65,D65,E65) -> 0
A66: Model Engineering / Applied Research net adds per quarter | B66: # | C66: 1 | D66: 1.5 | E66: 0.5 | F66: =CHOOSE(MATCH('Assumptions'!$C$4,{"Base","Upside","Downside"},0),C66,D66,E66) -> 0
A67: Model Engineering / Applied Research fully-loaded cost per FTE | B67: $/mo | C67: 18000 | D67: 18000 | E67: 18000 | F67: =CHOOSE(MATCH('Assumptions'!$C$4,{"Base","Upside","Downside"},0),C67,D67,E67) -> 0
A69: Headcount — Sales & Marketing (Opex)
A70: Starting GTM / Sales FTEs | B70: # | C70: 3 | D70: 3 | E70: 3 | F70: =CHOOSE(MATCH('Assumptions'!$C$4,{"Base","Upside","Downside"},0),C70,D70,E70) -> 0 | G70: Quota-carrying and solutions-oriented revenue team.
A71: GTM / Sales net adds per quarter | B71: # | C71: 1 | D71: 1.5 | E71: 0.5 | F71: =CHOOSE(MATCH('Assumptions'!$C$4,{"Base","Upside","Downside"},0),C71,D71,E71) -> 0
A72: GTM / Sales fully-loaded cost per FTE | B72: $/mo | C72: 15000 | D72: 15000 | E72: 15000 | F72: =CHOOSE(MATCH('Assumptions'!$C$4,{"Base","Upside","Downside"},0),C72,D72,E72) -> 0
A74: Headcount — G&A (Opex)
A75: Starting G&A FTEs | B75: # | C75: 2 | D75: 2 | E75: 2 | F75: =CHOOSE(MATCH('Assumptions'!$C$4,{"Base","Upside","Downside"},0),C75,D75,E75) -> 0 | G75: Finance, HR, legal, and ops.
A76: G&A net adds per quarter | B76: # | C76: 0.5 | D76: 0.5 | E76: 0.25 | F76: =CHOOSE(MATCH('Assumptions'!$C$4,{"Base","Upside","Downside"},0),C76,D76,E76) -> 0
A77: G&A fully-loaded cost per FTE | B77: $/mo | C77: 11000 | D77: 11000 | E77: 11000 | F77: =CHOOSE(MATCH('Assumptions'!$C$4,{"Base","Upside","Downside"},0),C77,D77,E77) -> 0
A79: GTM / Opex
A80: Sales commissions, % of new-customer revenue | B80: % | C80: 0.06 | D80: 0.05 | E80: 0.08 | F80: =CHOOSE(MATCH('Assumptions'!$C$4,{"Base","Upside","Downside"},0),C80,D80,E80) -> 0 | G80: Paid on new-customer monthly revenue added in the month it lands.
A81: Partner / marketplace fees, % of usage revenue | B81: % | C81: 0.025 | D81: 0.02 | E81: 0.03 | F81: =CHOOSE(MATCH('Assumptions'!$C$4,{"Base","Upside","Downside"},0),C81,D81,E81) -> 0 | G81: App-store / reseller / marketplace fees on metered usage revenue.
A82: Marketing programs, % of revenue | B82: % | C82: 0.07 | D82: 0.09 | E82: 0.05 | F82: =CHOOSE(MATCH('Assumptions'!$C$4,{"Base","Upside","Downside"},0),C82,D82,E82) -> 0 | G82: Paid acquisition, developer marketing, events, and ecosystem spend.
A83: Software / tools fixed monthly spend | B83: $/mo | C83: 12000 | D83: 12000 | E83: 12000 | F83: =CHOOSE(MATCH('Assumptions'!$C$4,{"Base","Upside","Downside"},0),C83,D83,E83) -> 0 | G83: Monitoring, CI/CD, developer tools, analytics, and security tooling.
A84: Facilities / admin fixed monthly spend | B84: $/mo | C84: 9000 | D84: 9000 | E84: 9000 | F84: =CHOOSE(MATCH('Assumptions'!$C$4,{"Base","Upside","Downside"},0),C84,D84,E84) -> 0 | G84: Office, insurance, audit, recruiting, and other overhead.
A86: Working Capital & Financing
A87: Days Sales Outstanding (AR) | B87: days | C87: 40 | D87: 35 | E87: 48 | F87: =CHOOSE(MATCH('Assumptions'!$C$4,{"Base","Upside","Downside"},0),C87,D87,E87) -> 0
A88: Days Payable Outstanding (AP) | B88: days | C88: 35 | D88: 38 | E88: 30 | F88: =CHOOSE(MATCH('Assumptions'!$C$4,{"Base","Upside","Downside"},0),C88,D88,E88) -> 0
A89: Deferred revenue held in advance | B89: mo | C89: 0.6 | D89: 0.8 | E89: 0.4 | F89: =CHOOSE(MATCH('Assumptions'!$C$4,{"Base","Upside","Downside"},0),C89,D89,E89) -> 0 | G89: Reflects annual prepaid platform commits and enterprise true-ups.
A90: Capex, % of revenue | B90: % | C90: 0.08 | D90: 0.06 | E90: 0.12 | F90: =CHOOSE(MATCH('Assumptions'!$C$4,{"Base","Upside","Downside"},0),C90,D90,E90) -> 0 | G90: Capitalized infrastructure, proprietary tooling, and internal platform investments.
A91: Useful life of capitalized assets | B91: months | C91: 30 | D91: 30 | E91: 24 | F91: =CHOOSE(MATCH('Assumptions'!$C$4,{"Base","Upside","Downside"},0),C91,D91,E91) -> 0
A92: Other current assets, % of revenue | B92: % | C92: 0.04 | D92: 0.04 | E92: 0.04 | F92: =CHOOSE(MATCH('Assumptions'!$C$4,{"Base","Upside","Downside"},0),C92,D92,E92) -> 0 | G92: Prepaids, deposits, and other small current assets.
A93: Venture debt annual interest rate | B93: % | C93: 0.1 | D93: 0.09 | E93: 0.12 | F93: =CHOOSE(MATCH('Assumptions'!$C$4,{"Base","Upside","Downside"},0),C93,D93,E93) -> 0
A94: Venture debt draw (one-time) | B94: $ | C94: 2500000 | D94: 3000000 | E94: 2000000 | F94: =CHOOSE(MATCH('Assumptions'!$C$4,{"Base","Upside","Downside"},0),C94,D94,E94) -> 0
A95: Venture debt monthly repayment | B95: $/mo | C95: 60000 | D95: 60000 | E95: 50000 | F95: =CHOOSE(MATCH('Assumptions'!$C$4,{"Base","Upside","Downside"},0),C95,D95,E95) -> 0
A96: Growth equity raise (month 4) | B96: $ | C96: 10000000 | D96: 12000000 | E96: 8000000 | F96: =CHOOSE(MATCH('Assumptions'!$C$4,{"Base","Upside","Downside"},0),C96,D96,E96) -> 0
A97: Follow-on equity raise (month 22) | B97: $ | C97: 20000000 | D97: 24000000 | E97: 15000000 | F97: =CHOOSE(MATCH('Assumptions'!$C$4,{"Base","Upside","Downside"},0),C97,D97,E97) -> 0
A100: Tip: start with Base, then stress-test growth, model mix, utilization, and capex in Upside/Downside.

Sheet Headcount
A1: AI API / Infrastructure — 3-Year Financial Model — Headcount
A2: Fully-loaded FTE ramps by role — flows into COGS or Opex by classification.
A5: Line item | B5: Units / source | C5: Monthly (36 months) | AN5: Quarterly | BA5: Annual
C6: 46023 | D6: 46054 | E6: 46082 | F6: 46113 | G6: 46143 | H6: 46174 | I6: 46204 | J6: 46235 | K6: 46266 | L6: 46296 | M6: 46327 | N6: 46357 | O6: 46388 | P6: 46419 | Q6: 46447 | R6: 46478 | S6: 46508 | T6: 46539 | U6: 46569 | V6: 46600 | W6: 46631 | X6: 46661 | Y6: 46692 | Z6: 46722 | AA6: 46753 | AB6: 46784 | AC6: 46813 | AD6: 46844 | AE6: 46874 | AF6: 46905 | AG6: 46935 | AH6: 46966 | AI6: 46997 | AJ6: 47027 | AK6: 47058 | AL6: 47088 | AN6: Q1 | AO6: Q2 | AP6: Q3 | AQ6: Q4 | AR6: Q5 | AS6: Q6 | AT6: Q7 | AU6: Q8 | AV6: Q9 | AW6: Q10 | AX6: Q11 | AY6: Q12 | BA6: FY1 | BB6: FY2 | BC6: FY3
A7: Cost of Goods Sold headcount (COGS-classified)
A8: Infrastructure / SRE — headcount (FTE) | B8: Cost of Revenue · start + net adds/qtr ÷ 3 | C8: =ROUND('Assumptions'!$F$60,1) -> 0 | D8: =ROUND(C8+'Assumptions'!$F$61/3,1) -> 0 | E8: =ROUND(D8+'Assumptions'!$F$61/3,1) -> 0 | F8: =ROUND(E8+'Assumptions'!$F$61/3,1) -> 0 | G8: =ROUND(F8+'Assumptions'!$F$61/3,1) -> 0 | H8: =ROUND(G8+'Assumptions'!$F$61/3,1) -> 0 | I8: =ROUND(H8+'Assumptions'!$F$61/3,1) -> 0 | J8: =ROUND(I8+'Assumptions'!$F$61/3,1) -> 0 | K8: =ROUND(J8+'Assumptions'!$F$61/3,1) -> 0 | ... AL8: =ROUND(AK8+'Assumptions'!$F$61/3,1) -> 0 | AN8: =E8 -> 0 | AO8: =H8 -> 0 | AP8: =K8 -> 0 | AQ8: =N8 -> 0 | AR8: =Q8 -> 0 | AS8: =T8 -> 0 | AT8: =W8 -> 0 | AU8: =Z8 -> 0 | AV8: =AC8 -> 0 | AW8: =AF8 -> 0 | AX8: =AI8 -> 0 | AY8: =AL8 -> 0 | BA8: =N8 -> 0 | BB8: =Z8 -> 0 | BC8: =AL8 -> 0
A9: Infrastructure / SRE — fully-loaded cost | B9: Headcount × monthly fully-loaded cost/FTE | C9: =C8*'Assumptions'!$F$62 -> 0 | D9: =D8*'Assumptions'!$F$62 -> 0 | E9: =E8*'Assumptions'!$F$62 -> 0 | F9: =F8*'Assumptions'!$F$62 -> 0 | G9: =G8*'Assumptions'!$F$62 -> 0 | H9: =H8*'Assumptions'!$F$62 -> 0 | I9: =I8*'Assumptions'!$F$62 -> 0 | J9: =J8*'Assumptions'!$F$62 -> 0 | ... AL9: =AL8*'Assumptions'!$F$62 -> 0 | AN9: =SUM(C9:E9) -> 0 | AO9: =SUM(F9:H9) -> 0 | AP9: =SUM(I9:K9) -> 0 | AQ9: =SUM(L9:N9) -> 0 | AR9: =SUM(O9:Q9) -> 0 | AS9: =SUM(R9:T9) -> 0 | AT9: =SUM(U9:W9) -> 0 | AU9: =SUM(X9:Z9) -> 0 | AV9: =SUM(AA9:AC9) -> 0 | AW9: =SUM(AD9:AF9) -> 0 | AX9: =SUM(AG9:AI9) -> 0 | AY9: =SUM(AJ9:AL9) -> 0 | BA9: =SUM(C9:N9) -> 0 | BB9: =SUM(O9:Z9) -> 0 | BC9: =SUM(AA9:AL9) -> 0
A11: Operating expense headcount (Opex-classified)
A12: Model Engineering / Applied Research — headcount (FTE) | B12: R&D / Engineering · start + net adds/qtr ÷ 3 | C12: =ROUND('Assumptions'!$F$65,1) -> 0 | D12: =ROUND(C12+'Assumptions'!$F$66/3,1) -> 0 | E12: =ROUND(D12+'Assumptions'!$F$66/3,1) -> 0 | F12: =ROUND(E12+'Assumptions'!$F$66/3,1) -> 0 | G12: =ROUND(F12+'Assumptions'!$F$66/3,1) -> 0 | H12: =ROUND(G12+'Assumptions'!$F$66/3,1) -> 0 | I12: =ROUND(H12+'Assumptions'!$F$66/3,1) -> 0 | J12: =ROUND(I12+'Assumptions'!$F$66/3,1) -> 0 | K12: =ROUND(J12+'Assumptions'!$F$66/3,1) -> 0 | ... AL12: =ROUND(AK12+'Assumptions'!$F$66/3,1) -> 0 | AN12: =E12 -> 0 | AO12: =H12 -> 0 | AP12: =K12 -> 0 | AQ12: =N12 -> 0 | AR12: =Q12 -> 0 | AS12: =T12 -> 0 | AT12: =W12 -> 0 | AU12: =Z12 -> 0 | AV12: =AC12 -> 0 | AW12: =AF12 -> 0 | AX12: =AI12 -> 0 | AY12: =AL12 -> 0 | BA12: =N12 -> 0 | BB12: =Z12 -> 0 | BC12: =AL12 -> 0
A13: Model Engineering / Applied Research — fully-loaded cost | B13: Headcount × monthly fully-loaded cost/FTE | C13: =C12*'Assumptions'!$F$67 -> 0 | D13: =D12*'Assumptions'!$F$67 -> 0 | E13: =E12*'Assumptions'!$F$67 -> 0 | F13: =F12*'Assumptions'!$F$67 -> 0 | G13: =G12*'Assumptions'!$F$67 -> 0 | H13: =H12*'Assumptions'!$F$67 -> 0 | I13: =I12*'Assumptions'!$F$67 -> 0 | J13: =J12*'Assumptions'!$F$67 -> 0 | ... AL13: =AL12*'Assumptions'!$F$67 -> 0 | AN13: =SUM(C13:E13) -> 0 | AO13: =SUM(F13:H13) -> 0 | AP13: =SUM(I13:K13) -> 0 | AQ13: =SUM(L13:N13) -> 0 | AR13: =SUM(O13:Q13) -> 0 | AS13: =SUM(R13:T13) -> 0 | AT13: =SUM(U13:W13) -> 0 | AU13: =SUM(X13:Z13) -> 0 | AV13: =SUM(AA13:AC13) -> 0 | AW13: =SUM(AD13:AF13) -> 0 | AX13: =SUM(AG13:AI13) -> 0 | AY13: =SUM(AJ13:AL13) -> 0 | BA13: =SUM(C13:N13) -> 0 | BB13: =SUM(O13:Z13) -> 0 | BC13: =SUM(AA13:AL13) -> 0
A14: GTM / Sales — headcount (FTE) | B14: Sales & Marketing · start + net adds/qtr ÷ 3 | C14: =ROUND('Assumptions'!$F$70,1) -> 0 | D14: =ROUND(C14+'Assumptions'!$F$71/3,1) -> 0 | E14: =ROUND(D14+'Assumptions'!$F$71/3,1) -> 0 | F14: =ROUND(E14+'Assumptions'!$F$71/3,1) -> 0 | G14: =ROUND(F14+'Assumptions'!$F$71/3,1) -> 0 | H14: =ROUND(G14+'Assumptions'!$F$71/3,1) -> 0 | I14: =ROUND(H14+'Assumptions'!$F$71/3,1) -> 0 | J14: =ROUND(I14+'Assumptions'!$F$71/3,1) -> 0 | K14: =ROUND(J14+'Assumptions'!$F$71/3,1) -> 0 | ... AL14: =ROUND(AK14+'Assumptions'!$F$71/3,1) -> 0 | AN14: =E14 -> 0 | AO14: =H14 -> 0 | AP14: =K14 -> 0 | AQ14: =N14 -> 0 | AR14: =Q14 -> 0 | AS14: =T14 -> 0 | AT14: =W14 -> 0 | AU14: =Z14 -> 0 | AV14: =AC14 -> 0 | AW14: =AF14 -> 0 | AX14: =AI14 -> 0 | AY14: =AL14 -> 0 | BA14: =N14 -> 0 | BB14: =Z14 -> 0 | BC14: =AL14 -> 0
A15: GTM / Sales — fully-loaded cost | B15: Headcount × monthly fully-loaded cost/FTE | C15: =C14*'Assumptions'!$F$72 -> 0 | D15: =D14*'Assumptions'!$F$72 -> 0 | E15: =E14*'Assumptions'!$F$72 -> 0 | F15: =F14*'Assumptions'!$F$72 -> 0 | G15: =G14*'Assumptions'!$F$72 -> 0 | H15: =H14*'Assumptions'!$F$72 -> 0 | I15: =I14*'Assumptions'!$F$72 -> 0 | J15: =J14*'Assumptions'!$F$72 -> 0 | ... AL15: =AL14*'Assumptions'!$F$72 -> 0 | AN15: =SUM(C15:E15) -> 0 | AO15: =SUM(F15:H15) -> 0 | AP15: =SUM(I15:K15) -> 0 | AQ15: =SUM(L15:N15) -> 0 | AR15: =SUM(O15:Q15) -> 0 | AS15: =SUM(R15:T15) -> 0 | AT15: =SUM(U15:W15) -> 0 | AU15: =SUM(X15:Z15) -> 0 | AV15: =SUM(AA15:AC15) -> 0 | AW15: =SUM(AD15:AF15) -> 0 | AX15: =SUM(AG15:AI15) -> 0 | AY15: =SUM(AJ15:AL15) -> 0 | BA15: =SUM(C15:N15) -> 0 | BB15: =SUM(O15:Z15) -> 0 | BC15: =SUM(AA15:AL15) -> 0
A16: G&A (Finance / HR / Ops) — headcount (FTE) | B16: General & Administrative · start + net adds/qtr ÷ 3 | C16: =ROUND('Assumptions'!$F$75,1) -> 0 | D16: =ROUND(C16+'Assumptions'!$F$76/3,1) -> 0 | E16: =ROUND(D16+'Assumptions'!$F$76/3,1) -> 0 | F16: =ROUND(E16+'Assumptions'!$F$76/3,1) -> 0 | G16: =ROUND(F16+'Assumptions'!$F$76/3,1) -> 0 | H16: =ROUND(G16+'Assumptions'!$F$76/3,1) -> 0 | I16: =ROUND(H16+'Assumptions'!$F$76/3,1) -> 0 | J16: =ROUND(I16+'Assumptions'!$F$76/3,1) -> 0 | K16: =ROUND(J16+'Assumptions'!$F$76/3,1) -> 0 | ... AL16: =ROUND(AK16+'Assumptions'!$F$76/3,1) -> 0 | AN16: =E16 -> 0 | AO16: =H16 -> 0 | AP16: =K16 -> 0 | AQ16: =N16 -> 0 | AR16: =Q16 -> 0 | AS16: =T16 -> 0 | AT16: =W16 -> 0 | AU16: =Z16 -> 0 | AV16: =AC16 -> 0 | AW16: =AF16 -> 0 | AX16: =AI16 -> 0 | AY16: =AL16 -> 0 | BA16: =N16 -> 0 | BB16: =Z16 -> 0 | BC16: =AL16 -> 0
A17: G&A (Finance / HR / Ops) — fully-loaded cost | B17: Headcount × monthly fully-loaded cost/FTE | C17: =C16*'Assumptions'!$F$77 -> 0 | D17: =D16*'Assumptions'!$F$77 -> 0 | E17: =E16*'Assumptions'!$F$77 -> 0 | F17: =F16*'Assumptions'!$F$77 -> 0 | G17: =G16*'Assumptions'!$F$77 -> 0 | H17: =H16*'Assumptions'!$F$77 -> 0 | I17: =I16*'Assumptions'!$F$77 -> 0 | J17: =J16*'Assumptions'!$F$77 -> 0 | ... AL17: =AL16*'Assumptions'!$F$77 -> 0 | AN17: =SUM(C17:E17) -> 0 | AO17: =SUM(F17:H17) -> 0 | AP17: =SUM(I17:K17) -> 0 | AQ17: =SUM(L17:N17) -> 0 | AR17: =SUM(O17:Q17) -> 0 | AS17: =SUM(R17:T17) -> 0 | AT17: =SUM(U17:W17) -> 0 | AU17: =SUM(X17:Z17) -> 0 | AV17: =SUM(AA17:AC17) -> 0 | AW17: =SUM(AD17:AF17) -> 0 | AX17: =SUM(AG17:AI17) -> 0 | AY17: =SUM(AJ17:AL17) -> 0 | BA17: =SUM(C17:N17) -> 0 | BB17: =SUM(O17:Z17) -> 0 | BC17: =SUM(AA17:AL17) -> 0
A19: Totals
A20: Total headcount (FTE) | B20: Sum of all roles | C20: =C8+C12+C14+C16 -> 0 | D20: =D8+D12+D14+D16 -> 0 | E20: =E8+E12+E14+E16 -> 0 | F20: =F8+F12+F14+F16 -> 0 | G20: =G8+G12+G14+G16 -> 0 | H20: =H8+H12+H14+H16 -> 0 | I20: =I8+I12+I14+I16 -> 0 | J20: =J8+J12+J14+J16 -> 0 | ... AL20: =AL8+AL12+AL14+AL16 -> 0 | AN20: =E20 -> 0 | AO20: =H20 -> 0 | AP20: =K20 -> 0 | AQ20: =N20 -> 0 | AR20: =Q20 -> 0 | AS20: =T20 -> 0 | AT20: =W20 -> 0 | AU20: =Z20 -> 0 | AV20: =AC20 -> 0 | AW20: =AF20 -> 0 | AX20: =AI20 -> 0 | AY20: =AL20 -> 0 | BA20: =N20 -> 0 | BB20: =Z20 -> 0 | BC20: =AL20 -> 0
A21: Total COGS-classified people cost | B21: Feeds COGS & GM tab | C21: =C9 -> 0 | D21: =D9 -> 0 | E21: =E9 -> 0 | F21: =F9 -> 0 | G21: =G9 -> 0 | H21: =H9 -> 0 | I21: =I9 -> 0 | J21: =J9 -> 0 | ... AL21: =AL9 -> 0 | AN21: =SUM(C21:E21) -> 0 | AO21: =SUM(F21:H21) -> 0 | AP21: =SUM(I21:K21) -> 0 | AQ21: =SUM(L21:N21) -> 0 | AR21: =SUM(O21:Q21) -> 0 | AS21: =SUM(R21:T21) -> 0 | AT21: =SUM(U21:W21) -> 0 | AU21: =SUM(X21:Z21) -> 0 | AV21: =SUM(AA21:AC21) -> 0 | AW21: =SUM(AD21:AF21) -> 0 | AX21: =SUM(AG21:AI21) -> 0 | AY21: =SUM(AJ21:AL21) -> 0 | BA21: =SUM(C21:N21) -> 0 | BB21: =SUM(O21:Z21) -> 0 | BC21: =SUM(AA21:AL21) -> 0
A22: Total Opex-classified people cost | B22: Feeds Opex tab | C22: =C13+C15+C17 -> 0 | D22: =D13+D15+D17 -> 0 | E22: =E13+E15+E17 -> 0 | F22: =F13+F15+F17 -> 0 | G22: =G13+G15+G17 -> 0 | H22: =H13+H15+H17 -> 0 | I22: =I13+I15+I17 -> 0 | J22: =J13+J15+J17 -> 0 | ... AL22: =AL13+AL15+AL17 -> 0 | AN22: =SUM(C22:E22) -> 0 | AO22: =SUM(F22:H22) -> 0 | AP22: =SUM(I22:K22) -> 0 | AQ22: =SUM(L22:N22) -> 0 | AR22: =SUM(O22:Q22) -> 0 | AS22: =SUM(R22:T22) -> 0 | AT22: =SUM(U22:W22) -> 0 | AU22: =SUM(X22:Z22) -> 0 | AV22: =SUM(AA22:AC22) -> 0 | AW22: =SUM(AD22:AF22) -> 0 | AX22: =SUM(AG22:AI22) -> 0 | AY22: =SUM(AJ22:AL22) -> 0 | BA22: =SUM(C22:N22) -> 0 | BB22: =SUM(O22:Z22) -> 0 | BC22: =SUM(AA22:AL22) -> 0
A23: General & Administrative people cost | C23: =C17 -> 0 | D23: =D17 -> 0 | E23: =E17 -> 0 | F23: =F17 -> 0 | G23: =G17 -> 0 | H23: =H17 -> 0 | I23: =I17 -> 0 | J23: =J17 -> 0 | ... AL23: =AL17 -> 0 | AN23: =SUM(C23:E23) -> 0 | AO23: =SUM(F23:H23) -> 0 | AP23: =SUM(I23:K23) -> 0 | AQ23: =SUM(L23:N23) -> 0 | AR23: =SUM(O23:Q23) -> 0 | AS23: =SUM(R23:T23) -> 0 | AT23: =SUM(U23:W23) -> 0 | AU23: =SUM(X23:Z23) -> 0 | AV23: =SUM(AA23:AC23) -> 0 | AW23: =SUM(AD23:AF23) -> 0 | AX23: =SUM(AG23:AI23) -> 0 | AY23: =SUM(AJ23:AL23) -> 0 | BA23: =SUM(C23:N23) -> 0 | BB23: =SUM(O23:Z23) -> 0 | BC23: =SUM(AA23:AL23) -> 0
A24: R&D / Engineering people cost | C24: =C13 -> 0 | D24: =D13 -> 0 | E24: =E13 -> 0 | F24: =F13 -> 0 | G24: =G13 -> 0 | H24: =H13 -> 0 | I24: =I13 -> 0 | J24: =J13 -> 0 | ... AL24: =AL13 -> 0 | AN24: =SUM(C24:E24) -> 0 | AO24: =SUM(F24:H24) -> 0 | AP24: =SUM(I24:K24) -> 0 | AQ24: =SUM(L24:N24) -> 0 | AR24: =SUM(O24:Q24) -> 0 | AS24: =SUM(R24:T24) -> 0 | AT24: =SUM(U24:W24) -> 0 | AU24: =SUM(X24:Z24) -> 0 | AV24: =SUM(AA24:AC24) -> 0 | AW24: =SUM(AD24:AF24) -> 0 | AX24: =SUM(AG24:AI24) -> 0 | AY24: =SUM(AJ24:AL24) -> 0 | BA24: =SUM(C24:N24) -> 0 | BB24: =SUM(O24:Z24) -> 0 | BC24: =SUM(AA24:AL24) -> 0
A25: Sales & Marketing people cost | C25: =C15 -> 0 | D25: =D15 -> 0 | E25: =E15 -> 0 | F25: =F15 -> 0 | G25: =G15 -> 0 | H25: =H15 -> 0 | I25: =I15 -> 0 | J25: =J15 -> 0 | ... AL25: =AL15 -> 0 | AN25: =SUM(C25:E25) -> 0 | AO25: =SUM(F25:H25) -> 0 | AP25: =SUM(I25:K25) -> 0 | AQ25: =SUM(L25:N25) -> 0 | AR25: =SUM(O25:Q25) -> 0 | AS25: =SUM(R25:T25) -> 0 | AT25: =SUM(U25:W25) -> 0 | AU25: =SUM(X25:Z25) -> 0 | AV25: =SUM(AA25:AC25) -> 0 | AW25: =SUM(AD25:AF25) -> 0 | AX25: =SUM(AG25:AI25) -> 0 | AY25: =SUM(AJ25:AL25) -> 0 | BA25: =SUM(C25:N25) -> 0 | BB25: =SUM(O25:Z25) -> 0 | BC25: =SUM(AA25:AL25) -> 0

Sheet Revenue
A1: AI API / Infrastructure — 3-Year Financial Model — Revenue
A2: Tiered customer bridge -> usage volume -> blended realized pricing -> usage + platform revenue.
A5: Line item | B5: Units / source | C5: Monthly (36 months) | AN5: Quarterly | BA5: Annual
C6: 46023 | D6: 46054 | E6: 46082 | F6: 46113 | G6: 46143 | H6: 46174 | I6: 46204 | J6: 46235 | K6: 46266 | L6: 46296 | M6: 46327 | N6: 46357 | O6: 46388 | P6: 46419 | Q6: 46447 | R6: 46478 | S6: 46508 | T6: 46539 | U6: 46569 | V6: 46600 | W6: 46631 | X6: 46661 | Y6: 46692 | Z6: 46722 | AA6: 46753 | AB6: 46784 | AC6: 46813 | AD6: 46844 | AE6: 46874 | AF6: 46905 | AG6: 46935 | AH6: 46966 | AI6: 46997 | AJ6: 47027 | AK6: 47058 | AL6: 47088 | AN6: Q1 | AO6: Q2 | AP6: Q3 | AQ6: Q4 | AR6: Q5 | AS6: Q6 | AT6: Q7 | AU6: Q8 | AV6: Q9 | AW6: Q10 | AX6: Q11 | AY6: Q12 | BA6: FY1 | BB6: FY2 | BC6: FY3
A7: Starter Tier
A8: Starter beginning customers | C8: ='Assumptions'!$F$13 -> 0 | D8: =C11 -> 0 | E8: =D11 -> 0 | F8: =E11 -> 0 | G8: =F11 -> 0 | H8: =G11 -> 0 | I8: =H11 -> 0 | J8: =I11 -> 0 | K8: =J11 -> 0 | ... AL8: =AK11 -> 0 | AN8: =E8 -> 0 | AO8: =H8 -> 0 | AP8: =K8 -> 0 | AQ8: =N8 -> 0 | AR8: =Q8 -> 0 | AS8: =T8 -> 0 | AT8: =W8 -> 0 | AU8: =Z8 -> 0 | AV8: =AC8 -> 0 | AW8: =AF8 -> 0 | AX8: =AI8 -> 0 | AY8: =AL8 -> 0 | BA8: =N8 -> 0 | BB8: =Z8 -> 0 | BC8: =AL8 -> 0
A9: Starter new customers | C9: ='Assumptions'!$F$14 -> 0 | D9: =C9*(1+'Assumptions'!$F$15) -> 0 | E9: =D9*(1+'Assumptions'!$F$15) -> 0 | F9: =E9*(1+'Assumptions'!$F$15) -> 0 | G9: =F9*(1+'Assumptions'!$F$15) -> 0 | H9: =G9*(1+'Assumptions'!$F$15) -> 0 | I9: =H9*(1+'Assumptions'!$F$15) -> 0 | J9: =I9*(1+'Assumptions'!$F$15) -> 0 | K9: =J9*(1+'Assumptions'!$F$15) -> 0 | ... AL9: =AK9*(1+'Assumptions'!$F$15) -> 0 | AN9: =SUM(C9:E9) -> 0 | AO9: =SUM(F9:H9) -> 0 | AP9: =SUM(I9:K9) -> 0 | AQ9: =SUM(L9:N9) -> 0 | AR9: =SUM(O9:Q9) -> 0 | AS9: =SUM(R9:T9) -> 0 | AT9: =SUM(U9:W9) -> 0 | AU9: =SUM(X9:Z9) -> 0 | AV9: =SUM(AA9:AC9) -> 0 | AW9: =SUM(AD9:AF9) -> 0 | AX9: =SUM(AG9:AI9) -> 0 | AY9: =SUM(AJ9:AL9) -> 0 | BA9: =SUM(C9:N9) -> 0 | BB9: =SUM(O9:Z9) -> 0 | BC9: =SUM(AA9:AL9) -> 0
A10: Starter churned customers | C10: =-C8*'Assumptions'!$F$16 -> 0 | D10: =-D8*'Assumptions'!$F$16 -> 0 | E10: =-E8*'Assumptions'!$F$16 -> 0 | F10: =-F8*'Assumptions'!$F$16 -> 0 | G10: =-G8*'Assumptions'!$F$16 -> 0 | H10: =-H8*'Assumptions'!$F$16 -> 0 | I10: =-I8*'Assumptions'!$F$16 -> 0 | J10: =-J8*'Assumptions'!$F$16 -> 0 | ... AL10: =-AL8*'Assumptions'!$F$16 -> 0 | AN10: =SUM(C10:E10) -> 0 | AO10: =SUM(F10:H10) -> 0 | AP10: =SUM(I10:K10) -> 0 | AQ10: =SUM(L10:N10) -> 0 | AR10: =SUM(O10:Q10) -> 0 | AS10: =SUM(R10:T10) -> 0 | AT10: =SUM(U10:W10) -> 0 | AU10: =SUM(X10:Z10) -> 0 | AV10: =SUM(AA10:AC10) -> 0 | AW10: =SUM(AD10:AF10) -> 0 | AX10: =SUM(AG10:AI10) -> 0 | AY10: =SUM(AJ10:AL10) -> 0 | BA10: =SUM(C10:N10) -> 0 | BB10: =SUM(O10:Z10) -> 0 | BC10: =SUM(AA10:AL10) -> 0
A11: Starter ending customers | C11: =C8+C9+C10 -> 0 | D11: =D8+D9+D10 -> 0 | E11: =E8+E9+E10 -> 0 | F11: =F8+F9+F10 -> 0 | G11: =G8+G9+G10 -> 0 | H11: =H8+H9+H10 -> 0 | I11: =I8+I9+I10 -> 0 | J11: =J8+J9+J10 -> 0 | ... AL11: =AL8+AL9+AL10 -> 0 | AN11: =E11 -> 0 | AO11: =H11 -> 0 | AP11: =K11 -> 0 | AQ11: =N11 -> 0 | AR11: =Q11 -> 0 | AS11: =T11 -> 0 | AT11: =W11 -> 0 | AU11: =Z11 -> 0 | AV11: =AC11 -> 0 | AW11: =AF11 -> 0 | AX11: =AI11 -> 0 | AY11: =AL11 -> 0 | BA11: =N11 -> 0 | BB11: =Z11 -> 0 | BC11: =AL11 -> 0
A12: Starter usage per customer | B12: Monthly inference request-equivalents in millions | C12: ='Assumptions'!$F$17 -> 0 | D12: =C12*(1+'Assumptions'!$F$18) -> 0 | E12: =D12*(1+'Assumptions'!$F$18) -> 0 | F12: =E12*(1+'Assumptions'!$F$18) -> 0 | G12: =F12*(1+'Assumptions'!$F$18) -> 0 | H12: =G12*(1+'Assumptions'!$F$18) -> 0 | I12: =H12*(1+'Assumptions'!$F$18) -> 0 | J12: =I12*(1+'Assumptions'!$F$18) -> 0 | K12: =J12*(1+'Assumptions'!$F$18) -> 0 | ... AL12: =AK12*(1+'Assumptions'!$F$18) -> 0 | AN12: =AVERAGE(C12:E12) -> 0 | AO12: =AVERAGE(F12:H12) -> 0 | AP12: =AVERAGE(I12:K12) -> 0 | AQ12: =AVERAGE(L12:N12) -> 0 | AR12: =AVERAGE(O12:Q12) -> 0 | AS12: =AVERAGE(R12:T12) -> 0 | AT12: =AVERAGE(U12:W12) -> 0 | AU12: =AVERAGE(X12:Z12) -> 0 | AV12: =AVERAGE(AA12:AC12) -> 0 | AW12: =AVERAGE(AD12:AF12) -> 0 | AX12: =AVERAGE(AG12:AI12) -> 0 | AY12: =AVERAGE(AJ12:AL12) -> 0 | BA12: =AVERAGE(C12:N12) -> 0 | BB12: =AVERAGE(O12:Z12) -> 0 | BC12: =AVERAGE(AA12:AL12) -> 0
A13: Starter gross request volume | B13: Active customers × usage per customer (M requests) | C13: =C11*C12 -> 0 | D13: =D11*D12 -> 0 | E13: =E11*E12 -> 0 | F13: =F11*F12 -> 0 | G13: =G11*G12 -> 0 | H13: =H11*H12 -> 0 | I13: =I11*I12 -> 0 | J13: =J11*J12 -> 0 | ... AL13: =AL11*AL12 -> 0 | AN13: =SUM(C13:E13) -> 0 | AO13: =SUM(F13:H13) -> 0 | AP13: =SUM(I13:K13) -> 0 | AQ13: =SUM(L13:N13) -> 0 | AR13: =SUM(O13:Q13) -> 0 | AS13: =SUM(R13:T13) -> 0 | AT13: =SUM(U13:W13) -> 0 | AU13: =SUM(X13:Z13) -> 0 | AV13: =SUM(AA13:AC13) -> 0 | AW13: =SUM(AD13:AF13) -> 0 | AX13: =SUM(AG13:AI13) -> 0 | AY13: =SUM(AJ13:AL13) -> 0 | BA13: =SUM(C13:N13) -> 0 | BB13: =SUM(O13:Z13) -> 0 | BC13: =SUM(AA13:AL13) -> 0
A15: Growth Tier
A16: Growth beginning customers | C16: ='Assumptions'!$F$19 -> 0 | D16: =C19 -> 0 | E16: =D19 -> 0 | F16: =E19 -> 0 | G16: =F19 -> 0 | H16: =G19 -> 0 | I16: =H19 -> 0 | J16: =I19 -> 0 | K16: =J19 -> 0 | ... AL16: =AK19 -> 0 | AN16: =E16 -> 0 | AO16: =H16 -> 0 | AP16: =K16 -> 0 | AQ16: =N16 -> 0 | AR16: =Q16 -> 0 | AS16: =T16 -> 0 | AT16: =W16 -> 0 | AU16: =Z16 -> 0 | AV16: =AC16 -> 0 | AW16: =AF16 -> 0 | AX16: =AI16 -> 0 | AY16: =AL16 -> 0 | BA16: =N16 -> 0 | BB16: =Z16 -> 0 | BC16: =AL16 -> 0
A17: Growth new customers | C17: ='Assumptions'!$F$20 -> 0 | D17: =C17*(1+'Assumptions'!$F$21) -> 0 | E17: =D17*(1+'Assumptions'!$F$21) -> 0 | F17: =E17*(1+'Assumptions'!$F$21) -> 0 | G17: =F17*(1+'Assumptions'!$F$21) -> 0 | H17: =G17*(1+'Assumptions'!$F$21) -> 0 | I17: =H17*(1+'Assumptions'!$F$21) -> 0 | J17: =I17*(1+'Assumptions'!$F$21) -> 0 | K17: =J17*(1+'Assumptions'!$F$21) -> 0 | ... AL17: =AK17*(1+'Assumptions'!$F$21) -> 0 | AN17: =SUM(C17:E17) -> 0 | AO17: =SUM(F17:H17) -> 0 | AP17: =SUM(I17:K17) -> 0 | AQ17: =SUM(L17:N17) -> 0 | AR17: =SUM(O17:Q17) -> 0 | AS17: =SUM(R17:T17) -> 0 | AT17: =SUM(U17:W17) -> 0 | AU17: =SUM(X17:Z17) -> 0 | AV17: =SUM(AA17:AC17) -> 0 | AW17: =SUM(AD17:AF17) -> 0 | AX17: =SUM(AG17:AI17) -> 0 | AY17: =SUM(AJ17:AL17) -> 0 | BA17: =SUM(C17:N17) -> 0 | BB17: =SUM(O17:Z17) -> 0 | BC17: =SUM(AA17:AL17) -> 0
A18: Growth churned customers | C18: =-C16*'Assumptions'!$F$22 -> 0 | D18: =-D16*'Assumptions'!$F$22 -> 0 | E18: =-E16*'Assumptions'!$F$22 -> 0 | F18: =-F16*'Assumptions'!$F$22 -> 0 | G18: =-G16*'Assumptions'!$F$22 -> 0 | H18: =-H16*'Assumptions'!$F$22 -> 0 | I18: =-I16*'Assumptions'!$F$22 -> 0 | J18: =-J16*'Assumptions'!$F$22 -> 0 | ... AL18: =-AL16*'Assumptions'!$F$22 -> 0 | AN18: =SUM(C18:E18) -> 0 | AO18: =SUM(F18:H18) -> 0 | AP18: =SUM(I18:K18) -> 0 | AQ18: =SUM(L18:N18) -> 0 | AR18: =SUM(O18:Q18) -> 0 | AS18: =SUM(R18:T18) -> 0 | AT18: =SUM(U18:W18) -> 0 | AU18: =SUM(X18:Z18) -> 0 | AV18: =SUM(AA18:AC18) -> 0 | AW18: =SUM(AD18:AF18) -> 0 | AX18: =SUM(AG18:AI18) -> 0 | AY18: =SUM(AJ18:AL18) -> 0 | BA18: =SUM(C18:N18) -> 0 | BB18: =SUM(O18:Z18) -> 0 | BC18: =SUM(AA18:AL18) -> 0
A19: Growth ending customers | C19: =C16+C17+C18 -> 0 | D19: =D16+D17+D18 -> 0 | E19: =E16+E17+E18 -> 0 | F19: =F16+F17+F18 -> 0 | G19: =G16+G17+G18 -> 0 | H19: =H16+H17+H18 -> 0 | I19: =I16+I17+I18 -> 0 | J19: =J16+J17+J18 -> 0 | ... AL19: =AL16+AL17+AL18 -> 0 | AN19: =E19 -> 0 | AO19: =H19 -> 0 | AP19: =K19 -> 0 | AQ19: =N19 -> 0 | AR19: =Q19 -> 0 | AS19: =T19 -> 0 | AT19: =W19 -> 0 | AU19: =Z19 -> 0 | AV19: =AC19 -> 0 | AW19: =AF19 -> 0 | AX19: =AI19 -> 0 | AY19: =AL19 -> 0 | BA19: =N19 -> 0 | BB19: =Z19 -> 0 | BC19: =AL19 -> 0
A20: Growth usage per customer | B20: Monthly inference request-equivalents in millions | C20: ='Assumptions'!$F$23 -> 0 | D20: =C20*(1+'Assumptions'!$F$24) -> 0 | E20: =D20*(1+'Assumptions'!$F$24) -> 0 | F20: =E20*(1+'Assumptions'!$F$24) -> 0 | G20: =F20*(1+'Assumptions'!$F$24) -> 0 | H20: =G20*(1+'Assumptions'!$F$24) -> 0 | I20: =H20*(1+'Assumptions'!$F$24) -> 0 | J20: =I20*(1+'Assumptions'!$F$24) -> 0 | K20: =J20*(1+'Assumptions'!$F$24) -> 0 | ... AL20: =AK20*(1+'Assumptions'!$F$24) -> 0 | AN20: =AVERAGE(C20:E20) -> 0 | AO20: =AVERAGE(F20:H20) -> 0 | AP20: =AVERAGE(I20:K20) -> 0 | AQ20: =AVERAGE(L20:N20) -> 0 | AR20: =AVERAGE(O20:Q20) -> 0 | AS20: =AVERAGE(R20:T20) -> 0 | AT20: =AVERAGE(U20:W20) -> 0 | AU20: =AVERAGE(X20:Z20) -> 0 | AV20: =AVERAGE(AA20:AC20) -> 0 | AW20: =AVERAGE(AD20:AF20) -> 0 | AX20: =AVERAGE(AG20:AI20) -> 0 | AY20: =AVERAGE(AJ20:AL20) -> 0 | BA20: =AVERAGE(C20:N20) -> 0 | BB20: =AVERAGE(O20:Z20) -> 0 | BC20: =AVERAGE(AA20:AL20) -> 0
A21: Growth gross request volume | B21: Active customers × usage per customer (M requests) | C21: =C19*C20 -> 0 | D21: =D19*D20 -> 0 | E21: =E19*E20 -> 0 | F21: =F19*F20 -> 0 | G21: =G19*G20 -> 0 | H21: =H19*H20 -> 0 | I21: =I19*I20 -> 0 | J21: =J19*J20 -> 0 | ... AL21: =AL19*AL20 -> 0 | AN21: =SUM(C21:E21) -> 0 | AO21: =SUM(F21:H21) -> 0 | AP21: =SUM(I21:K21) -> 0 | AQ21: =SUM(L21:N21) -> 0 | AR21: =SUM(O21:Q21) -> 0 | AS21: =SUM(R21:T21) -> 0 | AT21: =SUM(U21:W21) -> 0 | AU21: =SUM(X21:Z21) -> 0 | AV21: =SUM(AA21:AC21) -> 0 | AW21: =SUM(AD21:AF21) -> 0 | AX21: =SUM(AG21:AI21) -> 0 | AY21: =SUM(AJ21:AL21) -> 0 | BA21: =SUM(C21:N21) -> 0 | BB21: =SUM(O21:Z21) -> 0 | BC21: =SUM(AA21:AL21) -> 0
A23: Enterprise Tier
A24: Enterprise beginning customers | C24: ='Assumptions'!$F$25 -> 0 | D24: =C27 -> 0 | E24: =D27 -> 0 | F24: =E27 -> 0 | G24: =F27 -> 0 | H24: =G27 -> 0 | I24: =H27 -> 0 | J24: =I27 -> 0 | K24: =J27 -> 0 | ... AL24: =AK27 -> 0 | AN24: =E24 -> 0 | AO24: =H24 -> 0 | AP24: =K24 -> 0 | AQ24: =N24 -> 0 | AR24: =Q24 -> 0 | AS24: =T24 -> 0 | AT24: =W24 -> 0 | AU24: =Z24 -> 0 | AV24: =AC24 -> 0 | AW24: =AF24 -> 0 | AX24: =AI24 -> 0 | AY24: =AL24 -> 0 | BA24: =N24 -> 0 | BB24: =Z24 -> 0 | BC24: =AL24 -> 0
A25: Enterprise new customers | C25: ='Assumptions'!$F$26 -> 0 | D25: =C25*(1+'Assumptions'!$F$27) -> 0 | E25: =D25*(1+'Assumptions'!$F$27) -> 0 | F25: =E25*(1+'Assumptions'!$F$27) -> 0 | G25: =F25*(1+'Assumptions'!$F$27) -> 0 | H25: =G25*(1+'Assumptions'!$F$27) -> 0 | I25: =H25*(1+'Assumptions'!$F$27) -> 0 | J25: =I25*(1+'Assumptions'!$F$27) -> 0 | K25: =J25*(1+'Assumptions'!$F$27) -> 0 | ... AL25: =AK25*(1+'Assumptions'!$F$27) -> 0 | AN25: =SUM(C25:E25) -> 0 | AO25: =SUM(F25:H25) -> 0 | AP25: =SUM(I25:K25) -> 0 | AQ25: =SUM(L25:N25) -> 0 | AR25: =SUM(O25:Q25) -> 0 | AS25: =SUM(R25:T25) -> 0 | AT25: =SUM(U25:W25) -> 0 | AU25: =SUM(X25:Z25) -> 0 | AV25: =SUM(AA25:AC25) -> 0 | AW25: =SUM(AD25:AF25) -> 0 | AX25: =SUM(AG25:AI25) -> 0 | AY25: =SUM(AJ25:AL25) -> 0 | BA25: =SUM(C25:N25) -> 0 | BB25: =SUM(O25:Z25) -> 0 | BC25: =SUM(AA25:AL25) -> 0
A26: Enterprise churned customers | C26: =-C24*'Assumptions'!$F$28 -> 0 | D26: =-D24*'Assumptions'!$F$28 -> 0 | E26: =-E24*'Assumptions'!$F$28 -> 0 | F26: =-F24*'Assumptions'!$F$28 -> 0 | G26: =-G24*'Assumptions'!$F$28 -> 0 | H26: =-H24*'Assumptions'!$F$28 -> 0 | I26: =-I24*'Assumptions'!$F$28 -> 0 | J26: =-J24*'Assumptions'!$F$28 -> 0 | ... AL26: =-AL24*'Assumptions'!$F$28 -> 0 | AN26: =SUM(C26:E26) -> 0 | AO26: =SUM(F26:H26) -> 0 | AP26: =SUM(I26:K26) -> 0 | AQ26: =SUM(L26:N26) -> 0 | AR26: =SUM(O26:Q26) -> 0 | AS26: =SUM(R26:T26) -> 0 | AT26: =SUM(U26:W26) -> 0 | AU26: =SUM(X26:Z26) -> 0 | AV26: =SUM(AA26:AC26) -> 0 | AW26: =SUM(AD26:AF26) -> 0 | AX26: =SUM(AG26:AI26) -> 0 | AY26: =SUM(AJ26:AL26) -> 0 | BA26: =SUM(C26:N26) -> 0 | BB26: =SUM(O26:Z26) -> 0 | BC26: =SUM(AA26:AL26) -> 0
A27: Enterprise ending customers | C27: =C24+C25+C26 -> 0 | D27: =D24+D25+D26 -> 0 | E27: =E24+E25+E26 -> 0 | F27: =F24+F25+F26 -> 0 | G27: =G24+G25+G26 -> 0 | H27: =H24+H25+H26 -> 0 | I27: =I24+I25+I26 -> 0 | J27: =J24+J25+J26 -> 0 | ... AL27: =AL24+AL25+AL26 -> 0 | AN27: =E27 -> 0 | AO27: =H27 -> 0 | AP27: =K27 -> 0 | AQ27: =N27 -> 0 | AR27: =Q27 -> 0 | AS27: =T27 -> 0 | AT27: =W27 -> 0 | AU27: =Z27 -> 0 | AV27: =AC27 -> 0 | AW27: =AF27 -> 0 | AX27: =AI27 -> 0 | AY27: =AL27 -> 0 | BA27: =N27 -> 0 | BB27: =Z27 -> 0 | BC27: =AL27 -> 0
A28: Enterprise usage per customer | B28: Monthly inference request-equivalents in millions | C28: ='Assumptions'!$F$29 -> 0 | D28: =C28*(1+'Assumptions'!$F$30) -> 0 | E28: =D28*(1+'Assumptions'!$F$30) -> 0 | F28: =E28*(1+'Assumptions'!$F$30) -> 0 | G28: =F28*(1+'Assumptions'!$F$30) -> 0 | H28: =G28*(1+'Assumptions'!$F$30) -> 0 | I28: =H28*(1+'Assumptions'!$F$30) -> 0 | J28: =I28*(1+'Assumptions'!$F$30) -> 0 | K28: =J28*(1+'Assumptions'!$F$30) -> 0 | ... AL28: =AK28*(1+'Assumptions'!$F$30) -> 0 | AN28: =AVERAGE(C28:E28) -> 0 | AO28: =AVERAGE(F28:H28) -> 0 | AP28: =AVERAGE(I28:K28) -> 0 | AQ28: =AVERAGE(L28:N28) -> 0 | AR28: =AVERAGE(O28:Q28) -> 0 | AS28: =AVERAGE(R28:T28) -> 0 | AT28: =AVERAGE(U28:W28) -> 0 | AU28: =AVERAGE(X28:Z28) -> 0 | AV28: =AVERAGE(AA28:AC28) -> 0 | AW28: =AVERAGE(AD28:AF28) -> 0 | AX28: =AVERAGE(AG28:AI28) -> 0 | AY28: =AVERAGE(AJ28:AL28) -> 0 | BA28: =AVERAGE(C28:N28) -> 0 | BB28: =AVERAGE(O28:Z28) -> 0 | BC28: =AVERAGE(AA28:AL28) -> 0
A29: Enterprise gross request volume | B29: Active customers × usage per customer (M requests) | C29: =C27*C28 -> 0 | D29: =D27*D28 -> 0 | E29: =E27*E28 -> 0 | F29: =F27*F28 -> 0 | G29: =G27*G28 -> 0 | H29: =H27*H28 -> 0 | I29: =I27*I28 -> 0 | J29: =J27*J28 -> 0 | ... AL29: =AL27*AL28 -> 0 | AN29: =SUM(C29:E29) -> 0 | AO29: =SUM(F29:H29) -> 0 | AP29: =SUM(I29:K29) -> 0 | AQ29: =SUM(L29:N29) -> 0 | AR29: =SUM(O29:Q29) -> 0 | AS29: =SUM(R29:T29) -> 0 | AT29: =SUM(U29:W29) -> 0 | AU29: =SUM(X29:Z29) -> 0 | AV29: =SUM(AA29:AC29) -> 0 | AW29: =SUM(AD29:AF29) -> 0 | AX29: =SUM(AG29:AI29) -> 0 | AY29: =SUM(AJ29:AL29) -> 0 | BA29: =SUM(C29:N29) -> 0 | BB29: =SUM(O29:Z29) -> 0 | BC29: =SUM(AA29:AL29) -> 0
A31: Pricing, Volume & Revenue Bridge
A32: Premium-model mix | C32: ='Assumptions'!$F$35 -> 0 | D32: =MIN(0.60,MAX(0.05,C32+'Assumptions'!$F$36)) -> 0 | E32: =MIN(0.60,MAX(0.05,D32+'Assumptions'!$F$36)) -> 0 | F32: =MIN(0.60,MAX(0.05,E32+'Assumptions'!$F$36)) -> 0 | G32: =MIN(0.60,MAX(0.05,F32+'Assumptions'!$F$36)) -> 0 | H32: =MIN(0.60,MAX(0.05,G32+'Assumptions'!$F$36)) -> 0 | I32: =MIN(0.60,MAX(0.05,H32+'Assumptions'!$F$36)) -> 0 | J32: =MIN(0.60,MAX(0.05,I32+'Assumptions'!$F$36)) -> 0 | K32: =MIN(0.60,MAX(0.05,J32+'Assumptions'!$F$36)) -> 0 | ... AL32: =MIN(0.60,MAX(0.05,AK32+'Assumptions'!$F$36)) -> 0 | AN32: =AVERAGE(C32:E32) -> 0 | AO32: =AVERAGE(F32:H32) -> 0 | AP32: =AVERAGE(I32:K32) -> 0 | AQ32: =AVERAGE(L32:N32) -> 0 | AR32: =AVERAGE(O32:Q32) -> 0 | AS32: =AVERAGE(R32:T32) -> 0 | AT32: =AVERAGE(U32:W32) -> 0 | AU32: =AVERAGE(X32:Z32) -> 0 | AV32: =AVERAGE(AA32:AC32) -> 0 | AW32: =AVERAGE(AD32:AF32) -> 0 | AX32: =AVERAGE(AG32:AI32) -> 0 | AY32: =AVERAGE(AJ32:AL32) -> 0 | BA32: =AVERAGE(C32:N32) -> 0 | BB32: =AVERAGE(O32:Z32) -> 0 | BC32: =AVERAGE(AA32:AL32) -> 0
A33: Blended list price per 1M requests | C33: =('Assumptions'!$F$33*(1-C32)+'Assumptions'!$F$34*C32) -> 0 | D33: =('Assumptions'!$F$33*(1-D32)+'Assumptions'!$F$34*D32) -> 0 | E33: =('Assumptions'!$F$33*(1-E32)+'Assumptions'!$F$34*E32) -> 0 | F33: =('Assumptions'!$F$33*(1-F32)+'Assumptions'!$F$34*F32) -> 0 | G33: =('Assumptions'!$F$33*(1-G32)+'Assumptions'!$F$34*G32) -> 0 | H33: =('Assumptions'!$F$33*(1-H32)+'Assumptions'!$F$34*H32) -> 0 | I33: =('Assumptions'!$F$33*(1-I32)+'Assumptions'!$F$34*I32) -> 0 | J33: =('Assumptions'!$F$33*(1-J32)+'Assumptions'!$F$34*J32) -> 0 | ... AL33: =('Assumptions'!$F$33*(1-AL32)+'Assumptions'!$F$34*AL32) -> 0 | AN33: =AVERAGE(C33:E33) -> 0 | AO33: =AVERAGE(F33:H33) -> 0 | AP33: =AVERAGE(I33:K33) -> 0 | AQ33: =AVERAGE(L33:N33) -> 0 | AR33: =AVERAGE(O33:Q33) -> 0 | AS33: =AVERAGE(R33:T33) -> 0 | AT33: =AVERAGE(U33:W33) -> 0 | AU33: =AVERAGE(X33:Z33) -> 0 | AV33: =AVERAGE(AA33:AC33) -> 0 | AW33: =AVERAGE(AD33:AF33) -> 0 | AX33: =AVERAGE(AG33:AI33) -> 0 | AY33: =AVERAGE(AJ33:AL33) -> 0 | BA33: =AVERAGE(C33:N33) -> 0 | BB33: =AVERAGE(O33:Z33) -> 0 | BC33: =AVERAGE(AA33:AL33) -> 0
A34: Billable-volume factor | B34: Gross volume reduced for cache credits and batch discounts | C34: =(1-'Assumptions'!$F$41*'Assumptions'!$F$42)*(1-'Assumptions'!$F$43) -> 0 | D34: =(1-'Assumptions'!$F$41*'Assumptions'!$F$42)*(1-'Assumptions'!$F$43) -> 0 | E34: =(1-'Assumptions'!$F$41*'Assumptions'!$F$42)*(1-'Assumptions'!$F$43) -> 0 | F34: =(1-'Assumptions'!$F$41*'Assumptions'!$F$42)*(1-'Assumptions'!$F$43) -> 0 | G34: =(1-'Assumptions'!$F$41*'Assumptions'!$F$42)*(1-'Assumptions'!$F$43) -> 0 | H34: =(1-'Assumptions'!$F$41*'Assumptions'!$F$42)*(1-'Assumptions'!$F$43) -> 0 | I34: =(1-'Assumptions'!$F$41*'Assumptions'!$F$42)*(1-'Assumptions'!$F$43) -> 0 | J34: =(1-'Assumptions'!$F$41*'Assumptions'!$F$42)*(1-'Assumptions'!$F$43) -> 0 | ... AL34: =(1-'Assumptions'!$F$41*'Assumptions'!$F$42)*(1-'Assumptions'!$F$43) -> 0 | AN34: =AVERAGE(C34:E34) -> 0 | AO34: =AVERAGE(F34:H34) -> 0 | AP34: =AVERAGE(I34:K34) -> 0 | AQ34: =AVERAGE(L34:N34) -> 0 | AR34: =AVERAGE(O34:Q34) -> 0 | AS34: =AVERAGE(R34:T34) -> 0 | AT34: =AVERAGE(U34:W34) -> 0 | AU34: =AVERAGE(X34:Z34) -> 0 | AV34: =AVERAGE(AA34:AC34) -> 0 | AW34: =AVERAGE(AD34:AF34) -> 0 | AX34: =AVERAGE(AG34:AI34) -> 0 | AY34: =AVERAGE(AJ34:AL34) -> 0 | BA34: =AVERAGE(C34:N34) -> 0 | BB34: =AVERAGE(O34:Z34) -> 0 | BC34: =AVERAGE(AA34:AL34) -> 0
A35: Starter net price per 1M requests | C35: =C33*(1-'Assumptions'!$F$40)*'Assumptions'!$F$37 -> 0 | D35: =D33*(1-'Assumptions'!$F$40)*'Assumptions'!$F$37 -> 0 | E35: =E33*(1-'Assumptions'!$F$40)*'Assumptions'!$F$37 -> 0 | F35: =F33*(1-'Assumptions'!$F$40)*'Assumptions'!$F$37 -> 0 | G35: =G33*(1-'Assumptions'!$F$40)*'Assumptions'!$F$37 -> 0 | H35: =H33*(1-'Assumptions'!$F$40)*'Assumptions'!$F$37 -> 0 | I35: =I33*(1-'Assumptions'!$F$40)*'Assumptions'!$F$37 -> 0 | J35: =J33*(1-'Assumptions'!$F$40)*'Assumptions'!$F$37 -> 0 | ... AL35: =AL33*(1-'Assumptions'!$F$40)*'Assumptions'!$F$37 -> 0 | AN35: =AVERAGE(C35:E35) -> 0 | AO35: =AVERAGE(F35:H35) -> 0 | AP35: =AVERAGE(I35:K35) -> 0 | AQ35: =AVERAGE(L35:N35) -> 0 | AR35: =AVERAGE(O35:Q35) -> 0 | AS35: =AVERAGE(R35:T35) -> 0 | AT35: =AVERAGE(U35:W35) -> 0 | AU35: =AVERAGE(X35:Z35) -> 0 | AV35: =AVERAGE(AA35:AC35) -> 0 | AW35: =AVERAGE(AD35:AF35) -> 0 | AX35: =AVERAGE(AG35:AI35) -> 0 | AY35: =AVERAGE(AJ35:AL35) -> 0 | BA35: =AVERAGE(C35:N35) -> 0 | BB35: =AVERAGE(O35:Z35) -> 0 | BC35: =AVERAGE(AA35:AL35) -> 0
A36: Growth net price per 1M requests | C36: =C33*(1-'Assumptions'!$F$40)*'Assumptions'!$F$38 -> 0 | D36: =D33*(1-'Assumptions'!$F$40)*'Assumptions'!$F$38 -> 0 | E36: =E33*(1-'Assumptions'!$F$40)*'Assumptions'!$F$38 -> 0 | F36: =F33*(1-'Assumptions'!$F$40)*'Assumptions'!$F$38 -> 0 | G36: =G33*(1-'Assumptions'!$F$40)*'Assumptions'!$F$38 -> 0 | H36: =H33*(1-'Assumptions'!$F$40)*'Assumptions'!$F$38 -> 0 | I36: =I33*(1-'Assumptions'!$F$40)*'Assumptions'!$F$38 -> 0 | J36: =J33*(1-'Assumptions'!$F$40)*'Assumptions'!$F$38 -> 0 | ... AL36: =AL33*(1-'Assumptions'!$F$40)*'Assumptions'!$F$38 -> 0 | AN36: =AVERAGE(C36:E36) -> 0 | AO36: =AVERAGE(F36:H36) -> 0 | AP36: =AVERAGE(I36:K36) -> 0 | AQ36: =AVERAGE(L36:N36) -> 0 | AR36: =AVERAGE(O36:Q36) -> 0 | AS36: =AVERAGE(R36:T36) -> 0 | AT36: =AVERAGE(U36:W36) -> 0 | AU36: =AVERAGE(X36:Z36) -> 0 | AV36: =AVERAGE(AA36:AC36) -> 0 | AW36: =AVERAGE(AD36:AF36) -> 0 | AX36: =AVERAGE(AG36:AI36) -> 0 | AY36: =AVERAGE(AJ36:AL36) -> 0 | BA36: =AVERAGE(C36:N36) -> 0 | BB36: =AVERAGE(O36:Z36) -> 0 | BC36: =AVERAGE(AA36:AL36) -> 0
A37: Enterprise net price per 1M requests | C37: =C33*(1-'Assumptions'!$F$40)*'Assumptions'!$F$39 -> 0 | D37: =D33*(1-'Assumptions'!$F$40)*'Assumptions'!$F$39 -> 0 | E37: =E33*(1-'Assumptions'!$F$40)*'Assumptions'!$F$39 -> 0 | F37: =F33*(1-'Assumptions'!$F$40)*'Assumptions'!$F$39 -> 0 | G37: =G33*(1-'Assumptions'!$F$40)*'Assumptions'!$F$39 -> 0 | H37: =H33*(1-'Assumptions'!$F$40)*'Assumptions'!$F$39 -> 0 | I37: =I33*(1-'Assumptions'!$F$40)*'Assumptions'!$F$39 -> 0 | J37: =J33*(1-'Assumptions'!$F$40)*'Assumptions'!$F$39 -> 0 | ... AL37: =AL33*(1-'Assumptions'!$F$40)*'Assumptions'!$F$39 -> 0 | AN37: =AVERAGE(C37:E37) -> 0 | AO37: =AVERAGE(F37:H37) -> 0 | AP37: =AVERAGE(I37:K37) -> 0 | AQ37: =AVERAGE(L37:N37) -> 0 | AR37: =AVERAGE(O37:Q37) -> 0 | AS37: =AVERAGE(R37:T37) -> 0 | AT37: =AVERAGE(U37:W37) -> 0 | AU37: =AVERAGE(X37:Z37) -> 0 | AV37: =AVERAGE(AA37:AC37) -> 0 | AW37: =AVERAGE(AD37:AF37) -> 0 | AX37: =AVERAGE(AG37:AI37) -> 0 | AY37: =AVERAGE(AJ37:AL37) -> 0 | BA37: =AVERAGE(C37:N37) -> 0 | BB37: =AVERAGE(O37:Z37) -> 0 | BC37: =AVERAGE(AA37:AL37) -> 0
A39: Starter usage revenue | C39: =C13*C34*C35 -> 0 | D39: =D13*D34*D35 -> 0 | E39: =E13*E34*E35 -> 0 | F39: =F13*F34*F35 -> 0 | G39: =G13*G34*G35 -> 0 | H39: =H13*H34*H35 -> 0 | I39: =I13*I34*I35 -> 0 | J39: =J13*J34*J35 -> 0 | ... AL39: =AL13*AL34*AL35 -> 0 | AN39: =SUM(C39:E39) -> 0 | AO39: =SUM(F39:H39) -> 0 | AP39: =SUM(I39:K39) -> 0 | AQ39: =SUM(L39:N39) -> 0 | AR39: =SUM(O39:Q39) -> 0 | AS39: =SUM(R39:T39) -> 0 | AT39: =SUM(U39:W39) -> 0 | AU39: =SUM(X39:Z39) -> 0 | AV39: =SUM(AA39:AC39) -> 0 | AW39: =SUM(AD39:AF39) -> 0 | AX39: =SUM(AG39:AI39) -> 0 | AY39: =SUM(AJ39:AL39) -> 0 | BA39: =SUM(C39:N39) -> 0 | BB39: =SUM(O39:Z39) -> 0 | BC39: =SUM(AA39:AL39) -> 0
A40: Starter platform revenue | C40: =C11*'Assumptions'!$F$44 -> 0 | D40: =D11*'Assumptions'!$F$44 -> 0 | E40: =E11*'Assumptions'!$F$44 -> 0 | F40: =F11*'Assumptions'!$F$44 -> 0 | G40: =G11*'Assumptions'!$F$44 -> 0 | H40: =H11*'Assumptions'!$F$44 -> 0 | I40: =I11*'Assumptions'!$F$44 -> 0 | J40: =J11*'Assumptions'!$F$44 -> 0 | ... AL40: =AL11*'Assumptions'!$F$44 -> 0 | AN40: =SUM(C40:E40) -> 0 | AO40: =SUM(F40:H40) -> 0 | AP40: =SUM(I40:K40) -> 0 | AQ40: =SUM(L40:N40) -> 0 | AR40: =SUM(O40:Q40) -> 0 | AS40: =SUM(R40:T40) -> 0 | AT40: =SUM(U40:W40) -> 0 | AU40: =SUM(X40:Z40) -> 0 | AV40: =SUM(AA40:AC40) -> 0 | AW40: =SUM(AD40:AF40) -> 0 | AX40: =SUM(AG40:AI40) -> 0 | AY40: =SUM(AJ40:AL40) -> 0 | BA40: =SUM(C40:N40) -> 0 | BB40: =SUM(O40:Z40) -> 0 | BC40: =SUM(AA40:AL40) -> 0
A41: Starter total revenue | C41: =C39+C40 -> 0 | D41: =D39+D40 -> 0 | E41: =E39+E40 -> 0 | F41: =F39+F40 -> 0 | G41: =G39+G40 -> 0 | H41: =H39+H40 -> 0 | I41: =I39+I40 -> 0 | J41: =J39+J40 -> 0 | ... AL41: =AL39+AL40 -> 0 | AN41: =SUM(C41:E41) -> 0 | AO41: =SUM(F41:H41) -> 0 | AP41: =SUM(I41:K41) -> 0 | AQ41: =SUM(L41:N41) -> 0 | AR41: =SUM(O41:Q41) -> 0 | AS41: =SUM(R41:T41) -> 0 | AT41: =SUM(U41:W41) -> 0 | AU41: =SUM(X41:Z41) -> 0 | AV41: =SUM(AA41:AC41) -> 0 | AW41: =SUM(AD41:AF41) -> 0 | AX41: =SUM(AG41:AI41) -> 0 | AY41: =SUM(AJ41:AL41) -> 0 | BA41: =SUM(C41:N41) -> 0 | BB41: =SUM(O41:Z41) -> 0 | BC41: =SUM(AA41:AL41) -> 0
A42: Starter new-customer revenue added | B42: Used for sales commission modeling | C42: =C9*C12*C34*C35+C9*'Assumptions'!$F$44 -> 0 | D42: =D9*D12*D34*D35+D9*'Assumptions'!$F$44 -> 0 | E42: =E9*E12*E34*E35+E9*'Assumptions'!$F$44 -> 0 | F42: =F9*F12*F34*F35+F9*'Assumptions'!$F$44 -> 0 | G42: =G9*G12*G34*G35+G9*'Assumptions'!$F$44 -> 0 | H42: =H9*H12*H34*H35+H9*'Assumptions'!$F$44 -> 0 | I42: =I9*I12*I34*I35+I9*'Assumptions'!$F$44 -> 0 | J42: =J9*J12*J34*J35+J9*'Assumptions'!$F$44 -> 0 | ... AL42: =AL9*AL12*AL34*AL35+AL9*'Assumptions'!$F$44 -> 0 | AN42: =SUM(C42:E42) -> 0 | AO42: =SUM(F42:H42) -> 0 | AP42: =SUM(I42:K42) -> 0 | AQ42: =SUM(L42:N42) -> 0 | AR42: =SUM(O42:Q42) -> 0 | AS42: =SUM(R42:T42) -> 0 | AT42: =SUM(U42:W42) -> 0 | AU42: =SUM(X42:Z42) -> 0 | AV42: =SUM(AA42:AC42) -> 0 | AW42: =SUM(AD42:AF42) -> 0 | AX42: =SUM(AG42:AI42) -> 0 | AY42: =SUM(AJ42:AL42) -> 0 | BA42: =SUM(C42:N42) -> 0 | BB42: =SUM(O42:Z42) -> 0 | BC42: =SUM(AA42:AL42) -> 0
A44: Growth usage revenue | C44: =C21*C34*C36 -> 0 | D44: =D21*D34*D36 -> 0 | E44: =E21*E34*E36 -> 0 | F44: =F21*F34*F36 -> 0 | G44: =G21*G34*G36 -> 0 | H44: =H21*H34*H36 -> 0 | I44: =I21*I34*I36 -> 0 | J44: =J21*J34*J36 -> 0 | ... AL44: =AL21*AL34*AL36 -> 0 | AN44: =SUM(C44:E44) -> 0 | AO44: =SUM(F44:H44) -> 0 | AP44: =SUM(I44:K44) -> 0 | AQ44: =SUM(L44:N44) -> 0 | AR44: =SUM(O44:Q44) -> 0 | AS44: =SUM(R44:T44) -> 0 | AT44: =SUM(U44:W44) -> 0 | AU44: =SUM(X44:Z44) -> 0 | AV44: =SUM(AA44:AC44) -> 0 | AW44: =SUM(AD44:AF44) -> 0 | AX44: =SUM(AG44:AI44) -> 0 | AY44: =SUM(AJ44:AL44) -> 0 | BA44: =SUM(C44:N44) -> 0 | BB44: =SUM(O44:Z44) -> 0 | BC44: =SUM(AA44:AL44) -> 0
A45: Growth platform revenue | C45: =C19*'Assumptions'!$F$45 -> 0 | D45: =D19*'Assumptions'!$F$45 -> 0 | E45: =E19*'Assumptions'!$F$45 -> 0 | F45: =F19*'Assumptions'!$F$45 -> 0 | G45: =G19*'Assumptions'!$F$45 -> 0 | H45: =H19*'Assumptions'!$F$45 -> 0 | I45: =I19*'Assumptions'!$F$45 -> 0 | J45: =J19*'Assumptions'!$F$45 -> 0 | ... AL45: =AL19*'Assumptions'!$F$45 -> 0 | AN45: =SUM(C45:E45) -> 0 | AO45: =SUM(F45:H45) -> 0 | AP45: =SUM(I45:K45) -> 0 | AQ45: =SUM(L45:N45) -> 0 | AR45: =SUM(O45:Q45) -> 0 | AS45: =SUM(R45:T45) -> 0 | AT45: =SUM(U45:W45) -> 0 | AU45: =SUM(X45:Z45) -> 0 | AV45: =SUM(AA45:AC45) -> 0 | AW45: =SUM(AD45:AF45) -> 0 | AX45: =SUM(AG45:AI45) -> 0 | AY45: =SUM(AJ45:AL45) -> 0 | BA45: =SUM(C45:N45) -> 0 | BB45: =SUM(O45:Z45) -> 0 | BC45: =SUM(AA45:AL45) -> 0
A46: Growth total revenue | C46: =C44+C45 -> 0 | D46: =D44+D45 -> 0 | E46: =E44+E45 -> 0 | F46: =F44+F45 -> 0 | G46: =G44+G45 -> 0 | H46: =H44+H45 -> 0 | I46: =I44+I45 -> 0 | J46: =J44+J45 -> 0 | ... AL46: =AL44+AL45 -> 0 | AN46: =SUM(C46:E46) -> 0 | AO46: =SUM(F46:H46) -> 0 | AP46: =SUM(I46:K46) -> 0 | AQ46: =SUM(L46:N46) -> 0 | AR46: =SUM(O46:Q46) -> 0 | AS46: =SUM(R46:T46) -> 0 | AT46: =SUM(U46:W46) -> 0 | AU46: =SUM(X46:Z46) -> 0 | AV46: =SUM(AA46:AC46) -> 0 | AW46: =SUM(AD46:AF46) -> 0 | AX46: =SUM(AG46:AI46) -> 0 | AY46: =SUM(AJ46:AL46) -> 0 | BA46: =SUM(C46:N46) -> 0 | BB46: =SUM(O46:Z46) -> 0 | BC46: =SUM(AA46:AL46) -> 0
A47: Growth new-customer revenue added | B47: Used for sales commission modeling | C47: =C17*C20*C34*C36+C17*'Assumptions'!$F$45 -> 0 | D47: =D17*D20*D34*D36+D17*'Assumptions'!$F$45 -> 0 | E47: =E17*E20*E34*E36+E17*'Assumptions'!$F$45 -> 0 | F47: =F17*F20*F34*F36+F17*'Assumptions'!$F$45 -> 0 | G47: =G17*G20*G34*G36+G17*'Assumptions'!$F$45 -> 0 | H47: =H17*H20*H34*H36+H17*'Assumptions'!$F$45 -> 0 | I47: =I17*I20*I34*I36+I17*'Assumptions'!$F$45 -> 0 | J47: =J17*J20*J34*J36+J17*'Assumptions'!$F$45 -> 0 | ... AL47: =AL17*AL20*AL34*AL36+AL17*'Assumptions'!$F$45 -> 0 | AN47: =SUM(C47:E47) -> 0 | AO47: =SUM(F47:H47) -> 0 | AP47: =SUM(I47:K47) -> 0 | AQ47: =SUM(L47:N47) -> 0 | AR47: =SUM(O47:Q47) -> 0 | AS47: =SUM(R47:T47) -> 0 | AT47: =SUM(U47:W47) -> 0 | AU47: =SUM(X47:Z47) -> 0 | AV47: =SUM(AA47:AC47) -> 0 | AW47: =SUM(AD47:AF47) -> 0 | AX47: =SUM(AG47:AI47) -> 0 | AY47: =SUM(AJ47:AL47) -> 0 | BA47: =SUM(C47:N47) -> 0 | BB47: =SUM(O47:Z47) -> 0 | BC47: =SUM(AA47:AL47) -> 0
A49: Enterprise usage revenue | C49: =C29*C34*C37 -> 0 | D49: =D29*D34*D37 -> 0 | E49: =E29*E34*E37 -> 0 | F49: =F29*F34*F37 -> 0 | G49: =G29*G34*G37 -> 0 | H49: =H29*H34*H37 -> 0 | I49: =I29*I34*I37 -> 0 | J49: =J29*J34*J37 -> 0 | ... AL49: =AL29*AL34*AL37 -> 0 | AN49: =SUM(C49:E49) -> 0 | AO49: =SUM(F49:H49) -> 0 | AP49: =SUM(I49:K49) -> 0 | AQ49: =SUM(L49:N49) -> 0 | AR49: =SUM(O49:Q49) -> 0 | AS49: =SUM(R49:T49) -> 0 | AT49: =SUM(U49:W49) -> 0 | AU49: =SUM(X49:Z49) -> 0 | AV49: =SUM(AA49:AC49) -> 0 | AW49: =SUM(AD49:AF49) -> 0 | AX49: =SUM(AG49:AI49) -> 0 | AY49: =SUM(AJ49:AL49) -> 0 | BA49: =SUM(C49:N49) -> 0 | BB49: =SUM(O49:Z49) -> 0 | BC49: =SUM(AA49:AL49) -> 0
A50: Enterprise platform revenue | C50: =C27*'Assumptions'!$F$46 -> 0 | D50: =D27*'Assumptions'!$F$46 -> 0 | E50: =E27*'Assumptions'!$F$46 -> 0 | F50: =F27*'Assumptions'!$F$46 -> 0 | G50: =G27*'Assumptions'!$F$46 -> 0 | H50: =H27*'Assumptions'!$F$46 -> 0 | I50: =I27*'Assumptions'!$F$46 -> 0 | J50: =J27*'Assumptions'!$F$46 -> 0 | ... AL50: =AL27*'Assumptions'!$F$46 -> 0 | AN50: =SUM(C50:E50) -> 0 | AO50: =SUM(F50:H50) -> 0 | AP50: =SUM(I50:K50) -> 0 | AQ50: =SUM(L50:N50) -> 0 | AR50: =SUM(O50:Q50) -> 0 | AS50: =SUM(R50:T50) -> 0 | AT50: =SUM(U50:W50) -> 0 | AU50: =SUM(X50:Z50) -> 0 | AV50: =SUM(AA50:AC50) -> 0 | AW50: =SUM(AD50:AF50) -> 0 | AX50: =SUM(AG50:AI50) -> 0 | AY50: =SUM(AJ50:AL50) -> 0 | BA50: =SUM(C50:N50) -> 0 | BB50: =SUM(O50:Z50) -> 0 | BC50: =SUM(AA50:AL50) -> 0
A51: Enterprise total revenue | C51: =C49+C50 -> 0 | D51: =D49+D50 -> 0 | E51: =E49+E50 -> 0 | F51: =F49+F50 -> 0 | G51: =G49+G50 -> 0 | H51: =H49+H50 -> 0 | I51: =I49+I50 -> 0 | J51: =J49+J50 -> 0 | ... AL51: =AL49+AL50 -> 0 | AN51: =SUM(C51:E51) -> 0 | AO51: =SUM(F51:H51) -> 0 | AP51: =SUM(I51:K51) -> 0 | AQ51: =SUM(L51:N51) -> 0 | AR51: =SUM(O51:Q51) -> 0 | AS51: =SUM(R51:T51) -> 0 | AT51: =SUM(U51:W51) -> 0 | AU51: =SUM(X51:Z51) -> 0 | AV51: =SUM(AA51:AC51) -> 0 | AW51: =SUM(AD51:AF51) -> 0 | AX51: =SUM(AG51:AI51) -> 0 | AY51: =SUM(AJ51:AL51) -> 0 | BA51: =SUM(C51:N51) -> 0 | BB51: =SUM(O51:Z51) -> 0 | BC51: =SUM(AA51:AL51) -> 0
A52: Enterprise new-customer revenue added | B52: Used for sales commission modeling | C52: =C25*C28*C34*C37+C25*'Assumptions'!$F$46 -> 0 | D52: =D25*D28*D34*D37+D25*'Assumptions'!$F$46 -> 0 | E52: =E25*E28*E34*E37+E25*'Assumptions'!$F$46 -> 0 | F52: =F25*F28*F34*F37+F25*'Assumptions'!$F$46 -> 0 | G52: =G25*G28*G34*G37+G25*'Assumptions'!$F$46 -> 0 | H52: =H25*H28*H34*H37+H25*'Assumptions'!$F$46 -> 0 | I52: =I25*I28*I34*I37+I25*'Assumptions'!$F$46 -> 0 | J52: =J25*J28*J34*J37+J25*'Assumptions'!$F$46 -> 0 | ... AL52: =AL25*AL28*AL34*AL37+AL25*'Assumptions'!$F$46 -> 0 | AN52: =SUM(C52:E52) -> 0 | AO52: =SUM(F52:H52) -> 0 | AP52: =SUM(I52:K52) -> 0 | AQ52: =SUM(L52:N52) -> 0 | AR52: =SUM(O52:Q52) -> 0 | AS52: =SUM(R52:T52) -> 0 | AT52: =SUM(U52:W52) -> 0 | AU52: =SUM(X52:Z52) -> 0 | AV52: =SUM(AA52:AC52) -> 0 | AW52: =SUM(AD52:AF52) -> 0 | AX52: =SUM(AG52:AI52) -> 0 | AY52: =SUM(AJ52:AL52) -> 0 | BA52: =SUM(C52:N52) -> 0 | BB52: =SUM(O52:Z52) -> 0 | BC52: =SUM(AA52:AL52) -> 0
A54: Revenue Totals & KPIs
A55: Total gross request volume | B55: Sum of tier gross volume (M requests) | C55: =C13+C21+C29 -> 0 | D55: =D13+D21+D29 -> 0 | E55: =E13+E21+E29 -> 0 | F55: =F13+F21+F29 -> 0 | G55: =G13+G21+G29 -> 0 | H55: =H13+H21+H29 -> 0 | I55: =I13+I21+I29 -> 0 | J55: =J13+J21+J29 -> 0 | ... AL55: =AL13+AL21+AL29 -> 0 | AN55: =SUM(C55:E55) -> 0 | AO55: =SUM(F55:H55) -> 0 | AP55: =SUM(I55:K55) -> 0 | AQ55: =SUM(L55:N55) -> 0 | AR55: =SUM(O55:Q55) -> 0 | AS55: =SUM(R55:T55) -> 0 | AT55: =SUM(U55:W55) -> 0 | AU55: =SUM(X55:Z55) -> 0 | AV55: =SUM(AA55:AC55) -> 0 | AW55: =SUM(AD55:AF55) -> 0 | AX55: =SUM(AG55:AI55) -> 0 | AY55: =SUM(AJ55:AL55) -> 0 | BA55: =SUM(C55:N55) -> 0 | BB55: =SUM(O55:Z55) -> 0 | BC55: =SUM(AA55:AL55) -> 0
A56: Total billable request volume | B56: Gross volume × billable-volume factor (M requests) | C56: =C55*C34 -> 0 | D56: =D55*D34 -> 0 | E56: =E55*E34 -> 0 | F56: =F55*F34 -> 0 | G56: =G55*G34 -> 0 | H56: =H55*H34 -> 0 | I56: =I55*I34 -> 0 | J56: =J55*J34 -> 0 | ... AL56: =AL55*AL34 -> 0 | AN56: =SUM(C56:E56) -> 0 | AO56: =SUM(F56:H56) -> 0 | AP56: =SUM(I56:K56) -> 0 | AQ56: =SUM(L56:N56) -> 0 | AR56: =SUM(O56:Q56) -> 0 | AS56: =SUM(R56:T56) -> 0 | AT56: =SUM(U56:W56) -> 0 | AU56: =SUM(X56:Z56) -> 0 | AV56: =SUM(AA56:AC56) -> 0 | AW56: =SUM(AD56:AF56) -> 0 | AX56: =SUM(AG56:AI56) -> 0 | AY56: =SUM(AJ56:AL56) -> 0 | BA56: =SUM(C56:N56) -> 0 | BB56: =SUM(O56:Z56) -> 0 | BC56: =SUM(AA56:AL56) -> 0
A57: Total usage revenue | C57: =C39+C44+C49 -> 0 | D57: =D39+D44+D49 -> 0 | E57: =E39+E44+E49 -> 0 | F57: =F39+F44+F49 -> 0 | G57: =G39+G44+G49 -> 0 | H57: =H39+H44+H49 -> 0 | I57: =I39+I44+I49 -> 0 | J57: =J39+J44+J49 -> 0 | ... AL57: =AL39+AL44+AL49 -> 0 | AN57: =SUM(C57:E57) -> 0 | AO57: =SUM(F57:H57) -> 0 | AP57: =SUM(I57:K57) -> 0 | AQ57: =SUM(L57:N57) -> 0 | AR57: =SUM(O57:Q57) -> 0 | AS57: =SUM(R57:T57) -> 0 | AT57: =SUM(U57:W57) -> 0 | AU57: =SUM(X57:Z57) -> 0 | AV57: =SUM(AA57:AC57) -> 0 | AW57: =SUM(AD57:AF57) -> 0 | AX57: =SUM(AG57:AI57) -> 0 | AY57: =SUM(AJ57:AL57) -> 0 | BA57: =SUM(C57:N57) -> 0 | BB57: =SUM(O57:Z57) -> 0 | BC57: =SUM(AA57:AL57) -> 0
A58: Total platform / subscription revenue | C58: =C40+C45+C50 -> 0 | D58: =D40+D45+D50 -> 0 | E58: =E40+E45+E50 -> 0 | F58: =F40+F45+F50 -> 0 | G58: =G40+G45+G50 -> 0 | H58: =H40+H45+H50 -> 0 | I58: =I40+I45+I50 -> 0 | J58: =J40+J45+J50 -> 0 | ... AL58: =AL40+AL45+AL50 -> 0 | AN58: =SUM(C58:E58) -> 0 | AO58: =SUM(F58:H58) -> 0 | AP58: =SUM(I58:K58) -> 0 | AQ58: =SUM(L58:N58) -> 0 | AR58: =SUM(O58:Q58) -> 0 | AS58: =SUM(R58:T58) -> 0 | AT58: =SUM(U58:W58) -> 0 | AU58: =SUM(X58:Z58) -> 0 | AV58: =SUM(AA58:AC58) -> 0 | AW58: =SUM(AD58:AF58) -> 0 | AX58: =SUM(AG58:AI58) -> 0 | AY58: =SUM(AJ58:AL58) -> 0 | BA58: =SUM(C58:N58) -> 0 | BB58: =SUM(O58:Z58) -> 0 | BC58: =SUM(AA58:AL58) -> 0
A59: Total new-customer revenue added | B59: Used for variable sales commissions | C59: =C42+C47+C52 -> 0 | D59: =D42+D47+D52 -> 0 | E59: =E42+E47+E52 -> 0 | F59: =F42+F47+F52 -> 0 | G59: =G42+G47+G52 -> 0 | H59: =H42+H47+H52 -> 0 | I59: =I42+I47+I52 -> 0 | J59: =J42+J47+J52 -> 0 | ... AL59: =AL42+AL47+AL52 -> 0 | AN59: =SUM(C59:E59) -> 0 | AO59: =SUM(F59:H59) -> 0 | AP59: =SUM(I59:K59) -> 0 | AQ59: =SUM(L59:N59) -> 0 | AR59: =SUM(O59:Q59) -> 0 | AS59: =SUM(R59:T59) -> 0 | AT59: =SUM(U59:W59) -> 0 | AU59: =SUM(X59:Z59) -> 0 | AV59: =SUM(AA59:AC59) -> 0 | AW59: =SUM(AD59:AF59) -> 0 | AX59: =SUM(AG59:AI59) -> 0 | AY59: =SUM(AJ59:AL59) -> 0 | BA59: =SUM(C59:N59) -> 0 | BB59: =SUM(O59:Z59) -> 0 | BC59: =SUM(AA59:AL59) -> 0
A60: Total Revenue | C60: =C57+C58 -> 0 | D60: =D57+D58 -> 0 | E60: =E57+E58 -> 0 | F60: =F57+F58 -> 0 | G60: =G57+G58 -> 0 | H60: =H57+H58 -> 0 | I60: =I57+I58 -> 0 | J60: =J57+J58 -> 0 | ... AL60: =AL57+AL58 -> 0 | AN60: =SUM(C60:E60) -> 0 | AO60: =SUM(F60:H60) -> 0 | AP60: =SUM(I60:K60) -> 0 | AQ60: =SUM(L60:N60) -> 0 | AR60: =SUM(O60:Q60) -> 0 | AS60: =SUM(R60:T60) -> 0 | AT60: =SUM(U60:W60) -> 0 | AU60: =SUM(X60:Z60) -> 0 | AV60: =SUM(AA60:AC60) -> 0 | AW60: =SUM(AD60:AF60) -> 0 | AX60: =SUM(AG60:AI60) -> 0 | AY60: =SUM(AJ60:AL60) -> 0 | BA60: =SUM(C60:N60) -> 0 | BB60: =SUM(O60:Z60) -> 0 | BC60: =SUM(AA60:AL60) -> 0
A62: Total active customers | C62: =C11+C19+C27 -> 0 | D62: =D11+D19+D27 -> 0 | E62: =E11+E19+E27 -> 0 | F62: =F11+F19+F27 -> 0 | G62: =G11+G19+G27 -> 0 | H62: =H11+H19+H27 -> 0 | I62: =I11+I19+I27 -> 0 | J62: =J11+J19+J27 -> 0 | ... AL62: =AL11+AL19+AL27 -> 0 | AN62: =E62 -> 0 | AO62: =H62 -> 0 | AP62: =K62 -> 0 | AQ62: =N62 -> 0 | AR62: =Q62 -> 0 | AS62: =T62 -> 0 | AT62: =W62 -> 0 | AU62: =Z62 -> 0 | AV62: =AC62 -> 0 | AW62: =AF62 -> 0 | AX62: =AI62 -> 0 | AY62: =AL62 -> 0 | BA62: =N62 -> 0 | BB62: =Z62 -> 0 | BC62: =AL62 -> 0
A63: Usage revenue per billable 1M requests | C63: =IFERROR(C57/C56,0) -> 0 | D63: =IFERROR(D57/D56,0) -> 0 | E63: =IFERROR(E57/E56,0) -> 0 | F63: =IFERROR(F57/F56,0) -> 0 | G63: =IFERROR(G57/G56,0) -> 0 | H63: =IFERROR(H57/H56,0) -> 0 | I63: =IFERROR(I57/I56,0) -> 0 | J63: =IFERROR(J57/J56,0) -> 0 | ... AL63: =IFERROR(AL57/AL56,0) -> 0 | AN63: =AVERAGE(C63:E63) -> 0 | AO63: =AVERAGE(F63:H63) -> 0 | AP63: =AVERAGE(I63:K63) -> 0 | AQ63: =AVERAGE(L63:N63) -> 0 | AR63: =AVERAGE(O63:Q63) -> 0 | AS63: =AVERAGE(R63:T63) -> 0 | AT63: =AVERAGE(U63:W63) -> 0 | AU63: =AVERAGE(X63:Z63) -> 0 | AV63: =AVERAGE(AA63:AC63) -> 0 | AW63: =AVERAGE(AD63:AF63) -> 0 | AX63: =AVERAGE(AG63:AI63) -> 0 | AY63: =AVERAGE(AJ63:AL63) -> 0 | BA63: =AVERAGE(C63:N63) -> 0 | BB63: =AVERAGE(O63:Z63) -> 0 | BC63: =AVERAGE(AA63:AL63) -> 0
A64: Platform-fee share of revenue | C64: =IFERROR(C58/C60,0) -> 0 | D64: =IFERROR(D58/D60,0) -> 0 | E64: =IFERROR(E58/E60,0) -> 0 | F64: =IFERROR(F58/F60,0) -> 0 | G64: =IFERROR(G58/G60,0) -> 0 | H64: =IFERROR(H58/H60,0) -> 0 | I64: =IFERROR(I58/I60,0) -> 0 | J64: =IFERROR(J58/J60,0) -> 0 | ... AL64: =IFERROR(AL58/AL60,0) -> 0 | AN64: =AVERAGE(C64:E64) -> 0 | AO64: =AVERAGE(F64:H64) -> 0 | AP64: =AVERAGE(I64:K64) -> 0 | AQ64: =AVERAGE(L64:N64) -> 0 | AR64: =AVERAGE(O64:Q64) -> 0 | AS64: =AVERAGE(R64:T64) -> 0 | AT64: =AVERAGE(U64:W64) -> 0 | AU64: =AVERAGE(X64:Z64) -> 0 | AV64: =AVERAGE(AA64:AC64) -> 0 | AW64: =AVERAGE(AD64:AF64) -> 0 | AX64: =AVERAGE(AG64:AI64) -> 0 | AY64: =AVERAGE(AJ64:AL64) -> 0 | BA64: =AVERAGE(C64:N64) -> 0 | BB64: =AVERAGE(O64:Z64) -> 0 | BC64: =AVERAGE(AA64:AL64) -> 0
A65: Enterprise revenue concentration | B65: Enterprise-tier revenue as % of total revenue | C65: =IFERROR(C51/C60,0) -> 0 | D65: =IFERROR(D51/D60,0) -> 0 | E65: =IFERROR(E51/E60,0) -> 0 | F65: =IFERROR(F51/F60,0) -> 0 | G65: =IFERROR(G51/G60,0) -> 0 | H65: =IFERROR(H51/H60,0) -> 0 | I65: =IFERROR(I51/I60,0) -> 0 | J65: =IFERROR(J51/J60,0) -> 0 | ... AL65: =IFERROR(AL51/AL60,0) -> 0 | AN65: =AVERAGE(C65:E65) -> 0 | AO65: =AVERAGE(F65:H65) -> 0 | AP65: =AVERAGE(I65:K65) -> 0 | AQ65: =AVERAGE(L65:N65) -> 0 | AR65: =AVERAGE(O65:Q65) -> 0 | AS65: =AVERAGE(R65:T65) -> 0 | AT65: =AVERAGE(U65:W65) -> 0 | AU65: =AVERAGE(X65:Z65) -> 0 | AV65: =AVERAGE(AA65:AC65) -> 0 | AW65: =AVERAGE(AD65:AF65) -> 0 | AX65: =AVERAGE(AG65:AI65) -> 0 | AY65: =AVERAGE(AJ65:AL65) -> 0 | BA65: =AVERAGE(C65:N65) -> 0 | BB65: =AVERAGE(O65:Z65) -> 0 | BC65: =AVERAGE(AA65:AL65) -> 0
A66: Average revenue per active customer | C66: =IFERROR(C60/C62,0) -> 0 | D66: =IFERROR(D60/D62,0) -> 0 | E66: =IFERROR(E60/E62,0) -> 0 | F66: =IFERROR(F60/F62,0) -> 0 | G66: =IFERROR(G60/G62,0) -> 0 | H66: =IFERROR(H60/H62,0) -> 0 | I66: =IFERROR(I60/I62,0) -> 0 | J66: =IFERROR(J60/J62,0) -> 0 | ... AL66: =IFERROR(AL60/AL62,0) -> 0 | AN66: =AVERAGE(C66:E66) -> 0 | AO66: =AVERAGE(F66:H66) -> 0 | AP66: =AVERAGE(I66:K66) -> 0 | AQ66: =AVERAGE(L66:N66) -> 0 | AR66: =AVERAGE(O66:Q66) -> 0 | AS66: =AVERAGE(R66:T66) -> 0 | AT66: =AVERAGE(U66:W66) -> 0 | AU66: =AVERAGE(X66:Z66) -> 0 | AV66: =AVERAGE(AA66:AC66) -> 0 | AW66: =AVERAGE(AD66:AF66) -> 0 | AX66: =AVERAGE(AG66:AI66) -> 0 | AY66: =AVERAGE(AJ66:AL66) -> 0 | BA66: =AVERAGE(C66:N66) -> 0 | BB66: =AVERAGE(O66:Z66) -> 0 | BC66: =AVERAGE(AA66:AL66) -> 0
A67: Billable-volume growth (month over month) | C67: =0 -> 0 | D67: =IFERROR(D56/C56-1,0) -> 0 | E67: =IFERROR(E56/D56-1,0) -> 0 | F67: =IFERROR(F56/E56-1,0) -> 0 | G67: =IFERROR(G56/F56-1,0) -> 0 | H67: =IFERROR(H56/G56-1,0) -> 0 | I67: =IFERROR(I56/H56-1,0) -> 0 | J67: =IFERROR(J56/I56-1,0) -> 0 | K67: =IFERROR(K56/J56-1,0) -> 0 | ... AL67: =IFERROR(AL56/AK56-1,0) -> 0 | AN67: =AVERAGE(C67:E67) -> 0 | AO67: =AVERAGE(F67:H67) -> 0 | AP67: =AVERAGE(I67:K67) -> 0 | AQ67: =AVERAGE(L67:N67) -> 0 | AR67: =AVERAGE(O67:Q67) -> 0 | AS67: =AVERAGE(R67:T67) -> 0 | AT67: =AVERAGE(U67:W67) -> 0 | AU67: =AVERAGE(X67:Z67) -> 0 | AV67: =AVERAGE(AA67:AC67) -> 0 | AW67: =AVERAGE(AD67:AF67) -> 0 | AX67: =AVERAGE(AG67:AI67) -> 0 | AY67: =AVERAGE(AJ67:AL67) -> 0 | BA67: =AVERAGE(C67:N67) -> 0 | BB67: =AVERAGE(O67:Z67) -> 0 | BC67: =AVERAGE(AA67:AL67) -> 0
A68: Revenue growth (month over month) | C68: =0 -> 0 | D68: =IFERROR(D60/C60-1,0) -> 0 | E68: =IFERROR(E60/D60-1,0) -> 0 | F68: =IFERROR(F60/E60-1,0) -> 0 | G68: =IFERROR(G60/F60-1,0) -> 0 | H68: =IFERROR(H60/G60-1,0) -> 0 | I68: =IFERROR(I60/H60-1,0) -> 0 | J68: =IFERROR(J60/I60-1,0) -> 0 | K68: =IFERROR(K60/J60-1,0) -> 0 | ... AL68: =IFERROR(AL60/AK60-1,0) -> 0 | AN68: =AVERAGE(C68:E68) -> 0 | AO68: =AVERAGE(F68:H68) -> 0 | AP68: =AVERAGE(I68:K68) -> 0 | AQ68: =AVERAGE(L68:N68) -> 0 | AR68: =AVERAGE(O68:Q68) -> 0 | AS68: =AVERAGE(R68:T68) -> 0 | AT68: =AVERAGE(U68:W68) -> 0 | AU68: =AVERAGE(X68:Z68) -> 0 | AV68: =AVERAGE(AA68:AC68) -> 0 | AW68: =AVERAGE(AD68:AF68) -> 0 | AX68: =AVERAGE(AG68:AI68) -> 0 | AY68: =AVERAGE(AJ68:AL68) -> 0 | BA68: =AVERAGE(C68:N68) -> 0 | BB68: =AVERAGE(O68:Z68) -> 0 | BC68: =AVERAGE(AA68:AL68) -> 0

Sheet COGS & GM
A1: AI API / Infrastructure — 3-Year Financial Model — COGS & GM
A2: Compute, model-provider, storage, bandwidth, and infrastructure people costs tied to usage volume.
A5: Line item | B5: Units / source | C5: Monthly (36 months) | AN5: Quarterly | BA5: Annual
C6: 46023 | D6: 46054 | E6: 46082 | F6: 46113 | G6: 46143 | H6: 46174 | I6: 46204 | J6: 46235 | K6: 46266 | L6: 46296 | M6: 46327 | N6: 46357 | O6: 46388 | P6: 46419 | Q6: 46447 | R6: 46478 | S6: 46508 | T6: 46539 | U6: 46569 | V6: 46600 | W6: 46631 | X6: 46661 | Y6: 46692 | Z6: 46722 | AA6: 46753 | AB6: 46784 | AC6: 46813 | AD6: 46844 | AE6: 46874 | AF6: 46905 | AG6: 46935 | AH6: 46966 | AI6: 46997 | AJ6: 47027 | AK6: 47058 | AL6: 47088 | AN6: Q1 | AO6: Q2 | AP6: Q3 | AQ6: Q4 | AR6: Q5 | AS6: Q6 | AT6: Q7 | AU6: Q8 | AV6: Q9 | AW6: Q10 | AX6: Q11 | AY6: Q12 | BA6: FY1 | BB6: FY2 | BC6: FY3
A7: Volume Drivers & Utilization
A8: Gross request volume | B8: Linked from Revenue tab (M requests) | C8: ='Revenue'!$C$55 -> 0 | D8: ='Revenue'!$D$55 -> 0 | E8: ='Revenue'!$E$55 -> 0 | F8: ='Revenue'!$F$55 -> 0 | G8: ='Revenue'!$G$55 -> 0 | H8: ='Revenue'!$H$55 -> 0 | I8: ='Revenue'!$I$55 -> 0 | J8: ='Revenue'!$J$55 -> 0 | K8: ='Revenue'!$K$55 -> 0 | L8: ='Revenue'!$L$55 -> 0 | M8: ='Revenue'!$M$55 -> 0 | N8: ='Revenue'!$N$55 -> 0 | O8: ='Revenue'!$O$55 -> 0 | P8: ='Revenue'!$P$55 -> 0 | Q8: ='Revenue'!$Q$55 -> 0 | R8: ='Revenue'!$R$55 -> 0 | S8: ='Revenue'!$S$55 -> 0 | T8: ='Revenue'!$T$55 -> 0 | U8: ='Revenue'!$U$55 -> 0 | V8: ='Revenue'!$V$55 -> 0 | W8: ='Revenue'!$W$55 -> 0 | X8: ='Revenue'!$X$55 -> 0 | Y8: ='Revenue'!$Y$55 -> 0 | Z8: ='Revenue'!$Z$55 -> 0 | AA8: ='Revenue'!$AA$55 -> 0 | AB8: ='Revenue'!$AB$55 -> 0 | AC8: ='Revenue'!$AC$55 -> 0 | AD8: ='Revenue'!$AD$55 -> 0 | AE8: ='Revenue'!$AE$55 -> 0 | AF8: ='Revenue'!$AF$55 -> 0 | AG8: ='Revenue'!$AG$55 -> 0 | AH8: ='Revenue'!$AH$55 -> 0 | AI8: ='Revenue'!$AI$55 -> 0 | AJ8: ='Revenue'!$AJ$55 -> 0 | AK8: ='Revenue'!$AK$55 -> 0 | AL8: ='Revenue'!$AL$55 -> 0 | AN8: =SUM(C8:E8) -> 0 | AO8: =SUM(F8:H8) -> 0 | AP8: =SUM(I8:K8) -> 0 | AQ8: =SUM(L8:N8) -> 0 | AR8: =SUM(O8:Q8) -> 0 | AS8: =SUM(R8:T8) -> 0 | AT8: =SUM(U8:W8) -> 0 | AU8: =SUM(X8:Z8) -> 0 | AV8: =SUM(AA8:AC8) -> 0 | AW8: =SUM(AD8:AF8) -> 0 | AX8: =SUM(AG8:AI8) -> 0 | AY8: =SUM(AJ8:AL8) -> 0 | BA8: =SUM(C8:N8) -> 0 | BB8: =SUM(O8:Z8) -> 0 | BC8: =SUM(AA8:AL8) -> 0
A9: Billable request volume | B9: Linked from Revenue tab (M requests) | C9: ='Revenue'!$C$56 -> 0 | D9: ='Revenue'!$D$56 -> 0 | E9: ='Revenue'!$E$56 -> 0 | F9: ='Revenue'!$F$56 -> 0 | G9: ='Revenue'!$G$56 -> 0 | H9: ='Revenue'!$H$56 -> 0 | I9: ='Revenue'!$I$56 -> 0 | J9: ='Revenue'!$J$56 -> 0 | K9: ='Revenue'!$K$56 -> 0 | L9: ='Revenue'!$L$56 -> 0 | M9: ='Revenue'!$M$56 -> 0 | N9: ='Revenue'!$N$56 -> 0 | O9: ='Revenue'!$O$56 -> 0 | P9: ='Revenue'!$P$56 -> 0 | Q9: ='Revenue'!$Q$56 -> 0 | R9: ='Revenue'!$R$56 -> 0 | S9: ='Revenue'!$S$56 -> 0 | T9: ='Revenue'!$T$56 -> 0 | U9: ='Revenue'!$U$56 -> 0 | V9: ='Revenue'!$V$56 -> 0 | W9: ='Revenue'!$W$56 -> 0 | X9: ='Revenue'!$X$56 -> 0 | Y9: ='Revenue'!$Y$56 -> 0 | Z9: ='Revenue'!$Z$56 -> 0 | AA9: ='Revenue'!$AA$56 -> 0 | AB9: ='Revenue'!$AB$56 -> 0 | AC9: ='Revenue'!$AC$56 -> 0 | AD9: ='Revenue'!$AD$56 -> 0 | AE9: ='Revenue'!$AE$56 -> 0 | AF9: ='Revenue'!$AF$56 -> 0 | AG9: ='Revenue'!$AG$56 -> 0 | AH9: ='Revenue'!$AH$56 -> 0 | AI9: ='Revenue'!$AI$56 -> 0 | AJ9: ='Revenue'!$AJ$56 -> 0 | AK9: ='Revenue'!$AK$56 -> 0 | AL9: ='Revenue'!$AL$56 -> 0 | AN9: =SUM(C9:E9) -> 0 | AO9: =SUM(F9:H9) -> 0 | AP9: =SUM(I9:K9) -> 0 | AQ9: =SUM(L9:N9) -> 0 | AR9: =SUM(O9:Q9) -> 0 | AS9: =SUM(R9:T9) -> 0 | AT9: =SUM(U9:W9) -> 0 | AU9: =SUM(X9:Z9) -> 0 | AV9: =SUM(AA9:AC9) -> 0 | AW9: =SUM(AD9:AF9) -> 0 | AX9: =SUM(AG9:AI9) -> 0 | AY9: =SUM(AJ9:AL9) -> 0 | BA9: =SUM(C9:N9) -> 0 | BB9: =SUM(O9:Z9) -> 0 | BC9: =SUM(AA9:AL9) -> 0
A10: Fresh-inference / processed volume | B10: Gross volume after cache hits and batch discounts (M requests) | C10: ='Revenue'!C55*(1-'Assumptions'!$F$41)*(1-'Assumptions'!$F$43) -> 0 | D10: ='Revenue'!D55*(1-'Assumptions'!$F$41)*(1-'Assumptions'!$F$43) -> 0 | E10: ='Revenue'!E55*(1-'Assumptions'!$F$41)*(1-'Assumptions'!$F$43) -> 0 | F10: ='Revenue'!F55*(1-'Assumptions'!$F$41)*(1-'Assumptions'!$F$43) -> 0 | G10: ='Revenue'!G55*(1-'Assumptions'!$F$41)*(1-'Assumptions'!$F$43) -> 0 | H10: ='Revenue'!H55*(1-'Assumptions'!$F$41)*(1-'Assumptions'!$F$43) -> 0 | I10: ='Revenue'!I55*(1-'Assumptions'!$F$41)*(1-'Assumptions'!$F$43) -> 0 | J10: ='Revenue'!J55*(1-'Assumptions'!$F$41)*(1-'Assumptions'!$F$43) -> 0 | ... AL10: ='Revenue'!AL55*(1-'Assumptions'!$F$41)*(1-'Assumptions'!$F$43) -> 0 | AN10: =SUM(C10:E10) -> 0 | AO10: =SUM(F10:H10) -> 0 | AP10: =SUM(I10:K10) -> 0 | AQ10: =SUM(L10:N10) -> 0 | AR10: =SUM(O10:Q10) -> 0 | AS10: =SUM(R10:T10) -> 0 | AT10: =SUM(U10:W10) -> 0 | AU10: =SUM(X10:Z10) -> 0 | AV10: =SUM(AA10:AC10) -> 0 | AW10: =SUM(AD10:AF10) -> 0 | AX10: =SUM(AG10:AI10) -> 0 | AY10: =SUM(AJ10:AL10) -> 0 | BA10: =SUM(C10:N10) -> 0 | BB10: =SUM(O10:Z10) -> 0 | BC10: =SUM(AA10:AL10) -> 0
A11: Reserved-capacity utilization | C11: ='Assumptions'!$F$56 -> 0 | D11: =MIN(0.88,MAX(0.35,C11+'Assumptions'!$F$57)) -> 0 | E11: =MIN(0.88,MAX(0.35,D11+'Assumptions'!$F$57)) -> 0 | F11: =MIN(0.88,MAX(0.35,E11+'Assumptions'!$F$57)) -> 0 | G11: =MIN(0.88,MAX(0.35,F11+'Assumptions'!$F$57)) -> 0 | H11: =MIN(0.88,MAX(0.35,G11+'Assumptions'!$F$57)) -> 0 | I11: =MIN(0.88,MAX(0.35,H11+'Assumptions'!$F$57)) -> 0 | J11: =MIN(0.88,MAX(0.35,I11+'Assumptions'!$F$57)) -> 0 | K11: =MIN(0.88,MAX(0.35,J11+'Assumptions'!$F$57)) -> 0 | ... AL11: =MIN(0.88,MAX(0.35,AK11+'Assumptions'!$F$57)) -> 0 | AN11: =AVERAGE(C11:E11) -> 0 | AO11: =AVERAGE(F11:H11) -> 0 | AP11: =AVERAGE(I11:K11) -> 0 | AQ11: =AVERAGE(L11:N11) -> 0 | AR11: =AVERAGE(O11:Q11) -> 0 | AS11: =AVERAGE(R11:T11) -> 0 | AT11: =AVERAGE(U11:W11) -> 0 | AU11: =AVERAGE(X11:Z11) -> 0 | AV11: =AVERAGE(AA11:AC11) -> 0 | AW11: =AVERAGE(AD11:AF11) -> 0 | AX11: =AVERAGE(AG11:AI11) -> 0 | AY11: =AVERAGE(AJ11:AL11) -> 0 | BA11: =AVERAGE(C11:N11) -> 0 | BB11: =AVERAGE(O11:Z11) -> 0 | BC11: =AVERAGE(AA11:AL11) -> 0
A12: Effective compute cost per 1M requests | B12: Reserved cost is utilization-adjusted, then blended with on-demand | C12: =('Assumptions'!$F$55*'Assumptions'!$F$49/MAX(0.35,C11)+(1-'Assumptions'!$F$55)*'Assumptions'!$F$50) -> 0 | D12: =('Assumptions'!$F$55*'Assumptions'!$F$49/MAX(0.35,D11)+(1-'Assumptions'!$F$55)*'Assumptions'!$F$50) -> 0 | E12: =('Assumptions'!$F$55*'Assumptions'!$F$49/MAX(0.35,E11)+(1-'Assumptions'!$F$55)*'Assumptions'!$F$50) -> 0 | F12: =('Assumptions'!$F$55*'Assumptions'!$F$49/MAX(0.35,F11)+(1-'Assumptions'!$F$55)*'Assumptions'!$F$50) -> 0 | G12: =('Assumptions'!$F$55*'Assumptions'!$F$49/MAX(0.35,G11)+(1-'Assumptions'!$F$55)*'Assumptions'!$F$50) -> 0 | H12: =('Assumptions'!$F$55*'Assumptions'!$F$49/MAX(0.35,H11)+(1-'Assumptions'!$F$55)*'Assumptions'!$F$50) -> 0 | I12: =('Assumptions'!$F$55*'Assumptions'!$F$49/MAX(0.35,I11)+(1-'Assumptions'!$F$55)*'Assumptions'!$F$50) -> 0 | J12: =('Assumptions'!$F$55*'Assumptions'!$F$49/MAX(0.35,J11)+(1-'Assumptions'!$F$55)*'Assumptions'!$F$50) -> 0 | ... AL12: =('Assumptions'!$F$55*'Assumptions'!$F$49/MAX(0.35,AL11)+(1-'Assumptions'!$F$55)*'Assumptions'!$F$50) -> 0 | AN12: =AVERAGE(C12:E12) -> 0 | AO12: =AVERAGE(F12:H12) -> 0 | AP12: =AVERAGE(I12:K12) -> 0 | AQ12: =AVERAGE(L12:N12) -> 0 | AR12: =AVERAGE(O12:Q12) -> 0 | AS12: =AVERAGE(R12:T12) -> 0 | AT12: =AVERAGE(U12:W12) -> 0 | AU12: =AVERAGE(X12:Z12) -> 0 | AV12: =AVERAGE(AA12:AC12) -> 0 | AW12: =AVERAGE(AD12:AF12) -> 0 | AX12: =AVERAGE(AG12:AI12) -> 0 | AY12: =AVERAGE(AJ12:AL12) -> 0 | BA12: =AVERAGE(C12:N12) -> 0 | BB12: =AVERAGE(O12:Z12) -> 0 | BC12: =AVERAGE(AA12:AL12) -> 0
A13: Blended provider/API cost per 1M requests | B13: Weighted average of standard and premium provider cost | C13: =('Assumptions'!$F$51*(1-'Revenue'!C32)+'Assumptions'!$F$52*'Revenue'!C32) -> 0 | D13: =('Assumptions'!$F$51*(1-'Revenue'!D32)+'Assumptions'!$F$52*'Revenue'!D32) -> 0 | E13: =('Assumptions'!$F$51*(1-'Revenue'!E32)+'Assumptions'!$F$52*'Revenue'!E32) -> 0 | F13: =('Assumptions'!$F$51*(1-'Revenue'!F32)+'Assumptions'!$F$52*'Revenue'!F32) -> 0 | G13: =('Assumptions'!$F$51*(1-'Revenue'!G32)+'Assumptions'!$F$52*'Revenue'!G32) -> 0 | H13: =('Assumptions'!$F$51*(1-'Revenue'!H32)+'Assumptions'!$F$52*'Revenue'!H32) -> 0 | I13: =('Assumptions'!$F$51*(1-'Revenue'!I32)+'Assumptions'!$F$52*'Revenue'!I32) -> 0 | J13: =('Assumptions'!$F$51*(1-'Revenue'!J32)+'Assumptions'!$F$52*'Revenue'!J32) -> 0 | ... AL13: =('Assumptions'!$F$51*(1-'Revenue'!AL32)+'Assumptions'!$F$52*'Revenue'!AL32) -> 0 | AN13: =AVERAGE(C13:E13) -> 0 | AO13: =AVERAGE(F13:H13) -> 0 | AP13: =AVERAGE(I13:K13) -> 0 | AQ13: =AVERAGE(L13:N13) -> 0 | AR13: =AVERAGE(O13:Q13) -> 0 | AS13: =AVERAGE(R13:T13) -> 0 | AT13: =AVERAGE(U13:W13) -> 0 | AU13: =AVERAGE(X13:Z13) -> 0 | AV13: =AVERAGE(AA13:AC13) -> 0 | AW13: =AVERAGE(AD13:AF13) -> 0 | AX13: =AVERAGE(AG13:AI13) -> 0 | AY13: =AVERAGE(AJ13:AL13) -> 0 | BA13: =AVERAGE(C13:N13) -> 0 | BB13: =AVERAGE(O13:Z13) -> 0 | BC13: =AVERAGE(AA13:AL13) -> 0
A15: COGS Components
A16: Compute infrastructure | C16: =C10*C12 -> 0 | D16: =D10*D12 -> 0 | E16: =E10*E12 -> 0 | F16: =F10*F12 -> 0 | G16: =G10*G12 -> 0 | H16: =H10*H12 -> 0 | I16: =I10*I12 -> 0 | J16: =J10*J12 -> 0 | ... AL16: =AL10*AL12 -> 0 | AN16: =SUM(C16:E16) -> 0 | AO16: =SUM(F16:H16) -> 0 | AP16: =SUM(I16:K16) -> 0 | AQ16: =SUM(L16:N16) -> 0 | AR16: =SUM(O16:Q16) -> 0 | AS16: =SUM(R16:T16) -> 0 | AT16: =SUM(U16:W16) -> 0 | AU16: =SUM(X16:Z16) -> 0 | AV16: =SUM(AA16:AC16) -> 0 | AW16: =SUM(AD16:AF16) -> 0 | AX16: =SUM(AG16:AI16) -> 0 | AY16: =SUM(AJ16:AL16) -> 0 | BA16: =SUM(C16:N16) -> 0 | BB16: =SUM(O16:Z16) -> 0 | BC16: =SUM(AA16:AL16) -> 0
A17: External model / API providers | C17: =C10*C13 -> 0 | D17: =D10*D13 -> 0 | E17: =E10*E13 -> 0 | F17: =F10*F13 -> 0 | G17: =G10*G13 -> 0 | H17: =H10*H13 -> 0 | I17: =I10*I13 -> 0 | J17: =J10*J13 -> 0 | ... AL17: =AL10*AL13 -> 0 | AN17: =SUM(C17:E17) -> 0 | AO17: =SUM(F17:H17) -> 0 | AP17: =SUM(I17:K17) -> 0 | AQ17: =SUM(L17:N17) -> 0 | AR17: =SUM(O17:Q17) -> 0 | AS17: =SUM(R17:T17) -> 0 | AT17: =SUM(U17:W17) -> 0 | AU17: =SUM(X17:Z17) -> 0 | AV17: =SUM(AA17:AC17) -> 0 | AW17: =SUM(AD17:AF17) -> 0 | AX17: =SUM(AG17:AI17) -> 0 | AY17: =SUM(AJ17:AL17) -> 0 | BA17: =SUM(C17:N17) -> 0 | BB17: =SUM(O17:Z17) -> 0 | BC17: =SUM(AA17:AL17) -> 0
A18: Storage / vector / retrieval | C18: ='Revenue'!C55*'Assumptions'!$F$53 -> 0 | D18: ='Revenue'!D55*'Assumptions'!$F$53 -> 0 | E18: ='Revenue'!E55*'Assumptions'!$F$53 -> 0 | F18: ='Revenue'!F55*'Assumptions'!$F$53 -> 0 | G18: ='Revenue'!G55*'Assumptions'!$F$53 -> 0 | H18: ='Revenue'!H55*'Assumptions'!$F$53 -> 0 | I18: ='Revenue'!I55*'Assumptions'!$F$53 -> 0 | J18: ='Revenue'!J55*'Assumptions'!$F$53 -> 0 | ... AL18: ='Revenue'!AL55*'Assumptions'!$F$53 -> 0 | AN18: =SUM(C18:E18) -> 0 | AO18: =SUM(F18:H18) -> 0 | AP18: =SUM(I18:K18) -> 0 | AQ18: =SUM(L18:N18) -> 0 | AR18: =SUM(O18:Q18) -> 0 | AS18: =SUM(R18:T18) -> 0 | AT18: =SUM(U18:W18) -> 0 | AU18: =SUM(X18:Z18) -> 0 | AV18: =SUM(AA18:AC18) -> 0 | AW18: =SUM(AD18:AF18) -> 0 | AX18: =SUM(AG18:AI18) -> 0 | AY18: =SUM(AJ18:AL18) -> 0 | BA18: =SUM(C18:N18) -> 0 | BB18: =SUM(O18:Z18) -> 0 | BC18: =SUM(AA18:AL18) -> 0
A19: Bandwidth / egress | C19: ='Revenue'!C55*'Assumptions'!$F$54 -> 0 | D19: ='Revenue'!D55*'Assumptions'!$F$54 -> 0 | E19: ='Revenue'!E55*'Assumptions'!$F$54 -> 0 | F19: ='Revenue'!F55*'Assumptions'!$F$54 -> 0 | G19: ='Revenue'!G55*'Assumptions'!$F$54 -> 0 | H19: ='Revenue'!H55*'Assumptions'!$F$54 -> 0 | I19: ='Revenue'!I55*'Assumptions'!$F$54 -> 0 | J19: ='Revenue'!J55*'Assumptions'!$F$54 -> 0 | ... AL19: ='Revenue'!AL55*'Assumptions'!$F$54 -> 0 | AN19: =SUM(C19:E19) -> 0 | AO19: =SUM(F19:H19) -> 0 | AP19: =SUM(I19:K19) -> 0 | AQ19: =SUM(L19:N19) -> 0 | AR19: =SUM(O19:Q19) -> 0 | AS19: =SUM(R19:T19) -> 0 | AT19: =SUM(U19:W19) -> 0 | AU19: =SUM(X19:Z19) -> 0 | AV19: =SUM(AA19:AC19) -> 0 | AW19: =SUM(AD19:AF19) -> 0 | AX19: =SUM(AG19:AI19) -> 0 | AY19: =SUM(AJ19:AL19) -> 0 | BA19: =SUM(C19:N19) -> 0 | BB19: =SUM(O19:Z19) -> 0 | BC19: =SUM(AA19:AL19) -> 0
A20: Infrastructure / SRE people cost | C20: ='Headcount'!$C$21 -> 0 | D20: ='Headcount'!$D$21 -> 0 | E20: ='Headcount'!$E$21 -> 0 | F20: ='Headcount'!$F$21 -> 0 | G20: ='Headcount'!$G$21 -> 0 | H20: ='Headcount'!$H$21 -> 0 | I20: ='Headcount'!$I$21 -> 0 | J20: ='Headcount'!$J$21 -> 0 | K20: ='Headcount'!$K$21 -> 0 | L20: ='Headcount'!$L$21 -> 0 | M20: ='Headcount'!$M$21 -> 0 | N20: ='Headcount'!$N$21 -> 0 | O20: ='Headcount'!$O$21 -> 0 | P20: ='Headcount'!$P$21 -> 0 | Q20: ='Headcount'!$Q$21 -> 0 | R20: ='Headcount'!$R$21 -> 0 | S20: ='Headcount'!$S$21 -> 0 | T20: ='Headcount'!$T$21 -> 0 | U20: ='Headcount'!$U$21 -> 0 | V20: ='Headcount'!$V$21 -> 0 | W20: ='Headcount'!$W$21 -> 0 | X20: ='Headcount'!$X$21 -> 0 | Y20: ='Headcount'!$Y$21 -> 0 | Z20: ='Headcount'!$Z$21 -> 0 | AA20: ='Headcount'!$AA$21 -> 0 | AB20: ='Headcount'!$AB$21 -> 0 | AC20: ='Headcount'!$AC$21 -> 0 | AD20: ='Headcount'!$AD$21 -> 0 | AE20: ='Headcount'!$AE$21 -> 0 | AF20: ='Headcount'!$AF$21 -> 0 | AG20: ='Headcount'!$AG$21 -> 0 | AH20: ='Headcount'!$AH$21 -> 0 | AI20: ='Headcount'!$AI$21 -> 0 | AJ20: ='Headcount'!$AJ$21 -> 0 | AK20: ='Headcount'!$AK$21 -> 0 | AL20: ='Headcount'!$AL$21 -> 0 | AN20: =SUM(C20:E20) -> 0 | AO20: =SUM(F20:H20) -> 0 | AP20: =SUM(I20:K20) -> 0 | AQ20: =SUM(L20:N20) -> 0 | AR20: =SUM(O20:Q20) -> 0 | AS20: =SUM(R20:T20) -> 0 | AT20: =SUM(U20:W20) -> 0 | AU20: =SUM(X20:Z20) -> 0 | AV20: =SUM(AA20:AC20) -> 0 | AW20: =SUM(AD20:AF20) -> 0 | AX20: =SUM(AG20:AI20) -> 0 | AY20: =SUM(AJ20:AL20) -> 0 | BA20: =SUM(C20:N20) -> 0 | BB20: =SUM(O20:Z20) -> 0 | BC20: =SUM(AA20:AL20) -> 0
A21: Total COGS | C21: =C16+C17+C18+C19+C20 -> 0 | D21: =D16+D17+D18+D19+D20 -> 0 | E21: =E16+E17+E18+E19+E20 -> 0 | F21: =F16+F17+F18+F19+F20 -> 0 | G21: =G16+G17+G18+G19+G20 -> 0 | H21: =H16+H17+H18+H19+H20 -> 0 | I21: =I16+I17+I18+I19+I20 -> 0 | J21: =J16+J17+J18+J19+J20 -> 0 | ... AL21: =AL16+AL17+AL18+AL19+AL20 -> 0 | AN21: =SUM(C21:E21) -> 0 | AO21: =SUM(F21:H21) -> 0 | AP21: =SUM(I21:K21) -> 0 | AQ21: =SUM(L21:N21) -> 0 | AR21: =SUM(O21:Q21) -> 0 | AS21: =SUM(R21:T21) -> 0 | AT21: =SUM(U21:W21) -> 0 | AU21: =SUM(X21:Z21) -> 0 | AV21: =SUM(AA21:AC21) -> 0 | AW21: =SUM(AD21:AF21) -> 0 | AX21: =SUM(AG21:AI21) -> 0 | AY21: =SUM(AJ21:AL21) -> 0 | BA21: =SUM(C21:N21) -> 0 | BB21: =SUM(O21:Z21) -> 0 | BC21: =SUM(AA21:AL21) -> 0
A23: Margins & Unit-Economics KPIs
A24: Gross Profit | C24: ='Revenue'!C60-C21 -> 0 | D24: ='Revenue'!D60-D21 -> 0 | E24: ='Revenue'!E60-E21 -> 0 | F24: ='Revenue'!F60-F21 -> 0 | G24: ='Revenue'!G60-G21 -> 0 | H24: ='Revenue'!H60-H21 -> 0 | I24: ='Revenue'!I60-I21 -> 0 | J24: ='Revenue'!J60-J21 -> 0 | ... AL24: ='Revenue'!AL60-AL21 -> 0 | AN24: =SUM(C24:E24) -> 0 | AO24: =SUM(F24:H24) -> 0 | AP24: =SUM(I24:K24) -> 0 | AQ24: =SUM(L24:N24) -> 0 | AR24: =SUM(O24:Q24) -> 0 | AS24: =SUM(R24:T24) -> 0 | AT24: =SUM(U24:W24) -> 0 | AU24: =SUM(X24:Z24) -> 0 | AV24: =SUM(AA24:AC24) -> 0 | AW24: =SUM(AD24:AF24) -> 0 | AX24: =SUM(AG24:AI24) -> 0 | AY24: =SUM(AJ24:AL24) -> 0 | BA24: =SUM(C24:N24) -> 0 | BB24: =SUM(O24:Z24) -> 0 | BC24: =SUM(AA24:AL24) -> 0
A25: Gross Margin % | C25: =IFERROR(C24/'Revenue'!C60,0) -> 0 | D25: =IFERROR(D24/'Revenue'!D60,0) -> 0 | E25: =IFERROR(E24/'Revenue'!E60,0) -> 0 | F25: =IFERROR(F24/'Revenue'!F60,0) -> 0 | G25: =IFERROR(G24/'Revenue'!G60,0) -> 0 | H25: =IFERROR(H24/'Revenue'!H60,0) -> 0 | I25: =IFERROR(I24/'Revenue'!I60,0) -> 0 | J25: =IFERROR(J24/'Revenue'!J60,0) -> 0 | ... AL25: =IFERROR(AL24/'Revenue'!AL60,0) -> 0 | AN25: =AVERAGE(C25:E25) -> 0 | AO25: =AVERAGE(F25:H25) -> 0 | AP25: =AVERAGE(I25:K25) -> 0 | AQ25: =AVERAGE(L25:N25) -> 0 | AR25: =AVERAGE(O25:Q25) -> 0 | AS25: =AVERAGE(R25:T25) -> 0 | AT25: =AVERAGE(U25:W25) -> 0 | AU25: =AVERAGE(X25:Z25) -> 0 | AV25: =AVERAGE(AA25:AC25) -> 0 | AW25: =AVERAGE(AD25:AF25) -> 0 | AX25: =AVERAGE(AG25:AI25) -> 0 | AY25: =AVERAGE(AJ25:AL25) -> 0 | BA25: =AVERAGE(C25:N25) -> 0 | BB25: =AVERAGE(O25:Z25) -> 0 | BC25: =AVERAGE(AA25:AL25) -> 0
A26: COGS per billable 1M requests | C26: =IFERROR(C21/C9,0) -> 0 | D26: =IFERROR(D21/D9,0) -> 0 | E26: =IFERROR(E21/E9,0) -> 0 | F26: =IFERROR(F21/F9,0) -> 0 | G26: =IFERROR(G21/G9,0) -> 0 | H26: =IFERROR(H21/H9,0) -> 0 | I26: =IFERROR(I21/I9,0) -> 0 | J26: =IFERROR(J21/J9,0) -> 0 | ... AL26: =IFERROR(AL21/AL9,0) -> 0 | AN26: =AVERAGE(C26:E26) -> 0 | AO26: =AVERAGE(F26:H26) -> 0 | AP26: =AVERAGE(I26:K26) -> 0 | AQ26: =AVERAGE(L26:N26) -> 0 | AR26: =AVERAGE(O26:Q26) -> 0 | AS26: =AVERAGE(R26:T26) -> 0 | AT26: =AVERAGE(U26:W26) -> 0 | AU26: =AVERAGE(X26:Z26) -> 0 | AV26: =AVERAGE(AA26:AC26) -> 0 | AW26: =AVERAGE(AD26:AF26) -> 0 | AX26: =AVERAGE(AG26:AI26) -> 0 | AY26: =AVERAGE(AJ26:AL26) -> 0 | BA26: =AVERAGE(C26:N26) -> 0 | BB26: =AVERAGE(O26:Z26) -> 0 | BC26: =AVERAGE(AA26:AL26) -> 0
A27: Inference margin % | B27: Usage revenue less compute + provider cost, as % of usage revenue | C27: =IFERROR(('Revenue'!C57-(C16+C17))/'Revenue'!C57,0) -> 0 | D27: =IFERROR(('Revenue'!D57-(D16+D17))/'Revenue'!D57,0) -> 0 | E27: =IFERROR(('Revenue'!E57-(E16+E17))/'Revenue'!E57,0) -> 0 | F27: =IFERROR(('Revenue'!F57-(F16+F17))/'Revenue'!F57,0) -> 0 | G27: =IFERROR(('Revenue'!G57-(G16+G17))/'Revenue'!G57,0) -> 0 | H27: =IFERROR(('Revenue'!H57-(H16+H17))/'Revenue'!H57,0) -> 0 | I27: =IFERROR(('Revenue'!I57-(I16+I17))/'Revenue'!I57,0) -> 0 | J27: =IFERROR(('Revenue'!J57-(J16+J17))/'Revenue'!J57,0) -> 0 | ... AL27: =IFERROR(('Revenue'!AL57-(AL16+AL17))/'Revenue'!AL57,0) -> 0 | AN27: =AVERAGE(C27:E27) -> 0 | AO27: =AVERAGE(F27:H27) -> 0 | AP27: =AVERAGE(I27:K27) -> 0 | AQ27: =AVERAGE(L27:N27) -> 0 | AR27: =AVERAGE(O27:Q27) -> 0 | AS27: =AVERAGE(R27:T27) -> 0 | AT27: =AVERAGE(U27:W27) -> 0 | AU27: =AVERAGE(X27:Z27) -> 0 | AV27: =AVERAGE(AA27:AC27) -> 0 | AW27: =AVERAGE(AD27:AF27) -> 0 | AX27: =AVERAGE(AG27:AI27) -> 0 | AY27: =AVERAGE(AJ27:AL27) -> 0 | BA27: =AVERAGE(C27:N27) -> 0 | BB27: =AVERAGE(O27:Z27) -> 0 | BC27: =AVERAGE(AA27:AL27) -> 0
A28: Reserved-capacity utilization | C28: ='COGS & GM'!$C$11 -> 0 | D28: ='COGS & GM'!$D$11 -> 0 | E28: ='COGS & GM'!$E$11 -> 0 | F28: ='COGS & GM'!$F$11 -> 0 | G28: ='COGS & GM'!$G$11 -> 0 | H28: ='COGS & GM'!$H$11 -> 0 | I28: ='COGS & GM'!$I$11 -> 0 | J28: ='COGS & GM'!$J$11 -> 0 | K28: ='COGS & GM'!$K$11 -> 0 | L28: ='COGS & GM'!$L$11 -> 0 | M28: ='COGS & GM'!$M$11 -> 0 | N28: ='COGS & GM'!$N$11 -> 0 | O28: ='COGS & GM'!$O$11 -> 0 | P28: ='COGS & GM'!$P$11 -> 0 | Q28: ='COGS & GM'!$Q$11 -> 0 | R28: ='COGS & GM'!$R$11 -> 0 | S28: ='COGS & GM'!$S$11 -> 0 | T28: ='COGS & GM'!$T$11 -> 0 | U28: ='COGS & GM'!$U$11 -> 0 | V28: ='COGS & GM'!$V$11 -> 0 | W28: ='COGS & GM'!$W$11 -> 0 | X28: ='COGS & GM'!$X$11 -> 0 | Y28: ='COGS & GM'!$Y$11 -> 0 | Z28: ='COGS & GM'!$Z$11 -> 0 | AA28: ='COGS & GM'!$AA$11 -> 0 | AB28: ='COGS & GM'!$AB$11 -> 0 | AC28: ='COGS & GM'!$AC$11 -> 0 | AD28: ='COGS & GM'!$AD$11 -> 0 | AE28: ='COGS & GM'!$AE$11 -> 0 | AF28: ='COGS & GM'!$AF$11 -> 0 | AG28: ='COGS & GM'!$AG$11 -> 0 | AH28: ='COGS & GM'!$AH$11 -> 0 | AI28: ='COGS & GM'!$AI$11 -> 0 | AJ28: ='COGS & GM'!$AJ$11 -> 0 | AK28: ='COGS & GM'!$AK$11 -> 0 | AL28: ='COGS & GM'!$AL$11 -> 0 | AN28: =AVERAGE(C28:E28) -> 0 | AO28: =AVERAGE(F28:H28) -> 0 | AP28: =AVERAGE(I28:K28) -> 0 | AQ28: =AVERAGE(L28:N28) -> 0 | AR28: =AVERAGE(O28:Q28) -> 0 | AS28: =AVERAGE(R28:T28) -> 0 | AT28: =AVERAGE(U28:W28) -> 0 | AU28: =AVERAGE(X28:Z28) -> 0 | AV28: =AVERAGE(AA28:AC28) -> 0 | AW28: =AVERAGE(AD28:AF28) -> 0 | AX28: =AVERAGE(AG28:AI28) -> 0 | AY28: =AVERAGE(AJ28:AL28) -> 0 | BA28: =AVERAGE(C28:N28) -> 0 | BB28: =AVERAGE(O28:Z28) -> 0 | BC28: =AVERAGE(AA28:AL28) -> 0
A29: Enterprise revenue concentration | C29: ='Revenue'!C65 -> 0 | D29: ='Revenue'!D65 -> 0 | E29: ='Revenue'!E65 -> 0 | F29: ='Revenue'!F65 -> 0 | G29: ='Revenue'!G65 -> 0 | H29: ='Revenue'!H65 -> 0 | I29: ='Revenue'!I65 -> 0 | J29: ='Revenue'!J65 -> 0 | ... AL29: ='Revenue'!AL65 -> 0 | AN29: =AVERAGE(C29:E29) -> 0 | AO29: =AVERAGE(F29:H29) -> 0 | AP29: =AVERAGE(I29:K29) -> 0 | AQ29: =AVERAGE(L29:N29) -> 0 | AR29: =AVERAGE(O29:Q29) -> 0 | AS29: =AVERAGE(R29:T29) -> 0 | AT29: =AVERAGE(U29:W29) -> 0 | AU29: =AVERAGE(X29:Z29) -> 0 | AV29: =AVERAGE(AA29:AC29) -> 0 | AW29: =AVERAGE(AD29:AF29) -> 0 | AX29: =AVERAGE(AG29:AI29) -> 0 | AY29: =AVERAGE(AJ29:AL29) -> 0 | BA29: =AVERAGE(C29:N29) -> 0 | BB29: =AVERAGE(O29:Z29) -> 0 | BC29: =AVERAGE(AA29:AL29) -> 0
A30: Burn multiple | B30: Monthly net burn ÷ new-customer revenue added | C30: =IFERROR(INDEX('Cash & Runway'!$C:$AL,MATCH("Monthly Net Burn",'Cash & Runway'!$A:$A,0),1)/MAX(1,'Revenue'!C59),999) -> 0 | D30: =IFERROR(INDEX('Cash & Runway'!$C:$AL,MATCH("Monthly Net Burn",'Cash & Runway'!$A:$A,0),2)/MAX(1,'Revenue'!D59),999) -> 0 | E30: =IFERROR(INDEX('Cash & Runway'!$C:$AL,MATCH("Monthly Net Burn",'Cash & Runway'!$A:$A,0),3)/MAX(1,'Revenue'!E59),999) -> 0 | F30: =IFERROR(INDEX('Cash & Runway'!$C:$AL,MATCH("Monthly Net Burn",'Cash & Runway'!$A:$A,0),4)/MAX(1,'Revenue'!F59),999) -> 0 | G30: =IFERROR(INDEX('Cash & Runway'!$C:$AL,MATCH("Monthly Net Burn",'Cash & Runway'!$A:$A,0),5)/MAX(1,'Revenue'!G59),999) -> 0 | H30: =IFERROR(INDEX('Cash & Runway'!$C:$AL,MATCH("Monthly Net Burn",'Cash & Runway'!$A:$A,0),6)/MAX(1,'Revenue'!H59),999) -> 0 | I30: =IFERROR(INDEX('Cash & Runway'!$C:$AL,MATCH("Monthly Net Burn",'Cash & Runway'!$A:$A,0),7)/MAX(1,'Revenue'!I59),999) -> 0 | J30: =IFERROR(INDEX('Cash & Runway'!$C:$AL,MATCH("Monthly Net Burn",'Cash & Runway'!$A:$A,0),8)/MAX(1,'Revenue'!J59),999) -> 0 | K30: =IFERROR(INDEX('Cash & Runway'!$C:$AL,MATCH("Monthly Net Burn",'Cash & Runway'!$A:$A,0),9)/MAX(1,'Revenue'!K59),999) -> 0 | L30: =IFERROR(INDEX('Cash & Runway'!$C:$AL,MATCH("Monthly Net Burn",'Cash & Runway'!$A:$A,0),10)/MAX(1,'Revenue'!L59),999) -> 0 | M30: =IFERROR(INDEX('Cash & Runway'!$C:$AL,MATCH("Monthly Net Burn",'Cash & Runway'!$A:$A,0),11)/MAX(1,'Revenue'!M59),999) -> 0 | N30: =IFERROR(INDEX('Cash & Runway'!$C:$AL,MATCH("Monthly Net Burn",'Cash & Runway'!$A:$A,0),12)/MAX(1,'Revenue'!N59),999) -> 0 | O30: =IFERROR(INDEX('Cash & Runway'!$C:$AL,MATCH("Monthly Net Burn",'Cash & Runway'!$A:$A,0),13)/MAX(1,'Revenue'!O59),999) -> 0 | P30: =IFERROR(INDEX('Cash & Runway'!$C:$AL,MATCH("Monthly Net Burn",'Cash & Runway'!$A:$A,0),14)/MAX(1,'Revenue'!P59),999) -> 0 | Q30: =IFERROR(INDEX('Cash & Runway'!$C:$AL,MATCH("Monthly Net Burn",'Cash & Runway'!$A:$A,0),15)/MAX(1,'Revenue'!Q59),999) -> 0 | R30: =IFERROR(INDEX('Cash & Runway'!$C:$AL,MATCH("Monthly Net Burn",'Cash & Runway'!$A:$A,0),16)/MAX(1,'Revenue'!R59),999) -> 0 | S30: =IFERROR(INDEX('Cash & Runway'!$C:$AL,MATCH("Monthly Net Burn",'Cash & Runway'!$A:$A,0),17)/MAX(1,'Revenue'!S59),999) -> 0 | T30: =IFERROR(INDEX('Cash & Runway'!$C:$AL,MATCH("Monthly Net Burn",'Cash & Runway'!$A:$A,0),18)/MAX(1,'Revenue'!T59),999) -> 0 | U30: =IFERROR(INDEX('Cash & Runway'!$C:$AL,MATCH("Monthly Net Burn",'Cash & Runway'!$A:$A,0),19)/MAX(1,'Revenue'!U59),999) -> 0 | V30: =IFERROR(INDEX('Cash & Runway'!$C:$AL,MATCH("Monthly Net Burn",'Cash & Runway'!$A:$A,0),20)/MAX(1,'Revenue'!V59),999) -> 0 | W30: =IFERROR(INDEX('Cash & Runway'!$C:$AL,MATCH("Monthly Net Burn",'Cash & Runway'!$A:$A,0),21)/MAX(1,'Revenue'!W59),999) -> 0 | X30: =IFERROR(INDEX('Cash & Runway'!$C:$AL,MATCH("Monthly Net Burn",'Cash & Runway'!$A:$A,0),22)/MAX(1,'Revenue'!X59),999) -> 0 | Y30: =IFERROR(INDEX('Cash & Runway'!$C:$AL,MATCH("Monthly Net Burn",'Cash & Runway'!$A:$A,0),23)/MAX(1,'Revenue'!Y59),999) -> 0 | Z30: =IFERROR(INDEX('Cash & Runway'!$C:$AL,MATCH("Monthly Net Burn",'Cash & Runway'!$A:$A,0),24)/MAX(1,'Revenue'!Z59),999) -> 0 | AA30: =IFERROR(INDEX('Cash & Runway'!$C:$AL,MATCH("Monthly Net Burn",'Cash & Runway'!$A:$A,0),25)/MAX(1,'Revenue'!AA59),999) -> 0 | AB30: =IFERROR(INDEX('Cash & Runway'!$C:$AL,MATCH("Monthly Net Burn",'Cash & Runway'!$A:$A,0),26)/MAX(1,'Revenue'!AB59),999) -> 0 | AC30: =IFERROR(INDEX('Cash & Runway'!$C:$AL,MATCH("Monthly Net Burn",'Cash & Runway'!$A:$A,0),27)/MAX(1,'Revenue'!AC59),999) -> 0 | AD30: =IFERROR(INDEX('Cash & Runway'!$C:$AL,MATCH("Monthly Net Burn",'Cash & Runway'!$A:$A,0),28)/MAX(1,'Revenue'!AD59),999) -> 0 | AE30: =IFERROR(INDEX('Cash & Runway'!$C:$AL,MATCH("Monthly Net Burn",'Cash & Runway'!$A:$A,0),29)/MAX(1,'Revenue'!AE59),999) -> 0 | AF30: =IFERROR(INDEX('Cash & Runway'!$C:$AL,MATCH("Monthly Net Burn",'Cash & Runway'!$A:$A,0),30)/MAX(1,'Revenue'!AF59),999) -> 0 | AG30: =IFERROR(INDEX('Cash & Runway'!$C:$AL,MATCH("Monthly Net Burn",'Cash & Runway'!$A:$A,0),31)/MAX(1,'Revenue'!AG59),999) -> 0 | AH30: =IFERROR(INDEX('Cash & Runway'!$C:$AL,MATCH("Monthly Net Burn",'Cash & Runway'!$A:$A,0),32)/MAX(1,'Revenue'!AH59),999) -> 0 | AI30: =IFERROR(INDEX('Cash & Runway'!$C:$AL,MATCH("Monthly Net Burn",'Cash & Runway'!$A:$A,0),33)/MAX(1,'Revenue'!AI59),999) -> 0 | AJ30: =IFERROR(INDEX('Cash & Runway'!$C:$AL,MATCH("Monthly Net Burn",'Cash & Runway'!$A:$A,0),34)/MAX(1,'Revenue'!AJ59),999) -> 0 | AK30: =IFERROR(INDEX('Cash & Runway'!$C:$AL,MATCH("Monthly Net Burn",'Cash & Runway'!$A:$A,0),35)/MAX(1,'Revenue'!AK59),999) -> 0 | AL30: =IFERROR(INDEX('Cash & Runway'!$C:$AL,MATCH("Monthly Net Burn",'Cash & Runway'!$A:$A,0),36)/MAX(1,'Revenue'!AL59),999) -> 0 | AN30: =AVERAGE(C30:E30) -> 0 | AO30: =AVERAGE(F30:H30) -> 0 | AP30: =AVERAGE(I30:K30) -> 0 | AQ30: =AVERAGE(L30:N30) -> 0 | AR30: =AVERAGE(O30:Q30) -> 0 | AS30: =AVERAGE(R30:T30) -> 0 | AT30: =AVERAGE(U30:W30) -> 0 | AU30: =AVERAGE(X30:Z30) -> 0 | AV30: =AVERAGE(AA30:AC30) -> 0 | AW30: =AVERAGE(AD30:AF30) -> 0 | AX30: =AVERAGE(AG30:AI30) -> 0 | AY30: =AVERAGE(AJ30:AL30) -> 0 | BA30: =AVERAGE(C30:N30) -> 0 | BB30: =AVERAGE(O30:Z30) -> 0 | BC30: =AVERAGE(AA30:AL30) -> 0
A31: Runway (months) | C31: =INDEX('Cash & Runway'!$C:$AL,MATCH("Runway (months)",'Cash & Runway'!$A:$A,0),1) -> 0 | D31: =INDEX('Cash & Runway'!$C:$AL,MATCH("Runway (months)",'Cash & Runway'!$A:$A,0),2) -> 0 | E31: =INDEX('Cash & Runway'!$C:$AL,MATCH("Runway (months)",'Cash & Runway'!$A:$A,0),3) -> 0 | F31: =INDEX('Cash & Runway'!$C:$AL,MATCH("Runway (months)",'Cash & Runway'!$A:$A,0),4) -> 0 | G31: =INDEX('Cash & Runway'!$C:$AL,MATCH("Runway (months)",'Cash & Runway'!$A:$A,0),5) -> 0 | H31: =INDEX('Cash & Runway'!$C:$AL,MATCH("Runway (months)",'Cash & Runway'!$A:$A,0),6) -> 0 | I31: =INDEX('Cash & Runway'!$C:$AL,MATCH("Runway (months)",'Cash & Runway'!$A:$A,0),7) -> 0 | J31: =INDEX('Cash & Runway'!$C:$AL,MATCH("Runway (months)",'Cash & Runway'!$A:$A,0),8) -> 0 | K31: =INDEX('Cash & Runway'!$C:$AL,MATCH("Runway (months)",'Cash & Runway'!$A:$A,0),9) -> 0 | L31: =INDEX('Cash & Runway'!$C:$AL,MATCH("Runway (months)",'Cash & Runway'!$A:$A,0),10) -> 0 | M31: =INDEX('Cash & Runway'!$C:$AL,MATCH("Runway (months)",'Cash & Runway'!$A:$A,0),11) -> 0 | N31: =INDEX('Cash & Runway'!$C:$AL,MATCH("Runway (months)",'Cash & Runway'!$A:$A,0),12) -> 0 | O31: =INDEX('Cash & Runway'!$C:$AL,MATCH("Runway (months)",'Cash & Runway'!$A:$A,0),13) -> 0 | P31: =INDEX('Cash & Runway'!$C:$AL,MATCH("Runway (months)",'Cash & Runway'!$A:$A,0),14) -> 0 | Q31: =INDEX('Cash & Runway'!$C:$AL,MATCH("Runway (months)",'Cash & Runway'!$A:$A,0),15) -> 0 | R31: =INDEX('Cash & Runway'!$C:$AL,MATCH("Runway (months)",'Cash & Runway'!$A:$A,0),16) -> 0 | S31: =INDEX('Cash & Runway'!$C:$AL,MATCH("Runway (months)",'Cash & Runway'!$A:$A,0),17) -> 0 | T31: =INDEX('Cash & Runway'!$C:$AL,MATCH("Runway (months)",'Cash & Runway'!$A:$A,0),18) -> 0 | U31: =INDEX('Cash & Runway'!$C:$AL,MATCH("Runway (months)",'Cash & Runway'!$A:$A,0),19) -> 0 | V31: =INDEX('Cash & Runway'!$C:$AL,MATCH("Runway (months)",'Cash & Runway'!$A:$A,0),20) -> 0 | W31: =INDEX('Cash & Runway'!$C:$AL,MATCH("Runway (months)",'Cash & Runway'!$A:$A,0),21) -> 0 | X31: =INDEX('Cash & Runway'!$C:$AL,MATCH("Runway (months)",'Cash & Runway'!$A:$A,0),22) -> 0 | Y31: =INDEX('Cash & Runway'!$C:$AL,MATCH("Runway (months)",'Cash & Runway'!$A:$A,0),23) -> 0 | Z31: =INDEX('Cash & Runway'!$C:$AL,MATCH("Runway (months)",'Cash & Runway'!$A:$A,0),24) -> 0 | AA31: =INDEX('Cash & Runway'!$C:$AL,MATCH("Runway (months)",'Cash & Runway'!$A:$A,0),25) -> 0 | AB31: =INDEX('Cash & Runway'!$C:$AL,MATCH("Runway (months)",'Cash & Runway'!$A:$A,0),26) -> 0 | AC31: =INDEX('Cash & Runway'!$C:$AL,MATCH("Runway (months)",'Cash & Runway'!$A:$A,0),27) -> 0 | AD31: =INDEX('Cash & Runway'!$C:$AL,MATCH("Runway (months)",'Cash & Runway'!$A:$A,0),28) -> 0 | AE31: =INDEX('Cash & Runway'!$C:$AL,MATCH("Runway (months)",'Cash & Runway'!$A:$A,0),29) -> 0 | AF31: =INDEX('Cash & Runway'!$C:$AL,MATCH("Runway (months)",'Cash & Runway'!$A:$A,0),30) -> 0 | AG31: =INDEX('Cash & Runway'!$C:$AL,MATCH("Runway (months)",'Cash & Runway'!$A:$A,0),31) -> 0 | AH31: =INDEX('Cash & Runway'!$C:$AL,MATCH("Runway (months)",'Cash & Runway'!$A:$A,0),32) -> 0 | AI31: =INDEX('Cash & Runway'!$C:$AL,MATCH("Runway (months)",'Cash & Runway'!$A:$A,0),33) -> 0 | AJ31: =INDEX('Cash & Runway'!$C:$AL,MATCH("Runway (months)",'Cash & Runway'!$A:$A,0),34) -> 0 | AK31: =INDEX('Cash & Runway'!$C:$AL,MATCH("Runway (months)",'Cash & Runway'!$A:$A,0),35) -> 0 | AL31: =INDEX('Cash & Runway'!$C:$AL,MATCH("Runway (months)",'Cash & Runway'!$A:$A,0),36) -> 0 | AN31: =E31 -> 0 | AO31: =H31 -> 0 | AP31: =K31 -> 0 | AQ31: =N31 -> 0 | AR31: =Q31 -> 0 | AS31: =T31 -> 0 | AT31: =W31 -> 0 | AU31: =Z31 -> 0 | AV31: =AC31 -> 0 | AW31: =AF31 -> 0 | AX31: =AI31 -> 0 | AY31: =AL31 -> 0 | BA31: =N31 -> 0 | BB31: =Z31 -> 0 | BC31: =AL31 -> 0

Sheet Opex
A1: AI API / Infrastructure — 3-Year Financial Model — Opex
A2: Operating expenses by department — headcount cost plus program spend.
A5: Line item | B5: Units / source | C5: Monthly (36 months) | AN5: Quarterly | BA5: Annual
C6: 46023 | D6: 46054 | E6: 46082 | F6: 46113 | G6: 46143 | H6: 46174 | I6: 46204 | J6: 46235 | K6: 46266 | L6: 46296 | M6: 46327 | N6: 46357 | O6: 46388 | P6: 46419 | Q6: 46447 | R6: 46478 | S6: 46508 | T6: 46539 | U6: 46569 | V6: 46600 | W6: 46631 | X6: 46661 | Y6: 46692 | Z6: 46722 | AA6: 46753 | AB6: 46784 | AC6: 46813 | AD6: 46844 | AE6: 46874 | AF6: 46905 | AG6: 46935 | AH6: 46966 | AI6: 46997 | AJ6: 47027 | AK6: 47058 | AL6: 47088 | AN6: Q1 | AO6: Q2 | AP6: Q3 | AQ6: Q4 | AR6: Q5 | AS6: Q6 | AT6: Q7 | AU6: Q8 | AV6: Q9 | AW6: Q10 | AX6: Q11 | AY6: Q12 | BA6: FY1 | BB6: FY2 | BC6: FY3
A7: Sales & Marketing
A8: Sales & Marketing — people cost | B8: Linked from Headcount tab | C8: ='Headcount'!$C$25 -> 0 | D8: ='Headcount'!$D$25 -> 0 | E8: ='Headcount'!$E$25 -> 0 | F8: ='Headcount'!$F$25 -> 0 | G8: ='Headcount'!$G$25 -> 0 | H8: ='Headcount'!$H$25 -> 0 | I8: ='Headcount'!$I$25 -> 0 | J8: ='Headcount'!$J$25 -> 0 | K8: ='Headcount'!$K$25 -> 0 | L8: ='Headcount'!$L$25 -> 0 | M8: ='Headcount'!$M$25 -> 0 | N8: ='Headcount'!$N$25 -> 0 | O8: ='Headcount'!$O$25 -> 0 | P8: ='Headcount'!$P$25 -> 0 | Q8: ='Headcount'!$Q$25 -> 0 | R8: ='Headcount'!$R$25 -> 0 | S8: ='Headcount'!$S$25 -> 0 | T8: ='Headcount'!$T$25 -> 0 | U8: ='Headcount'!$U$25 -> 0 | V8: ='Headcount'!$V$25 -> 0 | W8: ='Headcount'!$W$25 -> 0 | X8: ='Headcount'!$X$25 -> 0 | Y8: ='Headcount'!$Y$25 -> 0 | Z8: ='Headcount'!$Z$25 -> 0 | AA8: ='Headcount'!$AA$25 -> 0 | AB8: ='Headcount'!$AB$25 -> 0 | AC8: ='Headcount'!$AC$25 -> 0 | AD8: ='Headcount'!$AD$25 -> 0 | AE8: ='Headcount'!$AE$25 -> 0 | AF8: ='Headcount'!$AF$25 -> 0 | AG8: ='Headcount'!$AG$25 -> 0 | AH8: ='Headcount'!$AH$25 -> 0 | AI8: ='Headcount'!$AI$25 -> 0 | AJ8: ='Headcount'!$AJ$25 -> 0 | AK8: ='Headcount'!$AK$25 -> 0 | AL8: ='Headcount'!$AL$25 -> 0 | AN8: =SUM(C8:E8) -> 0 | AO8: =SUM(F8:H8) -> 0 | AP8: =SUM(I8:K8) -> 0 | AQ8: =SUM(L8:N8) -> 0 | AR8: =SUM(O8:Q8) -> 0 | AS8: =SUM(R8:T8) -> 0 | AT8: =SUM(U8:W8) -> 0 | AU8: =SUM(X8:Z8) -> 0 | AV8: =SUM(AA8:AC8) -> 0 | AW8: =SUM(AD8:AF8) -> 0 | AX8: =SUM(AG8:AI8) -> 0 | AY8: =SUM(AJ8:AL8) -> 0 | BA8: =SUM(C8:N8) -> 0 | BB8: =SUM(O8:Z8) -> 0 | BC8: =SUM(AA8:AL8) -> 0
A9: Sales Commissions | B9: % of new-customer revenue added | C9: ='Revenue'!C59*'Assumptions'!$F$80 -> 0 | D9: ='Revenue'!D59*'Assumptions'!$F$80 -> 0 | E9: ='Revenue'!E59*'Assumptions'!$F$80 -> 0 | F9: ='Revenue'!F59*'Assumptions'!$F$80 -> 0 | G9: ='Revenue'!G59*'Assumptions'!$F$80 -> 0 | H9: ='Revenue'!H59*'Assumptions'!$F$80 -> 0 | I9: ='Revenue'!I59*'Assumptions'!$F$80 -> 0 | J9: ='Revenue'!J59*'Assumptions'!$F$80 -> 0 | ... AL9: ='Revenue'!AL59*'Assumptions'!$F$80 -> 0 | AN9: =SUM(C9:E9) -> 0 | AO9: =SUM(F9:H9) -> 0 | AP9: =SUM(I9:K9) -> 0 | AQ9: =SUM(L9:N9) -> 0 | AR9: =SUM(O9:Q9) -> 0 | AS9: =SUM(R9:T9) -> 0 | AT9: =SUM(U9:W9) -> 0 | AU9: =SUM(X9:Z9) -> 0 | AV9: =SUM(AA9:AC9) -> 0 | AW9: =SUM(AD9:AF9) -> 0 | AX9: =SUM(AG9:AI9) -> 0 | AY9: =SUM(AJ9:AL9) -> 0 | BA9: =SUM(C9:N9) -> 0 | BB9: =SUM(O9:Z9) -> 0 | BC9: =SUM(AA9:AL9) -> 0
A10: Partner / Marketplace Fees | B10: % of usage revenue | C10: ='Revenue'!C57*'Assumptions'!$F$81 -> 0 | D10: ='Revenue'!D57*'Assumptions'!$F$81 -> 0 | E10: ='Revenue'!E57*'Assumptions'!$F$81 -> 0 | F10: ='Revenue'!F57*'Assumptions'!$F$81 -> 0 | G10: ='Revenue'!G57*'Assumptions'!$F$81 -> 0 | H10: ='Revenue'!H57*'Assumptions'!$F$81 -> 0 | I10: ='Revenue'!I57*'Assumptions'!$F$81 -> 0 | J10: ='Revenue'!J57*'Assumptions'!$F$81 -> 0 | ... AL10: ='Revenue'!AL57*'Assumptions'!$F$81 -> 0 | AN10: =SUM(C10:E10) -> 0 | AO10: =SUM(F10:H10) -> 0 | AP10: =SUM(I10:K10) -> 0 | AQ10: =SUM(L10:N10) -> 0 | AR10: =SUM(O10:Q10) -> 0 | AS10: =SUM(R10:T10) -> 0 | AT10: =SUM(U10:W10) -> 0 | AU10: =SUM(X10:Z10) -> 0 | AV10: =SUM(AA10:AC10) -> 0 | AW10: =SUM(AD10:AF10) -> 0 | AX10: =SUM(AG10:AI10) -> 0 | AY10: =SUM(AJ10:AL10) -> 0 | BA10: =SUM(C10:N10) -> 0 | BB10: =SUM(O10:Z10) -> 0 | BC10: =SUM(AA10:AL10) -> 0
A11: Marketing Programs | B11: % of total revenue | C11: ='Revenue'!C60*'Assumptions'!$F$82 -> 0 | D11: ='Revenue'!D60*'Assumptions'!$F$82 -> 0 | E11: ='Revenue'!E60*'Assumptions'!$F$82 -> 0 | F11: ='Revenue'!F60*'Assumptions'!$F$82 -> 0 | G11: ='Revenue'!G60*'Assumptions'!$F$82 -> 0 | H11: ='Revenue'!H60*'Assumptions'!$F$82 -> 0 | I11: ='Revenue'!I60*'Assumptions'!$F$82 -> 0 | J11: ='Revenue'!J60*'Assumptions'!$F$82 -> 0 | ... AL11: ='Revenue'!AL60*'Assumptions'!$F$82 -> 0 | AN11: =SUM(C11:E11) -> 0 | AO11: =SUM(F11:H11) -> 0 | AP11: =SUM(I11:K11) -> 0 | AQ11: =SUM(L11:N11) -> 0 | AR11: =SUM(O11:Q11) -> 0 | AS11: =SUM(R11:T11) -> 0 | AT11: =SUM(U11:W11) -> 0 | AU11: =SUM(X11:Z11) -> 0 | AV11: =SUM(AA11:AC11) -> 0 | AW11: =SUM(AD11:AF11) -> 0 | AX11: =SUM(AG11:AI11) -> 0 | AY11: =SUM(AJ11:AL11) -> 0 | BA11: =SUM(C11:N11) -> 0 | BB11: =SUM(O11:Z11) -> 0 | BC11: =SUM(AA11:AL11) -> 0
A12: Total Sales & Marketing | C12: =C8+C9+C10+C11 -> 0 | D12: =D8+D9+D10+D11 -> 0 | E12: =E8+E9+E10+E11 -> 0 | F12: =F8+F9+F10+F11 -> 0 | G12: =G8+G9+G10+G11 -> 0 | H12: =H8+H9+H10+H11 -> 0 | I12: =I8+I9+I10+I11 -> 0 | J12: =J8+J9+J10+J11 -> 0 | ... AL12: =AL8+AL9+AL10+AL11 -> 0 | AN12: =SUM(C12:E12) -> 0 | AO12: =SUM(F12:H12) -> 0 | AP12: =SUM(I12:K12) -> 0 | AQ12: =SUM(L12:N12) -> 0 | AR12: =SUM(O12:Q12) -> 0 | AS12: =SUM(R12:T12) -> 0 | AT12: =SUM(U12:W12) -> 0 | AU12: =SUM(X12:Z12) -> 0 | AV12: =SUM(AA12:AC12) -> 0 | AW12: =SUM(AD12:AF12) -> 0 | AX12: =SUM(AG12:AI12) -> 0 | AY12: =SUM(AJ12:AL12) -> 0 | BA12: =SUM(C12:N12) -> 0 | BB12: =SUM(O12:Z12) -> 0 | BC12: =SUM(AA12:AL12) -> 0
A14: R&D / Engineering
A15: R&D / Engineering — people cost | B15: Linked from Headcount tab | C15: ='Headcount'!$C$24 -> 0 | D15: ='Headcount'!$D$24 -> 0 | E15: ='Headcount'!$E$24 -> 0 | F15: ='Headcount'!$F$24 -> 0 | G15: ='Headcount'!$G$24 -> 0 | H15: ='Headcount'!$H$24 -> 0 | I15: ='Headcount'!$I$24 -> 0 | J15: ='Headcount'!$J$24 -> 0 | K15: ='Headcount'!$K$24 -> 0 | L15: ='Headcount'!$L$24 -> 0 | M15: ='Headcount'!$M$24 -> 0 | N15: ='Headcount'!$N$24 -> 0 | O15: ='Headcount'!$O$24 -> 0 | P15: ='Headcount'!$P$24 -> 0 | Q15: ='Headcount'!$Q$24 -> 0 | R15: ='Headcount'!$R$24 -> 0 | S15: ='Headcount'!$S$24 -> 0 | T15: ='Headcount'!$T$24 -> 0 | U15: ='Headcount'!$U$24 -> 0 | V15: ='Headcount'!$V$24 -> 0 | W15: ='Headcount'!$W$24 -> 0 | X15: ='Headcount'!$X$24 -> 0 | Y15: ='Headcount'!$Y$24 -> 0 | Z15: ='Headcount'!$Z$24 -> 0 | AA15: ='Headcount'!$AA$24 -> 0 | AB15: ='Headcount'!$AB$24 -> 0 | AC15: ='Headcount'!$AC$24 -> 0 | AD15: ='Headcount'!$AD$24 -> 0 | AE15: ='Headcount'!$AE$24 -> 0 | AF15: ='Headcount'!$AF$24 -> 0 | AG15: ='Headcount'!$AG$24 -> 0 | AH15: ='Headcount'!$AH$24 -> 0 | AI15: ='Headcount'!$AI$24 -> 0 | AJ15: ='Headcount'!$AJ$24 -> 0 | AK15: ='Headcount'!$AK$24 -> 0 | AL15: ='Headcount'!$AL$24 -> 0 | AN15: =SUM(C15:E15) -> 0 | AO15: =SUM(F15:H15) -> 0 | AP15: =SUM(I15:K15) -> 0 | AQ15: =SUM(L15:N15) -> 0 | AR15: =SUM(O15:Q15) -> 0 | AS15: =SUM(R15:T15) -> 0 | AT15: =SUM(U15:W15) -> 0 | AU15: =SUM(X15:Z15) -> 0 | AV15: =SUM(AA15:AC15) -> 0 | AW15: =SUM(AD15:AF15) -> 0 | AX15: =SUM(AG15:AI15) -> 0 | AY15: =SUM(AJ15:AL15) -> 0 | BA15: =SUM(C15:N15) -> 0 | BB15: =SUM(O15:Z15) -> 0 | BC15: =SUM(AA15:AL15) -> 0
A16: Total R&D / Engineering | C16: =C15 -> 0 | D16: =D15 -> 0 | E16: =E15 -> 0 | F16: =F15 -> 0 | G16: =G15 -> 0 | H16: =H15 -> 0 | I16: =I15 -> 0 | J16: =J15 -> 0 | ... AL16: =AL15 -> 0 | AN16: =SUM(C16:E16) -> 0 | AO16: =SUM(F16:H16) -> 0 | AP16: =SUM(I16:K16) -> 0 | AQ16: =SUM(L16:N16) -> 0 | AR16: =SUM(O16:Q16) -> 0 | AS16: =SUM(R16:T16) -> 0 | AT16: =SUM(U16:W16) -> 0 | AU16: =SUM(X16:Z16) -> 0 | AV16: =SUM(AA16:AC16) -> 0 | AW16: =SUM(AD16:AF16) -> 0 | AX16: =SUM(AG16:AI16) -> 0 | AY16: =SUM(AJ16:AL16) -> 0 | BA16: =SUM(C16:N16) -> 0 | BB16: =SUM(O16:Z16) -> 0 | BC16: =SUM(AA16:AL16) -> 0
A18: General & Administrative
A19: General & Administrative — people cost | B19: Linked from Headcount tab | C19: ='Headcount'!$C$23 -> 0 | D19: ='Headcount'!$D$23 -> 0 | E19: ='Headcount'!$E$23 -> 0 | F19: ='Headcount'!$F$23 -> 0 | G19: ='Headcount'!$G$23 -> 0 | H19: ='Headcount'!$H$23 -> 0 | I19: ='Headcount'!$I$23 -> 0 | J19: ='Headcount'!$J$23 -> 0 | K19: ='Headcount'!$K$23 -> 0 | L19: ='Headcount'!$L$23 -> 0 | M19: ='Headcount'!$M$23 -> 0 | N19: ='Headcount'!$N$23 -> 0 | O19: ='Headcount'!$O$23 -> 0 | P19: ='Headcount'!$P$23 -> 0 | Q19: ='Headcount'!$Q$23 -> 0 | R19: ='Headcount'!$R$23 -> 0 | S19: ='Headcount'!$S$23 -> 0 | T19: ='Headcount'!$T$23 -> 0 | U19: ='Headcount'!$U$23 -> 0 | V19: ='Headcount'!$V$23 -> 0 | W19: ='Headcount'!$W$23 -> 0 | X19: ='Headcount'!$X$23 -> 0 | Y19: ='Headcount'!$Y$23 -> 0 | Z19: ='Headcount'!$Z$23 -> 0 | AA19: ='Headcount'!$AA$23 -> 0 | AB19: ='Headcount'!$AB$23 -> 0 | AC19: ='Headcount'!$AC$23 -> 0 | AD19: ='Headcount'!$AD$23 -> 0 | AE19: ='Headcount'!$AE$23 -> 0 | AF19: ='Headcount'!$AF$23 -> 0 | AG19: ='Headcount'!$AG$23 -> 0 | AH19: ='Headcount'!$AH$23 -> 0 | AI19: ='Headcount'!$AI$23 -> 0 | AJ19: ='Headcount'!$AJ$23 -> 0 | AK19: ='Headcount'!$AK$23 -> 0 | AL19: ='Headcount'!$AL$23 -> 0 | AN19: =SUM(C19:E19) -> 0 | AO19: =SUM(F19:H19) -> 0 | AP19: =SUM(I19:K19) -> 0 | AQ19: =SUM(L19:N19) -> 0 | AR19: =SUM(O19:Q19) -> 0 | AS19: =SUM(R19:T19) -> 0 | AT19: =SUM(U19:W19) -> 0 | AU19: =SUM(X19:Z19) -> 0 | AV19: =SUM(AA19:AC19) -> 0 | AW19: =SUM(AD19:AF19) -> 0 | AX19: =SUM(AG19:AI19) -> 0 | AY19: =SUM(AJ19:AL19) -> 0 | BA19: =SUM(C19:N19) -> 0 | BB19: =SUM(O19:Z19) -> 0 | BC19: =SUM(AA19:AL19) -> 0
A20: Software & Tools | B20: Fixed monthly | C20: ='Assumptions'!$F$83 -> 0 | D20: ='Assumptions'!$F$83 -> 0 | E20: ='Assumptions'!$F$83 -> 0 | F20: ='Assumptions'!$F$83 -> 0 | G20: ='Assumptions'!$F$83 -> 0 | H20: ='Assumptions'!$F$83 -> 0 | I20: ='Assumptions'!$F$83 -> 0 | J20: ='Assumptions'!$F$83 -> 0 | ... AL20: ='Assumptions'!$F$83 -> 0 | AN20: =SUM(C20:E20) -> 0 | AO20: =SUM(F20:H20) -> 0 | AP20: =SUM(I20:K20) -> 0 | AQ20: =SUM(L20:N20) -> 0 | AR20: =SUM(O20:Q20) -> 0 | AS20: =SUM(R20:T20) -> 0 | AT20: =SUM(U20:W20) -> 0 | AU20: =SUM(X20:Z20) -> 0 | AV20: =SUM(AA20:AC20) -> 0 | AW20: =SUM(AD20:AF20) -> 0 | AX20: =SUM(AG20:AI20) -> 0 | AY20: =SUM(AJ20:AL20) -> 0 | BA20: =SUM(C20:N20) -> 0 | BB20: =SUM(O20:Z20) -> 0 | BC20: =SUM(AA20:AL20) -> 0
A21: Facilities & Admin | B21: Fixed monthly | C21: ='Assumptions'!$F$84 -> 0 | D21: ='Assumptions'!$F$84 -> 0 | E21: ='Assumptions'!$F$84 -> 0 | F21: ='Assumptions'!$F$84 -> 0 | G21: ='Assumptions'!$F$84 -> 0 | H21: ='Assumptions'!$F$84 -> 0 | I21: ='Assumptions'!$F$84 -> 0 | J21: ='Assumptions'!$F$84 -> 0 | ... AL21: ='Assumptions'!$F$84 -> 0 | AN21: =SUM(C21:E21) -> 0 | AO21: =SUM(F21:H21) -> 0 | AP21: =SUM(I21:K21) -> 0 | AQ21: =SUM(L21:N21) -> 0 | AR21: =SUM(O21:Q21) -> 0 | AS21: =SUM(R21:T21) -> 0 | AT21: =SUM(U21:W21) -> 0 | AU21: =SUM(X21:Z21) -> 0 | AV21: =SUM(AA21:AC21) -> 0 | AW21: =SUM(AD21:AF21) -> 0 | AX21: =SUM(AG21:AI21) -> 0 | AY21: =SUM(AJ21:AL21) -> 0 | BA21: =SUM(C21:N21) -> 0 | BB21: =SUM(O21:Z21) -> 0 | BC21: =SUM(AA21:AL21) -> 0
A22: Total General & Administrative | C22: =C19+C20+C21 -> 0 | D22: =D19+D20+D21 -> 0 | E22: =E19+E20+E21 -> 0 | F22: =F19+F20+F21 -> 0 | G22: =G19+G20+G21 -> 0 | H22: =H19+H20+H21 -> 0 | I22: =I19+I20+I21 -> 0 | J22: =J19+J20+J21 -> 0 | ... AL22: =AL19+AL20+AL21 -> 0 | AN22: =SUM(C22:E22) -> 0 | AO22: =SUM(F22:H22) -> 0 | AP22: =SUM(I22:K22) -> 0 | AQ22: =SUM(L22:N22) -> 0 | AR22: =SUM(O22:Q22) -> 0 | AS22: =SUM(R22:T22) -> 0 | AT22: =SUM(U22:W22) -> 0 | AU22: =SUM(X22:Z22) -> 0 | AV22: =SUM(AA22:AC22) -> 0 | AW22: =SUM(AD22:AF22) -> 0 | AX22: =SUM(AG22:AI22) -> 0 | AY22: =SUM(AJ22:AL22) -> 0 | BA22: =SUM(C22:N22) -> 0 | BB22: =SUM(O22:Z22) -> 0 | BC22: =SUM(AA22:AL22) -> 0
A24: Total Operating Expenses
A25: Total Opex | C25: =C12+C16+C22 -> 0 | D25: =D12+D16+D22 -> 0 | E25: =E12+E16+E22 -> 0 | F25: =F12+F16+F22 -> 0 | G25: =G12+G16+G22 -> 0 | H25: =H12+H16+H22 -> 0 | I25: =I12+I16+I22 -> 0 | J25: =J12+J16+J22 -> 0 | ... AL25: =AL12+AL16+AL22 -> 0 | AN25: =SUM(C25:E25) -> 0 | AO25: =SUM(F25:H25) -> 0 | AP25: =SUM(I25:K25) -> 0 | AQ25: =SUM(L25:N25) -> 0 | AR25: =SUM(O25:Q25) -> 0 | AS25: =SUM(R25:T25) -> 0 | AT25: =SUM(U25:W25) -> 0 | AU25: =SUM(X25:Z25) -> 0 | AV25: =SUM(AA25:AC25) -> 0 | AW25: =SUM(AD25:AF25) -> 0 | AX25: =SUM(AG25:AI25) -> 0 | AY25: =SUM(AJ25:AL25) -> 0 | BA25: =SUM(C25:N25) -> 0 | BB25: =SUM(O25:Z25) -> 0 | BC25: =SUM(AA25:AL25) -> 0

Sheet Working Capital
A1: AI API / Infrastructure — 3-Year Financial Model — Working Capital
A2: Balance-sheet drivers: receivables, payables, deferred revenue, capex/depreciation, debt & equity financing.
A5: Line item | B5: Units / source | C5: Monthly (36 months) | AN5: Quarterly | BA5: Annual
C6: 46023 | D6: 46054 | E6: 46082 | F6: 46113 | G6: 46143 | H6: 46174 | I6: 46204 | J6: 46235 | K6: 46266 | L6: 46296 | M6: 46327 | N6: 46357 | O6: 46388 | P6: 46419 | Q6: 46447 | R6: 46478 | S6: 46508 | T6: 46539 | U6: 46569 | V6: 46600 | W6: 46631 | X6: 46661 | Y6: 46692 | Z6: 46722 | AA6: 46753 | AB6: 46784 | AC6: 46813 | AD6: 46844 | AE6: 46874 | AF6: 46905 | AG6: 46935 | AH6: 46966 | AI6: 46997 | AJ6: 47027 | AK6: 47058 | AL6: 47088 | AN6: Q1 | AO6: Q2 | AP6: Q3 | AQ6: Q4 | AR6: Q5 | AS6: Q6 | AT6: Q7 | AU6: Q8 | AV6: Q9 | AW6: Q10 | AX6: Q11 | AY6: Q12 | BA6: FY1 | BB6: FY2 | BC6: FY3
A7: Receivables, Payables & Deferred Revenue
A8: Accounts Receivable balance | B8: Revenue × DSO ÷ 30 | C8: ='Revenue'!C60*'Assumptions'!$F$87/30 -> 0 | D8: ='Revenue'!D60*'Assumptions'!$F$87/30 -> 0 | E8: ='Revenue'!E60*'Assumptions'!$F$87/30 -> 0 | F8: ='Revenue'!F60*'Assumptions'!$F$87/30 -> 0 | G8: ='Revenue'!G60*'Assumptions'!$F$87/30 -> 0 | H8: ='Revenue'!H60*'Assumptions'!$F$87/30 -> 0 | I8: ='Revenue'!I60*'Assumptions'!$F$87/30 -> 0 | J8: ='Revenue'!J60*'Assumptions'!$F$87/30 -> 0 | ... AL8: ='Revenue'!AL60*'Assumptions'!$F$87/30 -> 0 | AN8: =E8 -> 0 | AO8: =H8 -> 0 | AP8: =K8 -> 0 | AQ8: =N8 -> 0 | AR8: =Q8 -> 0 | AS8: =T8 -> 0 | AT8: =W8 -> 0 | AU8: =Z8 -> 0 | AV8: =AC8 -> 0 | AW8: =AF8 -> 0 | AX8: =AI8 -> 0 | AY8: =AL8 -> 0 | BA8: =N8 -> 0 | BB8: =Z8 -> 0 | BC8: =AL8 -> 0
A9: Accounts Payable balance | B9: (COGS + Opex) × DPO ÷ 30 | C9: =('COGS & GM'!C21+'Opex'!C25)*'Assumptions'!$F$88/30 -> 0 | D9: =('COGS & GM'!D21+'Opex'!D25)*'Assumptions'!$F$88/30 -> 0 | E9: =('COGS & GM'!E21+'Opex'!E25)*'Assumptions'!$F$88/30 -> 0 | F9: =('COGS & GM'!F21+'Opex'!F25)*'Assumptions'!$F$88/30 -> 0 | G9: =('COGS & GM'!G21+'Opex'!G25)*'Assumptions'!$F$88/30 -> 0 | H9: =('COGS & GM'!H21+'Opex'!H25)*'Assumptions'!$F$88/30 -> 0 | I9: =('COGS & GM'!I21+'Opex'!I25)*'Assumptions'!$F$88/30 -> 0 | J9: =('COGS & GM'!J21+'Opex'!J25)*'Assumptions'!$F$88/30 -> 0 | ... AL9: =('COGS & GM'!AL21+'Opex'!AL25)*'Assumptions'!$F$88/30 -> 0 | AN9: =E9 -> 0 | AO9: =H9 -> 0 | AP9: =K9 -> 0 | AQ9: =N9 -> 0 | AR9: =Q9 -> 0 | AS9: =T9 -> 0 | AT9: =W9 -> 0 | AU9: =Z9 -> 0 | AV9: =AC9 -> 0 | AW9: =AF9 -> 0 | AX9: =AI9 -> 0 | AY9: =AL9 -> 0 | BA9: =N9 -> 0 | BB9: =Z9 -> 0 | BC9: =AL9 -> 0
A10: Deferred Revenue balance | B10: Revenue × months collected in advance | C10: ='Revenue'!C60*'Assumptions'!$F$89 -> 0 | D10: ='Revenue'!D60*'Assumptions'!$F$89 -> 0 | E10: ='Revenue'!E60*'Assumptions'!$F$89 -> 0 | F10: ='Revenue'!F60*'Assumptions'!$F$89 -> 0 | G10: ='Revenue'!G60*'Assumptions'!$F$89 -> 0 | H10: ='Revenue'!H60*'Assumptions'!$F$89 -> 0 | I10: ='Revenue'!I60*'Assumptions'!$F$89 -> 0 | J10: ='Revenue'!J60*'Assumptions'!$F$89 -> 0 | ... AL10: ='Revenue'!AL60*'Assumptions'!$F$89 -> 0 | AN10: =E10 -> 0 | AO10: =H10 -> 0 | AP10: =K10 -> 0 | AQ10: =N10 -> 0 | AR10: =Q10 -> 0 | AS10: =T10 -> 0 | AT10: =W10 -> 0 | AU10: =Z10 -> 0 | AV10: =AC10 -> 0 | AW10: =AF10 -> 0 | AX10: =AI10 -> 0 | AY10: =AL10 -> 0 | BA10: =N10 -> 0 | BB10: =Z10 -> 0 | BC10: =AL10 -> 0
A11: Other Current Assets balance | B11: Revenue × assumption % (prepaid expenses, etc.) | C11: ='Revenue'!C60*'Assumptions'!$F$92 -> 0 | D11: ='Revenue'!D60*'Assumptions'!$F$92 -> 0 | E11: ='Revenue'!E60*'Assumptions'!$F$92 -> 0 | F11: ='Revenue'!F60*'Assumptions'!$F$92 -> 0 | G11: ='Revenue'!G60*'Assumptions'!$F$92 -> 0 | H11: ='Revenue'!H60*'Assumptions'!$F$92 -> 0 | I11: ='Revenue'!I60*'Assumptions'!$F$92 -> 0 | J11: ='Revenue'!J60*'Assumptions'!$F$92 -> 0 | ... AL11: ='Revenue'!AL60*'Assumptions'!$F$92 -> 0 | AN11: =E11 -> 0 | AO11: =H11 -> 0 | AP11: =K11 -> 0 | AQ11: =N11 -> 0 | AR11: =Q11 -> 0 | AS11: =T11 -> 0 | AT11: =W11 -> 0 | AU11: =Z11 -> 0 | AV11: =AC11 -> 0 | AW11: =AF11 -> 0 | AX11: =AI11 -> 0 | AY11: =AL11 -> 0 | BA11: =N11 -> 0 | BB11: =Z11 -> 0 | BC11: =AL11 -> 0
A12: Change in Accounts Receivable | C12: =C8 -> 0 | D12: =D8-C8 -> 0 | E12: =E8-D8 -> 0 | F12: =F8-E8 -> 0 | G12: =G8-F8 -> 0 | H12: =H8-G8 -> 0 | I12: =I8-H8 -> 0 | J12: =J8-I8 -> 0 | K12: =K8-J8 -> 0 | ... AL12: =AL8-AK8 -> 0 | AN12: =SUM(C12:E12) -> 0 | AO12: =SUM(F12:H12) -> 0 | AP12: =SUM(I12:K12) -> 0 | AQ12: =SUM(L12:N12) -> 0 | AR12: =SUM(O12:Q12) -> 0 | AS12: =SUM(R12:T12) -> 0 | AT12: =SUM(U12:W12) -> 0 | AU12: =SUM(X12:Z12) -> 0 | AV12: =SUM(AA12:AC12) -> 0 | AW12: =SUM(AD12:AF12) -> 0 | AX12: =SUM(AG12:AI12) -> 0 | AY12: =SUM(AJ12:AL12) -> 0 | BA12: =SUM(C12:N12) -> 0 | BB12: =SUM(O12:Z12) -> 0 | BC12: =SUM(AA12:AL12) -> 0
A13: Change in Accounts Payable | C13: =C9 -> 0 | D13: =D9-C9 -> 0 | E13: =E9-D9 -> 0 | F13: =F9-E9 -> 0 | G13: =G9-F9 -> 0 | H13: =H9-G9 -> 0 | I13: =I9-H9 -> 0 | J13: =J9-I9 -> 0 | K13: =K9-J9 -> 0 | ... AL13: =AL9-AK9 -> 0 | AN13: =SUM(C13:E13) -> 0 | AO13: =SUM(F13:H13) -> 0 | AP13: =SUM(I13:K13) -> 0 | AQ13: =SUM(L13:N13) -> 0 | AR13: =SUM(O13:Q13) -> 0 | AS13: =SUM(R13:T13) -> 0 | AT13: =SUM(U13:W13) -> 0 | AU13: =SUM(X13:Z13) -> 0 | AV13: =SUM(AA13:AC13) -> 0 | AW13: =SUM(AD13:AF13) -> 0 | AX13: =SUM(AG13:AI13) -> 0 | AY13: =SUM(AJ13:AL13) -> 0 | BA13: =SUM(C13:N13) -> 0 | BB13: =SUM(O13:Z13) -> 0 | BC13: =SUM(AA13:AL13) -> 0
A14: Change in Deferred Revenue | C14: =C10 -> 0 | D14: =D10-C10 -> 0 | E14: =E10-D10 -> 0 | F14: =F10-E10 -> 0 | G14: =G10-F10 -> 0 | H14: =H10-G10 -> 0 | I14: =I10-H10 -> 0 | J14: =J10-I10 -> 0 | K14: =K10-J10 -> 0 | ... AL14: =AL10-AK10 -> 0 | AN14: =SUM(C14:E14) -> 0 | AO14: =SUM(F14:H14) -> 0 | AP14: =SUM(I14:K14) -> 0 | AQ14: =SUM(L14:N14) -> 0 | AR14: =SUM(O14:Q14) -> 0 | AS14: =SUM(R14:T14) -> 0 | AT14: =SUM(U14:W14) -> 0 | AU14: =SUM(X14:Z14) -> 0 | AV14: =SUM(AA14:AC14) -> 0 | AW14: =SUM(AD14:AF14) -> 0 | AX14: =SUM(AG14:AI14) -> 0 | AY14: =SUM(AJ14:AL14) -> 0 | BA14: =SUM(C14:N14) -> 0 | BB14: =SUM(O14:Z14) -> 0 | BC14: =SUM(AA14:AL14) -> 0
A15: Change in Other Current Assets | C15: =C11 -> 0 | D15: =D11-C11 -> 0 | E15: =E11-D11 -> 0 | F15: =F11-E11 -> 0 | G15: =G11-F11 -> 0 | H15: =H11-G11 -> 0 | I15: =I11-H11 -> 0 | J15: =J11-I11 -> 0 | K15: =K11-J11 -> 0 | ... AL15: =AL11-AK11 -> 0 | AN15: =SUM(C15:E15) -> 0 | AO15: =SUM(F15:H15) -> 0 | AP15: =SUM(I15:K15) -> 0 | AQ15: =SUM(L15:N15) -> 0 | AR15: =SUM(O15:Q15) -> 0 | AS15: =SUM(R15:T15) -> 0 | AT15: =SUM(U15:W15) -> 0 | AU15: =SUM(X15:Z15) -> 0 | AV15: =SUM(AA15:AC15) -> 0 | AW15: =SUM(AD15:AF15) -> 0 | AX15: =SUM(AG15:AI15) -> 0 | AY15: =SUM(AJ15:AL15) -> 0 | BA15: =SUM(C15:N15) -> 0 | BB15: =SUM(O15:Z15) -> 0 | BC15: =SUM(AA15:AL15) -> 0
A17: Capex & Depreciation (PP&E)
A18: Capital expenditures | B18: Revenue × capex % of revenue | C18: ='Revenue'!C60*'Assumptions'!$F$90 -> 0 | D18: ='Revenue'!D60*'Assumptions'!$F$90 -> 0 | E18: ='Revenue'!E60*'Assumptions'!$F$90 -> 0 | F18: ='Revenue'!F60*'Assumptions'!$F$90 -> 0 | G18: ='Revenue'!G60*'Assumptions'!$F$90 -> 0 | H18: ='Revenue'!H60*'Assumptions'!$F$90 -> 0 | I18: ='Revenue'!I60*'Assumptions'!$F$90 -> 0 | J18: ='Revenue'!J60*'Assumptions'!$F$90 -> 0 | ... AL18: ='Revenue'!AL60*'Assumptions'!$F$90 -> 0 | AN18: =SUM(C18:E18) -> 0 | AO18: =SUM(F18:H18) -> 0 | AP18: =SUM(I18:K18) -> 0 | AQ18: =SUM(L18:N18) -> 0 | AR18: =SUM(O18:Q18) -> 0 | AS18: =SUM(R18:T18) -> 0 | AT18: =SUM(U18:W18) -> 0 | AU18: =SUM(X18:Z18) -> 0 | AV18: =SUM(AA18:AC18) -> 0 | AW18: =SUM(AD18:AF18) -> 0 | AX18: =SUM(AG18:AI18) -> 0 | AY18: =SUM(AJ18:AL18) -> 0 | BA18: =SUM(C18:N18) -> 0 | BB18: =SUM(O18:Z18) -> 0 | BC18: =SUM(AA18:AL18) -> 0
A19: Depreciation & amortization | B19: Straight-line over useful life; trailing-window formula | C19: =SUM(INDEX('Working Capital'!$C$18:$AL$18,1,MAX(1,1-ROUND('Assumptions'!$F$91,0)+1)):INDEX('Working Capital'!$C$18:$AL$18,1,1))/ROUND('Assumptions'!$F$91,0) -> 0 | D19: =SUM(INDEX('Working Capital'!$C$18:$AL$18,1,MAX(1,2-ROUND('Assumptions'!$F$91,0)+1)):INDEX('Working Capital'!$C$18:$AL$18,1,2))/ROUND('Assumptions'!$F$91,0) -> 0 | E19: =SUM(INDEX('Working Capital'!$C$18:$AL$18,1,MAX(1,3-ROUND('Assumptions'!$F$91,0)+1)):INDEX('Working Capital'!$C$18:$AL$18,1,3))/ROUND('Assumptions'!$F$91,0) -> 0 | F19: =SUM(INDEX('Working Capital'!$C$18:$AL$18,1,MAX(1,4-ROUND('Assumptions'!$F$91,0)+1)):INDEX('Working Capital'!$C$18:$AL$18,1,4))/ROUND('Assumptions'!$F$91,0) -> 0 | G19: =SUM(INDEX('Working Capital'!$C$18:$AL$18,1,MAX(1,5-ROUND('Assumptions'!$F$91,0)+1)):INDEX('Working Capital'!$C$18:$AL$18,1,5))/ROUND('Assumptions'!$F$91,0) -> 0 | H19: =SUM(INDEX('Working Capital'!$C$18:$AL$18,1,MAX(1,6-ROUND('Assumptions'!$F$91,0)+1)):INDEX('Working Capital'!$C$18:$AL$18,1,6))/ROUND('Assumptions'!$F$91,0) -> 0 | I19: =SUM(INDEX('Working Capital'!$C$18:$AL$18,1,MAX(1,7-ROUND('Assumptions'!$F$91,0)+1)):INDEX('Working Capital'!$C$18:$AL$18,1,7))/ROUND('Assumptions'!$F$91,0) -> 0 | J19: =SUM(INDEX('Working Capital'!$C$18:$AL$18,1,MAX(1,8-ROUND('Assumptions'!$F$91,0)+1)):INDEX('Working Capital'!$C$18:$AL$18,1,8))/ROUND('Assumptions'!$F$91,0) -> 0 | K19: =SUM(INDEX('Working Capital'!$C$18:$AL$18,1,MAX(1,9-ROUND('Assumptions'!$F$91,0)+1)):INDEX('Working Capital'!$C$18:$AL$18,1,9))/ROUND('Assumptions'!$F$91,0) -> 0 | L19: =SUM(INDEX('Working Capital'!$C$18:$AL$18,1,MAX(1,10-ROUND('Assumptions'!$F$91,0)+1)):INDEX('Working Capital'!$C$18:$AL$18,1,10))/ROUND('Assumptions'!$F$91,0) -> 0 | M19: =SUM(INDEX('Working Capital'!$C$18:$AL$18,1,MAX(1,11-ROUND('Assumptions'!$F$91,0)+1)):INDEX('Working Capital'!$C$18:$AL$18,1,11))/ROUND('Assumptions'!$F$91,0) -> 0 | N19: =SUM(INDEX('Working Capital'!$C$18:$AL$18,1,MAX(1,12-ROUND('Assumptions'!$F$91,0)+1)):INDEX('Working Capital'!$C$18:$AL$18,1,12))/ROUND('Assumptions'!$F$91,0) -> 0 | O19: =SUM(INDEX('Working Capital'!$C$18:$AL$18,1,MAX(1,13-ROUND('Assumptions'!$F$91,0)+1)):INDEX('Working Capital'!$C$18:$AL$18,1,13))/ROUND('Assumptions'!$F$91,0) -> 0 | P19: =SUM(INDEX('Working Capital'!$C$18:$AL$18,1,MAX(1,14-ROUND('Assumptions'!$F$91,0)+1)):INDEX('Working Capital'!$C$18:$AL$18,1,14))/ROUND('Assumptions'!$F$91,0) -> 0 | Q19: =SUM(INDEX('Working Capital'!$C$18:$AL$18,1,MAX(1,15-ROUND('Assumptions'!$F$91,0)+1)):INDEX('Working Capital'!$C$18:$AL$18,1,15))/ROUND('Assumptions'!$F$91,0) -> 0 | R19: =SUM(INDEX('Working Capital'!$C$18:$AL$18,1,MAX(1,16-ROUND('Assumptions'!$F$91,0)+1)):INDEX('Working Capital'!$C$18:$AL$18,1,16))/ROUND('Assumptions'!$F$91,0) -> 0 | S19: =SUM(INDEX('Working Capital'!$C$18:$AL$18,1,MAX(1,17-ROUND('Assumptions'!$F$91,0)+1)):INDEX('Working Capital'!$C$18:$AL$18,1,17))/ROUND('Assumptions'!$F$91,0) -> 0 | T19: =SUM(INDEX('Working Capital'!$C$18:$AL$18,1,MAX(1,18-ROUND('Assumptions'!$F$91,0)+1)):INDEX('Working Capital'!$C$18:$AL$18,1,18))/ROUND('Assumptions'!$F$91,0) -> 0 | U19: =SUM(INDEX('Working Capital'!$C$18:$AL$18,1,MAX(1,19-ROUND('Assumptions'!$F$91,0)+1)):INDEX('Working Capital'!$C$18:$AL$18,1,19))/ROUND('Assumptions'!$F$91,0) -> 0 | V19: =SUM(INDEX('Working Capital'!$C$18:$AL$18,1,MAX(1,20-ROUND('Assumptions'!$F$91,0)+1)):INDEX('Working Capital'!$C$18:$AL$18,1,20))/ROUND('Assumptions'!$F$91,0) -> 0 | W19: =SUM(INDEX('Working Capital'!$C$18:$AL$18,1,MAX(1,21-ROUND('Assumptions'!$F$91,0)+1)):INDEX('Working Capital'!$C$18:$AL$18,1,21))/ROUND('Assumptions'!$F$91,0) -> 0 | X19: =SUM(INDEX('Working Capital'!$C$18:$AL$18,1,MAX(1,22-ROUND('Assumptions'!$F$91,0)+1)):INDEX('Working Capital'!$C$18:$AL$18,1,22))/ROUND('Assumptions'!$F$91,0) -> 0 | Y19: =SUM(INDEX('Working Capital'!$C$18:$AL$18,1,MAX(1,23-ROUND('Assumptions'!$F$91,0)+1)):INDEX('Working Capital'!$C$18:$AL$18,1,23))/ROUND('Assumptions'!$F$91,0) -> 0 | Z19: =SUM(INDEX('Working Capital'!$C$18:$AL$18,1,MAX(1,24-ROUND('Assumptions'!$F$91,0)+1)):INDEX('Working Capital'!$C$18:$AL$18,1,24))/ROUND('Assumptions'!$F$91,0) -> 0 | AA19: =SUM(INDEX('Working Capital'!$C$18:$AL$18,1,MAX(1,25-ROUND('Assumptions'!$F$91,0)+1)):INDEX('Working Capital'!$C$18:$AL$18,1,25))/ROUND('Assumptions'!$F$91,0) -> 0 | AB19: =SUM(INDEX('Working Capital'!$C$18:$AL$18,1,MAX(1,26-ROUND('Assumptions'!$F$91,0)+1)):INDEX('Working Capital'!$C$18:$AL$18,1,26))/ROUND('Assumptions'!$F$91,0) -> 0 | AC19: =SUM(INDEX('Working Capital'!$C$18:$AL$18,1,MAX(1,27-ROUND('Assumptions'!$F$91,0)+1)):INDEX('Working Capital'!$C$18:$AL$18,1,27))/ROUND('Assumptions'!$F$91,0) -> 0 | AD19: =SUM(INDEX('Working Capital'!$C$18:$AL$18,1,MAX(1,28-ROUND('Assumptions'!$F$91,0)+1)):INDEX('Working Capital'!$C$18:$AL$18,1,28))/ROUND('Assumptions'!$F$91,0) -> 0 | AE19: =SUM(INDEX('Working Capital'!$C$18:$AL$18,1,MAX(1,29-ROUND('Assumptions'!$F$91,0)+1)):INDEX('Working Capital'!$C$18:$AL$18,1,29))/ROUND('Assumptions'!$F$91,0) -> 0 | AF19: =SUM(INDEX('Working Capital'!$C$18:$AL$18,1,MAX(1,30-ROUND('Assumptions'!$F$91,0)+1)):INDEX('Working Capital'!$C$18:$AL$18,1,30))/ROUND('Assumptions'!$F$91,0) -> 0 | AG19: =SUM(INDEX('Working Capital'!$C$18:$AL$18,1,MAX(1,31-ROUND('Assumptions'!$F$91,0)+1)):INDEX('Working Capital'!$C$18:$AL$18,1,31))/ROUND('Assumptions'!$F$91,0) -> 0 | AH19: =SUM(INDEX('Working Capital'!$C$18:$AL$18,1,MAX(1,32-ROUND('Assumptions'!$F$91,0)+1)):INDEX('Working Capital'!$C$18:$AL$18,1,32))/ROUND('Assumptions'!$F$91,0) -> 0 | AI19: =SUM(INDEX('Working Capital'!$C$18:$AL$18,1,MAX(1,33-ROUND('Assumptions'!$F$91,0)+1)):INDEX('Working Capital'!$C$18:$AL$18,1,33))/ROUND('Assumptions'!$F$91,0) -> 0 | AJ19: =SUM(INDEX('Working Capital'!$C$18:$AL$18,1,MAX(1,34-ROUND('Assumptions'!$F$91,0)+1)):INDEX('Working Capital'!$C$18:$AL$18,1,34))/ROUND('Assumptions'!$F$91,0) -> 0 | AK19: =SUM(INDEX('Working Capital'!$C$18:$AL$18,1,MAX(1,35-ROUND('Assumptions'!$F$91,0)+1)):INDEX('Working Capital'!$C$18:$AL$18,1,35))/ROUND('Assumptions'!$F$91,0) -> 0 | AL19: =SUM(INDEX('Working Capital'!$C$18:$AL$18,1,MAX(1,36-ROUND('Assumptions'!$F$91,0)+1)):INDEX('Working Capital'!$C$18:$AL$18,1,36))/ROUND('Assumptions'!$F$91,0) -> 0 | AN19: =SUM(C19:E19) -> 0 | AO19: =SUM(F19:H19) -> 0 | AP19: =SUM(I19:K19) -> 0 | AQ19: =SUM(L19:N19) -> 0 | AR19: =SUM(O19:Q19) -> 0 | AS19: =SUM(R19:T19) -> 0 | AT19: =SUM(U19:W19) -> 0 | AU19: =SUM(X19:Z19) -> 0 | AV19: =SUM(AA19:AC19) -> 0 | AW19: =SUM(AD19:AF19) -> 0 | AX19: =SUM(AG19:AI19) -> 0 | AY19: =SUM(AJ19:AL19) -> 0 | BA19: =SUM(C19:N19) -> 0 | BB19: =SUM(O19:Z19) -> 0 | BC19: =SUM(AA19:AL19) -> 0
A20: Net PP&E balance | C20: =C18-C19 -> 0 | D20: =C20+D18-D19 -> 0 | E20: =D20+E18-E19 -> 0 | F20: =E20+F18-F19 -> 0 | G20: =F20+G18-G19 -> 0 | H20: =G20+H18-H19 -> 0 | I20: =H20+I18-I19 -> 0 | J20: =I20+J18-J19 -> 0 | K20: =J20+K18-K19 -> 0 | ... AL20: =AK20+AL18-AL19 -> 0 | AN20: =E20 -> 0 | AO20: =H20 -> 0 | AP20: =K20 -> 0 | AQ20: =N20 -> 0 | AR20: =Q20 -> 0 | AS20: =T20 -> 0 | AT20: =W20 -> 0 | AU20: =Z20 -> 0 | AV20: =AC20 -> 0 | AW20: =AF20 -> 0 | AX20: =AI20 -> 0 | AY20: =AL20 -> 0 | BA20: =N20 -> 0 | BB20: =Z20 -> 0 | BC20: =AL20 -> 0
A22: Debt Schedule
A23: Debt draw | B23: One-time draw in month 9 | C23: =0 -> 0 | D23: =0 -> 0 | E23: =0 -> 0 | F23: =0 -> 0 | G23: =0 -> 0 | H23: =0 -> 0 | I23: =0 -> 0 | J23: =0 -> 0 | K23: ='Assumptions'!$F$94 -> 0 | L23: =0 -> 0 | M23: =0 -> 0 | N23: =0 -> 0 | O23: =0 -> 0 | P23: =0 -> 0 | Q23: =0 -> 0 | R23: =0 -> 0 | S23: =0 -> 0 | ... AL23: =0 -> 0 | AN23: =SUM(C23:E23) -> 0 | AO23: =SUM(F23:H23) -> 0 | AP23: =SUM(I23:K23) -> 0 | AQ23: =SUM(L23:N23) -> 0 | AR23: =SUM(O23:Q23) -> 0 | AS23: =SUM(R23:T23) -> 0 | AT23: =SUM(U23:W23) -> 0 | AU23: =SUM(X23:Z23) -> 0 | AV23: =SUM(AA23:AC23) -> 0 | AW23: =SUM(AD23:AF23) -> 0 | AX23: =SUM(AG23:AI23) -> 0 | AY23: =SUM(AJ23:AL23) -> 0 | BA23: =SUM(C23:N23) -> 0 | BB23: =SUM(O23:Z23) -> 0 | BC23: =SUM(AA23:AL23) -> 0
A24: Debt repayment | B24: Fixed $/month once balance exists, starting the assumed month | C24: =0 -> 0 | D24: =0 -> 0 | E24: =0 -> 0 | F24: =0 -> 0 | G24: =0 -> 0 | H24: =0 -> 0 | I24: =0 -> 0 | J24: =0 -> 0 | ... T24: =0 -> 0 | U24: =MIN(T25,'Assumptions'!$F$95) -> 0 | V24: =MIN(U25,'Assumptions'!$F$95) -> 0 | W24: =MIN(V25,'Assumptions'!$F$95) -> 0 | X24: =MIN(W25,'Assumptions'!$F$95) -> 0 | Y24: =MIN(X25,'Assumptions'!$F$95) -> 0 | Z24: =MIN(Y25,'Assumptions'!$F$95) -> 0 | AA24: =MIN(Z25,'Assumptions'!$F$95) -> 0 | AB24: =MIN(AA25,'Assumptions'!$F$95) -> 0 | ... AL24: =MIN(AK25,'Assumptions'!$F$95) -> 0 | AN24: =SUM(C24:E24) -> 0 | AO24: =SUM(F24:H24) -> 0 | AP24: =SUM(I24:K24) -> 0 | AQ24: =SUM(L24:N24) -> 0 | AR24: =SUM(O24:Q24) -> 0 | AS24: =SUM(R24:T24) -> 0 | AT24: =SUM(U24:W24) -> 0 | AU24: =SUM(X24:Z24) -> 0 | AV24: =SUM(AA24:AC24) -> 0 | AW24: =SUM(AD24:AF24) -> 0 | AX24: =SUM(AG24:AI24) -> 0 | AY24: =SUM(AJ24:AL24) -> 0 | BA24: =SUM(C24:N24) -> 0 | BB24: =SUM(O24:Z24) -> 0 | BC24: =SUM(AA24:AL24) -> 0
A25: Debt balance (ending) | B25: Prior balance + draw − repayment | C25: =C23-C24 -> 0 | D25: =C25+D23-D24 -> 0 | E25: =D25+E23-E24 -> 0 | F25: =E25+F23-F24 -> 0 | G25: =F25+G23-G24 -> 0 | H25: =G25+H23-H24 -> 0 | I25: =H25+I23-I24 -> 0 | J25: =I25+J23-J24 -> 0 | K25: =J25+K23-K24 -> 0 | ... AL25: =AK25+AL23-AL24 -> 0 | AN25: =E25 -> 0 | AO25: =H25 -> 0 | AP25: =K25 -> 0 | AQ25: =N25 -> 0 | AR25: =Q25 -> 0 | AS25: =T25 -> 0 | AT25: =W25 -> 0 | AU25: =Z25 -> 0 | AV25: =AC25 -> 0 | AW25: =AF25 -> 0 | AX25: =AI25 -> 0 | AY25: =AL25 -> 0 | BA25: =N25 -> 0 | BB25: =Z25 -> 0 | BC25: =AL25 -> 0
A26: Interest expense | B26: Prior month balance × annual rate ÷ 12 | C26: =C23*'Assumptions'!$F$93/12/2 -> 0 | D26: =C25*'Assumptions'!$F$93/12 -> 0 | E26: =D25*'Assumptions'!$F$93/12 -> 0 | F26: =E25*'Assumptions'!$F$93/12 -> 0 | G26: =F25*'Assumptions'!$F$93/12 -> 0 | H26: =G25*'Assumptions'!$F$93/12 -> 0 | I26: =H25*'Assumptions'!$F$93/12 -> 0 | J26: =I25*'Assumptions'!$F$93/12 -> 0 | K26: =J25*'Assumptions'!$F$93/12 -> 0 | ... AL26: =AK25*'Assumptions'!$F$93/12 -> 0 | AN26: =SUM(C26:E26) -> 0 | AO26: =SUM(F26:H26) -> 0 | AP26: =SUM(I26:K26) -> 0 | AQ26: =SUM(L26:N26) -> 0 | AR26: =SUM(O26:Q26) -> 0 | AS26: =SUM(R26:T26) -> 0 | AT26: =SUM(U26:W26) -> 0 | AU26: =SUM(X26:Z26) -> 0 | AV26: =SUM(AA26:AC26) -> 0 | AW26: =SUM(AD26:AF26) -> 0 | AX26: =SUM(AG26:AI26) -> 0 | AY26: =SUM(AJ26:AL26) -> 0 | BA26: =SUM(C26:N26) -> 0 | BB26: =SUM(O26:Z26) -> 0 | BC26: =SUM(AA26:AL26) -> 0
A28: Equity Financing
A29: Equity raised | B29: Growth Equity in month 4; Follow-on Equity in month 22 | C29: =0 -> 0 | D29: =0 -> 0 | E29: =0 -> 0 | F29: ='Assumptions'!$F$96 -> 0 | G29: =0 -> 0 | H29: =0 -> 0 | I29: =0 -> 0 | J29: =0 -> 0 | K29: =0 -> 0 | L29: =0 -> 0 | M29: =0 -> 0 | N29: =0 -> 0 | ... W29: =0 -> 0 | X29: ='Assumptions'!$F$97 -> 0 | Y29: =0 -> 0 | Z29: =0 -> 0 | AA29: =0 -> 0 | AB29: =0 -> 0 | AC29: =0 -> 0 | AD29: =0 -> 0 | AE29: =0 -> 0 | AF29: =0 -> 0 | ... AL29: =0 -> 0 | AN29: =SUM(C29:E29) -> 0 | AO29: =SUM(F29:H29) -> 0 | AP29: =SUM(I29:K29) -> 0 | AQ29: =SUM(L29:N29) -> 0 | AR29: =SUM(O29:Q29) -> 0 | AS29: =SUM(R29:T29) -> 0 | AT29: =SUM(U29:W29) -> 0 | AU29: =SUM(X29:Z29) -> 0 | AV29: =SUM(AA29:AC29) -> 0 | AW29: =SUM(AD29:AF29) -> 0 | AX29: =SUM(AG29:AI29) -> 0 | AY29: =SUM(AJ29:AL29) -> 0 | BA29: =SUM(C29:N29) -> 0 | BB29: =SUM(O29:Z29) -> 0 | BC29: =SUM(AA29:AL29) -> 0
A30: Cumulative paid-in capital | C30: =C29 -> 0 | D30: =C30+D29 -> 0 | E30: =D30+E29 -> 0 | F30: =E30+F29 -> 0 | G30: =F30+G29 -> 0 | H30: =G30+H29 -> 0 | I30: =H30+I29 -> 0 | J30: =I30+J29 -> 0 | K30: =J30+K29 -> 0 | ... AL30: =AK30+AL29 -> 0 | AN30: =E30 -> 0 | AO30: =H30 -> 0 | AP30: =K30 -> 0 | AQ30: =N30 -> 0 | AR30: =Q30 -> 0 | AS30: =T30 -> 0 | AT30: =W30 -> 0 | AU30: =Z30 -> 0 | AV30: =AC30 -> 0 | AW30: =AF30 -> 0 | AX30: =AI30 -> 0 | AY30: =AL30 -> 0 | BA30: =N30 -> 0 | BB30: =Z30 -> 0 | BC30: =AL30 -> 0

Sheet P&L
A1: AI API / Infrastructure — 3-Year Financial Model — P&L
A2: Integrated income statement — every line links to Revenue, COGS & GM, Opex, or Working Capital.
A5: Line item | B5: Units / source | C5: Monthly (36 months) | AN5: Quarterly | BA5: Annual
C6: 46023 | D6: 46054 | E6: 46082 | F6: 46113 | G6: 46143 | H6: 46174 | I6: 46204 | J6: 46235 | K6: 46266 | L6: 46296 | M6: 46327 | N6: 46357 | O6: 46388 | P6: 46419 | Q6: 46447 | R6: 46478 | S6: 46508 | T6: 46539 | U6: 46569 | V6: 46600 | W6: 46631 | X6: 46661 | Y6: 46692 | Z6: 46722 | AA6: 46753 | AB6: 46784 | AC6: 46813 | AD6: 46844 | AE6: 46874 | AF6: 46905 | AG6: 46935 | AH6: 46966 | AI6: 46997 | AJ6: 47027 | AK6: 47058 | AL6: 47088 | AN6: Q1 | AO6: Q2 | AP6: Q3 | AQ6: Q4 | AR6: Q5 | AS6: Q6 | AT6: Q7 | AU6: Q8 | AV6: Q9 | AW6: Q10 | AX6: Q11 | AY6: Q12 | BA6: FY1 | BB6: FY2 | BC6: FY3
A7: Revenue | C7: ='Revenue'!$C$60 -> 0 | D7: ='Revenue'!$D$60 -> 0 | E7: ='Revenue'!$E$60 -> 0 | F7: ='Revenue'!$F$60 -> 0 | G7: ='Revenue'!$G$60 -> 0 | H7: ='Revenue'!$H$60 -> 0 | I7: ='Revenue'!$I$60 -> 0 | J7: ='Revenue'!$J$60 -> 0 | K7: ='Revenue'!$K$60 -> 0 | L7: ='Revenue'!$L$60 -> 0 | M7: ='Revenue'!$M$60 -> 0 | N7: ='Revenue'!$N$60 -> 0 | O7: ='Revenue'!$O$60 -> 0 | P7: ='Revenue'!$P$60 -> 0 | Q7: ='Revenue'!$Q$60 -> 0 | R7: ='Revenue'!$R$60 -> 0 | S7: ='Revenue'!$S$60 -> 0 | T7: ='Revenue'!$T$60 -> 0 | U7: ='Revenue'!$U$60 -> 0 | V7: ='Revenue'!$V$60 -> 0 | W7: ='Revenue'!$W$60 -> 0 | X7: ='Revenue'!$X$60 -> 0 | Y7: ='Revenue'!$Y$60 -> 0 | Z7: ='Revenue'!$Z$60 -> 0 | AA7: ='Revenue'!$AA$60 -> 0 | AB7: ='Revenue'!$AB$60 -> 0 | AC7: ='Revenue'!$AC$60 -> 0 | AD7: ='Revenue'!$AD$60 -> 0 | AE7: ='Revenue'!$AE$60 -> 0 | AF7: ='Revenue'!$AF$60 -> 0 | AG7: ='Revenue'!$AG$60 -> 0 | AH7: ='Revenue'!$AH$60 -> 0 | AI7: ='Revenue'!$AI$60 -> 0 | AJ7: ='Revenue'!$AJ$60 -> 0 | AK7: ='Revenue'!$AK$60 -> 0 | AL7: ='Revenue'!$AL$60 -> 0 | AN7: =SUM(C7:E7) -> 0 | AO7: =SUM(F7:H7) -> 0 | AP7: =SUM(I7:K7) -> 0 | AQ7: =SUM(L7:N7) -> 0 | AR7: =SUM(O7:Q7) -> 0 | AS7: =SUM(R7:T7) -> 0 | AT7: =SUM(U7:W7) -> 0 | AU7: =SUM(X7:Z7) -> 0 | AV7: =SUM(AA7:AC7) -> 0 | AW7: =SUM(AD7:AF7) -> 0 | AX7: =SUM(AG7:AI7) -> 0 | AY7: =SUM(AJ7:AL7) -> 0 | BA7: =SUM(C7:N7) -> 0 | BB7: =SUM(O7:Z7) -> 0 | BC7: =SUM(AA7:AL7) -> 0
A8: Cost of Goods Sold | C8: ='COGS & GM'!$C$21 -> 0 | D8: ='COGS & GM'!$D$21 -> 0 | E8: ='COGS & GM'!$E$21 -> 0 | F8: ='COGS & GM'!$F$21 -> 0 | G8: ='COGS & GM'!$G$21 -> 0 | H8: ='COGS & GM'!$H$21 -> 0 | I8: ='COGS & GM'!$I$21 -> 0 | J8: ='COGS & GM'!$J$21 -> 0 | K8: ='COGS & GM'!$K$21 -> 0 | L8: ='COGS & GM'!$L$21 -> 0 | M8: ='COGS & GM'!$M$21 -> 0 | N8: ='COGS & GM'!$N$21 -> 0 | O8: ='COGS & GM'!$O$21 -> 0 | P8: ='COGS & GM'!$P$21 -> 0 | Q8: ='COGS & GM'!$Q$21 -> 0 | R8: ='COGS & GM'!$R$21 -> 0 | S8: ='COGS & GM'!$S$21 -> 0 | T8: ='COGS & GM'!$T$21 -> 0 | U8: ='COGS & GM'!$U$21 -> 0 | V8: ='COGS & GM'!$V$21 -> 0 | W8: ='COGS & GM'!$W$21 -> 0 | X8: ='COGS & GM'!$X$21 -> 0 | Y8: ='COGS & GM'!$Y$21 -> 0 | Z8: ='COGS & GM'!$Z$21 -> 0 | AA8: ='COGS & GM'!$AA$21 -> 0 | AB8: ='COGS & GM'!$AB$21 -> 0 | AC8: ='COGS & GM'!$AC$21 -> 0 | AD8: ='COGS & GM'!$AD$21 -> 0 | AE8: ='COGS & GM'!$AE$21 -> 0 | AF8: ='COGS & GM'!$AF$21 -> 0 | AG8: ='COGS & GM'!$AG$21 -> 0 | AH8: ='COGS & GM'!$AH$21 -> 0 | AI8: ='COGS & GM'!$AI$21 -> 0 | AJ8: ='COGS & GM'!$AJ$21 -> 0 | AK8: ='COGS & GM'!$AK$21 -> 0 | AL8: ='COGS & GM'!$AL$21 -> 0 | AN8: =SUM(C8:E8) -> 0 | AO8: =SUM(F8:H8) -> 0 | AP8: =SUM(I8:K8) -> 0 | AQ8: =SUM(L8:N8) -> 0 | AR8: =SUM(O8:Q8) -> 0 | AS8: =SUM(R8:T8) -> 0 | AT8: =SUM(U8:W8) -> 0 | AU8: =SUM(X8:Z8) -> 0 | AV8: =SUM(AA8:AC8) -> 0 | AW8: =SUM(AD8:AF8) -> 0 | AX8: =SUM(AG8:AI8) -> 0 | AY8: =SUM(AJ8:AL8) -> 0 | BA8: =SUM(C8:N8) -> 0 | BB8: =SUM(O8:Z8) -> 0 | BC8: =SUM(AA8:AL8) -> 0
A9: Gross Profit | C9: =C7-C8 -> 0 | D9: =D7-D8 -> 0 | E9: =E7-E8 -> 0 | F9: =F7-F8 -> 0 | G9: =G7-G8 -> 0 | H9: =H7-H8 -> 0 | I9: =I7-I8 -> 0 | J9: =J7-J8 -> 0 | ... AL9: =AL7-AL8 -> 0 | AN9: =SUM(C9:E9) -> 0 | AO9: =SUM(F9:H9) -> 0 | AP9: =SUM(I9:K9) -> 0 | AQ9: =SUM(L9:N9) -> 0 | AR9: =SUM(O9:Q9) -> 0 | AS9: =SUM(R9:T9) -> 0 | AT9: =SUM(U9:W9) -> 0 | AU9: =SUM(X9:Z9) -> 0 | AV9: =SUM(AA9:AC9) -> 0 | AW9: =SUM(AD9:AF9) -> 0 | AX9: =SUM(AG9:AI9) -> 0 | AY9: =SUM(AJ9:AL9) -> 0 | BA9: =SUM(C9:N9) -> 0 | BB9: =SUM(O9:Z9) -> 0 | BC9: =SUM(AA9:AL9) -> 0
A10: Gross Margin % | C10: =IFERROR(C9/C7,0) -> 0 | D10: =IFERROR(D9/D7,0) -> 0 | E10: =IFERROR(E9/E7,0) -> 0 | F10: =IFERROR(F9/F7,0) -> 0 | G10: =IFERROR(G9/G7,0) -> 0 | H10: =IFERROR(H9/H7,0) -> 0 | I10: =IFERROR(I9/I7,0) -> 0 | J10: =IFERROR(J9/J7,0) -> 0 | ... AL10: =IFERROR(AL9/AL7,0) -> 0 | AN10: =AVERAGE(C10:E10) -> 0 | AO10: =AVERAGE(F10:H10) -> 0 | AP10: =AVERAGE(I10:K10) -> 0 | AQ10: =AVERAGE(L10:N10) -> 0 | AR10: =AVERAGE(O10:Q10) -> 0 | AS10: =AVERAGE(R10:T10) -> 0 | AT10: =AVERAGE(U10:W10) -> 0 | AU10: =AVERAGE(X10:Z10) -> 0 | AV10: =AVERAGE(AA10:AC10) -> 0 | AW10: =AVERAGE(AD10:AF10) -> 0 | AX10: =AVERAGE(AG10:AI10) -> 0 | AY10: =AVERAGE(AJ10:AL10) -> 0 | BA10: =AVERAGE(C10:N10) -> 0 | BB10: =AVERAGE(O10:Z10) -> 0 | BC10: =AVERAGE(AA10:AL10) -> 0
A12: Operating Expenses
A13: Sales & Marketing | C13: ='Opex'!$C$12 -> 0 | D13: ='Opex'!$D$12 -> 0 | E13: ='Opex'!$E$12 -> 0 | F13: ='Opex'!$F$12 -> 0 | G13: ='Opex'!$G$12 -> 0 | H13: ='Opex'!$H$12 -> 0 | I13: ='Opex'!$I$12 -> 0 | J13: ='Opex'!$J$12 -> 0 | K13: ='Opex'!$K$12 -> 0 | L13: ='Opex'!$L$12 -> 0 | M13: ='Opex'!$M$12 -> 0 | N13: ='Opex'!$N$12 -> 0 | O13: ='Opex'!$O$12 -> 0 | P13: ='Opex'!$P$12 -> 0 | Q13: ='Opex'!$Q$12 -> 0 | R13: ='Opex'!$R$12 -> 0 | S13: ='Opex'!$S$12 -> 0 | T13: ='Opex'!$T$12 -> 0 | U13: ='Opex'!$U$12 -> 0 | V13: ='Opex'!$V$12 -> 0 | W13: ='Opex'!$W$12 -> 0 | X13: ='Opex'!$X$12 -> 0 | Y13: ='Opex'!$Y$12 -> 0 | Z13: ='Opex'!$Z$12 -> 0 | AA13: ='Opex'!$AA$12 -> 0 | AB13: ='Opex'!$AB$12 -> 0 | AC13: ='Opex'!$AC$12 -> 0 | AD13: ='Opex'!$AD$12 -> 0 | AE13: ='Opex'!$AE$12 -> 0 | AF13: ='Opex'!$AF$12 -> 0 | AG13: ='Opex'!$AG$12 -> 0 | AH13: ='Opex'!$AH$12 -> 0 | AI13: ='Opex'!$AI$12 -> 0 | AJ13: ='Opex'!$AJ$12 -> 0 | AK13: ='Opex'!$AK$12 -> 0 | AL13: ='Opex'!$AL$12 -> 0 | AN13: =SUM(C13:E13) -> 0 | AO13: =SUM(F13:H13) -> 0 | AP13: =SUM(I13:K13) -> 0 | AQ13: =SUM(L13:N13) -> 0 | AR13: =SUM(O13:Q13) -> 0 | AS13: =SUM(R13:T13) -> 0 | AT13: =SUM(U13:W13) -> 0 | AU13: =SUM(X13:Z13) -> 0 | AV13: =SUM(AA13:AC13) -> 0 | AW13: =SUM(AD13:AF13) -> 0 | AX13: =SUM(AG13:AI13) -> 0 | AY13: =SUM(AJ13:AL13) -> 0 | BA13: =SUM(C13:N13) -> 0 | BB13: =SUM(O13:Z13) -> 0 | BC13: =SUM(AA13:AL13) -> 0
A14: R&D / Engineering | C14: ='Opex'!$C$16 -> 0 | D14: ='Opex'!$D$16 -> 0 | E14: ='Opex'!$E$16 -> 0 | F14: ='Opex'!$F$16 -> 0 | G14: ='Opex'!$G$16 -> 0 | H14: ='Opex'!$H$16 -> 0 | I14: ='Opex'!$I$16 -> 0 | J14: ='Opex'!$J$16 -> 0 | K14: ='Opex'!$K$16 -> 0 | L14: ='Opex'!$L$16 -> 0 | M14: ='Opex'!$M$16 -> 0 | N14: ='Opex'!$N$16 -> 0 | O14: ='Opex'!$O$16 -> 0 | P14: ='Opex'!$P$16 -> 0 | Q14: ='Opex'!$Q$16 -> 0 | R14: ='Opex'!$R$16 -> 0 | S14: ='Opex'!$S$16 -> 0 | T14: ='Opex'!$T$16 -> 0 | U14: ='Opex'!$U$16 -> 0 | V14: ='Opex'!$V$16 -> 0 | W14: ='Opex'!$W$16 -> 0 | X14: ='Opex'!$X$16 -> 0 | Y14: ='Opex'!$Y$16 -> 0 | Z14: ='Opex'!$Z$16 -> 0 | AA14: ='Opex'!$AA$16 -> 0 | AB14: ='Opex'!$AB$16 -> 0 | AC14: ='Opex'!$AC$16 -> 0 | AD14: ='Opex'!$AD$16 -> 0 | AE14: ='Opex'!$AE$16 -> 0 | AF14: ='Opex'!$AF$16 -> 0 | AG14: ='Opex'!$AG$16 -> 0 | AH14: ='Opex'!$AH$16 -> 0 | AI14: ='Opex'!$AI$16 -> 0 | AJ14: ='Opex'!$AJ$16 -> 0 | AK14: ='Opex'!$AK$16 -> 0 | AL14: ='Opex'!$AL$16 -> 0 | AN14: =SUM(C14:E14) -> 0 | AO14: =SUM(F14:H14) -> 0 | AP14: =SUM(I14:K14) -> 0 | AQ14: =SUM(L14:N14) -> 0 | AR14: =SUM(O14:Q14) -> 0 | AS14: =SUM(R14:T14) -> 0 | AT14: =SUM(U14:W14) -> 0 | AU14: =SUM(X14:Z14) -> 0 | AV14: =SUM(AA14:AC14) -> 0 | AW14: =SUM(AD14:AF14) -> 0 | AX14: =SUM(AG14:AI14) -> 0 | AY14: =SUM(AJ14:AL14) -> 0 | BA14: =SUM(C14:N14) -> 0 | BB14: =SUM(O14:Z14) -> 0 | BC14: =SUM(AA14:AL14) -> 0
A15: General & Administrative | C15: ='Opex'!$C$22 -> 0 | D15: ='Opex'!$D$22 -> 0 | E15: ='Opex'!$E$22 -> 0 | F15: ='Opex'!$F$22 -> 0 | G15: ='Opex'!$G$22 -> 0 | H15: ='Opex'!$H$22 -> 0 | I15: ='Opex'!$I$22 -> 0 | J15: ='Opex'!$J$22 -> 0 | K15: ='Opex'!$K$22 -> 0 | L15: ='Opex'!$L$22 -> 0 | M15: ='Opex'!$M$22 -> 0 | N15: ='Opex'!$N$22 -> 0 | O15: ='Opex'!$O$22 -> 0 | P15: ='Opex'!$P$22 -> 0 | Q15: ='Opex'!$Q$22 -> 0 | R15: ='Opex'!$R$22 -> 0 | S15: ='Opex'!$S$22 -> 0 | T15: ='Opex'!$T$22 -> 0 | U15: ='Opex'!$U$22 -> 0 | V15: ='Opex'!$V$22 -> 0 | W15: ='Opex'!$W$22 -> 0 | X15: ='Opex'!$X$22 -> 0 | Y15: ='Opex'!$Y$22 -> 0 | Z15: ='Opex'!$Z$22 -> 0 | AA15: ='Opex'!$AA$22 -> 0 | AB15: ='Opex'!$AB$22 -> 0 | AC15: ='Opex'!$AC$22 -> 0 | AD15: ='Opex'!$AD$22 -> 0 | AE15: ='Opex'!$AE$22 -> 0 | AF15: ='Opex'!$AF$22 -> 0 | AG15: ='Opex'!$AG$22 -> 0 | AH15: ='Opex'!$AH$22 -> 0 | AI15: ='Opex'!$AI$22 -> 0 | AJ15: ='Opex'!$AJ$22 -> 0 | AK15: ='Opex'!$AK$22 -> 0 | AL15: ='Opex'!$AL$22 -> 0 | AN15: =SUM(C15:E15) -> 0 | AO15: =SUM(F15:H15) -> 0 | AP15: =SUM(I15:K15) -> 0 | AQ15: =SUM(L15:N15) -> 0 | AR15: =SUM(O15:Q15) -> 0 | AS15: =SUM(R15:T15) -> 0 | AT15: =SUM(U15:W15) -> 0 | AU15: =SUM(X15:Z15) -> 0 | AV15: =SUM(AA15:AC15) -> 0 | AW15: =SUM(AD15:AF15) -> 0 | AX15: =SUM(AG15:AI15) -> 0 | AY15: =SUM(AJ15:AL15) -> 0 | BA15: =SUM(C15:N15) -> 0 | BB15: =SUM(O15:Z15) -> 0 | BC15: =SUM(AA15:AL15) -> 0
A16: Total Operating Expenses | C16: =C13+C14+C15 -> 0 | D16: =D13+D14+D15 -> 0 | E16: =E13+E14+E15 -> 0 | F16: =F13+F14+F15 -> 0 | G16: =G13+G14+G15 -> 0 | H16: =H13+H14+H15 -> 0 | I16: =I13+I14+I15 -> 0 | J16: =J13+J14+J15 -> 0 | ... AL16: =AL13+AL14+AL15 -> 0 | AN16: =SUM(C16:E16) -> 0 | AO16: =SUM(F16:H16) -> 0 | AP16: =SUM(I16:K16) -> 0 | AQ16: =SUM(L16:N16) -> 0 | AR16: =SUM(O16:Q16) -> 0 | AS16: =SUM(R16:T16) -> 0 | AT16: =SUM(U16:W16) -> 0 | AU16: =SUM(X16:Z16) -> 0 | AV16: =SUM(AA16:AC16) -> 0 | AW16: =SUM(AD16:AF16) -> 0 | AX16: =SUM(AG16:AI16) -> 0 | AY16: =SUM(AJ16:AL16) -> 0 | BA16: =SUM(C16:N16) -> 0 | BB16: =SUM(O16:Z16) -> 0 | BC16: =SUM(AA16:AL16) -> 0
A18: EBITDA | C18: =C9-C16 -> 0 | D18: =D9-D16 -> 0 | E18: =E9-E16 -> 0 | F18: =F9-F16 -> 0 | G18: =G9-G16 -> 0 | H18: =H9-H16 -> 0 | I18: =I9-I16 -> 0 | J18: =J9-J16 -> 0 | ... AL18: =AL9-AL16 -> 0 | AN18: =SUM(C18:E18) -> 0 | AO18: =SUM(F18:H18) -> 0 | AP18: =SUM(I18:K18) -> 0 | AQ18: =SUM(L18:N18) -> 0 | AR18: =SUM(O18:Q18) -> 0 | AS18: =SUM(R18:T18) -> 0 | AT18: =SUM(U18:W18) -> 0 | AU18: =SUM(X18:Z18) -> 0 | AV18: =SUM(AA18:AC18) -> 0 | AW18: =SUM(AD18:AF18) -> 0 | AX18: =SUM(AG18:AI18) -> 0 | AY18: =SUM(AJ18:AL18) -> 0 | BA18: =SUM(C18:N18) -> 0 | BB18: =SUM(O18:Z18) -> 0 | BC18: =SUM(AA18:AL18) -> 0
A19: Depreciation & Amortization | C19: ='Working Capital'!$C$19 -> 0 | D19: ='Working Capital'!$D$19 -> 0 | E19: ='Working Capital'!$E$19 -> 0 | F19: ='Working Capital'!$F$19 -> 0 | G19: ='Working Capital'!$G$19 -> 0 | H19: ='Working Capital'!$H$19 -> 0 | I19: ='Working Capital'!$I$19 -> 0 | J19: ='Working Capital'!$J$19 -> 0 | K19: ='Working Capital'!$K$19 -> 0 | L19: ='Working Capital'!$L$19 -> 0 | M19: ='Working Capital'!$M$19 -> 0 | N19: ='Working Capital'!$N$19 -> 0 | O19: ='Working Capital'!$O$19 -> 0 | P19: ='Working Capital'!$P$19 -> 0 | Q19: ='Working Capital'!$Q$19 -> 0 | R19: ='Working Capital'!$R$19 -> 0 | S19: ='Working Capital'!$S$19 -> 0 | T19: ='Working Capital'!$T$19 -> 0 | U19: ='Working Capital'!$U$19 -> 0 | V19: ='Working Capital'!$V$19 -> 0 | W19: ='Working Capital'!$W$19 -> 0 | X19: ='Working Capital'!$X$19 -> 0 | Y19: ='Working Capital'!$Y$19 -> 0 | Z19: ='Working Capital'!$Z$19 -> 0 | AA19: ='Working Capital'!$AA$19 -> 0 | AB19: ='Working Capital'!$AB$19 -> 0 | AC19: ='Working Capital'!$AC$19 -> 0 | AD19: ='Working Capital'!$AD$19 -> 0 | AE19: ='Working Capital'!$AE$19 -> 0 | AF19: ='Working Capital'!$AF$19 -> 0 | AG19: ='Working Capital'!$AG$19 -> 0 | AH19: ='Working Capital'!$AH$19 -> 0 | AI19: ='Working Capital'!$AI$19 -> 0 | AJ19: ='Working Capital'!$AJ$19 -> 0 | AK19: ='Working Capital'!$AK$19 -> 0 | AL19: ='Working Capital'!$AL$19 -> 0 | AN19: =SUM(C19:E19) -> 0 | AO19: =SUM(F19:H19) -> 0 | AP19: =SUM(I19:K19) -> 0 | AQ19: =SUM(L19:N19) -> 0 | AR19: =SUM(O19:Q19) -> 0 | AS19: =SUM(R19:T19) -> 0 | AT19: =SUM(U19:W19) -> 0 | AU19: =SUM(X19:Z19) -> 0 | AV19: =SUM(AA19:AC19) -> 0 | AW19: =SUM(AD19:AF19) -> 0 | AX19: =SUM(AG19:AI19) -> 0 | AY19: =SUM(AJ19:AL19) -> 0 | BA19: =SUM(C19:N19) -> 0 | BB19: =SUM(O19:Z19) -> 0 | BC19: =SUM(AA19:AL19) -> 0
A20: EBIT (Operating Income) | C20: =C18-C19 -> 0 | D20: =D18-D19 -> 0 | E20: =E18-E19 -> 0 | F20: =F18-F19 -> 0 | G20: =G18-G19 -> 0 | H20: =H18-H19 -> 0 | I20: =I18-I19 -> 0 | J20: =J18-J19 -> 0 | ... AL20: =AL18-AL19 -> 0 | AN20: =SUM(C20:E20) -> 0 | AO20: =SUM(F20:H20) -> 0 | AP20: =SUM(I20:K20) -> 0 | AQ20: =SUM(L20:N20) -> 0 | AR20: =SUM(O20:Q20) -> 0 | AS20: =SUM(R20:T20) -> 0 | AT20: =SUM(U20:W20) -> 0 | AU20: =SUM(X20:Z20) -> 0 | AV20: =SUM(AA20:AC20) -> 0 | AW20: =SUM(AD20:AF20) -> 0 | AX20: =SUM(AG20:AI20) -> 0 | AY20: =SUM(AJ20:AL20) -> 0 | BA20: =SUM(C20:N20) -> 0 | BB20: =SUM(O20:Z20) -> 0 | BC20: =SUM(AA20:AL20) -> 0
A21: Interest Expense | C21: ='Working Capital'!$C$26 -> 0 | D21: ='Working Capital'!$D$26 -> 0 | E21: ='Working Capital'!$E$26 -> 0 | F21: ='Working Capital'!$F$26 -> 0 | G21: ='Working Capital'!$G$26 -> 0 | H21: ='Working Capital'!$H$26 -> 0 | I21: ='Working Capital'!$I$26 -> 0 | J21: ='Working Capital'!$J$26 -> 0 | K21: ='Working Capital'!$K$26 -> 0 | L21: ='Working Capital'!$L$26 -> 0 | M21: ='Working Capital'!$M$26 -> 0 | N21: ='Working Capital'!$N$26 -> 0 | O21: ='Working Capital'!$O$26 -> 0 | P21: ='Working Capital'!$P$26 -> 0 | Q21: ='Working Capital'!$Q$26 -> 0 | R21: ='Working Capital'!$R$26 -> 0 | S21: ='Working Capital'!$S$26 -> 0 | T21: ='Working Capital'!$T$26 -> 0 | U21: ='Working Capital'!$U$26 -> 0 | V21: ='Working Capital'!$V$26 -> 0 | W21: ='Working Capital'!$W$26 -> 0 | X21: ='Working Capital'!$X$26 -> 0 | Y21: ='Working Capital'!$Y$26 -> 0 | Z21: ='Working Capital'!$Z$26 -> 0 | AA21: ='Working Capital'!$AA$26 -> 0 | AB21: ='Working Capital'!$AB$26 -> 0 | AC21: ='Working Capital'!$AC$26 -> 0 | AD21: ='Working Capital'!$AD$26 -> 0 | AE21: ='Working Capital'!$AE$26 -> 0 | AF21: ='Working Capital'!$AF$26 -> 0 | AG21: ='Working Capital'!$AG$26 -> 0 | AH21: ='Working Capital'!$AH$26 -> 0 | AI21: ='Working Capital'!$AI$26 -> 0 | AJ21: ='Working Capital'!$AJ$26 -> 0 | AK21: ='Working Capital'!$AK$26 -> 0 | AL21: ='Working Capital'!$AL$26 -> 0 | AN21: =SUM(C21:E21) -> 0 | AO21: =SUM(F21:H21) -> 0 | AP21: =SUM(I21:K21) -> 0 | AQ21: =SUM(L21:N21) -> 0 | AR21: =SUM(O21:Q21) -> 0 | AS21: =SUM(R21:T21) -> 0 | AT21: =SUM(U21:W21) -> 0 | AU21: =SUM(X21:Z21) -> 0 | AV21: =SUM(AA21:AC21) -> 0 | AW21: =SUM(AD21:AF21) -> 0 | AX21: =SUM(AG21:AI21) -> 0 | AY21: =SUM(AJ21:AL21) -> 0 | BA21: =SUM(C21:N21) -> 0 | BB21: =SUM(O21:Z21) -> 0 | BC21: =SUM(AA21:AL21) -> 0
A22: Earnings Before Tax | C22: =C20-C21 -> 0 | D22: =D20-D21 -> 0 | E22: =E20-E21 -> 0 | F22: =F20-F21 -> 0 | G22: =G20-G21 -> 0 | H22: =H20-H21 -> 0 | I22: =I20-I21 -> 0 | J22: =J20-J21 -> 0 | ... AL22: =AL20-AL21 -> 0 | AN22: =SUM(C22:E22) -> 0 | AO22: =SUM(F22:H22) -> 0 | AP22: =SUM(I22:K22) -> 0 | AQ22: =SUM(L22:N22) -> 0 | AR22: =SUM(O22:Q22) -> 0 | AS22: =SUM(R22:T22) -> 0 | AT22: =SUM(U22:W22) -> 0 | AU22: =SUM(X22:Z22) -> 0 | AV22: =SUM(AA22:AC22) -> 0 | AW22: =SUM(AD22:AF22) -> 0 | AX22: =SUM(AG22:AI22) -> 0 | AY22: =SUM(AJ22:AL22) -> 0 | BA22: =SUM(C22:N22) -> 0 | BB22: =SUM(O22:Z22) -> 0 | BC22: =SUM(AA22:AL22) -> 0
A23: Income Tax Expense | B23: MAX(0, EBT) × tax rate — no NOL modeling | C23: =MAX(0,C22)*'Assumptions'!$F$10 -> 0 | D23: =MAX(0,D22)*'Assumptions'!$F$10 -> 0 | E23: =MAX(0,E22)*'Assumptions'!$F$10 -> 0 | F23: =MAX(0,F22)*'Assumptions'!$F$10 -> 0 | G23: =MAX(0,G22)*'Assumptions'!$F$10 -> 0 | H23: =MAX(0,H22)*'Assumptions'!$F$10 -> 0 | I23: =MAX(0,I22)*'Assumptions'!$F$10 -> 0 | J23: =MAX(0,J22)*'Assumptions'!$F$10 -> 0 | ... AL23: =MAX(0,AL22)*'Assumptions'!$F$10 -> 0 | AN23: =SUM(C23:E23) -> 0 | AO23: =SUM(F23:H23) -> 0 | AP23: =SUM(I23:K23) -> 0 | AQ23: =SUM(L23:N23) -> 0 | AR23: =SUM(O23:Q23) -> 0 | AS23: =SUM(R23:T23) -> 0 | AT23: =SUM(U23:W23) -> 0 | AU23: =SUM(X23:Z23) -> 0 | AV23: =SUM(AA23:AC23) -> 0 | AW23: =SUM(AD23:AF23) -> 0 | AX23: =SUM(AG23:AI23) -> 0 | AY23: =SUM(AJ23:AL23) -> 0 | BA23: =SUM(C23:N23) -> 0 | BB23: =SUM(O23:Z23) -> 0 | BC23: =SUM(AA23:AL23) -> 0
A24: Net Income | C24: =C22-C23 -> 0 | D24: =D22-D23 -> 0 | E24: =E22-E23 -> 0 | F24: =F22-F23 -> 0 | G24: =G22-G23 -> 0 | H24: =H22-H23 -> 0 | I24: =I22-I23 -> 0 | J24: =J22-J23 -> 0 | ... AL24: =AL22-AL23 -> 0 | AN24: =SUM(C24:E24) -> 0 | AO24: =SUM(F24:H24) -> 0 | AP24: =SUM(I24:K24) -> 0 | AQ24: =SUM(L24:N24) -> 0 | AR24: =SUM(O24:Q24) -> 0 | AS24: =SUM(R24:T24) -> 0 | AT24: =SUM(U24:W24) -> 0 | AU24: =SUM(X24:Z24) -> 0 | AV24: =SUM(AA24:AC24) -> 0 | AW24: =SUM(AD24:AF24) -> 0 | AX24: =SUM(AG24:AI24) -> 0 | AY24: =SUM(AJ24:AL24) -> 0 | BA24: =SUM(C24:N24) -> 0 | BB24: =SUM(O24:Z24) -> 0 | BC24: =SUM(AA24:AL24) -> 0

Sheet Cash Flow
A1: AI API / Infrastructure — 3-Year Financial Model — Cash Flow
A2: Indirect method — Net Income reconciled to the change in cash.
A5: Line item | B5: Units / source | C5: Monthly (36 months) | AN5: Quarterly | BA5: Annual
C6: 46023 | D6: 46054 | E6: 46082 | F6: 46113 | G6: 46143 | H6: 46174 | I6: 46204 | J6: 46235 | K6: 46266 | L6: 46296 | M6: 46327 | N6: 46357 | O6: 46388 | P6: 46419 | Q6: 46447 | R6: 46478 | S6: 46508 | T6: 46539 | U6: 46569 | V6: 46600 | W6: 46631 | X6: 46661 | Y6: 46692 | Z6: 46722 | AA6: 46753 | AB6: 46784 | AC6: 46813 | AD6: 46844 | AE6: 46874 | AF6: 46905 | AG6: 46935 | AH6: 46966 | AI6: 46997 | AJ6: 47027 | AK6: 47058 | AL6: 47088 | AN6: Q1 | AO6: Q2 | AP6: Q3 | AQ6: Q4 | AR6: Q5 | AS6: Q6 | AT6: Q7 | AU6: Q8 | AV6: Q9 | AW6: Q10 | AX6: Q11 | AY6: Q12 | BA6: FY1 | BB6: FY2 | BC6: FY3
A7: Cash from Operations
A8: Net Income | C8: ='P&L'!$C$24 -> 0 | D8: ='P&L'!$D$24 -> 0 | E8: ='P&L'!$E$24 -> 0 | F8: ='P&L'!$F$24 -> 0 | G8: ='P&L'!$G$24 -> 0 | H8: ='P&L'!$H$24 -> 0 | I8: ='P&L'!$I$24 -> 0 | J8: ='P&L'!$J$24 -> 0 | K8: ='P&L'!$K$24 -> 0 | L8: ='P&L'!$L$24 -> 0 | M8: ='P&L'!$M$24 -> 0 | N8: ='P&L'!$N$24 -> 0 | O8: ='P&L'!$O$24 -> 0 | P8: ='P&L'!$P$24 -> 0 | Q8: ='P&L'!$Q$24 -> 0 | R8: ='P&L'!$R$24 -> 0 | S8: ='P&L'!$S$24 -> 0 | T8: ='P&L'!$T$24 -> 0 | U8: ='P&L'!$U$24 -> 0 | V8: ='P&L'!$V$24 -> 0 | W8: ='P&L'!$W$24 -> 0 | X8: ='P&L'!$X$24 -> 0 | Y8: ='P&L'!$Y$24 -> 0 | Z8: ='P&L'!$Z$24 -> 0 | AA8: ='P&L'!$AA$24 -> 0 | AB8: ='P&L'!$AB$24 -> 0 | AC8: ='P&L'!$AC$24 -> 0 | AD8: ='P&L'!$AD$24 -> 0 | AE8: ='P&L'!$AE$24 -> 0 | AF8: ='P&L'!$AF$24 -> 0 | AG8: ='P&L'!$AG$24 -> 0 | AH8: ='P&L'!$AH$24 -> 0 | AI8: ='P&L'!$AI$24 -> 0 | AJ8: ='P&L'!$AJ$24 -> 0 | AK8: ='P&L'!$AK$24 -> 0 | AL8: ='P&L'!$AL$24 -> 0 | AN8: =SUM(C8:E8) -> 0 | AO8: =SUM(F8:H8) -> 0 | AP8: =SUM(I8:K8) -> 0 | AQ8: =SUM(L8:N8) -> 0 | AR8: =SUM(O8:Q8) -> 0 | AS8: =SUM(R8:T8) -> 0 | AT8: =SUM(U8:W8) -> 0 | AU8: =SUM(X8:Z8) -> 0 | AV8: =SUM(AA8:AC8) -> 0 | AW8: =SUM(AD8:AF8) -> 0 | AX8: =SUM(AG8:AI8) -> 0 | AY8: =SUM(AJ8:AL8) -> 0 | BA8: =SUM(C8:N8) -> 0 | BB8: =SUM(O8:Z8) -> 0 | BC8: =SUM(AA8:AL8) -> 0
A9: + Depreciation & Amortization | C9: ='P&L'!$C$19 -> 0 | D9: ='P&L'!$D$19 -> 0 | E9: ='P&L'!$E$19 -> 0 | F9: ='P&L'!$F$19 -> 0 | G9: ='P&L'!$G$19 -> 0 | H9: ='P&L'!$H$19 -> 0 | I9: ='P&L'!$I$19 -> 0 | J9: ='P&L'!$J$19 -> 0 | K9: ='P&L'!$K$19 -> 0 | L9: ='P&L'!$L$19 -> 0 | M9: ='P&L'!$M$19 -> 0 | N9: ='P&L'!$N$19 -> 0 | O9: ='P&L'!$O$19 -> 0 | P9: ='P&L'!$P$19 -> 0 | Q9: ='P&L'!$Q$19 -> 0 | R9: ='P&L'!$R$19 -> 0 | S9: ='P&L'!$S$19 -> 0 | T9: ='P&L'!$T$19 -> 0 | U9: ='P&L'!$U$19 -> 0 | V9: ='P&L'!$V$19 -> 0 | W9: ='P&L'!$W$19 -> 0 | X9: ='P&L'!$X$19 -> 0 | Y9: ='P&L'!$Y$19 -> 0 | Z9: ='P&L'!$Z$19 -> 0 | AA9: ='P&L'!$AA$19 -> 0 | AB9: ='P&L'!$AB$19 -> 0 | AC9: ='P&L'!$AC$19 -> 0 | AD9: ='P&L'!$AD$19 -> 0 | AE9: ='P&L'!$AE$19 -> 0 | AF9: ='P&L'!$AF$19 -> 0 | AG9: ='P&L'!$AG$19 -> 0 | AH9: ='P&L'!$AH$19 -> 0 | AI9: ='P&L'!$AI$19 -> 0 | AJ9: ='P&L'!$AJ$19 -> 0 | AK9: ='P&L'!$AK$19 -> 0 | AL9: ='P&L'!$AL$19 -> 0 | AN9: =SUM(C9:E9) -> 0 | AO9: =SUM(F9:H9) -> 0 | AP9: =SUM(I9:K9) -> 0 | AQ9: =SUM(L9:N9) -> 0 | AR9: =SUM(O9:Q9) -> 0 | AS9: =SUM(R9:T9) -> 0 | AT9: =SUM(U9:W9) -> 0 | AU9: =SUM(X9:Z9) -> 0 | AV9: =SUM(AA9:AC9) -> 0 | AW9: =SUM(AD9:AF9) -> 0 | AX9: =SUM(AG9:AI9) -> 0 | AY9: =SUM(AJ9:AL9) -> 0 | BA9: =SUM(C9:N9) -> 0 | BB9: =SUM(O9:Z9) -> 0 | BC9: =SUM(AA9:AL9) -> 0
A10: − Change in Accounts Receivable | C10: =-'Working Capital'!C12 -> 0 | D10: =-'Working Capital'!D12 -> 0 | E10: =-'Working Capital'!E12 -> 0 | F10: =-'Working Capital'!F12 -> 0 | G10: =-'Working Capital'!G12 -> 0 | H10: =-'Working Capital'!H12 -> 0 | I10: =-'Working Capital'!I12 -> 0 | J10: =-'Working Capital'!J12 -> 0 | ... AL10: =-'Working Capital'!AL12 -> 0 | AN10: =SUM(C10:E10) -> 0 | AO10: =SUM(F10:H10) -> 0 | AP10: =SUM(I10:K10) -> 0 | AQ10: =SUM(L10:N10) -> 0 | AR10: =SUM(O10:Q10) -> 0 | AS10: =SUM(R10:T10) -> 0 | AT10: =SUM(U10:W10) -> 0 | AU10: =SUM(X10:Z10) -> 0 | AV10: =SUM(AA10:AC10) -> 0 | AW10: =SUM(AD10:AF10) -> 0 | AX10: =SUM(AG10:AI10) -> 0 | AY10: =SUM(AJ10:AL10) -> 0 | BA10: =SUM(C10:N10) -> 0 | BB10: =SUM(O10:Z10) -> 0 | BC10: =SUM(AA10:AL10) -> 0
A11: − Change in Other Current Assets | C11: =-'Working Capital'!C15 -> 0 | D11: =-'Working Capital'!D15 -> 0 | E11: =-'Working Capital'!E15 -> 0 | F11: =-'Working Capital'!F15 -> 0 | G11: =-'Working Capital'!G15 -> 0 | H11: =-'Working Capital'!H15 -> 0 | I11: =-'Working Capital'!I15 -> 0 | J11: =-'Working Capital'!J15 -> 0 | ... AL11: =-'Working Capital'!AL15 -> 0 | AN11: =SUM(C11:E11) -> 0 | AO11: =SUM(F11:H11) -> 0 | AP11: =SUM(I11:K11) -> 0 | AQ11: =SUM(L11:N11) -> 0 | AR11: =SUM(O11:Q11) -> 0 | AS11: =SUM(R11:T11) -> 0 | AT11: =SUM(U11:W11) -> 0 | AU11: =SUM(X11:Z11) -> 0 | AV11: =SUM(AA11:AC11) -> 0 | AW11: =SUM(AD11:AF11) -> 0 | AX11: =SUM(AG11:AI11) -> 0 | AY11: =SUM(AJ11:AL11) -> 0 | BA11: =SUM(C11:N11) -> 0 | BB11: =SUM(O11:Z11) -> 0 | BC11: =SUM(AA11:AL11) -> 0
A12: + Change in Accounts Payable | C12: ='Working Capital'!C13 -> 0 | D12: ='Working Capital'!D13 -> 0 | E12: ='Working Capital'!E13 -> 0 | F12: ='Working Capital'!F13 -> 0 | G12: ='Working Capital'!G13 -> 0 | H12: ='Working Capital'!H13 -> 0 | I12: ='Working Capital'!I13 -> 0 | J12: ='Working Capital'!J13 -> 0 | ... AL12: ='Working Capital'!AL13 -> 0 | AN12: =SUM(C12:E12) -> 0 | AO12: =SUM(F12:H12) -> 0 | AP12: =SUM(I12:K12) -> 0 | AQ12: =SUM(L12:N12) -> 0 | AR12: =SUM(O12:Q12) -> 0 | AS12: =SUM(R12:T12) -> 0 | AT12: =SUM(U12:W12) -> 0 | AU12: =SUM(X12:Z12) -> 0 | AV12: =SUM(AA12:AC12) -> 0 | AW12: =SUM(AD12:AF12) -> 0 | AX12: =SUM(AG12:AI12) -> 0 | AY12: =SUM(AJ12:AL12) -> 0 | BA12: =SUM(C12:N12) -> 0 | BB12: =SUM(O12:Z12) -> 0 | BC12: =SUM(AA12:AL12) -> 0
A13: + Change in Deferred Revenue | C13: ='Working Capital'!C14 -> 0 | D13: ='Working Capital'!D14 -> 0 | E13: ='Working Capital'!E14 -> 0 | F13: ='Working Capital'!F14 -> 0 | G13: ='Working Capital'!G14 -> 0 | H13: ='Working Capital'!H14 -> 0 | I13: ='Working Capital'!I14 -> 0 | J13: ='Working Capital'!J14 -> 0 | ... AL13: ='Working Capital'!AL14 -> 0 | AN13: =SUM(C13:E13) -> 0 | AO13: =SUM(F13:H13) -> 0 | AP13: =SUM(I13:K13) -> 0 | AQ13: =SUM(L13:N13) -> 0 | AR13: =SUM(O13:Q13) -> 0 | AS13: =SUM(R13:T13) -> 0 | AT13: =SUM(U13:W13) -> 0 | AU13: =SUM(X13:Z13) -> 0 | AV13: =SUM(AA13:AC13) -> 0 | AW13: =SUM(AD13:AF13) -> 0 | AX13: =SUM(AG13:AI13) -> 0 | AY13: =SUM(AJ13:AL13) -> 0 | BA13: =SUM(C13:N13) -> 0 | BB13: =SUM(O13:Z13) -> 0 | BC13: =SUM(AA13:AL13) -> 0
A14: Cash from Operations | C14: =C8+C9+C10+C11+C12+C13 -> 0 | D14: =D8+D9+D10+D11+D12+D13 -> 0 | E14: =E8+E9+E10+E11+E12+E13 -> 0 | F14: =F8+F9+F10+F11+F12+F13 -> 0 | G14: =G8+G9+G10+G11+G12+G13 -> 0 | H14: =H8+H9+H10+H11+H12+H13 -> 0 | I14: =I8+I9+I10+I11+I12+I13 -> 0 | J14: =J8+J9+J10+J11+J12+J13 -> 0 | ... AL14: =AL8+AL9+AL10+AL11+AL12+AL13 -> 0 | AN14: =SUM(C14:E14) -> 0 | AO14: =SUM(F14:H14) -> 0 | AP14: =SUM(I14:K14) -> 0 | AQ14: =SUM(L14:N14) -> 0 | AR14: =SUM(O14:Q14) -> 0 | AS14: =SUM(R14:T14) -> 0 | AT14: =SUM(U14:W14) -> 0 | AU14: =SUM(X14:Z14) -> 0 | AV14: =SUM(AA14:AC14) -> 0 | AW14: =SUM(AD14:AF14) -> 0 | AX14: =SUM(AG14:AI14) -> 0 | AY14: =SUM(AJ14:AL14) -> 0 | BA14: =SUM(C14:N14) -> 0 | BB14: =SUM(O14:Z14) -> 0 | BC14: =SUM(AA14:AL14) -> 0
A16: Cash from Investing
A17: − Capital Expenditures | C17: =-'Working Capital'!C18 -> 0 | D17: =-'Working Capital'!D18 -> 0 | E17: =-'Working Capital'!E18 -> 0 | F17: =-'Working Capital'!F18 -> 0 | G17: =-'Working Capital'!G18 -> 0 | H17: =-'Working Capital'!H18 -> 0 | I17: =-'Working Capital'!I18 -> 0 | J17: =-'Working Capital'!J18 -> 0 | ... AL17: =-'Working Capital'!AL18 -> 0 | AN17: =SUM(C17:E17) -> 0 | AO17: =SUM(F17:H17) -> 0 | AP17: =SUM(I17:K17) -> 0 | AQ17: =SUM(L17:N17) -> 0 | AR17: =SUM(O17:Q17) -> 0 | AS17: =SUM(R17:T17) -> 0 | AT17: =SUM(U17:W17) -> 0 | AU17: =SUM(X17:Z17) -> 0 | AV17: =SUM(AA17:AC17) -> 0 | AW17: =SUM(AD17:AF17) -> 0 | AX17: =SUM(AG17:AI17) -> 0 | AY17: =SUM(AJ17:AL17) -> 0 | BA17: =SUM(C17:N17) -> 0 | BB17: =SUM(O17:Z17) -> 0 | BC17: =SUM(AA17:AL17) -> 0
A18: Cash from Investing | C18: =C17 -> 0 | D18: =D17 -> 0 | E18: =E17 -> 0 | F18: =F17 -> 0 | G18: =G17 -> 0 | H18: =H17 -> 0 | I18: =I17 -> 0 | J18: =J17 -> 0 | ... AL18: =AL17 -> 0 | AN18: =SUM(C18:E18) -> 0 | AO18: =SUM(F18:H18) -> 0 | AP18: =SUM(I18:K18) -> 0 | AQ18: =SUM(L18:N18) -> 0 | AR18: =SUM(O18:Q18) -> 0 | AS18: =SUM(R18:T18) -> 0 | AT18: =SUM(U18:W18) -> 0 | AU18: =SUM(X18:Z18) -> 0 | AV18: =SUM(AA18:AC18) -> 0 | AW18: =SUM(AD18:AF18) -> 0 | AX18: =SUM(AG18:AI18) -> 0 | AY18: =SUM(AJ18:AL18) -> 0 | BA18: =SUM(C18:N18) -> 0 | BB18: =SUM(O18:Z18) -> 0 | BC18: =SUM(AA18:AL18) -> 0
A20: Cash from Financing
A21: + Debt Draw | C21: ='Working Capital'!C23 -> 0 | D21: ='Working Capital'!D23 -> 0 | E21: ='Working Capital'!E23 -> 0 | F21: ='Working Capital'!F23 -> 0 | G21: ='Working Capital'!G23 -> 0 | H21: ='Working Capital'!H23 -> 0 | I21: ='Working Capital'!I23 -> 0 | J21: ='Working Capital'!J23 -> 0 | ... AL21: ='Working Capital'!AL23 -> 0 | AN21: =SUM(C21:E21) -> 0 | AO21: =SUM(F21:H21) -> 0 | AP21: =SUM(I21:K21) -> 0 | AQ21: =SUM(L21:N21) -> 0 | AR21: =SUM(O21:Q21) -> 0 | AS21: =SUM(R21:T21) -> 0 | AT21: =SUM(U21:W21) -> 0 | AU21: =SUM(X21:Z21) -> 0 | AV21: =SUM(AA21:AC21) -> 0 | AW21: =SUM(AD21:AF21) -> 0 | AX21: =SUM(AG21:AI21) -> 0 | AY21: =SUM(AJ21:AL21) -> 0 | BA21: =SUM(C21:N21) -> 0 | BB21: =SUM(O21:Z21) -> 0 | BC21: =SUM(AA21:AL21) -> 0
A22: − Debt Repayment | C22: =-'Working Capital'!C24 -> 0 | D22: =-'Working Capital'!D24 -> 0 | E22: =-'Working Capital'!E24 -> 0 | F22: =-'Working Capital'!F24 -> 0 | G22: =-'Working Capital'!G24 -> 0 | H22: =-'Working Capital'!H24 -> 0 | I22: =-'Working Capital'!I24 -> 0 | J22: =-'Working Capital'!J24 -> 0 | ... AL22: =-'Working Capital'!AL24 -> 0 | AN22: =SUM(C22:E22) -> 0 | AO22: =SUM(F22:H22) -> 0 | AP22: =SUM(I22:K22) -> 0 | AQ22: =SUM(L22:N22) -> 0 | AR22: =SUM(O22:Q22) -> 0 | AS22: =SUM(R22:T22) -> 0 | AT22: =SUM(U22:W22) -> 0 | AU22: =SUM(X22:Z22) -> 0 | AV22: =SUM(AA22:AC22) -> 0 | AW22: =SUM(AD22:AF22) -> 0 | AX22: =SUM(AG22:AI22) -> 0 | AY22: =SUM(AJ22:AL22) -> 0 | BA22: =SUM(C22:N22) -> 0 | BB22: =SUM(O22:Z22) -> 0 | BC22: =SUM(AA22:AL22) -> 0
A23: + Equity Raised | C23: ='Working Capital'!C29 -> 0 | D23: ='Working Capital'!D29 -> 0 | E23: ='Working Capital'!E29 -> 0 | F23: ='Working Capital'!F29 -> 0 | G23: ='Working Capital'!G29 -> 0 | H23: ='Working Capital'!H29 -> 0 | I23: ='Working Capital'!I29 -> 0 | J23: ='Working Capital'!J29 -> 0 | ... AL23: ='Working Capital'!AL29 -> 0 | AN23: =SUM(C23:E23) -> 0 | AO23: =SUM(F23:H23) -> 0 | AP23: =SUM(I23:K23) -> 0 | AQ23: =SUM(L23:N23) -> 0 | AR23: =SUM(O23:Q23) -> 0 | AS23: =SUM(R23:T23) -> 0 | AT23: =SUM(U23:W23) -> 0 | AU23: =SUM(X23:Z23) -> 0 | AV23: =SUM(AA23:AC23) -> 0 | AW23: =SUM(AD23:AF23) -> 0 | AX23: =SUM(AG23:AI23) -> 0 | AY23: =SUM(AJ23:AL23) -> 0 | BA23: =SUM(C23:N23) -> 0 | BB23: =SUM(O23:Z23) -> 0 | BC23: =SUM(AA23:AL23) -> 0
A24: Cash from Financing | C24: =C21+C22+C23 -> 0 | D24: =D21+D22+D23 -> 0 | E24: =E21+E22+E23 -> 0 | F24: =F21+F22+F23 -> 0 | G24: =G21+G22+G23 -> 0 | H24: =H21+H22+H23 -> 0 | I24: =I21+I22+I23 -> 0 | J24: =J21+J22+J23 -> 0 | ... AL24: =AL21+AL22+AL23 -> 0 | AN24: =SUM(C24:E24) -> 0 | AO24: =SUM(F24:H24) -> 0 | AP24: =SUM(I24:K24) -> 0 | AQ24: =SUM(L24:N24) -> 0 | AR24: =SUM(O24:Q24) -> 0 | AS24: =SUM(R24:T24) -> 0 | AT24: =SUM(U24:W24) -> 0 | AU24: =SUM(X24:Z24) -> 0 | AV24: =SUM(AA24:AC24) -> 0 | AW24: =SUM(AD24:AF24) -> 0 | AX24: =SUM(AG24:AI24) -> 0 | AY24: =SUM(AJ24:AL24) -> 0 | BA24: =SUM(C24:N24) -> 0 | BB24: =SUM(O24:Z24) -> 0 | BC24: =SUM(AA24:AL24) -> 0
A26: Net Change in Cash | C26: =C14+C18+C24 -> 0 | D26: =D14+D18+D24 -> 0 | E26: =E14+E18+E24 -> 0 | F26: =F14+F18+F24 -> 0 | G26: =G14+G18+G24 -> 0 | H26: =H14+H18+H24 -> 0 | I26: =I14+I18+I24 -> 0 | J26: =J14+J18+J24 -> 0 | ... AL26: =AL14+AL18+AL24 -> 0 | AN26: =SUM(C26:E26) -> 0 | AO26: =SUM(F26:H26) -> 0 | AP26: =SUM(I26:K26) -> 0 | AQ26: =SUM(L26:N26) -> 0 | AR26: =SUM(O26:Q26) -> 0 | AS26: =SUM(R26:T26) -> 0 | AT26: =SUM(U26:W26) -> 0 | AU26: =SUM(X26:Z26) -> 0 | AV26: =SUM(AA26:AC26) -> 0 | AW26: =SUM(AD26:AF26) -> 0 | AX26: =SUM(AG26:AI26) -> 0 | AY26: =SUM(AJ26:AL26) -> 0 | BA26: =SUM(C26:N26) -> 0 | BB26: =SUM(O26:Z26) -> 0 | BC26: =SUM(AA26:AL26) -> 0
A27: Beginning Cash | B27: Prior month ending cash (or starting cash in month 1) | C27: ='Assumptions'!$F$8 -> 0 | D27: =C28 -> 0 | E27: =D28 -> 0 | F27: =E28 -> 0 | G27: =F28 -> 0 | H27: =G28 -> 0 | I27: =H28 -> 0 | J27: =I28 -> 0 | K27: =J28 -> 0 | ... AL27: =AK28 -> 0 | AN27: =C27 -> 0 | AO27: =F27 -> 0 | AP27: =I27 -> 0 | AQ27: =L27 -> 0 | AR27: =O27 -> 0 | AS27: =R27 -> 0 | AT27: =U27 -> 0 | AU27: =X27 -> 0 | AV27: =AA27 -> 0 | AW27: =AD27 -> 0 | AX27: =AG27 -> 0 | AY27: =AJ27 -> 0 | BA27: =C27 -> 0 | BB27: =O27 -> 0 | BC27: =AA27 -> 0
A28: Ending Cash | B28: Beginning cash + net change in cash | C28: =C27+C26 -> 0 | D28: =D27+D26 -> 0 | E28: =E27+E26 -> 0 | F28: =F27+F26 -> 0 | G28: =G27+G26 -> 0 | H28: =H27+H26 -> 0 | I28: =I27+I26 -> 0 | J28: =J27+J26 -> 0 | ... AL28: =AL27+AL26 -> 0 | AN28: =E28 -> 0 | AO28: =H28 -> 0 | AP28: =K28 -> 0 | AQ28: =N28 -> 0 | AR28: =Q28 -> 0 | AS28: =T28 -> 0 | AT28: =W28 -> 0 | AU28: =Z28 -> 0 | AV28: =AC28 -> 0 | AW28: =AF28 -> 0 | AX28: =AI28 -> 0 | AY28: =AL28 -> 0 | BA28: =N28 -> 0 | BB28: =Z28 -> 0 | BC28: =AL28 -> 0

Sheet Balance Sheet
A1: AI API / Infrastructure — 3-Year Financial Model — Balance Sheet
A2: Assets = Liabilities + Equity every month, by construction.
A5: Line item | B5: Units / source | C5: Monthly (36 months) | AN5: Quarterly | BA5: Annual
C6: 46023 | D6: 46054 | E6: 46082 | F6: 46113 | G6: 46143 | H6: 46174 | I6: 46204 | J6: 46235 | K6: 46266 | L6: 46296 | M6: 46327 | N6: 46357 | O6: 46388 | P6: 46419 | Q6: 46447 | R6: 46478 | S6: 46508 | T6: 46539 | U6: 46569 | V6: 46600 | W6: 46631 | X6: 46661 | Y6: 46692 | Z6: 46722 | AA6: 46753 | AB6: 46784 | AC6: 46813 | AD6: 46844 | AE6: 46874 | AF6: 46905 | AG6: 46935 | AH6: 46966 | AI6: 46997 | AJ6: 47027 | AK6: 47058 | AL6: 47088 | AN6: Q1 | AO6: Q2 | AP6: Q3 | AQ6: Q4 | AR6: Q5 | AS6: Q6 | AT6: Q7 | AU6: Q8 | AV6: Q9 | AW6: Q10 | AX6: Q11 | AY6: Q12 | BA6: FY1 | BB6: FY2 | BC6: FY3
A7: Assets
A8: Cash & equivalents | B8: Linked from Cash Flow tab | C8: ='Cash Flow'!$C$28 -> 0 | D8: ='Cash Flow'!$D$28 -> 0 | E8: ='Cash Flow'!$E$28 -> 0 | F8: ='Cash Flow'!$F$28 -> 0 | G8: ='Cash Flow'!$G$28 -> 0 | H8: ='Cash Flow'!$H$28 -> 0 | I8: ='Cash Flow'!$I$28 -> 0 | J8: ='Cash Flow'!$J$28 -> 0 | K8: ='Cash Flow'!$K$28 -> 0 | L8: ='Cash Flow'!$L$28 -> 0 | M8: ='Cash Flow'!$M$28 -> 0 | N8: ='Cash Flow'!$N$28 -> 0 | O8: ='Cash Flow'!$O$28 -> 0 | P8: ='Cash Flow'!$P$28 -> 0 | Q8: ='Cash Flow'!$Q$28 -> 0 | R8: ='Cash Flow'!$R$28 -> 0 | S8: ='Cash Flow'!$S$28 -> 0 | T8: ='Cash Flow'!$T$28 -> 0 | U8: ='Cash Flow'!$U$28 -> 0 | V8: ='Cash Flow'!$V$28 -> 0 | W8: ='Cash Flow'!$W$28 -> 0 | X8: ='Cash Flow'!$X$28 -> 0 | Y8: ='Cash Flow'!$Y$28 -> 0 | Z8: ='Cash Flow'!$Z$28 -> 0 | AA8: ='Cash Flow'!$AA$28 -> 0 | AB8: ='Cash Flow'!$AB$28 -> 0 | AC8: ='Cash Flow'!$AC$28 -> 0 | AD8: ='Cash Flow'!$AD$28 -> 0 | AE8: ='Cash Flow'!$AE$28 -> 0 | AF8: ='Cash Flow'!$AF$28 -> 0 | AG8: ='Cash Flow'!$AG$28 -> 0 | AH8: ='Cash Flow'!$AH$28 -> 0 | AI8: ='Cash Flow'!$AI$28 -> 0 | AJ8: ='Cash Flow'!$AJ$28 -> 0 | AK8: ='Cash Flow'!$AK$28 -> 0 | AL8: ='Cash Flow'!$AL$28 -> 0 | AN8: =E8 -> 0 | AO8: =H8 -> 0 | AP8: =K8 -> 0 | AQ8: =N8 -> 0 | AR8: =Q8 -> 0 | AS8: =T8 -> 0 | AT8: =W8 -> 0 | AU8: =Z8 -> 0 | AV8: =AC8 -> 0 | AW8: =AF8 -> 0 | AX8: =AI8 -> 0 | AY8: =AL8 -> 0 | BA8: =N8 -> 0 | BB8: =Z8 -> 0 | BC8: =AL8 -> 0
A9: Accounts Receivable | C9: ='Working Capital'!$C$8 -> 0 | D9: ='Working Capital'!$D$8 -> 0 | E9: ='Working Capital'!$E$8 -> 0 | F9: ='Working Capital'!$F$8 -> 0 | G9: ='Working Capital'!$G$8 -> 0 | H9: ='Working Capital'!$H$8 -> 0 | I9: ='Working Capital'!$I$8 -> 0 | J9: ='Working Capital'!$J$8 -> 0 | K9: ='Working Capital'!$K$8 -> 0 | L9: ='Working Capital'!$L$8 -> 0 | M9: ='Working Capital'!$M$8 -> 0 | N9: ='Working Capital'!$N$8 -> 0 | O9: ='Working Capital'!$O$8 -> 0 | P9: ='Working Capital'!$P$8 -> 0 | Q9: ='Working Capital'!$Q$8 -> 0 | R9: ='Working Capital'!$R$8 -> 0 | S9: ='Working Capital'!$S$8 -> 0 | T9: ='Working Capital'!$T$8 -> 0 | U9: ='Working Capital'!$U$8 -> 0 | V9: ='Working Capital'!$V$8 -> 0 | W9: ='Working Capital'!$W$8 -> 0 | X9: ='Working Capital'!$X$8 -> 0 | Y9: ='Working Capital'!$Y$8 -> 0 | Z9: ='Working Capital'!$Z$8 -> 0 | AA9: ='Working Capital'!$AA$8 -> 0 | AB9: ='Working Capital'!$AB$8 -> 0 | AC9: ='Working Capital'!$AC$8 -> 0 | AD9: ='Working Capital'!$AD$8 -> 0 | AE9: ='Working Capital'!$AE$8 -> 0 | AF9: ='Working Capital'!$AF$8 -> 0 | AG9: ='Working Capital'!$AG$8 -> 0 | AH9: ='Working Capital'!$AH$8 -> 0 | AI9: ='Working Capital'!$AI$8 -> 0 | AJ9: ='Working Capital'!$AJ$8 -> 0 | AK9: ='Working Capital'!$AK$8 -> 0 | AL9: ='Working Capital'!$AL$8 -> 0 | AN9: =E9 -> 0 | AO9: =H9 -> 0 | AP9: =K9 -> 0 | AQ9: =N9 -> 0 | AR9: =Q9 -> 0 | AS9: =T9 -> 0 | AT9: =W9 -> 0 | AU9: =Z9 -> 0 | AV9: =AC9 -> 0 | AW9: =AF9 -> 0 | AX9: =AI9 -> 0 | AY9: =AL9 -> 0 | BA9: =N9 -> 0 | BB9: =Z9 -> 0 | BC9: =AL9 -> 0
A10: Other Current Assets (prepaid, etc.) | B10: Linked from Working Capital tab | C10: ='Working Capital'!C11 -> 0 | D10: ='Working Capital'!D11 -> 0 | E10: ='Working Capital'!E11 -> 0 | F10: ='Working Capital'!F11 -> 0 | G10: ='Working Capital'!G11 -> 0 | H10: ='Working Capital'!H11 -> 0 | I10: ='Working Capital'!I11 -> 0 | J10: ='Working Capital'!J11 -> 0 | ... AL10: ='Working Capital'!AL11 -> 0 | AN10: =E10 -> 0 | AO10: =H10 -> 0 | AP10: =K10 -> 0 | AQ10: =N10 -> 0 | AR10: =Q10 -> 0 | AS10: =T10 -> 0 | AT10: =W10 -> 0 | AU10: =Z10 -> 0 | AV10: =AC10 -> 0 | AW10: =AF10 -> 0 | AX10: =AI10 -> 0 | AY10: =AL10 -> 0 | BA10: =N10 -> 0 | BB10: =Z10 -> 0 | BC10: =AL10 -> 0
A11: Net PP&E | C11: ='Working Capital'!$C$20 -> 0 | D11: ='Working Capital'!$D$20 -> 0 | E11: ='Working Capital'!$E$20 -> 0 | F11: ='Working Capital'!$F$20 -> 0 | G11: ='Working Capital'!$G$20 -> 0 | H11: ='Working Capital'!$H$20 -> 0 | I11: ='Working Capital'!$I$20 -> 0 | J11: ='Working Capital'!$J$20 -> 0 | K11: ='Working Capital'!$K$20 -> 0 | L11: ='Working Capital'!$L$20 -> 0 | M11: ='Working Capital'!$M$20 -> 0 | N11: ='Working Capital'!$N$20 -> 0 | O11: ='Working Capital'!$O$20 -> 0 | P11: ='Working Capital'!$P$20 -> 0 | Q11: ='Working Capital'!$Q$20 -> 0 | R11: ='Working Capital'!$R$20 -> 0 | S11: ='Working Capital'!$S$20 -> 0 | T11: ='Working Capital'!$T$20 -> 0 | U11: ='Working Capital'!$U$20 -> 0 | V11: ='Working Capital'!$V$20 -> 0 | W11: ='Working Capital'!$W$20 -> 0 | X11: ='Working Capital'!$X$20 -> 0 | Y11: ='Working Capital'!$Y$20 -> 0 | Z11: ='Working Capital'!$Z$20 -> 0 | AA11: ='Working Capital'!$AA$20 -> 0 | AB11: ='Working Capital'!$AB$20 -> 0 | AC11: ='Working Capital'!$AC$20 -> 0 | AD11: ='Working Capital'!$AD$20 -> 0 | AE11: ='Working Capital'!$AE$20 -> 0 | AF11: ='Working Capital'!$AF$20 -> 0 | AG11: ='Working Capital'!$AG$20 -> 0 | AH11: ='Working Capital'!$AH$20 -> 0 | AI11: ='Working Capital'!$AI$20 -> 0 | AJ11: ='Working Capital'!$AJ$20 -> 0 | AK11: ='Working Capital'!$AK$20 -> 0 | AL11: ='Working Capital'!$AL$20 -> 0 | AN11: =E11 -> 0 | AO11: =H11 -> 0 | AP11: =K11 -> 0 | AQ11: =N11 -> 0 | AR11: =Q11 -> 0 | AS11: =T11 -> 0 | AT11: =W11 -> 0 | AU11: =Z11 -> 0 | AV11: =AC11 -> 0 | AW11: =AF11 -> 0 | AX11: =AI11 -> 0 | AY11: =AL11 -> 0 | BA11: =N11 -> 0 | BB11: =Z11 -> 0 | BC11: =AL11 -> 0
A12: Total Assets | C12: =C8+C9+C10+C11 -> 0 | D12: =D8+D9+D10+D11 -> 0 | E12: =E8+E9+E10+E11 -> 0 | F12: =F8+F9+F10+F11 -> 0 | G12: =G8+G9+G10+G11 -> 0 | H12: =H8+H9+H10+H11 -> 0 | I12: =I8+I9+I10+I11 -> 0 | J12: =J8+J9+J10+J11 -> 0 | ... AL12: =AL8+AL9+AL10+AL11 -> 0 | AN12: =E12 -> 0 | AO12: =H12 -> 0 | AP12: =K12 -> 0 | AQ12: =N12 -> 0 | AR12: =Q12 -> 0 | AS12: =T12 -> 0 | AT12: =W12 -> 0 | AU12: =Z12 -> 0 | AV12: =AC12 -> 0 | AW12: =AF12 -> 0 | AX12: =AI12 -> 0 | AY12: =AL12 -> 0 | BA12: =N12 -> 0 | BB12: =Z12 -> 0 | BC12: =AL12 -> 0
A14: Liabilities
A15: Accounts Payable | C15: ='Working Capital'!$C$9 -> 0 | D15: ='Working Capital'!$D$9 -> 0 | E15: ='Working Capital'!$E$9 -> 0 | F15: ='Working Capital'!$F$9 -> 0 | G15: ='Working Capital'!$G$9 -> 0 | H15: ='Working Capital'!$H$9 -> 0 | I15: ='Working Capital'!$I$9 -> 0 | J15: ='Working Capital'!$J$9 -> 0 | K15: ='Working Capital'!$K$9 -> 0 | L15: ='Working Capital'!$L$9 -> 0 | M15: ='Working Capital'!$M$9 -> 0 | N15: ='Working Capital'!$N$9 -> 0 | O15: ='Working Capital'!$O$9 -> 0 | P15: ='Working Capital'!$P$9 -> 0 | Q15: ='Working Capital'!$Q$9 -> 0 | R15: ='Working Capital'!$R$9 -> 0 | S15: ='Working Capital'!$S$9 -> 0 | T15: ='Working Capital'!$T$9 -> 0 | U15: ='Working Capital'!$U$9 -> 0 | V15: ='Working Capital'!$V$9 -> 0 | W15: ='Working Capital'!$W$9 -> 0 | X15: ='Working Capital'!$X$9 -> 0 | Y15: ='Working Capital'!$Y$9 -> 0 | Z15: ='Working Capital'!$Z$9 -> 0 | AA15: ='Working Capital'!$AA$9 -> 0 | AB15: ='Working Capital'!$AB$9 -> 0 | AC15: ='Working Capital'!$AC$9 -> 0 | AD15: ='Working Capital'!$AD$9 -> 0 | AE15: ='Working Capital'!$AE$9 -> 0 | AF15: ='Working Capital'!$AF$9 -> 0 | AG15: ='Working Capital'!$AG$9 -> 0 | AH15: ='Working Capital'!$AH$9 -> 0 | AI15: ='Working Capital'!$AI$9 -> 0 | AJ15: ='Working Capital'!$AJ$9 -> 0 | AK15: ='Working Capital'!$AK$9 -> 0 | AL15: ='Working Capital'!$AL$9 -> 0 | AN15: =E15 -> 0 | AO15: =H15 -> 0 | AP15: =K15 -> 0 | AQ15: =N15 -> 0 | AR15: =Q15 -> 0 | AS15: =T15 -> 0 | AT15: =W15 -> 0 | AU15: =Z15 -> 0 | AV15: =AC15 -> 0 | AW15: =AF15 -> 0 | AX15: =AI15 -> 0 | AY15: =AL15 -> 0 | BA15: =N15 -> 0 | BB15: =Z15 -> 0 | BC15: =AL15 -> 0
A16: Deferred Revenue | C16: ='Working Capital'!$C$10 -> 0 | D16: ='Working Capital'!$D$10 -> 0 | E16: ='Working Capital'!$E$10 -> 0 | F16: ='Working Capital'!$F$10 -> 0 | G16: ='Working Capital'!$G$10 -> 0 | H16: ='Working Capital'!$H$10 -> 0 | I16: ='Working Capital'!$I$10 -> 0 | J16: ='Working Capital'!$J$10 -> 0 | K16: ='Working Capital'!$K$10 -> 0 | L16: ='Working Capital'!$L$10 -> 0 | M16: ='Working Capital'!$M$10 -> 0 | N16: ='Working Capital'!$N$10 -> 0 | O16: ='Working Capital'!$O$10 -> 0 | P16: ='Working Capital'!$P$10 -> 0 | Q16: ='Working Capital'!$Q$10 -> 0 | R16: ='Working Capital'!$R$10 -> 0 | S16: ='Working Capital'!$S$10 -> 0 | T16: ='Working Capital'!$T$10 -> 0 | U16: ='Working Capital'!$U$10 -> 0 | V16: ='Working Capital'!$V$10 -> 0 | W16: ='Working Capital'!$W$10 -> 0 | X16: ='Working Capital'!$X$10 -> 0 | Y16: ='Working Capital'!$Y$10 -> 0 | Z16: ='Working Capital'!$Z$10 -> 0 | AA16: ='Working Capital'!$AA$10 -> 0 | AB16: ='Working Capital'!$AB$10 -> 0 | AC16: ='Working Capital'!$AC$10 -> 0 | AD16: ='Working Capital'!$AD$10 -> 0 | AE16: ='Working Capital'!$AE$10 -> 0 | AF16: ='Working Capital'!$AF$10 -> 0 | AG16: ='Working Capital'!$AG$10 -> 0 | AH16: ='Working Capital'!$AH$10 -> 0 | AI16: ='Working Capital'!$AI$10 -> 0 | AJ16: ='Working Capital'!$AJ$10 -> 0 | AK16: ='Working Capital'!$AK$10 -> 0 | AL16: ='Working Capital'!$AL$10 -> 0 | AN16: =E16 -> 0 | AO16: =H16 -> 0 | AP16: =K16 -> 0 | AQ16: =N16 -> 0 | AR16: =Q16 -> 0 | AS16: =T16 -> 0 | AT16: =W16 -> 0 | AU16: =Z16 -> 0 | AV16: =AC16 -> 0 | AW16: =AF16 -> 0 | AX16: =AI16 -> 0 | AY16: =AL16 -> 0 | BA16: =N16 -> 0 | BB16: =Z16 -> 0 | BC16: =AL16 -> 0
A17: Debt | C17: ='Working Capital'!$C$25 -> 0 | D17: ='Working Capital'!$D$25 -> 0 | E17: ='Working Capital'!$E$25 -> 0 | F17: ='Working Capital'!$F$25 -> 0 | G17: ='Working Capital'!$G$25 -> 0 | H17: ='Working Capital'!$H$25 -> 0 | I17: ='Working Capital'!$I$25 -> 0 | J17: ='Working Capital'!$J$25 -> 0 | K17: ='Working Capital'!$K$25 -> 0 | L17: ='Working Capital'!$L$25 -> 0 | M17: ='Working Capital'!$M$25 -> 0 | N17: ='Working Capital'!$N$25 -> 0 | O17: ='Working Capital'!$O$25 -> 0 | P17: ='Working Capital'!$P$25 -> 0 | Q17: ='Working Capital'!$Q$25 -> 0 | R17: ='Working Capital'!$R$25 -> 0 | S17: ='Working Capital'!$S$25 -> 0 | T17: ='Working Capital'!$T$25 -> 0 | U17: ='Working Capital'!$U$25 -> 0 | V17: ='Working Capital'!$V$25 -> 0 | W17: ='Working Capital'!$W$25 -> 0 | X17: ='Working Capital'!$X$25 -> 0 | Y17: ='Working Capital'!$Y$25 -> 0 | Z17: ='Working Capital'!$Z$25 -> 0 | AA17: ='Working Capital'!$AA$25 -> 0 | AB17: ='Working Capital'!$AB$25 -> 0 | AC17: ='Working Capital'!$AC$25 -> 0 | AD17: ='Working Capital'!$AD$25 -> 0 | AE17: ='Working Capital'!$AE$25 -> 0 | AF17: ='Working Capital'!$AF$25 -> 0 | AG17: ='Working Capital'!$AG$25 -> 0 | AH17: ='Working Capital'!$AH$25 -> 0 | AI17: ='Working Capital'!$AI$25 -> 0 | AJ17: ='Working Capital'!$AJ$25 -> 0 | AK17: ='Working Capital'!$AK$25 -> 0 | AL17: ='Working Capital'!$AL$25 -> 0 | AN17: =E17 -> 0 | AO17: =H17 -> 0 | AP17: =K17 -> 0 | AQ17: =N17 -> 0 | AR17: =Q17 -> 0 | AS17: =T17 -> 0 | AT17: =W17 -> 0 | AU17: =Z17 -> 0 | AV17: =AC17 -> 0 | AW17: =AF17 -> 0 | AX17: =AI17 -> 0 | AY17: =AL17 -> 0 | BA17: =N17 -> 0 | BB17: =Z17 -> 0 | BC17: =AL17 -> 0
A18: Total Liabilities | C18: =C15+C16+C17 -> 0 | D18: =D15+D16+D17 -> 0 | E18: =E15+E16+E17 -> 0 | F18: =F15+F16+F17 -> 0 | G18: =G15+G16+G17 -> 0 | H18: =H15+H16+H17 -> 0 | I18: =I15+I16+I17 -> 0 | J18: =J15+J16+J17 -> 0 | ... AL18: =AL15+AL16+AL17 -> 0 | AN18: =E18 -> 0 | AO18: =H18 -> 0 | AP18: =K18 -> 0 | AQ18: =N18 -> 0 | AR18: =Q18 -> 0 | AS18: =T18 -> 0 | AT18: =W18 -> 0 | AU18: =Z18 -> 0 | AV18: =AC18 -> 0 | AW18: =AF18 -> 0 | AX18: =AI18 -> 0 | AY18: =AL18 -> 0 | BA18: =N18 -> 0 | BB18: =Z18 -> 0 | BC18: =AL18 -> 0
A20: Equity
A21: Paid-in Capital | B21: Starting paid-in capital + cumulative equity raised | C21: ='Assumptions'!$F$9+'Working Capital'!C30 -> 0 | D21: ='Assumptions'!$F$9+'Working Capital'!D30 -> 0 | E21: ='Assumptions'!$F$9+'Working Capital'!E30 -> 0 | F21: ='Assumptions'!$F$9+'Working Capital'!F30 -> 0 | G21: ='Assumptions'!$F$9+'Working Capital'!G30 -> 0 | H21: ='Assumptions'!$F$9+'Working Capital'!H30 -> 0 | I21: ='Assumptions'!$F$9+'Working Capital'!I30 -> 0 | J21: ='Assumptions'!$F$9+'Working Capital'!J30 -> 0 | ... AL21: ='Assumptions'!$F$9+'Working Capital'!AL30 -> 0 | AN21: =E21 -> 0 | AO21: =H21 -> 0 | AP21: =K21 -> 0 | AQ21: =N21 -> 0 | AR21: =Q21 -> 0 | AS21: =T21 -> 0 | AT21: =W21 -> 0 | AU21: =Z21 -> 0 | AV21: =AC21 -> 0 | AW21: =AF21 -> 0 | AX21: =AI21 -> 0 | AY21: =AL21 -> 0 | BA21: =N21 -> 0 | BB21: =Z21 -> 0 | BC21: =AL21 -> 0
A22: Retained Earnings | B22: Starting RE (= starting cash − starting paid-in capital) + cumulative Net Income | C22: =('Assumptions'!$F$8-'Assumptions'!$F$9)+'P&L'!C24 -> 0 | D22: =C22+'P&L'!D24 -> 0 | E22: =D22+'P&L'!E24 -> 0 | F22: =E22+'P&L'!F24 -> 0 | G22: =F22+'P&L'!G24 -> 0 | H22: =G22+'P&L'!H24 -> 0 | I22: =H22+'P&L'!I24 -> 0 | J22: =I22+'P&L'!J24 -> 0 | K22: =J22+'P&L'!K24 -> 0 | ... AL22: =AK22+'P&L'!AL24 -> 0 | AN22: =E22 -> 0 | AO22: =H22 -> 0 | AP22: =K22 -> 0 | AQ22: =N22 -> 0 | AR22: =Q22 -> 0 | AS22: =T22 -> 0 | AT22: =W22 -> 0 | AU22: =Z22 -> 0 | AV22: =AC22 -> 0 | AW22: =AF22 -> 0 | AX22: =AI22 -> 0 | AY22: =AL22 -> 0 | BA22: =N22 -> 0 | BB22: =Z22 -> 0 | BC22: =AL22 -> 0
A23: Total Equity | C23: =C21+C22 -> 0 | D23: =D21+D22 -> 0 | E23: =E21+E22 -> 0 | F23: =F21+F22 -> 0 | G23: =G21+G22 -> 0 | H23: =H21+H22 -> 0 | I23: =I21+I22 -> 0 | J23: =J21+J22 -> 0 | ... AL23: =AL21+AL22 -> 0 | AN23: =E23 -> 0 | AO23: =H23 -> 0 | AP23: =K23 -> 0 | AQ23: =N23 -> 0 | AR23: =Q23 -> 0 | AS23: =T23 -> 0 | AT23: =W23 -> 0 | AU23: =Z23 -> 0 | AV23: =AC23 -> 0 | AW23: =AF23 -> 0 | AX23: =AI23 -> 0 | AY23: =AL23 -> 0 | BA23: =N23 -> 0 | BB23: =Z23 -> 0 | BC23: =AL23 -> 0
A24: Total Liabilities + Equity | C24: =C18+C23 -> 0 | D24: =D18+D23 -> 0 | E24: =E18+E23 -> 0 | F24: =F18+F23 -> 0 | G24: =G18+G23 -> 0 | H24: =H18+H23 -> 0 | I24: =I18+I23 -> 0 | J24: =J18+J23 -> 0 | ... AL24: =AL18+AL23 -> 0 | AN24: =E24 -> 0 | AO24: =H24 -> 0 | AP24: =K24 -> 0 | AQ24: =N24 -> 0 | AR24: =Q24 -> 0 | AS24: =T24 -> 0 | AT24: =W24 -> 0 | AU24: =Z24 -> 0 | AV24: =AC24 -> 0 | AW24: =AF24 -> 0 | AX24: =AI24 -> 0 | AY24: =AL24 -> 0 | BA24: =N24 -> 0 | BB24: =Z24 -> 0 | BC24: =AL24 -> 0
A26: Balance check (Assets − Liab&Equity) | B26: Must equal ~0 every month | C26: =C12-C24 -> 0 | D26: =D12-D24 -> 0 | E26: =E12-E24 -> 0 | F26: =F12-F24 -> 0 | G26: =G12-G24 -> 0 | H26: =H12-H24 -> 0 | I26: =I12-I24 -> 0 | J26: =J12-J24 -> 0 | ... AL26: =AL12-AL24 -> 0 | AN26: =E26 -> 0 | AO26: =H26 -> 0 | AP26: =K26 -> 0 | AQ26: =N26 -> 0 | AR26: =Q26 -> 0 | AS26: =T26 -> 0 | AT26: =W26 -> 0 | AU26: =Z26 -> 0 | AV26: =AC26 -> 0 | AW26: =AF26 -> 0 | AX26: =AI26 -> 0 | AY26: =AL26 -> 0 | BA26: =N26 -> 0 | BB26: =Z26 -> 0 | BC26: =AL26 -> 0

Sheet Cash & Runway
A1: AI API / Infrastructure — 3-Year Financial Model — Cash & Runway
A2: Burn rate and runway — reconciled to the Cash Flow tab.
A5: Line item | B5: Units / source | C5: Monthly (36 months) | AN5: Quarterly | BA5: Annual
C6: 46023 | D6: 46054 | E6: 46082 | F6: 46113 | G6: 46143 | H6: 46174 | I6: 46204 | J6: 46235 | K6: 46266 | L6: 46296 | M6: 46327 | N6: 46357 | O6: 46388 | P6: 46419 | Q6: 46447 | R6: 46478 | S6: 46508 | T6: 46539 | U6: 46569 | V6: 46600 | W6: 46631 | X6: 46661 | Y6: 46692 | Z6: 46722 | AA6: 46753 | AB6: 46784 | AC6: 46813 | AD6: 46844 | AE6: 46874 | AF6: 46905 | AG6: 46935 | AH6: 46966 | AI6: 46997 | AJ6: 47027 | AK6: 47058 | AL6: 47088 | AN6: Q1 | AO6: Q2 | AP6: Q3 | AQ6: Q4 | AR6: Q5 | AS6: Q6 | AT6: Q7 | AU6: Q8 | AV6: Q9 | AW6: Q10 | AX6: Q11 | AY6: Q12 | BA6: FY1 | BB6: FY2 | BC6: FY3
A7: Cash Position
A8: Ending Cash Balance | C8: ='Cash Flow'!$C$28 -> 0 | D8: ='Cash Flow'!$D$28 -> 0 | E8: ='Cash Flow'!$E$28 -> 0 | F8: ='Cash Flow'!$F$28 -> 0 | G8: ='Cash Flow'!$G$28 -> 0 | H8: ='Cash Flow'!$H$28 -> 0 | I8: ='Cash Flow'!$I$28 -> 0 | J8: ='Cash Flow'!$J$28 -> 0 | K8: ='Cash Flow'!$K$28 -> 0 | L8: ='Cash Flow'!$L$28 -> 0 | M8: ='Cash Flow'!$M$28 -> 0 | N8: ='Cash Flow'!$N$28 -> 0 | O8: ='Cash Flow'!$O$28 -> 0 | P8: ='Cash Flow'!$P$28 -> 0 | Q8: ='Cash Flow'!$Q$28 -> 0 | R8: ='Cash Flow'!$R$28 -> 0 | S8: ='Cash Flow'!$S$28 -> 0 | T8: ='Cash Flow'!$T$28 -> 0 | U8: ='Cash Flow'!$U$28 -> 0 | V8: ='Cash Flow'!$V$28 -> 0 | W8: ='Cash Flow'!$W$28 -> 0 | X8: ='Cash Flow'!$X$28 -> 0 | Y8: ='Cash Flow'!$Y$28 -> 0 | Z8: ='Cash Flow'!$Z$28 -> 0 | AA8: ='Cash Flow'!$AA$28 -> 0 | AB8: ='Cash Flow'!$AB$28 -> 0 | AC8: ='Cash Flow'!$AC$28 -> 0 | AD8: ='Cash Flow'!$AD$28 -> 0 | AE8: ='Cash Flow'!$AE$28 -> 0 | AF8: ='Cash Flow'!$AF$28 -> 0 | AG8: ='Cash Flow'!$AG$28 -> 0 | AH8: ='Cash Flow'!$AH$28 -> 0 | AI8: ='Cash Flow'!$AI$28 -> 0 | AJ8: ='Cash Flow'!$AJ$28 -> 0 | AK8: ='Cash Flow'!$AK$28 -> 0 | AL8: ='Cash Flow'!$AL$28 -> 0 | AN8: =E8 -> 0 | AO8: =H8 -> 0 | AP8: =K8 -> 0 | AQ8: =N8 -> 0 | AR8: =Q8 -> 0 | AS8: =T8 -> 0 | AT8: =W8 -> 0 | AU8: =Z8 -> 0 | AV8: =AC8 -> 0 | AW8: =AF8 -> 0 | AX8: =AI8 -> 0 | AY8: =AL8 -> 0 | BA8: =N8 -> 0 | BB8: =Z8 -> 0 | BC8: =AL8 -> 0
A9: Monthly Net Burn (pre-financing) | B9: MAX(0, −(operating + investing cash flow)); excludes debt and equity proceeds | C9: =MAX(0,-('Cash Flow'!C14+'Cash Flow'!C18)) -> 0 | D9: =MAX(0,-('Cash Flow'!D14+'Cash Flow'!D18)) -> 0 | E9: =MAX(0,-('Cash Flow'!E14+'Cash Flow'!E18)) -> 0 | F9: =MAX(0,-('Cash Flow'!F14+'Cash Flow'!F18)) -> 0 | G9: =MAX(0,-('Cash Flow'!G14+'Cash Flow'!G18)) -> 0 | H9: =MAX(0,-('Cash Flow'!H14+'Cash Flow'!H18)) -> 0 | I9: =MAX(0,-('Cash Flow'!I14+'Cash Flow'!I18)) -> 0 | J9: =MAX(0,-('Cash Flow'!J14+'Cash Flow'!J18)) -> 0 | ... AL9: =MAX(0,-('Cash Flow'!AL14+'Cash Flow'!AL18)) -> 0 | AN9: =SUM(C9:E9) -> 0 | AO9: =SUM(F9:H9) -> 0 | AP9: =SUM(I9:K9) -> 0 | AQ9: =SUM(L9:N9) -> 0 | AR9: =SUM(O9:Q9) -> 0 | AS9: =SUM(R9:T9) -> 0 | AT9: =SUM(U9:W9) -> 0 | AU9: =SUM(X9:Z9) -> 0 | AV9: =SUM(AA9:AC9) -> 0 | AW9: =SUM(AD9:AF9) -> 0 | AX9: =SUM(AG9:AI9) -> 0 | AY9: =SUM(AJ9:AL9) -> 0 | BA9: =SUM(C9:N9) -> 0 | BB9: =SUM(O9:Z9) -> 0 | BC9: =SUM(AA9:AL9) -> 0
A10: Trailing 3-Month Avg Burn | C10: =AVERAGE(C9:C9) -> 0 | D10: =AVERAGE(C9:D9) -> 0 | E10: =AVERAGE(C9:E9) -> 0 | F10: =AVERAGE(D9:F9) -> 0 | G10: =AVERAGE(E9:G9) -> 0 | H10: =AVERAGE(F9:H9) -> 0 | I10: =AVERAGE(G9:I9) -> 0 | J10: =AVERAGE(H9:J9) -> 0 | K10: =AVERAGE(I9:K9) -> 0 | L10: =AVERAGE(J9:L9) -> 0 | ... AL10: =AVERAGE(AJ9:AL9) -> 0 | AN10: =AVERAGE(C10:E10) -> 0 | AO10: =AVERAGE(F10:H10) -> 0 | AP10: =AVERAGE(I10:K10) -> 0 | AQ10: =AVERAGE(L10:N10) -> 0 | AR10: =AVERAGE(O10:Q10) -> 0 | AS10: =AVERAGE(R10:T10) -> 0 | AT10: =AVERAGE(U10:W10) -> 0 | AU10: =AVERAGE(X10:Z10) -> 0 | AV10: =AVERAGE(AA10:AC10) -> 0 | AW10: =AVERAGE(AD10:AF10) -> 0 | AX10: =AVERAGE(AG10:AI10) -> 0 | AY10: =AVERAGE(AJ10:AL10) -> 0 | BA10: =AVERAGE(C10:N10) -> 0 | BB10: =AVERAGE(O10:Z10) -> 0 | BC10: =AVERAGE(AA10:AL10) -> 0
A11: Runway (months) | B11: Ending cash ÷ trailing 3-month pre-financing burn; 0 if cash is depleted; 999 if cash-flow positive | C11: =IF(C8<=0,0,IF(C10<=0,999,C8/C10)) -> 0 | D11: =IF(D8<=0,0,IF(D10<=0,999,D8/D10)) -> 0 | E11: =IF(E8<=0,0,IF(E10<=0,999,E8/E10)) -> 0 | F11: =IF(F8<=0,0,IF(F10<=0,999,F8/F10)) -> 0 | G11: =IF(G8<=0,0,IF(G10<=0,999,G8/G10)) -> 0 | H11: =IF(H8<=0,0,IF(H10<=0,999,H8/H10)) -> 0 | I11: =IF(I8<=0,0,IF(I10<=0,999,I8/I10)) -> 0 | J11: =IF(J8<=0,0,IF(J10<=0,999,J8/J10)) -> 0 | ... AL11: =IF(AL8<=0,0,IF(AL10<=0,999,AL8/AL10)) -> 0 | AN11: =E11 -> 0 | AO11: =H11 -> 0 | AP11: =K11 -> 0 | AQ11: =N11 -> 0 | AR11: =Q11 -> 0 | AS11: =T11 -> 0 | AT11: =W11 -> 0 | AU11: =Z11 -> 0 | AV11: =AC11 -> 0 | AW11: =AF11 -> 0 | AX11: =AI11 -> 0 | AY11: =AL11 -> 0 | BA11: =N11 -> 0 | BB11: =Z11 -> 0 | BC11: =AL11 -> 0
A13: Headline
A14: Runway as of final month (36) | C14: =IF(AL8<=0,0,IF(AL10<=0,"Cash-flow positive",AL11)) -> 0

Sheet Scenarios
A1: AI API / Infrastructure — 3-Year Financial Model — Scenario Comparison
A2: Base/Upside/Downside columns are a fast analytical approximation for side-by-side comparison. The 'Full model' column reflects the detailed 36-month model at the scenario currently selected on the Assumptions tab.
A4: Currently selected scenario: | C4: ='Assumptions'!$C$4 -> 0
A6: KPI | B6: Definition | C6: Base | D6: Upside | E6: Downside | F6: Full model (selected)
A7: Starting billable volume (Month 1) | B7: Month-1 gross request volume reduced for cache credits and batch discounts. | C7: =((('Assumptions'!$C$13+'Assumptions'!$C$14-'Assumptions'!$C$13*'Assumptions'!$C$16)*'Assumptions'!$C$17+('Assumptions'!$C$19+'Assumptions'!$C$20-'Assumptions'!$C$19*'Assumptions'!$C$22)*'Assumptions'!$C$23+('Assumptions'!$C$25+'Assumptions'!$C$26-'Assumptions'!$C$25*'Assumptions'!$C$28)*'Assumptions'!$C$29))*((1-'Assumptions'!$C$41*'Assumptions'!$C$42)*(1-'Assumptions'!$C$43)) -> 0 | D7: =((('Assumptions'!$D$13+'Assumptions'!$D$14-'Assumptions'!$D$13*'Assumptions'!$D$16)*'Assumptions'!$D$17+('Assumptions'!$D$19+'Assumptions'!$D$20-'Assumptions'!$D$19*'Assumptions'!$D$22)*'Assumptions'!$D$23+('Assumptions'!$D$25+'Assumptions'!$D$26-'Assumptions'!$D$25*'Assumptions'!$D$28)*'Assumptions'!$D$29))*((1-'Assumptions'!$D$41*'Assumptions'!$D$42)*(1-'Assumptions'!$D$43)) -> 0 | E7: =((('Assumptions'!$E$13+'Assumptions'!$E$14-'Assumptions'!$E$13*'Assumptions'!$E$16)*'Assumptions'!$E$17+('Assumptions'!$E$19+'Assumptions'!$E$20-'Assumptions'!$E$19*'Assumptions'!$E$22)*'Assumptions'!$E$23+('Assumptions'!$E$25+'Assumptions'!$E$26-'Assumptions'!$E$25*'Assumptions'!$E$28)*'Assumptions'!$E$29))*((1-'Assumptions'!$E$41*'Assumptions'!$E$42)*(1-'Assumptions'!$E$43)) -> 0 | F7: ='Revenue'!C56 -> 0
A8: Revenue run-rate (Month 1 x 12) | B8: Month-1 total revenue annualized for a simple run-rate comparison. | C8: =((((('Assumptions'!$C$13+'Assumptions'!$C$14-'Assumptions'!$C$13*'Assumptions'!$C$16)*'Assumptions'!$C$17)*((1-'Assumptions'!$C$41*'Assumptions'!$C$42)*(1-'Assumptions'!$C$43))*((('Assumptions'!$C$33*(1-'Assumptions'!$C$35)+'Assumptions'!$C$34*'Assumptions'!$C$35))*(1-'Assumptions'!$C$40)*'Assumptions'!$C$37)+(('Assumptions'!$C$19+'Assumptions'!$C$20-'Assumptions'!$C$19*'Assumptions'!$C$22)*'Assumptions'!$C$23)*((1-'Assumptions'!$C$41*'Assumptions'!$C$42)*(1-'Assumptions'!$C$43))*((('Assumptions'!$C$33*(1-'Assumptions'!$C$35)+'Assumptions'!$C$34*'Assumptions'!$C$35))*(1-'Assumptions'!$C$40)*'Assumptions'!$C$38)+(('Assumptions'!$C$25+'Assumptions'!$C$26-'Assumptions'!$C$25*'Assumptions'!$C$28)*'Assumptions'!$C$29)*((1-'Assumptions'!$C$41*'Assumptions'!$C$42)*(1-'Assumptions'!$C$43))*((('Assumptions'!$C$33*(1-'Assumptions'!$C$35)+'Assumptions'!$C$34*'Assumptions'!$C$35))*(1-'Assumptions'!$C$40)*'Assumptions'!$C$39)))+((('Assumptions'!$C$13+'Assumptions'!$C$14-'Assumptions'!$C$13*'Assumptions'!$C$16)*'Assumptions'!$C$44+('Assumptions'!$C$19+'Assumptions'!$C$20-'Assumptions'!$C$19*'Assumptions'!$C$22)*'Assumptions'!$C$45+('Assumptions'!$C$25+'Assumptions'!$C$26-'Assumptions'!$C$25*'Assumptions'!$C$28)*'Assumptions'!$C$46)))*12 -> 0 | D8: =((((('Assumptions'!$D$13+'Assumptions'!$D$14-'Assumptions'!$D$13*'Assumptions'!$D$16)*'Assumptions'!$D$17)*((1-'Assumptions'!$D$41*'Assumptions'!$D$42)*(1-'Assumptions'!$D$43))*((('Assumptions'!$D$33*(1-'Assumptions'!$D$35)+'Assumptions'!$D$34*'Assumptions'!$D$35))*(1-'Assumptions'!$D$40)*'Assumptions'!$D$37)+(('Assumptions'!$D$19+'Assumptions'!$D$20-'Assumptions'!$D$19*'Assumptions'!$D$22)*'Assumptions'!$D$23)*((1-'Assumptions'!$D$41*'Assumptions'!$D$42)*(1-'Assumptions'!$D$43))*((('Assumptions'!$D$33*(1-'Assumptions'!$D$35)+'Assumptions'!$D$34*'Assumptions'!$D$35))*(1-'Assumptions'!$D$40)*'Assumptions'!$D$38)+(('Assumptions'!$D$25+'Assumptions'!$D$26-'Assumptions'!$D$25*'Assumptions'!$D$28)*'Assumptions'!$D$29)*((1-'Assumptions'!$D$41*'Assumptions'!$D$42)*(1-'Assumptions'!$D$43))*((('Assumptions'!$D$33*(1-'Assumptions'!$D$35)+'Assumptions'!$D$34*'Assumptions'!$D$35))*(1-'Assumptions'!$D$40)*'Assumptions'!$D$39)))+((('Assumptions'!$D$13+'Assumptions'!$D$14-'Assumptions'!$D$13*'Assumptions'!$D$16)*'Assumptions'!$D$44+('Assumptions'!$D$19+'Assumptions'!$D$20-'Assumptions'!$D$19*'Assumptions'!$D$22)*'Assumptions'!$D$45+('Assumptions'!$D$25+'Assumptions'!$D$26-'Assumptions'!$D$25*'Assumptions'!$D$28)*'Assumptions'!$D$46)))*12 -> 0 | E8: =((((('Assumptions'!$E$13+'Assumptions'!$E$14-'Assumptions'!$E$13*'Assumptions'!$E$16)*'Assumptions'!$E$17)*((1-'Assumptions'!$E$41*'Assumptions'!$E$42)*(1-'Assumptions'!$E$43))*((('Assumptions'!$E$33*(1-'Assumptions'!$E$35)+'Assumptions'!$E$34*'Assumptions'!$E$35))*(1-'Assumptions'!$E$40)*'Assumptions'!$E$37)+(('Assumptions'!$E$19+'Assumptions'!$E$20-'Assumptions'!$E$19*'Assumptions'!$E$22)*'Assumptions'!$E$23)*((1-'Assumptions'!$E$41*'Assumptions'!$E$42)*(1-'Assumptions'!$E$43))*((('Assumptions'!$E$33*(1-'Assumptions'!$E$35)+'Assumptions'!$E$34*'Assumptions'!$E$35))*(1-'Assumptions'!$E$40)*'Assumptions'!$E$38)+(('Assumptions'!$E$25+'Assumptions'!$E$26-'Assumptions'!$E$25*'Assumptions'!$E$28)*'Assumptions'!$E$29)*((1-'Assumptions'!$E$41*'Assumptions'!$E$42)*(1-'Assumptions'!$E$43))*((('Assumptions'!$E$33*(1-'Assumptions'!$E$35)+'Assumptions'!$E$34*'Assumptions'!$E$35))*(1-'Assumptions'!$E$40)*'Assumptions'!$E$39)))+((('Assumptions'!$E$13+'Assumptions'!$E$14-'Assumptions'!$E$13*'Assumptions'!$E$16)*'Assumptions'!$E$44+('Assumptions'!$E$19+'Assumptions'!$E$20-'Assumptions'!$E$19*'Assumptions'!$E$22)*'Assumptions'!$E$45+('Assumptions'!$E$25+'Assumptions'!$E$26-'Assumptions'!$E$25*'Assumptions'!$E$28)*'Assumptions'!$E$46)))*12 -> 0 | F8: ='Revenue'!C60*12 -> 0
A9: Implied Revenue at Month 36 (approx.) | B9: Month-1 revenue compounded at an illustrative blended growth rate for 35 more months. | C9: =((((('Assumptions'!$C$13+'Assumptions'!$C$14-'Assumptions'!$C$13*'Assumptions'!$C$16)*'Assumptions'!$C$17)*((1-'Assumptions'!$C$41*'Assumptions'!$C$42)*(1-'Assumptions'!$C$43))*((('Assumptions'!$C$33*(1-'Assumptions'!$C$35)+'Assumptions'!$C$34*'Assumptions'!$C$35))*(1-'Assumptions'!$C$40)*'Assumptions'!$C$37)+(('Assumptions'!$C$19+'Assumptions'!$C$20-'Assumptions'!$C$19*'Assumptions'!$C$22)*'Assumptions'!$C$23)*((1-'Assumptions'!$C$41*'Assumptions'!$C$42)*(1-'Assumptions'!$C$43))*((('Assumptions'!$C$33*(1-'Assumptions'!$C$35)+'Assumptions'!$C$34*'Assumptions'!$C$35))*(1-'Assumptions'!$C$40)*'Assumptions'!$C$38)+(('Assumptions'!$C$25+'Assumptions'!$C$26-'Assumptions'!$C$25*'Assumptions'!$C$28)*'Assumptions'!$C$29)*((1-'Assumptions'!$C$41*'Assumptions'!$C$42)*(1-'Assumptions'!$C$43))*((('Assumptions'!$C$33*(1-'Assumptions'!$C$35)+'Assumptions'!$C$34*'Assumptions'!$C$35))*(1-'Assumptions'!$C$40)*'Assumptions'!$C$39)))+((('Assumptions'!$C$13+'Assumptions'!$C$14-'Assumptions'!$C$13*'Assumptions'!$C$16)*'Assumptions'!$C$44+('Assumptions'!$C$19+'Assumptions'!$C$20-'Assumptions'!$C$19*'Assumptions'!$C$22)*'Assumptions'!$C$45+('Assumptions'!$C$25+'Assumptions'!$C$26-'Assumptions'!$C$25*'Assumptions'!$C$28)*'Assumptions'!$C$46)))*(1+(('Assumptions'!$C$15+'Assumptions'!$C$21+'Assumptions'!$C$27)/3+('Assumptions'!$C$18+'Assumptions'!$C$24+'Assumptions'!$C$30)/3-('Assumptions'!$C$16+'Assumptions'!$C$22+'Assumptions'!$C$28)/3+'Assumptions'!$C$36*0.5))^35 -> 0 | D9: =((((('Assumptions'!$D$13+'Assumptions'!$D$14-'Assumptions'!$D$13*'Assumptions'!$D$16)*'Assumptions'!$D$17)*((1-'Assumptions'!$D$41*'Assumptions'!$D$42)*(1-'Assumptions'!$D$43))*((('Assumptions'!$D$33*(1-'Assumptions'!$D$35)+'Assumptions'!$D$34*'Assumptions'!$D$35))*(1-'Assumptions'!$D$40)*'Assumptions'!$D$37)+(('Assumptions'!$D$19+'Assumptions'!$D$20-'Assumptions'!$D$19*'Assumptions'!$D$22)*'Assumptions'!$D$23)*((1-'Assumptions'!$D$41*'Assumptions'!$D$42)*(1-'Assumptions'!$D$43))*((('Assumptions'!$D$33*(1-'Assumptions'!$D$35)+'Assumptions'!$D$34*'Assumptions'!$D$35))*(1-'Assumptions'!$D$40)*'Assumptions'!$D$38)+(('Assumptions'!$D$25+'Assumptions'!$D$26-'Assumptions'!$D$25*'Assumptions'!$D$28)*'Assumptions'!$D$29)*((1-'Assumptions'!$D$41*'Assumptions'!$D$42)*(1-'Assumptions'!$D$43))*((('Assumptions'!$D$33*(1-'Assumptions'!$D$35)+'Assumptions'!$D$34*'Assumptions'!$D$35))*(1-'Assumptions'!$D$40)*'Assumptions'!$D$39)))+((('Assumptions'!$D$13+'Assumptions'!$D$14-'Assumptions'!$D$13*'Assumptions'!$D$16)*'Assumptions'!$D$44+('Assumptions'!$D$19+'Assumptions'!$D$20-'Assumptions'!$D$19*'Assumptions'!$D$22)*'Assumptions'!$D$45+('Assumptions'!$D$25+'Assumptions'!$D$26-'Assumptions'!$D$25*'Assumptions'!$D$28)*'Assumptions'!$D$46)))*(1+(('Assumptions'!$D$15+'Assumptions'!$D$21+'Assumptions'!$D$27)/3+('Assumptions'!$D$18+'Assumptions'!$D$24+'Assumptions'!$D$30)/3-('Assumptions'!$D$16+'Assumptions'!$D$22+'Assumptions'!$D$28)/3+'Assumptions'!$D$36*0.5))^35 -> 0 | E9: =((((('Assumptions'!$E$13+'Assumptions'!$E$14-'Assumptions'!$E$13*'Assumptions'!$E$16)*'Assumptions'!$E$17)*((1-'Assumptions'!$E$41*'Assumptions'!$E$42)*(1-'Assumptions'!$E$43))*((('Assumptions'!$E$33*(1-'Assumptions'!$E$35)+'Assumptions'!$E$34*'Assumptions'!$E$35))*(1-'Assumptions'!$E$40)*'Assumptions'!$E$37)+(('Assumptions'!$E$19+'Assumptions'!$E$20-'Assumptions'!$E$19*'Assumptions'!$E$22)*'Assumptions'!$E$23)*((1-'Assumptions'!$E$41*'Assumptions'!$E$42)*(1-'Assumptions'!$E$43))*((('Assumptions'!$E$33*(1-'Assumptions'!$E$35)+'Assumptions'!$E$34*'Assumptions'!$E$35))*(1-'Assumptions'!$E$40)*'Assumptions'!$E$38)+(('Assumptions'!$E$25+'Assumptions'!$E$26-'Assumptions'!$E$25*'Assumptions'!$E$28)*'Assumptions'!$E$29)*((1-'Assumptions'!$E$41*'Assumptions'!$E$42)*(1-'Assumptions'!$E$43))*((('Assumptions'!$E$33*(1-'Assumptions'!$E$35)+'Assumptions'!$E$34*'Assumptions'!$E$35))*(1-'Assumptions'!$E$40)*'Assumptions'!$E$39)))+((('Assumptions'!$E$13+'Assumptions'!$E$14-'Assumptions'!$E$13*'Assumptions'!$E$16)*'Assumptions'!$E$44+('Assumptions'!$E$19+'Assumptions'!$E$20-'Assumptions'!$E$19*'Assumptions'!$E$22)*'Assumptions'!$E$45+('Assumptions'!$E$25+'Assumptions'!$E$26-'Assumptions'!$E$25*'Assumptions'!$E$28)*'Assumptions'!$E$46)))*(1+(('Assumptions'!$E$15+'Assumptions'!$E$21+'Assumptions'!$E$27)/3+('Assumptions'!$E$18+'Assumptions'!$E$24+'Assumptions'!$E$30)/3-('Assumptions'!$E$16+'Assumptions'!$E$22+'Assumptions'!$E$28)/3+'Assumptions'!$E$36*0.5))^35 -> 0 | F9: ='Revenue'!AL60 -> 0
