Workbook

Sheet Read Me
A1: AI-Enabled Services — 3-Year Financial Model
A2: 36-month integrated financial model — Read Me
A4: Overview
A5: A 36-month, formula-driven financial model for an AI-enabled services company. Start on the Assumptions tab, pick Base/Upside/Downside, and the model flows from sales pipeline to bookings, backlog, recognized revenue, gross margin, cash flow, and runway.
A7: How this workbook is organized
A8: Assumptions -> Headcount -> Revenue -> COGS & GM -> Opex -> Working Capital -> P&L -> Balance Sheet -> Cash Flow -> Cash & Runway -> Scenarios -> Visuals -> Checks. Data flows strictly left-to-right through that order: change an assumption, and every downstream tab recalculates automatically (workbook calculation mode is Automatic).
A10: Formatting legend
A11: Blue text on light-blue fill = an input you can edit (Assumptions tab, and scenario selector).
A12: Black text on white = a live formula. Do not hard-code over these cells.
A13: Cells on a light-gray band = a value linked in from another tab.
A15: Color palette
A16: Purple (#7B68EE)
... A35: 36 monthly periods, plus quarterly (12) and annual (3) roll-up columns on each schedule tab. Workbook calculation is set to Automatic — Excel recalculates on every edit. Deterministic, seeded default assumptions are provided so the model is internally consistent out of the box; replace them with your own numbers on the Assumptions tab.

Sheet Assumptions
A1: AI-Enabled Services — 3-Year Financial Model — Assumptions
A2: Plain-language inputs. Edit the Base / Upside / Downside columns only — everything else in this workbook is a formula.
A4: Scenario selector: | C4: Base | D4: << Pick Base / Upside / Downside. This one cell drives every formula in the model.
A6: Assumption | B6: Unit | C6: Base | D6: Upside | E6: Downside | F6: Active (used in model) | G6: Notes / definition
A7: Company & Financial
A8: Starting cash balance | B8: $ | C8: 900000 | D8: 900000 | E8: 900000 | F8: =CHOOSE(MATCH('Assumptions'!$C$4,{"Base","Upside","Downside"},0),C8,D8,E8) -> 0 | G8: Cash on hand at the start of month 1.
A9: Starting paid-in capital | B9: $ | C9: 1250000 | D9: 1250000 | E9: 1250000 | F9: =CHOOSE(MATCH('Assumptions'!$C$4,{"Base","Upside","Downside"},0),C9,D9,E9) -> 0 | G9: Cumulative equity funded before the model begins.
A10: Income tax rate | B10: % | C10: 0 | D10: 0 | E10: 0 | F10: =CHOOSE(MATCH('Assumptions'!$C$4,{"Base","Upside","Downside"},0),C10,D10,E10) -> 0 | G10: Applied only to positive EBT; no NOL carryforward modeled.
A12: Pipeline & Bookings
A13: Starting signed backlog | B13: $ | C13: 650000 | D13: 725000 | E13: 500000 | F13: =CHOOSE(MATCH('Assumptions'!$C$4,{"Base","Upside","Downside"},0),C13,D13,E13) -> 0 | G13: Contracted work not yet recognized as revenue at the start of month 1.
A14: Qualified pipeline opportunities per Sales/BD FTE, month 1 | B14: #/mo | C14: 2.4 | D14: 2.9 | E14: 1.9 | F14: =CHOOSE(MATCH('Assumptions'!$C$4,{"Base","Upside","Downside"},0),C14,D14,E14) -> 0 | G14: Average proposal-ready projects each sales rep creates in month 1.
A15: Pipeline opportunities growth, month over month | B15: % | C15: 0.0384 | D15: 0.0491 | E15: 0.0123 | F15: =CHOOSE(MATCH('Assumptions'!$C$4,{"Base","Upside","Downside"},0),C15,D15,E15) -> 0 | G15: Improvement in qualified opportunities per sales rep over time from references, content, and partner channels.
A16: Proposal win rate | B16: % | C16: 0.34 | D16: 0.4 | E16: 0.26 | F16: =CHOOSE(MATCH('Assumptions'!$C$4,{"Base","Upside","Downside"},0),C16,D16,E16) -> 0 | G16: Share of qualified opportunities that close into signed projects.
A17: Average project contract value, month 1 | B17: $ | C17: 85000 | D17: 95000 | E17: 72000 | F17: =CHOOSE(MATCH('Assumptions'!$C$4,{"Base","Upside","Downside"},0),C17,D17,E17) -> 0 | G17: Fixed-fee project value equivalent for a typical implementation or consulting engagement.
A18: Average project value growth, month over month | B18: % | C18: 0.0037 | D18: 0.0123 | E18: -0.0017 | F18: =CHOOSE(MATCH('Assumptions'!$C$4,{"Base","Upside","Downside"},0),C18,D18,E18) -> 0 | G18: Mix/pricing improvement in signed project value over time.
A19: Average project duration | B19: months | C19: 2.5 | D19: 2.2 | E19: 3.1 | F19: =CHOOSE(MATCH('Assumptions'!$C$4,{"Base","Upside","Downside"},0),C19,D19,E19) -> 0 | G19: Average time over which signed backlog converts into recognized revenue.
A21: Delivery & Utilization
A22: Standard billable-hours capacity per Delivery FTE | B22: hrs/mo | C22: 140 | D22: 145 | E22: 135 | F22: =CHOOSE(MATCH('Assumptions'!$C$4,{"Base","Upside","Downside"},0),C22,D22,E22) -> 0 | G22: Monthly capacity before utilization and AI productivity uplift.
A23: Target delivery utilization | B23: % | C23: 0.72 | D23: 0.8 | E23: 0.62 | F23: =CHOOSE(MATCH('Assumptions'!$C$4,{"Base","Upside","Downside"},0),C23,D23,E23) -> 0 | G23: Share of effective delivery capacity expected to be client-billable.
A24: Realization rate | B24: % | C24: 0.93 | D24: 0.97 | E24: 0.88 | F24: =CHOOSE(MATCH('Assumptions'!$C$4,{"Base","Upside","Downside"},0),C24,D24,E24) -> 0 | G24: Billed/collected rate as a % of standard rate after discounts, write-offs, and scope leakage.
A25: Blended billing rate, month 1 | B25: $/hr | C25: 195 | D25: 210 | E25: 180 | F25: =CHOOSE(MATCH('Assumptions'!$C$4,{"Base","Upside","Downside"},0),C25,D25,E25) -> 0 | G25: Average realized delivery price before realization adjustments.
A26: Billing-rate growth, month over month | B26: % | C26: 0.0049 | D26: 0.009 | E26: 0.0001 | F26: =CHOOSE(MATCH('Assumptions'!$C$4,{"Base","Upside","Downside"},0),C26,D26,E26) -> 0 | G26: Price/mix improvement in the standard delivery rate.
A27: AI productivity uplift | B27: % | C27: 0.18 | D27: 0.28 | E27: 0.08 | F27: =CHOOSE(MATCH('Assumptions'!$C$4,{"Base","Upside","Downside"},0),C27,D27,E27) -> 0 | G27: AI tooling increases effective delivery capacity without a proportional increase in headcount.
A29: COGS & AI Tooling
A30: Subcontractor cost, % of revenue | B30: % | C30: 0.1 | D30: 0.07 | E30: 0.14 | F30: =CHOOSE(MATCH('Assumptions'!$C$4,{"Base","Upside","Downside"},0),C30,D30,E30) -> 0 | G30: External specialists used to flex delivery capacity or cover niche skills.
A31: AI tool/API cost per Delivery FTE | B31: $/mo | C31: 1450 | D31: 1300 | E31: 1700 | F31: =CHOOSE(MATCH('Assumptions'!$C$4,{"Base","Upside","Downside"},0),C31,D31,E31) -> 0 | G31: Model/API/tooling spend consumed directly in service delivery.
A33: Headcount — Delivery (COGS)
A34: Starting Delivery/Consulting FTEs | B34: # | C34: 6 | D34: 7 | E34: 5 | F34: =CHOOSE(MATCH('Assumptions'!$C$4,{"Base","Upside","Downside"},0),C34,D34,E34) -> 0 | G34: Billable consultants and implementation specialists.
A35: Delivery/Consulting net adds per quarter | B35: # | C35: 1.5 | D35: 2 | E35: 0.8 | F35: =CHOOSE(MATCH('Assumptions'!$C$4,{"Base","Upside","Downside"},0),C35,D35,E35) -> 0 | G35: Net hires supporting growth in signed and delivered work.
A36: Delivery/Consulting fully-loaded cost per FTE | B36: $/mo | C36: 12500 | D36: 12500 | E36: 12500 | F36: =CHOOSE(MATCH('Assumptions'!$C$4,{"Base","Upside","Downside"},0),C36,D36,E36) -> 0 | G36: Salary, benefits, payroll tax, and bonus accrual.
A38: Headcount — Delivery Management / Solutions (COGS)
A39: Starting Delivery Management / Solutions FTEs | B39: # | C39: 1.5 | D39: 2 | E39: 1 | F39: =CHOOSE(MATCH('Assumptions'!$C$4,{"Base","Upside","Downside"},0),C39,D39,E39) -> 0 | G39: Classified in COGS because this team is directly tied to project oversight and solution delivery.
A40: Delivery Management / Solutions net adds per quarter | B40: # | C40: 0.5 | D40: 0.8 | E40: 0.2 | F40: =CHOOSE(MATCH('Assumptions'!$C$4,{"Base","Upside","Downside"},0),C40,D40,E40) -> 0 | G40: Staffing added as project volume and delivery complexity increase.
A41: Delivery Management / Solutions fully-loaded cost per FTE | B41: $/mo | C41: 15500 | D41: 15500 | E41: 15500 | F41: =CHOOSE(MATCH('Assumptions'!$C$4,{"Base","Upside","Downside"},0),C41,D41,E41) -> 0 | G41: Higher-cost solution leads / delivery managers.
A43: Headcount — Sales / BD (Opex)
A44: Starting Sales / BD FTEs | B44: # | C44: 2 | D44: 2 | E44: 2 | F44: =CHOOSE(MATCH('Assumptions'!$C$4,{"Base","Upside","Downside"},0),C44,D44,E44) -> 0 | G44: Quota-carrying sales and business development reps.
A45: Sales / BD net adds per quarter | B45: # | C45: 0.75 | D45: 1 | E45: 0.4 | F45: =CHOOSE(MATCH('Assumptions'!$C$4,{"Base","Upside","Downside"},0),C45,D45,E45) -> 0 | G45: Net rep additions supporting pipeline generation.
A46: Sales / BD fully-loaded cost per FTE | B46: $/mo | C46: 13500 | D46: 13500 | E46: 13500 | F46: =CHOOSE(MATCH('Assumptions'!$C$4,{"Base","Upside","Downside"},0),C46,D46,E46) -> 0 | G46: Base pay, benefits, payroll tax, and bonus accrual before commissions.
A48: Headcount — G&A (Opex)
A49: Starting G&A FTEs | B49: # | C49: 2 | D49: 2 | E49: 2 | F49: =CHOOSE(MATCH('Assumptions'!$C$4,{"Base","Upside","Downside"},0),C49,D49,E49) -> 0 | G49: Finance, ops, recruiting, and admin.
A50: G&A net adds per quarter | B50: # | C50: 0.4 | D50: 0.5 | E50: 0.2 | F50: =CHOOSE(MATCH('Assumptions'!$C$4,{"Base","Upside","Downside"},0),C50,D50,E50) -> 0 | G50: Back-office scaling as the services business grows.
A51: G&A fully-loaded cost per FTE | B51: $/mo | C51: 10500 | D51: 10500 | E51: 10500 | F51: =CHOOSE(MATCH('Assumptions'!$C$4,{"Base","Upside","Downside"},0),C51,D51,E51) -> 0 | G51: Salary, benefits, payroll tax, and bonus accrual.
A53: Sales / Opex
A54: Sales commissions, % of new bookings | B54: % | C54: 0.06 | D54: 0.05 | E54: 0.07 | F54: =CHOOSE(MATCH('Assumptions'!$C$4,{"Base","Upside","Downside"},0),C54,D54,E54) -> 0 | G54: Variable sales compensation paid on signed bookings.
A55: Marketing / BD programs, month 1 | B55: $/mo | C55: 18000 | D55: 22000 | E55: 14000 | F55: =CHOOSE(MATCH('Assumptions'!$C$4,{"Base","Upside","Downside"},0),C55,D55,E55) -> 0 | G55: Events, outbound tools, content, and partner development spend.
A56: Marketing / BD spend growth, month over month | B56: % | C56: 0.0082 | D56: 0.0143 | E56: 0.0039 | F56: =CHOOSE(MATCH('Assumptions'!$C$4,{"Base","Upside","Downside"},0),C56,D56,E56) -> 0 | G56: Growth in non-people demand generation and business development spend.
A57: Corporate software & tools | B57: $/mo | C57: 7500 | D57: 7500 | E57: 7500 | F57: =CHOOSE(MATCH('Assumptions'!$C$4,{"Base","Upside","Downside"},0),C57,D57,E57) -> 0 | G57: Back-office software not directly consumed in delivery.
A58: Facilities & admin overhead | B58: $/mo | C58: 5500 | D58: 5500 | E58: 5500 | F58: =CHOOSE(MATCH('Assumptions'!$C$4,{"Base","Upside","Downside"},0),C58,D58,E58) -> 0 | G58: Office, insurance, and other fixed operating overhead.
A60: Working Capital & Financing
A61: Days Sales Outstanding (AR) | B61: days | C61: 55 | D61: 45 | E61: 65 | F61: =CHOOSE(MATCH('Assumptions'!$C$4,{"Base","Upside","Downside"},0),C61,D61,E61) -> 0 | G61: Services businesses typically invoice and collect on net-30/45/60 terms.
A62: Days Payable Outstanding (AP) | B62: days | C62: 30 | D62: 35 | E62: 25 | F62: =CHOOSE(MATCH('Assumptions'!$C$4,{"Base","Upside","Downside"},0),C62,D62,E62) -> 0 | G62: Vendor payment timing.
A63: Deferred revenue (months of revenue collected in advance) | B63: mo | C63: 0.1 | D63: 0.2 | E63: 0 | F63: =CHOOSE(MATCH('Assumptions'!$C$4,{"Base","Upside","Downside"},0),C63,D63,E63) -> 0 | G63: Kept small: backlog on the Revenue tab does the primary signed-work tracking.
A64: Capex, % of revenue | B64: % | C64: 0.01 | D64: 0.008 | E64: 0.015 | F64: =CHOOSE(MATCH('Assumptions'!$C$4,{"Base","Upside","Downside"},0),C64,D64,E64) -> 0 | G64: Laptop refreshes and modest internal tooling capitalization.
A65: Useful life of capitalized assets | B65: months | C65: 36 | D65: 36 | E65: 36 | F65: =CHOOSE(MATCH('Assumptions'!$C$4,{"Base","Upside","Downside"},0),C65,D65,E65) -> 0
A66: Other current assets, % of revenue | B66: % | C66: 0.02 | D66: 0.02 | E66: 0.025 | F66: =CHOOSE(MATCH('Assumptions'!$C$4,{"Base","Upside","Downside"},0),C66,D66,E66) -> 0 | G66: Prepaids and other small current asset balances.
A67: Debt annual interest rate | B67: % | C67: 0.1 | D67: 0.09 | E67: 0.12 | F67: =CHOOSE(MATCH('Assumptions'!$C$4,{"Base","Upside","Downside"},0),C67,D67,E67) -> 0
A68: Debt draw (one-time) | B68: $ | C68: 300000 | D68: 300000 | E68: 200000 | F68: =CHOOSE(MATCH('Assumptions'!$C$4,{"Base","Upside","Downside"},0),C68,D68,E68) -> 0
A69: Debt monthly repayment | B69: $/mo | C69: 10000 | D69: 10000 | E69: 8000 | F69: =CHOOSE(MATCH('Assumptions'!$C$4,{"Base","Upside","Downside"},0),C69,D69,E69) -> 0
A70: Seed extension / bridge raise (month 4) | B70: $ | C70: 2000000 | D70: 2400000 | E70: 1500000 | F70: =CHOOSE(MATCH('Assumptions'!$C$4,{"Base","Upside","Downside"},0),C70,D70,E70) -> 0
A71: Growth equity raise (month 19) | B71: $ | C71: 4000000 | D71: 5000000 | E71: 3000000 | F71: =CHOOSE(MATCH('Assumptions'!$C$4,{"Base","Upside","Downside"},0),C71,D71,E71) -> 0
A74: Tip: backlog and delivery-capacity assumptions drive revenue timing more than signed bookings alone.

Sheet Headcount
A1: AI-Enabled Services — 3-Year Financial Model — Headcount
A2: Fully-loaded FTE ramps by role — flows into COGS or Opex by classification.
A5: Line item | B5: Units / source | C5: Monthly (36 months) | AN5: Quarterly | BA5: Annual
C6: 46023 | D6: 46054 | E6: 46082 | F6: 46113 | G6: 46143 | H6: 46174 | I6: 46204 | J6: 46235 | K6: 46266 | L6: 46296 | M6: 46327 | N6: 46357 | O6: 46388 | P6: 46419 | Q6: 46447 | R6: 46478 | S6: 46508 | T6: 46539 | U6: 46569 | V6: 46600 | W6: 46631 | X6: 46661 | Y6: 46692 | Z6: 46722 | AA6: 46753 | AB6: 46784 | AC6: 46813 | AD6: 46844 | AE6: 46874 | AF6: 46905 | AG6: 46935 | AH6: 46966 | AI6: 46997 | AJ6: 47027 | AK6: 47058 | AL6: 47088 | AN6: Q1 | AO6: Q2 | AP6: Q3 | AQ6: Q4 | AR6: Q5 | AS6: Q6 | AT6: Q7 | AU6: Q8 | AV6: Q9 | AW6: Q10 | AX6: Q11 | AY6: Q12 | BA6: FY1 | BB6: FY2 | BC6: FY3
A7: Cost of Goods Sold headcount (COGS-classified)
A8: Delivery / Consulting — headcount (FTE) | B8: Delivery · start + net adds/qtr ÷ 3 | C8: =ROUND('Assumptions'!$F$34,1) -> 0 | D8: =ROUND(C8+'Assumptions'!$F$35/3,1) -> 0 | E8: =ROUND(D8+'Assumptions'!$F$35/3,1) -> 0 | F8: =ROUND(E8+'Assumptions'!$F$35/3,1) -> 0 | G8: =ROUND(F8+'Assumptions'!$F$35/3,1) -> 0 | H8: =ROUND(G8+'Assumptions'!$F$35/3,1) -> 0 | I8: =ROUND(H8+'Assumptions'!$F$35/3,1) -> 0 | J8: =ROUND(I8+'Assumptions'!$F$35/3,1) -> 0 | K8: =ROUND(J8+'Assumptions'!$F$35/3,1) -> 0 | ... AL8: =ROUND(AK8+'Assumptions'!$F$35/3,1) -> 0 | AN8: =E8 -> 0 | AO8: =H8 -> 0 | AP8: =K8 -> 0 | AQ8: =N8 -> 0 | AR8: =Q8 -> 0 | AS8: =T8 -> 0 | AT8: =W8 -> 0 | AU8: =Z8 -> 0 | AV8: =AC8 -> 0 | AW8: =AF8 -> 0 | AX8: =AI8 -> 0 | AY8: =AL8 -> 0 | BA8: =N8 -> 0 | BB8: =Z8 -> 0 | BC8: =AL8 -> 0
A9: Delivery / Consulting — fully-loaded cost | B9: Headcount × monthly fully-loaded cost/FTE | C9: =C8*'Assumptions'!$F$36 -> 0 | D9: =D8*'Assumptions'!$F$36 -> 0 | E9: =E8*'Assumptions'!$F$36 -> 0 | F9: =F8*'Assumptions'!$F$36 -> 0 | G9: =G8*'Assumptions'!$F$36 -> 0 | H9: =H8*'Assumptions'!$F$36 -> 0 | I9: =I8*'Assumptions'!$F$36 -> 0 | J9: =J8*'Assumptions'!$F$36 -> 0 | ... AL9: =AL8*'Assumptions'!$F$36 -> 0 | AN9: =SUM(C9:E9) -> 0 | AO9: =SUM(F9:H9) -> 0 | AP9: =SUM(I9:K9) -> 0 | AQ9: =SUM(L9:N9) -> 0 | AR9: =SUM(O9:Q9) -> 0 | AS9: =SUM(R9:T9) -> 0 | AT9: =SUM(U9:W9) -> 0 | AU9: =SUM(X9:Z9) -> 0 | AV9: =SUM(AA9:AC9) -> 0 | AW9: =SUM(AD9:AF9) -> 0 | AX9: =SUM(AG9:AI9) -> 0 | AY9: =SUM(AJ9:AL9) -> 0 | BA9: =SUM(C9:N9) -> 0 | BB9: =SUM(O9:Z9) -> 0 | BC9: =SUM(AA9:AL9) -> 0
A10: Delivery Management / Solutions — headcount (FTE) | B10: Delivery · start + net adds/qtr ÷ 3 | C10: =ROUND('Assumptions'!$F$39,1) -> 0 | D10: =ROUND(C10+'Assumptions'!$F$40/3,1) -> 0 | E10: =ROUND(D10+'Assumptions'!$F$40/3,1) -> 0 | F10: =ROUND(E10+'Assumptions'!$F$40/3,1) -> 0 | G10: =ROUND(F10+'Assumptions'!$F$40/3,1) -> 0 | H10: =ROUND(G10+'Assumptions'!$F$40/3,1) -> 0 | I10: =ROUND(H10+'Assumptions'!$F$40/3,1) -> 0 | J10: =ROUND(I10+'Assumptions'!$F$40/3,1) -> 0 | K10: =ROUND(J10+'Assumptions'!$F$40/3,1) -> 0 | ... AL10: =ROUND(AK10+'Assumptions'!$F$40/3,1) -> 0 | AN10: =E10 -> 0 | AO10: =H10 -> 0 | AP10: =K10 -> 0 | AQ10: =N10 -> 0 | AR10: =Q10 -> 0 | AS10: =T10 -> 0 | AT10: =W10 -> 0 | AU10: =Z10 -> 0 | AV10: =AC10 -> 0 | AW10: =AF10 -> 0 | AX10: =AI10 -> 0 | AY10: =AL10 -> 0 | BA10: =N10 -> 0 | BB10: =Z10 -> 0 | BC10: =AL10 -> 0
A11: Delivery Management / Solutions — fully-loaded cost | B11: Headcount × monthly fully-loaded cost/FTE | C11: =C10*'Assumptions'!$F$41 -> 0 | D11: =D10*'Assumptions'!$F$41 -> 0 | E11: =E10*'Assumptions'!$F$41 -> 0 | F11: =F10*'Assumptions'!$F$41 -> 0 | G11: =G10*'Assumptions'!$F$41 -> 0 | H11: =H10*'Assumptions'!$F$41 -> 0 | I11: =I10*'Assumptions'!$F$41 -> 0 | J11: =J10*'Assumptions'!$F$41 -> 0 | ... AL11: =AL10*'Assumptions'!$F$41 -> 0 | AN11: =SUM(C11:E11) -> 0 | AO11: =SUM(F11:H11) -> 0 | AP11: =SUM(I11:K11) -> 0 | AQ11: =SUM(L11:N11) -> 0 | AR11: =SUM(O11:Q11) -> 0 | AS11: =SUM(R11:T11) -> 0 | AT11: =SUM(U11:W11) -> 0 | AU11: =SUM(X11:Z11) -> 0 | AV11: =SUM(AA11:AC11) -> 0 | AW11: =SUM(AD11:AF11) -> 0 | AX11: =SUM(AG11:AI11) -> 0 | AY11: =SUM(AJ11:AL11) -> 0 | BA11: =SUM(C11:N11) -> 0 | BB11: =SUM(O11:Z11) -> 0 | BC11: =SUM(AA11:AL11) -> 0
A13: Operating expense headcount (Opex-classified)
A14: Sales / Business Development — headcount (FTE) | B14: Sales & Marketing · start + net adds/qtr ÷ 3 | C14: =ROUND('Assumptions'!$F$44,1) -> 0 | D14: =ROUND(C14+'Assumptions'!$F$45/3,1) -> 0 | E14: =ROUND(D14+'Assumptions'!$F$45/3,1) -> 0 | F14: =ROUND(E14+'Assumptions'!$F$45/3,1) -> 0 | G14: =ROUND(F14+'Assumptions'!$F$45/3,1) -> 0 | H14: =ROUND(G14+'Assumptions'!$F$45/3,1) -> 0 | I14: =ROUND(H14+'Assumptions'!$F$45/3,1) -> 0 | J14: =ROUND(I14+'Assumptions'!$F$45/3,1) -> 0 | K14: =ROUND(J14+'Assumptions'!$F$45/3,1) -> 0 | ... AL14: =ROUND(AK14+'Assumptions'!$F$45/3,1) -> 0 | AN14: =E14 -> 0 | AO14: =H14 -> 0 | AP14: =K14 -> 0 | AQ14: =N14 -> 0 | AR14: =Q14 -> 0 | AS14: =T14 -> 0 | AT14: =W14 -> 0 | AU14: =Z14 -> 0 | AV14: =AC14 -> 0 | AW14: =AF14 -> 0 | AX14: =AI14 -> 0 | AY14: =AL14 -> 0 | BA14: =N14 -> 0 | BB14: =Z14 -> 0 | BC14: =AL14 -> 0
A15: Sales / Business Development — fully-loaded cost | B15: Headcount × monthly fully-loaded cost/FTE | C15: =C14*'Assumptions'!$F$46 -> 0 | D15: =D14*'Assumptions'!$F$46 -> 0 | E15: =E14*'Assumptions'!$F$46 -> 0 | F15: =F14*'Assumptions'!$F$46 -> 0 | G15: =G14*'Assumptions'!$F$46 -> 0 | H15: =H14*'Assumptions'!$F$46 -> 0 | I15: =I14*'Assumptions'!$F$46 -> 0 | J15: =J14*'Assumptions'!$F$46 -> 0 | ... AL15: =AL14*'Assumptions'!$F$46 -> 0 | AN15: =SUM(C15:E15) -> 0 | AO15: =SUM(F15:H15) -> 0 | AP15: =SUM(I15:K15) -> 0 | AQ15: =SUM(L15:N15) -> 0 | AR15: =SUM(O15:Q15) -> 0 | AS15: =SUM(R15:T15) -> 0 | AT15: =SUM(U15:W15) -> 0 | AU15: =SUM(X15:Z15) -> 0 | AV15: =SUM(AA15:AC15) -> 0 | AW15: =SUM(AD15:AF15) -> 0 | AX15: =SUM(AG15:AI15) -> 0 | AY15: =SUM(AJ15:AL15) -> 0 | BA15: =SUM(C15:N15) -> 0 | BB15: =SUM(O15:Z15) -> 0 | BC15: =SUM(AA15:AL15) -> 0
A16: General & Administrative — headcount (FTE) | B16: General & Administrative · start + net adds/qtr ÷ 3 | C16: =ROUND('Assumptions'!$F$49,1) -> 0 | D16: =ROUND(C16+'Assumptions'!$F$50/3,1) -> 0 | E16: =ROUND(D16+'Assumptions'!$F$50/3,1) -> 0 | F16: =ROUND(E16+'Assumptions'!$F$50/3,1) -> 0 | G16: =ROUND(F16+'Assumptions'!$F$50/3,1) -> 0 | H16: =ROUND(G16+'Assumptions'!$F$50/3,1) -> 0 | I16: =ROUND(H16+'Assumptions'!$F$50/3,1) -> 0 | J16: =ROUND(I16+'Assumptions'!$F$50/3,1) -> 0 | K16: =ROUND(J16+'Assumptions'!$F$50/3,1) -> 0 | ... AL16: =ROUND(AK16+'Assumptions'!$F$50/3,1) -> 0 | AN16: =E16 -> 0 | AO16: =H16 -> 0 | AP16: =K16 -> 0 | AQ16: =N16 -> 0 | AR16: =Q16 -> 0 | AS16: =T16 -> 0 | AT16: =W16 -> 0 | AU16: =Z16 -> 0 | AV16: =AC16 -> 0 | AW16: =AF16 -> 0 | AX16: =AI16 -> 0 | AY16: =AL16 -> 0 | BA16: =N16 -> 0 | BB16: =Z16 -> 0 | BC16: =AL16 -> 0
A17: General & Administrative — fully-loaded cost | B17: Headcount × monthly fully-loaded cost/FTE | C17: =C16*'Assumptions'!$F$51 -> 0 | D17: =D16*'Assumptions'!$F$51 -> 0 | E17: =E16*'Assumptions'!$F$51 -> 0 | F17: =F16*'Assumptions'!$F$51 -> 0 | G17: =G16*'Assumptions'!$F$51 -> 0 | H17: =H16*'Assumptions'!$F$51 -> 0 | I17: =I16*'Assumptions'!$F$51 -> 0 | J17: =J16*'Assumptions'!$F$51 -> 0 | ... AL17: =AL16*'Assumptions'!$F$51 -> 0 | AN17: =SUM(C17:E17) -> 0 | AO17: =SUM(F17:H17) -> 0 | AP17: =SUM(I17:K17) -> 0 | AQ17: =SUM(L17:N17) -> 0 | AR17: =SUM(O17:Q17) -> 0 | AS17: =SUM(R17:T17) -> 0 | AT17: =SUM(U17:W17) -> 0 | AU17: =SUM(X17:Z17) -> 0 | AV17: =SUM(AA17:AC17) -> 0 | AW17: =SUM(AD17:AF17) -> 0 | AX17: =SUM(AG17:AI17) -> 0 | AY17: =SUM(AJ17:AL17) -> 0 | BA17: =SUM(C17:N17) -> 0 | BB17: =SUM(O17:Z17) -> 0 | BC17: =SUM(AA17:AL17) -> 0
A19: Totals
A20: Total headcount (FTE) | B20: Sum of all roles | C20: =C8+C10+C14+C16 -> 0 | D20: =D8+D10+D14+D16 -> 0 | E20: =E8+E10+E14+E16 -> 0 | F20: =F8+F10+F14+F16 -> 0 | G20: =G8+G10+G14+G16 -> 0 | H20: =H8+H10+H14+H16 -> 0 | I20: =I8+I10+I14+I16 -> 0 | J20: =J8+J10+J14+J16 -> 0 | ... AL20: =AL8+AL10+AL14+AL16 -> 0 | AN20: =E20 -> 0 | AO20: =H20 -> 0 | AP20: =K20 -> 0 | AQ20: =N20 -> 0 | AR20: =Q20 -> 0 | AS20: =T20 -> 0 | AT20: =W20 -> 0 | AU20: =Z20 -> 0 | AV20: =AC20 -> 0 | AW20: =AF20 -> 0 | AX20: =AI20 -> 0 | AY20: =AL20 -> 0 | BA20: =N20 -> 0 | BB20: =Z20 -> 0 | BC20: =AL20 -> 0
A21: Total COGS-classified people cost | B21: Feeds COGS & GM tab | C21: =C9+C11 -> 0 | D21: =D9+D11 -> 0 | E21: =E9+E11 -> 0 | F21: =F9+F11 -> 0 | G21: =G9+G11 -> 0 | H21: =H9+H11 -> 0 | I21: =I9+I11 -> 0 | J21: =J9+J11 -> 0 | ... AL21: =AL9+AL11 -> 0 | AN21: =SUM(C21:E21) -> 0 | AO21: =SUM(F21:H21) -> 0 | AP21: =SUM(I21:K21) -> 0 | AQ21: =SUM(L21:N21) -> 0 | AR21: =SUM(O21:Q21) -> 0 | AS21: =SUM(R21:T21) -> 0 | AT21: =SUM(U21:W21) -> 0 | AU21: =SUM(X21:Z21) -> 0 | AV21: =SUM(AA21:AC21) -> 0 | AW21: =SUM(AD21:AF21) -> 0 | AX21: =SUM(AG21:AI21) -> 0 | AY21: =SUM(AJ21:AL21) -> 0 | BA21: =SUM(C21:N21) -> 0 | BB21: =SUM(O21:Z21) -> 0 | BC21: =SUM(AA21:AL21) -> 0
A22: Total Opex-classified people cost | B22: Feeds Opex tab | C22: =C15+C17 -> 0 | D22: =D15+D17 -> 0 | E22: =E15+E17 -> 0 | F22: =F15+F17 -> 0 | G22: =G15+G17 -> 0 | H22: =H15+H17 -> 0 | I22: =I15+I17 -> 0 | J22: =J15+J17 -> 0 | ... AL22: =AL15+AL17 -> 0 | AN22: =SUM(C22:E22) -> 0 | AO22: =SUM(F22:H22) -> 0 | AP22: =SUM(I22:K22) -> 0 | AQ22: =SUM(L22:N22) -> 0 | AR22: =SUM(O22:Q22) -> 0 | AS22: =SUM(R22:T22) -> 0 | AT22: =SUM(U22:W22) -> 0 | AU22: =SUM(X22:Z22) -> 0 | AV22: =SUM(AA22:AC22) -> 0 | AW22: =SUM(AD22:AF22) -> 0 | AX22: =SUM(AG22:AI22) -> 0 | AY22: =SUM(AJ22:AL22) -> 0 | BA22: =SUM(C22:N22) -> 0 | BB22: =SUM(O22:Z22) -> 0 | BC22: =SUM(AA22:AL22) -> 0
A23: General & Administrative people cost | C23: =C17 -> 0 | D23: =D17 -> 0 | E23: =E17 -> 0 | F23: =F17 -> 0 | G23: =G17 -> 0 | H23: =H17 -> 0 | I23: =I17 -> 0 | J23: =J17 -> 0 | ... AL23: =AL17 -> 0 | AN23: =SUM(C23:E23) -> 0 | AO23: =SUM(F23:H23) -> 0 | AP23: =SUM(I23:K23) -> 0 | AQ23: =SUM(L23:N23) -> 0 | AR23: =SUM(O23:Q23) -> 0 | AS23: =SUM(R23:T23) -> 0 | AT23: =SUM(U23:W23) -> 0 | AU23: =SUM(X23:Z23) -> 0 | AV23: =SUM(AA23:AC23) -> 0 | AW23: =SUM(AD23:AF23) -> 0 | AX23: =SUM(AG23:AI23) -> 0 | AY23: =SUM(AJ23:AL23) -> 0 | BA23: =SUM(C23:N23) -> 0 | BB23: =SUM(O23:Z23) -> 0 | BC23: =SUM(AA23:AL23) -> 0
A24: Sales & Marketing people cost | C24: =C15 -> 0 | D24: =D15 -> 0 | E24: =E15 -> 0 | F24: =F15 -> 0 | G24: =G15 -> 0 | H24: =H15 -> 0 | I24: =I15 -> 0 | J24: =J15 -> 0 | ... AL24: =AL15 -> 0 | AN24: =SUM(C24:E24) -> 0 | AO24: =SUM(F24:H24) -> 0 | AP24: =SUM(I24:K24) -> 0 | AQ24: =SUM(L24:N24) -> 0 | AR24: =SUM(O24:Q24) -> 0 | AS24: =SUM(R24:T24) -> 0 | AT24: =SUM(U24:W24) -> 0 | AU24: =SUM(X24:Z24) -> 0 | AV24: =SUM(AA24:AC24) -> 0 | AW24: =SUM(AD24:AF24) -> 0 | AX24: =SUM(AG24:AI24) -> 0 | AY24: =SUM(AJ24:AL24) -> 0 | BA24: =SUM(C24:N24) -> 0 | BB24: =SUM(O24:Z24) -> 0 | BC24: =SUM(AA24:AL24) -> 0

Sheet Revenue
A1: AI-Enabled Services — 3-Year Financial Model — Revenue
A2: Pipeline -> bookings -> backlog -> revenue recognized as projects are delivered against capacity.
A5: Line item | B5: Units / source | C5: Monthly (36 months) | AN5: Quarterly | BA5: Annual
C6: 46023 | D6: 46054 | E6: 46082 | F6: 46113 | G6: 46143 | H6: 46174 | I6: 46204 | J6: 46235 | K6: 46266 | L6: 46296 | M6: 46327 | N6: 46357 | O6: 46388 | P6: 46419 | Q6: 46447 | R6: 46478 | S6: 46508 | T6: 46539 | U6: 46569 | V6: 46600 | W6: 46631 | X6: 46661 | Y6: 46692 | Z6: 46722 | AA6: 46753 | AB6: 46784 | AC6: 46813 | AD6: 46844 | AE6: 46874 | AF6: 46905 | AG6: 46935 | AH6: 46966 | AI6: 46997 | AJ6: 47027 | AK6: 47058 | AL6: 47088 | AN6: Q1 | AO6: Q2 | AP6: Q3 | AQ6: Q4 | AR6: Q5 | AS6: Q6 | AT6: Q7 | AU6: Q8 | AV6: Q9 | AW6: Q10 | AX6: Q11 | AY6: Q12 | BA6: FY1 | BB6: FY2 | BC6: FY3
A7: Pipeline & Bookings
A8: Sales / BD FTE | B8: Linked from Headcount tab | C8: ='Headcount'!$C$14 -> 0 | D8: ='Headcount'!$D$14 -> 0 | E8: ='Headcount'!$E$14 -> 0 | F8: ='Headcount'!$F$14 -> 0 | G8: ='Headcount'!$G$14 -> 0 | H8: ='Headcount'!$H$14 -> 0 | I8: ='Headcount'!$I$14 -> 0 | J8: ='Headcount'!$J$14 -> 0 | K8: ='Headcount'!$K$14 -> 0 | L8: ='Headcount'!$L$14 -> 0 | M8: ='Headcount'!$M$14 -> 0 | N8: ='Headcount'!$N$14 -> 0 | O8: ='Headcount'!$O$14 -> 0 | P8: ='Headcount'!$P$14 -> 0 | Q8: ='Headcount'!$Q$14 -> 0 | R8: ='Headcount'!$R$14 -> 0 | S8: ='Headcount'!$S$14 -> 0 | T8: ='Headcount'!$T$14 -> 0 | U8: ='Headcount'!$U$14 -> 0 | V8: ='Headcount'!$V$14 -> 0 | W8: ='Headcount'!$W$14 -> 0 | X8: ='Headcount'!$X$14 -> 0 | Y8: ='Headcount'!$Y$14 -> 0 | Z8: ='Headcount'!$Z$14 -> 0 | AA8: ='Headcount'!$AA$14 -> 0 | AB8: ='Headcount'!$AB$14 -> 0 | AC8: ='Headcount'!$AC$14 -> 0 | AD8: ='Headcount'!$AD$14 -> 0 | AE8: ='Headcount'!$AE$14 -> 0 | AF8: ='Headcount'!$AF$14 -> 0 | AG8: ='Headcount'!$AG$14 -> 0 | AH8: ='Headcount'!$AH$14 -> 0 | AI8: ='Headcount'!$AI$14 -> 0 | AJ8: ='Headcount'!$AJ$14 -> 0 | AK8: ='Headcount'!$AK$14 -> 0 | AL8: ='Headcount'!$AL$14 -> 0 | AN8: =E8 -> 0 | AO8: =H8 -> 0 | AP8: =K8 -> 0 | AQ8: =N8 -> 0 | AR8: =Q8 -> 0 | AS8: =T8 -> 0 | AT8: =W8 -> 0 | AU8: =Z8 -> 0 | AV8: =AC8 -> 0 | AW8: =AF8 -> 0 | AX8: =AI8 -> 0 | AY8: =AL8 -> 0 | BA8: =N8 -> 0 | BB8: =Z8 -> 0 | BC8: =AL8 -> 0
A9: Qualified pipeline opportunities / Sales FTE | B9: Starts from month-1 assumption and compounds with go-to-market efficiency gains | C9: ='Assumptions'!$F$14 -> 0 | D9: =C9*(1+'Assumptions'!$F$15) -> 0 | E9: =D9*(1+'Assumptions'!$F$15) -> 0 | F9: =E9*(1+'Assumptions'!$F$15) -> 0 | G9: =F9*(1+'Assumptions'!$F$15) -> 0 | H9: =G9*(1+'Assumptions'!$F$15) -> 0 | I9: =H9*(1+'Assumptions'!$F$15) -> 0 | J9: =I9*(1+'Assumptions'!$F$15) -> 0 | K9: =J9*(1+'Assumptions'!$F$15) -> 0 | ... AL9: =AK9*(1+'Assumptions'!$F$15) -> 0 | AN9: =AVERAGE(C9:E9) -> 0 | AO9: =AVERAGE(F9:H9) -> 0 | AP9: =AVERAGE(I9:K9) -> 0 | AQ9: =AVERAGE(L9:N9) -> 0 | AR9: =AVERAGE(O9:Q9) -> 0 | AS9: =AVERAGE(R9:T9) -> 0 | AT9: =AVERAGE(U9:W9) -> 0 | AU9: =AVERAGE(X9:Z9) -> 0 | AV9: =AVERAGE(AA9:AC9) -> 0 | AW9: =AVERAGE(AD9:AF9) -> 0 | AX9: =AVERAGE(AG9:AI9) -> 0 | AY9: =AVERAGE(AJ9:AL9) -> 0 | BA9: =AVERAGE(C9:N9) -> 0 | BB9: =AVERAGE(O9:Z9) -> 0 | BC9: =AVERAGE(AA9:AL9) -> 0
A10: Qualified pipeline opportunities | B10: Sales FTE x qualified opportunities per Sales FTE | C10: =C8*C9 -> 0 | D10: =D8*D9 -> 0 | E10: =E8*E9 -> 0 | F10: =F8*F9 -> 0 | G10: =G8*G9 -> 0 | H10: =H8*H9 -> 0 | I10: =I8*I9 -> 0 | J10: =J8*J9 -> 0 | ... AL10: =AL8*AL9 -> 0 | AN10: =SUM(C10:E10) -> 0 | AO10: =SUM(F10:H10) -> 0 | AP10: =SUM(I10:K10) -> 0 | AQ10: =SUM(L10:N10) -> 0 | AR10: =SUM(O10:Q10) -> 0 | AS10: =SUM(R10:T10) -> 0 | AT10: =SUM(U10:W10) -> 0 | AU10: =SUM(X10:Z10) -> 0 | AV10: =SUM(AA10:AC10) -> 0 | AW10: =SUM(AD10:AF10) -> 0 | AX10: =SUM(AG10:AI10) -> 0 | AY10: =SUM(AJ10:AL10) -> 0 | BA10: =SUM(C10:N10) -> 0 | BB10: =SUM(O10:Z10) -> 0 | BC10: =SUM(AA10:AL10) -> 0
A11: Proposal win rate | B11: Active scenario assumption | C11: ='Assumptions'!$F$16 -> 0 | D11: ='Assumptions'!$F$16 -> 0 | E11: ='Assumptions'!$F$16 -> 0 | F11: ='Assumptions'!$F$16 -> 0 | G11: ='Assumptions'!$F$16 -> 0 | H11: ='Assumptions'!$F$16 -> 0 | I11: ='Assumptions'!$F$16 -> 0 | J11: ='Assumptions'!$F$16 -> 0 | ... AL11: ='Assumptions'!$F$16 -> 0 | AN11: =AVERAGE(C11:E11) -> 0 | AO11: =AVERAGE(F11:H11) -> 0 | AP11: =AVERAGE(I11:K11) -> 0 | AQ11: =AVERAGE(L11:N11) -> 0 | AR11: =AVERAGE(O11:Q11) -> 0 | AS11: =AVERAGE(R11:T11) -> 0 | AT11: =AVERAGE(U11:W11) -> 0 | AU11: =AVERAGE(X11:Z11) -> 0 | AV11: =AVERAGE(AA11:AC11) -> 0 | AW11: =AVERAGE(AD11:AF11) -> 0 | AX11: =AVERAGE(AG11:AI11) -> 0 | AY11: =AVERAGE(AJ11:AL11) -> 0 | BA11: =AVERAGE(C11:N11) -> 0 | BB11: =AVERAGE(O11:Z11) -> 0 | BC11: =AVERAGE(AA11:AL11) -> 0
A12: New projects booked | B12: Qualified pipeline x win rate | C12: =C10*C11 -> 0 | D12: =D10*D11 -> 0 | E12: =E10*E11 -> 0 | F12: =F10*F11 -> 0 | G12: =G10*G11 -> 0 | H12: =H10*H11 -> 0 | I12: =I10*I11 -> 0 | J12: =J10*J11 -> 0 | ... AL12: =AL10*AL11 -> 0 | AN12: =SUM(C12:E12) -> 0 | AO12: =SUM(F12:H12) -> 0 | AP12: =SUM(I12:K12) -> 0 | AQ12: =SUM(L12:N12) -> 0 | AR12: =SUM(O12:Q12) -> 0 | AS12: =SUM(R12:T12) -> 0 | AT12: =SUM(U12:W12) -> 0 | AU12: =SUM(X12:Z12) -> 0 | AV12: =SUM(AA12:AC12) -> 0 | AW12: =SUM(AD12:AF12) -> 0 | AX12: =SUM(AG12:AI12) -> 0 | AY12: =SUM(AJ12:AL12) -> 0 | BA12: =SUM(C12:N12) -> 0 | BB12: =SUM(O12:Z12) -> 0 | BC12: =SUM(AA12:AL12) -> 0
A13: Average project contract value | B13: Fixed-fee project equivalent; grows with pricing and mix | C13: ='Assumptions'!$F$17 -> 0 | D13: =C13*(1+'Assumptions'!$F$18) -> 0 | E13: =D13*(1+'Assumptions'!$F$18) -> 0 | F13: =E13*(1+'Assumptions'!$F$18) -> 0 | G13: =F13*(1+'Assumptions'!$F$18) -> 0 | H13: =G13*(1+'Assumptions'!$F$18) -> 0 | I13: =H13*(1+'Assumptions'!$F$18) -> 0 | J13: =I13*(1+'Assumptions'!$F$18) -> 0 | K13: =J13*(1+'Assumptions'!$F$18) -> 0 | ... AL13: =AK13*(1+'Assumptions'!$F$18) -> 0 | AN13: =AVERAGE(C13:E13) -> 0 | AO13: =AVERAGE(F13:H13) -> 0 | AP13: =AVERAGE(I13:K13) -> 0 | AQ13: =AVERAGE(L13:N13) -> 0 | AR13: =AVERAGE(O13:Q13) -> 0 | AS13: =AVERAGE(R13:T13) -> 0 | AT13: =AVERAGE(U13:W13) -> 0 | AU13: =AVERAGE(X13:Z13) -> 0 | AV13: =AVERAGE(AA13:AC13) -> 0 | AW13: =AVERAGE(AD13:AF13) -> 0 | AX13: =AVERAGE(AG13:AI13) -> 0 | AY13: =AVERAGE(AJ13:AL13) -> 0 | BA13: =AVERAGE(C13:N13) -> 0 | BB13: =AVERAGE(O13:Z13) -> 0 | BC13: =AVERAGE(AA13:AL13) -> 0
A14: New Bookings | B14: New projects booked x average project value | C14: =C12*C13 -> 0 | D14: =D12*D13 -> 0 | E14: =E12*E13 -> 0 | F14: =F12*F13 -> 0 | G14: =G12*G13 -> 0 | H14: =H12*H13 -> 0 | I14: =I12*I13 -> 0 | J14: =J12*J13 -> 0 | ... AL14: =AL12*AL13 -> 0 | AN14: =SUM(C14:E14) -> 0 | AO14: =SUM(F14:H14) -> 0 | AP14: =SUM(I14:K14) -> 0 | AQ14: =SUM(L14:N14) -> 0 | AR14: =SUM(O14:Q14) -> 0 | AS14: =SUM(R14:T14) -> 0 | AT14: =SUM(U14:W14) -> 0 | AU14: =SUM(X14:Z14) -> 0 | AV14: =SUM(AA14:AC14) -> 0 | AW14: =SUM(AD14:AF14) -> 0 | AX14: =SUM(AG14:AI14) -> 0 | AY14: =SUM(AJ14:AL14) -> 0 | BA14: =SUM(C14:N14) -> 0 | BB14: =SUM(O14:Z14) -> 0 | BC14: =SUM(AA14:AL14) -> 0
A16: Delivery Capacity
A17: Delivery / Consulting FTE | B17: Linked from Headcount tab | C17: ='Headcount'!$C$8 -> 0 | D17: ='Headcount'!$D$8 -> 0 | E17: ='Headcount'!$E$8 -> 0 | F17: ='Headcount'!$F$8 -> 0 | G17: ='Headcount'!$G$8 -> 0 | H17: ='Headcount'!$H$8 -> 0 | I17: ='Headcount'!$I$8 -> 0 | J17: ='Headcount'!$J$8 -> 0 | K17: ='Headcount'!$K$8 -> 0 | L17: ='Headcount'!$L$8 -> 0 | M17: ='Headcount'!$M$8 -> 0 | N17: ='Headcount'!$N$8 -> 0 | O17: ='Headcount'!$O$8 -> 0 | P17: ='Headcount'!$P$8 -> 0 | Q17: ='Headcount'!$Q$8 -> 0 | R17: ='Headcount'!$R$8 -> 0 | S17: ='Headcount'!$S$8 -> 0 | T17: ='Headcount'!$T$8 -> 0 | U17: ='Headcount'!$U$8 -> 0 | V17: ='Headcount'!$V$8 -> 0 | W17: ='Headcount'!$W$8 -> 0 | X17: ='Headcount'!$X$8 -> 0 | Y17: ='Headcount'!$Y$8 -> 0 | Z17: ='Headcount'!$Z$8 -> 0 | AA17: ='Headcount'!$AA$8 -> 0 | AB17: ='Headcount'!$AB$8 -> 0 | AC17: ='Headcount'!$AC$8 -> 0 | AD17: ='Headcount'!$AD$8 -> 0 | AE17: ='Headcount'!$AE$8 -> 0 | AF17: ='Headcount'!$AF$8 -> 0 | AG17: ='Headcount'!$AG$8 -> 0 | AH17: ='Headcount'!$AH$8 -> 0 | AI17: ='Headcount'!$AI$8 -> 0 | AJ17: ='Headcount'!$AJ$8 -> 0 | AK17: ='Headcount'!$AK$8 -> 0 | AL17: ='Headcount'!$AL$8 -> 0 | AN17: =E17 -> 0 | AO17: =H17 -> 0 | AP17: =K17 -> 0 | AQ17: =N17 -> 0 | AR17: =Q17 -> 0 | AS17: =T17 -> 0 | AT17: =W17 -> 0 | AU17: =Z17 -> 0 | AV17: =AC17 -> 0 | AW17: =AF17 -> 0 | AX17: =AI17 -> 0 | AY17: =AL17 -> 0 | BA17: =N17 -> 0 | BB17: =Z17 -> 0 | BC17: =AL17 -> 0
A18: Standard billable-hours capacity / Delivery FTE | B18: Per-FTE monthly capacity before AI uplift and utilization | C18: ='Assumptions'!$F$22 -> 0 | D18: ='Assumptions'!$F$22 -> 0 | E18: ='Assumptions'!$F$22 -> 0 | F18: ='Assumptions'!$F$22 -> 0 | G18: ='Assumptions'!$F$22 -> 0 | H18: ='Assumptions'!$F$22 -> 0 | I18: ='Assumptions'!$F$22 -> 0 | J18: ='Assumptions'!$F$22 -> 0 | ... AL18: ='Assumptions'!$F$22 -> 0 | AN18: =AVERAGE(C18:E18) -> 0 | AO18: =AVERAGE(F18:H18) -> 0 | AP18: =AVERAGE(I18:K18) -> 0 | AQ18: =AVERAGE(L18:N18) -> 0 | AR18: =AVERAGE(O18:Q18) -> 0 | AS18: =AVERAGE(R18:T18) -> 0 | AT18: =AVERAGE(U18:W18) -> 0 | AU18: =AVERAGE(X18:Z18) -> 0 | AV18: =AVERAGE(AA18:AC18) -> 0 | AW18: =AVERAGE(AD18:AF18) -> 0 | AX18: =AVERAGE(AG18:AI18) -> 0 | AY18: =AVERAGE(AJ18:AL18) -> 0 | BA18: =AVERAGE(C18:N18) -> 0 | BB18: =AVERAGE(O18:Z18) -> 0 | BC18: =AVERAGE(AA18:AL18) -> 0
A19: Standard delivery capacity hours | B19: Delivery FTE x standard billable-hours capacity | C19: =C17*C18 -> 0 | D19: =D17*D18 -> 0 | E19: =E17*E18 -> 0 | F19: =F17*F18 -> 0 | G19: =G17*G18 -> 0 | H19: =H17*H18 -> 0 | I19: =I17*I18 -> 0 | J19: =J17*J18 -> 0 | ... AL19: =AL17*AL18 -> 0 | AN19: =SUM(C19:E19) -> 0 | AO19: =SUM(F19:H19) -> 0 | AP19: =SUM(I19:K19) -> 0 | AQ19: =SUM(L19:N19) -> 0 | AR19: =SUM(O19:Q19) -> 0 | AS19: =SUM(R19:T19) -> 0 | AT19: =SUM(U19:W19) -> 0 | AU19: =SUM(X19:Z19) -> 0 | AV19: =SUM(AA19:AC19) -> 0 | AW19: =SUM(AD19:AF19) -> 0 | AX19: =SUM(AG19:AI19) -> 0 | AY19: =SUM(AJ19:AL19) -> 0 | BA19: =SUM(C19:N19) -> 0 | BB19: =SUM(O19:Z19) -> 0 | BC19: =SUM(AA19:AL19) -> 0
A20: AI productivity uplift | B20: AI-assisted hours improve effective delivery capacity | C20: ='Assumptions'!$F$27 -> 0 | D20: ='Assumptions'!$F$27 -> 0 | E20: ='Assumptions'!$F$27 -> 0 | F20: ='Assumptions'!$F$27 -> 0 | G20: ='Assumptions'!$F$27 -> 0 | H20: ='Assumptions'!$F$27 -> 0 | I20: ='Assumptions'!$F$27 -> 0 | J20: ='Assumptions'!$F$27 -> 0 | ... AL20: ='Assumptions'!$F$27 -> 0 | AN20: =AVERAGE(C20:E20) -> 0 | AO20: =AVERAGE(F20:H20) -> 0 | AP20: =AVERAGE(I20:K20) -> 0 | AQ20: =AVERAGE(L20:N20) -> 0 | AR20: =AVERAGE(O20:Q20) -> 0 | AS20: =AVERAGE(R20:T20) -> 0 | AT20: =AVERAGE(U20:W20) -> 0 | AU20: =AVERAGE(X20:Z20) -> 0 | AV20: =AVERAGE(AA20:AC20) -> 0 | AW20: =AVERAGE(AD20:AF20) -> 0 | AX20: =AVERAGE(AG20:AI20) -> 0 | AY20: =AVERAGE(AJ20:AL20) -> 0 | BA20: =AVERAGE(C20:N20) -> 0 | BB20: =AVERAGE(O20:Z20) -> 0 | BC20: =AVERAGE(AA20:AL20) -> 0
A21: Effective capacity hours (post-AI) | B21: Standard capacity x (1 + AI productivity uplift) | C21: =C19*(1+C20) -> 0 | D21: =D19*(1+D20) -> 0 | E21: =E19*(1+E20) -> 0 | F21: =F19*(1+F20) -> 0 | G21: =G19*(1+G20) -> 0 | H21: =H19*(1+H20) -> 0 | I21: =I19*(1+I20) -> 0 | J21: =J19*(1+J20) -> 0 | ... AL21: =AL19*(1+AL20) -> 0 | AN21: =SUM(C21:E21) -> 0 | AO21: =SUM(F21:H21) -> 0 | AP21: =SUM(I21:K21) -> 0 | AQ21: =SUM(L21:N21) -> 0 | AR21: =SUM(O21:Q21) -> 0 | AS21: =SUM(R21:T21) -> 0 | AT21: =SUM(U21:W21) -> 0 | AU21: =SUM(X21:Z21) -> 0 | AV21: =SUM(AA21:AC21) -> 0 | AW21: =SUM(AD21:AF21) -> 0 | AX21: =SUM(AG21:AI21) -> 0 | AY21: =SUM(AJ21:AL21) -> 0 | BA21: =SUM(C21:N21) -> 0 | BB21: =SUM(O21:Z21) -> 0 | BC21: =SUM(AA21:AL21) -> 0
A22: Target utilization | B22: Share of effective capacity expected to be client-billable | C22: ='Assumptions'!$F$23 -> 0 | D22: ='Assumptions'!$F$23 -> 0 | E22: ='Assumptions'!$F$23 -> 0 | F22: ='Assumptions'!$F$23 -> 0 | G22: ='Assumptions'!$F$23 -> 0 | H22: ='Assumptions'!$F$23 -> 0 | I22: ='Assumptions'!$F$23 -> 0 | J22: ='Assumptions'!$F$23 -> 0 | ... AL22: ='Assumptions'!$F$23 -> 0 | AN22: =AVERAGE(C22:E22) -> 0 | AO22: =AVERAGE(F22:H22) -> 0 | AP22: =AVERAGE(I22:K22) -> 0 | AQ22: =AVERAGE(L22:N22) -> 0 | AR22: =AVERAGE(O22:Q22) -> 0 | AS22: =AVERAGE(R22:T22) -> 0 | AT22: =AVERAGE(U22:W22) -> 0 | AU22: =AVERAGE(X22:Z22) -> 0 | AV22: =AVERAGE(AA22:AC22) -> 0 | AW22: =AVERAGE(AD22:AF22) -> 0 | AX22: =AVERAGE(AG22:AI22) -> 0 | AY22: =AVERAGE(AJ22:AL22) -> 0 | BA22: =AVERAGE(C22:N22) -> 0 | BB22: =AVERAGE(O22:Z22) -> 0 | BC22: =AVERAGE(AA22:AL22) -> 0
A23: Standard blended billing rate | B23: Starting rate grown by monthly price/mix improvement | C23: ='Assumptions'!$F$25 -> 0 | D23: =C23*(1+'Assumptions'!$F$26) -> 0 | E23: =D23*(1+'Assumptions'!$F$26) -> 0 | F23: =E23*(1+'Assumptions'!$F$26) -> 0 | G23: =F23*(1+'Assumptions'!$F$26) -> 0 | H23: =G23*(1+'Assumptions'!$F$26) -> 0 | I23: =H23*(1+'Assumptions'!$F$26) -> 0 | J23: =I23*(1+'Assumptions'!$F$26) -> 0 | K23: =J23*(1+'Assumptions'!$F$26) -> 0 | ... AL23: =AK23*(1+'Assumptions'!$F$26) -> 0 | AN23: =AVERAGE(C23:E23) -> 0 | AO23: =AVERAGE(F23:H23) -> 0 | AP23: =AVERAGE(I23:K23) -> 0 | AQ23: =AVERAGE(L23:N23) -> 0 | AR23: =AVERAGE(O23:Q23) -> 0 | AS23: =AVERAGE(R23:T23) -> 0 | AT23: =AVERAGE(U23:W23) -> 0 | AU23: =AVERAGE(X23:Z23) -> 0 | AV23: =AVERAGE(AA23:AC23) -> 0 | AW23: =AVERAGE(AD23:AF23) -> 0 | AX23: =AVERAGE(AG23:AI23) -> 0 | AY23: =AVERAGE(AJ23:AL23) -> 0 | BA23: =AVERAGE(C23:N23) -> 0 | BB23: =AVERAGE(O23:Z23) -> 0 | BC23: =AVERAGE(AA23:AL23) -> 0
A24: Realization rate | B24: Collected / billed rate versus standard rate | C24: ='Assumptions'!$F$24 -> 0 | D24: ='Assumptions'!$F$24 -> 0 | E24: ='Assumptions'!$F$24 -> 0 | F24: ='Assumptions'!$F$24 -> 0 | G24: ='Assumptions'!$F$24 -> 0 | H24: ='Assumptions'!$F$24 -> 0 | I24: ='Assumptions'!$F$24 -> 0 | J24: ='Assumptions'!$F$24 -> 0 | ... AL24: ='Assumptions'!$F$24 -> 0 | AN24: =AVERAGE(C24:E24) -> 0 | AO24: =AVERAGE(F24:H24) -> 0 | AP24: =AVERAGE(I24:K24) -> 0 | AQ24: =AVERAGE(L24:N24) -> 0 | AR24: =AVERAGE(O24:Q24) -> 0 | AS24: =AVERAGE(R24:T24) -> 0 | AT24: =AVERAGE(U24:W24) -> 0 | AU24: =AVERAGE(X24:Z24) -> 0 | AV24: =AVERAGE(AA24:AC24) -> 0 | AW24: =AVERAGE(AD24:AF24) -> 0 | AX24: =AVERAGE(AG24:AI24) -> 0 | AY24: =AVERAGE(AJ24:AL24) -> 0 | BA24: =AVERAGE(C24:N24) -> 0 | BB24: =AVERAGE(O24:Z24) -> 0 | BC24: =AVERAGE(AA24:AL24) -> 0
A25: Realized billing rate | B25: Standard blended rate x realization rate | C25: =C23*C24 -> 0 | D25: =D23*D24 -> 0 | E25: =E23*E24 -> 0 | F25: =F23*F24 -> 0 | G25: =G23*G24 -> 0 | H25: =H23*H24 -> 0 | I25: =I23*I24 -> 0 | J25: =J23*J24 -> 0 | ... AL25: =AL23*AL24 -> 0 | AN25: =AVERAGE(C25:E25) -> 0 | AO25: =AVERAGE(F25:H25) -> 0 | AP25: =AVERAGE(I25:K25) -> 0 | AQ25: =AVERAGE(L25:N25) -> 0 | AR25: =AVERAGE(O25:Q25) -> 0 | AS25: =AVERAGE(R25:T25) -> 0 | AT25: =AVERAGE(U25:W25) -> 0 | AU25: =AVERAGE(X25:Z25) -> 0 | AV25: =AVERAGE(AA25:AC25) -> 0 | AW25: =AVERAGE(AD25:AF25) -> 0 | AX25: =AVERAGE(AG25:AI25) -> 0 | AY25: =AVERAGE(AJ25:AL25) -> 0 | BA25: =AVERAGE(C25:N25) -> 0 | BB25: =AVERAGE(O25:Z25) -> 0 | BC25: =AVERAGE(AA25:AL25) -> 0
A26: Revenue capacity at target utilization | B26: Effective capacity hours x utilization x realized rate | C26: =C21*C22*C25 -> 0 | D26: =D21*D22*D25 -> 0 | E26: =E21*E22*E25 -> 0 | F26: =F21*F22*F25 -> 0 | G26: =G21*G22*G25 -> 0 | H26: =H21*H22*H25 -> 0 | I26: =I21*I22*I25 -> 0 | J26: =J21*J22*J25 -> 0 | ... AL26: =AL21*AL22*AL25 -> 0 | AN26: =SUM(C26:E26) -> 0 | AO26: =SUM(F26:H26) -> 0 | AP26: =SUM(I26:K26) -> 0 | AQ26: =SUM(L26:N26) -> 0 | AR26: =SUM(O26:Q26) -> 0 | AS26: =SUM(R26:T26) -> 0 | AT26: =SUM(U26:W26) -> 0 | AU26: =SUM(X26:Z26) -> 0 | AV26: =SUM(AA26:AC26) -> 0 | AW26: =SUM(AD26:AF26) -> 0 | AX26: =SUM(AG26:AI26) -> 0 | AY26: =SUM(AJ26:AL26) -> 0 | BA26: =SUM(C26:N26) -> 0 | BB26: =SUM(O26:Z26) -> 0 | BC26: =SUM(AA26:AL26) -> 0
A28: Backlog & Revenue Recognition
A29: Beginning Backlog | B29: Prior month ending backlog; month 1 seeded from assumptions | C29: ='Assumptions'!$F$13 -> 0 | D29: =C35 -> 0 | E29: =D35 -> 0 | F29: =E35 -> 0 | G29: =F35 -> 0 | H29: =G35 -> 0 | I29: =H35 -> 0 | J29: =I35 -> 0 | K29: =J35 -> 0 | ... AL29: =AK35 -> 0 | AN29: =E29 -> 0 | AO29: =H29 -> 0 | AP29: =K29 -> 0 | AQ29: =N29 -> 0 | AR29: =Q29 -> 0 | AS29: =T29 -> 0 | AT29: =W29 -> 0 | AU29: =Z29 -> 0 | AV29: =AC29 -> 0 | AW29: =AF29 -> 0 | AX29: =AI29 -> 0 | AY29: =AL29 -> 0 | BA29: =N29 -> 0 | BB29: =Z29 -> 0 | BC29: =AL29 -> 0
A30: + New Bookings | B30: Linked from Pipeline & Bookings above | C30: ='Revenue'!$C$14 -> 0 | D30: ='Revenue'!$D$14 -> 0 | E30: ='Revenue'!$E$14 -> 0 | F30: ='Revenue'!$F$14 -> 0 | G30: ='Revenue'!$G$14 -> 0 | H30: ='Revenue'!$H$14 -> 0 | I30: ='Revenue'!$I$14 -> 0 | J30: ='Revenue'!$J$14 -> 0 | K30: ='Revenue'!$K$14 -> 0 | L30: ='Revenue'!$L$14 -> 0 | M30: ='Revenue'!$M$14 -> 0 | N30: ='Revenue'!$N$14 -> 0 | O30: ='Revenue'!$O$14 -> 0 | P30: ='Revenue'!$P$14 -> 0 | Q30: ='Revenue'!$Q$14 -> 0 | R30: ='Revenue'!$R$14 -> 0 | S30: ='Revenue'!$S$14 -> 0 | T30: ='Revenue'!$T$14 -> 0 | U30: ='Revenue'!$U$14 -> 0 | V30: ='Revenue'!$V$14 -> 0 | W30: ='Revenue'!$W$14 -> 0 | X30: ='Revenue'!$X$14 -> 0 | Y30: ='Revenue'!$Y$14 -> 0 | Z30: ='Revenue'!$Z$14 -> 0 | AA30: ='Revenue'!$AA$14 -> 0 | AB30: ='Revenue'!$AB$14 -> 0 | AC30: ='Revenue'!$AC$14 -> 0 | AD30: ='Revenue'!$AD$14 -> 0 | AE30: ='Revenue'!$AE$14 -> 0 | AF30: ='Revenue'!$AF$14 -> 0 | AG30: ='Revenue'!$AG$14 -> 0 | AH30: ='Revenue'!$AH$14 -> 0 | AI30: ='Revenue'!$AI$14 -> 0 | AJ30: ='Revenue'!$AJ$14 -> 0 | AK30: ='Revenue'!$AK$14 -> 0 | AL30: ='Revenue'!$AL$14 -> 0 | AN30: =SUM(C30:E30) -> 0 | AO30: =SUM(F30:H30) -> 0 | AP30: =SUM(I30:K30) -> 0 | AQ30: =SUM(L30:N30) -> 0 | AR30: =SUM(O30:Q30) -> 0 | AS30: =SUM(R30:T30) -> 0 | AT30: =SUM(U30:W30) -> 0 | AU30: =SUM(X30:Z30) -> 0 | AV30: =SUM(AA30:AC30) -> 0 | AW30: =SUM(AD30:AF30) -> 0 | AX30: =SUM(AG30:AI30) -> 0 | AY30: =SUM(AJ30:AL30) -> 0 | BA30: =SUM(C30:N30) -> 0 | BB30: =SUM(O30:Z30) -> 0 | BC30: =SUM(AA30:AL30) -> 0
A31: Backlog available to deliver | B31: Beginning backlog + new bookings | C31: =C29+'Revenue'!C14 -> 0 | D31: =D29+'Revenue'!D14 -> 0 | E31: =E29+'Revenue'!E14 -> 0 | F31: =F29+'Revenue'!F14 -> 0 | G31: =G29+'Revenue'!G14 -> 0 | H31: =H29+'Revenue'!H14 -> 0 | I31: =I29+'Revenue'!I14 -> 0 | J31: =J29+'Revenue'!J14 -> 0 | ... AL31: =AL29+'Revenue'!AL14 -> 0 | AN31: =E31 -> 0 | AO31: =H31 -> 0 | AP31: =K31 -> 0 | AQ31: =N31 -> 0 | AR31: =Q31 -> 0 | AS31: =T31 -> 0 | AT31: =W31 -> 0 | AU31: =Z31 -> 0 | AV31: =AC31 -> 0 | AW31: =AF31 -> 0 | AX31: =AI31 -> 0 | AY31: =AL31 -> 0 | BA31: =N31 -> 0 | BB31: =Z31 -> 0 | BC31: =AL31 -> 0
A32: Revenue recognized at project-duration pace | B32: Backlog available / average project duration | C32: =C31/MAX(1,'Assumptions'!$F$19) -> 0 | D32: =D31/MAX(1,'Assumptions'!$F$19) -> 0 | E32: =E31/MAX(1,'Assumptions'!$F$19) -> 0 | F32: =F31/MAX(1,'Assumptions'!$F$19) -> 0 | G32: =G31/MAX(1,'Assumptions'!$F$19) -> 0 | H32: =H31/MAX(1,'Assumptions'!$F$19) -> 0 | I32: =I31/MAX(1,'Assumptions'!$F$19) -> 0 | J32: =J31/MAX(1,'Assumptions'!$F$19) -> 0 | ... AL32: =AL31/MAX(1,'Assumptions'!$F$19) -> 0 | AN32: =SUM(C32:E32) -> 0 | AO32: =SUM(F32:H32) -> 0 | AP32: =SUM(I32:K32) -> 0 | AQ32: =SUM(L32:N32) -> 0 | AR32: =SUM(O32:Q32) -> 0 | AS32: =SUM(R32:T32) -> 0 | AT32: =SUM(U32:W32) -> 0 | AU32: =SUM(X32:Z32) -> 0 | AV32: =SUM(AA32:AC32) -> 0 | AW32: =SUM(AD32:AF32) -> 0 | AX32: =SUM(AG32:AI32) -> 0 | AY32: =SUM(AJ32:AL32) -> 0 | BA32: =SUM(C32:N32) -> 0 | BB32: =SUM(O32:Z32) -> 0 | BC32: =SUM(AA32:AL32) -> 0
A33: Revenue recognized at delivery capacity | B33: Linked from delivery-capacity calculation above | C33: ='Revenue'!$C$26 -> 0 | D33: ='Revenue'!$D$26 -> 0 | E33: ='Revenue'!$E$26 -> 0 | F33: ='Revenue'!$F$26 -> 0 | G33: ='Revenue'!$G$26 -> 0 | H33: ='Revenue'!$H$26 -> 0 | I33: ='Revenue'!$I$26 -> 0 | J33: ='Revenue'!$J$26 -> 0 | K33: ='Revenue'!$K$26 -> 0 | L33: ='Revenue'!$L$26 -> 0 | M33: ='Revenue'!$M$26 -> 0 | N33: ='Revenue'!$N$26 -> 0 | O33: ='Revenue'!$O$26 -> 0 | P33: ='Revenue'!$P$26 -> 0 | Q33: ='Revenue'!$Q$26 -> 0 | R33: ='Revenue'!$R$26 -> 0 | S33: ='Revenue'!$S$26 -> 0 | T33: ='Revenue'!$T$26 -> 0 | U33: ='Revenue'!$U$26 -> 0 | V33: ='Revenue'!$V$26 -> 0 | W33: ='Revenue'!$W$26 -> 0 | X33: ='Revenue'!$X$26 -> 0 | Y33: ='Revenue'!$Y$26 -> 0 | Z33: ='Revenue'!$Z$26 -> 0 | AA33: ='Revenue'!$AA$26 -> 0 | AB33: ='Revenue'!$AB$26 -> 0 | AC33: ='Revenue'!$AC$26 -> 0 | AD33: ='Revenue'!$AD$26 -> 0 | AE33: ='Revenue'!$AE$26 -> 0 | AF33: ='Revenue'!$AF$26 -> 0 | AG33: ='Revenue'!$AG$26 -> 0 | AH33: ='Revenue'!$AH$26 -> 0 | AI33: ='Revenue'!$AI$26 -> 0 | AJ33: ='Revenue'!$AJ$26 -> 0 | AK33: ='Revenue'!$AK$26 -> 0 | AL33: ='Revenue'!$AL$26 -> 0 | AN33: =SUM(C33:E33) -> 0 | AO33: =SUM(F33:H33) -> 0 | AP33: =SUM(I33:K33) -> 0 | AQ33: =SUM(L33:N33) -> 0 | AR33: =SUM(O33:Q33) -> 0 | AS33: =SUM(R33:T33) -> 0 | AT33: =SUM(U33:W33) -> 0 | AU33: =SUM(X33:Z33) -> 0 | AV33: =SUM(AA33:AC33) -> 0 | AW33: =SUM(AD33:AF33) -> 0 | AX33: =SUM(AG33:AI33) -> 0 | AY33: =SUM(AJ33:AL33) -> 0 | BA33: =SUM(C33:N33) -> 0 | BB33: =SUM(O33:Z33) -> 0 | BC33: =SUM(AA33:AL33) -> 0
A34: Revenue Recognized | B34: The lower of backlog runoff pace and delivery capacity | C34: =MIN(C32,C33) -> 0 | D34: =MIN(D32,D33) -> 0 | E34: =MIN(E32,E33) -> 0 | F34: =MIN(F32,F33) -> 0 | G34: =MIN(G32,G33) -> 0 | H34: =MIN(H32,H33) -> 0 | I34: =MIN(I32,I33) -> 0 | J34: =MIN(J32,J33) -> 0 | ... AL34: =MIN(AL32,AL33) -> 0 | AN34: =SUM(C34:E34) -> 0 | AO34: =SUM(F34:H34) -> 0 | AP34: =SUM(I34:K34) -> 0 | AQ34: =SUM(L34:N34) -> 0 | AR34: =SUM(O34:Q34) -> 0 | AS34: =SUM(R34:T34) -> 0 | AT34: =SUM(U34:W34) -> 0 | AU34: =SUM(X34:Z34) -> 0 | AV34: =SUM(AA34:AC34) -> 0 | AW34: =SUM(AD34:AF34) -> 0 | AX34: =SUM(AG34:AI34) -> 0 | AY34: =SUM(AJ34:AL34) -> 0 | BA34: =SUM(C34:N34) -> 0 | BB34: =SUM(O34:Z34) -> 0 | BC34: =SUM(AA34:AL34) -> 0
A35: Ending Backlog | B35: Backlog available to deliver - revenue recognized | C35: =C31-C34 -> 0 | D35: =D31-D34 -> 0 | E35: =E31-E34 -> 0 | F35: =F31-F34 -> 0 | G35: =G31-G34 -> 0 | H35: =H31-H34 -> 0 | I35: =I31-I34 -> 0 | J35: =J31-J34 -> 0 | ... AL35: =AL31-AL34 -> 0 | AN35: =E35 -> 0 | AO35: =H35 -> 0 | AP35: =K35 -> 0 | AQ35: =N35 -> 0 | AR35: =Q35 -> 0 | AS35: =T35 -> 0 | AT35: =W35 -> 0 | AU35: =Z35 -> 0 | AV35: =AC35 -> 0 | AW35: =AF35 -> 0 | AX35: =AI35 -> 0 | AY35: =AL35 -> 0 | BA35: =N35 -> 0 | BB35: =Z35 -> 0 | BC35: =AL35 -> 0
A36: Total Revenue | B36: Services revenue equals recognized project delivery | C36: ='Revenue'!$C$34 -> 0 | D36: ='Revenue'!$D$34 -> 0 | E36: ='Revenue'!$E$34 -> 0 | F36: ='Revenue'!$F$34 -> 0 | G36: ='Revenue'!$G$34 -> 0 | H36: ='Revenue'!$H$34 -> 0 | I36: ='Revenue'!$I$34 -> 0 | J36: ='Revenue'!$J$34 -> 0 | K36: ='Revenue'!$K$34 -> 0 | L36: ='Revenue'!$L$34 -> 0 | M36: ='Revenue'!$M$34 -> 0 | N36: ='Revenue'!$N$34 -> 0 | O36: ='Revenue'!$O$34 -> 0 | P36: ='Revenue'!$P$34 -> 0 | Q36: ='Revenue'!$Q$34 -> 0 | R36: ='Revenue'!$R$34 -> 0 | S36: ='Revenue'!$S$34 -> 0 | T36: ='Revenue'!$T$34 -> 0 | U36: ='Revenue'!$U$34 -> 0 | V36: ='Revenue'!$V$34 -> 0 | W36: ='Revenue'!$W$34 -> 0 | X36: ='Revenue'!$X$34 -> 0 | Y36: ='Revenue'!$Y$34 -> 0 | Z36: ='Revenue'!$Z$34 -> 0 | AA36: ='Revenue'!$AA$34 -> 0 | AB36: ='Revenue'!$AB$34 -> 0 | AC36: ='Revenue'!$AC$34 -> 0 | AD36: ='Revenue'!$AD$34 -> 0 | AE36: ='Revenue'!$AE$34 -> 0 | AF36: ='Revenue'!$AF$34 -> 0 | AG36: ='Revenue'!$AG$34 -> 0 | AH36: ='Revenue'!$AH$34 -> 0 | AI36: ='Revenue'!$AI$34 -> 0 | AJ36: ='Revenue'!$AJ$34 -> 0 | AK36: ='Revenue'!$AK$34 -> 0 | AL36: ='Revenue'!$AL$34 -> 0 | AN36: =SUM(C36:E36) -> 0 | AO36: =SUM(F36:H36) -> 0 | AP36: =SUM(I36:K36) -> 0 | AQ36: =SUM(L36:N36) -> 0 | AR36: =SUM(O36:Q36) -> 0 | AS36: =SUM(R36:T36) -> 0 | AT36: =SUM(U36:W36) -> 0 | AU36: =SUM(X36:Z36) -> 0 | AV36: =SUM(AA36:AC36) -> 0 | AW36: =SUM(AD36:AF36) -> 0 | AX36: =SUM(AG36:AI36) -> 0 | AY36: =SUM(AJ36:AL36) -> 0 | BA36: =SUM(C36:N36) -> 0 | BB36: =SUM(O36:Z36) -> 0 | BC36: =SUM(AA36:AL36) -> 0
A38: Service Delivery KPIs
A39: Billable hours delivered | B39: Revenue recognized / realized billing rate | C39: =IFERROR(C34/C25,0) -> 0 | D39: =IFERROR(D34/D25,0) -> 0 | E39: =IFERROR(E34/E25,0) -> 0 | F39: =IFERROR(F34/F25,0) -> 0 | G39: =IFERROR(G34/G25,0) -> 0 | H39: =IFERROR(H34/H25,0) -> 0 | I39: =IFERROR(I34/I25,0) -> 0 | J39: =IFERROR(J34/J25,0) -> 0 | ... AL39: =IFERROR(AL34/AL25,0) -> 0 | AN39: =SUM(C39:E39) -> 0 | AO39: =SUM(F39:H39) -> 0 | AP39: =SUM(I39:K39) -> 0 | AQ39: =SUM(L39:N39) -> 0 | AR39: =SUM(O39:Q39) -> 0 | AS39: =SUM(R39:T39) -> 0 | AT39: =SUM(U39:W39) -> 0 | AU39: =SUM(X39:Z39) -> 0 | AV39: =SUM(AA39:AC39) -> 0 | AW39: =SUM(AD39:AF39) -> 0 | AX39: =SUM(AG39:AI39) -> 0 | AY39: =SUM(AJ39:AL39) -> 0 | BA39: =SUM(C39:N39) -> 0 | BB39: =SUM(O39:Z39) -> 0 | BC39: =SUM(AA39:AL39) -> 0
A40: Utilization % | B40: Billable hours delivered / effective capacity hours | C40: =IFERROR(C39/C21,0) -> 0 | D40: =IFERROR(D39/D21,0) -> 0 | E40: =IFERROR(E39/E21,0) -> 0 | F40: =IFERROR(F39/F21,0) -> 0 | G40: =IFERROR(G39/G21,0) -> 0 | H40: =IFERROR(H39/H21,0) -> 0 | I40: =IFERROR(I39/I21,0) -> 0 | J40: =IFERROR(J39/J21,0) -> 0 | ... AL40: =IFERROR(AL39/AL21,0) -> 0 | AN40: =AVERAGE(C40:E40) -> 0 | AO40: =AVERAGE(F40:H40) -> 0 | AP40: =AVERAGE(I40:K40) -> 0 | AQ40: =AVERAGE(L40:N40) -> 0 | AR40: =AVERAGE(O40:Q40) -> 0 | AS40: =AVERAGE(R40:T40) -> 0 | AT40: =AVERAGE(U40:W40) -> 0 | AU40: =AVERAGE(X40:Z40) -> 0 | AV40: =AVERAGE(AA40:AC40) -> 0 | AW40: =AVERAGE(AD40:AF40) -> 0 | AX40: =AVERAGE(AG40:AI40) -> 0 | AY40: =AVERAGE(AJ40:AL40) -> 0 | BA40: =AVERAGE(C40:N40) -> 0 | BB40: =AVERAGE(O40:Z40) -> 0 | BC40: =AVERAGE(AA40:AL40) -> 0
A41: Realization % | B41: Realized rate / standard blended billing rate | C41: =IFERROR(C25/C23,0) -> 0 | D41: =IFERROR(D25/D23,0) -> 0 | E41: =IFERROR(E25/E23,0) -> 0 | F41: =IFERROR(F25/F23,0) -> 0 | G41: =IFERROR(G25/G23,0) -> 0 | H41: =IFERROR(H25/H23,0) -> 0 | I41: =IFERROR(I25/I23,0) -> 0 | J41: =IFERROR(J25/J23,0) -> 0 | ... AL41: =IFERROR(AL25/AL23,0) -> 0 | AN41: =AVERAGE(C41:E41) -> 0 | AO41: =AVERAGE(F41:H41) -> 0 | AP41: =AVERAGE(I41:K41) -> 0 | AQ41: =AVERAGE(L41:N41) -> 0 | AR41: =AVERAGE(O41:Q41) -> 0 | AS41: =AVERAGE(R41:T41) -> 0 | AT41: =AVERAGE(U41:W41) -> 0 | AU41: =AVERAGE(X41:Z41) -> 0 | AV41: =AVERAGE(AA41:AC41) -> 0 | AW41: =AVERAGE(AD41:AF41) -> 0 | AX41: =AVERAGE(AG41:AI41) -> 0 | AY41: =AVERAGE(AJ41:AL41) -> 0 | BA41: =AVERAGE(C41:N41) -> 0 | BB41: =AVERAGE(O41:Z41) -> 0 | BC41: =AVERAGE(AA41:AL41) -> 0
A42: Revenue per Delivery FTE | B42: Total revenue / delivery FTE | C42: =IFERROR(C36/C17,0) -> 0 | D42: =IFERROR(D36/D17,0) -> 0 | E42: =IFERROR(E36/E17,0) -> 0 | F42: =IFERROR(F36/F17,0) -> 0 | G42: =IFERROR(G36/G17,0) -> 0 | H42: =IFERROR(H36/H17,0) -> 0 | I42: =IFERROR(I36/I17,0) -> 0 | J42: =IFERROR(J36/J17,0) -> 0 | ... AL42: =IFERROR(AL36/AL17,0) -> 0 | AN42: =AVERAGE(C42:E42) -> 0 | AO42: =AVERAGE(F42:H42) -> 0 | AP42: =AVERAGE(I42:K42) -> 0 | AQ42: =AVERAGE(L42:N42) -> 0 | AR42: =AVERAGE(O42:Q42) -> 0 | AS42: =AVERAGE(R42:T42) -> 0 | AT42: =AVERAGE(U42:W42) -> 0 | AU42: =AVERAGE(X42:Z42) -> 0 | AV42: =AVERAGE(AA42:AC42) -> 0 | AW42: =AVERAGE(AD42:AF42) -> 0 | AX42: =AVERAGE(AG42:AI42) -> 0 | AY42: =AVERAGE(AJ42:AL42) -> 0 | BA42: =AVERAGE(C42:N42) -> 0 | BB42: =AVERAGE(O42:Z42) -> 0 | BC42: =AVERAGE(AA42:AL42) -> 0
A43: Trailing 3-month avg revenue | B43: Used for backlog coverage KPI | C43: =AVERAGE(C36:C36) -> 0 | D43: =AVERAGE(C36:D36) -> 0 | E43: =AVERAGE(C36:E36) -> 0 | F43: =AVERAGE(D36:F36) -> 0 | G43: =AVERAGE(E36:G36) -> 0 | H43: =AVERAGE(F36:H36) -> 0 | I43: =AVERAGE(G36:I36) -> 0 | J43: =AVERAGE(H36:J36) -> 0 | K43: =AVERAGE(I36:K36) -> 0 | L43: =AVERAGE(J36:L36) -> 0 | ... AL43: =AVERAGE(AJ36:AL36) -> 0 | AN43: =AVERAGE(C43:E43) -> 0 | AO43: =AVERAGE(F43:H43) -> 0 | AP43: =AVERAGE(I43:K43) -> 0 | AQ43: =AVERAGE(L43:N43) -> 0 | AR43: =AVERAGE(O43:Q43) -> 0 | AS43: =AVERAGE(R43:T43) -> 0 | AT43: =AVERAGE(U43:W43) -> 0 | AU43: =AVERAGE(X43:Z43) -> 0 | AV43: =AVERAGE(AA43:AC43) -> 0 | AW43: =AVERAGE(AD43:AF43) -> 0 | AX43: =AVERAGE(AG43:AI43) -> 0 | AY43: =AVERAGE(AJ43:AL43) -> 0 | BA43: =AVERAGE(C43:N43) -> 0 | BB43: =AVERAGE(O43:Z43) -> 0 | BC43: =AVERAGE(AA43:AL43) -> 0
A44: Backlog coverage (months) | B44: Ending backlog / trailing 3-month revenue run-rate | C44: =IFERROR(C35/C43,0) -> 0 | D44: =IFERROR(D35/D43,0) -> 0 | E44: =IFERROR(E35/E43,0) -> 0 | F44: =IFERROR(F35/F43,0) -> 0 | G44: =IFERROR(G35/G43,0) -> 0 | H44: =IFERROR(H35/H43,0) -> 0 | I44: =IFERROR(I35/I43,0) -> 0 | J44: =IFERROR(J35/J43,0) -> 0 | ... AL44: =IFERROR(AL35/AL43,0) -> 0 | AN44: =AVERAGE(C44:E44) -> 0 | AO44: =AVERAGE(F44:H44) -> 0 | AP44: =AVERAGE(I44:K44) -> 0 | AQ44: =AVERAGE(L44:N44) -> 0 | AR44: =AVERAGE(O44:Q44) -> 0 | AS44: =AVERAGE(R44:T44) -> 0 | AT44: =AVERAGE(U44:W44) -> 0 | AU44: =AVERAGE(X44:Z44) -> 0 | AV44: =AVERAGE(AA44:AC44) -> 0 | AW44: =AVERAGE(AD44:AF44) -> 0 | AX44: =AVERAGE(AG44:AI44) -> 0 | AY44: =AVERAGE(AJ44:AL44) -> 0 | BA44: =AVERAGE(C44:N44) -> 0 | BB44: =AVERAGE(O44:Z44) -> 0 | BC44: =AVERAGE(AA44:AL44) -> 0
A45: AI productivity uplift | B45: Effective capacity / standard capacity - 1 | C45: =IFERROR(C21/C19-1,0) -> 0 | D45: =IFERROR(D21/D19-1,0) -> 0 | E45: =IFERROR(E21/E19-1,0) -> 0 | F45: =IFERROR(F21/F19-1,0) -> 0 | G45: =IFERROR(G21/G19-1,0) -> 0 | H45: =IFERROR(H21/H19-1,0) -> 0 | I45: =IFERROR(I21/I19-1,0) -> 0 | J45: =IFERROR(J21/J19-1,0) -> 0 | ... AL45: =IFERROR(AL21/AL19-1,0) -> 0 | AN45: =AVERAGE(C45:E45) -> 0 | AO45: =AVERAGE(F45:H45) -> 0 | AP45: =AVERAGE(I45:K45) -> 0 | AQ45: =AVERAGE(L45:N45) -> 0 | AR45: =AVERAGE(O45:Q45) -> 0 | AS45: =AVERAGE(R45:T45) -> 0 | AT45: =AVERAGE(U45:W45) -> 0 | AU45: =AVERAGE(X45:Z45) -> 0 | AV45: =AVERAGE(AA45:AC45) -> 0 | AW45: =AVERAGE(AD45:AF45) -> 0 | AX45: =AVERAGE(AG45:AI45) -> 0 | AY45: =AVERAGE(AJ45:AL45) -> 0 | BA45: =AVERAGE(C45:N45) -> 0 | BB45: =AVERAGE(O45:Z45) -> 0 | BC45: =AVERAGE(AA45:AL45) -> 0

Sheet COGS & GM
A1: AI-Enabled Services — 3-Year Financial Model — COGS & GM
A2: Delivery people, subcontractors, and AI tool/API spend roll up into project gross margin.
A5: Line item | B5: Units / source | C5: Monthly (36 months) | AN5: Quarterly | BA5: Annual
C6: 46023 | D6: 46054 | E6: 46082 | F6: 46113 | G6: 46143 | H6: 46174 | I6: 46204 | J6: 46235 | K6: 46266 | L6: 46296 | M6: 46327 | N6: 46357 | O6: 46388 | P6: 46419 | Q6: 46447 | R6: 46478 | S6: 46508 | T6: 46539 | U6: 46569 | V6: 46600 | W6: 46631 | X6: 46661 | Y6: 46692 | Z6: 46722 | AA6: 46753 | AB6: 46784 | AC6: 46813 | AD6: 46844 | AE6: 46874 | AF6: 46905 | AG6: 46935 | AH6: 46966 | AI6: 46997 | AJ6: 47027 | AK6: 47058 | AL6: 47088 | AN6: Q1 | AO6: Q2 | AP6: Q3 | AQ6: Q4 | AR6: Q5 | AS6: Q6 | AT6: Q7 | AU6: Q8 | AV6: Q9 | AW6: Q10 | AX6: Q11 | AY6: Q12 | BA6: FY1 | BB6: FY2 | BC6: FY3
A7: COGS Components
A8: Delivery / Consulting people cost | B8: Linked from Headcount tab | C8: ='Headcount'!$C$9 -> 0 | D8: ='Headcount'!$D$9 -> 0 | E8: ='Headcount'!$E$9 -> 0 | F8: ='Headcount'!$F$9 -> 0 | G8: ='Headcount'!$G$9 -> 0 | H8: ='Headcount'!$H$9 -> 0 | I8: ='Headcount'!$I$9 -> 0 | J8: ='Headcount'!$J$9 -> 0 | K8: ='Headcount'!$K$9 -> 0 | L8: ='Headcount'!$L$9 -> 0 | M8: ='Headcount'!$M$9 -> 0 | N8: ='Headcount'!$N$9 -> 0 | O8: ='Headcount'!$O$9 -> 0 | P8: ='Headcount'!$P$9 -> 0 | Q8: ='Headcount'!$Q$9 -> 0 | R8: ='Headcount'!$R$9 -> 0 | S8: ='Headcount'!$S$9 -> 0 | T8: ='Headcount'!$T$9 -> 0 | U8: ='Headcount'!$U$9 -> 0 | V8: ='Headcount'!$V$9 -> 0 | W8: ='Headcount'!$W$9 -> 0 | X8: ='Headcount'!$X$9 -> 0 | Y8: ='Headcount'!$Y$9 -> 0 | Z8: ='Headcount'!$Z$9 -> 0 | AA8: ='Headcount'!$AA$9 -> 0 | AB8: ='Headcount'!$AB$9 -> 0 | AC8: ='Headcount'!$AC$9 -> 0 | AD8: ='Headcount'!$AD$9 -> 0 | AE8: ='Headcount'!$AE$9 -> 0 | AF8: ='Headcount'!$AF$9 -> 0 | AG8: ='Headcount'!$AG$9 -> 0 | AH8: ='Headcount'!$AH$9 -> 0 | AI8: ='Headcount'!$AI$9 -> 0 | AJ8: ='Headcount'!$AJ$9 -> 0 | AK8: ='Headcount'!$AK$9 -> 0 | AL8: ='Headcount'!$AL$9 -> 0 | AN8: =SUM(C8:E8) -> 0 | AO8: =SUM(F8:H8) -> 0 | AP8: =SUM(I8:K8) -> 0 | AQ8: =SUM(L8:N8) -> 0 | AR8: =SUM(O8:Q8) -> 0 | AS8: =SUM(R8:T8) -> 0 | AT8: =SUM(U8:W8) -> 0 | AU8: =SUM(X8:Z8) -> 0 | AV8: =SUM(AA8:AC8) -> 0 | AW8: =SUM(AD8:AF8) -> 0 | AX8: =SUM(AG8:AI8) -> 0 | AY8: =SUM(AJ8:AL8) -> 0 | BA8: =SUM(C8:N8) -> 0 | BB8: =SUM(O8:Z8) -> 0 | BC8: =SUM(AA8:AL8) -> 0
A9: Delivery Management / Solutions people cost | B9: Linked from Headcount tab | C9: ='Headcount'!$C$11 -> 0 | D9: ='Headcount'!$D$11 -> 0 | E9: ='Headcount'!$E$11 -> 0 | F9: ='Headcount'!$F$11 -> 0 | G9: ='Headcount'!$G$11 -> 0 | H9: ='Headcount'!$H$11 -> 0 | I9: ='Headcount'!$I$11 -> 0 | J9: ='Headcount'!$J$11 -> 0 | K9: ='Headcount'!$K$11 -> 0 | L9: ='Headcount'!$L$11 -> 0 | M9: ='Headcount'!$M$11 -> 0 | N9: ='Headcount'!$N$11 -> 0 | O9: ='Headcount'!$O$11 -> 0 | P9: ='Headcount'!$P$11 -> 0 | Q9: ='Headcount'!$Q$11 -> 0 | R9: ='Headcount'!$R$11 -> 0 | S9: ='Headcount'!$S$11 -> 0 | T9: ='Headcount'!$T$11 -> 0 | U9: ='Headcount'!$U$11 -> 0 | V9: ='Headcount'!$V$11 -> 0 | W9: ='Headcount'!$W$11 -> 0 | X9: ='Headcount'!$X$11 -> 0 | Y9: ='Headcount'!$Y$11 -> 0 | Z9: ='Headcount'!$Z$11 -> 0 | AA9: ='Headcount'!$AA$11 -> 0 | AB9: ='Headcount'!$AB$11 -> 0 | AC9: ='Headcount'!$AC$11 -> 0 | AD9: ='Headcount'!$AD$11 -> 0 | AE9: ='Headcount'!$AE$11 -> 0 | AF9: ='Headcount'!$AF$11 -> 0 | AG9: ='Headcount'!$AG$11 -> 0 | AH9: ='Headcount'!$AH$11 -> 0 | AI9: ='Headcount'!$AI$11 -> 0 | AJ9: ='Headcount'!$AJ$11 -> 0 | AK9: ='Headcount'!$AK$11 -> 0 | AL9: ='Headcount'!$AL$11 -> 0 | AN9: =SUM(C9:E9) -> 0 | AO9: =SUM(F9:H9) -> 0 | AP9: =SUM(I9:K9) -> 0 | AQ9: =SUM(L9:N9) -> 0 | AR9: =SUM(O9:Q9) -> 0 | AS9: =SUM(R9:T9) -> 0 | AT9: =SUM(U9:W9) -> 0 | AU9: =SUM(X9:Z9) -> 0 | AV9: =SUM(AA9:AC9) -> 0 | AW9: =SUM(AD9:AF9) -> 0 | AX9: =SUM(AG9:AI9) -> 0 | AY9: =SUM(AJ9:AL9) -> 0 | BA9: =SUM(C9:N9) -> 0 | BB9: =SUM(O9:Z9) -> 0 | BC9: =SUM(AA9:AL9) -> 0
A10: Subcontractor costs | B10: Total revenue x subcontractor % | C10: ='Revenue'!C36*'Assumptions'!$F$30 -> 0 | D10: ='Revenue'!D36*'Assumptions'!$F$30 -> 0 | E10: ='Revenue'!E36*'Assumptions'!$F$30 -> 0 | F10: ='Revenue'!F36*'Assumptions'!$F$30 -> 0 | G10: ='Revenue'!G36*'Assumptions'!$F$30 -> 0 | H10: ='Revenue'!H36*'Assumptions'!$F$30 -> 0 | I10: ='Revenue'!I36*'Assumptions'!$F$30 -> 0 | J10: ='Revenue'!J36*'Assumptions'!$F$30 -> 0 | ... AL10: ='Revenue'!AL36*'Assumptions'!$F$30 -> 0 | AN10: =SUM(C10:E10) -> 0 | AO10: =SUM(F10:H10) -> 0 | AP10: =SUM(I10:K10) -> 0 | AQ10: =SUM(L10:N10) -> 0 | AR10: =SUM(O10:Q10) -> 0 | AS10: =SUM(R10:T10) -> 0 | AT10: =SUM(U10:W10) -> 0 | AU10: =SUM(X10:Z10) -> 0 | AV10: =SUM(AA10:AC10) -> 0 | AW10: =SUM(AD10:AF10) -> 0 | AX10: =SUM(AG10:AI10) -> 0 | AY10: =SUM(AJ10:AL10) -> 0 | BA10: =SUM(C10:N10) -> 0 | BB10: =SUM(O10:Z10) -> 0 | BC10: =SUM(AA10:AL10) -> 0
A11: AI tool / API delivery costs | B11: Delivery FTE x AI tooling / API spend per FTE | C11: ='Revenue'!C17*'Assumptions'!$F$31 -> 0 | D11: ='Revenue'!D17*'Assumptions'!$F$31 -> 0 | E11: ='Revenue'!E17*'Assumptions'!$F$31 -> 0 | F11: ='Revenue'!F17*'Assumptions'!$F$31 -> 0 | G11: ='Revenue'!G17*'Assumptions'!$F$31 -> 0 | H11: ='Revenue'!H17*'Assumptions'!$F$31 -> 0 | I11: ='Revenue'!I17*'Assumptions'!$F$31 -> 0 | J11: ='Revenue'!J17*'Assumptions'!$F$31 -> 0 | ... AL11: ='Revenue'!AL17*'Assumptions'!$F$31 -> 0 | AN11: =SUM(C11:E11) -> 0 | AO11: =SUM(F11:H11) -> 0 | AP11: =SUM(I11:K11) -> 0 | AQ11: =SUM(L11:N11) -> 0 | AR11: =SUM(O11:Q11) -> 0 | AS11: =SUM(R11:T11) -> 0 | AT11: =SUM(U11:W11) -> 0 | AU11: =SUM(X11:Z11) -> 0 | AV11: =SUM(AA11:AC11) -> 0 | AW11: =SUM(AD11:AF11) -> 0 | AX11: =SUM(AG11:AI11) -> 0 | AY11: =SUM(AJ11:AL11) -> 0 | BA11: =SUM(C11:N11) -> 0 | BB11: =SUM(O11:Z11) -> 0 | BC11: =SUM(AA11:AL11) -> 0
A12: Total COGS | C12: =C8+C9+C10+C11 -> 0 | D12: =D8+D9+D10+D11 -> 0 | E12: =E8+E9+E10+E11 -> 0 | F12: =F8+F9+F10+F11 -> 0 | G12: =G8+G9+G10+G11 -> 0 | H12: =H8+H9+H10+H11 -> 0 | I12: =I8+I9+I10+I11 -> 0 | J12: =J8+J9+J10+J11 -> 0 | ... AL12: =AL8+AL9+AL10+AL11 -> 0 | AN12: =SUM(C12:E12) -> 0 | AO12: =SUM(F12:H12) -> 0 | AP12: =SUM(I12:K12) -> 0 | AQ12: =SUM(L12:N12) -> 0 | AR12: =SUM(O12:Q12) -> 0 | AS12: =SUM(R12:T12) -> 0 | AT12: =SUM(U12:W12) -> 0 | AU12: =SUM(X12:Z12) -> 0 | AV12: =SUM(AA12:AC12) -> 0 | AW12: =SUM(AD12:AF12) -> 0 | AX12: =SUM(AG12:AI12) -> 0 | AY12: =SUM(AJ12:AL12) -> 0 | BA12: =SUM(C12:N12) -> 0 | BB12: =SUM(O12:Z12) -> 0 | BC12: =SUM(AA12:AL12) -> 0
A14: Gross Profit & Service Economics
A15: Gross Profit | C15: ='Revenue'!C36-C12 -> 0 | D15: ='Revenue'!D36-D12 -> 0 | E15: ='Revenue'!E36-E12 -> 0 | F15: ='Revenue'!F36-F12 -> 0 | G15: ='Revenue'!G36-G12 -> 0 | H15: ='Revenue'!H36-H12 -> 0 | I15: ='Revenue'!I36-I12 -> 0 | J15: ='Revenue'!J36-J12 -> 0 | ... AL15: ='Revenue'!AL36-AL12 -> 0 | AN15: =SUM(C15:E15) -> 0 | AO15: =SUM(F15:H15) -> 0 | AP15: =SUM(I15:K15) -> 0 | AQ15: =SUM(L15:N15) -> 0 | AR15: =SUM(O15:Q15) -> 0 | AS15: =SUM(R15:T15) -> 0 | AT15: =SUM(U15:W15) -> 0 | AU15: =SUM(X15:Z15) -> 0 | AV15: =SUM(AA15:AC15) -> 0 | AW15: =SUM(AD15:AF15) -> 0 | AX15: =SUM(AG15:AI15) -> 0 | AY15: =SUM(AJ15:AL15) -> 0 | BA15: =SUM(C15:N15) -> 0 | BB15: =SUM(O15:Z15) -> 0 | BC15: =SUM(AA15:AL15) -> 0
A16: Project Gross Margin % | C16: =IFERROR(C15/'Revenue'!C36,0) -> 0 | D16: =IFERROR(D15/'Revenue'!D36,0) -> 0 | E16: =IFERROR(E15/'Revenue'!E36,0) -> 0 | F16: =IFERROR(F15/'Revenue'!F36,0) -> 0 | G16: =IFERROR(G15/'Revenue'!G36,0) -> 0 | H16: =IFERROR(H15/'Revenue'!H36,0) -> 0 | I16: =IFERROR(I15/'Revenue'!I36,0) -> 0 | J16: =IFERROR(J15/'Revenue'!J36,0) -> 0 | ... AL16: =IFERROR(AL15/'Revenue'!AL36,0) -> 0 | AN16: =AVERAGE(C16:E16) -> 0 | AO16: =AVERAGE(F16:H16) -> 0 | AP16: =AVERAGE(I16:K16) -> 0 | AQ16: =AVERAGE(L16:N16) -> 0 | AR16: =AVERAGE(O16:Q16) -> 0 | AS16: =AVERAGE(R16:T16) -> 0 | AT16: =AVERAGE(U16:W16) -> 0 | AU16: =AVERAGE(X16:Z16) -> 0 | AV16: =AVERAGE(AA16:AC16) -> 0 | AW16: =AVERAGE(AD16:AF16) -> 0 | AX16: =AVERAGE(AG16:AI16) -> 0 | AY16: =AVERAGE(AJ16:AL16) -> 0 | BA16: =AVERAGE(C16:N16) -> 0 | BB16: =AVERAGE(O16:Z16) -> 0 | BC16: =AVERAGE(AA16:AL16) -> 0
A17: Utilization % | B17: Linked from Revenue tab | C17: ='Revenue'!$C$40 -> 0 | D17: ='Revenue'!$D$40 -> 0 | E17: ='Revenue'!$E$40 -> 0 | F17: ='Revenue'!$F$40 -> 0 | G17: ='Revenue'!$G$40 -> 0 | H17: ='Revenue'!$H$40 -> 0 | I17: ='Revenue'!$I$40 -> 0 | J17: ='Revenue'!$J$40 -> 0 | K17: ='Revenue'!$K$40 -> 0 | L17: ='Revenue'!$L$40 -> 0 | M17: ='Revenue'!$M$40 -> 0 | N17: ='Revenue'!$N$40 -> 0 | O17: ='Revenue'!$O$40 -> 0 | P17: ='Revenue'!$P$40 -> 0 | Q17: ='Revenue'!$Q$40 -> 0 | R17: ='Revenue'!$R$40 -> 0 | S17: ='Revenue'!$S$40 -> 0 | T17: ='Revenue'!$T$40 -> 0 | U17: ='Revenue'!$U$40 -> 0 | V17: ='Revenue'!$V$40 -> 0 | W17: ='Revenue'!$W$40 -> 0 | X17: ='Revenue'!$X$40 -> 0 | Y17: ='Revenue'!$Y$40 -> 0 | Z17: ='Revenue'!$Z$40 -> 0 | AA17: ='Revenue'!$AA$40 -> 0 | AB17: ='Revenue'!$AB$40 -> 0 | AC17: ='Revenue'!$AC$40 -> 0 | AD17: ='Revenue'!$AD$40 -> 0 | AE17: ='Revenue'!$AE$40 -> 0 | AF17: ='Revenue'!$AF$40 -> 0 | AG17: ='Revenue'!$AG$40 -> 0 | AH17: ='Revenue'!$AH$40 -> 0 | AI17: ='Revenue'!$AI$40 -> 0 | AJ17: ='Revenue'!$AJ$40 -> 0 | AK17: ='Revenue'!$AK$40 -> 0 | AL17: ='Revenue'!$AL$40 -> 0 | AN17: =AVERAGE(C17:E17) -> 0 | AO17: =AVERAGE(F17:H17) -> 0 | AP17: =AVERAGE(I17:K17) -> 0 | AQ17: =AVERAGE(L17:N17) -> 0 | AR17: =AVERAGE(O17:Q17) -> 0 | AS17: =AVERAGE(R17:T17) -> 0 | AT17: =AVERAGE(U17:W17) -> 0 | AU17: =AVERAGE(X17:Z17) -> 0 | AV17: =AVERAGE(AA17:AC17) -> 0 | AW17: =AVERAGE(AD17:AF17) -> 0 | AX17: =AVERAGE(AG17:AI17) -> 0 | AY17: =AVERAGE(AJ17:AL17) -> 0 | BA17: =AVERAGE(C17:N17) -> 0 | BB17: =AVERAGE(O17:Z17) -> 0 | BC17: =AVERAGE(AA17:AL17) -> 0
A18: Realization % | B18: Linked from Revenue tab | C18: ='Revenue'!$C$41 -> 0 | D18: ='Revenue'!$D$41 -> 0 | E18: ='Revenue'!$E$41 -> 0 | F18: ='Revenue'!$F$41 -> 0 | G18: ='Revenue'!$G$41 -> 0 | H18: ='Revenue'!$H$41 -> 0 | I18: ='Revenue'!$I$41 -> 0 | J18: ='Revenue'!$J$41 -> 0 | K18: ='Revenue'!$K$41 -> 0 | L18: ='Revenue'!$L$41 -> 0 | M18: ='Revenue'!$M$41 -> 0 | N18: ='Revenue'!$N$41 -> 0 | O18: ='Revenue'!$O$41 -> 0 | P18: ='Revenue'!$P$41 -> 0 | Q18: ='Revenue'!$Q$41 -> 0 | R18: ='Revenue'!$R$41 -> 0 | S18: ='Revenue'!$S$41 -> 0 | T18: ='Revenue'!$T$41 -> 0 | U18: ='Revenue'!$U$41 -> 0 | V18: ='Revenue'!$V$41 -> 0 | W18: ='Revenue'!$W$41 -> 0 | X18: ='Revenue'!$X$41 -> 0 | Y18: ='Revenue'!$Y$41 -> 0 | Z18: ='Revenue'!$Z$41 -> 0 | AA18: ='Revenue'!$AA$41 -> 0 | AB18: ='Revenue'!$AB$41 -> 0 | AC18: ='Revenue'!$AC$41 -> 0 | AD18: ='Revenue'!$AD$41 -> 0 | AE18: ='Revenue'!$AE$41 -> 0 | AF18: ='Revenue'!$AF$41 -> 0 | AG18: ='Revenue'!$AG$41 -> 0 | AH18: ='Revenue'!$AH$41 -> 0 | AI18: ='Revenue'!$AI$41 -> 0 | AJ18: ='Revenue'!$AJ$41 -> 0 | AK18: ='Revenue'!$AK$41 -> 0 | AL18: ='Revenue'!$AL$41 -> 0 | AN18: =AVERAGE(C18:E18) -> 0 | AO18: =AVERAGE(F18:H18) -> 0 | AP18: =AVERAGE(I18:K18) -> 0 | AQ18: =AVERAGE(L18:N18) -> 0 | AR18: =AVERAGE(O18:Q18) -> 0 | AS18: =AVERAGE(R18:T18) -> 0 | AT18: =AVERAGE(U18:W18) -> 0 | AU18: =AVERAGE(X18:Z18) -> 0 | AV18: =AVERAGE(AA18:AC18) -> 0 | AW18: =AVERAGE(AD18:AF18) -> 0 | AX18: =AVERAGE(AG18:AI18) -> 0 | AY18: =AVERAGE(AJ18:AL18) -> 0 | BA18: =AVERAGE(C18:N18) -> 0 | BB18: =AVERAGE(O18:Z18) -> 0 | BC18: =AVERAGE(AA18:AL18) -> 0
A19: Revenue per Delivery FTE | B19: Linked from Revenue tab | C19: ='Revenue'!$C$42 -> 0 | D19: ='Revenue'!$D$42 -> 0 | E19: ='Revenue'!$E$42 -> 0 | F19: ='Revenue'!$F$42 -> 0 | G19: ='Revenue'!$G$42 -> 0 | H19: ='Revenue'!$H$42 -> 0 | I19: ='Revenue'!$I$42 -> 0 | J19: ='Revenue'!$J$42 -> 0 | K19: ='Revenue'!$K$42 -> 0 | L19: ='Revenue'!$L$42 -> 0 | M19: ='Revenue'!$M$42 -> 0 | N19: ='Revenue'!$N$42 -> 0 | O19: ='Revenue'!$O$42 -> 0 | P19: ='Revenue'!$P$42 -> 0 | Q19: ='Revenue'!$Q$42 -> 0 | R19: ='Revenue'!$R$42 -> 0 | S19: ='Revenue'!$S$42 -> 0 | T19: ='Revenue'!$T$42 -> 0 | U19: ='Revenue'!$U$42 -> 0 | V19: ='Revenue'!$V$42 -> 0 | W19: ='Revenue'!$W$42 -> 0 | X19: ='Revenue'!$X$42 -> 0 | Y19: ='Revenue'!$Y$42 -> 0 | Z19: ='Revenue'!$Z$42 -> 0 | AA19: ='Revenue'!$AA$42 -> 0 | AB19: ='Revenue'!$AB$42 -> 0 | AC19: ='Revenue'!$AC$42 -> 0 | AD19: ='Revenue'!$AD$42 -> 0 | AE19: ='Revenue'!$AE$42 -> 0 | AF19: ='Revenue'!$AF$42 -> 0 | AG19: ='Revenue'!$AG$42 -> 0 | AH19: ='Revenue'!$AH$42 -> 0 | AI19: ='Revenue'!$AI$42 -> 0 | AJ19: ='Revenue'!$AJ$42 -> 0 | AK19: ='Revenue'!$AK$42 -> 0 | AL19: ='Revenue'!$AL$42 -> 0 | AN19: =AVERAGE(C19:E19) -> 0 | AO19: =AVERAGE(F19:H19) -> 0 | AP19: =AVERAGE(I19:K19) -> 0 | AQ19: =AVERAGE(L19:N19) -> 0 | AR19: =AVERAGE(O19:Q19) -> 0 | AS19: =AVERAGE(R19:T19) -> 0 | AT19: =AVERAGE(U19:W19) -> 0 | AU19: =AVERAGE(X19:Z19) -> 0 | AV19: =AVERAGE(AA19:AC19) -> 0 | AW19: =AVERAGE(AD19:AF19) -> 0 | AX19: =AVERAGE(AG19:AI19) -> 0 | AY19: =AVERAGE(AJ19:AL19) -> 0 | BA19: =AVERAGE(C19:N19) -> 0 | BB19: =AVERAGE(O19:Z19) -> 0 | BC19: =AVERAGE(AA19:AL19) -> 0
A20: Contribution margin per Delivery FTE | B20: Gross profit / delivery FTE | C20: =IFERROR(C15/'Revenue'!C17,0) -> 0 | D20: =IFERROR(D15/'Revenue'!D17,0) -> 0 | E20: =IFERROR(E15/'Revenue'!E17,0) -> 0 | F20: =IFERROR(F15/'Revenue'!F17,0) -> 0 | G20: =IFERROR(G15/'Revenue'!G17,0) -> 0 | H20: =IFERROR(H15/'Revenue'!H17,0) -> 0 | I20: =IFERROR(I15/'Revenue'!I17,0) -> 0 | J20: =IFERROR(J15/'Revenue'!J17,0) -> 0 | ... AL20: =IFERROR(AL15/'Revenue'!AL17,0) -> 0 | AN20: =AVERAGE(C20:E20) -> 0 | AO20: =AVERAGE(F20:H20) -> 0 | AP20: =AVERAGE(I20:K20) -> 0 | AQ20: =AVERAGE(L20:N20) -> 0 | AR20: =AVERAGE(O20:Q20) -> 0 | AS20: =AVERAGE(R20:T20) -> 0 | AT20: =AVERAGE(U20:W20) -> 0 | AU20: =AVERAGE(X20:Z20) -> 0 | AV20: =AVERAGE(AA20:AC20) -> 0 | AW20: =AVERAGE(AD20:AF20) -> 0 | AX20: =AVERAGE(AG20:AI20) -> 0 | AY20: =AVERAGE(AJ20:AL20) -> 0 | BA20: =AVERAGE(C20:N20) -> 0 | BB20: =AVERAGE(O20:Z20) -> 0 | BC20: =AVERAGE(AA20:AL20) -> 0
A21: AI productivity uplift | B21: Linked from Revenue tab | C21: ='Revenue'!$C$45 -> 0 | D21: ='Revenue'!$D$45 -> 0 | E21: ='Revenue'!$E$45 -> 0 | F21: ='Revenue'!$F$45 -> 0 | G21: ='Revenue'!$G$45 -> 0 | H21: ='Revenue'!$H$45 -> 0 | I21: ='Revenue'!$I$45 -> 0 | J21: ='Revenue'!$J$45 -> 0 | K21: ='Revenue'!$K$45 -> 0 | L21: ='Revenue'!$L$45 -> 0 | M21: ='Revenue'!$M$45 -> 0 | N21: ='Revenue'!$N$45 -> 0 | O21: ='Revenue'!$O$45 -> 0 | P21: ='Revenue'!$P$45 -> 0 | Q21: ='Revenue'!$Q$45 -> 0 | R21: ='Revenue'!$R$45 -> 0 | S21: ='Revenue'!$S$45 -> 0 | T21: ='Revenue'!$T$45 -> 0 | U21: ='Revenue'!$U$45 -> 0 | V21: ='Revenue'!$V$45 -> 0 | W21: ='Revenue'!$W$45 -> 0 | X21: ='Revenue'!$X$45 -> 0 | Y21: ='Revenue'!$Y$45 -> 0 | Z21: ='Revenue'!$Z$45 -> 0 | AA21: ='Revenue'!$AA$45 -> 0 | AB21: ='Revenue'!$AB$45 -> 0 | AC21: ='Revenue'!$AC$45 -> 0 | AD21: ='Revenue'!$AD$45 -> 0 | AE21: ='Revenue'!$AE$45 -> 0 | AF21: ='Revenue'!$AF$45 -> 0 | AG21: ='Revenue'!$AG$45 -> 0 | AH21: ='Revenue'!$AH$45 -> 0 | AI21: ='Revenue'!$AI$45 -> 0 | AJ21: ='Revenue'!$AJ$45 -> 0 | AK21: ='Revenue'!$AK$45 -> 0 | AL21: ='Revenue'!$AL$45 -> 0 | AN21: =AVERAGE(C21:E21) -> 0 | AO21: =AVERAGE(F21:H21) -> 0 | AP21: =AVERAGE(I21:K21) -> 0 | AQ21: =AVERAGE(L21:N21) -> 0 | AR21: =AVERAGE(O21:Q21) -> 0 | AS21: =AVERAGE(R21:T21) -> 0 | AT21: =AVERAGE(U21:W21) -> 0 | AU21: =AVERAGE(X21:Z21) -> 0 | AV21: =AVERAGE(AA21:AC21) -> 0 | AW21: =AVERAGE(AD21:AF21) -> 0 | AX21: =AVERAGE(AG21:AI21) -> 0 | AY21: =AVERAGE(AJ21:AL21) -> 0 | BA21: =AVERAGE(C21:N21) -> 0 | BB21: =AVERAGE(O21:Z21) -> 0 | BC21: =AVERAGE(AA21:AL21) -> 0
A23: Cash Conversion
A24: Cash conversion (CFO / Net Income) | B24: Monthly cash from operations divided by net income; 0 when net income is ~0 | C24: =IF(ABS('P&L'!C23)<1,0,'Cash Flow'!C14/'P&L'!C23) -> 0 | D24: =IF(ABS('P&L'!D23)<1,0,'Cash Flow'!D14/'P&L'!D23) -> 0 | E24: =IF(ABS('P&L'!E23)<1,0,'Cash Flow'!E14/'P&L'!E23) -> 0 | F24: =IF(ABS('P&L'!F23)<1,0,'Cash Flow'!F14/'P&L'!F23) -> 0 | G24: =IF(ABS('P&L'!G23)<1,0,'Cash Flow'!G14/'P&L'!G23) -> 0 | H24: =IF(ABS('P&L'!H23)<1,0,'Cash Flow'!H14/'P&L'!H23) -> 0 | I24: =IF(ABS('P&L'!I23)<1,0,'Cash Flow'!I14/'P&L'!I23) -> 0 | J24: =IF(ABS('P&L'!J23)<1,0,'Cash Flow'!J14/'P&L'!J23) -> 0 | ... AL24: =IF(ABS('P&L'!AL23)<1,0,'Cash Flow'!AL14/'P&L'!AL23) -> 0 | AN24: =AVERAGE(C24:E24) -> 0 | AO24: =AVERAGE(F24:H24) -> 0 | AP24: =AVERAGE(I24:K24) -> 0 | AQ24: =AVERAGE(L24:N24) -> 0 | AR24: =AVERAGE(O24:Q24) -> 0 | AS24: =AVERAGE(R24:T24) -> 0 | AT24: =AVERAGE(U24:W24) -> 0 | AU24: =AVERAGE(X24:Z24) -> 0 | AV24: =AVERAGE(AA24:AC24) -> 0 | AW24: =AVERAGE(AD24:AF24) -> 0 | AX24: =AVERAGE(AG24:AI24) -> 0 | AY24: =AVERAGE(AJ24:AL24) -> 0 | BA24: =AVERAGE(C24:N24) -> 0 | BB24: =AVERAGE(O24:Z24) -> 0 | BC24: =AVERAGE(AA24:AL24) -> 0

Sheet Opex
A1: AI-Enabled Services — 3-Year Financial Model — Opex
A2: Operating expenses by department — headcount cost plus program spend.
A5: Line item | B5: Units / source | C5: Monthly (36 months) | AN5: Quarterly | BA5: Annual
C6: 46023 | D6: 46054 | E6: 46082 | F6: 46113 | G6: 46143 | H6: 46174 | I6: 46204 | J6: 46235 | K6: 46266 | L6: 46296 | M6: 46327 | N6: 46357 | O6: 46388 | P6: 46419 | Q6: 46447 | R6: 46478 | S6: 46508 | T6: 46539 | U6: 46569 | V6: 46600 | W6: 46631 | X6: 46661 | Y6: 46692 | Z6: 46722 | AA6: 46753 | AB6: 46784 | AC6: 46813 | AD6: 46844 | AE6: 46874 | AF6: 46905 | AG6: 46935 | AH6: 46966 | AI6: 46997 | AJ6: 47027 | AK6: 47058 | AL6: 47088 | AN6: Q1 | AO6: Q2 | AP6: Q3 | AQ6: Q4 | AR6: Q5 | AS6: Q6 | AT6: Q7 | AU6: Q8 | AV6: Q9 | AW6: Q10 | AX6: Q11 | AY6: Q12 | BA6: FY1 | BB6: FY2 | BC6: FY3
A7: Sales & Marketing
A8: Sales & Marketing — people cost | B8: Linked from Headcount tab | C8: ='Headcount'!$C$24 -> 0 | D8: ='Headcount'!$D$24 -> 0 | E8: ='Headcount'!$E$24 -> 0 | F8: ='Headcount'!$F$24 -> 0 | G8: ='Headcount'!$G$24 -> 0 | H8: ='Headcount'!$H$24 -> 0 | I8: ='Headcount'!$I$24 -> 0 | J8: ='Headcount'!$J$24 -> 0 | K8: ='Headcount'!$K$24 -> 0 | L8: ='Headcount'!$L$24 -> 0 | M8: ='Headcount'!$M$24 -> 0 | N8: ='Headcount'!$N$24 -> 0 | O8: ='Headcount'!$O$24 -> 0 | P8: ='Headcount'!$P$24 -> 0 | Q8: ='Headcount'!$Q$24 -> 0 | R8: ='Headcount'!$R$24 -> 0 | S8: ='Headcount'!$S$24 -> 0 | T8: ='Headcount'!$T$24 -> 0 | U8: ='Headcount'!$U$24 -> 0 | V8: ='Headcount'!$V$24 -> 0 | W8: ='Headcount'!$W$24 -> 0 | X8: ='Headcount'!$X$24 -> 0 | Y8: ='Headcount'!$Y$24 -> 0 | Z8: ='Headcount'!$Z$24 -> 0 | AA8: ='Headcount'!$AA$24 -> 0 | AB8: ='Headcount'!$AB$24 -> 0 | AC8: ='Headcount'!$AC$24 -> 0 | AD8: ='Headcount'!$AD$24 -> 0 | AE8: ='Headcount'!$AE$24 -> 0 | AF8: ='Headcount'!$AF$24 -> 0 | AG8: ='Headcount'!$AG$24 -> 0 | AH8: ='Headcount'!$AH$24 -> 0 | AI8: ='Headcount'!$AI$24 -> 0 | AJ8: ='Headcount'!$AJ$24 -> 0 | AK8: ='Headcount'!$AK$24 -> 0 | AL8: ='Headcount'!$AL$24 -> 0 | AN8: =SUM(C8:E8) -> 0 | AO8: =SUM(F8:H8) -> 0 | AP8: =SUM(I8:K8) -> 0 | AQ8: =SUM(L8:N8) -> 0 | AR8: =SUM(O8:Q8) -> 0 | AS8: =SUM(R8:T8) -> 0 | AT8: =SUM(U8:W8) -> 0 | AU8: =SUM(X8:Z8) -> 0 | AV8: =SUM(AA8:AC8) -> 0 | AW8: =SUM(AD8:AF8) -> 0 | AX8: =SUM(AG8:AI8) -> 0 | AY8: =SUM(AJ8:AL8) -> 0 | BA8: =SUM(C8:N8) -> 0 | BB8: =SUM(O8:Z8) -> 0 | BC8: =SUM(AA8:AL8) -> 0
A9: Sales Commissions | B9: % of monthly new bookings | C9: ='Revenue'!C14*'Assumptions'!$F$54 -> 0 | D9: ='Revenue'!D14*'Assumptions'!$F$54 -> 0 | E9: ='Revenue'!E14*'Assumptions'!$F$54 -> 0 | F9: ='Revenue'!F14*'Assumptions'!$F$54 -> 0 | G9: ='Revenue'!G14*'Assumptions'!$F$54 -> 0 | H9: ='Revenue'!H14*'Assumptions'!$F$54 -> 0 | I9: ='Revenue'!I14*'Assumptions'!$F$54 -> 0 | J9: ='Revenue'!J14*'Assumptions'!$F$54 -> 0 | ... AL9: ='Revenue'!AL14*'Assumptions'!$F$54 -> 0 | AN9: =SUM(C9:E9) -> 0 | AO9: =SUM(F9:H9) -> 0 | AP9: =SUM(I9:K9) -> 0 | AQ9: =SUM(L9:N9) -> 0 | AR9: =SUM(O9:Q9) -> 0 | AS9: =SUM(R9:T9) -> 0 | AT9: =SUM(U9:W9) -> 0 | AU9: =SUM(X9:Z9) -> 0 | AV9: =SUM(AA9:AC9) -> 0 | AW9: =SUM(AD9:AF9) -> 0 | AX9: =SUM(AG9:AI9) -> 0 | AY9: =SUM(AJ9:AL9) -> 0 | BA9: =SUM(C9:N9) -> 0 | BB9: =SUM(O9:Z9) -> 0 | BC9: =SUM(AA9:AL9) -> 0
A10: Marketing / BD Programs | B10: Month-1 assumption compounded by monthly growth | C10: ='Assumptions'!$F$55*(1+'Assumptions'!$F$56)^0 -> 0 | D10: ='Assumptions'!$F$55*(1+'Assumptions'!$F$56)^1 -> 0 | E10: ='Assumptions'!$F$55*(1+'Assumptions'!$F$56)^2 -> 0 | F10: ='Assumptions'!$F$55*(1+'Assumptions'!$F$56)^3 -> 0 | G10: ='Assumptions'!$F$55*(1+'Assumptions'!$F$56)^4 -> 0 | H10: ='Assumptions'!$F$55*(1+'Assumptions'!$F$56)^5 -> 0 | I10: ='Assumptions'!$F$55*(1+'Assumptions'!$F$56)^6 -> 0 | J10: ='Assumptions'!$F$55*(1+'Assumptions'!$F$56)^7 -> 0 | K10: ='Assumptions'!$F$55*(1+'Assumptions'!$F$56)^8 -> 0 | L10: ='Assumptions'!$F$55*(1+'Assumptions'!$F$56)^9 -> 0 | M10: ='Assumptions'!$F$55*(1+'Assumptions'!$F$56)^10 -> 0 | N10: ='Assumptions'!$F$55*(1+'Assumptions'!$F$56)^11 -> 0 | O10: ='Assumptions'!$F$55*(1+'Assumptions'!$F$56)^12 -> 0 | P10: ='Assumptions'!$F$55*(1+'Assumptions'!$F$56)^13 -> 0 | Q10: ='Assumptions'!$F$55*(1+'Assumptions'!$F$56)^14 -> 0 | R10: ='Assumptions'!$F$55*(1+'Assumptions'!$F$56)^15 -> 0 | S10: ='Assumptions'!$F$55*(1+'Assumptions'!$F$56)^16 -> 0 | T10: ='Assumptions'!$F$55*(1+'Assumptions'!$F$56)^17 -> 0 | U10: ='Assumptions'!$F$55*(1+'Assumptions'!$F$56)^18 -> 0 | V10: ='Assumptions'!$F$55*(1+'Assumptions'!$F$56)^19 -> 0 | W10: ='Assumptions'!$F$55*(1+'Assumptions'!$F$56)^20 -> 0 | X10: ='Assumptions'!$F$55*(1+'Assumptions'!$F$56)^21 -> 0 | Y10: ='Assumptions'!$F$55*(1+'Assumptions'!$F$56)^22 -> 0 | Z10: ='Assumptions'!$F$55*(1+'Assumptions'!$F$56)^23 -> 0 | AA10: ='Assumptions'!$F$55*(1+'Assumptions'!$F$56)^24 -> 0 | AB10: ='Assumptions'!$F$55*(1+'Assumptions'!$F$56)^25 -> 0 | AC10: ='Assumptions'!$F$55*(1+'Assumptions'!$F$56)^26 -> 0 | AD10: ='Assumptions'!$F$55*(1+'Assumptions'!$F$56)^27 -> 0 | AE10: ='Assumptions'!$F$55*(1+'Assumptions'!$F$56)^28 -> 0 | AF10: ='Assumptions'!$F$55*(1+'Assumptions'!$F$56)^29 -> 0 | AG10: ='Assumptions'!$F$55*(1+'Assumptions'!$F$56)^30 -> 0 | AH10: ='Assumptions'!$F$55*(1+'Assumptions'!$F$56)^31 -> 0 | AI10: ='Assumptions'!$F$55*(1+'Assumptions'!$F$56)^32 -> 0 | AJ10: ='Assumptions'!$F$55*(1+'Assumptions'!$F$56)^33 -> 0 | AK10: ='Assumptions'!$F$55*(1+'Assumptions'!$F$56)^34 -> 0 | AL10: ='Assumptions'!$F$55*(1+'Assumptions'!$F$56)^35 -> 0 | AN10: =SUM(C10:E10) -> 0 | AO10: =SUM(F10:H10) -> 0 | AP10: =SUM(I10:K10) -> 0 | AQ10: =SUM(L10:N10) -> 0 | AR10: =SUM(O10:Q10) -> 0 | AS10: =SUM(R10:T10) -> 0 | AT10: =SUM(U10:W10) -> 0 | AU10: =SUM(X10:Z10) -> 0 | AV10: =SUM(AA10:AC10) -> 0 | AW10: =SUM(AD10:AF10) -> 0 | AX10: =SUM(AG10:AI10) -> 0 | AY10: =SUM(AJ10:AL10) -> 0 | BA10: =SUM(C10:N10) -> 0 | BB10: =SUM(O10:Z10) -> 0 | BC10: =SUM(AA10:AL10) -> 0
A11: Total Sales & Marketing | C11: =C8+C9+C10 -> 0 | D11: =D8+D9+D10 -> 0 | E11: =E8+E9+E10 -> 0 | F11: =F8+F9+F10 -> 0 | G11: =G8+G9+G10 -> 0 | H11: =H8+H9+H10 -> 0 | I11: =I8+I9+I10 -> 0 | J11: =J8+J9+J10 -> 0 | ... AL11: =AL8+AL9+AL10 -> 0 | AN11: =SUM(C11:E11) -> 0 | AO11: =SUM(F11:H11) -> 0 | AP11: =SUM(I11:K11) -> 0 | AQ11: =SUM(L11:N11) -> 0 | AR11: =SUM(O11:Q11) -> 0 | AS11: =SUM(R11:T11) -> 0 | AT11: =SUM(U11:W11) -> 0 | AU11: =SUM(X11:Z11) -> 0 | AV11: =SUM(AA11:AC11) -> 0 | AW11: =SUM(AD11:AF11) -> 0 | AX11: =SUM(AG11:AI11) -> 0 | AY11: =SUM(AJ11:AL11) -> 0 | BA11: =SUM(C11:N11) -> 0 | BB11: =SUM(O11:Z11) -> 0 | BC11: =SUM(AA11:AL11) -> 0
A13: General & Administrative
A14: General & Administrative — people cost | B14: Linked from Headcount tab | C14: ='Headcount'!$C$23 -> 0 | D14: ='Headcount'!$D$23 -> 0 | E14: ='Headcount'!$E$23 -> 0 | F14: ='Headcount'!$F$23 -> 0 | G14: ='Headcount'!$G$23 -> 0 | H14: ='Headcount'!$H$23 -> 0 | I14: ='Headcount'!$I$23 -> 0 | J14: ='Headcount'!$J$23 -> 0 | K14: ='Headcount'!$K$23 -> 0 | L14: ='Headcount'!$L$23 -> 0 | M14: ='Headcount'!$M$23 -> 0 | N14: ='Headcount'!$N$23 -> 0 | O14: ='Headcount'!$O$23 -> 0 | P14: ='Headcount'!$P$23 -> 0 | Q14: ='Headcount'!$Q$23 -> 0 | R14: ='Headcount'!$R$23 -> 0 | S14: ='Headcount'!$S$23 -> 0 | T14: ='Headcount'!$T$23 -> 0 | U14: ='Headcount'!$U$23 -> 0 | V14: ='Headcount'!$V$23 -> 0 | W14: ='Headcount'!$W$23 -> 0 | X14: ='Headcount'!$X$23 -> 0 | Y14: ='Headcount'!$Y$23 -> 0 | Z14: ='Headcount'!$Z$23 -> 0 | AA14: ='Headcount'!$AA$23 -> 0 | AB14: ='Headcount'!$AB$23 -> 0 | AC14: ='Headcount'!$AC$23 -> 0 | AD14: ='Headcount'!$AD$23 -> 0 | AE14: ='Headcount'!$AE$23 -> 0 | AF14: ='Headcount'!$AF$23 -> 0 | AG14: ='Headcount'!$AG$23 -> 0 | AH14: ='Headcount'!$AH$23 -> 0 | AI14: ='Headcount'!$AI$23 -> 0 | AJ14: ='Headcount'!$AJ$23 -> 0 | AK14: ='Headcount'!$AK$23 -> 0 | AL14: ='Headcount'!$AL$23 -> 0 | AN14: =SUM(C14:E14) -> 0 | AO14: =SUM(F14:H14) -> 0 | AP14: =SUM(I14:K14) -> 0 | AQ14: =SUM(L14:N14) -> 0 | AR14: =SUM(O14:Q14) -> 0 | AS14: =SUM(R14:T14) -> 0 | AT14: =SUM(U14:W14) -> 0 | AU14: =SUM(X14:Z14) -> 0 | AV14: =SUM(AA14:AC14) -> 0 | AW14: =SUM(AD14:AF14) -> 0 | AX14: =SUM(AG14:AI14) -> 0 | AY14: =SUM(AJ14:AL14) -> 0 | BA14: =SUM(C14:N14) -> 0 | BB14: =SUM(O14:Z14) -> 0 | BC14: =SUM(AA14:AL14) -> 0
A15: Corporate Software & Tools | B15: Fixed monthly | C15: ='Assumptions'!$F$57 -> 0 | D15: ='Assumptions'!$F$57 -> 0 | E15: ='Assumptions'!$F$57 -> 0 | F15: ='Assumptions'!$F$57 -> 0 | G15: ='Assumptions'!$F$57 -> 0 | H15: ='Assumptions'!$F$57 -> 0 | I15: ='Assumptions'!$F$57 -> 0 | J15: ='Assumptions'!$F$57 -> 0 | ... AL15: ='Assumptions'!$F$57 -> 0 | AN15: =SUM(C15:E15) -> 0 | AO15: =SUM(F15:H15) -> 0 | AP15: =SUM(I15:K15) -> 0 | AQ15: =SUM(L15:N15) -> 0 | AR15: =SUM(O15:Q15) -> 0 | AS15: =SUM(R15:T15) -> 0 | AT15: =SUM(U15:W15) -> 0 | AU15: =SUM(X15:Z15) -> 0 | AV15: =SUM(AA15:AC15) -> 0 | AW15: =SUM(AD15:AF15) -> 0 | AX15: =SUM(AG15:AI15) -> 0 | AY15: =SUM(AJ15:AL15) -> 0 | BA15: =SUM(C15:N15) -> 0 | BB15: =SUM(O15:Z15) -> 0 | BC15: =SUM(AA15:AL15) -> 0
A16: Facilities & Admin Overhead | B16: Fixed monthly | C16: ='Assumptions'!$F$58 -> 0 | D16: ='Assumptions'!$F$58 -> 0 | E16: ='Assumptions'!$F$58 -> 0 | F16: ='Assumptions'!$F$58 -> 0 | G16: ='Assumptions'!$F$58 -> 0 | H16: ='Assumptions'!$F$58 -> 0 | I16: ='Assumptions'!$F$58 -> 0 | J16: ='Assumptions'!$F$58 -> 0 | ... AL16: ='Assumptions'!$F$58 -> 0 | AN16: =SUM(C16:E16) -> 0 | AO16: =SUM(F16:H16) -> 0 | AP16: =SUM(I16:K16) -> 0 | AQ16: =SUM(L16:N16) -> 0 | AR16: =SUM(O16:Q16) -> 0 | AS16: =SUM(R16:T16) -> 0 | AT16: =SUM(U16:W16) -> 0 | AU16: =SUM(X16:Z16) -> 0 | AV16: =SUM(AA16:AC16) -> 0 | AW16: =SUM(AD16:AF16) -> 0 | AX16: =SUM(AG16:AI16) -> 0 | AY16: =SUM(AJ16:AL16) -> 0 | BA16: =SUM(C16:N16) -> 0 | BB16: =SUM(O16:Z16) -> 0 | BC16: =SUM(AA16:AL16) -> 0
A17: Total General & Administrative | C17: =C14+C15+C16 -> 0 | D17: =D14+D15+D16 -> 0 | E17: =E14+E15+E16 -> 0 | F17: =F14+F15+F16 -> 0 | G17: =G14+G15+G16 -> 0 | H17: =H14+H15+H16 -> 0 | I17: =I14+I15+I16 -> 0 | J17: =J14+J15+J16 -> 0 | ... AL17: =AL14+AL15+AL16 -> 0 | AN17: =SUM(C17:E17) -> 0 | AO17: =SUM(F17:H17) -> 0 | AP17: =SUM(I17:K17) -> 0 | AQ17: =SUM(L17:N17) -> 0 | AR17: =SUM(O17:Q17) -> 0 | AS17: =SUM(R17:T17) -> 0 | AT17: =SUM(U17:W17) -> 0 | AU17: =SUM(X17:Z17) -> 0 | AV17: =SUM(AA17:AC17) -> 0 | AW17: =SUM(AD17:AF17) -> 0 | AX17: =SUM(AG17:AI17) -> 0 | AY17: =SUM(AJ17:AL17) -> 0 | BA17: =SUM(C17:N17) -> 0 | BB17: =SUM(O17:Z17) -> 0 | BC17: =SUM(AA17:AL17) -> 0
A19: Total Operating Expenses
A20: Total Opex | C20: =C11+C17 -> 0 | D20: =D11+D17 -> 0 | E20: =E11+E17 -> 0 | F20: =F11+F17 -> 0 | G20: =G11+G17 -> 0 | H20: =H11+H17 -> 0 | I20: =I11+I17 -> 0 | J20: =J11+J17 -> 0 | ... AL20: =AL11+AL17 -> 0 | AN20: =SUM(C20:E20) -> 0 | AO20: =SUM(F20:H20) -> 0 | AP20: =SUM(I20:K20) -> 0 | AQ20: =SUM(L20:N20) -> 0 | AR20: =SUM(O20:Q20) -> 0 | AS20: =SUM(R20:T20) -> 0 | AT20: =SUM(U20:W20) -> 0 | AU20: =SUM(X20:Z20) -> 0 | AV20: =SUM(AA20:AC20) -> 0 | AW20: =SUM(AD20:AF20) -> 0 | AX20: =SUM(AG20:AI20) -> 0 | AY20: =SUM(AJ20:AL20) -> 0 | BA20: =SUM(C20:N20) -> 0 | BB20: =SUM(O20:Z20) -> 0 | BC20: =SUM(AA20:AL20) -> 0

Sheet Working Capital
A1: AI-Enabled Services — 3-Year Financial Model — Working Capital
A2: Balance-sheet drivers: receivables, payables, deferred revenue, capex/depreciation, debt & equity financing.
A5: Line item | B5: Units / source | C5: Monthly (36 months) | AN5: Quarterly | BA5: Annual
C6: 46023 | D6: 46054 | E6: 46082 | F6: 46113 | G6: 46143 | H6: 46174 | I6: 46204 | J6: 46235 | K6: 46266 | L6: 46296 | M6: 46327 | N6: 46357 | O6: 46388 | P6: 46419 | Q6: 46447 | R6: 46478 | S6: 46508 | T6: 46539 | U6: 46569 | V6: 46600 | W6: 46631 | X6: 46661 | Y6: 46692 | Z6: 46722 | AA6: 46753 | AB6: 46784 | AC6: 46813 | AD6: 46844 | AE6: 46874 | AF6: 46905 | AG6: 46935 | AH6: 46966 | AI6: 46997 | AJ6: 47027 | AK6: 47058 | AL6: 47088 | AN6: Q1 | AO6: Q2 | AP6: Q3 | AQ6: Q4 | AR6: Q5 | AS6: Q6 | AT6: Q7 | AU6: Q8 | AV6: Q9 | AW6: Q10 | AX6: Q11 | AY6: Q12 | BA6: FY1 | BB6: FY2 | BC6: FY3
A7: Receivables, Payables & Deferred Revenue
A8: Accounts Receivable balance | B8: Revenue × DSO ÷ 30 | C8: ='Revenue'!C36*'Assumptions'!$F$61/30 -> 0 | D8: ='Revenue'!D36*'Assumptions'!$F$61/30 -> 0 | E8: ='Revenue'!E36*'Assumptions'!$F$61/30 -> 0 | F8: ='Revenue'!F36*'Assumptions'!$F$61/30 -> 0 | G8: ='Revenue'!G36*'Assumptions'!$F$61/30 -> 0 | H8: ='Revenue'!H36*'Assumptions'!$F$61/30 -> 0 | I8: ='Revenue'!I36*'Assumptions'!$F$61/30 -> 0 | J8: ='Revenue'!J36*'Assumptions'!$F$61/30 -> 0 | ... AL8: ='Revenue'!AL36*'Assumptions'!$F$61/30 -> 0 | AN8: =E8 -> 0 | AO8: =H8 -> 0 | AP8: =K8 -> 0 | AQ8: =N8 -> 0 | AR8: =Q8 -> 0 | AS8: =T8 -> 0 | AT8: =W8 -> 0 | AU8: =Z8 -> 0 | AV8: =AC8 -> 0 | AW8: =AF8 -> 0 | AX8: =AI8 -> 0 | AY8: =AL8 -> 0 | BA8: =N8 -> 0 | BB8: =Z8 -> 0 | BC8: =AL8 -> 0
A9: Accounts Payable balance | B9: (COGS + Opex) × DPO ÷ 30 | C9: =('COGS & GM'!C12+'Opex'!C20)*'Assumptions'!$F$62/30 -> 0 | D9: =('COGS & GM'!D12+'Opex'!D20)*'Assumptions'!$F$62/30 -> 0 | E9: =('COGS & GM'!E12+'Opex'!E20)*'Assumptions'!$F$62/30 -> 0 | F9: =('COGS & GM'!F12+'Opex'!F20)*'Assumptions'!$F$62/30 -> 0 | G9: =('COGS & GM'!G12+'Opex'!G20)*'Assumptions'!$F$62/30 -> 0 | H9: =('COGS & GM'!H12+'Opex'!H20)*'Assumptions'!$F$62/30 -> 0 | I9: =('COGS & GM'!I12+'Opex'!I20)*'Assumptions'!$F$62/30 -> 0 | J9: =('COGS & GM'!J12+'Opex'!J20)*'Assumptions'!$F$62/30 -> 0 | ... AL9: =('COGS & GM'!AL12+'Opex'!AL20)*'Assumptions'!$F$62/30 -> 0 | AN9: =E9 -> 0 | AO9: =H9 -> 0 | AP9: =K9 -> 0 | AQ9: =N9 -> 0 | AR9: =Q9 -> 0 | AS9: =T9 -> 0 | AT9: =W9 -> 0 | AU9: =Z9 -> 0 | AV9: =AC9 -> 0 | AW9: =AF9 -> 0 | AX9: =AI9 -> 0 | AY9: =AL9 -> 0 | BA9: =N9 -> 0 | BB9: =Z9 -> 0 | BC9: =AL9 -> 0
A10: Deferred Revenue balance | B10: Revenue × months collected in advance | C10: ='Revenue'!C36*'Assumptions'!$F$63 -> 0 | D10: ='Revenue'!D36*'Assumptions'!$F$63 -> 0 | E10: ='Revenue'!E36*'Assumptions'!$F$63 -> 0 | F10: ='Revenue'!F36*'Assumptions'!$F$63 -> 0 | G10: ='Revenue'!G36*'Assumptions'!$F$63 -> 0 | H10: ='Revenue'!H36*'Assumptions'!$F$63 -> 0 | I10: ='Revenue'!I36*'Assumptions'!$F$63 -> 0 | J10: ='Revenue'!J36*'Assumptions'!$F$63 -> 0 | ... AL10: ='Revenue'!AL36*'Assumptions'!$F$63 -> 0 | AN10: =E10 -> 0 | AO10: =H10 -> 0 | AP10: =K10 -> 0 | AQ10: =N10 -> 0 | AR10: =Q10 -> 0 | AS10: =T10 -> 0 | AT10: =W10 -> 0 | AU10: =Z10 -> 0 | AV10: =AC10 -> 0 | AW10: =AF10 -> 0 | AX10: =AI10 -> 0 | AY10: =AL10 -> 0 | BA10: =N10 -> 0 | BB10: =Z10 -> 0 | BC10: =AL10 -> 0
A11: Other Current Assets balance | B11: Revenue × assumption % (prepaid expenses, etc.) | C11: ='Revenue'!C36*'Assumptions'!$F$66 -> 0 | D11: ='Revenue'!D36*'Assumptions'!$F$66 -> 0 | E11: ='Revenue'!E36*'Assumptions'!$F$66 -> 0 | F11: ='Revenue'!F36*'Assumptions'!$F$66 -> 0 | G11: ='Revenue'!G36*'Assumptions'!$F$66 -> 0 | H11: ='Revenue'!H36*'Assumptions'!$F$66 -> 0 | I11: ='Revenue'!I36*'Assumptions'!$F$66 -> 0 | J11: ='Revenue'!J36*'Assumptions'!$F$66 -> 0 | ... AL11: ='Revenue'!AL36*'Assumptions'!$F$66 -> 0 | AN11: =E11 -> 0 | AO11: =H11 -> 0 | AP11: =K11 -> 0 | AQ11: =N11 -> 0 | AR11: =Q11 -> 0 | AS11: =T11 -> 0 | AT11: =W11 -> 0 | AU11: =Z11 -> 0 | AV11: =AC11 -> 0 | AW11: =AF11 -> 0 | AX11: =AI11 -> 0 | AY11: =AL11 -> 0 | BA11: =N11 -> 0 | BB11: =Z11 -> 0 | BC11: =AL11 -> 0
A12: Change in Accounts Receivable | C12: =C8 -> 0 | D12: =D8-C8 -> 0 | E12: =E8-D8 -> 0 | F12: =F8-E8 -> 0 | G12: =G8-F8 -> 0 | H12: =H8-G8 -> 0 | I12: =I8-H8 -> 0 | J12: =J8-I8 -> 0 | K12: =K8-J8 -> 0 | ... AL12: =AL8-AK8 -> 0 | AN12: =SUM(C12:E12) -> 0 | AO12: =SUM(F12:H12) -> 0 | AP12: =SUM(I12:K12) -> 0 | AQ12: =SUM(L12:N12) -> 0 | AR12: =SUM(O12:Q12) -> 0 | AS12: =SUM(R12:T12) -> 0 | AT12: =SUM(U12:W12) -> 0 | AU12: =SUM(X12:Z12) -> 0 | AV12: =SUM(AA12:AC12) -> 0 | AW12: =SUM(AD12:AF12) -> 0 | AX12: =SUM(AG12:AI12) -> 0 | AY12: =SUM(AJ12:AL12) -> 0 | BA12: =SUM(C12:N12) -> 0 | BB12: =SUM(O12:Z12) -> 0 | BC12: =SUM(AA12:AL12) -> 0
A13: Change in Accounts Payable | C13: =C9 -> 0 | D13: =D9-C9 -> 0 | E13: =E9-D9 -> 0 | F13: =F9-E9 -> 0 | G13: =G9-F9 -> 0 | H13: =H9-G9 -> 0 | I13: =I9-H9 -> 0 | J13: =J9-I9 -> 0 | K13: =K9-J9 -> 0 | ... AL13: =AL9-AK9 -> 0 | AN13: =SUM(C13:E13) -> 0 | AO13: =SUM(F13:H13) -> 0 | AP13: =SUM(I13:K13) -> 0 | AQ13: =SUM(L13:N13) -> 0 | AR13: =SUM(O13:Q13) -> 0 | AS13: =SUM(R13:T13) -> 0 | AT13: =SUM(U13:W13) -> 0 | AU13: =SUM(X13:Z13) -> 0 | AV13: =SUM(AA13:AC13) -> 0 | AW13: =SUM(AD13:AF13) -> 0 | AX13: =SUM(AG13:AI13) -> 0 | AY13: =SUM(AJ13:AL13) -> 0 | BA13: =SUM(C13:N13) -> 0 | BB13: =SUM(O13:Z13) -> 0 | BC13: =SUM(AA13:AL13) -> 0
A14: Change in Deferred Revenue | C14: =C10 -> 0 | D14: =D10-C10 -> 0 | E14: =E10-D10 -> 0 | F14: =F10-E10 -> 0 | G14: =G10-F10 -> 0 | H14: =H10-G10 -> 0 | I14: =I10-H10 -> 0 | J14: =J10-I10 -> 0 | K14: =K10-J10 -> 0 | ... AL14: =AL10-AK10 -> 0 | AN14: =SUM(C14:E14) -> 0 | AO14: =SUM(F14:H14) -> 0 | AP14: =SUM(I14:K14) -> 0 | AQ14: =SUM(L14:N14) -> 0 | AR14: =SUM(O14:Q14) -> 0 | AS14: =SUM(R14:T14) -> 0 | AT14: =SUM(U14:W14) -> 0 | AU14: =SUM(X14:Z14) -> 0 | AV14: =SUM(AA14:AC14) -> 0 | AW14: =SUM(AD14:AF14) -> 0 | AX14: =SUM(AG14:AI14) -> 0 | AY14: =SUM(AJ14:AL14) -> 0 | BA14: =SUM(C14:N14) -> 0 | BB14: =SUM(O14:Z14) -> 0 | BC14: =SUM(AA14:AL14) -> 0
A15: Change in Other Current Assets | C15: =C11 -> 0 | D15: =D11-C11 -> 0 | E15: =E11-D11 -> 0 | F15: =F11-E11 -> 0 | G15: =G11-F11 -> 0 | H15: =H11-G11 -> 0 | I15: =I11-H11 -> 0 | J15: =J11-I11 -> 0 | K15: =K11-J11 -> 0 | ... AL15: =AL11-AK11 -> 0 | AN15: =SUM(C15:E15) -> 0 | AO15: =SUM(F15:H15) -> 0 | AP15: =SUM(I15:K15) -> 0 | AQ15: =SUM(L15:N15) -> 0 | AR15: =SUM(O15:Q15) -> 0 | AS15: =SUM(R15:T15) -> 0 | AT15: =SUM(U15:W15) -> 0 | AU15: =SUM(X15:Z15) -> 0 | AV15: =SUM(AA15:AC15) -> 0 | AW15: =SUM(AD15:AF15) -> 0 | AX15: =SUM(AG15:AI15) -> 0 | AY15: =SUM(AJ15:AL15) -> 0 | BA15: =SUM(C15:N15) -> 0 | BB15: =SUM(O15:Z15) -> 0 | BC15: =SUM(AA15:AL15) -> 0
A17: Capex & Depreciation (PP&E)
A18: Capital expenditures | B18: Revenue × capex % of revenue | C18: ='Revenue'!C36*'Assumptions'!$F$64 -> 0 | D18: ='Revenue'!D36*'Assumptions'!$F$64 -> 0 | E18: ='Revenue'!E36*'Assumptions'!$F$64 -> 0 | F18: ='Revenue'!F36*'Assumptions'!$F$64 -> 0 | G18: ='Revenue'!G36*'Assumptions'!$F$64 -> 0 | H18: ='Revenue'!H36*'Assumptions'!$F$64 -> 0 | I18: ='Revenue'!I36*'Assumptions'!$F$64 -> 0 | J18: ='Revenue'!J36*'Assumptions'!$F$64 -> 0 | ... AL18: ='Revenue'!AL36*'Assumptions'!$F$64 -> 0 | AN18: =SUM(C18:E18) -> 0 | AO18: =SUM(F18:H18) -> 0 | AP18: =SUM(I18:K18) -> 0 | AQ18: =SUM(L18:N18) -> 0 | AR18: =SUM(O18:Q18) -> 0 | AS18: =SUM(R18:T18) -> 0 | AT18: =SUM(U18:W18) -> 0 | AU18: =SUM(X18:Z18) -> 0 | AV18: =SUM(AA18:AC18) -> 0 | AW18: =SUM(AD18:AF18) -> 0 | AX18: =SUM(AG18:AI18) -> 0 | AY18: =SUM(AJ18:AL18) -> 0 | BA18: =SUM(C18:N18) -> 0 | BB18: =SUM(O18:Z18) -> 0 | BC18: =SUM(AA18:AL18) -> 0
A19: Depreciation & amortization | B19: Straight-line over useful life; trailing-window formula | C19: =SUM(INDEX('Working Capital'!$C$18:$AL$18,1,MAX(1,1-ROUND('Assumptions'!$F$65,0)+1)):INDEX('Working Capital'!$C$18:$AL$18,1,1))/ROUND('Assumptions'!$F$65,0) -> 0 | D19: =SUM(INDEX('Working Capital'!$C$18:$AL$18,1,MAX(1,2-ROUND('Assumptions'!$F$65,0)+1)):INDEX('Working Capital'!$C$18:$AL$18,1,2))/ROUND('Assumptions'!$F$65,0) -> 0 | E19: =SUM(INDEX('Working Capital'!$C$18:$AL$18,1,MAX(1,3-ROUND('Assumptions'!$F$65,0)+1)):INDEX('Working Capital'!$C$18:$AL$18,1,3))/ROUND('Assumptions'!$F$65,0) -> 0 | F19: =SUM(INDEX('Working Capital'!$C$18:$AL$18,1,MAX(1,4-ROUND('Assumptions'!$F$65,0)+1)):INDEX('Working Capital'!$C$18:$AL$18,1,4))/ROUND('Assumptions'!$F$65,0) -> 0 | G19: =SUM(INDEX('Working Capital'!$C$18:$AL$18,1,MAX(1,5-ROUND('Assumptions'!$F$65,0)+1)):INDEX('Working Capital'!$C$18:$AL$18,1,5))/ROUND('Assumptions'!$F$65,0) -> 0 | H19: =SUM(INDEX('Working Capital'!$C$18:$AL$18,1,MAX(1,6-ROUND('Assumptions'!$F$65,0)+1)):INDEX('Working Capital'!$C$18:$AL$18,1,6))/ROUND('Assumptions'!$F$65,0) -> 0 | I19: =SUM(INDEX('Working Capital'!$C$18:$AL$18,1,MAX(1,7-ROUND('Assumptions'!$F$65,0)+1)):INDEX('Working Capital'!$C$18:$AL$18,1,7))/ROUND('Assumptions'!$F$65,0) -> 0 | J19: =SUM(INDEX('Working Capital'!$C$18:$AL$18,1,MAX(1,8-ROUND('Assumptions'!$F$65,0)+1)):INDEX('Working Capital'!$C$18:$AL$18,1,8))/ROUND('Assumptions'!$F$65,0) -> 0 | K19: =SUM(INDEX('Working Capital'!$C$18:$AL$18,1,MAX(1,9-ROUND('Assumptions'!$F$65,0)+1)):INDEX('Working Capital'!$C$18:$AL$18,1,9))/ROUND('Assumptions'!$F$65,0) -> 0 | L19: =SUM(INDEX('Working Capital'!$C$18:$AL$18,1,MAX(1,10-ROUND('Assumptions'!$F$65,0)+1)):INDEX('Working Capital'!$C$18:$AL$18,1,10))/ROUND('Assumptions'!$F$65,0) -> 0 | M19: =SUM(INDEX('Working Capital'!$C$18:$AL$18,1,MAX(1,11-ROUND('Assumptions'!$F$65,0)+1)):INDEX('Working Capital'!$C$18:$AL$18,1,11))/ROUND('Assumptions'!$F$65,0) -> 0 | N19: =SUM(INDEX('Working Capital'!$C$18:$AL$18,1,MAX(1,12-ROUND('Assumptions'!$F$65,0)+1)):INDEX('Working Capital'!$C$18:$AL$18,1,12))/ROUND('Assumptions'!$F$65,0) -> 0 | O19: =SUM(INDEX('Working Capital'!$C$18:$AL$18,1,MAX(1,13-ROUND('Assumptions'!$F$65,0)+1)):INDEX('Working Capital'!$C$18:$AL$18,1,13))/ROUND('Assumptions'!$F$65,0) -> 0 | P19: =SUM(INDEX('Working Capital'!$C$18:$AL$18,1,MAX(1,14-ROUND('Assumptions'!$F$65,0)+1)):INDEX('Working Capital'!$C$18:$AL$18,1,14))/ROUND('Assumptions'!$F$65,0) -> 0 | Q19: =SUM(INDEX('Working Capital'!$C$18:$AL$18,1,MAX(1,15-ROUND('Assumptions'!$F$65,0)+1)):INDEX('Working Capital'!$C$18:$AL$18,1,15))/ROUND('Assumptions'!$F$65,0) -> 0 | R19: =SUM(INDEX('Working Capital'!$C$18:$AL$18,1,MAX(1,16-ROUND('Assumptions'!$F$65,0)+1)):INDEX('Working Capital'!$C$18:$AL$18,1,16))/ROUND('Assumptions'!$F$65,0) -> 0 | S19: =SUM(INDEX('Working Capital'!$C$18:$AL$18,1,MAX(1,17-ROUND('Assumptions'!$F$65,0)+1)):INDEX('Working Capital'!$C$18:$AL$18,1,17))/ROUND('Assumptions'!$F$65,0) -> 0 | T19: =SUM(INDEX('Working Capital'!$C$18:$AL$18,1,MAX(1,18-ROUND('Assumptions'!$F$65,0)+1)):INDEX('Working Capital'!$C$18:$AL$18,1,18))/ROUND('Assumptions'!$F$65,0) -> 0 | U19: =SUM(INDEX('Working Capital'!$C$18:$AL$18,1,MAX(1,19-ROUND('Assumptions'!$F$65,0)+1)):INDEX('Working Capital'!$C$18:$AL$18,1,19))/ROUND('Assumptions'!$F$65,0) -> 0 | V19: =SUM(INDEX('Working Capital'!$C$18:$AL$18,1,MAX(1,20-ROUND('Assumptions'!$F$65,0)+1)):INDEX('Working Capital'!$C$18:$AL$18,1,20))/ROUND('Assumptions'!$F$65,0) -> 0 | W19: =SUM(INDEX('Working Capital'!$C$18:$AL$18,1,MAX(1,21-ROUND('Assumptions'!$F$65,0)+1)):INDEX('Working Capital'!$C$18:$AL$18,1,21))/ROUND('Assumptions'!$F$65,0) -> 0 | X19: =SUM(INDEX('Working Capital'!$C$18:$AL$18,1,MAX(1,22-ROUND('Assumptions'!$F$65,0)+1)):INDEX('Working Capital'!$C$18:$AL$18,1,22))/ROUND('Assumptions'!$F$65,0) -> 0 | Y19: =SUM(INDEX('Working Capital'!$C$18:$AL$18,1,MAX(1,23-ROUND('Assumptions'!$F$65,0)+1)):INDEX('Working Capital'!$C$18:$AL$18,1,23))/ROUND('Assumptions'!$F$65,0) -> 0 | Z19: =SUM(INDEX('Working Capital'!$C$18:$AL$18,1,MAX(1,24-ROUND('Assumptions'!$F$65,0)+1)):INDEX('Working Capital'!$C$18:$AL$18,1,24))/ROUND('Assumptions'!$F$65,0) -> 0 | AA19: =SUM(INDEX('Working Capital'!$C$18:$AL$18,1,MAX(1,25-ROUND('Assumptions'!$F$65,0)+1)):INDEX('Working Capital'!$C$18:$AL$18,1,25))/ROUND('Assumptions'!$F$65,0) -> 0 | AB19: =SUM(INDEX('Working Capital'!$C$18:$AL$18,1,MAX(1,26-ROUND('Assumptions'!$F$65,0)+1)):INDEX('Working Capital'!$C$18:$AL$18,1,26))/ROUND('Assumptions'!$F$65,0) -> 0 | AC19: =SUM(INDEX('Working Capital'!$C$18:$AL$18,1,MAX(1,27-ROUND('Assumptions'!$F$65,0)+1)):INDEX('Working Capital'!$C$18:$AL$18,1,27))/ROUND('Assumptions'!$F$65,0) -> 0 | AD19: =SUM(INDEX('Working Capital'!$C$18:$AL$18,1,MAX(1,28-ROUND('Assumptions'!$F$65,0)+1)):INDEX('Working Capital'!$C$18:$AL$18,1,28))/ROUND('Assumptions'!$F$65,0) -> 0 | AE19: =SUM(INDEX('Working Capital'!$C$18:$AL$18,1,MAX(1,29-ROUND('Assumptions'!$F$65,0)+1)):INDEX('Working Capital'!$C$18:$AL$18,1,29))/ROUND('Assumptions'!$F$65,0) -> 0 | AF19: =SUM(INDEX('Working Capital'!$C$18:$AL$18,1,MAX(1,30-ROUND('Assumptions'!$F$65,0)+1)):INDEX('Working Capital'!$C$18:$AL$18,1,30))/ROUND('Assumptions'!$F$65,0) -> 0 | AG19: =SUM(INDEX('Working Capital'!$C$18:$AL$18,1,MAX(1,31-ROUND('Assumptions'!$F$65,0)+1)):INDEX('Working Capital'!$C$18:$AL$18,1,31))/ROUND('Assumptions'!$F$65,0) -> 0 | AH19: =SUM(INDEX('Working Capital'!$C$18:$AL$18,1,MAX(1,32-ROUND('Assumptions'!$F$65,0)+1)):INDEX('Working Capital'!$C$18:$AL$18,1,32))/ROUND('Assumptions'!$F$65,0) -> 0 | AI19: =SUM(INDEX('Working Capital'!$C$18:$AL$18,1,MAX(1,33-ROUND('Assumptions'!$F$65,0)+1)):INDEX('Working Capital'!$C$18:$AL$18,1,33))/ROUND('Assumptions'!$F$65,0) -> 0 | AJ19: =SUM(INDEX('Working Capital'!$C$18:$AL$18,1,MAX(1,34-ROUND('Assumptions'!$F$65,0)+1)):INDEX('Working Capital'!$C$18:$AL$18,1,34))/ROUND('Assumptions'!$F$65,0) -> 0 | AK19: =SUM(INDEX('Working Capital'!$C$18:$AL$18,1,MAX(1,35-ROUND('Assumptions'!$F$65,0)+1)):INDEX('Working Capital'!$C$18:$AL$18,1,35))/ROUND('Assumptions'!$F$65,0) -> 0 | AL19: =SUM(INDEX('Working Capital'!$C$18:$AL$18,1,MAX(1,36-ROUND('Assumptions'!$F$65,0)+1)):INDEX('Working Capital'!$C$18:$AL$18,1,36))/ROUND('Assumptions'!$F$65,0) -> 0 | AN19: =SUM(C19:E19) -> 0 | AO19: =SUM(F19:H19) -> 0 | AP19: =SUM(I19:K19) -> 0 | AQ19: =SUM(L19:N19) -> 0 | AR19: =SUM(O19:Q19) -> 0 | AS19: =SUM(R19:T19) -> 0 | AT19: =SUM(U19:W19) -> 0 | AU19: =SUM(X19:Z19) -> 0 | AV19: =SUM(AA19:AC19) -> 0 | AW19: =SUM(AD19:AF19) -> 0 | AX19: =SUM(AG19:AI19) -> 0 | AY19: =SUM(AJ19:AL19) -> 0 | BA19: =SUM(C19:N19) -> 0 | BB19: =SUM(O19:Z19) -> 0 | BC19: =SUM(AA19:AL19) -> 0
A20: Net PP&E balance | C20: =C18-C19 -> 0 | D20: =C20+D18-D19 -> 0 | E20: =D20+E18-E19 -> 0 | F20: =E20+F18-F19 -> 0 | G20: =F20+G18-G19 -> 0 | H20: =G20+H18-H19 -> 0 | I20: =H20+I18-I19 -> 0 | J20: =I20+J18-J19 -> 0 | K20: =J20+K18-K19 -> 0 | ... AL20: =AK20+AL18-AL19 -> 0 | AN20: =E20 -> 0 | AO20: =H20 -> 0 | AP20: =K20 -> 0 | AQ20: =N20 -> 0 | AR20: =Q20 -> 0 | AS20: =T20 -> 0 | AT20: =W20 -> 0 | AU20: =Z20 -> 0 | AV20: =AC20 -> 0 | AW20: =AF20 -> 0 | AX20: =AI20 -> 0 | AY20: =AL20 -> 0 | BA20: =N20 -> 0 | BB20: =Z20 -> 0 | BC20: =AL20 -> 0
A22: Debt Schedule
A23: Debt draw | B23: One-time draw in month 9 | C23: =0 -> 0 | D23: =0 -> 0 | E23: =0 -> 0 | F23: =0 -> 0 | G23: =0 -> 0 | H23: =0 -> 0 | I23: =0 -> 0 | J23: =0 -> 0 | K23: ='Assumptions'!$F$68 -> 0 | L23: =0 -> 0 | M23: =0 -> 0 | N23: =0 -> 0 | O23: =0 -> 0 | P23: =0 -> 0 | Q23: =0 -> 0 | R23: =0 -> 0 | S23: =0 -> 0 | ... AL23: =0 -> 0 | AN23: =SUM(C23:E23) -> 0 | AO23: =SUM(F23:H23) -> 0 | AP23: =SUM(I23:K23) -> 0 | AQ23: =SUM(L23:N23) -> 0 | AR23: =SUM(O23:Q23) -> 0 | AS23: =SUM(R23:T23) -> 0 | AT23: =SUM(U23:W23) -> 0 | AU23: =SUM(X23:Z23) -> 0 | AV23: =SUM(AA23:AC23) -> 0 | AW23: =SUM(AD23:AF23) -> 0 | AX23: =SUM(AG23:AI23) -> 0 | AY23: =SUM(AJ23:AL23) -> 0 | BA23: =SUM(C23:N23) -> 0 | BB23: =SUM(O23:Z23) -> 0 | BC23: =SUM(AA23:AL23) -> 0
A24: Debt repayment | B24: Fixed $/month once balance exists, starting the assumed month | C24: =0 -> 0 | D24: =0 -> 0 | E24: =0 -> 0 | F24: =0 -> 0 | G24: =0 -> 0 | H24: =0 -> 0 | I24: =0 -> 0 | J24: =0 -> 0 | ... T24: =0 -> 0 | U24: =MIN(T25,'Assumptions'!$F$69) -> 0 | V24: =MIN(U25,'Assumptions'!$F$69) -> 0 | W24: =MIN(V25,'Assumptions'!$F$69) -> 0 | X24: =MIN(W25,'Assumptions'!$F$69) -> 0 | Y24: =MIN(X25,'Assumptions'!$F$69) -> 0 | Z24: =MIN(Y25,'Assumptions'!$F$69) -> 0 | AA24: =MIN(Z25,'Assumptions'!$F$69) -> 0 | AB24: =MIN(AA25,'Assumptions'!$F$69) -> 0 | ... AL24: =MIN(AK25,'Assumptions'!$F$69) -> 0 | AN24: =SUM(C24:E24) -> 0 | AO24: =SUM(F24:H24) -> 0 | AP24: =SUM(I24:K24) -> 0 | AQ24: =SUM(L24:N24) -> 0 | AR24: =SUM(O24:Q24) -> 0 | AS24: =SUM(R24:T24) -> 0 | AT24: =SUM(U24:W24) -> 0 | AU24: =SUM(X24:Z24) -> 0 | AV24: =SUM(AA24:AC24) -> 0 | AW24: =SUM(AD24:AF24) -> 0 | AX24: =SUM(AG24:AI24) -> 0 | AY24: =SUM(AJ24:AL24) -> 0 | BA24: =SUM(C24:N24) -> 0 | BB24: =SUM(O24:Z24) -> 0 | BC24: =SUM(AA24:AL24) -> 0
A25: Debt balance (ending) | B25: Prior balance + draw − repayment | C25: =C23-C24 -> 0 | D25: =C25+D23-D24 -> 0 | E25: =D25+E23-E24 -> 0 | F25: =E25+F23-F24 -> 0 | G25: =F25+G23-G24 -> 0 | H25: =G25+H23-H24 -> 0 | I25: =H25+I23-I24 -> 0 | J25: =I25+J23-J24 -> 0 | K25: =J25+K23-K24 -> 0 | ... AL25: =AK25+AL23-AL24 -> 0 | AN25: =E25 -> 0 | AO25: =H25 -> 0 | AP25: =K25 -> 0 | AQ25: =N25 -> 0 | AR25: =Q25 -> 0 | AS25: =T25 -> 0 | AT25: =W25 -> 0 | AU25: =Z25 -> 0 | AV25: =AC25 -> 0 | AW25: =AF25 -> 0 | AX25: =AI25 -> 0 | AY25: =AL25 -> 0 | BA25: =N25 -> 0 | BB25: =Z25 -> 0 | BC25: =AL25 -> 0
A26: Interest expense | B26: Prior month balance × annual rate ÷ 12 | C26: =C23*'Assumptions'!$F$67/12/2 -> 0 | D26: =C25*'Assumptions'!$F$67/12 -> 0 | E26: =D25*'Assumptions'!$F$67/12 -> 0 | F26: =E25*'Assumptions'!$F$67/12 -> 0 | G26: =F25*'Assumptions'!$F$67/12 -> 0 | H26: =G25*'Assumptions'!$F$67/12 -> 0 | I26: =H25*'Assumptions'!$F$67/12 -> 0 | J26: =I25*'Assumptions'!$F$67/12 -> 0 | K26: =J25*'Assumptions'!$F$67/12 -> 0 | ... AL26: =AK25*'Assumptions'!$F$67/12 -> 0 | AN26: =SUM(C26:E26) -> 0 | AO26: =SUM(F26:H26) -> 0 | AP26: =SUM(I26:K26) -> 0 | AQ26: =SUM(L26:N26) -> 0 | AR26: =SUM(O26:Q26) -> 0 | AS26: =SUM(R26:T26) -> 0 | AT26: =SUM(U26:W26) -> 0 | AU26: =SUM(X26:Z26) -> 0 | AV26: =SUM(AA26:AC26) -> 0 | AW26: =SUM(AD26:AF26) -> 0 | AX26: =SUM(AG26:AI26) -> 0 | AY26: =SUM(AJ26:AL26) -> 0 | BA26: =SUM(C26:N26) -> 0 | BB26: =SUM(O26:Z26) -> 0 | BC26: =SUM(AA26:AL26) -> 0
A28: Equity Financing
A29: Equity raised | B29: Seed extension in month 4; Growth equity in month 19 | C29: =0 -> 0 | D29: =0 -> 0 | E29: =0 -> 0 | F29: ='Assumptions'!$F$70 -> 0 | G29: =0 -> 0 | H29: =0 -> 0 | I29: =0 -> 0 | J29: =0 -> 0 | K29: =0 -> 0 | L29: =0 -> 0 | M29: =0 -> 0 | N29: =0 -> 0 | ... T29: =0 -> 0 | U29: ='Assumptions'!$F$71 -> 0 | V29: =0 -> 0 | W29: =0 -> 0 | X29: =0 -> 0 | Y29: =0 -> 0 | Z29: =0 -> 0 | AA29: =0 -> 0 | AB29: =0 -> 0 | AC29: =0 -> 0 | ... AL29: =0 -> 0 | AN29: =SUM(C29:E29) -> 0 | AO29: =SUM(F29:H29) -> 0 | AP29: =SUM(I29:K29) -> 0 | AQ29: =SUM(L29:N29) -> 0 | AR29: =SUM(O29:Q29) -> 0 | AS29: =SUM(R29:T29) -> 0 | AT29: =SUM(U29:W29) -> 0 | AU29: =SUM(X29:Z29) -> 0 | AV29: =SUM(AA29:AC29) -> 0 | AW29: =SUM(AD29:AF29) -> 0 | AX29: =SUM(AG29:AI29) -> 0 | AY29: =SUM(AJ29:AL29) -> 0 | BA29: =SUM(C29:N29) -> 0 | BB29: =SUM(O29:Z29) -> 0 | BC29: =SUM(AA29:AL29) -> 0
A30: Cumulative paid-in capital | C30: =C29 -> 0 | D30: =C30+D29 -> 0 | E30: =D30+E29 -> 0 | F30: =E30+F29 -> 0 | G30: =F30+G29 -> 0 | H30: =G30+H29 -> 0 | I30: =H30+I29 -> 0 | J30: =I30+J29 -> 0 | K30: =J30+K29 -> 0 | ... AL30: =AK30+AL29 -> 0 | AN30: =E30 -> 0 | AO30: =H30 -> 0 | AP30: =K30 -> 0 | AQ30: =N30 -> 0 | AR30: =Q30 -> 0 | AS30: =T30 -> 0 | AT30: =W30 -> 0 | AU30: =Z30 -> 0 | AV30: =AC30 -> 0 | AW30: =AF30 -> 0 | AX30: =AI30 -> 0 | AY30: =AL30 -> 0 | BA30: =N30 -> 0 | BB30: =Z30 -> 0 | BC30: =AL30 -> 0

Sheet P&L
A1: AI-Enabled Services — 3-Year Financial Model — P&L
A2: Integrated income statement — every line links to Revenue, COGS & GM, Opex, or Working Capital.
A5: Line item | B5: Units / source | C5: Monthly (36 months) | AN5: Quarterly | BA5: Annual
C6: 46023 | D6: 46054 | E6: 46082 | F6: 46113 | G6: 46143 | H6: 46174 | I6: 46204 | J6: 46235 | K6: 46266 | L6: 46296 | M6: 46327 | N6: 46357 | O6: 46388 | P6: 46419 | Q6: 46447 | R6: 46478 | S6: 46508 | T6: 46539 | U6: 46569 | V6: 46600 | W6: 46631 | X6: 46661 | Y6: 46692 | Z6: 46722 | AA6: 46753 | AB6: 46784 | AC6: 46813 | AD6: 46844 | AE6: 46874 | AF6: 46905 | AG6: 46935 | AH6: 46966 | AI6: 46997 | AJ6: 47027 | AK6: 47058 | AL6: 47088 | AN6: Q1 | AO6: Q2 | AP6: Q3 | AQ6: Q4 | AR6: Q5 | AS6: Q6 | AT6: Q7 | AU6: Q8 | AV6: Q9 | AW6: Q10 | AX6: Q11 | AY6: Q12 | BA6: FY1 | BB6: FY2 | BC6: FY3
A7: Revenue | C7: ='Revenue'!$C$36 -> 0 | D7: ='Revenue'!$D$36 -> 0 | E7: ='Revenue'!$E$36 -> 0 | F7: ='Revenue'!$F$36 -> 0 | G7: ='Revenue'!$G$36 -> 0 | H7: ='Revenue'!$H$36 -> 0 | I7: ='Revenue'!$I$36 -> 0 | J7: ='Revenue'!$J$36 -> 0 | K7: ='Revenue'!$K$36 -> 0 | L7: ='Revenue'!$L$36 -> 0 | M7: ='Revenue'!$M$36 -> 0 | N7: ='Revenue'!$N$36 -> 0 | O7: ='Revenue'!$O$36 -> 0 | P7: ='Revenue'!$P$36 -> 0 | Q7: ='Revenue'!$Q$36 -> 0 | R7: ='Revenue'!$R$36 -> 0 | S7: ='Revenue'!$S$36 -> 0 | T7: ='Revenue'!$T$36 -> 0 | U7: ='Revenue'!$U$36 -> 0 | V7: ='Revenue'!$V$36 -> 0 | W7: ='Revenue'!$W$36 -> 0 | X7: ='Revenue'!$X$36 -> 0 | Y7: ='Revenue'!$Y$36 -> 0 | Z7: ='Revenue'!$Z$36 -> 0 | AA7: ='Revenue'!$AA$36 -> 0 | AB7: ='Revenue'!$AB$36 -> 0 | AC7: ='Revenue'!$AC$36 -> 0 | AD7: ='Revenue'!$AD$36 -> 0 | AE7: ='Revenue'!$AE$36 -> 0 | AF7: ='Revenue'!$AF$36 -> 0 | AG7: ='Revenue'!$AG$36 -> 0 | AH7: ='Revenue'!$AH$36 -> 0 | AI7: ='Revenue'!$AI$36 -> 0 | AJ7: ='Revenue'!$AJ$36 -> 0 | AK7: ='Revenue'!$AK$36 -> 0 | AL7: ='Revenue'!$AL$36 -> 0 | AN7: =SUM(C7:E7) -> 0 | AO7: =SUM(F7:H7) -> 0 | AP7: =SUM(I7:K7) -> 0 | AQ7: =SUM(L7:N7) -> 0 | AR7: =SUM(O7:Q7) -> 0 | AS7: =SUM(R7:T7) -> 0 | AT7: =SUM(U7:W7) -> 0 | AU7: =SUM(X7:Z7) -> 0 | AV7: =SUM(AA7:AC7) -> 0 | AW7: =SUM(AD7:AF7) -> 0 | AX7: =SUM(AG7:AI7) -> 0 | AY7: =SUM(AJ7:AL7) -> 0 | BA7: =SUM(C7:N7) -> 0 | BB7: =SUM(O7:Z7) -> 0 | BC7: =SUM(AA7:AL7) -> 0
A8: Cost of Goods Sold | C8: ='COGS & GM'!$C$12 -> 0 | D8: ='COGS & GM'!$D$12 -> 0 | E8: ='COGS & GM'!$E$12 -> 0 | F8: ='COGS & GM'!$F$12 -> 0 | G8: ='COGS & GM'!$G$12 -> 0 | H8: ='COGS & GM'!$H$12 -> 0 | I8: ='COGS & GM'!$I$12 -> 0 | J8: ='COGS & GM'!$J$12 -> 0 | K8: ='COGS & GM'!$K$12 -> 0 | L8: ='COGS & GM'!$L$12 -> 0 | M8: ='COGS & GM'!$M$12 -> 0 | N8: ='COGS & GM'!$N$12 -> 0 | O8: ='COGS & GM'!$O$12 -> 0 | P8: ='COGS & GM'!$P$12 -> 0 | Q8: ='COGS & GM'!$Q$12 -> 0 | R8: ='COGS & GM'!$R$12 -> 0 | S8: ='COGS & GM'!$S$12 -> 0 | T8: ='COGS & GM'!$T$12 -> 0 | U8: ='COGS & GM'!$U$12 -> 0 | V8: ='COGS & GM'!$V$12 -> 0 | W8: ='COGS & GM'!$W$12 -> 0 | X8: ='COGS & GM'!$X$12 -> 0 | Y8: ='COGS & GM'!$Y$12 -> 0 | Z8: ='COGS & GM'!$Z$12 -> 0 | AA8: ='COGS & GM'!$AA$12 -> 0 | AB8: ='COGS & GM'!$AB$12 -> 0 | AC8: ='COGS & GM'!$AC$12 -> 0 | AD8: ='COGS & GM'!$AD$12 -> 0 | AE8: ='COGS & GM'!$AE$12 -> 0 | AF8: ='COGS & GM'!$AF$12 -> 0 | AG8: ='COGS & GM'!$AG$12 -> 0 | AH8: ='COGS & GM'!$AH$12 -> 0 | AI8: ='COGS & GM'!$AI$12 -> 0 | AJ8: ='COGS & GM'!$AJ$12 -> 0 | AK8: ='COGS & GM'!$AK$12 -> 0 | AL8: ='COGS & GM'!$AL$12 -> 0 | AN8: =SUM(C8:E8) -> 0 | AO8: =SUM(F8:H8) -> 0 | AP8: =SUM(I8:K8) -> 0 | AQ8: =SUM(L8:N8) -> 0 | AR8: =SUM(O8:Q8) -> 0 | AS8: =SUM(R8:T8) -> 0 | AT8: =SUM(U8:W8) -> 0 | AU8: =SUM(X8:Z8) -> 0 | AV8: =SUM(AA8:AC8) -> 0 | AW8: =SUM(AD8:AF8) -> 0 | AX8: =SUM(AG8:AI8) -> 0 | AY8: =SUM(AJ8:AL8) -> 0 | BA8: =SUM(C8:N8) -> 0 | BB8: =SUM(O8:Z8) -> 0 | BC8: =SUM(AA8:AL8) -> 0
A9: Gross Profit | C9: =C7-C8 -> 0 | D9: =D7-D8 -> 0 | E9: =E7-E8 -> 0 | F9: =F7-F8 -> 0 | G9: =G7-G8 -> 0 | H9: =H7-H8 -> 0 | I9: =I7-I8 -> 0 | J9: =J7-J8 -> 0 | ... AL9: =AL7-AL8 -> 0 | AN9: =SUM(C9:E9) -> 0 | AO9: =SUM(F9:H9) -> 0 | AP9: =SUM(I9:K9) -> 0 | AQ9: =SUM(L9:N9) -> 0 | AR9: =SUM(O9:Q9) -> 0 | AS9: =SUM(R9:T9) -> 0 | AT9: =SUM(U9:W9) -> 0 | AU9: =SUM(X9:Z9) -> 0 | AV9: =SUM(AA9:AC9) -> 0 | AW9: =SUM(AD9:AF9) -> 0 | AX9: =SUM(AG9:AI9) -> 0 | AY9: =SUM(AJ9:AL9) -> 0 | BA9: =SUM(C9:N9) -> 0 | BB9: =SUM(O9:Z9) -> 0 | BC9: =SUM(AA9:AL9) -> 0
A10: Gross Margin % | C10: =IFERROR(C9/C7,0) -> 0 | D10: =IFERROR(D9/D7,0) -> 0 | E10: =IFERROR(E9/E7,0) -> 0 | F10: =IFERROR(F9/F7,0) -> 0 | G10: =IFERROR(G9/G7,0) -> 0 | H10: =IFERROR(H9/H7,0) -> 0 | I10: =IFERROR(I9/I7,0) -> 0 | J10: =IFERROR(J9/J7,0) -> 0 | ... AL10: =IFERROR(AL9/AL7,0) -> 0 | AN10: =AVERAGE(C10:E10) -> 0 | AO10: =AVERAGE(F10:H10) -> 0 | AP10: =AVERAGE(I10:K10) -> 0 | AQ10: =AVERAGE(L10:N10) -> 0 | AR10: =AVERAGE(O10:Q10) -> 0 | AS10: =AVERAGE(R10:T10) -> 0 | AT10: =AVERAGE(U10:W10) -> 0 | AU10: =AVERAGE(X10:Z10) -> 0 | AV10: =AVERAGE(AA10:AC10) -> 0 | AW10: =AVERAGE(AD10:AF10) -> 0 | AX10: =AVERAGE(AG10:AI10) -> 0 | AY10: =AVERAGE(AJ10:AL10) -> 0 | BA10: =AVERAGE(C10:N10) -> 0 | BB10: =AVERAGE(O10:Z10) -> 0 | BC10: =AVERAGE(AA10:AL10) -> 0
A12: Operating Expenses
A13: Sales & Marketing | C13: ='Opex'!$C$11 -> 0 | D13: ='Opex'!$D$11 -> 0 | E13: ='Opex'!$E$11 -> 0 | F13: ='Opex'!$F$11 -> 0 | G13: ='Opex'!$G$11 -> 0 | H13: ='Opex'!$H$11 -> 0 | I13: ='Opex'!$I$11 -> 0 | J13: ='Opex'!$J$11 -> 0 | K13: ='Opex'!$K$11 -> 0 | L13: ='Opex'!$L$11 -> 0 | M13: ='Opex'!$M$11 -> 0 | N13: ='Opex'!$N$11 -> 0 | O13: ='Opex'!$O$11 -> 0 | P13: ='Opex'!$P$11 -> 0 | Q13: ='Opex'!$Q$11 -> 0 | R13: ='Opex'!$R$11 -> 0 | S13: ='Opex'!$S$11 -> 0 | T13: ='Opex'!$T$11 -> 0 | U13: ='Opex'!$U$11 -> 0 | V13: ='Opex'!$V$11 -> 0 | W13: ='Opex'!$W$11 -> 0 | X13: ='Opex'!$X$11 -> 0 | Y13: ='Opex'!$Y$11 -> 0 | Z13: ='Opex'!$Z$11 -> 0 | AA13: ='Opex'!$AA$11 -> 0 | AB13: ='Opex'!$AB$11 -> 0 | AC13: ='Opex'!$AC$11 -> 0 | AD13: ='Opex'!$AD$11 -> 0 | AE13: ='Opex'!$AE$11 -> 0 | AF13: ='Opex'!$AF$11 -> 0 | AG13: ='Opex'!$AG$11 -> 0 | AH13: ='Opex'!$AH$11 -> 0 | AI13: ='Opex'!$AI$11 -> 0 | AJ13: ='Opex'!$AJ$11 -> 0 | AK13: ='Opex'!$AK$11 -> 0 | AL13: ='Opex'!$AL$11 -> 0 | AN13: =SUM(C13:E13) -> 0 | AO13: =SUM(F13:H13) -> 0 | AP13: =SUM(I13:K13) -> 0 | AQ13: =SUM(L13:N13) -> 0 | AR13: =SUM(O13:Q13) -> 0 | AS13: =SUM(R13:T13) -> 0 | AT13: =SUM(U13:W13) -> 0 | AU13: =SUM(X13:Z13) -> 0 | AV13: =SUM(AA13:AC13) -> 0 | AW13: =SUM(AD13:AF13) -> 0 | AX13: =SUM(AG13:AI13) -> 0 | AY13: =SUM(AJ13:AL13) -> 0 | BA13: =SUM(C13:N13) -> 0 | BB13: =SUM(O13:Z13) -> 0 | BC13: =SUM(AA13:AL13) -> 0
A14: General & Administrative | C14: ='Opex'!$C$17 -> 0 | D14: ='Opex'!$D$17 -> 0 | E14: ='Opex'!$E$17 -> 0 | F14: ='Opex'!$F$17 -> 0 | G14: ='Opex'!$G$17 -> 0 | H14: ='Opex'!$H$17 -> 0 | I14: ='Opex'!$I$17 -> 0 | J14: ='Opex'!$J$17 -> 0 | K14: ='Opex'!$K$17 -> 0 | L14: ='Opex'!$L$17 -> 0 | M14: ='Opex'!$M$17 -> 0 | N14: ='Opex'!$N$17 -> 0 | O14: ='Opex'!$O$17 -> 0 | P14: ='Opex'!$P$17 -> 0 | Q14: ='Opex'!$Q$17 -> 0 | R14: ='Opex'!$R$17 -> 0 | S14: ='Opex'!$S$17 -> 0 | T14: ='Opex'!$T$17 -> 0 | U14: ='Opex'!$U$17 -> 0 | V14: ='Opex'!$V$17 -> 0 | W14: ='Opex'!$W$17 -> 0 | X14: ='Opex'!$X$17 -> 0 | Y14: ='Opex'!$Y$17 -> 0 | Z14: ='Opex'!$Z$17 -> 0 | AA14: ='Opex'!$AA$17 -> 0 | AB14: ='Opex'!$AB$17 -> 0 | AC14: ='Opex'!$AC$17 -> 0 | AD14: ='Opex'!$AD$17 -> 0 | AE14: ='Opex'!$AE$17 -> 0 | AF14: ='Opex'!$AF$17 -> 0 | AG14: ='Opex'!$AG$17 -> 0 | AH14: ='Opex'!$AH$17 -> 0 | AI14: ='Opex'!$AI$17 -> 0 | AJ14: ='Opex'!$AJ$17 -> 0 | AK14: ='Opex'!$AK$17 -> 0 | AL14: ='Opex'!$AL$17 -> 0 | AN14: =SUM(C14:E14) -> 0 | AO14: =SUM(F14:H14) -> 0 | AP14: =SUM(I14:K14) -> 0 | AQ14: =SUM(L14:N14) -> 0 | AR14: =SUM(O14:Q14) -> 0 | AS14: =SUM(R14:T14) -> 0 | AT14: =SUM(U14:W14) -> 0 | AU14: =SUM(X14:Z14) -> 0 | AV14: =SUM(AA14:AC14) -> 0 | AW14: =SUM(AD14:AF14) -> 0 | AX14: =SUM(AG14:AI14) -> 0 | AY14: =SUM(AJ14:AL14) -> 0 | BA14: =SUM(C14:N14) -> 0 | BB14: =SUM(O14:Z14) -> 0 | BC14: =SUM(AA14:AL14) -> 0
A15: Total Operating Expenses | C15: =C13+C14 -> 0 | D15: =D13+D14 -> 0 | E15: =E13+E14 -> 0 | F15: =F13+F14 -> 0 | G15: =G13+G14 -> 0 | H15: =H13+H14 -> 0 | I15: =I13+I14 -> 0 | J15: =J13+J14 -> 0 | ... AL15: =AL13+AL14 -> 0 | AN15: =SUM(C15:E15) -> 0 | AO15: =SUM(F15:H15) -> 0 | AP15: =SUM(I15:K15) -> 0 | AQ15: =SUM(L15:N15) -> 0 | AR15: =SUM(O15:Q15) -> 0 | AS15: =SUM(R15:T15) -> 0 | AT15: =SUM(U15:W15) -> 0 | AU15: =SUM(X15:Z15) -> 0 | AV15: =SUM(AA15:AC15) -> 0 | AW15: =SUM(AD15:AF15) -> 0 | AX15: =SUM(AG15:AI15) -> 0 | AY15: =SUM(AJ15:AL15) -> 0 | BA15: =SUM(C15:N15) -> 0 | BB15: =SUM(O15:Z15) -> 0 | BC15: =SUM(AA15:AL15) -> 0
A17: EBITDA | C17: =C9-C15 -> 0 | D17: =D9-D15 -> 0 | E17: =E9-E15 -> 0 | F17: =F9-F15 -> 0 | G17: =G9-G15 -> 0 | H17: =H9-H15 -> 0 | I17: =I9-I15 -> 0 | J17: =J9-J15 -> 0 | ... AL17: =AL9-AL15 -> 0 | AN17: =SUM(C17:E17) -> 0 | AO17: =SUM(F17:H17) -> 0 | AP17: =SUM(I17:K17) -> 0 | AQ17: =SUM(L17:N17) -> 0 | AR17: =SUM(O17:Q17) -> 0 | AS17: =SUM(R17:T17) -> 0 | AT17: =SUM(U17:W17) -> 0 | AU17: =SUM(X17:Z17) -> 0 | AV17: =SUM(AA17:AC17) -> 0 | AW17: =SUM(AD17:AF17) -> 0 | AX17: =SUM(AG17:AI17) -> 0 | AY17: =SUM(AJ17:AL17) -> 0 | BA17: =SUM(C17:N17) -> 0 | BB17: =SUM(O17:Z17) -> 0 | BC17: =SUM(AA17:AL17) -> 0
A18: Depreciation & Amortization | C18: ='Working Capital'!$C$19 -> 0 | D18: ='Working Capital'!$D$19 -> 0 | E18: ='Working Capital'!$E$19 -> 0 | F18: ='Working Capital'!$F$19 -> 0 | G18: ='Working Capital'!$G$19 -> 0 | H18: ='Working Capital'!$H$19 -> 0 | I18: ='Working Capital'!$I$19 -> 0 | J18: ='Working Capital'!$J$19 -> 0 | K18: ='Working Capital'!$K$19 -> 0 | L18: ='Working Capital'!$L$19 -> 0 | M18: ='Working Capital'!$M$19 -> 0 | N18: ='Working Capital'!$N$19 -> 0 | O18: ='Working Capital'!$O$19 -> 0 | P18: ='Working Capital'!$P$19 -> 0 | Q18: ='Working Capital'!$Q$19 -> 0 | R18: ='Working Capital'!$R$19 -> 0 | S18: ='Working Capital'!$S$19 -> 0 | T18: ='Working Capital'!$T$19 -> 0 | U18: ='Working Capital'!$U$19 -> 0 | V18: ='Working Capital'!$V$19 -> 0 | W18: ='Working Capital'!$W$19 -> 0 | X18: ='Working Capital'!$X$19 -> 0 | Y18: ='Working Capital'!$Y$19 -> 0 | Z18: ='Working Capital'!$Z$19 -> 0 | AA18: ='Working Capital'!$AA$19 -> 0 | AB18: ='Working Capital'!$AB$19 -> 0 | AC18: ='Working Capital'!$AC$19 -> 0 | AD18: ='Working Capital'!$AD$19 -> 0 | AE18: ='Working Capital'!$AE$19 -> 0 | AF18: ='Working Capital'!$AF$19 -> 0 | AG18: ='Working Capital'!$AG$19 -> 0 | AH18: ='Working Capital'!$AH$19 -> 0 | AI18: ='Working Capital'!$AI$19 -> 0 | AJ18: ='Working Capital'!$AJ$19 -> 0 | AK18: ='Working Capital'!$AK$19 -> 0 | AL18: ='Working Capital'!$AL$19 -> 0 | AN18: =SUM(C18:E18) -> 0 | AO18: =SUM(F18:H18) -> 0 | AP18: =SUM(I18:K18) -> 0 | AQ18: =SUM(L18:N18) -> 0 | AR18: =SUM(O18:Q18) -> 0 | AS18: =SUM(R18:T18) -> 0 | AT18: =SUM(U18:W18) -> 0 | AU18: =SUM(X18:Z18) -> 0 | AV18: =SUM(AA18:AC18) -> 0 | AW18: =SUM(AD18:AF18) -> 0 | AX18: =SUM(AG18:AI18) -> 0 | AY18: =SUM(AJ18:AL18) -> 0 | BA18: =SUM(C18:N18) -> 0 | BB18: =SUM(O18:Z18) -> 0 | BC18: =SUM(AA18:AL18) -> 0
A19: EBIT (Operating Income) | C19: =C17-C18 -> 0 | D19: =D17-D18 -> 0 | E19: =E17-E18 -> 0 | F19: =F17-F18 -> 0 | G19: =G17-G18 -> 0 | H19: =H17-H18 -> 0 | I19: =I17-I18 -> 0 | J19: =J17-J18 -> 0 | ... AL19: =AL17-AL18 -> 0 | AN19: =SUM(C19:E19) -> 0 | AO19: =SUM(F19:H19) -> 0 | AP19: =SUM(I19:K19) -> 0 | AQ19: =SUM(L19:N19) -> 0 | AR19: =SUM(O19:Q19) -> 0 | AS19: =SUM(R19:T19) -> 0 | AT19: =SUM(U19:W19) -> 0 | AU19: =SUM(X19:Z19) -> 0 | AV19: =SUM(AA19:AC19) -> 0 | AW19: =SUM(AD19:AF19) -> 0 | AX19: =SUM(AG19:AI19) -> 0 | AY19: =SUM(AJ19:AL19) -> 0 | BA19: =SUM(C19:N19) -> 0 | BB19: =SUM(O19:Z19) -> 0 | BC19: =SUM(AA19:AL19) -> 0
A20: Interest Expense | C20: ='Working Capital'!$C$26 -> 0 | D20: ='Working Capital'!$D$26 -> 0 | E20: ='Working Capital'!$E$26 -> 0 | F20: ='Working Capital'!$F$26 -> 0 | G20: ='Working Capital'!$G$26 -> 0 | H20: ='Working Capital'!$H$26 -> 0 | I20: ='Working Capital'!$I$26 -> 0 | J20: ='Working Capital'!$J$26 -> 0 | K20: ='Working Capital'!$K$26 -> 0 | L20: ='Working Capital'!$L$26 -> 0 | M20: ='Working Capital'!$M$26 -> 0 | N20: ='Working Capital'!$N$26 -> 0 | O20: ='Working Capital'!$O$26 -> 0 | P20: ='Working Capital'!$P$26 -> 0 | Q20: ='Working Capital'!$Q$26 -> 0 | R20: ='Working Capital'!$R$26 -> 0 | S20: ='Working Capital'!$S$26 -> 0 | T20: ='Working Capital'!$T$26 -> 0 | U20: ='Working Capital'!$U$26 -> 0 | V20: ='Working Capital'!$V$26 -> 0 | W20: ='Working Capital'!$W$26 -> 0 | X20: ='Working Capital'!$X$26 -> 0 | Y20: ='Working Capital'!$Y$26 -> 0 | Z20: ='Working Capital'!$Z$26 -> 0 | AA20: ='Working Capital'!$AA$26 -> 0 | AB20: ='Working Capital'!$AB$26 -> 0 | AC20: ='Working Capital'!$AC$26 -> 0 | AD20: ='Working Capital'!$AD$26 -> 0 | AE20: ='Working Capital'!$AE$26 -> 0 | AF20: ='Working Capital'!$AF$26 -> 0 | AG20: ='Working Capital'!$AG$26 -> 0 | AH20: ='Working Capital'!$AH$26 -> 0 | AI20: ='Working Capital'!$AI$26 -> 0 | AJ20: ='Working Capital'!$AJ$26 -> 0 | AK20: ='Working Capital'!$AK$26 -> 0 | AL20: ='Working Capital'!$AL$26 -> 0 | AN20: =SUM(C20:E20) -> 0 | AO20: =SUM(F20:H20) -> 0 | AP20: =SUM(I20:K20) -> 0 | AQ20: =SUM(L20:N20) -> 0 | AR20: =SUM(O20:Q20) -> 0 | AS20: =SUM(R20:T20) -> 0 | AT20: =SUM(U20:W20) -> 0 | AU20: =SUM(X20:Z20) -> 0 | AV20: =SUM(AA20:AC20) -> 0 | AW20: =SUM(AD20:AF20) -> 0 | AX20: =SUM(AG20:AI20) -> 0 | AY20: =SUM(AJ20:AL20) -> 0 | BA20: =SUM(C20:N20) -> 0 | BB20: =SUM(O20:Z20) -> 0 | BC20: =SUM(AA20:AL20) -> 0
A21: Earnings Before Tax | C21: =C19-C20 -> 0 | D21: =D19-D20 -> 0 | E21: =E19-E20 -> 0 | F21: =F19-F20 -> 0 | G21: =G19-G20 -> 0 | H21: =H19-H20 -> 0 | I21: =I19-I20 -> 0 | J21: =J19-J20 -> 0 | ... AL21: =AL19-AL20 -> 0 | AN21: =SUM(C21:E21) -> 0 | AO21: =SUM(F21:H21) -> 0 | AP21: =SUM(I21:K21) -> 0 | AQ21: =SUM(L21:N21) -> 0 | AR21: =SUM(O21:Q21) -> 0 | AS21: =SUM(R21:T21) -> 0 | AT21: =SUM(U21:W21) -> 0 | AU21: =SUM(X21:Z21) -> 0 | AV21: =SUM(AA21:AC21) -> 0 | AW21: =SUM(AD21:AF21) -> 0 | AX21: =SUM(AG21:AI21) -> 0 | AY21: =SUM(AJ21:AL21) -> 0 | BA21: =SUM(C21:N21) -> 0 | BB21: =SUM(O21:Z21) -> 0 | BC21: =SUM(AA21:AL21) -> 0
A22: Income Tax Expense | B22: MAX(0, EBT) × tax rate — no NOL modeling | C22: =MAX(0,C21)*'Assumptions'!$F$10 -> 0 | D22: =MAX(0,D21)*'Assumptions'!$F$10 -> 0 | E22: =MAX(0,E21)*'Assumptions'!$F$10 -> 0 | F22: =MAX(0,F21)*'Assumptions'!$F$10 -> 0 | G22: =MAX(0,G21)*'Assumptions'!$F$10 -> 0 | H22: =MAX(0,H21)*'Assumptions'!$F$10 -> 0 | I22: =MAX(0,I21)*'Assumptions'!$F$10 -> 0 | J22: =MAX(0,J21)*'Assumptions'!$F$10 -> 0 | ... AL22: =MAX(0,AL21)*'Assumptions'!$F$10 -> 0 | AN22: =SUM(C22:E22) -> 0 | AO22: =SUM(F22:H22) -> 0 | AP22: =SUM(I22:K22) -> 0 | AQ22: =SUM(L22:N22) -> 0 | AR22: =SUM(O22:Q22) -> 0 | AS22: =SUM(R22:T22) -> 0 | AT22: =SUM(U22:W22) -> 0 | AU22: =SUM(X22:Z22) -> 0 | AV22: =SUM(AA22:AC22) -> 0 | AW22: =SUM(AD22:AF22) -> 0 | AX22: =SUM(AG22:AI22) -> 0 | AY22: =SUM(AJ22:AL22) -> 0 | BA22: =SUM(C22:N22) -> 0 | BB22: =SUM(O22:Z22) -> 0 | BC22: =SUM(AA22:AL22) -> 0
A23: Net Income | C23: =C21-C22 -> 0 | D23: =D21-D22 -> 0 | E23: =E21-E22 -> 0 | F23: =F21-F22 -> 0 | G23: =G21-G22 -> 0 | H23: =H21-H22 -> 0 | I23: =I21-I22 -> 0 | J23: =J21-J22 -> 0 | ... AL23: =AL21-AL22 -> 0 | AN23: =SUM(C23:E23) -> 0 | AO23: =SUM(F23:H23) -> 0 | AP23: =SUM(I23:K23) -> 0 | AQ23: =SUM(L23:N23) -> 0 | AR23: =SUM(O23:Q23) -> 0 | AS23: =SUM(R23:T23) -> 0 | AT23: =SUM(U23:W23) -> 0 | AU23: =SUM(X23:Z23) -> 0 | AV23: =SUM(AA23:AC23) -> 0 | AW23: =SUM(AD23:AF23) -> 0 | AX23: =SUM(AG23:AI23) -> 0 | AY23: =SUM(AJ23:AL23) -> 0 | BA23: =SUM(C23:N23) -> 0 | BB23: =SUM(O23:Z23) -> 0 | BC23: =SUM(AA23:AL23) -> 0

Sheet Cash Flow
A1: AI-Enabled Services — 3-Year Financial Model — Cash Flow
A2: Indirect method — Net Income reconciled to the change in cash.
A5: Line item | B5: Units / source | C5: Monthly (36 months) | AN5: Quarterly | BA5: Annual
C6: 46023 | D6: 46054 | E6: 46082 | F6: 46113 | G6: 46143 | H6: 46174 | I6: 46204 | J6: 46235 | K6: 46266 | L6: 46296 | M6: 46327 | N6: 46357 | O6: 46388 | P6: 46419 | Q6: 46447 | R6: 46478 | S6: 46508 | T6: 46539 | U6: 46569 | V6: 46600 | W6: 46631 | X6: 46661 | Y6: 46692 | Z6: 46722 | AA6: 46753 | AB6: 46784 | AC6: 46813 | AD6: 46844 | AE6: 46874 | AF6: 46905 | AG6: 46935 | AH6: 46966 | AI6: 46997 | AJ6: 47027 | AK6: 47058 | AL6: 47088 | AN6: Q1 | AO6: Q2 | AP6: Q3 | AQ6: Q4 | AR6: Q5 | AS6: Q6 | AT6: Q7 | AU6: Q8 | AV6: Q9 | AW6: Q10 | AX6: Q11 | AY6: Q12 | BA6: FY1 | BB6: FY2 | BC6: FY3
A7: Cash from Operations
A8: Net Income | C8: ='P&L'!$C$23 -> 0 | D8: ='P&L'!$D$23 -> 0 | E8: ='P&L'!$E$23 -> 0 | F8: ='P&L'!$F$23 -> 0 | G8: ='P&L'!$G$23 -> 0 | H8: ='P&L'!$H$23 -> 0 | I8: ='P&L'!$I$23 -> 0 | J8: ='P&L'!$J$23 -> 0 | K8: ='P&L'!$K$23 -> 0 | L8: ='P&L'!$L$23 -> 0 | M8: ='P&L'!$M$23 -> 0 | N8: ='P&L'!$N$23 -> 0 | O8: ='P&L'!$O$23 -> 0 | P8: ='P&L'!$P$23 -> 0 | Q8: ='P&L'!$Q$23 -> 0 | R8: ='P&L'!$R$23 -> 0 | S8: ='P&L'!$S$23 -> 0 | T8: ='P&L'!$T$23 -> 0 | U8: ='P&L'!$U$23 -> 0 | V8: ='P&L'!$V$23 -> 0 | W8: ='P&L'!$W$23 -> 0 | X8: ='P&L'!$X$23 -> 0 | Y8: ='P&L'!$Y$23 -> 0 | Z8: ='P&L'!$Z$23 -> 0 | AA8: ='P&L'!$AA$23 -> 0 | AB8: ='P&L'!$AB$23 -> 0 | AC8: ='P&L'!$AC$23 -> 0 | AD8: ='P&L'!$AD$23 -> 0 | AE8: ='P&L'!$AE$23 -> 0 | AF8: ='P&L'!$AF$23 -> 0 | AG8: ='P&L'!$AG$23 -> 0 | AH8: ='P&L'!$AH$23 -> 0 | AI8: ='P&L'!$AI$23 -> 0 | AJ8: ='P&L'!$AJ$23 -> 0 | AK8: ='P&L'!$AK$23 -> 0 | AL8: ='P&L'!$AL$23 -> 0 | AN8: =SUM(C8:E8) -> 0 | AO8: =SUM(F8:H8) -> 0 | AP8: =SUM(I8:K8) -> 0 | AQ8: =SUM(L8:N8) -> 0 | AR8: =SUM(O8:Q8) -> 0 | AS8: =SUM(R8:T8) -> 0 | AT8: =SUM(U8:W8) -> 0 | AU8: =SUM(X8:Z8) -> 0 | AV8: =SUM(AA8:AC8) -> 0 | AW8: =SUM(AD8:AF8) -> 0 | AX8: =SUM(AG8:AI8) -> 0 | AY8: =SUM(AJ8:AL8) -> 0 | BA8: =SUM(C8:N8) -> 0 | BB8: =SUM(O8:Z8) -> 0 | BC8: =SUM(AA8:AL8) -> 0
A9: + Depreciation & Amortization | C9: ='P&L'!$C$18 -> 0 | D9: ='P&L'!$D$18 -> 0 | E9: ='P&L'!$E$18 -> 0 | F9: ='P&L'!$F$18 -> 0 | G9: ='P&L'!$G$18 -> 0 | H9: ='P&L'!$H$18 -> 0 | I9: ='P&L'!$I$18 -> 0 | J9: ='P&L'!$J$18 -> 0 | K9: ='P&L'!$K$18 -> 0 | L9: ='P&L'!$L$18 -> 0 | M9: ='P&L'!$M$18 -> 0 | N9: ='P&L'!$N$18 -> 0 | O9: ='P&L'!$O$18 -> 0 | P9: ='P&L'!$P$18 -> 0 | Q9: ='P&L'!$Q$18 -> 0 | R9: ='P&L'!$R$18 -> 0 | S9: ='P&L'!$S$18 -> 0 | T9: ='P&L'!$T$18 -> 0 | U9: ='P&L'!$U$18 -> 0 | V9: ='P&L'!$V$18 -> 0 | W9: ='P&L'!$W$18 -> 0 | X9: ='P&L'!$X$18 -> 0 | Y9: ='P&L'!$Y$18 -> 0 | Z9: ='P&L'!$Z$18 -> 0 | AA9: ='P&L'!$AA$18 -> 0 | AB9: ='P&L'!$AB$18 -> 0 | AC9: ='P&L'!$AC$18 -> 0 | AD9: ='P&L'!$AD$18 -> 0 | AE9: ='P&L'!$AE$18 -> 0 | AF9: ='P&L'!$AF$18 -> 0 | AG9: ='P&L'!$AG$18 -> 0 | AH9: ='P&L'!$AH$18 -> 0 | AI9: ='P&L'!$AI$18 -> 0 | AJ9: ='P&L'!$AJ$18 -> 0 | AK9: ='P&L'!$AK$18 -> 0 | AL9: ='P&L'!$AL$18 -> 0 | AN9: =SUM(C9:E9) -> 0 | AO9: =SUM(F9:H9) -> 0 | AP9: =SUM(I9:K9) -> 0 | AQ9: =SUM(L9:N9) -> 0 | AR9: =SUM(O9:Q9) -> 0 | AS9: =SUM(R9:T9) -> 0 | AT9: =SUM(U9:W9) -> 0 | AU9: =SUM(X9:Z9) -> 0 | AV9: =SUM(AA9:AC9) -> 0 | AW9: =SUM(AD9:AF9) -> 0 | AX9: =SUM(AG9:AI9) -> 0 | AY9: =SUM(AJ9:AL9) -> 0 | BA9: =SUM(C9:N9) -> 0 | BB9: =SUM(O9:Z9) -> 0 | BC9: =SUM(AA9:AL9) -> 0
A10: − Change in Accounts Receivable | C10: =-'Working Capital'!C12 -> 0 | D10: =-'Working Capital'!D12 -> 0 | E10: =-'Working Capital'!E12 -> 0 | F10: =-'Working Capital'!F12 -> 0 | G10: =-'Working Capital'!G12 -> 0 | H10: =-'Working Capital'!H12 -> 0 | I10: =-'Working Capital'!I12 -> 0 | J10: =-'Working Capital'!J12 -> 0 | ... AL10: =-'Working Capital'!AL12 -> 0 | AN10: =SUM(C10:E10) -> 0 | AO10: =SUM(F10:H10) -> 0 | AP10: =SUM(I10:K10) -> 0 | AQ10: =SUM(L10:N10) -> 0 | AR10: =SUM(O10:Q10) -> 0 | AS10: =SUM(R10:T10) -> 0 | AT10: =SUM(U10:W10) -> 0 | AU10: =SUM(X10:Z10) -> 0 | AV10: =SUM(AA10:AC10) -> 0 | AW10: =SUM(AD10:AF10) -> 0 | AX10: =SUM(AG10:AI10) -> 0 | AY10: =SUM(AJ10:AL10) -> 0 | BA10: =SUM(C10:N10) -> 0 | BB10: =SUM(O10:Z10) -> 0 | BC10: =SUM(AA10:AL10) -> 0
A11: − Change in Other Current Assets | C11: =-'Working Capital'!C15 -> 0 | D11: =-'Working Capital'!D15 -> 0 | E11: =-'Working Capital'!E15 -> 0 | F11: =-'Working Capital'!F15 -> 0 | G11: =-'Working Capital'!G15 -> 0 | H11: =-'Working Capital'!H15 -> 0 | I11: =-'Working Capital'!I15 -> 0 | J11: =-'Working Capital'!J15 -> 0 | ... AL11: =-'Working Capital'!AL15 -> 0 | AN11: =SUM(C11:E11) -> 0 | AO11: =SUM(F11:H11) -> 0 | AP11: =SUM(I11:K11) -> 0 | AQ11: =SUM(L11:N11) -> 0 | AR11: =SUM(O11:Q11) -> 0 | AS11: =SUM(R11:T11) -> 0 | AT11: =SUM(U11:W11) -> 0 | AU11: =SUM(X11:Z11) -> 0 | AV11: =SUM(AA11:AC11) -> 0 | AW11: =SUM(AD11:AF11) -> 0 | AX11: =SUM(AG11:AI11) -> 0 | AY11: =SUM(AJ11:AL11) -> 0 | BA11: =SUM(C11:N11) -> 0 | BB11: =SUM(O11:Z11) -> 0 | BC11: =SUM(AA11:AL11) -> 0
A12: + Change in Accounts Payable | C12: ='Working Capital'!C13 -> 0 | D12: ='Working Capital'!D13 -> 0 | E12: ='Working Capital'!E13 -> 0 | F12: ='Working Capital'!F13 -> 0 | G12: ='Working Capital'!G13 -> 0 | H12: ='Working Capital'!H13 -> 0 | I12: ='Working Capital'!I13 -> 0 | J12: ='Working Capital'!J13 -> 0 | ... AL12: ='Working Capital'!AL13 -> 0 | AN12: =SUM(C12:E12) -> 0 | AO12: =SUM(F12:H12) -> 0 | AP12: =SUM(I12:K12) -> 0 | AQ12: =SUM(L12:N12) -> 0 | AR12: =SUM(O12:Q12) -> 0 | AS12: =SUM(R12:T12) -> 0 | AT12: =SUM(U12:W12) -> 0 | AU12: =SUM(X12:Z12) -> 0 | AV12: =SUM(AA12:AC12) -> 0 | AW12: =SUM(AD12:AF12) -> 0 | AX12: =SUM(AG12:AI12) -> 0 | AY12: =SUM(AJ12:AL12) -> 0 | BA12: =SUM(C12:N12) -> 0 | BB12: =SUM(O12:Z12) -> 0 | BC12: =SUM(AA12:AL12) -> 0
A13: + Change in Deferred Revenue | C13: ='Working Capital'!C14 -> 0 | D13: ='Working Capital'!D14 -> 0 | E13: ='Working Capital'!E14 -> 0 | F13: ='Working Capital'!F14 -> 0 | G13: ='Working Capital'!G14 -> 0 | H13: ='Working Capital'!H14 -> 0 | I13: ='Working Capital'!I14 -> 0 | J13: ='Working Capital'!J14 -> 0 | ... AL13: ='Working Capital'!AL14 -> 0 | AN13: =SUM(C13:E13) -> 0 | AO13: =SUM(F13:H13) -> 0 | AP13: =SUM(I13:K13) -> 0 | AQ13: =SUM(L13:N13) -> 0 | AR13: =SUM(O13:Q13) -> 0 | AS13: =SUM(R13:T13) -> 0 | AT13: =SUM(U13:W13) -> 0 | AU13: =SUM(X13:Z13) -> 0 | AV13: =SUM(AA13:AC13) -> 0 | AW13: =SUM(AD13:AF13) -> 0 | AX13: =SUM(AG13:AI13) -> 0 | AY13: =SUM(AJ13:AL13) -> 0 | BA13: =SUM(C13:N13) -> 0 | BB13: =SUM(O13:Z13) -> 0 | BC13: =SUM(AA13:AL13) -> 0
A14: Cash from Operations | C14: =C8+C9+C10+C11+C12+C13 -> 0 | D14: =D8+D9+D10+D11+D12+D13 -> 0 | E14: =E8+E9+E10+E11+E12+E13 -> 0 | F14: =F8+F9+F10+F11+F12+F13 -> 0 | G14: =G8+G9+G10+G11+G12+G13 -> 0 | H14: =H8+H9+H10+H11+H12+H13 -> 0 | I14: =I8+I9+I10+I11+I12+I13 -> 0 | J14: =J8+J9+J10+J11+J12+J13 -> 0 | ... AL14: =AL8+AL9+AL10+AL11+AL12+AL13 -> 0 | AN14: =SUM(C14:E14) -> 0 | AO14: =SUM(F14:H14) -> 0 | AP14: =SUM(I14:K14) -> 0 | AQ14: =SUM(L14:N14) -> 0 | AR14: =SUM(O14:Q14) -> 0 | AS14: =SUM(R14:T14) -> 0 | AT14: =SUM(U14:W14) -> 0 | AU14: =SUM(X14:Z14) -> 0 | AV14: =SUM(AA14:AC14) -> 0 | AW14: =SUM(AD14:AF14) -> 0 | AX14: =SUM(AG14:AI14) -> 0 | AY14: =SUM(AJ14:AL14) -> 0 | BA14: =SUM(C14:N14) -> 0 | BB14: =SUM(O14:Z14) -> 0 | BC14: =SUM(AA14:AL14) -> 0
A16: Cash from Investing
A17: − Capital Expenditures | C17: =-'Working Capital'!C18 -> 0 | D17: =-'Working Capital'!D18 -> 0 | E17: =-'Working Capital'!E18 -> 0 | F17: =-'Working Capital'!F18 -> 0 | G17: =-'Working Capital'!G18 -> 0 | H17: =-'Working Capital'!H18 -> 0 | I17: =-'Working Capital'!I18 -> 0 | J17: =-'Working Capital'!J18 -> 0 | ... AL17: =-'Working Capital'!AL18 -> 0 | AN17: =SUM(C17:E17) -> 0 | AO17: =SUM(F17:H17) -> 0 | AP17: =SUM(I17:K17) -> 0 | AQ17: =SUM(L17:N17) -> 0 | AR17: =SUM(O17:Q17) -> 0 | AS17: =SUM(R17:T17) -> 0 | AT17: =SUM(U17:W17) -> 0 | AU17: =SUM(X17:Z17) -> 0 | AV17: =SUM(AA17:AC17) -> 0 | AW17: =SUM(AD17:AF17) -> 0 | AX17: =SUM(AG17:AI17) -> 0 | AY17: =SUM(AJ17:AL17) -> 0 | BA17: =SUM(C17:N17) -> 0 | BB17: =SUM(O17:Z17) -> 0 | BC17: =SUM(AA17:AL17) -> 0
A18: Cash from Investing | C18: =C17 -> 0 | D18: =D17 -> 0 | E18: =E17 -> 0 | F18: =F17 -> 0 | G18: =G17 -> 0 | H18: =H17 -> 0 | I18: =I17 -> 0 | J18: =J17 -> 0 | ... AL18: =AL17 -> 0 | AN18: =SUM(C18:E18) -> 0 | AO18: =SUM(F18:H18) -> 0 | AP18: =SUM(I18:K18) -> 0 | AQ18: =SUM(L18:N18) -> 0 | AR18: =SUM(O18:Q18) -> 0 | AS18: =SUM(R18:T18) -> 0 | AT18: =SUM(U18:W18) -> 0 | AU18: =SUM(X18:Z18) -> 0 | AV18: =SUM(AA18:AC18) -> 0 | AW18: =SUM(AD18:AF18) -> 0 | AX18: =SUM(AG18:AI18) -> 0 | AY18: =SUM(AJ18:AL18) -> 0 | BA18: =SUM(C18:N18) -> 0 | BB18: =SUM(O18:Z18) -> 0 | BC18: =SUM(AA18:AL18) -> 0
A20: Cash from Financing
A21: + Debt Draw | C21: ='Working Capital'!C23 -> 0 | D21: ='Working Capital'!D23 -> 0 | E21: ='Working Capital'!E23 -> 0 | F21: ='Working Capital'!F23 -> 0 | G21: ='Working Capital'!G23 -> 0 | H21: ='Working Capital'!H23 -> 0 | I21: ='Working Capital'!I23 -> 0 | J21: ='Working Capital'!J23 -> 0 | ... AL21: ='Working Capital'!AL23 -> 0 | AN21: =SUM(C21:E21) -> 0 | AO21: =SUM(F21:H21) -> 0 | AP21: =SUM(I21:K21) -> 0 | AQ21: =SUM(L21:N21) -> 0 | AR21: =SUM(O21:Q21) -> 0 | AS21: =SUM(R21:T21) -> 0 | AT21: =SUM(U21:W21) -> 0 | AU21: =SUM(X21:Z21) -> 0 | AV21: =SUM(AA21:AC21) -> 0 | AW21: =SUM(AD21:AF21) -> 0 | AX21: =SUM(AG21:AI21) -> 0 | AY21: =SUM(AJ21:AL21) -> 0 | BA21: =SUM(C21:N21) -> 0 | BB21: =SUM(O21:Z21) -> 0 | BC21: =SUM(AA21:AL21) -> 0
A22: − Debt Repayment | C22: =-'Working Capital'!C24 -> 0 | D22: =-'Working Capital'!D24 -> 0 | E22: =-'Working Capital'!E24 -> 0 | F22: =-'Working Capital'!F24 -> 0 | G22: =-'Working Capital'!G24 -> 0 | H22: =-'Working Capital'!H24 -> 0 | I22: =-'Working Capital'!I24 -> 0 | J22: =-'Working Capital'!J24 -> 0 | ... AL22: =-'Working Capital'!AL24 -> 0 | AN22: =SUM(C22:E22) -> 0 | AO22: =SUM(F22:H22) -> 0 | AP22: =SUM(I22:K22) -> 0 | AQ22: =SUM(L22:N22) -> 0 | AR22: =SUM(O22:Q22) -> 0 | AS22: =SUM(R22:T22) -> 0 | AT22: =SUM(U22:W22) -> 0 | AU22: =SUM(X22:Z22) -> 0 | AV22: =SUM(AA22:AC22) -> 0 | AW22: =SUM(AD22:AF22) -> 0 | AX22: =SUM(AG22:AI22) -> 0 | AY22: =SUM(AJ22:AL22) -> 0 | BA22: =SUM(C22:N22) -> 0 | BB22: =SUM(O22:Z22) -> 0 | BC22: =SUM(AA22:AL22) -> 0
A23: + Equity Raised | C23: ='Working Capital'!C29 -> 0 | D23: ='Working Capital'!D29 -> 0 | E23: ='Working Capital'!E29 -> 0 | F23: ='Working Capital'!F29 -> 0 | G23: ='Working Capital'!G29 -> 0 | H23: ='Working Capital'!H29 -> 0 | I23: ='Working Capital'!I29 -> 0 | J23: ='Working Capital'!J29 -> 0 | ... AL23: ='Working Capital'!AL29 -> 0 | AN23: =SUM(C23:E23) -> 0 | AO23: =SUM(F23:H23) -> 0 | AP23: =SUM(I23:K23) -> 0 | AQ23: =SUM(L23:N23) -> 0 | AR23: =SUM(O23:Q23) -> 0 | AS23: =SUM(R23:T23) -> 0 | AT23: =SUM(U23:W23) -> 0 | AU23: =SUM(X23:Z23) -> 0 | AV23: =SUM(AA23:AC23) -> 0 | AW23: =SUM(AD23:AF23) -> 0 | AX23: =SUM(AG23:AI23) -> 0 | AY23: =SUM(AJ23:AL23) -> 0 | BA23: =SUM(C23:N23) -> 0 | BB23: =SUM(O23:Z23) -> 0 | BC23: =SUM(AA23:AL23) -> 0
A24: Cash from Financing | C24: =C21+C22+C23 -> 0 | D24: =D21+D22+D23 -> 0 | E24: =E21+E22+E23 -> 0 | F24: =F21+F22+F23 -> 0 | G24: =G21+G22+G23 -> 0 | H24: =H21+H22+H23 -> 0 | I24: =I21+I22+I23 -> 0 | J24: =J21+J22+J23 -> 0 | ... AL24: =AL21+AL22+AL23 -> 0 | AN24: =SUM(C24:E24) -> 0 | AO24: =SUM(F24:H24) -> 0 | AP24: =SUM(I24:K24) -> 0 | AQ24: =SUM(L24:N24) -> 0 | AR24: =SUM(O24:Q24) -> 0 | AS24: =SUM(R24:T24) -> 0 | AT24: =SUM(U24:W24) -> 0 | AU24: =SUM(X24:Z24) -> 0 | AV24: =SUM(AA24:AC24) -> 0 | AW24: =SUM(AD24:AF24) -> 0 | AX24: =SUM(AG24:AI24) -> 0 | AY24: =SUM(AJ24:AL24) -> 0 | BA24: =SUM(C24:N24) -> 0 | BB24: =SUM(O24:Z24) -> 0 | BC24: =SUM(AA24:AL24) -> 0
A26: Net Change in Cash | C26: =C14+C18+C24 -> 0 | D26: =D14+D18+D24 -> 0 | E26: =E14+E18+E24 -> 0 | F26: =F14+F18+F24 -> 0 | G26: =G14+G18+G24 -> 0 | H26: =H14+H18+H24 -> 0 | I26: =I14+I18+I24 -> 0 | J26: =J14+J18+J24 -> 0 | ... AL26: =AL14+AL18+AL24 -> 0 | AN26: =SUM(C26:E26) -> 0 | AO26: =SUM(F26:H26) -> 0 | AP26: =SUM(I26:K26) -> 0 | AQ26: =SUM(L26:N26) -> 0 | AR26: =SUM(O26:Q26) -> 0 | AS26: =SUM(R26:T26) -> 0 | AT26: =SUM(U26:W26) -> 0 | AU26: =SUM(X26:Z26) -> 0 | AV26: =SUM(AA26:AC26) -> 0 | AW26: =SUM(AD26:AF26) -> 0 | AX26: =SUM(AG26:AI26) -> 0 | AY26: =SUM(AJ26:AL26) -> 0 | BA26: =SUM(C26:N26) -> 0 | BB26: =SUM(O26:Z26) -> 0 | BC26: =SUM(AA26:AL26) -> 0
A27: Beginning Cash | B27: Prior month ending cash (or starting cash in month 1) | C27: ='Assumptions'!$F$8 -> 0 | D27: =C28 -> 0 | E27: =D28 -> 0 | F27: =E28 -> 0 | G27: =F28 -> 0 | H27: =G28 -> 0 | I27: =H28 -> 0 | J27: =I28 -> 0 | K27: =J28 -> 0 | ... AL27: =AK28 -> 0 | AN27: =C27 -> 0 | AO27: =F27 -> 0 | AP27: =I27 -> 0 | AQ27: =L27 -> 0 | AR27: =O27 -> 0 | AS27: =R27 -> 0 | AT27: =U27 -> 0 | AU27: =X27 -> 0 | AV27: =AA27 -> 0 | AW27: =AD27 -> 0 | AX27: =AG27 -> 0 | AY27: =AJ27 -> 0 | BA27: =C27 -> 0 | BB27: =O27 -> 0 | BC27: =AA27 -> 0
A28: Ending Cash | B28: Beginning cash + net change in cash | C28: =C27+C26 -> 0 | D28: =D27+D26 -> 0 | E28: =E27+E26 -> 0 | F28: =F27+F26 -> 0 | G28: =G27+G26 -> 0 | H28: =H27+H26 -> 0 | I28: =I27+I26 -> 0 | J28: =J27+J26 -> 0 | ... AL28: =AL27+AL26 -> 0 | AN28: =E28 -> 0 | AO28: =H28 -> 0 | AP28: =K28 -> 0 | AQ28: =N28 -> 0 | AR28: =Q28 -> 0 | AS28: =T28 -> 0 | AT28: =W28 -> 0 | AU28: =Z28 -> 0 | AV28: =AC28 -> 0 | AW28: =AF28 -> 0 | AX28: =AI28 -> 0 | AY28: =AL28 -> 0 | BA28: =N28 -> 0 | BB28: =Z28 -> 0 | BC28: =AL28 -> 0

Sheet Balance Sheet
A1: AI-Enabled Services — 3-Year Financial Model — Balance Sheet
A2: Assets = Liabilities + Equity every month, by construction.
A5: Line item | B5: Units / source | C5: Monthly (36 months) | AN5: Quarterly | BA5: Annual
C6: 46023 | D6: 46054 | E6: 46082 | F6: 46113 | G6: 46143 | H6: 46174 | I6: 46204 | J6: 46235 | K6: 46266 | L6: 46296 | M6: 46327 | N6: 46357 | O6: 46388 | P6: 46419 | Q6: 46447 | R6: 46478 | S6: 46508 | T6: 46539 | U6: 46569 | V6: 46600 | W6: 46631 | X6: 46661 | Y6: 46692 | Z6: 46722 | AA6: 46753 | AB6: 46784 | AC6: 46813 | AD6: 46844 | AE6: 46874 | AF6: 46905 | AG6: 46935 | AH6: 46966 | AI6: 46997 | AJ6: 47027 | AK6: 47058 | AL6: 47088 | AN6: Q1 | AO6: Q2 | AP6: Q3 | AQ6: Q4 | AR6: Q5 | AS6: Q6 | AT6: Q7 | AU6: Q8 | AV6: Q9 | AW6: Q10 | AX6: Q11 | AY6: Q12 | BA6: FY1 | BB6: FY2 | BC6: FY3
A7: Assets
A8: Cash & equivalents | B8: Linked from Cash Flow tab | C8: ='Cash Flow'!$C$28 -> 0 | D8: ='Cash Flow'!$D$28 -> 0 | E8: ='Cash Flow'!$E$28 -> 0 | F8: ='Cash Flow'!$F$28 -> 0 | G8: ='Cash Flow'!$G$28 -> 0 | H8: ='Cash Flow'!$H$28 -> 0 | I8: ='Cash Flow'!$I$28 -> 0 | J8: ='Cash Flow'!$J$28 -> 0 | K8: ='Cash Flow'!$K$28 -> 0 | L8: ='Cash Flow'!$L$28 -> 0 | M8: ='Cash Flow'!$M$28 -> 0 | N8: ='Cash Flow'!$N$28 -> 0 | O8: ='Cash Flow'!$O$28 -> 0 | P8: ='Cash Flow'!$P$28 -> 0 | Q8: ='Cash Flow'!$Q$28 -> 0 | R8: ='Cash Flow'!$R$28 -> 0 | S8: ='Cash Flow'!$S$28 -> 0 | T8: ='Cash Flow'!$T$28 -> 0 | U8: ='Cash Flow'!$U$28 -> 0 | V8: ='Cash Flow'!$V$28 -> 0 | W8: ='Cash Flow'!$W$28 -> 0 | X8: ='Cash Flow'!$X$28 -> 0 | Y8: ='Cash Flow'!$Y$28 -> 0 | Z8: ='Cash Flow'!$Z$28 -> 0 | AA8: ='Cash Flow'!$AA$28 -> 0 | AB8: ='Cash Flow'!$AB$28 -> 0 | AC8: ='Cash Flow'!$AC$28 -> 0 | AD8: ='Cash Flow'!$AD$28 -> 0 | AE8: ='Cash Flow'!$AE$28 -> 0 | AF8: ='Cash Flow'!$AF$28 -> 0 | AG8: ='Cash Flow'!$AG$28 -> 0 | AH8: ='Cash Flow'!$AH$28 -> 0 | AI8: ='Cash Flow'!$AI$28 -> 0 | AJ8: ='Cash Flow'!$AJ$28 -> 0 | AK8: ='Cash Flow'!$AK$28 -> 0 | AL8: ='Cash Flow'!$AL$28 -> 0 | AN8: =E8 -> 0 | AO8: =H8 -> 0 | AP8: =K8 -> 0 | AQ8: =N8 -> 0 | AR8: =Q8 -> 0 | AS8: =T8 -> 0 | AT8: =W8 -> 0 | AU8: =Z8 -> 0 | AV8: =AC8 -> 0 | AW8: =AF8 -> 0 | AX8: =AI8 -> 0 | AY8: =AL8 -> 0 | BA8: =N8 -> 0 | BB8: =Z8 -> 0 | BC8: =AL8 -> 0
A9: Accounts Receivable | C9: ='Working Capital'!$C$8 -> 0 | D9: ='Working Capital'!$D$8 -> 0 | E9: ='Working Capital'!$E$8 -> 0 | F9: ='Working Capital'!$F$8 -> 0 | G9: ='Working Capital'!$G$8 -> 0 | H9: ='Working Capital'!$H$8 -> 0 | I9: ='Working Capital'!$I$8 -> 0 | J9: ='Working Capital'!$J$8 -> 0 | K9: ='Working Capital'!$K$8 -> 0 | L9: ='Working Capital'!$L$8 -> 0 | M9: ='Working Capital'!$M$8 -> 0 | N9: ='Working Capital'!$N$8 -> 0 | O9: ='Working Capital'!$O$8 -> 0 | P9: ='Working Capital'!$P$8 -> 0 | Q9: ='Working Capital'!$Q$8 -> 0 | R9: ='Working Capital'!$R$8 -> 0 | S9: ='Working Capital'!$S$8 -> 0 | T9: ='Working Capital'!$T$8 -> 0 | U9: ='Working Capital'!$U$8 -> 0 | V9: ='Working Capital'!$V$8 -> 0 | W9: ='Working Capital'!$W$8 -> 0 | X9: ='Working Capital'!$X$8 -> 0 | Y9: ='Working Capital'!$Y$8 -> 0 | Z9: ='Working Capital'!$Z$8 -> 0 | AA9: ='Working Capital'!$AA$8 -> 0 | AB9: ='Working Capital'!$AB$8 -> 0 | AC9: ='Working Capital'!$AC$8 -> 0 | AD9: ='Working Capital'!$AD$8 -> 0 | AE9: ='Working Capital'!$AE$8 -> 0 | AF9: ='Working Capital'!$AF$8 -> 0 | AG9: ='Working Capital'!$AG$8 -> 0 | AH9: ='Working Capital'!$AH$8 -> 0 | AI9: ='Working Capital'!$AI$8 -> 0 | AJ9: ='Working Capital'!$AJ$8 -> 0 | AK9: ='Working Capital'!$AK$8 -> 0 | AL9: ='Working Capital'!$AL$8 -> 0 | AN9: =E9 -> 0 | AO9: =H9 -> 0 | AP9: =K9 -> 0 | AQ9: =N9 -> 0 | AR9: =Q9 -> 0 | AS9: =T9 -> 0 | AT9: =W9 -> 0 | AU9: =Z9 -> 0 | AV9: =AC9 -> 0 | AW9: =AF9 -> 0 | AX9: =AI9 -> 0 | AY9: =AL9 -> 0 | BA9: =N9 -> 0 | BB9: =Z9 -> 0 | BC9: =AL9 -> 0
A10: Other Current Assets (prepaid, etc.) | B10: Linked from Working Capital tab | C10: ='Working Capital'!C11 -> 0 | D10: ='Working Capital'!D11 -> 0 | E10: ='Working Capital'!E11 -> 0 | F10: ='Working Capital'!F11 -> 0 | G10: ='Working Capital'!G11 -> 0 | H10: ='Working Capital'!H11 -> 0 | I10: ='Working Capital'!I11 -> 0 | J10: ='Working Capital'!J11 -> 0 | ... AL10: ='Working Capital'!AL11 -> 0 | AN10: =E10 -> 0 | AO10: =H10 -> 0 | AP10: =K10 -> 0 | AQ10: =N10 -> 0 | AR10: =Q10 -> 0 | AS10: =T10 -> 0 | AT10: =W10 -> 0 | AU10: =Z10 -> 0 | AV10: =AC10 -> 0 | AW10: =AF10 -> 0 | AX10: =AI10 -> 0 | AY10: =AL10 -> 0 | BA10: =N10 -> 0 | BB10: =Z10 -> 0 | BC10: =AL10 -> 0
A11: Net PP&E | C11: ='Working Capital'!$C$20 -> 0 | D11: ='Working Capital'!$D$20 -> 0 | E11: ='Working Capital'!$E$20 -> 0 | F11: ='Working Capital'!$F$20 -> 0 | G11: ='Working Capital'!$G$20 -> 0 | H11: ='Working Capital'!$H$20 -> 0 | I11: ='Working Capital'!$I$20 -> 0 | J11: ='Working Capital'!$J$20 -> 0 | K11: ='Working Capital'!$K$20 -> 0 | L11: ='Working Capital'!$L$20 -> 0 | M11: ='Working Capital'!$M$20 -> 0 | N11: ='Working Capital'!$N$20 -> 0 | O11: ='Working Capital'!$O$20 -> 0 | P11: ='Working Capital'!$P$20 -> 0 | Q11: ='Working Capital'!$Q$20 -> 0 | R11: ='Working Capital'!$R$20 -> 0 | S11: ='Working Capital'!$S$20 -> 0 | T11: ='Working Capital'!$T$20 -> 0 | U11: ='Working Capital'!$U$20 -> 0 | V11: ='Working Capital'!$V$20 -> 0 | W11: ='Working Capital'!$W$20 -> 0 | X11: ='Working Capital'!$X$20 -> 0 | Y11: ='Working Capital'!$Y$20 -> 0 | Z11: ='Working Capital'!$Z$20 -> 0 | AA11: ='Working Capital'!$AA$20 -> 0 | AB11: ='Working Capital'!$AB$20 -> 0 | AC11: ='Working Capital'!$AC$20 -> 0 | AD11: ='Working Capital'!$AD$20 -> 0 | AE11: ='Working Capital'!$AE$20 -> 0 | AF11: ='Working Capital'!$AF$20 -> 0 | AG11: ='Working Capital'!$AG$20 -> 0 | AH11: ='Working Capital'!$AH$20 -> 0 | AI11: ='Working Capital'!$AI$20 -> 0 | AJ11: ='Working Capital'!$AJ$20 -> 0 | AK11: ='Working Capital'!$AK$20 -> 0 | AL11: ='Working Capital'!$AL$20 -> 0 | AN11: =E11 -> 0 | AO11: =H11 -> 0 | AP11: =K11 -> 0 | AQ11: =N11 -> 0 | AR11: =Q11 -> 0 | AS11: =T11 -> 0 | AT11: =W11 -> 0 | AU11: =Z11 -> 0 | AV11: =AC11 -> 0 | AW11: =AF11 -> 0 | AX11: =AI11 -> 0 | AY11: =AL11 -> 0 | BA11: =N11 -> 0 | BB11: =Z11 -> 0 | BC11: =AL11 -> 0
A12: Total Assets | C12: =C8+C9+C10+C11 -> 0 | D12: =D8+D9+D10+D11 -> 0 | E12: =E8+E9+E10+E11 -> 0 | F12: =F8+F9+F10+F11 -> 0 | G12: =G8+G9+G10+G11 -> 0 | H12: =H8+H9+H10+H11 -> 0 | I12: =I8+I9+I10+I11 -> 0 | J12: =J8+J9+J10+J11 -> 0 | ... AL12: =AL8+AL9+AL10+AL11 -> 0 | AN12: =E12 -> 0 | AO12: =H12 -> 0 | AP12: =K12 -> 0 | AQ12: =N12 -> 0 | AR12: =Q12 -> 0 | AS12: =T12 -> 0 | AT12: =W12 -> 0 | AU12: =Z12 -> 0 | AV12: =AC12 -> 0 | AW12: =AF12 -> 0 | AX12: =AI12 -> 0 | AY12: =AL12 -> 0 | BA12: =N12 -> 0 | BB12: =Z12 -> 0 | BC12: =AL12 -> 0
A14: Liabilities
A15: Accounts Payable | C15: ='Working Capital'!$C$9 -> 0 | D15: ='Working Capital'!$D$9 -> 0 | E15: ='Working Capital'!$E$9 -> 0 | F15: ='Working Capital'!$F$9 -> 0 | G15: ='Working Capital'!$G$9 -> 0 | H15: ='Working Capital'!$H$9 -> 0 | I15: ='Working Capital'!$I$9 -> 0 | J15: ='Working Capital'!$J$9 -> 0 | K15: ='Working Capital'!$K$9 -> 0 | L15: ='Working Capital'!$L$9 -> 0 | M15: ='Working Capital'!$M$9 -> 0 | N15: ='Working Capital'!$N$9 -> 0 | O15: ='Working Capital'!$O$9 -> 0 | P15: ='Working Capital'!$P$9 -> 0 | Q15: ='Working Capital'!$Q$9 -> 0 | R15: ='Working Capital'!$R$9 -> 0 | S15: ='Working Capital'!$S$9 -> 0 | T15: ='Working Capital'!$T$9 -> 0 | U15: ='Working Capital'!$U$9 -> 0 | V15: ='Working Capital'!$V$9 -> 0 | W15: ='Working Capital'!$W$9 -> 0 | X15: ='Working Capital'!$X$9 -> 0 | Y15: ='Working Capital'!$Y$9 -> 0 | Z15: ='Working Capital'!$Z$9 -> 0 | AA15: ='Working Capital'!$AA$9 -> 0 | AB15: ='Working Capital'!$AB$9 -> 0 | AC15: ='Working Capital'!$AC$9 -> 0 | AD15: ='Working Capital'!$AD$9 -> 0 | AE15: ='Working Capital'!$AE$9 -> 0 | AF15: ='Working Capital'!$AF$9 -> 0 | AG15: ='Working Capital'!$AG$9 -> 0 | AH15: ='Working Capital'!$AH$9 -> 0 | AI15: ='Working Capital'!$AI$9 -> 0 | AJ15: ='Working Capital'!$AJ$9 -> 0 | AK15: ='Working Capital'!$AK$9 -> 0 | AL15: ='Working Capital'!$AL$9 -> 0 | AN15: =E15 -> 0 | AO15: =H15 -> 0 | AP15: =K15 -> 0 | AQ15: =N15 -> 0 | AR15: =Q15 -> 0 | AS15: =T15 -> 0 | AT15: =W15 -> 0 | AU15: =Z15 -> 0 | AV15: =AC15 -> 0 | AW15: =AF15 -> 0 | AX15: =AI15 -> 0 | AY15: =AL15 -> 0 | BA15: =N15 -> 0 | BB15: =Z15 -> 0 | BC15: =AL15 -> 0
A16: Deferred Revenue | C16: ='Working Capital'!$C$10 -> 0 | D16: ='Working Capital'!$D$10 -> 0 | E16: ='Working Capital'!$E$10 -> 0 | F16: ='Working Capital'!$F$10 -> 0 | G16: ='Working Capital'!$G$10 -> 0 | H16: ='Working Capital'!$H$10 -> 0 | I16: ='Working Capital'!$I$10 -> 0 | J16: ='Working Capital'!$J$10 -> 0 | K16: ='Working Capital'!$K$10 -> 0 | L16: ='Working Capital'!$L$10 -> 0 | M16: ='Working Capital'!$M$10 -> 0 | N16: ='Working Capital'!$N$10 -> 0 | O16: ='Working Capital'!$O$10 -> 0 | P16: ='Working Capital'!$P$10 -> 0 | Q16: ='Working Capital'!$Q$10 -> 0 | R16: ='Working Capital'!$R$10 -> 0 | S16: ='Working Capital'!$S$10 -> 0 | T16: ='Working Capital'!$T$10 -> 0 | U16: ='Working Capital'!$U$10 -> 0 | V16: ='Working Capital'!$V$10 -> 0 | W16: ='Working Capital'!$W$10 -> 0 | X16: ='Working Capital'!$X$10 -> 0 | Y16: ='Working Capital'!$Y$10 -> 0 | Z16: ='Working Capital'!$Z$10 -> 0 | AA16: ='Working Capital'!$AA$10 -> 0 | AB16: ='Working Capital'!$AB$10 -> 0 | AC16: ='Working Capital'!$AC$10 -> 0 | AD16: ='Working Capital'!$AD$10 -> 0 | AE16: ='Working Capital'!$AE$10 -> 0 | AF16: ='Working Capital'!$AF$10 -> 0 | AG16: ='Working Capital'!$AG$10 -> 0 | AH16: ='Working Capital'!$AH$10 -> 0 | AI16: ='Working Capital'!$AI$10 -> 0 | AJ16: ='Working Capital'!$AJ$10 -> 0 | AK16: ='Working Capital'!$AK$10 -> 0 | AL16: ='Working Capital'!$AL$10 -> 0 | AN16: =E16 -> 0 | AO16: =H16 -> 0 | AP16: =K16 -> 0 | AQ16: =N16 -> 0 | AR16: =Q16 -> 0 | AS16: =T16 -> 0 | AT16: =W16 -> 0 | AU16: =Z16 -> 0 | AV16: =AC16 -> 0 | AW16: =AF16 -> 0 | AX16: =AI16 -> 0 | AY16: =AL16 -> 0 | BA16: =N16 -> 0 | BB16: =Z16 -> 0 | BC16: =AL16 -> 0
A17: Debt | C17: ='Working Capital'!$C$25 -> 0 | D17: ='Working Capital'!$D$25 -> 0 | E17: ='Working Capital'!$E$25 -> 0 | F17: ='Working Capital'!$F$25 -> 0 | G17: ='Working Capital'!$G$25 -> 0 | H17: ='Working Capital'!$H$25 -> 0 | I17: ='Working Capital'!$I$25 -> 0 | J17: ='Working Capital'!$J$25 -> 0 | K17: ='Working Capital'!$K$25 -> 0 | L17: ='Working Capital'!$L$25 -> 0 | M17: ='Working Capital'!$M$25 -> 0 | N17: ='Working Capital'!$N$25 -> 0 | O17: ='Working Capital'!$O$25 -> 0 | P17: ='Working Capital'!$P$25 -> 0 | Q17: ='Working Capital'!$Q$25 -> 0 | R17: ='Working Capital'!$R$25 -> 0 | S17: ='Working Capital'!$S$25 -> 0 | T17: ='Working Capital'!$T$25 -> 0 | U17: ='Working Capital'!$U$25 -> 0 | V17: ='Working Capital'!$V$25 -> 0 | W17: ='Working Capital'!$W$25 -> 0 | X17: ='Working Capital'!$X$25 -> 0 | Y17: ='Working Capital'!$Y$25 -> 0 | Z17: ='Working Capital'!$Z$25 -> 0 | AA17: ='Working Capital'!$AA$25 -> 0 | AB17: ='Working Capital'!$AB$25 -> 0 | AC17: ='Working Capital'!$AC$25 -> 0 | AD17: ='Working Capital'!$AD$25 -> 0 | AE17: ='Working Capital'!$AE$25 -> 0 | AF17: ='Working Capital'!$AF$25 -> 0 | AG17: ='Working Capital'!$AG$25 -> 0 | AH17: ='Working Capital'!$AH$25 -> 0 | AI17: ='Working Capital'!$AI$25 -> 0 | AJ17: ='Working Capital'!$AJ$25 -> 0 | AK17: ='Working Capital'!$AK$25 -> 0 | AL17: ='Working Capital'!$AL$25 -> 0 | AN17: =E17 -> 0 | AO17: =H17 -> 0 | AP17: =K17 -> 0 | AQ17: =N17 -> 0 | AR17: =Q17 -> 0 | AS17: =T17 -> 0 | AT17: =W17 -> 0 | AU17: =Z17 -> 0 | AV17: =AC17 -> 0 | AW17: =AF17 -> 0 | AX17: =AI17 -> 0 | AY17: =AL17 -> 0 | BA17: =N17 -> 0 | BB17: =Z17 -> 0 | BC17: =AL17 -> 0
A18: Total Liabilities | C18: =C15+C16+C17 -> 0 | D18: =D15+D16+D17 -> 0 | E18: =E15+E16+E17 -> 0 | F18: =F15+F16+F17 -> 0 | G18: =G15+G16+G17 -> 0 | H18: =H15+H16+H17 -> 0 | I18: =I15+I16+I17 -> 0 | J18: =J15+J16+J17 -> 0 | ... AL18: =AL15+AL16+AL17 -> 0 | AN18: =E18 -> 0 | AO18: =H18 -> 0 | AP18: =K18 -> 0 | AQ18: =N18 -> 0 | AR18: =Q18 -> 0 | AS18: =T18 -> 0 | AT18: =W18 -> 0 | AU18: =Z18 -> 0 | AV18: =AC18 -> 0 | AW18: =AF18 -> 0 | AX18: =AI18 -> 0 | AY18: =AL18 -> 0 | BA18: =N18 -> 0 | BB18: =Z18 -> 0 | BC18: =AL18 -> 0
A20: Equity
A21: Paid-in Capital | B21: Starting paid-in capital + cumulative equity raised | C21: ='Assumptions'!$F$9+'Working Capital'!C30 -> 0 | D21: ='Assumptions'!$F$9+'Working Capital'!D30 -> 0 | E21: ='Assumptions'!$F$9+'Working Capital'!E30 -> 0 | F21: ='Assumptions'!$F$9+'Working Capital'!F30 -> 0 | G21: ='Assumptions'!$F$9+'Working Capital'!G30 -> 0 | H21: ='Assumptions'!$F$9+'Working Capital'!H30 -> 0 | I21: ='Assumptions'!$F$9+'Working Capital'!I30 -> 0 | J21: ='Assumptions'!$F$9+'Working Capital'!J30 -> 0 | ... AL21: ='Assumptions'!$F$9+'Working Capital'!AL30 -> 0 | AN21: =E21 -> 0 | AO21: =H21 -> 0 | AP21: =K21 -> 0 | AQ21: =N21 -> 0 | AR21: =Q21 -> 0 | AS21: =T21 -> 0 | AT21: =W21 -> 0 | AU21: =Z21 -> 0 | AV21: =AC21 -> 0 | AW21: =AF21 -> 0 | AX21: =AI21 -> 0 | AY21: =AL21 -> 0 | BA21: =N21 -> 0 | BB21: =Z21 -> 0 | BC21: =AL21 -> 0
A22: Retained Earnings | B22: Starting RE (= starting cash − starting paid-in capital) + cumulative Net Income | C22: =('Assumptions'!$F$8-'Assumptions'!$F$9)+'P&L'!C23 -> 0 | D22: =C22+'P&L'!D23 -> 0 | E22: =D22+'P&L'!E23 -> 0 | F22: =E22+'P&L'!F23 -> 0 | G22: =F22+'P&L'!G23 -> 0 | H22: =G22+'P&L'!H23 -> 0 | I22: =H22+'P&L'!I23 -> 0 | J22: =I22+'P&L'!J23 -> 0 | K22: =J22+'P&L'!K23 -> 0 | ... AL22: =AK22+'P&L'!AL23 -> 0 | AN22: =E22 -> 0 | AO22: =H22 -> 0 | AP22: =K22 -> 0 | AQ22: =N22 -> 0 | AR22: =Q22 -> 0 | AS22: =T22 -> 0 | AT22: =W22 -> 0 | AU22: =Z22 -> 0 | AV22: =AC22 -> 0 | AW22: =AF22 -> 0 | AX22: =AI22 -> 0 | AY22: =AL22 -> 0 | BA22: =N22 -> 0 | BB22: =Z22 -> 0 | BC22: =AL22 -> 0
A23: Total Equity | C23: =C21+C22 -> 0 | D23: =D21+D22 -> 0 | E23: =E21+E22 -> 0 | F23: =F21+F22 -> 0 | G23: =G21+G22 -> 0 | H23: =H21+H22 -> 0 | I23: =I21+I22 -> 0 | J23: =J21+J22 -> 0 | ... AL23: =AL21+AL22 -> 0 | AN23: =E23 -> 0 | AO23: =H23 -> 0 | AP23: =K23 -> 0 | AQ23: =N23 -> 0 | AR23: =Q23 -> 0 | AS23: =T23 -> 0 | AT23: =W23 -> 0 | AU23: =Z23 -> 0 | AV23: =AC23 -> 0 | AW23: =AF23 -> 0 | AX23: =AI23 -> 0 | AY23: =AL23 -> 0 | BA23: =N23 -> 0 | BB23: =Z23 -> 0 | BC23: =AL23 -> 0
A24: Total Liabilities + Equity | C24: =C18+C23 -> 0 | D24: =D18+D23 -> 0 | E24: =E18+E23 -> 0 | F24: =F18+F23 -> 0 | G24: =G18+G23 -> 0 | H24: =H18+H23 -> 0 | I24: =I18+I23 -> 0 | J24: =J18+J23 -> 0 | ... AL24: =AL18+AL23 -> 0 | AN24: =E24 -> 0 | AO24: =H24 -> 0 | AP24: =K24 -> 0 | AQ24: =N24 -> 0 | AR24: =Q24 -> 0 | AS24: =T24 -> 0 | AT24: =W24 -> 0 | AU24: =Z24 -> 0 | AV24: =AC24 -> 0 | AW24: =AF24 -> 0 | AX24: =AI24 -> 0 | AY24: =AL24 -> 0 | BA24: =N24 -> 0 | BB24: =Z24 -> 0 | BC24: =AL24 -> 0
A26: Balance check (Assets − Liab&Equity) | B26: Must equal ~0 every month | C26: =C12-C24 -> 0 | D26: =D12-D24 -> 0 | E26: =E12-E24 -> 0 | F26: =F12-F24 -> 0 | G26: =G12-G24 -> 0 | H26: =H12-H24 -> 0 | I26: =I12-I24 -> 0 | J26: =J12-J24 -> 0 | ... AL26: =AL12-AL24 -> 0 | AN26: =E26 -> 0 | AO26: =H26 -> 0 | AP26: =K26 -> 0 | AQ26: =N26 -> 0 | AR26: =Q26 -> 0 | AS26: =T26 -> 0 | AT26: =W26 -> 0 | AU26: =Z26 -> 0 | AV26: =AC26 -> 0 | AW26: =AF26 -> 0 | AX26: =AI26 -> 0 | AY26: =AL26 -> 0 | BA26: =N26 -> 0 | BB26: =Z26 -> 0 | BC26: =AL26 -> 0

Sheet Cash & Runway
A1: AI-Enabled Services — 3-Year Financial Model — Cash & Runway
A2: Burn rate and runway — reconciled to the Cash Flow tab.
A5: Line item | B5: Units / source | C5: Monthly (36 months) | AN5: Quarterly | BA5: Annual
C6: 46023 | D6: 46054 | E6: 46082 | F6: 46113 | G6: 46143 | H6: 46174 | I6: 46204 | J6: 46235 | K6: 46266 | L6: 46296 | M6: 46327 | N6: 46357 | O6: 46388 | P6: 46419 | Q6: 46447 | R6: 46478 | S6: 46508 | T6: 46539 | U6: 46569 | V6: 46600 | W6: 46631 | X6: 46661 | Y6: 46692 | Z6: 46722 | AA6: 46753 | AB6: 46784 | AC6: 46813 | AD6: 46844 | AE6: 46874 | AF6: 46905 | AG6: 46935 | AH6: 46966 | AI6: 46997 | AJ6: 47027 | AK6: 47058 | AL6: 47088 | AN6: Q1 | AO6: Q2 | AP6: Q3 | AQ6: Q4 | AR6: Q5 | AS6: Q6 | AT6: Q7 | AU6: Q8 | AV6: Q9 | AW6: Q10 | AX6: Q11 | AY6: Q12 | BA6: FY1 | BB6: FY2 | BC6: FY3
A7: Cash Position
A8: Ending Cash Balance | C8: ='Cash Flow'!$C$28 -> 0 | D8: ='Cash Flow'!$D$28 -> 0 | E8: ='Cash Flow'!$E$28 -> 0 | F8: ='Cash Flow'!$F$28 -> 0 | G8: ='Cash Flow'!$G$28 -> 0 | H8: ='Cash Flow'!$H$28 -> 0 | I8: ='Cash Flow'!$I$28 -> 0 | J8: ='Cash Flow'!$J$28 -> 0 | K8: ='Cash Flow'!$K$28 -> 0 | L8: ='Cash Flow'!$L$28 -> 0 | M8: ='Cash Flow'!$M$28 -> 0 | N8: ='Cash Flow'!$N$28 -> 0 | O8: ='Cash Flow'!$O$28 -> 0 | P8: ='Cash Flow'!$P$28 -> 0 | Q8: ='Cash Flow'!$Q$28 -> 0 | R8: ='Cash Flow'!$R$28 -> 0 | S8: ='Cash Flow'!$S$28 -> 0 | T8: ='Cash Flow'!$T$28 -> 0 | U8: ='Cash Flow'!$U$28 -> 0 | V8: ='Cash Flow'!$V$28 -> 0 | W8: ='Cash Flow'!$W$28 -> 0 | X8: ='Cash Flow'!$X$28 -> 0 | Y8: ='Cash Flow'!$Y$28 -> 0 | Z8: ='Cash Flow'!$Z$28 -> 0 | AA8: ='Cash Flow'!$AA$28 -> 0 | AB8: ='Cash Flow'!$AB$28 -> 0 | AC8: ='Cash Flow'!$AC$28 -> 0 | AD8: ='Cash Flow'!$AD$28 -> 0 | AE8: ='Cash Flow'!$AE$28 -> 0 | AF8: ='Cash Flow'!$AF$28 -> 0 | AG8: ='Cash Flow'!$AG$28 -> 0 | AH8: ='Cash Flow'!$AH$28 -> 0 | AI8: ='Cash Flow'!$AI$28 -> 0 | AJ8: ='Cash Flow'!$AJ$28 -> 0 | AK8: ='Cash Flow'!$AK$28 -> 0 | AL8: ='Cash Flow'!$AL$28 -> 0 | AN8: =E8 -> 0 | AO8: =H8 -> 0 | AP8: =K8 -> 0 | AQ8: =N8 -> 0 | AR8: =Q8 -> 0 | AS8: =T8 -> 0 | AT8: =W8 -> 0 | AU8: =Z8 -> 0 | AV8: =AC8 -> 0 | AW8: =AF8 -> 0 | AX8: =AI8 -> 0 | AY8: =AL8 -> 0 | BA8: =N8 -> 0 | BB8: =Z8 -> 0 | BC8: =AL8 -> 0
A9: Monthly Net Burn (pre-financing) | B9: MAX(0, −(operating + investing cash flow)); excludes debt and equity proceeds | C9: =MAX(0,-('Cash Flow'!C14+'Cash Flow'!C18)) -> 0 | D9: =MAX(0,-('Cash Flow'!D14+'Cash Flow'!D18)) -> 0 | E9: =MAX(0,-('Cash Flow'!E14+'Cash Flow'!E18)) -> 0 | F9: =MAX(0,-('Cash Flow'!F14+'Cash Flow'!F18)) -> 0 | G9: =MAX(0,-('Cash Flow'!G14+'Cash Flow'!G18)) -> 0 | H9: =MAX(0,-('Cash Flow'!H14+'Cash Flow'!H18)) -> 0 | I9: =MAX(0,-('Cash Flow'!I14+'Cash Flow'!I18)) -> 0 | J9: =MAX(0,-('Cash Flow'!J14+'Cash Flow'!J18)) -> 0 | ... AL9: =MAX(0,-('Cash Flow'!AL14+'Cash Flow'!AL18)) -> 0 | AN9: =SUM(C9:E9) -> 0 | AO9: =SUM(F9:H9) -> 0 | AP9: =SUM(I9:K9) -> 0 | AQ9: =SUM(L9:N9) -> 0 | AR9: =SUM(O9:Q9) -> 0 | AS9: =SUM(R9:T9) -> 0 | AT9: =SUM(U9:W9) -> 0 | AU9: =SUM(X9:Z9) -> 0 | AV9: =SUM(AA9:AC9) -> 0 | AW9: =SUM(AD9:AF9) -> 0 | AX9: =SUM(AG9:AI9) -> 0 | AY9: =SUM(AJ9:AL9) -> 0 | BA9: =SUM(C9:N9) -> 0 | BB9: =SUM(O9:Z9) -> 0 | BC9: =SUM(AA9:AL9) -> 0
A10: Trailing 3-Month Avg Burn | C10: =AVERAGE(C9:C9) -> 0 | D10: =AVERAGE(C9:D9) -> 0 | E10: =AVERAGE(C9:E9) -> 0 | F10: =AVERAGE(D9:F9) -> 0 | G10: =AVERAGE(E9:G9) -> 0 | H10: =AVERAGE(F9:H9) -> 0 | I10: =AVERAGE(G9:I9) -> 0 | J10: =AVERAGE(H9:J9) -> 0 | K10: =AVERAGE(I9:K9) -> 0 | L10: =AVERAGE(J9:L9) -> 0 | ... AL10: =AVERAGE(AJ9:AL9) -> 0 | AN10: =AVERAGE(C10:E10) -> 0 | AO10: =AVERAGE(F10:H10) -> 0 | AP10: =AVERAGE(I10:K10) -> 0 | AQ10: =AVERAGE(L10:N10) -> 0 | AR10: =AVERAGE(O10:Q10) -> 0 | AS10: =AVERAGE(R10:T10) -> 0 | AT10: =AVERAGE(U10:W10) -> 0 | AU10: =AVERAGE(X10:Z10) -> 0 | AV10: =AVERAGE(AA10:AC10) -> 0 | AW10: =AVERAGE(AD10:AF10) -> 0 | AX10: =AVERAGE(AG10:AI10) -> 0 | AY10: =AVERAGE(AJ10:AL10) -> 0 | BA10: =AVERAGE(C10:N10) -> 0 | BB10: =AVERAGE(O10:Z10) -> 0 | BC10: =AVERAGE(AA10:AL10) -> 0
A11: Runway (months) | B11: Ending cash ÷ trailing 3-month pre-financing burn; 0 if cash is depleted; 999 if cash-flow positive | C11: =IF(C8<=0,0,IF(C10<=0,999,C8/C10)) -> 0 | D11: =IF(D8<=0,0,IF(D10<=0,999,D8/D10)) -> 0 | E11: =IF(E8<=0,0,IF(E10<=0,999,E8/E10)) -> 0 | F11: =IF(F8<=0,0,IF(F10<=0,999,F8/F10)) -> 0 | G11: =IF(G8<=0,0,IF(G10<=0,999,G8/G10)) -> 0 | H11: =IF(H8<=0,0,IF(H10<=0,999,H8/H10)) -> 0 | I11: =IF(I8<=0,0,IF(I10<=0,999,I8/I10)) -> 0 | J11: =IF(J8<=0,0,IF(J10<=0,999,J8/J10)) -> 0 | ... AL11: =IF(AL8<=0,0,IF(AL10<=0,999,AL8/AL10)) -> 0 | AN11: =E11 -> 0 | AO11: =H11 -> 0 | AP11: =K11 -> 0 | AQ11: =N11 -> 0 | AR11: =Q11 -> 0 | AS11: =T11 -> 0 | AT11: =W11 -> 0 | AU11: =Z11 -> 0 | AV11: =AC11 -> 0 | AW11: =AF11 -> 0 | AX11: =AI11 -> 0 | AY11: =AL11 -> 0 | BA11: =N11 -> 0 | BB11: =Z11 -> 0 | BC11: =AL11 -> 0
A13: Headline
A14: Runway as of final month (36) | C14: =IF(AL8<=0,0,IF(AL10<=0,"Cash-flow positive",AL11)) -> 0

Sheet Scenarios
A1: AI-Enabled Services — 3-Year Financial Model — Scenario Comparison
A2: Base/Upside/Downside columns are a fast analytical approximation for side-by-side comparison. The 'Full model' column reflects the detailed 36-month model at the scenario currently selected on the Assumptions tab.
A4: Currently selected scenario: | C4: ='Assumptions'!$C$4 -> 0
A6: KPI | B6: Definition | C6: Base | D6: Upside | E6: Downside | F6: Full model (selected)
A7: Month-1 New Bookings | B7: Starting sales capacity x pipeline generation x win rate x average project value. | C7: ='Assumptions'!$C$44*'Assumptions'!$C$14*'Assumptions'!$C$16*'Assumptions'!$C$17 -> 0 | D7: ='Assumptions'!$D$44*'Assumptions'!$D$14*'Assumptions'!$D$16*'Assumptions'!$D$17 -> 0 | E7: ='Assumptions'!$E$44*'Assumptions'!$E$14*'Assumptions'!$E$16*'Assumptions'!$E$17 -> 0 | F7: ='Revenue'!C14 -> 0
A8: Utilization % (illustrative, Month 36) | B8: Approximate month-36 recognized revenue divided by effective delivery capacity at realized rates. | C8: =IFERROR((MIN(((('Assumptions'!$C$44+35*'Assumptions'!$C$45/3))*('Assumptions'!$C$14*(1+'Assumptions'!$C$15)^35)*'Assumptions'!$C$16*('Assumptions'!$C$17*(1+'Assumptions'!$C$18)^35)),(('Assumptions'!$C$34+35*'Assumptions'!$C$35/3))*'Assumptions'!$C$22*(1+'Assumptions'!$C$27)*'Assumptions'!$C$23*('Assumptions'!$C$25*(1+'Assumptions'!$C$26)^35)*'Assumptions'!$C$24))/((('Assumptions'!$C$34+35*'Assumptions'!$C$35/3))*'Assumptions'!$C$22*(1+'Assumptions'!$C$27)*('Assumptions'!$C$25*(1+'Assumptions'!$C$26)^35)*'Assumptions'!$C$24),0) -> 0 | D8: =IFERROR((MIN(((('Assumptions'!$D$44+35*'Assumptions'!$D$45/3))*('Assumptions'!$D$14*(1+'Assumptions'!$D$15)^35)*'Assumptions'!$D$16*('Assumptions'!$D$17*(1+'Assumptions'!$D$18)^35)),(('Assumptions'!$D$34+35*'Assumptions'!$D$35/3))*'Assumptions'!$D$22*(1+'Assumptions'!$D$27)*'Assumptions'!$D$23*('Assumptions'!$D$25*(1+'Assumptions'!$D$26)^35)*'Assumptions'!$D$24))/((('Assumptions'!$D$34+35*'Assumptions'!$D$35/3))*'Assumptions'!$D$22*(1+'Assumptions'!$D$27)*('Assumptions'!$D$25*(1+'Assumptions'!$D$26)^35)*'Assumptions'!$D$24),0) -> 0 | E8: =IFERROR((MIN(((('Assumptions'!$E$44+35*'Assumptions'!$E$45/3))*('Assumptions'!$E$14*(1+'Assumptions'!$E$15)^35)*'Assumptions'!$E$16*('Assumptions'!$E$17*(1+'Assumptions'!$E$18)^35)),(('Assumptions'!$E$34+35*'Assumptions'!$E$35/3))*'Assumptions'!$E$22*(1+'Assumptions'!$E$27)*'Assumptions'!$E$23*('Assumptions'!$E$25*(1+'Assumptions'!$E$26)^35)*'Assumptions'!$E$24))/((('Assumptions'!$E$34+35*'Assumptions'!$E$35/3))*'Assumptions'!$E$22*(1+'Assumptions'!$E$27)*('Assumptions'!$E$25*(1+'Assumptions'!$E$26)^35)*'Assumptions'!$E$24),0) -> 0 | F8: ='Revenue'!AL40 -> 0
A9: Implied Revenue at Month 36 (approx.) | B9: Approximate month-36 recognized revenue, constrained by the lower of bookings and delivery capacity. | C9: =MIN(((('Assumptions'!$C$44+35*'Assumptions'!$C$45/3))*('Assumptions'!$C$14*(1+'Assumptions'!$C$15)^35)*'Assumptions'!$C$16*('Assumptions'!$C$17*(1+'Assumptions'!$C$18)^35)),(('Assumptions'!$C$34+35*'Assumptions'!$C$35/3))*'Assumptions'!$C$22*(1+'Assumptions'!$C$27)*'Assumptions'!$C$23*('Assumptions'!$C$25*(1+'Assumptions'!$C$26)^35)*'Assumptions'!$C$24) -> 0 | D9: =MIN(((('Assumptions'!$D$44+35*'Assumptions'!$D$45/3))*('Assumptions'!$D$14*(1+'Assumptions'!$D$15)^35)*'Assumptions'!$D$16*('Assumptions'!$D$17*(1+'Assumptions'!$D$18)^35)),(('Assumptions'!$D$34+35*'Assumptions'!$D$35/3))*'Assumptions'!$D$22*(1+'Assumptions'!$D$27)*'Assumptions'!$D$23*('Assumptions'!$D$25*(1+'Assumptions'!$D$26)^35)*'Assumptions'!$D$24) -> 0 | E9: =MIN(((('Assumptions'!$E$44+35*'Assumptions'!$E$45/3))*('Assumptions'!$E$14*(1+'Assumptions'!$E$15)^35)*'Assumptions'!$E$16*('Assumptions'!$E$17*(1+'Assumptions'!$E$18)^35)),(('Assumptions'!$E$34+35*'Assumptions'!$E$35/3))*'Assumptions'!$E$22*(1+'Assumptions'!$E$27)*'Assumptions'!$E$23*('Assumptions'!$E$25*(1+'Assumptions'!$E$26)^35)*'Assumptions'!$E$24) -> 0 | F9: ='Revenue'!AL36 -> 0
A10: Project Gross Margin % (illustrative, Month 36) | B10: 1 - (delivery people + subcontractors + AI tools) / approximate month-36 revenue. | C10: =1-IFERROR((((('Assumptions'!$C$34+35*'Assumptions'!$C$35/3))*'Assumptions'!$C$36+(('Assumptions'!$C$39+35*'Assumptions'!$C$40/3))*'Assumptions'!$C$41)+((('Assumptions'!$C$34+35*'Assumptions'!$C$35/3))*'Assumptions'!$C$31)+(MIN(((('Assumptions'!$C$44+35*'Assumptions'!$C$45/3))*('Assumptions'!$C$14*(1+'Assumptions'!$C$15)^35)*'Assumptions'!$C$16*('Assumptions'!$C$17*(1+'Assumptions'!$C$18)^35)),(('Assumptions'!$C$34+35*'Assumptions'!$C$35/3))*'Assumptions'!$C$22*(1+'Assumptions'!$C$27)*'Assumptions'!$C$23*('Assumptions'!$C$25*(1+'Assumptions'!$C$26)^35)*'Assumptions'!$C$24))*'Assumptions'!$C$30)/(MIN(((('Assumptions'!$C$44+35*'Assumptions'!$C$45/3))*('Assumptions'!$C$14*(1+'Assumptions'!$C$15)^35)*'Assumptions'!$C$16*('Assumptions'!$C$17*(1+'Assumptions'!$C$18)^35)),(('Assumptions'!$C$34+35*'Assumptions'!$C$35/3))*'Assumptions'!$C$22*(1+'Assumptions'!$C$27)*'Assumptions'!$C$23*('Assumptions'!$C$25*(1+'Assumptions'!$C$26)^35)*'Assumptions'!$C$24)),0) -> 0 | D10: =1-IFERROR((((('Assumptions'!$D$34+35*'Assumptions'!$D$35/3))*'Assumptions'!$D$36+(('Assumptions'!$D$39+35*'Assumptions'!$D$40/3))*'Assumptions'!$D$41)+((('Assumptions'!$D$34+35*'Assumptions'!$D$35/3))*'Assumptions'!$D$31)+(MIN(((('Assumptions'!$D$44+35*'Assumptions'!$D$45/3))*('Assumptions'!$D$14*(1+'Assumptions'!$D$15)^35)*'Assumptions'!$D$16*('Assumptions'!$D$17*(1+'Assumptions'!$D$18)^35)),(('Assumptions'!$D$34+35*'Assumptions'!$D$35/3))*'Assumptions'!$D$22*(1+'Assumptions'!$D$27)*'Assumptions'!$D$23*('Assumptions'!$D$25*(1+'Assumptions'!$D$26)^35)*'Assumptions'!$D$24))*'Assumptions'!$D$30)/(MIN(((('Assumptions'!$D$44+35*'Assumptions'!$D$45/3))*('Assumptions'!$D$14*(1+'Assumptions'!$D$15)^35)*'Assumptions'!$D$16*('Assumptions'!$D$17*(1+'Assumptions'!$D$18)^35)),(('Assumptions'!$D$34+35*'Assumptions'!$D$35/3))*'Assumptions'!$D$22*(1+'Assumptions'!$D$27)*'Assumptions'!$D$23*('Assumptions'!$D$25*(1+'Assumptions'!$D$26)^35)*'Assumptions'!$D$24)),0) -> 0 | E10: =1-IFERROR((((('Assumptions'!$E$34+35*'Assumptions'!$E$35/3))*'Assumptions'!$E$36+(('Assumptions'!$E$39+35*'Assumptions'!$E$40/3))*'Assumptions'!$E$41)+((('Assumptions'!$E$34+35*'Assumptions'!$E$35/3))*'Assumptions'!$E$31)+(MIN(((('Assumptions'!$E$44+35*'Assumptions'!$E$45/3))*('Assumptions'!$E$14*(1+'Assumptions'!$E$15)^35)*'Assumptions'!$E$16*('Assumptions'!$E$17*(1+'Assumptions'!$E$18)^35)),(('Assumptions'!$E$34+35*'Assumptions'!$E$35/3))*'Assumptions'!$E$22*(1+'Assumptions'!$E$27)*'Assumptions'!$E$23*('Assumptions'!$E$25*(1+'Assumptions'!$E$26)^35)*'Assumptions'!$E$24))*'Assumptions'!$E$30)/(MIN(((('Assumptions'!$E$44+35*'Assumptions'!$E$45/3))*('Assumptions'!$E$14*(1+'Assumptions'!$E$15)^35)*'Assumptions'!$E$16*('Assumptions'!$E$17*(1+'Assumptions'!$E$18)^35)),(('Assumptions'!$E$34+35*'Assumptions'!$E$35/3))*'Assumptions'!$E$22*(1+'Assumptions'!$E$27)*'Assumptions'!$E$23*('Assumptions'!$E$25*(1+'Assumptions'!$E$26)^35)*'Assumptions'!$E$24)),0) -> 0 | F10: ='COGS & GM'!AL16 -> 0
A11: Month-1 Net Burn (illustrative) | B11: Month-1 people cost + variable delivery costs + operating programs - recognized revenue. | C11: =MAX(0,('Assumptions'!$C$34*'Assumptions'!$C$36+'Assumptions'!$C$39*'Assumptions'!$C$41+'Assumptions'!$C$44*'Assumptions'!$C$46+'Assumptions'!$C$49*'Assumptions'!$C$51)+((MIN(('Assumptions'!$C$13+('Assumptions'!$C$44*'Assumptions'!$C$14*'Assumptions'!$C$16*'Assumptions'!$C$17))/MAX(1,'Assumptions'!$C$19),'Assumptions'!$C$34*'Assumptions'!$C$22*(1+'Assumptions'!$C$27)*'Assumptions'!$C$23*'Assumptions'!$C$25*'Assumptions'!$C$24))*'Assumptions'!$C$30+'Assumptions'!$C$34*'Assumptions'!$C$31)+(('Assumptions'!$C$44*'Assumptions'!$C$14*'Assumptions'!$C$16*'Assumptions'!$C$17)*'Assumptions'!$C$54+'Assumptions'!$C$55+'Assumptions'!$C$57+'Assumptions'!$C$58)-(MIN(('Assumptions'!$C$13+('Assumptions'!$C$44*'Assumptions'!$C$14*'Assumptions'!$C$16*'Assumptions'!$C$17))/MAX(1,'Assumptions'!$C$19),'Assumptions'!$C$34*'Assumptions'!$C$22*(1+'Assumptions'!$C$27)*'Assumptions'!$C$23*'Assumptions'!$C$25*'Assumptions'!$C$24))) -> 0 | D11: =MAX(0,('Assumptions'!$D$34*'Assumptions'!$D$36+'Assumptions'!$D$39*'Assumptions'!$D$41+'Assumptions'!$D$44*'Assumptions'!$D$46+'Assumptions'!$D$49*'Assumptions'!$D$51)+((MIN(('Assumptions'!$D$13+('Assumptions'!$D$44*'Assumptions'!$D$14*'Assumptions'!$D$16*'Assumptions'!$D$17))/MAX(1,'Assumptions'!$D$19),'Assumptions'!$D$34*'Assumptions'!$D$22*(1+'Assumptions'!$D$27)*'Assumptions'!$D$23*'Assumptions'!$D$25*'Assumptions'!$D$24))*'Assumptions'!$D$30+'Assumptions'!$D$34*'Assumptions'!$D$31)+(('Assumptions'!$D$44*'Assumptions'!$D$14*'Assumptions'!$D$16*'Assumptions'!$D$17)*'Assumptions'!$D$54+'Assumptions'!$D$55+'Assumptions'!$D$57+'Assumptions'!$D$58)-(MIN(('Assumptions'!$D$13+('Assumptions'!$D$44*'Assumptions'!$D$14*'Assumptions'!$D$16*'Assumptions'!$D$17))/MAX(1,'Assumptions'!$D$19),'Assumptions'!$D$34*'Assumptions'!$D$22*(1+'Assumptions'!$D$27)*'Assumptions'!$D$23*'Assumptions'!$D$25*'Assumptions'!$D$24))) -> 0 | E11: =MAX(0,('Assumptions'!$E$34*'Assumptions'!$E$36+'Assumptions'!$E$39*'Assumptions'!$E$41+'Assumptions'!$E$44*'Assumptions'!$E$46+'Assumptions'!$E$49*'Assumptions'!$E$51)+((MIN(('Assumptions'!$E$13+('Assumptions'!$E$44*'Assumptions'!$E$14*'Assumptions'!$E$16*'Assumptions'!$E$17))/MAX(1,'Assumptions'!$E$19),'Assumptions'!$E$34*'Assumptions'!$E$22*(1+'Assumptions'!$E$27)*'Assumptions'!$E$23*'Assumptions'!$E$25*'Assumptions'!$E$24))*'Assumptions'!$E$30+'Assumptions'!$E$34*'Assumptions'!$E$31)+(('Assumptions'!$E$44*'Assumptions'!$E$14*'Assumptions'!$E$16*'Assumptions'!$E$17)*'Assumptions'!$E$54+'Assumptions'!$E$55+'Assumptions'!$E$57+'Assumptions'!$E$58)-(MIN(('Assumptions'!$E$13+('Assumptions'!$E$44*'Assumptions'!$E$14*'Assumptions'!$E$16*'Assumptions'!$E$17))/MAX(1,'Assumptions'!$E$19),'Assumptions'!$E$34*'Assumptions'!$E$22*(1+'Assumptions'!$E$27)*'Assumptions'!$E$23*'Assumptions'!$E$25*'Assumptions'!$E$24))) -> 0 | F11: ='Cash & Runway'!C9 -> 0
A12: Runway (illustrative, months) | B12: Starting cash divided by illustrative month-1 burn; 999 means cash-flow positive / effectively infinite. | C12: =IF((MAX(0,('Assumptions'!$C$34*'Assumptions'!$C$36+'Assumptions'!$C$39*'Assumptions'!$C$41+'Assumptions'!$C$44*'Assumptions'!$C$46+'Assumptions'!$C$49*'Assumptions'!$C$51)+((MIN(('Assumptions'!$C$13+('Assumptions'!$C$44*'Assumptions'!$C$14*'Assumptions'!$C$16*'Assumptions'!$C$17))/MAX(1,'Assumptions'!$C$19),'Assumptions'!$C$34*'Assumptions'!$C$22*(1+'Assumptions'!$C$27)*'Assumptions'!$C$23*'Assumptions'!$C$25*'Assumptions'!$C$24))*'Assumptions'!$C$30+'Assumptions'!$C$34*'Assumptions'!$C$31)+(('Assumptions'!$C$44*'Assumptions'!$C$14*'Assumptions'!$C$16*'Assumptions'!$C$17)*'Assumptions'!$C$54+'Assumptions'!$C$55+'Assumptions'!$C$57+'Assumptions'!$C$58)-(MIN(('Assumptions'!$C$13+('Assumptions'!$C$44*'Assumptions'!$C$14*'Assumptions'!$C$16*'Assumptions'!$C$17))/MAX(1,'Assumptions'!$C$19),'Assumptions'!$C$34*'Assumptions'!$C$22*(1+'Assumptions'!$C$27)*'Assumptions'!$C$23*'Assumptions'!$C$25*'Assumptions'!$C$24))))<=0,999,'Assumptions'!$C$8/(MAX(0,('Assumptions'!$C$34*'Assumptions'!$C$36+'Assumptions'!$C$39*'Assumptions'!$C$41+'Assumptions'!$C$44*'Assumptions'!$C$46+'Assumptions'!$C$49*'Assumptions'!$C$51)+((MIN(('Assumptions'!$C$13+('Assumptions'!$C$44*'Assumptions'!$C$14*'Assumptions'!$C$16*'Assumptions'!$C$17))/MAX(1,'Assumptions'!$C$19),'Assumptions'!$C$34*'Assumptions'!$C$22*(1+'Assumptions'!$C$27)*'Assumptions'!$C$23*'Assumptions'!$C$25*'Assumptions'!$C$24))*'Assumptions'!$C$30+'Assumptions'!$C$34*'Assumptions'!$C$31)+(('Assumptions'!$C$44*'Assumptions'!$C$14*'Assumptions'!$C$16*'Assumptions'!$C$17)*'Assumptions'!$C$54+'Assumptions'!$C$55+'Assumptions'!$C$57+'Assumptions'!$C$58)-(MIN(('Assumptions'!$C$13+('Assumptions'!$C$44*'Assumptions'!$C$14*'Assumptions'!$C$16*'Assumptions'!$C$17))/MAX(1,'Assumptions'!$C$19),'Assumptions'!$C$34*'Assumptions'!$C$22*(1+'Assumptions'!$C$27)*'Assumptions'!$C$23*'Assumptions'!$C$25*'Assumptions'!$C$24))))) -> 0 | D12: =IF((MAX(0,('Assumptions'!$D$34*'Assumptions'!$D$36+'Assumptions'!$D$39*'Assumptions'!$D$41+'Assumptions'!$D$44*'Assumptions'!$D$46+'Assumptions'!$D$49*'Assumptions'!$D$51)+((MIN(('Assumptions'!$D$13+('Assumptions'!$D$44*'Assumptions'!$D$14*'Assumptions'!$D$16*'Assumptions'!$D$17))/MAX(1,'Assumptions'!$D$19),'Assumptions'!$D$34*'Assumptions'!$D$22*(1+'Assumptions'!$D$27)*'Assumptions'!$D$23*'Assumptions'!$D$25*'Assumptions'!$D$24))*'Assumptions'!$D$30+'Assumptions'!$D$34*'Assumptions'!$D$31)+(('Assumptions'!$D$44*'Assumptions'!$D$14*'Assumptions'!$D$16*'Assumptions'!$D$17)*'Assumptions'!$D$54+'Assumptions'!$D$55+'Assumptions'!$D$57+'Assumptions'!$D$58)-(MIN(('Assumptions'!$D$13+('Assumptions'!$D$44*'Assumptions'!$D$14*'Assumptions'!$D$16*'Assumptions'!$D$17))/MAX(1,'Assumptions'!$D$19),'Assumptions'!$D$34*'Assumptions'!$D$22*(1+'Assumptions'!$D$27)*'Assumptions'!$D$23*'Assumptions'!$D$25*'Assumptions'!$D$24))))<=0,999,'Assumptions'!$D$8/(MAX(0,('Assumptions'!$D$34*'Assumptions'!$D$36+'Assumptions'!$D$39*'Assumptions'!$D$41+'Assumptions'!$D$44*'Assumptions'!$D$46+'Assumptions'!$D$49*'Assumptions'!$D$51)+((MIN(('Assumptions'!$D$13+('Assumptions'!$D$44*'Assumptions'!$D$14*'Assumptions'!$D$16*'Assumptions'!$D$17))/MAX(1,'Assumptions'!$D$19),'Assumptions'!$D$34*'Assumptions'!$D$22*(1+'Assumptions'!$D$27)*'Assumptions'!$D$23*'Assumptions'!$D$25*'Assumptions'!$D$24))*'Assumptions'!$D$30+'Assumptions'!$D$34*'Assumptions'!$D$31)+(('Assumptions'!$D$44*'Assumptions'!$D$14*'Assumptions'!$D$16*'Assumptions'!$D$17)*'Assumptions'!$D$54+'Assumptions'!$D$55+'Assumptions'!$D$57+'Assumptions'!$D$58)-(MIN(('Assumptions'!$D$13+('Assumptions'!$D$44*'Assumptions'!$D$14*'Assumptions'!$D$16*'Assumptions'!$D$17))/MAX(1,'Assumptions'!$D$19),'Assumptions'!$D$34*'Assumptions'!$D$22*(1+'Assumptions'!$D$27)*'Assumptions'!$D$23*'Assumptions'!$D$25*'Assumptions'!$D$24))))) -> 0 | E12: =IF((MAX(0,('Assumptions'!$E$34*'Assumptions'!$E$36+'Assumptions'!$E$39*'Assumptions'!$E$41+'Assumptions'!$E$44*'Assumptions'!$E$46+'Assumptions'!$E$49*'Assumptions'!$E$51)+((MIN(('Assumptions'!$E$13+('Assumptions'!$E$44*'Assumptions'!$E$14*'Assumptions'!$E$16*'Assumptions'!$E$17))/MAX(1,'Assumptions'!$E$19),'Assumptions'!$E$34*'Assumptions'!$E$22*(1+'Assumptions'!$E$27)*'Assumptions'!$E$23*'Assumptions'!$E$25*'Assumptions'!$E$24))*'Assumptions'!$E$30+'Assumptions'!$E$34*'Assumptions'!$E$31)+(('Assumptions'!$E$44*'Assumptions'!$E$14*'Assumptions'!$E$16*'Assumptions'!$E$17)*'Assumptions'!$E$54+'Assumptions'!$E$55+'Assumptions'!$E$57+'Assumptions'!$E$58)-(MIN(('Assumptions'!$E$13+('Assumptions'!$E$44*'Assumptions'!$E$14*'Assumptions'!$E$16*'Assumptions'!$E$17))/MAX(1,'Assumptions'!$E$19),'Assumptions'!$E$34*'Assumptions'!$E$22*(1+'Assumptions'!$E$27)*'Assumptions'!$E$23*'Assumptions'!$E$25*'Assumptions'!$E$24))))<=0,999,'Assumptions'!$E$8/(MAX(0,('Assumptions'!$E$34*'Assumptions'!$E$36+'Assumptions'!$E$39*'Assumptions'!$E$41+'Assumptions'!$E$44*'Assumptions'!$E$46+'Assumptions'!$E$49*'Assumptions'!$E$51)+((MIN(('Assumptions'!$E$13+('Assumptions'!$E$44*'Assumptions'!$E$14*'Assumptions'!$E$16*'Assumptions'!$E$17))/MAX(1,'Assumptions'!$E$19),'Assumptions'!$E$34*'Assumptions'!$E$22*(1+'Assumptions'!$E$27)*'Assumptions'!$E$23*'Assumptions'!$E$25*'Assumptions'!$E$24))*'Assumptions'!$E$30+'Assumptions'!$E$34*'Assumptions'!$E$31)+(('Assumptions'!$E$44*'Assumptions'!$E$14*'Assumptions'!$E$16*'Assumptions'!$E$17)*'Assumptions'!$E$54+'Assumptions'!$E$55+'Assumptions'!$E$57+'Assumptions'!$E$58)-(MIN(('Assumptions'!$E$13+('Assumptions'!$E$44*'Assumptions'!$E$14*'Assumptions'!$E$16*'Assumptions'!$E$17))/MAX(1,'Assumptions'!$E$19),'Assumptions'!$E$34*'Assumptions'!$E$22*(1+'Assumptions'!$E$27)*'Assumptions'!$E$23*'Assumptions'!$E$25*'Assumptions'!$E$24))))) -> 0 | F12: ='Cash & Runway'!AL11 -> 0
A14: Scenario Validity
A15: Selector value is valid (Base/Upside/Downside)? | C15: =IF(ISNUMBER(MATCH('Assumptions'!$C$4,{"Base","Upside","Downside"},0)),"OK","INVALID") -> 0

Sheet Visuals
A1: AI-Enabled Services — 3-Year Financial Model — Visuals
A2: Bookings, backlog, delivery efficiency, gross margin, cash, and runway for the AI-Enabled Services model.
A4: Revenue (Month 36) | D4: Ending Backlog (Month 36) | G4: Project Gross Margin % | J4: Utilization % | M4: Runway (months) | P4: AI productivity uplift
A5: ='Revenue'!AL36 -> 0 | D5: ='Revenue'!AL35 -> 0 | G5: ='COGS & GM'!AL16 -> 0 | J5: ='Revenue'!AL40 -> 0 | M5: ='Cash & Runway'!AL11 -> 0 | P5: ='Revenue'!AL45 -> 0

Sheet Checks
A1: AI-Enabled Services — 3-Year Financial Model — Checks
A2: Every control below should read PASS. If anything reads FAIL, trace it back through the linked tabs before trusting the outputs.
A4: Check | B4: Description | C4: Metric | D4: Status
A5: Balance Sheet balances | B5: MAX absolute (Assets − Liabilities&Equity) across all 36 months | C5: {=MAX(ABS('Balance Sheet'!C26:AL26))} -> 0 | D5: {=IF(MAX(ABS('Balance Sheet'!C26:AL26))<1.0,"PASS","FAIL")} -> 0
A6: Cash Flow reconciles to Balance Sheet | B6: MAX absolute difference between BS cash and CF ending cash across all 36 months | C6: {=MAX(ABS('Balance Sheet'!C8:AL8-'Cash Flow'!C28:AL28))} -> 0 | D6: {=IF(MAX(ABS('Balance Sheet'!C8:AL8-'Cash Flow'!C28:AL28))<1.0,"PASS","FAIL")} -> 0
A7: Retained Earnings roll-forward | B7: MAX absolute (RE(m) − RE(m−1) − NetIncome(m)) for months 2-36 | C7: {=MAX(ABS('Balance Sheet'!D22:AL22-'Balance Sheet'!C22:AK22-'P&L'!D23:AL23))} -> 0 | D7: {=IF(MAX(ABS('Balance Sheet'!D22:AL22-'Balance Sheet'!C22:AK22-'P&L'!D23:AL23))<1.0,"PASS","FAIL")} -> 0
A8: P&L subtotal integrity | B8: MAX absolute error across Gross Profit / EBITDA / EBIT / EBT / Net Income subtotals | C8: {=MAX(MAX(ABS(('P&L'!C7:AL7-'P&L'!C8:AL8)-'P&L'!C9:AL9)),MAX(ABS(('P&L'!C9:AL9-'P&L'!C15:AL15)-'P&L'!C17:AL17)),MAX(ABS(('P&L'!C17:AL17-'P&L'!C18:AL18)-'P&L'!C19:AL19)),MAX(ABS(('P&L'!C19:AL19-'P&L'!C20:AL20)-'P&L'!C21:AL21)),MAX(ABS(('P&L'!C21:AL21-'P&L'!C22:AL22)-'P&L'!C23:AL23)))} -> 0 | D8: {=IF(MAX(MAX(ABS(('P&L'!C7:AL7-'P&L'!C8:AL8)-'P&L'!C9:AL9)),MAX(ABS(('P&L'!C9:AL9-'P&L'!C15:AL15)-'P&L'!C17:AL17)),MAX(ABS(('P&L'!C17:AL17-'P&L'!C18:AL18)-'P&L'!C19:AL19)),MAX(ABS(('P&L'!C19:AL19-'P&L'!C20:AL20)-'P&L'!C21:AL21)),MAX(ABS(('P&L'!C21:AL21-'P&L'!C22:AL22)-'P&L'!C23:AL23)))<1.0,"PASS","FAIL")} -> 0
A9: Scenario selector validity | B9: Assumptions scenario selector must equal Base, Upside, or Downside | C9: {=IF('Scenarios'!C15="OK",1,0)} -> 0 | D9: {=IF('Scenarios'!C15="OK","PASS","FAIL")} -> 0
A10: No formula errors | B10: Count of #REF!/#DIV0!/#VALUE! etc. across all key schedules (Headcount through Cash & Runway) | C10: {=SUMPRODUCT(--ISERROR('Headcount'!C5:BC260))+SUMPRODUCT(--ISERROR('Revenue'!C5:BC260))+SUMPRODUCT(--ISERROR('COGS & GM'!C5:BC260))+SUMPRODUCT(--ISERROR('Opex'!C5:BC260))+SUMPRODUCT(--ISERROR('Working Capital'!C5:BC260))+SUMPRODUCT(--ISERROR('P&L'!C5:BC260))+SUMPRODUCT(--ISERROR('Balance Sheet'!C5:BC260))+SUMPRODUCT(--ISERROR('Cash Flow'!C5:BC260))+SUMPRODUCT(--ISERROR('Cash & Runway'!C5:BC260))} -> 0 | D10: {=IF((SUMPRODUCT(--ISERROR('Headcount'!C5:BC260))+SUMPRODUCT(--ISERROR('Revenue'!C5:BC260))+SUMPRODUCT(--ISERROR('COGS & GM'!C5:BC260))+SUMPRODUCT(--ISERROR('Opex'!C5:BC260))+SUMPRODUCT(--ISERROR('Working Capital'!C5:BC260))+SUMPRODUCT(--ISERROR('P&L'!C5:BC260))+SUMPRODUCT(--ISERROR('Balance Sheet'!C5:BC260))+SUMPRODUCT(--ISERROR('Cash Flow'!C5:BC260))+SUMPRODUCT(--ISERROR('Cash & Runway'!C5:BC260)))=0,"PASS","FAIL")} -> 0
A12: ALL CHECKS | B12: Overall model integrity status | D12: =IF(AND(D5="PASS",D6="PASS",D7="PASS",D8="PASS",D9="PASS",D10="PASS"),"ALL PASS","REVIEW NEEDED") -> 0
