Workbook

Sheet Read Me
A1: B2B SaaS + Usage — 3-Year Financial Model
A2: 36-month integrated financial model — Read Me
A4: Overview
A5: A 36-month, formula-driven financial model for an early-stage B2B SaaS company with a usage/overage component. Start on the Assumptions tab: set your Base/Upside/Downside inputs and pick a scenario. Every other tab recalculates automatically.
A7: How this workbook is organized
A8: Assumptions -> Headcount -> Revenue -> COGS & GM -> Opex -> Working Capital -> P&L -> Balance Sheet -> Cash Flow -> Cash & Runway -> Scenarios -> Visuals -> Checks. Data flows strictly left-to-right through that order: change an assumption, and every downstream tab recalculates automatically (workbook calculation mode is Automatic).
A10: Formatting legend
A11: Blue text on light-blue fill = an input you can edit (Assumptions tab, and scenario selector).
A12: Black text on white = a live formula. Do not hard-code over these cells.
A13: Cells on a light-gray band = a value linked in from another tab.
A15: Color palette
A16: Purple (#7B68EE)
... A35: 36 monthly periods, plus quarterly (12) and annual (3) roll-up columns on each schedule tab. Workbook calculation is set to Automatic — Excel recalculates on every edit. Deterministic, seeded default assumptions are provided so the model is internally consistent out of the box; replace them with your own numbers on the Assumptions tab.

Sheet Assumptions
A1: B2B SaaS + Usage — 3-Year Financial Model — Assumptions
A2: Plain-language inputs. Edit the Base / Upside / Downside columns only — everything else in this workbook is a formula.
A4: Scenario selector: | C4: Base | D4: << Pick Base / Upside / Downside. This one cell drives every formula in the model.
A6: Assumption | B6: Unit | C6: Base | D6: Upside | E6: Downside | F6: Active (used in model) | G6: Notes / definition
A7: Company & Financial
A8: Starting cash balance | B8: $ | C8: 1500000 | D8: 1500000 | E8: 1500000 | F8: =CHOOSE(MATCH('Assumptions'!$C$4,{"Base","Upside","Downside"},0),C8,D8,E8) -> 0 | G8: Cash in the bank on day 1 of the model.
A9: Starting paid-in capital | B9: $ | C9: 1800000 | D9: 1800000 | E9: 1800000 | F9: =CHOOSE(MATCH('Assumptions'!$C$4,{"Base","Upside","Downside"},0),C9,D9,E9) -> 0 | G9: Cumulative equity raised before month 1 (seed round).
A10: Income tax rate | B10: % | C10: 0 | D10: 0 | E10: 0 | F10: =CHOOSE(MATCH('Assumptions'!$C$4,{"Base","Upside","Downside"},0),C10,D10,E10) -> 0 | G10: Applied to positive Earnings Before Tax only; no NOL carryforward modeled.
A12: Customers & Growth
A13: Starting paying customers | B13: # | C13: 40 | D13: 40 | E13: 40 | F13: =CHOOSE(MATCH('Assumptions'!$C$4,{"Base","Upside","Downside"},0),C13,D13,E13) -> 0 | G13: Logos under contract at the start of month 1.
A14: New logos added, month 1 | B14: # | C14: 6 | D14: 8 | E14: 4 | F14: =CHOOSE(MATCH('Assumptions'!$C$4,{"Base","Upside","Downside"},0),C14,D14,E14) -> 0 | G14: New paying customers signed in month 1; grows monthly below.
A15: New-logo growth, month over month | B15: % | C15: 0.0322 | D15: 0.0464 | E15: 0.0039 | F15: =CHOOSE(MATCH('Assumptions'!$C$4,{"Base","Upside","Downside"},0),C15,D15,E15) -> 0 | G15: Compounding growth in the number of new logos signed each month.
A16: Gross logo/dollar churn rate | B16: % | C16: 0.015 | D16: 0.01 | E16: 0.025 | F16: =CHOOSE(MATCH('Assumptions'!$C$4,{"Base","Upside","Downside"},0),C16,D16,E16) -> 0 | G16: Share of beginning customers (and beginning MRR) lost each month.
A17: Expansion (upsell) rate | B17: % | C17: 0.01 | D17: 0.016 | E17: 0.006 | F17: =CHOOSE(MATCH('Assumptions'!$C$4,{"Base","Upside","Downside"},0),C17,D17,E17) -> 0 | G17: Upsell/seat-expansion MRR as % of beginning MRR each month.
A18: Contraction (downgrade) rate | B18: % | C18: 0.004 | D18: 0.002 | E18: 0.008 | F18: =CHOOSE(MATCH('Assumptions'!$C$4,{"Base","Upside","Downside"},0),C18,D18,E18) -> 0 | G18: Downgrade MRR as % of beginning MRR each month.
A20: Pricing & Usage
A21: Starting ARPA (avg MRR per account) | B21: $/mo | C21: 1200 | D21: 1300 | E21: 1100 | F21: =CHOOSE(MATCH('Assumptions'!$C$4,{"Base","Upside","Downside"},0),C21,D21,E21) -> 0 | G21: Average recurring revenue per account at month 1.
A22: ARPA growth, month over month | B22: % | C22: 0.005 | D22: 0.009 | E22: 0.001 | F22: =CHOOSE(MATCH('Assumptions'!$C$4,{"Base","Upside","Downside"},0),C22,D22,E22) -> 0 | G22: Price/packaging/mix improvement applied to ARPA each month.
A23: Usage/overage revenue per customer | B23: $/mo | C23: 150 | D23: 190 | E23: 100 | F23: =CHOOSE(MATCH('Assumptions'!$C$4,{"Base","Upside","Downside"},0),C23,D23,E23) -> 0 | G23: Average metered usage revenue billed on top of subscription, per active account.
A24: Usage revenue growth, month over month | B24: % | C24: 0.01 | D24: 0.018 | E24: 0.003 | F24: =CHOOSE(MATCH('Assumptions'!$C$4,{"Base","Upside","Downside"},0),C24,D24,E24) -> 0 | G24: Growth in metered usage intensity per account each month.
A26: COGS & Gross Margin
A27: Hosting & infrastructure, % of revenue | B27: % | C27: 0.08 | D27: 0.065 | E27: 0.1 | F27: =CHOOSE(MATCH('Assumptions'!$C$4,{"Base","Upside","Downside"},0),C27,D27,E27) -> 0 | G27: Cloud hosting cost to serve, as a % of total revenue.
A28: Third-party data/API costs, % of revenue | B28: % | C28: 0.03 | D28: 0.025 | E28: 0.04 | F28: =CHOOSE(MATCH('Assumptions'!$C$4,{"Base","Upside","Downside"},0),C28,D28,E28) -> 0 | G28: Licensed data feeds / third-party APIs embedded in the product.
A29: Payment processing fees, % of revenue | B29: % | C29: 0.015 | D29: 0.013 | E29: 0.018 | F29: =CHOOSE(MATCH('Assumptions'!$C$4,{"Base","Upside","Downside"},0),C29,D29,E29) -> 0 | G29: Card/ACH processing fees on billed revenue.
A31: Headcount — Customer Success (COGS)
A32: Starting CS/Support FTEs | B32: # | C32: 2 | D32: 2 | E32: 2 | F32: =CHOOSE(MATCH('Assumptions'!$C$4,{"Base","Upside","Downside"},0),C32,D32,E32) -> 0 | G32: Customer Success & Support team.
A33: CS/Support net adds per quarter | B33: # | C33: 1 | D33: 1.5 | E33: 0.5 | F33: =CHOOSE(MATCH('Assumptions'!$C$4,{"Base","Upside","Downside"},0),C33,D33,E33) -> 0
A34: CS/Support fully-loaded cost per FTE | B34: $/mo | C34: 9000 | D34: 9000 | E34: 9000 | F34: =CHOOSE(MATCH('Assumptions'!$C$4,{"Base","Upside","Downside"},0),C34,D34,E34) -> 0 | G34: Salary + benefits + payroll tax, monthly.
A36: Headcount — Sales & Marketing (Opex)
A37: Starting Account Executive FTEs | B37: # | C37: 3 | D37: 3 | E37: 3 | F37: =CHOOSE(MATCH('Assumptions'!$C$4,{"Base","Upside","Downside"},0),C37,D37,E37) -> 0
A38: AE net adds per quarter | B38: # | C38: 1 | D38: 2 | E38: 0.5 | F38: =CHOOSE(MATCH('Assumptions'!$C$4,{"Base","Upside","Downside"},0),C38,D38,E38) -> 0
A39: AE fully-loaded cost per FTE | B39: $/mo | C39: 14000 | D39: 14000 | E39: 14000 | F39: =CHOOSE(MATCH('Assumptions'!$C$4,{"Base","Upside","Downside"},0),C39,D39,E39) -> 0
A40: Starting SDR/BDR FTEs | B40: # | C40: 2 | D40: 2 | E40: 2 | F40: =CHOOSE(MATCH('Assumptions'!$C$4,{"Base","Upside","Downside"},0),C40,D40,E40) -> 0 | G40: Pipeline-generation reps.
A41: SDR/BDR net adds per quarter | B41: # | C41: 1 | D41: 1.5 | E41: 0.5 | F41: =CHOOSE(MATCH('Assumptions'!$C$4,{"Base","Upside","Downside"},0),C41,D41,E41) -> 0
A42: SDR/BDR fully-loaded cost per FTE | B42: $/mo | C42: 8000 | D42: 8000 | E42: 8000 | F42: =CHOOSE(MATCH('Assumptions'!$C$4,{"Base","Upside","Downside"},0),C42,D42,E42) -> 0
A44: Headcount — R&D / Engineering (Opex)
A45: Starting Engineering/Product FTEs | B45: # | C45: 6 | D45: 6 | E45: 6 | F45: =CHOOSE(MATCH('Assumptions'!$C$4,{"Base","Upside","Downside"},0),C45,D45,E45) -> 0
A46: Engineering net adds per quarter | B46: # | C46: 2 | D46: 3 | E46: 1 | F46: =CHOOSE(MATCH('Assumptions'!$C$4,{"Base","Upside","Downside"},0),C46,D46,E46) -> 0
A47: Engineering fully-loaded cost per FTE | B47: $/mo | C47: 15000 | D47: 15000 | E47: 15000 | F47: =CHOOSE(MATCH('Assumptions'!$C$4,{"Base","Upside","Downside"},0),C47,D47,E47) -> 0
A49: Headcount — G&A (Opex)
A50: Starting G&A FTEs | B50: # | C50: 2 | D50: 2 | E50: 2 | F50: =CHOOSE(MATCH('Assumptions'!$C$4,{"Base","Upside","Downside"},0),C50,D50,E50) -> 0 | G50: Finance, HR, Ops.
A51: G&A net adds per quarter | B51: # | C51: 0.5 | D51: 0.5 | E51: 0.25 | F51: =CHOOSE(MATCH('Assumptions'!$C$4,{"Base","Upside","Downside"},0),C51,D51,E51) -> 0
A52: G&A fully-loaded cost per FTE | B52: $/mo | C52: 11000 | D52: 11000 | E52: 11000 | F52: =CHOOSE(MATCH('Assumptions'!$C$4,{"Base","Upside","Downside"},0),C52,D52,E52) -> 0
A54: GTM Economics & Other Opex
A55: Sales commission, % of new ARR booked | B55: % | C55: 0.1 | D55: 0.09 | E55: 0.12 | F55: =CHOOSE(MATCH('Assumptions'!$C$4,{"Base","Upside","Downside"},0),C55,D55,E55) -> 0 | G55: Paid on newly booked ARR the month it is signed.
A56: Marketing programs, % of revenue | B56: % | C56: 0.12 | D56: 0.15 | E56: 0.08 | F56: =CHOOSE(MATCH('Assumptions'!$C$4,{"Base","Upside","Downside"},0),C56,D56,E56) -> 0 | G56: Paid demand-gen / brand spend.
A57: G&A software & tools | B57: $/mo | C57: 6000 | D57: 6000 | E57: 6000 | F57: =CHOOSE(MATCH('Assumptions'!$C$4,{"Base","Upside","Downside"},0),C57,D57,E57) -> 0
A58: G&A facilities & other fixed costs | B58: $/mo | C58: 4000 | D58: 4000 | E58: 4000 | F58: =CHOOSE(MATCH('Assumptions'!$C$4,{"Base","Upside","Downside"},0),C58,D58,E58) -> 0
A60: Working Capital & Financing
A61: Days Sales Outstanding (AR) | B61: days | C61: 35 | D61: 30 | E61: 42 | F61: =CHOOSE(MATCH('Assumptions'!$C$4,{"Base","Upside","Downside"},0),C61,D61,E61) -> 0
A62: Days Payable Outstanding (AP) | B62: days | C62: 30 | D62: 30 | E62: 30 | F62: =CHOOSE(MATCH('Assumptions'!$C$4,{"Base","Upside","Downside"},0),C62,D62,E62) -> 0
A63: Deferred revenue (months of revenue held) | B63: mo | C63: 1 | D63: 1.2 | E63: 0.8 | F63: =CHOOSE(MATCH('Assumptions'!$C$4,{"Base","Upside","Downside"},0),C63,D63,E63) -> 0 | G63: Reflects the mix of customers pre-paying annually.
A64: Capex, % of revenue | B64: % | C64: 0.02 | D64: 0.015 | E64: 0.025 | F64: =CHOOSE(MATCH('Assumptions'!$C$4,{"Base","Upside","Downside"},0),C64,D64,E64) -> 0
A65: Useful life of capitalized assets | B65: months | C65: 36 | D65: 36 | E65: 36 | F65: =CHOOSE(MATCH('Assumptions'!$C$4,{"Base","Upside","Downside"},0),C65,D65,E65) -> 0
A66: Other current assets, % of revenue | B66: % | C66: 0.03 | D66: 0.03 | E66: 0.03 | F66: =CHOOSE(MATCH('Assumptions'!$C$4,{"Base","Upside","Downside"},0),C66,D66,E66) -> 0 | G66: Prepaid expenses and other small current assets.
A67: Venture debt annual interest rate | B67: % | C67: 0.09 | D67: 0.08 | E67: 0.11 | F67: =CHOOSE(MATCH('Assumptions'!$C$4,{"Base","Upside","Downside"},0),C67,D67,E67) -> 0
A68: Venture debt draw (one-time) | B68: $ | C68: 750000 | D68: 750000 | E68: 500000 | F68: =CHOOSE(MATCH('Assumptions'!$C$4,{"Base","Upside","Downside"},0),C68,D68,E68) -> 0
A69: Venture debt monthly repayment | B69: $/mo | C69: 25000 | D69: 25000 | E69: 20000 | F69: =CHOOSE(MATCH('Assumptions'!$C$4,{"Base","Upside","Downside"},0),C69,D69,E69) -> 0
A70: Series A raise (month 4) | B70: $ | C70: 6000000 | D70: 6000000 | E70: 5000000 | F70: =CHOOSE(MATCH('Assumptions'!$C$4,{"Base","Upside","Downside"},0),C70,D70,E70) -> 0
A71: Series B raise (month 22) | B71: $ | C71: 12000000 | D71: 14000000 | E71: 9000000 | F71: =CHOOSE(MATCH('Assumptions'!$C$4,{"Base","Upside","Downside"},0),C71,D71,E71) -> 0
A74: Tip: start with the Base column, then stress-test with Upside/Downside.

Sheet Headcount
A1: B2B SaaS + Usage — 3-Year Financial Model — Headcount
A2: Fully-loaded FTE ramps by role — flows into COGS or Opex by classification.
A5: Line item | B5: Units / source | C5: Monthly (36 months) | AN5: Quarterly | BA5: Annual
C6: 46023 | D6: 46054 | E6: 46082 | F6: 46113 | G6: 46143 | H6: 46174 | I6: 46204 | J6: 46235 | K6: 46266 | L6: 46296 | M6: 46327 | N6: 46357 | O6: 46388 | P6: 46419 | Q6: 46447 | R6: 46478 | S6: 46508 | T6: 46539 | U6: 46569 | V6: 46600 | W6: 46631 | X6: 46661 | Y6: 46692 | Z6: 46722 | AA6: 46753 | AB6: 46784 | AC6: 46813 | AD6: 46844 | AE6: 46874 | AF6: 46905 | AG6: 46935 | AH6: 46966 | AI6: 46997 | AJ6: 47027 | AK6: 47058 | AL6: 47088 | AN6: Q1 | AO6: Q2 | AP6: Q3 | AQ6: Q4 | AR6: Q5 | AS6: Q6 | AT6: Q7 | AU6: Q8 | AV6: Q9 | AW6: Q10 | AX6: Q11 | AY6: Q12 | BA6: FY1 | BB6: FY2 | BC6: FY3
A7: Cost of Goods Sold headcount (COGS-classified)
A8: Customer Success / Support — headcount (FTE) | B8: Customer Success · start + net adds/qtr ÷ 3 | C8: =ROUND('Assumptions'!$F$32,1) -> 0 | D8: =ROUND(C8+'Assumptions'!$F$33/3,1) -> 0 | E8: =ROUND(D8+'Assumptions'!$F$33/3,1) -> 0 | F8: =ROUND(E8+'Assumptions'!$F$33/3,1) -> 0 | G8: =ROUND(F8+'Assumptions'!$F$33/3,1) -> 0 | H8: =ROUND(G8+'Assumptions'!$F$33/3,1) -> 0 | I8: =ROUND(H8+'Assumptions'!$F$33/3,1) -> 0 | J8: =ROUND(I8+'Assumptions'!$F$33/3,1) -> 0 | K8: =ROUND(J8+'Assumptions'!$F$33/3,1) -> 0 | ... AL8: =ROUND(AK8+'Assumptions'!$F$33/3,1) -> 0 | AN8: =E8 -> 0 | AO8: =H8 -> 0 | AP8: =K8 -> 0 | AQ8: =N8 -> 0 | AR8: =Q8 -> 0 | AS8: =T8 -> 0 | AT8: =W8 -> 0 | AU8: =Z8 -> 0 | AV8: =AC8 -> 0 | AW8: =AF8 -> 0 | AX8: =AI8 -> 0 | AY8: =AL8 -> 0 | BA8: =N8 -> 0 | BB8: =Z8 -> 0 | BC8: =AL8 -> 0
A9: Customer Success / Support — fully-loaded cost | B9: Headcount × monthly fully-loaded cost/FTE | C9: =C8*'Assumptions'!$F$34 -> 0 | D9: =D8*'Assumptions'!$F$34 -> 0 | E9: =E8*'Assumptions'!$F$34 -> 0 | F9: =F8*'Assumptions'!$F$34 -> 0 | G9: =G8*'Assumptions'!$F$34 -> 0 | H9: =H8*'Assumptions'!$F$34 -> 0 | I9: =I8*'Assumptions'!$F$34 -> 0 | J9: =J8*'Assumptions'!$F$34 -> 0 | ... AL9: =AL8*'Assumptions'!$F$34 -> 0 | AN9: =SUM(C9:E9) -> 0 | AO9: =SUM(F9:H9) -> 0 | AP9: =SUM(I9:K9) -> 0 | AQ9: =SUM(L9:N9) -> 0 | AR9: =SUM(O9:Q9) -> 0 | AS9: =SUM(R9:T9) -> 0 | AT9: =SUM(U9:W9) -> 0 | AU9: =SUM(X9:Z9) -> 0 | AV9: =SUM(AA9:AC9) -> 0 | AW9: =SUM(AD9:AF9) -> 0 | AX9: =SUM(AG9:AI9) -> 0 | AY9: =SUM(AJ9:AL9) -> 0 | BA9: =SUM(C9:N9) -> 0 | BB9: =SUM(O9:Z9) -> 0 | BC9: =SUM(AA9:AL9) -> 0
A11: Operating expense headcount (Opex-classified)
A12: Account Executives (Sales) — headcount (FTE) | B12: Sales & Marketing · start + net adds/qtr ÷ 3 | C12: =ROUND('Assumptions'!$F$37,1) -> 0 | D12: =ROUND(C12+'Assumptions'!$F$38/3,1) -> 0 | E12: =ROUND(D12+'Assumptions'!$F$38/3,1) -> 0 | F12: =ROUND(E12+'Assumptions'!$F$38/3,1) -> 0 | G12: =ROUND(F12+'Assumptions'!$F$38/3,1) -> 0 | H12: =ROUND(G12+'Assumptions'!$F$38/3,1) -> 0 | I12: =ROUND(H12+'Assumptions'!$F$38/3,1) -> 0 | J12: =ROUND(I12+'Assumptions'!$F$38/3,1) -> 0 | K12: =ROUND(J12+'Assumptions'!$F$38/3,1) -> 0 | ... AL12: =ROUND(AK12+'Assumptions'!$F$38/3,1) -> 0 | AN12: =E12 -> 0 | AO12: =H12 -> 0 | AP12: =K12 -> 0 | AQ12: =N12 -> 0 | AR12: =Q12 -> 0 | AS12: =T12 -> 0 | AT12: =W12 -> 0 | AU12: =Z12 -> 0 | AV12: =AC12 -> 0 | AW12: =AF12 -> 0 | AX12: =AI12 -> 0 | AY12: =AL12 -> 0 | BA12: =N12 -> 0 | BB12: =Z12 -> 0 | BC12: =AL12 -> 0
A13: Account Executives (Sales) — fully-loaded cost | B13: Headcount × monthly fully-loaded cost/FTE | C13: =C12*'Assumptions'!$F$39 -> 0 | D13: =D12*'Assumptions'!$F$39 -> 0 | E13: =E12*'Assumptions'!$F$39 -> 0 | F13: =F12*'Assumptions'!$F$39 -> 0 | G13: =G12*'Assumptions'!$F$39 -> 0 | H13: =H12*'Assumptions'!$F$39 -> 0 | I13: =I12*'Assumptions'!$F$39 -> 0 | J13: =J12*'Assumptions'!$F$39 -> 0 | ... AL13: =AL12*'Assumptions'!$F$39 -> 0 | AN13: =SUM(C13:E13) -> 0 | AO13: =SUM(F13:H13) -> 0 | AP13: =SUM(I13:K13) -> 0 | AQ13: =SUM(L13:N13) -> 0 | AR13: =SUM(O13:Q13) -> 0 | AS13: =SUM(R13:T13) -> 0 | AT13: =SUM(U13:W13) -> 0 | AU13: =SUM(X13:Z13) -> 0 | AV13: =SUM(AA13:AC13) -> 0 | AW13: =SUM(AD13:AF13) -> 0 | AX13: =SUM(AG13:AI13) -> 0 | AY13: =SUM(AJ13:AL13) -> 0 | BA13: =SUM(C13:N13) -> 0 | BB13: =SUM(O13:Z13) -> 0 | BC13: =SUM(AA13:AL13) -> 0
A14: SDR / BDR (Pipeline) — headcount (FTE) | B14: Sales & Marketing · start + net adds/qtr ÷ 3 | C14: =ROUND('Assumptions'!$F$40,1) -> 0 | D14: =ROUND(C14+'Assumptions'!$F$41/3,1) -> 0 | E14: =ROUND(D14+'Assumptions'!$F$41/3,1) -> 0 | F14: =ROUND(E14+'Assumptions'!$F$41/3,1) -> 0 | G14: =ROUND(F14+'Assumptions'!$F$41/3,1) -> 0 | H14: =ROUND(G14+'Assumptions'!$F$41/3,1) -> 0 | I14: =ROUND(H14+'Assumptions'!$F$41/3,1) -> 0 | J14: =ROUND(I14+'Assumptions'!$F$41/3,1) -> 0 | K14: =ROUND(J14+'Assumptions'!$F$41/3,1) -> 0 | ... AL14: =ROUND(AK14+'Assumptions'!$F$41/3,1) -> 0 | AN14: =E14 -> 0 | AO14: =H14 -> 0 | AP14: =K14 -> 0 | AQ14: =N14 -> 0 | AR14: =Q14 -> 0 | AS14: =T14 -> 0 | AT14: =W14 -> 0 | AU14: =Z14 -> 0 | AV14: =AC14 -> 0 | AW14: =AF14 -> 0 | AX14: =AI14 -> 0 | AY14: =AL14 -> 0 | BA14: =N14 -> 0 | BB14: =Z14 -> 0 | BC14: =AL14 -> 0
A15: SDR / BDR (Pipeline) — fully-loaded cost | B15: Headcount × monthly fully-loaded cost/FTE | C15: =C14*'Assumptions'!$F$42 -> 0 | D15: =D14*'Assumptions'!$F$42 -> 0 | E15: =E14*'Assumptions'!$F$42 -> 0 | F15: =F14*'Assumptions'!$F$42 -> 0 | G15: =G14*'Assumptions'!$F$42 -> 0 | H15: =H14*'Assumptions'!$F$42 -> 0 | I15: =I14*'Assumptions'!$F$42 -> 0 | J15: =J14*'Assumptions'!$F$42 -> 0 | ... AL15: =AL14*'Assumptions'!$F$42 -> 0 | AN15: =SUM(C15:E15) -> 0 | AO15: =SUM(F15:H15) -> 0 | AP15: =SUM(I15:K15) -> 0 | AQ15: =SUM(L15:N15) -> 0 | AR15: =SUM(O15:Q15) -> 0 | AS15: =SUM(R15:T15) -> 0 | AT15: =SUM(U15:W15) -> 0 | AU15: =SUM(X15:Z15) -> 0 | AV15: =SUM(AA15:AC15) -> 0 | AW15: =SUM(AD15:AF15) -> 0 | AX15: =SUM(AG15:AI15) -> 0 | AY15: =SUM(AJ15:AL15) -> 0 | BA15: =SUM(C15:N15) -> 0 | BB15: =SUM(O15:Z15) -> 0 | BC15: =SUM(AA15:AL15) -> 0
A16: Engineering / Product — headcount (FTE) | B16: R&D / Engineering · start + net adds/qtr ÷ 3 | C16: =ROUND('Assumptions'!$F$45,1) -> 0 | D16: =ROUND(C16+'Assumptions'!$F$46/3,1) -> 0 | E16: =ROUND(D16+'Assumptions'!$F$46/3,1) -> 0 | F16: =ROUND(E16+'Assumptions'!$F$46/3,1) -> 0 | G16: =ROUND(F16+'Assumptions'!$F$46/3,1) -> 0 | H16: =ROUND(G16+'Assumptions'!$F$46/3,1) -> 0 | I16: =ROUND(H16+'Assumptions'!$F$46/3,1) -> 0 | J16: =ROUND(I16+'Assumptions'!$F$46/3,1) -> 0 | K16: =ROUND(J16+'Assumptions'!$F$46/3,1) -> 0 | ... AL16: =ROUND(AK16+'Assumptions'!$F$46/3,1) -> 0 | AN16: =E16 -> 0 | AO16: =H16 -> 0 | AP16: =K16 -> 0 | AQ16: =N16 -> 0 | AR16: =Q16 -> 0 | AS16: =T16 -> 0 | AT16: =W16 -> 0 | AU16: =Z16 -> 0 | AV16: =AC16 -> 0 | AW16: =AF16 -> 0 | AX16: =AI16 -> 0 | AY16: =AL16 -> 0 | BA16: =N16 -> 0 | BB16: =Z16 -> 0 | BC16: =AL16 -> 0
A17: Engineering / Product — fully-loaded cost | B17: Headcount × monthly fully-loaded cost/FTE | C17: =C16*'Assumptions'!$F$47 -> 0 | D17: =D16*'Assumptions'!$F$47 -> 0 | E17: =E16*'Assumptions'!$F$47 -> 0 | F17: =F16*'Assumptions'!$F$47 -> 0 | G17: =G16*'Assumptions'!$F$47 -> 0 | H17: =H16*'Assumptions'!$F$47 -> 0 | I17: =I16*'Assumptions'!$F$47 -> 0 | J17: =J16*'Assumptions'!$F$47 -> 0 | ... AL17: =AL16*'Assumptions'!$F$47 -> 0 | AN17: =SUM(C17:E17) -> 0 | AO17: =SUM(F17:H17) -> 0 | AP17: =SUM(I17:K17) -> 0 | AQ17: =SUM(L17:N17) -> 0 | AR17: =SUM(O17:Q17) -> 0 | AS17: =SUM(R17:T17) -> 0 | AT17: =SUM(U17:W17) -> 0 | AU17: =SUM(X17:Z17) -> 0 | AV17: =SUM(AA17:AC17) -> 0 | AW17: =SUM(AD17:AF17) -> 0 | AX17: =SUM(AG17:AI17) -> 0 | AY17: =SUM(AJ17:AL17) -> 0 | BA17: =SUM(C17:N17) -> 0 | BB17: =SUM(O17:Z17) -> 0 | BC17: =SUM(AA17:AL17) -> 0
A18: G&A (Finance/HR/Ops) — headcount (FTE) | B18: General & Administrative · start + net adds/qtr ÷ 3 | C18: =ROUND('Assumptions'!$F$50,1) -> 0 | D18: =ROUND(C18+'Assumptions'!$F$51/3,1) -> 0 | E18: =ROUND(D18+'Assumptions'!$F$51/3,1) -> 0 | F18: =ROUND(E18+'Assumptions'!$F$51/3,1) -> 0 | G18: =ROUND(F18+'Assumptions'!$F$51/3,1) -> 0 | H18: =ROUND(G18+'Assumptions'!$F$51/3,1) -> 0 | I18: =ROUND(H18+'Assumptions'!$F$51/3,1) -> 0 | J18: =ROUND(I18+'Assumptions'!$F$51/3,1) -> 0 | K18: =ROUND(J18+'Assumptions'!$F$51/3,1) -> 0 | ... AL18: =ROUND(AK18+'Assumptions'!$F$51/3,1) -> 0 | AN18: =E18 -> 0 | AO18: =H18 -> 0 | AP18: =K18 -> 0 | AQ18: =N18 -> 0 | AR18: =Q18 -> 0 | AS18: =T18 -> 0 | AT18: =W18 -> 0 | AU18: =Z18 -> 0 | AV18: =AC18 -> 0 | AW18: =AF18 -> 0 | AX18: =AI18 -> 0 | AY18: =AL18 -> 0 | BA18: =N18 -> 0 | BB18: =Z18 -> 0 | BC18: =AL18 -> 0
A19: G&A (Finance/HR/Ops) — fully-loaded cost | B19: Headcount × monthly fully-loaded cost/FTE | C19: =C18*'Assumptions'!$F$52 -> 0 | D19: =D18*'Assumptions'!$F$52 -> 0 | E19: =E18*'Assumptions'!$F$52 -> 0 | F19: =F18*'Assumptions'!$F$52 -> 0 | G19: =G18*'Assumptions'!$F$52 -> 0 | H19: =H18*'Assumptions'!$F$52 -> 0 | I19: =I18*'Assumptions'!$F$52 -> 0 | J19: =J18*'Assumptions'!$F$52 -> 0 | ... AL19: =AL18*'Assumptions'!$F$52 -> 0 | AN19: =SUM(C19:E19) -> 0 | AO19: =SUM(F19:H19) -> 0 | AP19: =SUM(I19:K19) -> 0 | AQ19: =SUM(L19:N19) -> 0 | AR19: =SUM(O19:Q19) -> 0 | AS19: =SUM(R19:T19) -> 0 | AT19: =SUM(U19:W19) -> 0 | AU19: =SUM(X19:Z19) -> 0 | AV19: =SUM(AA19:AC19) -> 0 | AW19: =SUM(AD19:AF19) -> 0 | AX19: =SUM(AG19:AI19) -> 0 | AY19: =SUM(AJ19:AL19) -> 0 | BA19: =SUM(C19:N19) -> 0 | BB19: =SUM(O19:Z19) -> 0 | BC19: =SUM(AA19:AL19) -> 0
A21: Totals
A22: Total headcount (FTE) | B22: Sum of all roles | C22: =C8+C12+C14+C16+C18 -> 0 | D22: =D8+D12+D14+D16+D18 -> 0 | E22: =E8+E12+E14+E16+E18 -> 0 | F22: =F8+F12+F14+F16+F18 -> 0 | G22: =G8+G12+G14+G16+G18 -> 0 | H22: =H8+H12+H14+H16+H18 -> 0 | I22: =I8+I12+I14+I16+I18 -> 0 | J22: =J8+J12+J14+J16+J18 -> 0 | ... AL22: =AL8+AL12+AL14+AL16+AL18 -> 0 | AN22: =E22 -> 0 | AO22: =H22 -> 0 | AP22: =K22 -> 0 | AQ22: =N22 -> 0 | AR22: =Q22 -> 0 | AS22: =T22 -> 0 | AT22: =W22 -> 0 | AU22: =Z22 -> 0 | AV22: =AC22 -> 0 | AW22: =AF22 -> 0 | AX22: =AI22 -> 0 | AY22: =AL22 -> 0 | BA22: =N22 -> 0 | BB22: =Z22 -> 0 | BC22: =AL22 -> 0
A23: Total COGS-classified people cost | B23: Feeds COGS & GM tab | C23: =C9 -> 0 | D23: =D9 -> 0 | E23: =E9 -> 0 | F23: =F9 -> 0 | G23: =G9 -> 0 | H23: =H9 -> 0 | I23: =I9 -> 0 | J23: =J9 -> 0 | ... AL23: =AL9 -> 0 | AN23: =SUM(C23:E23) -> 0 | AO23: =SUM(F23:H23) -> 0 | AP23: =SUM(I23:K23) -> 0 | AQ23: =SUM(L23:N23) -> 0 | AR23: =SUM(O23:Q23) -> 0 | AS23: =SUM(R23:T23) -> 0 | AT23: =SUM(U23:W23) -> 0 | AU23: =SUM(X23:Z23) -> 0 | AV23: =SUM(AA23:AC23) -> 0 | AW23: =SUM(AD23:AF23) -> 0 | AX23: =SUM(AG23:AI23) -> 0 | AY23: =SUM(AJ23:AL23) -> 0 | BA23: =SUM(C23:N23) -> 0 | BB23: =SUM(O23:Z23) -> 0 | BC23: =SUM(AA23:AL23) -> 0
A24: Total Opex-classified people cost | B24: Feeds Opex tab | C24: =C13+C15+C17+C19 -> 0 | D24: =D13+D15+D17+D19 -> 0 | E24: =E13+E15+E17+E19 -> 0 | F24: =F13+F15+F17+F19 -> 0 | G24: =G13+G15+G17+G19 -> 0 | H24: =H13+H15+H17+H19 -> 0 | I24: =I13+I15+I17+I19 -> 0 | J24: =J13+J15+J17+J19 -> 0 | ... AL24: =AL13+AL15+AL17+AL19 -> 0 | AN24: =SUM(C24:E24) -> 0 | AO24: =SUM(F24:H24) -> 0 | AP24: =SUM(I24:K24) -> 0 | AQ24: =SUM(L24:N24) -> 0 | AR24: =SUM(O24:Q24) -> 0 | AS24: =SUM(R24:T24) -> 0 | AT24: =SUM(U24:W24) -> 0 | AU24: =SUM(X24:Z24) -> 0 | AV24: =SUM(AA24:AC24) -> 0 | AW24: =SUM(AD24:AF24) -> 0 | AX24: =SUM(AG24:AI24) -> 0 | AY24: =SUM(AJ24:AL24) -> 0 | BA24: =SUM(C24:N24) -> 0 | BB24: =SUM(O24:Z24) -> 0 | BC24: =SUM(AA24:AL24) -> 0
A25: General & Administrative people cost | C25: =C19 -> 0 | D25: =D19 -> 0 | E25: =E19 -> 0 | F25: =F19 -> 0 | G25: =G19 -> 0 | H25: =H19 -> 0 | I25: =I19 -> 0 | J25: =J19 -> 0 | ... AL25: =AL19 -> 0 | AN25: =SUM(C25:E25) -> 0 | AO25: =SUM(F25:H25) -> 0 | AP25: =SUM(I25:K25) -> 0 | AQ25: =SUM(L25:N25) -> 0 | AR25: =SUM(O25:Q25) -> 0 | AS25: =SUM(R25:T25) -> 0 | AT25: =SUM(U25:W25) -> 0 | AU25: =SUM(X25:Z25) -> 0 | AV25: =SUM(AA25:AC25) -> 0 | AW25: =SUM(AD25:AF25) -> 0 | AX25: =SUM(AG25:AI25) -> 0 | AY25: =SUM(AJ25:AL25) -> 0 | BA25: =SUM(C25:N25) -> 0 | BB25: =SUM(O25:Z25) -> 0 | BC25: =SUM(AA25:AL25) -> 0
A26: R&D / Engineering people cost | C26: =C17 -> 0 | D26: =D17 -> 0 | E26: =E17 -> 0 | F26: =F17 -> 0 | G26: =G17 -> 0 | H26: =H17 -> 0 | I26: =I17 -> 0 | J26: =J17 -> 0 | ... AL26: =AL17 -> 0 | AN26: =SUM(C26:E26) -> 0 | AO26: =SUM(F26:H26) -> 0 | AP26: =SUM(I26:K26) -> 0 | AQ26: =SUM(L26:N26) -> 0 | AR26: =SUM(O26:Q26) -> 0 | AS26: =SUM(R26:T26) -> 0 | AT26: =SUM(U26:W26) -> 0 | AU26: =SUM(X26:Z26) -> 0 | AV26: =SUM(AA26:AC26) -> 0 | AW26: =SUM(AD26:AF26) -> 0 | AX26: =SUM(AG26:AI26) -> 0 | AY26: =SUM(AJ26:AL26) -> 0 | BA26: =SUM(C26:N26) -> 0 | BB26: =SUM(O26:Z26) -> 0 | BC26: =SUM(AA26:AL26) -> 0
A27: Sales & Marketing people cost | C27: =C13+C15 -> 0 | D27: =D13+D15 -> 0 | E27: =E13+E15 -> 0 | F27: =F13+F15 -> 0 | G27: =G13+G15 -> 0 | H27: =H13+H15 -> 0 | I27: =I13+I15 -> 0 | J27: =J13+J15 -> 0 | ... AL27: =AL13+AL15 -> 0 | AN27: =SUM(C27:E27) -> 0 | AO27: =SUM(F27:H27) -> 0 | AP27: =SUM(I27:K27) -> 0 | AQ27: =SUM(L27:N27) -> 0 | AR27: =SUM(O27:Q27) -> 0 | AS27: =SUM(R27:T27) -> 0 | AT27: =SUM(U27:W27) -> 0 | AU27: =SUM(X27:Z27) -> 0 | AV27: =SUM(AA27:AC27) -> 0 | AW27: =SUM(AD27:AF27) -> 0 | AX27: =SUM(AG27:AI27) -> 0 | AY27: =SUM(AJ27:AL27) -> 0 | BA27: =SUM(C27:N27) -> 0 | BB27: =SUM(O27:Z27) -> 0 | BC27: =SUM(AA27:AL27) -> 0

Sheet Revenue
A1: B2B SaaS + Usage — 3-Year Financial Model — Revenue
A2: Customer/logo bridge -> MRR bridge (new/expansion/contraction/churn) -> usage overage revenue.
A5: Line item | B5: Units / source | C5: Monthly (36 months) | AN5: Quarterly | BA5: Annual
C6: 46023 | D6: 46054 | E6: 46082 | F6: 46113 | G6: 46143 | H6: 46174 | I6: 46204 | J6: 46235 | K6: 46266 | L6: 46296 | M6: 46327 | N6: 46357 | O6: 46388 | P6: 46419 | Q6: 46447 | R6: 46478 | S6: 46508 | T6: 46539 | U6: 46569 | V6: 46600 | W6: 46631 | X6: 46661 | Y6: 46692 | Z6: 46722 | AA6: 46753 | AB6: 46784 | AC6: 46813 | AD6: 46844 | AE6: 46874 | AF6: 46905 | AG6: 46935 | AH6: 46966 | AI6: 46997 | AJ6: 47027 | AK6: 47058 | AL6: 47088 | AN6: Q1 | AO6: Q2 | AP6: Q3 | AQ6: Q4 | AR6: Q5 | AS6: Q6 | AT6: Q7 | AU6: Q8 | AV6: Q9 | AW6: Q10 | AX6: Q11 | AY6: Q12 | BA6: FY1 | BB6: FY2 | BC6: FY3
A7: Customer / Logo Bridge
A8: Beginning Customers | C8: ='Assumptions'!$F$13 -> 0 | D8: =C8 -> 0 | E8: =D8 -> 0 | F8: =E8 -> 0 | G8: =F8 -> 0 | H8: =G8 -> 0 | I8: =H8 -> 0 | J8: =I8 -> 0 | K8: =J8 -> 0 | ... AL8: =AK8 -> 0 | AN8: =E8 -> 0 | AO8: =H8 -> 0 | AP8: =K8 -> 0 | AQ8: =N8 -> 0 | AR8: =Q8 -> 0 | AS8: =T8 -> 0 | AT8: =W8 -> 0 | AU8: =Z8 -> 0 | AV8: =AC8 -> 0 | AW8: =AF8 -> 0 | AX8: =AI8 -> 0 | AY8: =AL8 -> 0 | BA8: =N8 -> 0 | BB8: =Z8 -> 0 | BC8: =AL8 -> 0
A9: New Logos Added | C9: ='Assumptions'!$F$14 -> 0 | D9: =C9*(1+'Assumptions'!$F$15) -> 0 | E9: =D9*(1+'Assumptions'!$F$15) -> 0 | F9: =E9*(1+'Assumptions'!$F$15) -> 0 | G9: =F9*(1+'Assumptions'!$F$15) -> 0 | H9: =G9*(1+'Assumptions'!$F$15) -> 0 | I9: =H9*(1+'Assumptions'!$F$15) -> 0 | J9: =I9*(1+'Assumptions'!$F$15) -> 0 | K9: =J9*(1+'Assumptions'!$F$15) -> 0 | ... AL9: =AK9*(1+'Assumptions'!$F$15) -> 0 | AN9: =SUM(C9:E9) -> 0 | AO9: =SUM(F9:H9) -> 0 | AP9: =SUM(I9:K9) -> 0 | AQ9: =SUM(L9:N9) -> 0 | AR9: =SUM(O9:Q9) -> 0 | AS9: =SUM(R9:T9) -> 0 | AT9: =SUM(U9:W9) -> 0 | AU9: =SUM(X9:Z9) -> 0 | AV9: =SUM(AA9:AC9) -> 0 | AW9: =SUM(AD9:AF9) -> 0 | AX9: =SUM(AG9:AI9) -> 0 | AY9: =SUM(AJ9:AL9) -> 0 | BA9: =SUM(C9:N9) -> 0 | BB9: =SUM(O9:Z9) -> 0 | BC9: =SUM(AA9:AL9) -> 0
A10: Churned Customers | C10: =-C8*'Assumptions'!$F$16 -> 0 | D10: =-D8*'Assumptions'!$F$16 -> 0 | E10: =-E8*'Assumptions'!$F$16 -> 0 | F10: =-F8*'Assumptions'!$F$16 -> 0 | G10: =-G8*'Assumptions'!$F$16 -> 0 | H10: =-H8*'Assumptions'!$F$16 -> 0 | I10: =-I8*'Assumptions'!$F$16 -> 0 | J10: =-J8*'Assumptions'!$F$16 -> 0 | ... AL10: =-AL8*'Assumptions'!$F$16 -> 0 | AN10: =SUM(C10:E10) -> 0 | AO10: =SUM(F10:H10) -> 0 | AP10: =SUM(I10:K10) -> 0 | AQ10: =SUM(L10:N10) -> 0 | AR10: =SUM(O10:Q10) -> 0 | AS10: =SUM(R10:T10) -> 0 | AT10: =SUM(U10:W10) -> 0 | AU10: =SUM(X10:Z10) -> 0 | AV10: =SUM(AA10:AC10) -> 0 | AW10: =SUM(AD10:AF10) -> 0 | AX10: =SUM(AG10:AI10) -> 0 | AY10: =SUM(AJ10:AL10) -> 0 | BA10: =SUM(C10:N10) -> 0 | BB10: =SUM(O10:Z10) -> 0 | BC10: =SUM(AA10:AL10) -> 0
A11: Ending Customers | C11: =C8+C9+C10 -> 0 | D11: =D8+D9+D10 -> 0 | E11: =E8+E9+E10 -> 0 | F11: =F8+F9+F10 -> 0 | G11: =G8+G9+G10 -> 0 | H11: =H8+H9+H10 -> 0 | I11: =I8+I9+I10 -> 0 | J11: =J8+J9+J10 -> 0 | ... AL11: =AL8+AL9+AL10 -> 0 | AN11: =E11 -> 0 | AO11: =H11 -> 0 | AP11: =K11 -> 0 | AQ11: =N11 -> 0 | AR11: =Q11 -> 0 | AS11: =T11 -> 0 | AT11: =W11 -> 0 | AU11: =Z11 -> 0 | AV11: =AC11 -> 0 | AW11: =AF11 -> 0 | AX11: =AI11 -> 0 | AY11: =AL11 -> 0 | BA11: =N11 -> 0 | BB11: =Z11 -> 0 | BC11: =AL11 -> 0
A13: MRR Bridge
A14: ARPA (avg MRR per account) | C14: ='Assumptions'!$F$21 -> 0 | D14: =C14*(1+'Assumptions'!$F$22) -> 0 | E14: =D14*(1+'Assumptions'!$F$22) -> 0 | F14: =E14*(1+'Assumptions'!$F$22) -> 0 | G14: =F14*(1+'Assumptions'!$F$22) -> 0 | H14: =G14*(1+'Assumptions'!$F$22) -> 0 | I14: =H14*(1+'Assumptions'!$F$22) -> 0 | J14: =I14*(1+'Assumptions'!$F$22) -> 0 | K14: =J14*(1+'Assumptions'!$F$22) -> 0 | ... AL14: =AK14*(1+'Assumptions'!$F$22) -> 0 | AN14: =AVERAGE(C14:E14) -> 0 | AO14: =AVERAGE(F14:H14) -> 0 | AP14: =AVERAGE(I14:K14) -> 0 | AQ14: =AVERAGE(L14:N14) -> 0 | AR14: =AVERAGE(O14:Q14) -> 0 | AS14: =AVERAGE(R14:T14) -> 0 | AT14: =AVERAGE(U14:W14) -> 0 | AU14: =AVERAGE(X14:Z14) -> 0 | AV14: =AVERAGE(AA14:AC14) -> 0 | AW14: =AVERAGE(AD14:AF14) -> 0 | AX14: =AVERAGE(AG14:AI14) -> 0 | AY14: =AVERAGE(AJ14:AL14) -> 0 | BA14: =AVERAGE(C14:N14) -> 0 | BB14: =AVERAGE(O14:Z14) -> 0 | BC14: =AVERAGE(AA14:AL14) -> 0
A15: Beginning MRR | C15: ='Assumptions'!$F$13*'Assumptions'!$F$21 -> 0 | D15: =C15 -> 0 | E15: =D15 -> 0 | F15: =E15 -> 0 | G15: =F15 -> 0 | H15: =G15 -> 0 | I15: =H15 -> 0 | J15: =I15 -> 0 | K15: =J15 -> 0 | ... AL15: =AK15 -> 0 | AN15: =E15 -> 0 | AO15: =H15 -> 0 | AP15: =K15 -> 0 | AQ15: =N15 -> 0 | AR15: =Q15 -> 0 | AS15: =T15 -> 0 | AT15: =W15 -> 0 | AU15: =Z15 -> 0 | AV15: =AC15 -> 0 | AW15: =AF15 -> 0 | AX15: =AI15 -> 0 | AY15: =AL15 -> 0 | BA15: =N15 -> 0 | BB15: =Z15 -> 0 | BC15: =AL15 -> 0
A16: New MRR | C16: =C9*C14 -> 0 | D16: =D9*D14 -> 0 | E16: =E9*E14 -> 0 | F16: =F9*F14 -> 0 | G16: =G9*G14 -> 0 | H16: =H9*H14 -> 0 | I16: =I9*I14 -> 0 | J16: =J9*J14 -> 0 | ... AL16: =AL9*AL14 -> 0 | AN16: =SUM(C16:E16) -> 0 | AO16: =SUM(F16:H16) -> 0 | AP16: =SUM(I16:K16) -> 0 | AQ16: =SUM(L16:N16) -> 0 | AR16: =SUM(O16:Q16) -> 0 | AS16: =SUM(R16:T16) -> 0 | AT16: =SUM(U16:W16) -> 0 | AU16: =SUM(X16:Z16) -> 0 | AV16: =SUM(AA16:AC16) -> 0 | AW16: =SUM(AD16:AF16) -> 0 | AX16: =SUM(AG16:AI16) -> 0 | AY16: =SUM(AJ16:AL16) -> 0 | BA16: =SUM(C16:N16) -> 0 | BB16: =SUM(O16:Z16) -> 0 | BC16: =SUM(AA16:AL16) -> 0
A17: Expansion MRR | C17: =C15*'Assumptions'!$F$17 -> 0 | D17: =D15*'Assumptions'!$F$17 -> 0 | E17: =E15*'Assumptions'!$F$17 -> 0 | F17: =F15*'Assumptions'!$F$17 -> 0 | G17: =G15*'Assumptions'!$F$17 -> 0 | H17: =H15*'Assumptions'!$F$17 -> 0 | I17: =I15*'Assumptions'!$F$17 -> 0 | J17: =J15*'Assumptions'!$F$17 -> 0 | ... AL17: =AL15*'Assumptions'!$F$17 -> 0 | AN17: =SUM(C17:E17) -> 0 | AO17: =SUM(F17:H17) -> 0 | AP17: =SUM(I17:K17) -> 0 | AQ17: =SUM(L17:N17) -> 0 | AR17: =SUM(O17:Q17) -> 0 | AS17: =SUM(R17:T17) -> 0 | AT17: =SUM(U17:W17) -> 0 | AU17: =SUM(X17:Z17) -> 0 | AV17: =SUM(AA17:AC17) -> 0 | AW17: =SUM(AD17:AF17) -> 0 | AX17: =SUM(AG17:AI17) -> 0 | AY17: =SUM(AJ17:AL17) -> 0 | BA17: =SUM(C17:N17) -> 0 | BB17: =SUM(O17:Z17) -> 0 | BC17: =SUM(AA17:AL17) -> 0
A18: Contraction MRR | C18: =-C15*'Assumptions'!$F$18 -> 0 | D18: =-D15*'Assumptions'!$F$18 -> 0 | E18: =-E15*'Assumptions'!$F$18 -> 0 | F18: =-F15*'Assumptions'!$F$18 -> 0 | G18: =-G15*'Assumptions'!$F$18 -> 0 | H18: =-H15*'Assumptions'!$F$18 -> 0 | I18: =-I15*'Assumptions'!$F$18 -> 0 | J18: =-J15*'Assumptions'!$F$18 -> 0 | ... AL18: =-AL15*'Assumptions'!$F$18 -> 0 | AN18: =SUM(C18:E18) -> 0 | AO18: =SUM(F18:H18) -> 0 | AP18: =SUM(I18:K18) -> 0 | AQ18: =SUM(L18:N18) -> 0 | AR18: =SUM(O18:Q18) -> 0 | AS18: =SUM(R18:T18) -> 0 | AT18: =SUM(U18:W18) -> 0 | AU18: =SUM(X18:Z18) -> 0 | AV18: =SUM(AA18:AC18) -> 0 | AW18: =SUM(AD18:AF18) -> 0 | AX18: =SUM(AG18:AI18) -> 0 | AY18: =SUM(AJ18:AL18) -> 0 | BA18: =SUM(C18:N18) -> 0 | BB18: =SUM(O18:Z18) -> 0 | BC18: =SUM(AA18:AL18) -> 0
A19: Churned MRR | C19: =-C15*'Assumptions'!$F$16 -> 0 | D19: =-D15*'Assumptions'!$F$16 -> 0 | E19: =-E15*'Assumptions'!$F$16 -> 0 | F19: =-F15*'Assumptions'!$F$16 -> 0 | G19: =-G15*'Assumptions'!$F$16 -> 0 | H19: =-H15*'Assumptions'!$F$16 -> 0 | I19: =-I15*'Assumptions'!$F$16 -> 0 | J19: =-J15*'Assumptions'!$F$16 -> 0 | ... AL19: =-AL15*'Assumptions'!$F$16 -> 0 | AN19: =SUM(C19:E19) -> 0 | AO19: =SUM(F19:H19) -> 0 | AP19: =SUM(I19:K19) -> 0 | AQ19: =SUM(L19:N19) -> 0 | AR19: =SUM(O19:Q19) -> 0 | AS19: =SUM(R19:T19) -> 0 | AT19: =SUM(U19:W19) -> 0 | AU19: =SUM(X19:Z19) -> 0 | AV19: =SUM(AA19:AC19) -> 0 | AW19: =SUM(AD19:AF19) -> 0 | AX19: =SUM(AG19:AI19) -> 0 | AY19: =SUM(AJ19:AL19) -> 0 | BA19: =SUM(C19:N19) -> 0 | BB19: =SUM(O19:Z19) -> 0 | BC19: =SUM(AA19:AL19) -> 0
A20: Ending MRR | C20: =C15+C16+C17+C18+C19 -> 0 | D20: =D15+D16+D17+D18+D19 -> 0 | E20: =E15+E16+E17+E18+E19 -> 0 | F20: =F15+F16+F17+F18+F19 -> 0 | G20: =G15+G16+G17+G18+G19 -> 0 | H20: =H15+H16+H17+H18+H19 -> 0 | I20: =I15+I16+I17+I18+I19 -> 0 | J20: =J15+J16+J17+J18+J19 -> 0 | ... AL20: =AL15+AL16+AL17+AL18+AL19 -> 0 | AN20: =E20 -> 0 | AO20: =H20 -> 0 | AP20: =K20 -> 0 | AQ20: =N20 -> 0 | AR20: =Q20 -> 0 | AS20: =T20 -> 0 | AT20: =W20 -> 0 | AU20: =Z20 -> 0 | AV20: =AC20 -> 0 | AW20: =AF20 -> 0 | AX20: =AI20 -> 0 | AY20: =AL20 -> 0 | BA20: =N20 -> 0 | BB20: =Z20 -> 0 | BC20: =AL20 -> 0
A21: ARR (Ending MRR x 12) | C21: =C20*12 -> 0 | D21: =D20*12 -> 0 | E21: =E20*12 -> 0 | F21: =F20*12 -> 0 | G21: =G20*12 -> 0 | H21: =H20*12 -> 0 | I21: =I20*12 -> 0 | J21: =J20*12 -> 0 | ... AL21: =AL20*12 -> 0 | AN21: =E21 -> 0 | AO21: =H21 -> 0 | AP21: =K21 -> 0 | AQ21: =N21 -> 0 | AR21: =Q21 -> 0 | AS21: =T21 -> 0 | AT21: =W21 -> 0 | AU21: =Z21 -> 0 | AV21: =AC21 -> 0 | AW21: =AF21 -> 0 | AX21: =AI21 -> 0 | AY21: =AL21 -> 0 | BA21: =N21 -> 0 | BB21: =Z21 -> 0 | BC21: =AL21 -> 0
A23: Usage & Overage Revenue
A24: Usage revenue per customer | C24: ='Assumptions'!$F$23 -> 0 | D24: =C24*(1+'Assumptions'!$F$24) -> 0 | E24: =D24*(1+'Assumptions'!$F$24) -> 0 | F24: =E24*(1+'Assumptions'!$F$24) -> 0 | G24: =F24*(1+'Assumptions'!$F$24) -> 0 | H24: =G24*(1+'Assumptions'!$F$24) -> 0 | I24: =H24*(1+'Assumptions'!$F$24) -> 0 | J24: =I24*(1+'Assumptions'!$F$24) -> 0 | K24: =J24*(1+'Assumptions'!$F$24) -> 0 | ... AL24: =AK24*(1+'Assumptions'!$F$24) -> 0 | AN24: =AVERAGE(C24:E24) -> 0 | AO24: =AVERAGE(F24:H24) -> 0 | AP24: =AVERAGE(I24:K24) -> 0 | AQ24: =AVERAGE(L24:N24) -> 0 | AR24: =AVERAGE(O24:Q24) -> 0 | AS24: =AVERAGE(R24:T24) -> 0 | AT24: =AVERAGE(U24:W24) -> 0 | AU24: =AVERAGE(X24:Z24) -> 0 | AV24: =AVERAGE(AA24:AC24) -> 0 | AW24: =AVERAGE(AD24:AF24) -> 0 | AX24: =AVERAGE(AG24:AI24) -> 0 | AY24: =AVERAGE(AJ24:AL24) -> 0 | BA24: =AVERAGE(C24:N24) -> 0 | BB24: =AVERAGE(O24:Z24) -> 0 | BC24: =AVERAGE(AA24:AL24) -> 0
A25: Usage & Overage Revenue | C25: =C11*C24 -> 0 | D25: =D11*D24 -> 0 | E25: =E11*E24 -> 0 | F25: =F11*F24 -> 0 | G25: =G11*G24 -> 0 | H25: =H11*H24 -> 0 | I25: =I11*I24 -> 0 | J25: =J11*J24 -> 0 | ... AL25: =AL11*AL24 -> 0 | AN25: =SUM(C25:E25) -> 0 | AO25: =SUM(F25:H25) -> 0 | AP25: =SUM(I25:K25) -> 0 | AQ25: =SUM(L25:N25) -> 0 | AR25: =SUM(O25:Q25) -> 0 | AS25: =SUM(R25:T25) -> 0 | AT25: =SUM(U25:W25) -> 0 | AU25: =SUM(X25:Z25) -> 0 | AV25: =SUM(AA25:AC25) -> 0 | AW25: =SUM(AD25:AF25) -> 0 | AX25: =SUM(AG25:AI25) -> 0 | AY25: =SUM(AJ25:AL25) -> 0 | BA25: =SUM(C25:N25) -> 0 | BB25: =SUM(O25:Z25) -> 0 | BC25: =SUM(AA25:AL25) -> 0
A27: Total Revenue | C27: =C20+C25 -> 0 | D27: =D20+D25 -> 0 | E27: =E20+E25 -> 0 | F27: =F20+F25 -> 0 | G27: =G20+G25 -> 0 | H27: =H20+H25 -> 0 | I27: =I20+I25 -> 0 | J27: =J20+J25 -> 0 | ... AL27: =AL20+AL25 -> 0 | AN27: =SUM(C27:E27) -> 0 | AO27: =SUM(F27:H27) -> 0 | AP27: =SUM(I27:K27) -> 0 | AQ27: =SUM(L27:N27) -> 0 | AR27: =SUM(O27:Q27) -> 0 | AS27: =SUM(R27:T27) -> 0 | AT27: =SUM(U27:W27) -> 0 | AU27: =SUM(X27:Z27) -> 0 | AV27: =SUM(AA27:AC27) -> 0 | AW27: =SUM(AD27:AF27) -> 0 | AX27: =SUM(AG27:AI27) -> 0 | AY27: =SUM(AJ27:AL27) -> 0 | BA27: =SUM(C27:N27) -> 0 | BB27: =SUM(O27:Z27) -> 0 | BC27: =SUM(AA27:AL27) -> 0
A29: SaaS KPIs
A30: Gross Revenue Retention (GRR) | C30: =IFERROR((C15+C18+C19)/C15,1) -> 0 | D30: =IFERROR((D15+D18+D19)/D15,1) -> 0 | E30: =IFERROR((E15+E18+E19)/E15,1) -> 0 | F30: =IFERROR((F15+F18+F19)/F15,1) -> 0 | G30: =IFERROR((G15+G18+G19)/G15,1) -> 0 | H30: =IFERROR((H15+H18+H19)/H15,1) -> 0 | I30: =IFERROR((I15+I18+I19)/I15,1) -> 0 | J30: =IFERROR((J15+J18+J19)/J15,1) -> 0 | ... AL30: =IFERROR((AL15+AL18+AL19)/AL15,1) -> 0 | AN30: =AVERAGE(C30:E30) -> 0 | AO30: =AVERAGE(F30:H30) -> 0 | AP30: =AVERAGE(I30:K30) -> 0 | AQ30: =AVERAGE(L30:N30) -> 0 | AR30: =AVERAGE(O30:Q30) -> 0 | AS30: =AVERAGE(R30:T30) -> 0 | AT30: =AVERAGE(U30:W30) -> 0 | AU30: =AVERAGE(X30:Z30) -> 0 | AV30: =AVERAGE(AA30:AC30) -> 0 | AW30: =AVERAGE(AD30:AF30) -> 0 | AX30: =AVERAGE(AG30:AI30) -> 0 | AY30: =AVERAGE(AJ30:AL30) -> 0 | BA30: =AVERAGE(C30:N30) -> 0 | BB30: =AVERAGE(O30:Z30) -> 0 | BC30: =AVERAGE(AA30:AL30) -> 0
A31: Net Revenue Retention (NRR) | C31: =IFERROR((C15+C17+C18+C19)/C15,1) -> 0 | D31: =IFERROR((D15+D17+D18+D19)/D15,1) -> 0 | E31: =IFERROR((E15+E17+E18+E19)/E15,1) -> 0 | F31: =IFERROR((F15+F17+F18+F19)/F15,1) -> 0 | G31: =IFERROR((G15+G17+G18+G19)/G15,1) -> 0 | H31: =IFERROR((H15+H17+H18+H19)/H15,1) -> 0 | I31: =IFERROR((I15+I17+I18+I19)/I15,1) -> 0 | J31: =IFERROR((J15+J17+J18+J19)/J15,1) -> 0 | ... AL31: =IFERROR((AL15+AL17+AL18+AL19)/AL15,1) -> 0 | AN31: =AVERAGE(C31:E31) -> 0 | AO31: =AVERAGE(F31:H31) -> 0 | AP31: =AVERAGE(I31:K31) -> 0 | AQ31: =AVERAGE(L31:N31) -> 0 | AR31: =AVERAGE(O31:Q31) -> 0 | AS31: =AVERAGE(R31:T31) -> 0 | AT31: =AVERAGE(U31:W31) -> 0 | AU31: =AVERAGE(X31:Z31) -> 0 | AV31: =AVERAGE(AA31:AC31) -> 0 | AW31: =AVERAGE(AD31:AF31) -> 0 | AX31: =AVERAGE(AG31:AI31) -> 0 | AY31: =AVERAGE(AJ31:AL31) -> 0 | BA31: =AVERAGE(C31:N31) -> 0 | BB31: =AVERAGE(O31:Z31) -> 0 | BC31: =AVERAGE(AA31:AL31) -> 0
A32: MRR Growth (month over month) | C32: =IFERROR(C20/C15-1,0) -> 0 | D32: =IFERROR(D20/D15-1,0) -> 0 | E32: =IFERROR(E20/E15-1,0) -> 0 | F32: =IFERROR(F20/F15-1,0) -> 0 | G32: =IFERROR(G20/G15-1,0) -> 0 | H32: =IFERROR(H20/H15-1,0) -> 0 | I32: =IFERROR(I20/I15-1,0) -> 0 | J32: =IFERROR(J20/J15-1,0) -> 0 | ... AL32: =IFERROR(AL20/AL15-1,0) -> 0 | AN32: =AVERAGE(C32:E32) -> 0 | AO32: =AVERAGE(F32:H32) -> 0 | AP32: =AVERAGE(I32:K32) -> 0 | AQ32: =AVERAGE(L32:N32) -> 0 | AR32: =AVERAGE(O32:Q32) -> 0 | AS32: =AVERAGE(R32:T32) -> 0 | AT32: =AVERAGE(U32:W32) -> 0 | AU32: =AVERAGE(X32:Z32) -> 0 | AV32: =AVERAGE(AA32:AC32) -> 0 | AW32: =AVERAGE(AD32:AF32) -> 0 | AX32: =AVERAGE(AG32:AI32) -> 0 | AY32: =AVERAGE(AJ32:AL32) -> 0 | BA32: =AVERAGE(C32:N32) -> 0 | BB32: =AVERAGE(O32:Z32) -> 0 | BC32: =AVERAGE(AA32:AL32) -> 0

Sheet COGS & GM
A1: B2B SaaS + Usage — 3-Year Financial Model — COGS & GM
A2: Hosting, third-party data/API, payment processing, and Customer Success headcount.
A5: Line item | B5: Units / source | C5: Monthly (36 months) | AN5: Quarterly | BA5: Annual
C6: 46023 | D6: 46054 | E6: 46082 | F6: 46113 | G6: 46143 | H6: 46174 | I6: 46204 | J6: 46235 | K6: 46266 | L6: 46296 | M6: 46327 | N6: 46357 | O6: 46388 | P6: 46419 | Q6: 46447 | R6: 46478 | S6: 46508 | T6: 46539 | U6: 46569 | V6: 46600 | W6: 46631 | X6: 46661 | Y6: 46692 | Z6: 46722 | AA6: 46753 | AB6: 46784 | AC6: 46813 | AD6: 46844 | AE6: 46874 | AF6: 46905 | AG6: 46935 | AH6: 46966 | AI6: 46997 | AJ6: 47027 | AK6: 47058 | AL6: 47088 | AN6: Q1 | AO6: Q2 | AP6: Q3 | AQ6: Q4 | AR6: Q5 | AS6: Q6 | AT6: Q7 | AU6: Q8 | AV6: Q9 | AW6: Q10 | AX6: Q11 | AY6: Q12 | BA6: FY1 | BB6: FY2 | BC6: FY3
A7: COGS Components
A8: Hosting & Infrastructure | C8: ='Revenue'!C27*'Assumptions'!$F$27 -> 0 | D8: ='Revenue'!D27*'Assumptions'!$F$27 -> 0 | E8: ='Revenue'!E27*'Assumptions'!$F$27 -> 0 | F8: ='Revenue'!F27*'Assumptions'!$F$27 -> 0 | G8: ='Revenue'!G27*'Assumptions'!$F$27 -> 0 | H8: ='Revenue'!H27*'Assumptions'!$F$27 -> 0 | I8: ='Revenue'!I27*'Assumptions'!$F$27 -> 0 | J8: ='Revenue'!J27*'Assumptions'!$F$27 -> 0 | ... AL8: ='Revenue'!AL27*'Assumptions'!$F$27 -> 0 | AN8: =SUM(C8:E8) -> 0 | AO8: =SUM(F8:H8) -> 0 | AP8: =SUM(I8:K8) -> 0 | AQ8: =SUM(L8:N8) -> 0 | AR8: =SUM(O8:Q8) -> 0 | AS8: =SUM(R8:T8) -> 0 | AT8: =SUM(U8:W8) -> 0 | AU8: =SUM(X8:Z8) -> 0 | AV8: =SUM(AA8:AC8) -> 0 | AW8: =SUM(AD8:AF8) -> 0 | AX8: =SUM(AG8:AI8) -> 0 | AY8: =SUM(AJ8:AL8) -> 0 | BA8: =SUM(C8:N8) -> 0 | BB8: =SUM(O8:Z8) -> 0 | BC8: =SUM(AA8:AL8) -> 0
A9: Third-Party Data / APIs | C9: ='Revenue'!C27*'Assumptions'!$F$28 -> 0 | D9: ='Revenue'!D27*'Assumptions'!$F$28 -> 0 | E9: ='Revenue'!E27*'Assumptions'!$F$28 -> 0 | F9: ='Revenue'!F27*'Assumptions'!$F$28 -> 0 | G9: ='Revenue'!G27*'Assumptions'!$F$28 -> 0 | H9: ='Revenue'!H27*'Assumptions'!$F$28 -> 0 | I9: ='Revenue'!I27*'Assumptions'!$F$28 -> 0 | J9: ='Revenue'!J27*'Assumptions'!$F$28 -> 0 | ... AL9: ='Revenue'!AL27*'Assumptions'!$F$28 -> 0 | AN9: =SUM(C9:E9) -> 0 | AO9: =SUM(F9:H9) -> 0 | AP9: =SUM(I9:K9) -> 0 | AQ9: =SUM(L9:N9) -> 0 | AR9: =SUM(O9:Q9) -> 0 | AS9: =SUM(R9:T9) -> 0 | AT9: =SUM(U9:W9) -> 0 | AU9: =SUM(X9:Z9) -> 0 | AV9: =SUM(AA9:AC9) -> 0 | AW9: =SUM(AD9:AF9) -> 0 | AX9: =SUM(AG9:AI9) -> 0 | AY9: =SUM(AJ9:AL9) -> 0 | BA9: =SUM(C9:N9) -> 0 | BB9: =SUM(O9:Z9) -> 0 | BC9: =SUM(AA9:AL9) -> 0
A10: Payment Processing Fees | C10: ='Revenue'!C27*'Assumptions'!$F$29 -> 0 | D10: ='Revenue'!D27*'Assumptions'!$F$29 -> 0 | E10: ='Revenue'!E27*'Assumptions'!$F$29 -> 0 | F10: ='Revenue'!F27*'Assumptions'!$F$29 -> 0 | G10: ='Revenue'!G27*'Assumptions'!$F$29 -> 0 | H10: ='Revenue'!H27*'Assumptions'!$F$29 -> 0 | I10: ='Revenue'!I27*'Assumptions'!$F$29 -> 0 | J10: ='Revenue'!J27*'Assumptions'!$F$29 -> 0 | ... AL10: ='Revenue'!AL27*'Assumptions'!$F$29 -> 0 | AN10: =SUM(C10:E10) -> 0 | AO10: =SUM(F10:H10) -> 0 | AP10: =SUM(I10:K10) -> 0 | AQ10: =SUM(L10:N10) -> 0 | AR10: =SUM(O10:Q10) -> 0 | AS10: =SUM(R10:T10) -> 0 | AT10: =SUM(U10:W10) -> 0 | AU10: =SUM(X10:Z10) -> 0 | AV10: =SUM(AA10:AC10) -> 0 | AW10: =SUM(AD10:AF10) -> 0 | AX10: =SUM(AG10:AI10) -> 0 | AY10: =SUM(AJ10:AL10) -> 0 | BA10: =SUM(C10:N10) -> 0 | BB10: =SUM(O10:Z10) -> 0 | BC10: =SUM(AA10:AL10) -> 0
A11: Customer Success & Support (people) | C11: ='Headcount'!$C$23 -> 0 | D11: ='Headcount'!$D$23 -> 0 | E11: ='Headcount'!$E$23 -> 0 | F11: ='Headcount'!$F$23 -> 0 | G11: ='Headcount'!$G$23 -> 0 | H11: ='Headcount'!$H$23 -> 0 | I11: ='Headcount'!$I$23 -> 0 | J11: ='Headcount'!$J$23 -> 0 | K11: ='Headcount'!$K$23 -> 0 | L11: ='Headcount'!$L$23 -> 0 | M11: ='Headcount'!$M$23 -> 0 | N11: ='Headcount'!$N$23 -> 0 | O11: ='Headcount'!$O$23 -> 0 | P11: ='Headcount'!$P$23 -> 0 | Q11: ='Headcount'!$Q$23 -> 0 | R11: ='Headcount'!$R$23 -> 0 | S11: ='Headcount'!$S$23 -> 0 | T11: ='Headcount'!$T$23 -> 0 | U11: ='Headcount'!$U$23 -> 0 | V11: ='Headcount'!$V$23 -> 0 | W11: ='Headcount'!$W$23 -> 0 | X11: ='Headcount'!$X$23 -> 0 | Y11: ='Headcount'!$Y$23 -> 0 | Z11: ='Headcount'!$Z$23 -> 0 | AA11: ='Headcount'!$AA$23 -> 0 | AB11: ='Headcount'!$AB$23 -> 0 | AC11: ='Headcount'!$AC$23 -> 0 | AD11: ='Headcount'!$AD$23 -> 0 | AE11: ='Headcount'!$AE$23 -> 0 | AF11: ='Headcount'!$AF$23 -> 0 | AG11: ='Headcount'!$AG$23 -> 0 | AH11: ='Headcount'!$AH$23 -> 0 | AI11: ='Headcount'!$AI$23 -> 0 | AJ11: ='Headcount'!$AJ$23 -> 0 | AK11: ='Headcount'!$AK$23 -> 0 | AL11: ='Headcount'!$AL$23 -> 0 | AN11: =SUM(C11:E11) -> 0 | AO11: =SUM(F11:H11) -> 0 | AP11: =SUM(I11:K11) -> 0 | AQ11: =SUM(L11:N11) -> 0 | AR11: =SUM(O11:Q11) -> 0 | AS11: =SUM(R11:T11) -> 0 | AT11: =SUM(U11:W11) -> 0 | AU11: =SUM(X11:Z11) -> 0 | AV11: =SUM(AA11:AC11) -> 0 | AW11: =SUM(AD11:AF11) -> 0 | AX11: =SUM(AG11:AI11) -> 0 | AY11: =SUM(AJ11:AL11) -> 0 | BA11: =SUM(C11:N11) -> 0 | BB11: =SUM(O11:Z11) -> 0 | BC11: =SUM(AA11:AL11) -> 0
A12: Total COGS | C12: =C8+C9+C10+C11 -> 0 | D12: =D8+D9+D10+D11 -> 0 | E12: =E8+E9+E10+E11 -> 0 | F12: =F8+F9+F10+F11 -> 0 | G12: =G8+G9+G10+G11 -> 0 | H12: =H8+H9+H10+H11 -> 0 | I12: =I8+I9+I10+I11 -> 0 | J12: =J8+J9+J10+J11 -> 0 | ... AL12: =AL8+AL9+AL10+AL11 -> 0 | AN12: =SUM(C12:E12) -> 0 | AO12: =SUM(F12:H12) -> 0 | AP12: =SUM(I12:K12) -> 0 | AQ12: =SUM(L12:N12) -> 0 | AR12: =SUM(O12:Q12) -> 0 | AS12: =SUM(R12:T12) -> 0 | AT12: =SUM(U12:W12) -> 0 | AU12: =SUM(X12:Z12) -> 0 | AV12: =SUM(AA12:AC12) -> 0 | AW12: =SUM(AD12:AF12) -> 0 | AX12: =SUM(AG12:AI12) -> 0 | AY12: =SUM(AJ12:AL12) -> 0 | BA12: =SUM(C12:N12) -> 0 | BB12: =SUM(O12:Z12) -> 0 | BC12: =SUM(AA12:AL12) -> 0
A14: Gross Profit
A15: Gross Profit | C15: ='Revenue'!C27-C12 -> 0 | D15: ='Revenue'!D27-D12 -> 0 | E15: ='Revenue'!E27-E12 -> 0 | F15: ='Revenue'!F27-F12 -> 0 | G15: ='Revenue'!G27-G12 -> 0 | H15: ='Revenue'!H27-H12 -> 0 | I15: ='Revenue'!I27-I12 -> 0 | J15: ='Revenue'!J27-J12 -> 0 | ... AL15: ='Revenue'!AL27-AL12 -> 0 | AN15: =SUM(C15:E15) -> 0 | AO15: =SUM(F15:H15) -> 0 | AP15: =SUM(I15:K15) -> 0 | AQ15: =SUM(L15:N15) -> 0 | AR15: =SUM(O15:Q15) -> 0 | AS15: =SUM(R15:T15) -> 0 | AT15: =SUM(U15:W15) -> 0 | AU15: =SUM(X15:Z15) -> 0 | AV15: =SUM(AA15:AC15) -> 0 | AW15: =SUM(AD15:AF15) -> 0 | AX15: =SUM(AG15:AI15) -> 0 | AY15: =SUM(AJ15:AL15) -> 0 | BA15: =SUM(C15:N15) -> 0 | BB15: =SUM(O15:Z15) -> 0 | BC15: =SUM(AA15:AL15) -> 0
A16: Gross Margin % | C16: =IFERROR(C15/'Revenue'!C27,0) -> 0 | D16: =IFERROR(D15/'Revenue'!D27,0) -> 0 | E16: =IFERROR(E15/'Revenue'!E27,0) -> 0 | F16: =IFERROR(F15/'Revenue'!F27,0) -> 0 | G16: =IFERROR(G15/'Revenue'!G27,0) -> 0 | H16: =IFERROR(H15/'Revenue'!H27,0) -> 0 | I16: =IFERROR(I15/'Revenue'!I27,0) -> 0 | J16: =IFERROR(J15/'Revenue'!J27,0) -> 0 | ... AL16: =IFERROR(AL15/'Revenue'!AL27,0) -> 0 | AN16: =AVERAGE(C16:E16) -> 0 | AO16: =AVERAGE(F16:H16) -> 0 | AP16: =AVERAGE(I16:K16) -> 0 | AQ16: =AVERAGE(L16:N16) -> 0 | AR16: =AVERAGE(O16:Q16) -> 0 | AS16: =AVERAGE(R16:T16) -> 0 | AT16: =AVERAGE(U16:W16) -> 0 | AU16: =AVERAGE(X16:Z16) -> 0 | AV16: =AVERAGE(AA16:AC16) -> 0 | AW16: =AVERAGE(AD16:AF16) -> 0 | AX16: =AVERAGE(AG16:AI16) -> 0 | AY16: =AVERAGE(AJ16:AL16) -> 0 | BA16: =AVERAGE(C16:N16) -> 0 | BB16: =AVERAGE(O16:Z16) -> 0 | BC16: =AVERAGE(AA16:AL16) -> 0

Sheet Opex
A1: B2B SaaS + Usage — 3-Year Financial Model — Opex
A2: Operating expenses by department — headcount cost plus program spend.
A5: Line item | B5: Units / source | C5: Monthly (36 months) | AN5: Quarterly | BA5: Annual
C6: 46023 | D6: 46054 | E6: 46082 | F6: 46113 | G6: 46143 | H6: 46174 | I6: 46204 | J6: 46235 | K6: 46266 | L6: 46296 | M6: 46327 | N6: 46357 | O6: 46388 | P6: 46419 | Q6: 46447 | R6: 46478 | S6: 46508 | T6: 46539 | U6: 46569 | V6: 46600 | W6: 46631 | X6: 46661 | Y6: 46692 | Z6: 46722 | AA6: 46753 | AB6: 46784 | AC6: 46813 | AD6: 46844 | AE6: 46874 | AF6: 46905 | AG6: 46935 | AH6: 46966 | AI6: 46997 | AJ6: 47027 | AK6: 47058 | AL6: 47088 | AN6: Q1 | AO6: Q2 | AP6: Q3 | AQ6: Q4 | AR6: Q5 | AS6: Q6 | AT6: Q7 | AU6: Q8 | AV6: Q9 | AW6: Q10 | AX6: Q11 | AY6: Q12 | BA6: FY1 | BB6: FY2 | BC6: FY3
A7: Sales & Marketing
A8: Sales & Marketing — people cost | B8: Linked from Headcount tab | C8: ='Headcount'!$C$27 -> 0 | D8: ='Headcount'!$D$27 -> 0 | E8: ='Headcount'!$E$27 -> 0 | F8: ='Headcount'!$F$27 -> 0 | G8: ='Headcount'!$G$27 -> 0 | H8: ='Headcount'!$H$27 -> 0 | I8: ='Headcount'!$I$27 -> 0 | J8: ='Headcount'!$J$27 -> 0 | K8: ='Headcount'!$K$27 -> 0 | L8: ='Headcount'!$L$27 -> 0 | M8: ='Headcount'!$M$27 -> 0 | N8: ='Headcount'!$N$27 -> 0 | O8: ='Headcount'!$O$27 -> 0 | P8: ='Headcount'!$P$27 -> 0 | Q8: ='Headcount'!$Q$27 -> 0 | R8: ='Headcount'!$R$27 -> 0 | S8: ='Headcount'!$S$27 -> 0 | T8: ='Headcount'!$T$27 -> 0 | U8: ='Headcount'!$U$27 -> 0 | V8: ='Headcount'!$V$27 -> 0 | W8: ='Headcount'!$W$27 -> 0 | X8: ='Headcount'!$X$27 -> 0 | Y8: ='Headcount'!$Y$27 -> 0 | Z8: ='Headcount'!$Z$27 -> 0 | AA8: ='Headcount'!$AA$27 -> 0 | AB8: ='Headcount'!$AB$27 -> 0 | AC8: ='Headcount'!$AC$27 -> 0 | AD8: ='Headcount'!$AD$27 -> 0 | AE8: ='Headcount'!$AE$27 -> 0 | AF8: ='Headcount'!$AF$27 -> 0 | AG8: ='Headcount'!$AG$27 -> 0 | AH8: ='Headcount'!$AH$27 -> 0 | AI8: ='Headcount'!$AI$27 -> 0 | AJ8: ='Headcount'!$AJ$27 -> 0 | AK8: ='Headcount'!$AK$27 -> 0 | AL8: ='Headcount'!$AL$27 -> 0 | AN8: =SUM(C8:E8) -> 0 | AO8: =SUM(F8:H8) -> 0 | AP8: =SUM(I8:K8) -> 0 | AQ8: =SUM(L8:N8) -> 0 | AR8: =SUM(O8:Q8) -> 0 | AS8: =SUM(R8:T8) -> 0 | AT8: =SUM(U8:W8) -> 0 | AU8: =SUM(X8:Z8) -> 0 | AV8: =SUM(AA8:AC8) -> 0 | AW8: =SUM(AD8:AF8) -> 0 | AX8: =SUM(AG8:AI8) -> 0 | AY8: =SUM(AJ8:AL8) -> 0 | BA8: =SUM(C8:N8) -> 0 | BB8: =SUM(O8:Z8) -> 0 | BC8: =SUM(AA8:AL8) -> 0
A9: Sales Commissions | B9: 10% of newly booked ARR | C9: ='Revenue'!C16*12*'Assumptions'!$F$55 -> 0 | D9: ='Revenue'!D16*12*'Assumptions'!$F$55 -> 0 | E9: ='Revenue'!E16*12*'Assumptions'!$F$55 -> 0 | F9: ='Revenue'!F16*12*'Assumptions'!$F$55 -> 0 | G9: ='Revenue'!G16*12*'Assumptions'!$F$55 -> 0 | H9: ='Revenue'!H16*12*'Assumptions'!$F$55 -> 0 | I9: ='Revenue'!I16*12*'Assumptions'!$F$55 -> 0 | J9: ='Revenue'!J16*12*'Assumptions'!$F$55 -> 0 | ... AL9: ='Revenue'!AL16*12*'Assumptions'!$F$55 -> 0 | AN9: =SUM(C9:E9) -> 0 | AO9: =SUM(F9:H9) -> 0 | AP9: =SUM(I9:K9) -> 0 | AQ9: =SUM(L9:N9) -> 0 | AR9: =SUM(O9:Q9) -> 0 | AS9: =SUM(R9:T9) -> 0 | AT9: =SUM(U9:W9) -> 0 | AU9: =SUM(X9:Z9) -> 0 | AV9: =SUM(AA9:AC9) -> 0 | AW9: =SUM(AD9:AF9) -> 0 | AX9: =SUM(AG9:AI9) -> 0 | AY9: =SUM(AJ9:AL9) -> 0 | BA9: =SUM(C9:N9) -> 0 | BB9: =SUM(O9:Z9) -> 0 | BC9: =SUM(AA9:AL9) -> 0
A10: Marketing Programs | B10: % of total revenue | C10: ='Revenue'!C27*'Assumptions'!$F$56 -> 0 | D10: ='Revenue'!D27*'Assumptions'!$F$56 -> 0 | E10: ='Revenue'!E27*'Assumptions'!$F$56 -> 0 | F10: ='Revenue'!F27*'Assumptions'!$F$56 -> 0 | G10: ='Revenue'!G27*'Assumptions'!$F$56 -> 0 | H10: ='Revenue'!H27*'Assumptions'!$F$56 -> 0 | I10: ='Revenue'!I27*'Assumptions'!$F$56 -> 0 | J10: ='Revenue'!J27*'Assumptions'!$F$56 -> 0 | ... AL10: ='Revenue'!AL27*'Assumptions'!$F$56 -> 0 | AN10: =SUM(C10:E10) -> 0 | AO10: =SUM(F10:H10) -> 0 | AP10: =SUM(I10:K10) -> 0 | AQ10: =SUM(L10:N10) -> 0 | AR10: =SUM(O10:Q10) -> 0 | AS10: =SUM(R10:T10) -> 0 | AT10: =SUM(U10:W10) -> 0 | AU10: =SUM(X10:Z10) -> 0 | AV10: =SUM(AA10:AC10) -> 0 | AW10: =SUM(AD10:AF10) -> 0 | AX10: =SUM(AG10:AI10) -> 0 | AY10: =SUM(AJ10:AL10) -> 0 | BA10: =SUM(C10:N10) -> 0 | BB10: =SUM(O10:Z10) -> 0 | BC10: =SUM(AA10:AL10) -> 0
A11: Total Sales & Marketing | C11: =C8+C9+C10 -> 0 | D11: =D8+D9+D10 -> 0 | E11: =E8+E9+E10 -> 0 | F11: =F8+F9+F10 -> 0 | G11: =G8+G9+G10 -> 0 | H11: =H8+H9+H10 -> 0 | I11: =I8+I9+I10 -> 0 | J11: =J8+J9+J10 -> 0 | ... AL11: =AL8+AL9+AL10 -> 0 | AN11: =SUM(C11:E11) -> 0 | AO11: =SUM(F11:H11) -> 0 | AP11: =SUM(I11:K11) -> 0 | AQ11: =SUM(L11:N11) -> 0 | AR11: =SUM(O11:Q11) -> 0 | AS11: =SUM(R11:T11) -> 0 | AT11: =SUM(U11:W11) -> 0 | AU11: =SUM(X11:Z11) -> 0 | AV11: =SUM(AA11:AC11) -> 0 | AW11: =SUM(AD11:AF11) -> 0 | AX11: =SUM(AG11:AI11) -> 0 | AY11: =SUM(AJ11:AL11) -> 0 | BA11: =SUM(C11:N11) -> 0 | BB11: =SUM(O11:Z11) -> 0 | BC11: =SUM(AA11:AL11) -> 0
A13: R&D / Engineering
A14: R&D / Engineering — people cost | B14: Linked from Headcount tab | C14: ='Headcount'!$C$26 -> 0 | D14: ='Headcount'!$D$26 -> 0 | E14: ='Headcount'!$E$26 -> 0 | F14: ='Headcount'!$F$26 -> 0 | G14: ='Headcount'!$G$26 -> 0 | H14: ='Headcount'!$H$26 -> 0 | I14: ='Headcount'!$I$26 -> 0 | J14: ='Headcount'!$J$26 -> 0 | K14: ='Headcount'!$K$26 -> 0 | L14: ='Headcount'!$L$26 -> 0 | M14: ='Headcount'!$M$26 -> 0 | N14: ='Headcount'!$N$26 -> 0 | O14: ='Headcount'!$O$26 -> 0 | P14: ='Headcount'!$P$26 -> 0 | Q14: ='Headcount'!$Q$26 -> 0 | R14: ='Headcount'!$R$26 -> 0 | S14: ='Headcount'!$S$26 -> 0 | T14: ='Headcount'!$T$26 -> 0 | U14: ='Headcount'!$U$26 -> 0 | V14: ='Headcount'!$V$26 -> 0 | W14: ='Headcount'!$W$26 -> 0 | X14: ='Headcount'!$X$26 -> 0 | Y14: ='Headcount'!$Y$26 -> 0 | Z14: ='Headcount'!$Z$26 -> 0 | AA14: ='Headcount'!$AA$26 -> 0 | AB14: ='Headcount'!$AB$26 -> 0 | AC14: ='Headcount'!$AC$26 -> 0 | AD14: ='Headcount'!$AD$26 -> 0 | AE14: ='Headcount'!$AE$26 -> 0 | AF14: ='Headcount'!$AF$26 -> 0 | AG14: ='Headcount'!$AG$26 -> 0 | AH14: ='Headcount'!$AH$26 -> 0 | AI14: ='Headcount'!$AI$26 -> 0 | AJ14: ='Headcount'!$AJ$26 -> 0 | AK14: ='Headcount'!$AK$26 -> 0 | AL14: ='Headcount'!$AL$26 -> 0 | AN14: =SUM(C14:E14) -> 0 | AO14: =SUM(F14:H14) -> 0 | AP14: =SUM(I14:K14) -> 0 | AQ14: =SUM(L14:N14) -> 0 | AR14: =SUM(O14:Q14) -> 0 | AS14: =SUM(R14:T14) -> 0 | AT14: =SUM(U14:W14) -> 0 | AU14: =SUM(X14:Z14) -> 0 | AV14: =SUM(AA14:AC14) -> 0 | AW14: =SUM(AD14:AF14) -> 0 | AX14: =SUM(AG14:AI14) -> 0 | AY14: =SUM(AJ14:AL14) -> 0 | BA14: =SUM(C14:N14) -> 0 | BB14: =SUM(O14:Z14) -> 0 | BC14: =SUM(AA14:AL14) -> 0
A15: Total R&D / Engineering | C15: =C14 -> 0 | D15: =D14 -> 0 | E15: =E14 -> 0 | F15: =F14 -> 0 | G15: =G14 -> 0 | H15: =H14 -> 0 | I15: =I14 -> 0 | J15: =J14 -> 0 | ... AL15: =AL14 -> 0 | AN15: =SUM(C15:E15) -> 0 | AO15: =SUM(F15:H15) -> 0 | AP15: =SUM(I15:K15) -> 0 | AQ15: =SUM(L15:N15) -> 0 | AR15: =SUM(O15:Q15) -> 0 | AS15: =SUM(R15:T15) -> 0 | AT15: =SUM(U15:W15) -> 0 | AU15: =SUM(X15:Z15) -> 0 | AV15: =SUM(AA15:AC15) -> 0 | AW15: =SUM(AD15:AF15) -> 0 | AX15: =SUM(AG15:AI15) -> 0 | AY15: =SUM(AJ15:AL15) -> 0 | BA15: =SUM(C15:N15) -> 0 | BB15: =SUM(O15:Z15) -> 0 | BC15: =SUM(AA15:AL15) -> 0
A17: General & Administrative
A18: General & Administrative — people cost | B18: Linked from Headcount tab | C18: ='Headcount'!$C$25 -> 0 | D18: ='Headcount'!$D$25 -> 0 | E18: ='Headcount'!$E$25 -> 0 | F18: ='Headcount'!$F$25 -> 0 | G18: ='Headcount'!$G$25 -> 0 | H18: ='Headcount'!$H$25 -> 0 | I18: ='Headcount'!$I$25 -> 0 | J18: ='Headcount'!$J$25 -> 0 | K18: ='Headcount'!$K$25 -> 0 | L18: ='Headcount'!$L$25 -> 0 | M18: ='Headcount'!$M$25 -> 0 | N18: ='Headcount'!$N$25 -> 0 | O18: ='Headcount'!$O$25 -> 0 | P18: ='Headcount'!$P$25 -> 0 | Q18: ='Headcount'!$Q$25 -> 0 | R18: ='Headcount'!$R$25 -> 0 | S18: ='Headcount'!$S$25 -> 0 | T18: ='Headcount'!$T$25 -> 0 | U18: ='Headcount'!$U$25 -> 0 | V18: ='Headcount'!$V$25 -> 0 | W18: ='Headcount'!$W$25 -> 0 | X18: ='Headcount'!$X$25 -> 0 | Y18: ='Headcount'!$Y$25 -> 0 | Z18: ='Headcount'!$Z$25 -> 0 | AA18: ='Headcount'!$AA$25 -> 0 | AB18: ='Headcount'!$AB$25 -> 0 | AC18: ='Headcount'!$AC$25 -> 0 | AD18: ='Headcount'!$AD$25 -> 0 | AE18: ='Headcount'!$AE$25 -> 0 | AF18: ='Headcount'!$AF$25 -> 0 | AG18: ='Headcount'!$AG$25 -> 0 | AH18: ='Headcount'!$AH$25 -> 0 | AI18: ='Headcount'!$AI$25 -> 0 | AJ18: ='Headcount'!$AJ$25 -> 0 | AK18: ='Headcount'!$AK$25 -> 0 | AL18: ='Headcount'!$AL$25 -> 0 | AN18: =SUM(C18:E18) -> 0 | AO18: =SUM(F18:H18) -> 0 | AP18: =SUM(I18:K18) -> 0 | AQ18: =SUM(L18:N18) -> 0 | AR18: =SUM(O18:Q18) -> 0 | AS18: =SUM(R18:T18) -> 0 | AT18: =SUM(U18:W18) -> 0 | AU18: =SUM(X18:Z18) -> 0 | AV18: =SUM(AA18:AC18) -> 0 | AW18: =SUM(AD18:AF18) -> 0 | AX18: =SUM(AG18:AI18) -> 0 | AY18: =SUM(AJ18:AL18) -> 0 | BA18: =SUM(C18:N18) -> 0 | BB18: =SUM(O18:Z18) -> 0 | BC18: =SUM(AA18:AL18) -> 0
A19: Software & Tools | B19: Fixed monthly | C19: ='Assumptions'!$F$57 -> 0 | D19: ='Assumptions'!$F$57 -> 0 | E19: ='Assumptions'!$F$57 -> 0 | F19: ='Assumptions'!$F$57 -> 0 | G19: ='Assumptions'!$F$57 -> 0 | H19: ='Assumptions'!$F$57 -> 0 | I19: ='Assumptions'!$F$57 -> 0 | J19: ='Assumptions'!$F$57 -> 0 | ... AL19: ='Assumptions'!$F$57 -> 0 | AN19: =SUM(C19:E19) -> 0 | AO19: =SUM(F19:H19) -> 0 | AP19: =SUM(I19:K19) -> 0 | AQ19: =SUM(L19:N19) -> 0 | AR19: =SUM(O19:Q19) -> 0 | AS19: =SUM(R19:T19) -> 0 | AT19: =SUM(U19:W19) -> 0 | AU19: =SUM(X19:Z19) -> 0 | AV19: =SUM(AA19:AC19) -> 0 | AW19: =SUM(AD19:AF19) -> 0 | AX19: =SUM(AG19:AI19) -> 0 | AY19: =SUM(AJ19:AL19) -> 0 | BA19: =SUM(C19:N19) -> 0 | BB19: =SUM(O19:Z19) -> 0 | BC19: =SUM(AA19:AL19) -> 0
A20: Facilities & Other | B20: Fixed monthly | C20: ='Assumptions'!$F$58 -> 0 | D20: ='Assumptions'!$F$58 -> 0 | E20: ='Assumptions'!$F$58 -> 0 | F20: ='Assumptions'!$F$58 -> 0 | G20: ='Assumptions'!$F$58 -> 0 | H20: ='Assumptions'!$F$58 -> 0 | I20: ='Assumptions'!$F$58 -> 0 | J20: ='Assumptions'!$F$58 -> 0 | ... AL20: ='Assumptions'!$F$58 -> 0 | AN20: =SUM(C20:E20) -> 0 | AO20: =SUM(F20:H20) -> 0 | AP20: =SUM(I20:K20) -> 0 | AQ20: =SUM(L20:N20) -> 0 | AR20: =SUM(O20:Q20) -> 0 | AS20: =SUM(R20:T20) -> 0 | AT20: =SUM(U20:W20) -> 0 | AU20: =SUM(X20:Z20) -> 0 | AV20: =SUM(AA20:AC20) -> 0 | AW20: =SUM(AD20:AF20) -> 0 | AX20: =SUM(AG20:AI20) -> 0 | AY20: =SUM(AJ20:AL20) -> 0 | BA20: =SUM(C20:N20) -> 0 | BB20: =SUM(O20:Z20) -> 0 | BC20: =SUM(AA20:AL20) -> 0
A21: Total General & Administrative | C21: =C18+C19+C20 -> 0 | D21: =D18+D19+D20 -> 0 | E21: =E18+E19+E20 -> 0 | F21: =F18+F19+F20 -> 0 | G21: =G18+G19+G20 -> 0 | H21: =H18+H19+H20 -> 0 | I21: =I18+I19+I20 -> 0 | J21: =J18+J19+J20 -> 0 | ... AL21: =AL18+AL19+AL20 -> 0 | AN21: =SUM(C21:E21) -> 0 | AO21: =SUM(F21:H21) -> 0 | AP21: =SUM(I21:K21) -> 0 | AQ21: =SUM(L21:N21) -> 0 | AR21: =SUM(O21:Q21) -> 0 | AS21: =SUM(R21:T21) -> 0 | AT21: =SUM(U21:W21) -> 0 | AU21: =SUM(X21:Z21) -> 0 | AV21: =SUM(AA21:AC21) -> 0 | AW21: =SUM(AD21:AF21) -> 0 | AX21: =SUM(AG21:AI21) -> 0 | AY21: =SUM(AJ21:AL21) -> 0 | BA21: =SUM(C21:N21) -> 0 | BB21: =SUM(O21:Z21) -> 0 | BC21: =SUM(AA21:AL21) -> 0
A23: Total Operating Expenses
A24: Total Opex | C24: =C11+C15+C21 -> 0 | D24: =D11+D15+D21 -> 0 | E24: =E11+E15+E21 -> 0 | F24: =F11+F15+F21 -> 0 | G24: =G11+G15+G21 -> 0 | H24: =H11+H15+H21 -> 0 | I24: =I11+I15+I21 -> 0 | J24: =J11+J15+J21 -> 0 | ... AL24: =AL11+AL15+AL21 -> 0 | AN24: =SUM(C24:E24) -> 0 | AO24: =SUM(F24:H24) -> 0 | AP24: =SUM(I24:K24) -> 0 | AQ24: =SUM(L24:N24) -> 0 | AR24: =SUM(O24:Q24) -> 0 | AS24: =SUM(R24:T24) -> 0 | AT24: =SUM(U24:W24) -> 0 | AU24: =SUM(X24:Z24) -> 0 | AV24: =SUM(AA24:AC24) -> 0 | AW24: =SUM(AD24:AF24) -> 0 | AX24: =SUM(AG24:AI24) -> 0 | AY24: =SUM(AJ24:AL24) -> 0 | BA24: =SUM(C24:N24) -> 0 | BB24: =SUM(O24:Z24) -> 0 | BC24: =SUM(AA24:AL24) -> 0

Sheet Working Capital
A1: B2B SaaS + Usage — 3-Year Financial Model — Working Capital
A2: Balance-sheet drivers: receivables, payables, deferred revenue, capex/depreciation, debt & equity financing.
A5: Line item | B5: Units / source | C5: Monthly (36 months) | AN5: Quarterly | BA5: Annual
C6: 46023 | D6: 46054 | E6: 46082 | F6: 46113 | G6: 46143 | H6: 46174 | I6: 46204 | J6: 46235 | K6: 46266 | L6: 46296 | M6: 46327 | N6: 46357 | O6: 46388 | P6: 46419 | Q6: 46447 | R6: 46478 | S6: 46508 | T6: 46539 | U6: 46569 | V6: 46600 | W6: 46631 | X6: 46661 | Y6: 46692 | Z6: 46722 | AA6: 46753 | AB6: 46784 | AC6: 46813 | AD6: 46844 | AE6: 46874 | AF6: 46905 | AG6: 46935 | AH6: 46966 | AI6: 46997 | AJ6: 47027 | AK6: 47058 | AL6: 47088 | AN6: Q1 | AO6: Q2 | AP6: Q3 | AQ6: Q4 | AR6: Q5 | AS6: Q6 | AT6: Q7 | AU6: Q8 | AV6: Q9 | AW6: Q10 | AX6: Q11 | AY6: Q12 | BA6: FY1 | BB6: FY2 | BC6: FY3
A7: Receivables, Payables & Deferred Revenue
A8: Accounts Receivable balance | B8: Revenue × DSO ÷ 30 | C8: ='Revenue'!C27*'Assumptions'!$F$61/30 -> 0 | D8: ='Revenue'!D27*'Assumptions'!$F$61/30 -> 0 | E8: ='Revenue'!E27*'Assumptions'!$F$61/30 -> 0 | F8: ='Revenue'!F27*'Assumptions'!$F$61/30 -> 0 | G8: ='Revenue'!G27*'Assumptions'!$F$61/30 -> 0 | H8: ='Revenue'!H27*'Assumptions'!$F$61/30 -> 0 | I8: ='Revenue'!I27*'Assumptions'!$F$61/30 -> 0 | J8: ='Revenue'!J27*'Assumptions'!$F$61/30 -> 0 | ... AL8: ='Revenue'!AL27*'Assumptions'!$F$61/30 -> 0 | AN8: =E8 -> 0 | AO8: =H8 -> 0 | AP8: =K8 -> 0 | AQ8: =N8 -> 0 | AR8: =Q8 -> 0 | AS8: =T8 -> 0 | AT8: =W8 -> 0 | AU8: =Z8 -> 0 | AV8: =AC8 -> 0 | AW8: =AF8 -> 0 | AX8: =AI8 -> 0 | AY8: =AL8 -> 0 | BA8: =N8 -> 0 | BB8: =Z8 -> 0 | BC8: =AL8 -> 0
A9: Accounts Payable balance | B9: (COGS + Opex) × DPO ÷ 30 | C9: =('COGS & GM'!C12+'Opex'!C24)*'Assumptions'!$F$62/30 -> 0 | D9: =('COGS & GM'!D12+'Opex'!D24)*'Assumptions'!$F$62/30 -> 0 | E9: =('COGS & GM'!E12+'Opex'!E24)*'Assumptions'!$F$62/30 -> 0 | F9: =('COGS & GM'!F12+'Opex'!F24)*'Assumptions'!$F$62/30 -> 0 | G9: =('COGS & GM'!G12+'Opex'!G24)*'Assumptions'!$F$62/30 -> 0 | H9: =('COGS & GM'!H12+'Opex'!H24)*'Assumptions'!$F$62/30 -> 0 | I9: =('COGS & GM'!I12+'Opex'!I24)*'Assumptions'!$F$62/30 -> 0 | J9: =('COGS & GM'!J12+'Opex'!J24)*'Assumptions'!$F$62/30 -> 0 | ... AL9: =('COGS & GM'!AL12+'Opex'!AL24)*'Assumptions'!$F$62/30 -> 0 | AN9: =E9 -> 0 | AO9: =H9 -> 0 | AP9: =K9 -> 0 | AQ9: =N9 -> 0 | AR9: =Q9 -> 0 | AS9: =T9 -> 0 | AT9: =W9 -> 0 | AU9: =Z9 -> 0 | AV9: =AC9 -> 0 | AW9: =AF9 -> 0 | AX9: =AI9 -> 0 | AY9: =AL9 -> 0 | BA9: =N9 -> 0 | BB9: =Z9 -> 0 | BC9: =AL9 -> 0
A10: Deferred Revenue balance | B10: Revenue × months collected in advance | C10: ='Revenue'!C27*'Assumptions'!$F$63 -> 0 | D10: ='Revenue'!D27*'Assumptions'!$F$63 -> 0 | E10: ='Revenue'!E27*'Assumptions'!$F$63 -> 0 | F10: ='Revenue'!F27*'Assumptions'!$F$63 -> 0 | G10: ='Revenue'!G27*'Assumptions'!$F$63 -> 0 | H10: ='Revenue'!H27*'Assumptions'!$F$63 -> 0 | I10: ='Revenue'!I27*'Assumptions'!$F$63 -> 0 | J10: ='Revenue'!J27*'Assumptions'!$F$63 -> 0 | ... AL10: ='Revenue'!AL27*'Assumptions'!$F$63 -> 0 | AN10: =E10 -> 0 | AO10: =H10 -> 0 | AP10: =K10 -> 0 | AQ10: =N10 -> 0 | AR10: =Q10 -> 0 | AS10: =T10 -> 0 | AT10: =W10 -> 0 | AU10: =Z10 -> 0 | AV10: =AC10 -> 0 | AW10: =AF10 -> 0 | AX10: =AI10 -> 0 | AY10: =AL10 -> 0 | BA10: =N10 -> 0 | BB10: =Z10 -> 0 | BC10: =AL10 -> 0
A11: Other Current Assets balance | B11: Revenue × assumption % (prepaid expenses, etc.) | C11: ='Revenue'!C27*'Assumptions'!$F$66 -> 0 | D11: ='Revenue'!D27*'Assumptions'!$F$66 -> 0 | E11: ='Revenue'!E27*'Assumptions'!$F$66 -> 0 | F11: ='Revenue'!F27*'Assumptions'!$F$66 -> 0 | G11: ='Revenue'!G27*'Assumptions'!$F$66 -> 0 | H11: ='Revenue'!H27*'Assumptions'!$F$66 -> 0 | I11: ='Revenue'!I27*'Assumptions'!$F$66 -> 0 | J11: ='Revenue'!J27*'Assumptions'!$F$66 -> 0 | ... AL11: ='Revenue'!AL27*'Assumptions'!$F$66 -> 0 | AN11: =E11 -> 0 | AO11: =H11 -> 0 | AP11: =K11 -> 0 | AQ11: =N11 -> 0 | AR11: =Q11 -> 0 | AS11: =T11 -> 0 | AT11: =W11 -> 0 | AU11: =Z11 -> 0 | AV11: =AC11 -> 0 | AW11: =AF11 -> 0 | AX11: =AI11 -> 0 | AY11: =AL11 -> 0 | BA11: =N11 -> 0 | BB11: =Z11 -> 0 | BC11: =AL11 -> 0
A12: Change in Accounts Receivable | C12: =C8 -> 0 | D12: =D8-C8 -> 0 | E12: =E8-D8 -> 0 | F12: =F8-E8 -> 0 | G12: =G8-F8 -> 0 | H12: =H8-G8 -> 0 | I12: =I8-H8 -> 0 | J12: =J8-I8 -> 0 | K12: =K8-J8 -> 0 | ... AL12: =AL8-AK8 -> 0 | AN12: =SUM(C12:E12) -> 0 | AO12: =SUM(F12:H12) -> 0 | AP12: =SUM(I12:K12) -> 0 | AQ12: =SUM(L12:N12) -> 0 | AR12: =SUM(O12:Q12) -> 0 | AS12: =SUM(R12:T12) -> 0 | AT12: =SUM(U12:W12) -> 0 | AU12: =SUM(X12:Z12) -> 0 | AV12: =SUM(AA12:AC12) -> 0 | AW12: =SUM(AD12:AF12) -> 0 | AX12: =SUM(AG12:AI12) -> 0 | AY12: =SUM(AJ12:AL12) -> 0 | BA12: =SUM(C12:N12) -> 0 | BB12: =SUM(O12:Z12) -> 0 | BC12: =SUM(AA12:AL12) -> 0
A13: Change in Accounts Payable | C13: =C9 -> 0 | D13: =D9-C9 -> 0 | E13: =E9-D9 -> 0 | F13: =F9-E9 -> 0 | G13: =G9-F9 -> 0 | H13: =H9-G9 -> 0 | I13: =I9-H9 -> 0 | J13: =J9-I9 -> 0 | K13: =K9-J9 -> 0 | ... AL13: =AL9-AK9 -> 0 | AN13: =SUM(C13:E13) -> 0 | AO13: =SUM(F13:H13) -> 0 | AP13: =SUM(I13:K13) -> 0 | AQ13: =SUM(L13:N13) -> 0 | AR13: =SUM(O13:Q13) -> 0 | AS13: =SUM(R13:T13) -> 0 | AT13: =SUM(U13:W13) -> 0 | AU13: =SUM(X13:Z13) -> 0 | AV13: =SUM(AA13:AC13) -> 0 | AW13: =SUM(AD13:AF13) -> 0 | AX13: =SUM(AG13:AI13) -> 0 | AY13: =SUM(AJ13:AL13) -> 0 | BA13: =SUM(C13:N13) -> 0 | BB13: =SUM(O13:Z13) -> 0 | BC13: =SUM(AA13:AL13) -> 0
A14: Change in Deferred Revenue | C14: =C10 -> 0 | D14: =D10-C10 -> 0 | E14: =E10-D10 -> 0 | F14: =F10-E10 -> 0 | G14: =G10-F10 -> 0 | H14: =H10-G10 -> 0 | I14: =I10-H10 -> 0 | J14: =J10-I10 -> 0 | K14: =K10-J10 -> 0 | ... AL14: =AL10-AK10 -> 0 | AN14: =SUM(C14:E14) -> 0 | AO14: =SUM(F14:H14) -> 0 | AP14: =SUM(I14:K14) -> 0 | AQ14: =SUM(L14:N14) -> 0 | AR14: =SUM(O14:Q14) -> 0 | AS14: =SUM(R14:T14) -> 0 | AT14: =SUM(U14:W14) -> 0 | AU14: =SUM(X14:Z14) -> 0 | AV14: =SUM(AA14:AC14) -> 0 | AW14: =SUM(AD14:AF14) -> 0 | AX14: =SUM(AG14:AI14) -> 0 | AY14: =SUM(AJ14:AL14) -> 0 | BA14: =SUM(C14:N14) -> 0 | BB14: =SUM(O14:Z14) -> 0 | BC14: =SUM(AA14:AL14) -> 0
A15: Change in Other Current Assets | C15: =C11 -> 0 | D15: =D11-C11 -> 0 | E15: =E11-D11 -> 0 | F15: =F11-E11 -> 0 | G15: =G11-F11 -> 0 | H15: =H11-G11 -> 0 | I15: =I11-H11 -> 0 | J15: =J11-I11 -> 0 | K15: =K11-J11 -> 0 | ... AL15: =AL11-AK11 -> 0 | AN15: =SUM(C15:E15) -> 0 | AO15: =SUM(F15:H15) -> 0 | AP15: =SUM(I15:K15) -> 0 | AQ15: =SUM(L15:N15) -> 0 | AR15: =SUM(O15:Q15) -> 0 | AS15: =SUM(R15:T15) -> 0 | AT15: =SUM(U15:W15) -> 0 | AU15: =SUM(X15:Z15) -> 0 | AV15: =SUM(AA15:AC15) -> 0 | AW15: =SUM(AD15:AF15) -> 0 | AX15: =SUM(AG15:AI15) -> 0 | AY15: =SUM(AJ15:AL15) -> 0 | BA15: =SUM(C15:N15) -> 0 | BB15: =SUM(O15:Z15) -> 0 | BC15: =SUM(AA15:AL15) -> 0
A17: Capex & Depreciation (PP&E)
A18: Capital expenditures | B18: Revenue × capex % of revenue | C18: ='Revenue'!C27*'Assumptions'!$F$64 -> 0 | D18: ='Revenue'!D27*'Assumptions'!$F$64 -> 0 | E18: ='Revenue'!E27*'Assumptions'!$F$64 -> 0 | F18: ='Revenue'!F27*'Assumptions'!$F$64 -> 0 | G18: ='Revenue'!G27*'Assumptions'!$F$64 -> 0 | H18: ='Revenue'!H27*'Assumptions'!$F$64 -> 0 | I18: ='Revenue'!I27*'Assumptions'!$F$64 -> 0 | J18: ='Revenue'!J27*'Assumptions'!$F$64 -> 0 | ... AL18: ='Revenue'!AL27*'Assumptions'!$F$64 -> 0 | AN18: =SUM(C18:E18) -> 0 | AO18: =SUM(F18:H18) -> 0 | AP18: =SUM(I18:K18) -> 0 | AQ18: =SUM(L18:N18) -> 0 | AR18: =SUM(O18:Q18) -> 0 | AS18: =SUM(R18:T18) -> 0 | AT18: =SUM(U18:W18) -> 0 | AU18: =SUM(X18:Z18) -> 0 | AV18: =SUM(AA18:AC18) -> 0 | AW18: =SUM(AD18:AF18) -> 0 | AX18: =SUM(AG18:AI18) -> 0 | AY18: =SUM(AJ18:AL18) -> 0 | BA18: =SUM(C18:N18) -> 0 | BB18: =SUM(O18:Z18) -> 0 | BC18: =SUM(AA18:AL18) -> 0
A19: Depreciation & amortization | B19: Straight-line over useful life; trailing-window formula | C19: =SUM(INDEX('Working Capital'!$C$18:$AL$18,1,MAX(1,1-ROUND('Assumptions'!$F$65,0)+1)):INDEX('Working Capital'!$C$18:$AL$18,1,1))/ROUND('Assumptions'!$F$65,0) -> 0 | D19: =SUM(INDEX('Working Capital'!$C$18:$AL$18,1,MAX(1,2-ROUND('Assumptions'!$F$65,0)+1)):INDEX('Working Capital'!$C$18:$AL$18,1,2))/ROUND('Assumptions'!$F$65,0) -> 0 | E19: =SUM(INDEX('Working Capital'!$C$18:$AL$18,1,MAX(1,3-ROUND('Assumptions'!$F$65,0)+1)):INDEX('Working Capital'!$C$18:$AL$18,1,3))/ROUND('Assumptions'!$F$65,0) -> 0 | F19: =SUM(INDEX('Working Capital'!$C$18:$AL$18,1,MAX(1,4-ROUND('Assumptions'!$F$65,0)+1)):INDEX('Working Capital'!$C$18:$AL$18,1,4))/ROUND('Assumptions'!$F$65,0) -> 0 | G19: =SUM(INDEX('Working Capital'!$C$18:$AL$18,1,MAX(1,5-ROUND('Assumptions'!$F$65,0)+1)):INDEX('Working Capital'!$C$18:$AL$18,1,5))/ROUND('Assumptions'!$F$65,0) -> 0 | H19: =SUM(INDEX('Working Capital'!$C$18:$AL$18,1,MAX(1,6-ROUND('Assumptions'!$F$65,0)+1)):INDEX('Working Capital'!$C$18:$AL$18,1,6))/ROUND('Assumptions'!$F$65,0) -> 0 | I19: =SUM(INDEX('Working Capital'!$C$18:$AL$18,1,MAX(1,7-ROUND('Assumptions'!$F$65,0)+1)):INDEX('Working Capital'!$C$18:$AL$18,1,7))/ROUND('Assumptions'!$F$65,0) -> 0 | J19: =SUM(INDEX('Working Capital'!$C$18:$AL$18,1,MAX(1,8-ROUND('Assumptions'!$F$65,0)+1)):INDEX('Working Capital'!$C$18:$AL$18,1,8))/ROUND('Assumptions'!$F$65,0) -> 0 | K19: =SUM(INDEX('Working Capital'!$C$18:$AL$18,1,MAX(1,9-ROUND('Assumptions'!$F$65,0)+1)):INDEX('Working Capital'!$C$18:$AL$18,1,9))/ROUND('Assumptions'!$F$65,0) -> 0 | L19: =SUM(INDEX('Working Capital'!$C$18:$AL$18,1,MAX(1,10-ROUND('Assumptions'!$F$65,0)+1)):INDEX('Working Capital'!$C$18:$AL$18,1,10))/ROUND('Assumptions'!$F$65,0) -> 0 | M19: =SUM(INDEX('Working Capital'!$C$18:$AL$18,1,MAX(1,11-ROUND('Assumptions'!$F$65,0)+1)):INDEX('Working Capital'!$C$18:$AL$18,1,11))/ROUND('Assumptions'!$F$65,0) -> 0 | N19: =SUM(INDEX('Working Capital'!$C$18:$AL$18,1,MAX(1,12-ROUND('Assumptions'!$F$65,0)+1)):INDEX('Working Capital'!$C$18:$AL$18,1,12))/ROUND('Assumptions'!$F$65,0) -> 0 | O19: =SUM(INDEX('Working Capital'!$C$18:$AL$18,1,MAX(1,13-ROUND('Assumptions'!$F$65,0)+1)):INDEX('Working Capital'!$C$18:$AL$18,1,13))/ROUND('Assumptions'!$F$65,0) -> 0 | P19: =SUM(INDEX('Working Capital'!$C$18:$AL$18,1,MAX(1,14-ROUND('Assumptions'!$F$65,0)+1)):INDEX('Working Capital'!$C$18:$AL$18,1,14))/ROUND('Assumptions'!$F$65,0) -> 0 | Q19: =SUM(INDEX('Working Capital'!$C$18:$AL$18,1,MAX(1,15-ROUND('Assumptions'!$F$65,0)+1)):INDEX('Working Capital'!$C$18:$AL$18,1,15))/ROUND('Assumptions'!$F$65,0) -> 0 | R19: =SUM(INDEX('Working Capital'!$C$18:$AL$18,1,MAX(1,16-ROUND('Assumptions'!$F$65,0)+1)):INDEX('Working Capital'!$C$18:$AL$18,1,16))/ROUND('Assumptions'!$F$65,0) -> 0 | S19: =SUM(INDEX('Working Capital'!$C$18:$AL$18,1,MAX(1,17-ROUND('Assumptions'!$F$65,0)+1)):INDEX('Working Capital'!$C$18:$AL$18,1,17))/ROUND('Assumptions'!$F$65,0) -> 0 | T19: =SUM(INDEX('Working Capital'!$C$18:$AL$18,1,MAX(1,18-ROUND('Assumptions'!$F$65,0)+1)):INDEX('Working Capital'!$C$18:$AL$18,1,18))/ROUND('Assumptions'!$F$65,0) -> 0 | U19: =SUM(INDEX('Working Capital'!$C$18:$AL$18,1,MAX(1,19-ROUND('Assumptions'!$F$65,0)+1)):INDEX('Working Capital'!$C$18:$AL$18,1,19))/ROUND('Assumptions'!$F$65,0) -> 0 | V19: =SUM(INDEX('Working Capital'!$C$18:$AL$18,1,MAX(1,20-ROUND('Assumptions'!$F$65,0)+1)):INDEX('Working Capital'!$C$18:$AL$18,1,20))/ROUND('Assumptions'!$F$65,0) -> 0 | W19: =SUM(INDEX('Working Capital'!$C$18:$AL$18,1,MAX(1,21-ROUND('Assumptions'!$F$65,0)+1)):INDEX('Working Capital'!$C$18:$AL$18,1,21))/ROUND('Assumptions'!$F$65,0) -> 0 | X19: =SUM(INDEX('Working Capital'!$C$18:$AL$18,1,MAX(1,22-ROUND('Assumptions'!$F$65,0)+1)):INDEX('Working Capital'!$C$18:$AL$18,1,22))/ROUND('Assumptions'!$F$65,0) -> 0 | Y19: =SUM(INDEX('Working Capital'!$C$18:$AL$18,1,MAX(1,23-ROUND('Assumptions'!$F$65,0)+1)):INDEX('Working Capital'!$C$18:$AL$18,1,23))/ROUND('Assumptions'!$F$65,0) -> 0 | Z19: =SUM(INDEX('Working Capital'!$C$18:$AL$18,1,MAX(1,24-ROUND('Assumptions'!$F$65,0)+1)):INDEX('Working Capital'!$C$18:$AL$18,1,24))/ROUND('Assumptions'!$F$65,0) -> 0 | AA19: =SUM(INDEX('Working Capital'!$C$18:$AL$18,1,MAX(1,25-ROUND('Assumptions'!$F$65,0)+1)):INDEX('Working Capital'!$C$18:$AL$18,1,25))/ROUND('Assumptions'!$F$65,0) -> 0 | AB19: =SUM(INDEX('Working Capital'!$C$18:$AL$18,1,MAX(1,26-ROUND('Assumptions'!$F$65,0)+1)):INDEX('Working Capital'!$C$18:$AL$18,1,26))/ROUND('Assumptions'!$F$65,0) -> 0 | AC19: =SUM(INDEX('Working Capital'!$C$18:$AL$18,1,MAX(1,27-ROUND('Assumptions'!$F$65,0)+1)):INDEX('Working Capital'!$C$18:$AL$18,1,27))/ROUND('Assumptions'!$F$65,0) -> 0 | AD19: =SUM(INDEX('Working Capital'!$C$18:$AL$18,1,MAX(1,28-ROUND('Assumptions'!$F$65,0)+1)):INDEX('Working Capital'!$C$18:$AL$18,1,28))/ROUND('Assumptions'!$F$65,0) -> 0 | AE19: =SUM(INDEX('Working Capital'!$C$18:$AL$18,1,MAX(1,29-ROUND('Assumptions'!$F$65,0)+1)):INDEX('Working Capital'!$C$18:$AL$18,1,29))/ROUND('Assumptions'!$F$65,0) -> 0 | AF19: =SUM(INDEX('Working Capital'!$C$18:$AL$18,1,MAX(1,30-ROUND('Assumptions'!$F$65,0)+1)):INDEX('Working Capital'!$C$18:$AL$18,1,30))/ROUND('Assumptions'!$F$65,0) -> 0 | AG19: =SUM(INDEX('Working Capital'!$C$18:$AL$18,1,MAX(1,31-ROUND('Assumptions'!$F$65,0)+1)):INDEX('Working Capital'!$C$18:$AL$18,1,31))/ROUND('Assumptions'!$F$65,0) -> 0 | AH19: =SUM(INDEX('Working Capital'!$C$18:$AL$18,1,MAX(1,32-ROUND('Assumptions'!$F$65,0)+1)):INDEX('Working Capital'!$C$18:$AL$18,1,32))/ROUND('Assumptions'!$F$65,0) -> 0 | AI19: =SUM(INDEX('Working Capital'!$C$18:$AL$18,1,MAX(1,33-ROUND('Assumptions'!$F$65,0)+1)):INDEX('Working Capital'!$C$18:$AL$18,1,33))/ROUND('Assumptions'!$F$65,0) -> 0 | AJ19: =SUM(INDEX('Working Capital'!$C$18:$AL$18,1,MAX(1,34-ROUND('Assumptions'!$F$65,0)+1)):INDEX('Working Capital'!$C$18:$AL$18,1,34))/ROUND('Assumptions'!$F$65,0) -> 0 | AK19: =SUM(INDEX('Working Capital'!$C$18:$AL$18,1,MAX(1,35-ROUND('Assumptions'!$F$65,0)+1)):INDEX('Working Capital'!$C$18:$AL$18,1,35))/ROUND('Assumptions'!$F$65,0) -> 0 | AL19: =SUM(INDEX('Working Capital'!$C$18:$AL$18,1,MAX(1,36-ROUND('Assumptions'!$F$65,0)+1)):INDEX('Working Capital'!$C$18:$AL$18,1,36))/ROUND('Assumptions'!$F$65,0) -> 0 | AN19: =SUM(C19:E19) -> 0 | AO19: =SUM(F19:H19) -> 0 | AP19: =SUM(I19:K19) -> 0 | AQ19: =SUM(L19:N19) -> 0 | AR19: =SUM(O19:Q19) -> 0 | AS19: =SUM(R19:T19) -> 0 | AT19: =SUM(U19:W19) -> 0 | AU19: =SUM(X19:Z19) -> 0 | AV19: =SUM(AA19:AC19) -> 0 | AW19: =SUM(AD19:AF19) -> 0 | AX19: =SUM(AG19:AI19) -> 0 | AY19: =SUM(AJ19:AL19) -> 0 | BA19: =SUM(C19:N19) -> 0 | BB19: =SUM(O19:Z19) -> 0 | BC19: =SUM(AA19:AL19) -> 0
A20: Net PP&E balance | C20: =C18-C19 -> 0 | D20: =C20+D18-D19 -> 0 | E20: =D20+E18-E19 -> 0 | F20: =E20+F18-F19 -> 0 | G20: =F20+G18-G19 -> 0 | H20: =G20+H18-H19 -> 0 | I20: =H20+I18-I19 -> 0 | J20: =I20+J18-J19 -> 0 | K20: =J20+K18-K19 -> 0 | ... AL20: =AK20+AL18-AL19 -> 0 | AN20: =E20 -> 0 | AO20: =H20 -> 0 | AP20: =K20 -> 0 | AQ20: =N20 -> 0 | AR20: =Q20 -> 0 | AS20: =T20 -> 0 | AT20: =W20 -> 0 | AU20: =Z20 -> 0 | AV20: =AC20 -> 0 | AW20: =AF20 -> 0 | AX20: =AI20 -> 0 | AY20: =AL20 -> 0 | BA20: =N20 -> 0 | BB20: =Z20 -> 0 | BC20: =AL20 -> 0
A22: Debt Schedule
A23: Debt draw | B23: One-time draw in month 13 | C23: =0 -> 0 | D23: =0 -> 0 | E23: =0 -> 0 | F23: =0 -> 0 | G23: =0 -> 0 | H23: =0 -> 0 | I23: =0 -> 0 | J23: =0 -> 0 | ... N23: =0 -> 0 | O23: ='Assumptions'!$F$68 -> 0 | P23: =0 -> 0 | Q23: =0 -> 0 | R23: =0 -> 0 | S23: =0 -> 0 | T23: =0 -> 0 | U23: =0 -> 0 | V23: =0 -> 0 | W23: =0 -> 0 | ... AL23: =0 -> 0 | AN23: =SUM(C23:E23) -> 0 | AO23: =SUM(F23:H23) -> 0 | AP23: =SUM(I23:K23) -> 0 | AQ23: =SUM(L23:N23) -> 0 | AR23: =SUM(O23:Q23) -> 0 | AS23: =SUM(R23:T23) -> 0 | AT23: =SUM(U23:W23) -> 0 | AU23: =SUM(X23:Z23) -> 0 | AV23: =SUM(AA23:AC23) -> 0 | AW23: =SUM(AD23:AF23) -> 0 | AX23: =SUM(AG23:AI23) -> 0 | AY23: =SUM(AJ23:AL23) -> 0 | BA23: =SUM(C23:N23) -> 0 | BB23: =SUM(O23:Z23) -> 0 | BC23: =SUM(AA23:AL23) -> 0
A24: Debt repayment | B24: Fixed $/month once balance exists, starting the assumed month | C24: =0 -> 0 | D24: =0 -> 0 | E24: =0 -> 0 | F24: =0 -> 0 | G24: =0 -> 0 | H24: =0 -> 0 | I24: =0 -> 0 | J24: =0 -> 0 | ... Z24: =0 -> 0 | AA24: =MIN(Z25,'Assumptions'!$F$69) -> 0 | AB24: =MIN(AA25,'Assumptions'!$F$69) -> 0 | AC24: =MIN(AB25,'Assumptions'!$F$69) -> 0 | AD24: =MIN(AC25,'Assumptions'!$F$69) -> 0 | AE24: =MIN(AD25,'Assumptions'!$F$69) -> 0 | AF24: =MIN(AE25,'Assumptions'!$F$69) -> 0 | AG24: =MIN(AF25,'Assumptions'!$F$69) -> 0 | AH24: =MIN(AG25,'Assumptions'!$F$69) -> 0 | ... AL24: =MIN(AK25,'Assumptions'!$F$69) -> 0 | AN24: =SUM(C24:E24) -> 0 | AO24: =SUM(F24:H24) -> 0 | AP24: =SUM(I24:K24) -> 0 | AQ24: =SUM(L24:N24) -> 0 | AR24: =SUM(O24:Q24) -> 0 | AS24: =SUM(R24:T24) -> 0 | AT24: =SUM(U24:W24) -> 0 | AU24: =SUM(X24:Z24) -> 0 | AV24: =SUM(AA24:AC24) -> 0 | AW24: =SUM(AD24:AF24) -> 0 | AX24: =SUM(AG24:AI24) -> 0 | AY24: =SUM(AJ24:AL24) -> 0 | BA24: =SUM(C24:N24) -> 0 | BB24: =SUM(O24:Z24) -> 0 | BC24: =SUM(AA24:AL24) -> 0
A25: Debt balance (ending) | B25: Prior balance + draw − repayment | C25: =C23-C24 -> 0 | D25: =C25+D23-D24 -> 0 | E25: =D25+E23-E24 -> 0 | F25: =E25+F23-F24 -> 0 | G25: =F25+G23-G24 -> 0 | H25: =G25+H23-H24 -> 0 | I25: =H25+I23-I24 -> 0 | J25: =I25+J23-J24 -> 0 | K25: =J25+K23-K24 -> 0 | ... AL25: =AK25+AL23-AL24 -> 0 | AN25: =E25 -> 0 | AO25: =H25 -> 0 | AP25: =K25 -> 0 | AQ25: =N25 -> 0 | AR25: =Q25 -> 0 | AS25: =T25 -> 0 | AT25: =W25 -> 0 | AU25: =Z25 -> 0 | AV25: =AC25 -> 0 | AW25: =AF25 -> 0 | AX25: =AI25 -> 0 | AY25: =AL25 -> 0 | BA25: =N25 -> 0 | BB25: =Z25 -> 0 | BC25: =AL25 -> 0
A26: Interest expense | B26: Prior month balance × annual rate ÷ 12 | C26: =C23*'Assumptions'!$F$67/12/2 -> 0 | D26: =C25*'Assumptions'!$F$67/12 -> 0 | E26: =D25*'Assumptions'!$F$67/12 -> 0 | F26: =E25*'Assumptions'!$F$67/12 -> 0 | G26: =F25*'Assumptions'!$F$67/12 -> 0 | H26: =G25*'Assumptions'!$F$67/12 -> 0 | I26: =H25*'Assumptions'!$F$67/12 -> 0 | J26: =I25*'Assumptions'!$F$67/12 -> 0 | K26: =J25*'Assumptions'!$F$67/12 -> 0 | ... AL26: =AK25*'Assumptions'!$F$67/12 -> 0 | AN26: =SUM(C26:E26) -> 0 | AO26: =SUM(F26:H26) -> 0 | AP26: =SUM(I26:K26) -> 0 | AQ26: =SUM(L26:N26) -> 0 | AR26: =SUM(O26:Q26) -> 0 | AS26: =SUM(R26:T26) -> 0 | AT26: =SUM(U26:W26) -> 0 | AU26: =SUM(X26:Z26) -> 0 | AV26: =SUM(AA26:AC26) -> 0 | AW26: =SUM(AD26:AF26) -> 0 | AX26: =SUM(AG26:AI26) -> 0 | AY26: =SUM(AJ26:AL26) -> 0 | BA26: =SUM(C26:N26) -> 0 | BB26: =SUM(O26:Z26) -> 0 | BC26: =SUM(AA26:AL26) -> 0
A28: Equity Financing
A29: Equity raised | B29: Series A in month 4; Series B in month 22 | C29: =0 -> 0 | D29: =0 -> 0 | E29: =0 -> 0 | F29: ='Assumptions'!$F$70 -> 0 | G29: =0 -> 0 | H29: =0 -> 0 | I29: =0 -> 0 | J29: =0 -> 0 | K29: =0 -> 0 | L29: =0 -> 0 | M29: =0 -> 0 | N29: =0 -> 0 | ... W29: =0 -> 0 | X29: ='Assumptions'!$F$71 -> 0 | Y29: =0 -> 0 | Z29: =0 -> 0 | AA29: =0 -> 0 | AB29: =0 -> 0 | AC29: =0 -> 0 | AD29: =0 -> 0 | AE29: =0 -> 0 | AF29: =0 -> 0 | ... AL29: =0 -> 0 | AN29: =SUM(C29:E29) -> 0 | AO29: =SUM(F29:H29) -> 0 | AP29: =SUM(I29:K29) -> 0 | AQ29: =SUM(L29:N29) -> 0 | AR29: =SUM(O29:Q29) -> 0 | AS29: =SUM(R29:T29) -> 0 | AT29: =SUM(U29:W29) -> 0 | AU29: =SUM(X29:Z29) -> 0 | AV29: =SUM(AA29:AC29) -> 0 | AW29: =SUM(AD29:AF29) -> 0 | AX29: =SUM(AG29:AI29) -> 0 | AY29: =SUM(AJ29:AL29) -> 0 | BA29: =SUM(C29:N29) -> 0 | BB29: =SUM(O29:Z29) -> 0 | BC29: =SUM(AA29:AL29) -> 0
A30: Cumulative paid-in capital | C30: =C29 -> 0 | D30: =C30+D29 -> 0 | E30: =D30+E29 -> 0 | F30: =E30+F29 -> 0 | G30: =F30+G29 -> 0 | H30: =G30+H29 -> 0 | I30: =H30+I29 -> 0 | J30: =I30+J29 -> 0 | K30: =J30+K29 -> 0 | ... AL30: =AK30+AL29 -> 0 | AN30: =E30 -> 0 | AO30: =H30 -> 0 | AP30: =K30 -> 0 | AQ30: =N30 -> 0 | AR30: =Q30 -> 0 | AS30: =T30 -> 0 | AT30: =W30 -> 0 | AU30: =Z30 -> 0 | AV30: =AC30 -> 0 | AW30: =AF30 -> 0 | AX30: =AI30 -> 0 | AY30: =AL30 -> 0 | BA30: =N30 -> 0 | BB30: =Z30 -> 0 | BC30: =AL30 -> 0

Sheet P&L
A1: B2B SaaS + Usage — 3-Year Financial Model — P&L
A2: Integrated income statement — every line links to Revenue, COGS & GM, Opex, or Working Capital.
A5: Line item | B5: Units / source | C5: Monthly (36 months) | AN5: Quarterly | BA5: Annual
C6: 46023 | D6: 46054 | E6: 46082 | F6: 46113 | G6: 46143 | H6: 46174 | I6: 46204 | J6: 46235 | K6: 46266 | L6: 46296 | M6: 46327 | N6: 46357 | O6: 46388 | P6: 46419 | Q6: 46447 | R6: 46478 | S6: 46508 | T6: 46539 | U6: 46569 | V6: 46600 | W6: 46631 | X6: 46661 | Y6: 46692 | Z6: 46722 | AA6: 46753 | AB6: 46784 | AC6: 46813 | AD6: 46844 | AE6: 46874 | AF6: 46905 | AG6: 46935 | AH6: 46966 | AI6: 46997 | AJ6: 47027 | AK6: 47058 | AL6: 47088 | AN6: Q1 | AO6: Q2 | AP6: Q3 | AQ6: Q4 | AR6: Q5 | AS6: Q6 | AT6: Q7 | AU6: Q8 | AV6: Q9 | AW6: Q10 | AX6: Q11 | AY6: Q12 | BA6: FY1 | BB6: FY2 | BC6: FY3
A7: Revenue | C7: ='Revenue'!$C$27 -> 0 | D7: ='Revenue'!$D$27 -> 0 | E7: ='Revenue'!$E$27 -> 0 | F7: ='Revenue'!$F$27 -> 0 | G7: ='Revenue'!$G$27 -> 0 | H7: ='Revenue'!$H$27 -> 0 | I7: ='Revenue'!$I$27 -> 0 | J7: ='Revenue'!$J$27 -> 0 | K7: ='Revenue'!$K$27 -> 0 | L7: ='Revenue'!$L$27 -> 0 | M7: ='Revenue'!$M$27 -> 0 | N7: ='Revenue'!$N$27 -> 0 | O7: ='Revenue'!$O$27 -> 0 | P7: ='Revenue'!$P$27 -> 0 | Q7: ='Revenue'!$Q$27 -> 0 | R7: ='Revenue'!$R$27 -> 0 | S7: ='Revenue'!$S$27 -> 0 | T7: ='Revenue'!$T$27 -> 0 | U7: ='Revenue'!$U$27 -> 0 | V7: ='Revenue'!$V$27 -> 0 | W7: ='Revenue'!$W$27 -> 0 | X7: ='Revenue'!$X$27 -> 0 | Y7: ='Revenue'!$Y$27 -> 0 | Z7: ='Revenue'!$Z$27 -> 0 | AA7: ='Revenue'!$AA$27 -> 0 | AB7: ='Revenue'!$AB$27 -> 0 | AC7: ='Revenue'!$AC$27 -> 0 | AD7: ='Revenue'!$AD$27 -> 0 | AE7: ='Revenue'!$AE$27 -> 0 | AF7: ='Revenue'!$AF$27 -> 0 | AG7: ='Revenue'!$AG$27 -> 0 | AH7: ='Revenue'!$AH$27 -> 0 | AI7: ='Revenue'!$AI$27 -> 0 | AJ7: ='Revenue'!$AJ$27 -> 0 | AK7: ='Revenue'!$AK$27 -> 0 | AL7: ='Revenue'!$AL$27 -> 0 | AN7: =SUM(C7:E7) -> 0 | AO7: =SUM(F7:H7) -> 0 | AP7: =SUM(I7:K7) -> 0 | AQ7: =SUM(L7:N7) -> 0 | AR7: =SUM(O7:Q7) -> 0 | AS7: =SUM(R7:T7) -> 0 | AT7: =SUM(U7:W7) -> 0 | AU7: =SUM(X7:Z7) -> 0 | AV7: =SUM(AA7:AC7) -> 0 | AW7: =SUM(AD7:AF7) -> 0 | AX7: =SUM(AG7:AI7) -> 0 | AY7: =SUM(AJ7:AL7) -> 0 | BA7: =SUM(C7:N7) -> 0 | BB7: =SUM(O7:Z7) -> 0 | BC7: =SUM(AA7:AL7) -> 0
A8: Cost of Goods Sold | C8: ='COGS & GM'!$C$12 -> 0 | D8: ='COGS & GM'!$D$12 -> 0 | E8: ='COGS & GM'!$E$12 -> 0 | F8: ='COGS & GM'!$F$12 -> 0 | G8: ='COGS & GM'!$G$12 -> 0 | H8: ='COGS & GM'!$H$12 -> 0 | I8: ='COGS & GM'!$I$12 -> 0 | J8: ='COGS & GM'!$J$12 -> 0 | K8: ='COGS & GM'!$K$12 -> 0 | L8: ='COGS & GM'!$L$12 -> 0 | M8: ='COGS & GM'!$M$12 -> 0 | N8: ='COGS & GM'!$N$12 -> 0 | O8: ='COGS & GM'!$O$12 -> 0 | P8: ='COGS & GM'!$P$12 -> 0 | Q8: ='COGS & GM'!$Q$12 -> 0 | R8: ='COGS & GM'!$R$12 -> 0 | S8: ='COGS & GM'!$S$12 -> 0 | T8: ='COGS & GM'!$T$12 -> 0 | U8: ='COGS & GM'!$U$12 -> 0 | V8: ='COGS & GM'!$V$12 -> 0 | W8: ='COGS & GM'!$W$12 -> 0 | X8: ='COGS & GM'!$X$12 -> 0 | Y8: ='COGS & GM'!$Y$12 -> 0 | Z8: ='COGS & GM'!$Z$12 -> 0 | AA8: ='COGS & GM'!$AA$12 -> 0 | AB8: ='COGS & GM'!$AB$12 -> 0 | AC8: ='COGS & GM'!$AC$12 -> 0 | AD8: ='COGS & GM'!$AD$12 -> 0 | AE8: ='COGS & GM'!$AE$12 -> 0 | AF8: ='COGS & GM'!$AF$12 -> 0 | AG8: ='COGS & GM'!$AG$12 -> 0 | AH8: ='COGS & GM'!$AH$12 -> 0 | AI8: ='COGS & GM'!$AI$12 -> 0 | AJ8: ='COGS & GM'!$AJ$12 -> 0 | AK8: ='COGS & GM'!$AK$12 -> 0 | AL8: ='COGS & GM'!$AL$12 -> 0 | AN8: =SUM(C8:E8) -> 0 | AO8: =SUM(F8:H8) -> 0 | AP8: =SUM(I8:K8) -> 0 | AQ8: =SUM(L8:N8) -> 0 | AR8: =SUM(O8:Q8) -> 0 | AS8: =SUM(R8:T8) -> 0 | AT8: =SUM(U8:W8) -> 0 | AU8: =SUM(X8:Z8) -> 0 | AV8: =SUM(AA8:AC8) -> 0 | AW8: =SUM(AD8:AF8) -> 0 | AX8: =SUM(AG8:AI8) -> 0 | AY8: =SUM(AJ8:AL8) -> 0 | BA8: =SUM(C8:N8) -> 0 | BB8: =SUM(O8:Z8) -> 0 | BC8: =SUM(AA8:AL8) -> 0
A9: Gross Profit | C9: =C7-C8 -> 0 | D9: =D7-D8 -> 0 | E9: =E7-E8 -> 0 | F9: =F7-F8 -> 0 | G9: =G7-G8 -> 0 | H9: =H7-H8 -> 0 | I9: =I7-I8 -> 0 | J9: =J7-J8 -> 0 | ... AL9: =AL7-AL8 -> 0 | AN9: =SUM(C9:E9) -> 0 | AO9: =SUM(F9:H9) -> 0 | AP9: =SUM(I9:K9) -> 0 | AQ9: =SUM(L9:N9) -> 0 | AR9: =SUM(O9:Q9) -> 0 | AS9: =SUM(R9:T9) -> 0 | AT9: =SUM(U9:W9) -> 0 | AU9: =SUM(X9:Z9) -> 0 | AV9: =SUM(AA9:AC9) -> 0 | AW9: =SUM(AD9:AF9) -> 0 | AX9: =SUM(AG9:AI9) -> 0 | AY9: =SUM(AJ9:AL9) -> 0 | BA9: =SUM(C9:N9) -> 0 | BB9: =SUM(O9:Z9) -> 0 | BC9: =SUM(AA9:AL9) -> 0
A10: Gross Margin % | C10: =IFERROR(C9/C7,0) -> 0 | D10: =IFERROR(D9/D7,0) -> 0 | E10: =IFERROR(E9/E7,0) -> 0 | F10: =IFERROR(F9/F7,0) -> 0 | G10: =IFERROR(G9/G7,0) -> 0 | H10: =IFERROR(H9/H7,0) -> 0 | I10: =IFERROR(I9/I7,0) -> 0 | J10: =IFERROR(J9/J7,0) -> 0 | ... AL10: =IFERROR(AL9/AL7,0) -> 0 | AN10: =AVERAGE(C10:E10) -> 0 | AO10: =AVERAGE(F10:H10) -> 0 | AP10: =AVERAGE(I10:K10) -> 0 | AQ10: =AVERAGE(L10:N10) -> 0 | AR10: =AVERAGE(O10:Q10) -> 0 | AS10: =AVERAGE(R10:T10) -> 0 | AT10: =AVERAGE(U10:W10) -> 0 | AU10: =AVERAGE(X10:Z10) -> 0 | AV10: =AVERAGE(AA10:AC10) -> 0 | AW10: =AVERAGE(AD10:AF10) -> 0 | AX10: =AVERAGE(AG10:AI10) -> 0 | AY10: =AVERAGE(AJ10:AL10) -> 0 | BA10: =AVERAGE(C10:N10) -> 0 | BB10: =AVERAGE(O10:Z10) -> 0 | BC10: =AVERAGE(AA10:AL10) -> 0
A12: Operating Expenses
A13: Sales & Marketing | C13: ='Opex'!$C$11 -> 0 | D13: ='Opex'!$D$11 -> 0 | E13: ='Opex'!$E$11 -> 0 | F13: ='Opex'!$F$11 -> 0 | G13: ='Opex'!$G$11 -> 0 | H13: ='Opex'!$H$11 -> 0 | I13: ='Opex'!$I$11 -> 0 | J13: ='Opex'!$J$11 -> 0 | K13: ='Opex'!$K$11 -> 0 | L13: ='Opex'!$L$11 -> 0 | M13: ='Opex'!$M$11 -> 0 | N13: ='Opex'!$N$11 -> 0 | O13: ='Opex'!$O$11 -> 0 | P13: ='Opex'!$P$11 -> 0 | Q13: ='Opex'!$Q$11 -> 0 | R13: ='Opex'!$R$11 -> 0 | S13: ='Opex'!$S$11 -> 0 | T13: ='Opex'!$T$11 -> 0 | U13: ='Opex'!$U$11 -> 0 | V13: ='Opex'!$V$11 -> 0 | W13: ='Opex'!$W$11 -> 0 | X13: ='Opex'!$X$11 -> 0 | Y13: ='Opex'!$Y$11 -> 0 | Z13: ='Opex'!$Z$11 -> 0 | AA13: ='Opex'!$AA$11 -> 0 | AB13: ='Opex'!$AB$11 -> 0 | AC13: ='Opex'!$AC$11 -> 0 | AD13: ='Opex'!$AD$11 -> 0 | AE13: ='Opex'!$AE$11 -> 0 | AF13: ='Opex'!$AF$11 -> 0 | AG13: ='Opex'!$AG$11 -> 0 | AH13: ='Opex'!$AH$11 -> 0 | AI13: ='Opex'!$AI$11 -> 0 | AJ13: ='Opex'!$AJ$11 -> 0 | AK13: ='Opex'!$AK$11 -> 0 | AL13: ='Opex'!$AL$11 -> 0 | AN13: =SUM(C13:E13) -> 0 | AO13: =SUM(F13:H13) -> 0 | AP13: =SUM(I13:K13) -> 0 | AQ13: =SUM(L13:N13) -> 0 | AR13: =SUM(O13:Q13) -> 0 | AS13: =SUM(R13:T13) -> 0 | AT13: =SUM(U13:W13) -> 0 | AU13: =SUM(X13:Z13) -> 0 | AV13: =SUM(AA13:AC13) -> 0 | AW13: =SUM(AD13:AF13) -> 0 | AX13: =SUM(AG13:AI13) -> 0 | AY13: =SUM(AJ13:AL13) -> 0 | BA13: =SUM(C13:N13) -> 0 | BB13: =SUM(O13:Z13) -> 0 | BC13: =SUM(AA13:AL13) -> 0
A14: R&D / Engineering | C14: ='Opex'!$C$15 -> 0 | D14: ='Opex'!$D$15 -> 0 | E14: ='Opex'!$E$15 -> 0 | F14: ='Opex'!$F$15 -> 0 | G14: ='Opex'!$G$15 -> 0 | H14: ='Opex'!$H$15 -> 0 | I14: ='Opex'!$I$15 -> 0 | J14: ='Opex'!$J$15 -> 0 | K14: ='Opex'!$K$15 -> 0 | L14: ='Opex'!$L$15 -> 0 | M14: ='Opex'!$M$15 -> 0 | N14: ='Opex'!$N$15 -> 0 | O14: ='Opex'!$O$15 -> 0 | P14: ='Opex'!$P$15 -> 0 | Q14: ='Opex'!$Q$15 -> 0 | R14: ='Opex'!$R$15 -> 0 | S14: ='Opex'!$S$15 -> 0 | T14: ='Opex'!$T$15 -> 0 | U14: ='Opex'!$U$15 -> 0 | V14: ='Opex'!$V$15 -> 0 | W14: ='Opex'!$W$15 -> 0 | X14: ='Opex'!$X$15 -> 0 | Y14: ='Opex'!$Y$15 -> 0 | Z14: ='Opex'!$Z$15 -> 0 | AA14: ='Opex'!$AA$15 -> 0 | AB14: ='Opex'!$AB$15 -> 0 | AC14: ='Opex'!$AC$15 -> 0 | AD14: ='Opex'!$AD$15 -> 0 | AE14: ='Opex'!$AE$15 -> 0 | AF14: ='Opex'!$AF$15 -> 0 | AG14: ='Opex'!$AG$15 -> 0 | AH14: ='Opex'!$AH$15 -> 0 | AI14: ='Opex'!$AI$15 -> 0 | AJ14: ='Opex'!$AJ$15 -> 0 | AK14: ='Opex'!$AK$15 -> 0 | AL14: ='Opex'!$AL$15 -> 0 | AN14: =SUM(C14:E14) -> 0 | AO14: =SUM(F14:H14) -> 0 | AP14: =SUM(I14:K14) -> 0 | AQ14: =SUM(L14:N14) -> 0 | AR14: =SUM(O14:Q14) -> 0 | AS14: =SUM(R14:T14) -> 0 | AT14: =SUM(U14:W14) -> 0 | AU14: =SUM(X14:Z14) -> 0 | AV14: =SUM(AA14:AC14) -> 0 | AW14: =SUM(AD14:AF14) -> 0 | AX14: =SUM(AG14:AI14) -> 0 | AY14: =SUM(AJ14:AL14) -> 0 | BA14: =SUM(C14:N14) -> 0 | BB14: =SUM(O14:Z14) -> 0 | BC14: =SUM(AA14:AL14) -> 0
A15: General & Administrative | C15: ='Opex'!$C$21 -> 0 | D15: ='Opex'!$D$21 -> 0 | E15: ='Opex'!$E$21 -> 0 | F15: ='Opex'!$F$21 -> 0 | G15: ='Opex'!$G$21 -> 0 | H15: ='Opex'!$H$21 -> 0 | I15: ='Opex'!$I$21 -> 0 | J15: ='Opex'!$J$21 -> 0 | K15: ='Opex'!$K$21 -> 0 | L15: ='Opex'!$L$21 -> 0 | M15: ='Opex'!$M$21 -> 0 | N15: ='Opex'!$N$21 -> 0 | O15: ='Opex'!$O$21 -> 0 | P15: ='Opex'!$P$21 -> 0 | Q15: ='Opex'!$Q$21 -> 0 | R15: ='Opex'!$R$21 -> 0 | S15: ='Opex'!$S$21 -> 0 | T15: ='Opex'!$T$21 -> 0 | U15: ='Opex'!$U$21 -> 0 | V15: ='Opex'!$V$21 -> 0 | W15: ='Opex'!$W$21 -> 0 | X15: ='Opex'!$X$21 -> 0 | Y15: ='Opex'!$Y$21 -> 0 | Z15: ='Opex'!$Z$21 -> 0 | AA15: ='Opex'!$AA$21 -> 0 | AB15: ='Opex'!$AB$21 -> 0 | AC15: ='Opex'!$AC$21 -> 0 | AD15: ='Opex'!$AD$21 -> 0 | AE15: ='Opex'!$AE$21 -> 0 | AF15: ='Opex'!$AF$21 -> 0 | AG15: ='Opex'!$AG$21 -> 0 | AH15: ='Opex'!$AH$21 -> 0 | AI15: ='Opex'!$AI$21 -> 0 | AJ15: ='Opex'!$AJ$21 -> 0 | AK15: ='Opex'!$AK$21 -> 0 | AL15: ='Opex'!$AL$21 -> 0 | AN15: =SUM(C15:E15) -> 0 | AO15: =SUM(F15:H15) -> 0 | AP15: =SUM(I15:K15) -> 0 | AQ15: =SUM(L15:N15) -> 0 | AR15: =SUM(O15:Q15) -> 0 | AS15: =SUM(R15:T15) -> 0 | AT15: =SUM(U15:W15) -> 0 | AU15: =SUM(X15:Z15) -> 0 | AV15: =SUM(AA15:AC15) -> 0 | AW15: =SUM(AD15:AF15) -> 0 | AX15: =SUM(AG15:AI15) -> 0 | AY15: =SUM(AJ15:AL15) -> 0 | BA15: =SUM(C15:N15) -> 0 | BB15: =SUM(O15:Z15) -> 0 | BC15: =SUM(AA15:AL15) -> 0
A16: Total Operating Expenses | C16: =C13+C14+C15 -> 0 | D16: =D13+D14+D15 -> 0 | E16: =E13+E14+E15 -> 0 | F16: =F13+F14+F15 -> 0 | G16: =G13+G14+G15 -> 0 | H16: =H13+H14+H15 -> 0 | I16: =I13+I14+I15 -> 0 | J16: =J13+J14+J15 -> 0 | ... AL16: =AL13+AL14+AL15 -> 0 | AN16: =SUM(C16:E16) -> 0 | AO16: =SUM(F16:H16) -> 0 | AP16: =SUM(I16:K16) -> 0 | AQ16: =SUM(L16:N16) -> 0 | AR16: =SUM(O16:Q16) -> 0 | AS16: =SUM(R16:T16) -> 0 | AT16: =SUM(U16:W16) -> 0 | AU16: =SUM(X16:Z16) -> 0 | AV16: =SUM(AA16:AC16) -> 0 | AW16: =SUM(AD16:AF16) -> 0 | AX16: =SUM(AG16:AI16) -> 0 | AY16: =SUM(AJ16:AL16) -> 0 | BA16: =SUM(C16:N16) -> 0 | BB16: =SUM(O16:Z16) -> 0 | BC16: =SUM(AA16:AL16) -> 0
A18: EBITDA | C18: =C9-C16 -> 0 | D18: =D9-D16 -> 0 | E18: =E9-E16 -> 0 | F18: =F9-F16 -> 0 | G18: =G9-G16 -> 0 | H18: =H9-H16 -> 0 | I18: =I9-I16 -> 0 | J18: =J9-J16 -> 0 | ... AL18: =AL9-AL16 -> 0 | AN18: =SUM(C18:E18) -> 0 | AO18: =SUM(F18:H18) -> 0 | AP18: =SUM(I18:K18) -> 0 | AQ18: =SUM(L18:N18) -> 0 | AR18: =SUM(O18:Q18) -> 0 | AS18: =SUM(R18:T18) -> 0 | AT18: =SUM(U18:W18) -> 0 | AU18: =SUM(X18:Z18) -> 0 | AV18: =SUM(AA18:AC18) -> 0 | AW18: =SUM(AD18:AF18) -> 0 | AX18: =SUM(AG18:AI18) -> 0 | AY18: =SUM(AJ18:AL18) -> 0 | BA18: =SUM(C18:N18) -> 0 | BB18: =SUM(O18:Z18) -> 0 | BC18: =SUM(AA18:AL18) -> 0
A19: Depreciation & Amortization | C19: ='Working Capital'!$C$19 -> 0 | D19: ='Working Capital'!$D$19 -> 0 | E19: ='Working Capital'!$E$19 -> 0 | F19: ='Working Capital'!$F$19 -> 0 | G19: ='Working Capital'!$G$19 -> 0 | H19: ='Working Capital'!$H$19 -> 0 | I19: ='Working Capital'!$I$19 -> 0 | J19: ='Working Capital'!$J$19 -> 0 | K19: ='Working Capital'!$K$19 -> 0 | L19: ='Working Capital'!$L$19 -> 0 | M19: ='Working Capital'!$M$19 -> 0 | N19: ='Working Capital'!$N$19 -> 0 | O19: ='Working Capital'!$O$19 -> 0 | P19: ='Working Capital'!$P$19 -> 0 | Q19: ='Working Capital'!$Q$19 -> 0 | R19: ='Working Capital'!$R$19 -> 0 | S19: ='Working Capital'!$S$19 -> 0 | T19: ='Working Capital'!$T$19 -> 0 | U19: ='Working Capital'!$U$19 -> 0 | V19: ='Working Capital'!$V$19 -> 0 | W19: ='Working Capital'!$W$19 -> 0 | X19: ='Working Capital'!$X$19 -> 0 | Y19: ='Working Capital'!$Y$19 -> 0 | Z19: ='Working Capital'!$Z$19 -> 0 | AA19: ='Working Capital'!$AA$19 -> 0 | AB19: ='Working Capital'!$AB$19 -> 0 | AC19: ='Working Capital'!$AC$19 -> 0 | AD19: ='Working Capital'!$AD$19 -> 0 | AE19: ='Working Capital'!$AE$19 -> 0 | AF19: ='Working Capital'!$AF$19 -> 0 | AG19: ='Working Capital'!$AG$19 -> 0 | AH19: ='Working Capital'!$AH$19 -> 0 | AI19: ='Working Capital'!$AI$19 -> 0 | AJ19: ='Working Capital'!$AJ$19 -> 0 | AK19: ='Working Capital'!$AK$19 -> 0 | AL19: ='Working Capital'!$AL$19 -> 0 | AN19: =SUM(C19:E19) -> 0 | AO19: =SUM(F19:H19) -> 0 | AP19: =SUM(I19:K19) -> 0 | AQ19: =SUM(L19:N19) -> 0 | AR19: =SUM(O19:Q19) -> 0 | AS19: =SUM(R19:T19) -> 0 | AT19: =SUM(U19:W19) -> 0 | AU19: =SUM(X19:Z19) -> 0 | AV19: =SUM(AA19:AC19) -> 0 | AW19: =SUM(AD19:AF19) -> 0 | AX19: =SUM(AG19:AI19) -> 0 | AY19: =SUM(AJ19:AL19) -> 0 | BA19: =SUM(C19:N19) -> 0 | BB19: =SUM(O19:Z19) -> 0 | BC19: =SUM(AA19:AL19) -> 0
A20: EBIT (Operating Income) | C20: =C18-C19 -> 0 | D20: =D18-D19 -> 0 | E20: =E18-E19 -> 0 | F20: =F18-F19 -> 0 | G20: =G18-G19 -> 0 | H20: =H18-H19 -> 0 | I20: =I18-I19 -> 0 | J20: =J18-J19 -> 0 | ... AL20: =AL18-AL19 -> 0 | AN20: =SUM(C20:E20) -> 0 | AO20: =SUM(F20:H20) -> 0 | AP20: =SUM(I20:K20) -> 0 | AQ20: =SUM(L20:N20) -> 0 | AR20: =SUM(O20:Q20) -> 0 | AS20: =SUM(R20:T20) -> 0 | AT20: =SUM(U20:W20) -> 0 | AU20: =SUM(X20:Z20) -> 0 | AV20: =SUM(AA20:AC20) -> 0 | AW20: =SUM(AD20:AF20) -> 0 | AX20: =SUM(AG20:AI20) -> 0 | AY20: =SUM(AJ20:AL20) -> 0 | BA20: =SUM(C20:N20) -> 0 | BB20: =SUM(O20:Z20) -> 0 | BC20: =SUM(AA20:AL20) -> 0
A21: Interest Expense | C21: ='Working Capital'!$C$26 -> 0 | D21: ='Working Capital'!$D$26 -> 0 | E21: ='Working Capital'!$E$26 -> 0 | F21: ='Working Capital'!$F$26 -> 0 | G21: ='Working Capital'!$G$26 -> 0 | H21: ='Working Capital'!$H$26 -> 0 | I21: ='Working Capital'!$I$26 -> 0 | J21: ='Working Capital'!$J$26 -> 0 | K21: ='Working Capital'!$K$26 -> 0 | L21: ='Working Capital'!$L$26 -> 0 | M21: ='Working Capital'!$M$26 -> 0 | N21: ='Working Capital'!$N$26 -> 0 | O21: ='Working Capital'!$O$26 -> 0 | P21: ='Working Capital'!$P$26 -> 0 | Q21: ='Working Capital'!$Q$26 -> 0 | R21: ='Working Capital'!$R$26 -> 0 | S21: ='Working Capital'!$S$26 -> 0 | T21: ='Working Capital'!$T$26 -> 0 | U21: ='Working Capital'!$U$26 -> 0 | V21: ='Working Capital'!$V$26 -> 0 | W21: ='Working Capital'!$W$26 -> 0 | X21: ='Working Capital'!$X$26 -> 0 | Y21: ='Working Capital'!$Y$26 -> 0 | Z21: ='Working Capital'!$Z$26 -> 0 | AA21: ='Working Capital'!$AA$26 -> 0 | AB21: ='Working Capital'!$AB$26 -> 0 | AC21: ='Working Capital'!$AC$26 -> 0 | AD21: ='Working Capital'!$AD$26 -> 0 | AE21: ='Working Capital'!$AE$26 -> 0 | AF21: ='Working Capital'!$AF$26 -> 0 | AG21: ='Working Capital'!$AG$26 -> 0 | AH21: ='Working Capital'!$AH$26 -> 0 | AI21: ='Working Capital'!$AI$26 -> 0 | AJ21: ='Working Capital'!$AJ$26 -> 0 | AK21: ='Working Capital'!$AK$26 -> 0 | AL21: ='Working Capital'!$AL$26 -> 0 | AN21: =SUM(C21:E21) -> 0 | AO21: =SUM(F21:H21) -> 0 | AP21: =SUM(I21:K21) -> 0 | AQ21: =SUM(L21:N21) -> 0 | AR21: =SUM(O21:Q21) -> 0 | AS21: =SUM(R21:T21) -> 0 | AT21: =SUM(U21:W21) -> 0 | AU21: =SUM(X21:Z21) -> 0 | AV21: =SUM(AA21:AC21) -> 0 | AW21: =SUM(AD21:AF21) -> 0 | AX21: =SUM(AG21:AI21) -> 0 | AY21: =SUM(AJ21:AL21) -> 0 | BA21: =SUM(C21:N21) -> 0 | BB21: =SUM(O21:Z21) -> 0 | BC21: =SUM(AA21:AL21) -> 0
A22: Earnings Before Tax | C22: =C20-C21 -> 0 | D22: =D20-D21 -> 0 | E22: =E20-E21 -> 0 | F22: =F20-F21 -> 0 | G22: =G20-G21 -> 0 | H22: =H20-H21 -> 0 | I22: =I20-I21 -> 0 | J22: =J20-J21 -> 0 | ... AL22: =AL20-AL21 -> 0 | AN22: =SUM(C22:E22) -> 0 | AO22: =SUM(F22:H22) -> 0 | AP22: =SUM(I22:K22) -> 0 | AQ22: =SUM(L22:N22) -> 0 | AR22: =SUM(O22:Q22) -> 0 | AS22: =SUM(R22:T22) -> 0 | AT22: =SUM(U22:W22) -> 0 | AU22: =SUM(X22:Z22) -> 0 | AV22: =SUM(AA22:AC22) -> 0 | AW22: =SUM(AD22:AF22) -> 0 | AX22: =SUM(AG22:AI22) -> 0 | AY22: =SUM(AJ22:AL22) -> 0 | BA22: =SUM(C22:N22) -> 0 | BB22: =SUM(O22:Z22) -> 0 | BC22: =SUM(AA22:AL22) -> 0
A23: Income Tax Expense | B23: MAX(0, EBT) × tax rate — no NOL modeling | C23: =MAX(0,C22)*'Assumptions'!$F$10 -> 0 | D23: =MAX(0,D22)*'Assumptions'!$F$10 -> 0 | E23: =MAX(0,E22)*'Assumptions'!$F$10 -> 0 | F23: =MAX(0,F22)*'Assumptions'!$F$10 -> 0 | G23: =MAX(0,G22)*'Assumptions'!$F$10 -> 0 | H23: =MAX(0,H22)*'Assumptions'!$F$10 -> 0 | I23: =MAX(0,I22)*'Assumptions'!$F$10 -> 0 | J23: =MAX(0,J22)*'Assumptions'!$F$10 -> 0 | ... AL23: =MAX(0,AL22)*'Assumptions'!$F$10 -> 0 | AN23: =SUM(C23:E23) -> 0 | AO23: =SUM(F23:H23) -> 0 | AP23: =SUM(I23:K23) -> 0 | AQ23: =SUM(L23:N23) -> 0 | AR23: =SUM(O23:Q23) -> 0 | AS23: =SUM(R23:T23) -> 0 | AT23: =SUM(U23:W23) -> 0 | AU23: =SUM(X23:Z23) -> 0 | AV23: =SUM(AA23:AC23) -> 0 | AW23: =SUM(AD23:AF23) -> 0 | AX23: =SUM(AG23:AI23) -> 0 | AY23: =SUM(AJ23:AL23) -> 0 | BA23: =SUM(C23:N23) -> 0 | BB23: =SUM(O23:Z23) -> 0 | BC23: =SUM(AA23:AL23) -> 0
A24: Net Income | C24: =C22-C23 -> 0 | D24: =D22-D23 -> 0 | E24: =E22-E23 -> 0 | F24: =F22-F23 -> 0 | G24: =G22-G23 -> 0 | H24: =H22-H23 -> 0 | I24: =I22-I23 -> 0 | J24: =J22-J23 -> 0 | ... AL24: =AL22-AL23 -> 0 | AN24: =SUM(C24:E24) -> 0 | AO24: =SUM(F24:H24) -> 0 | AP24: =SUM(I24:K24) -> 0 | AQ24: =SUM(L24:N24) -> 0 | AR24: =SUM(O24:Q24) -> 0 | AS24: =SUM(R24:T24) -> 0 | AT24: =SUM(U24:W24) -> 0 | AU24: =SUM(X24:Z24) -> 0 | AV24: =SUM(AA24:AC24) -> 0 | AW24: =SUM(AD24:AF24) -> 0 | AX24: =SUM(AG24:AI24) -> 0 | AY24: =SUM(AJ24:AL24) -> 0 | BA24: =SUM(C24:N24) -> 0 | BB24: =SUM(O24:Z24) -> 0 | BC24: =SUM(AA24:AL24) -> 0

Sheet Cash Flow
A1: B2B SaaS + Usage — 3-Year Financial Model — Cash Flow
A2: Indirect method — Net Income reconciled to the change in cash.
A5: Line item | B5: Units / source | C5: Monthly (36 months) | AN5: Quarterly | BA5: Annual
C6: 46023 | D6: 46054 | E6: 46082 | F6: 46113 | G6: 46143 | H6: 46174 | I6: 46204 | J6: 46235 | K6: 46266 | L6: 46296 | M6: 46327 | N6: 46357 | O6: 46388 | P6: 46419 | Q6: 46447 | R6: 46478 | S6: 46508 | T6: 46539 | U6: 46569 | V6: 46600 | W6: 46631 | X6: 46661 | Y6: 46692 | Z6: 46722 | AA6: 46753 | AB6: 46784 | AC6: 46813 | AD6: 46844 | AE6: 46874 | AF6: 46905 | AG6: 46935 | AH6: 46966 | AI6: 46997 | AJ6: 47027 | AK6: 47058 | AL6: 47088 | AN6: Q1 | AO6: Q2 | AP6: Q3 | AQ6: Q4 | AR6: Q5 | AS6: Q6 | AT6: Q7 | AU6: Q8 | AV6: Q9 | AW6: Q10 | AX6: Q11 | AY6: Q12 | BA6: FY1 | BB6: FY2 | BC6: FY3
A7: Cash from Operations
A8: Net Income | C8: ='P&L'!$C$24 -> 0 | D8: ='P&L'!$D$24 -> 0 | E8: ='P&L'!$E$24 -> 0 | F8: ='P&L'!$F$24 -> 0 | G8: ='P&L'!$G$24 -> 0 | H8: ='P&L'!$H$24 -> 0 | I8: ='P&L'!$I$24 -> 0 | J8: ='P&L'!$J$24 -> 0 | K8: ='P&L'!$K$24 -> 0 | L8: ='P&L'!$L$24 -> 0 | M8: ='P&L'!$M$24 -> 0 | N8: ='P&L'!$N$24 -> 0 | O8: ='P&L'!$O$24 -> 0 | P8: ='P&L'!$P$24 -> 0 | Q8: ='P&L'!$Q$24 -> 0 | R8: ='P&L'!$R$24 -> 0 | S8: ='P&L'!$S$24 -> 0 | T8: ='P&L'!$T$24 -> 0 | U8: ='P&L'!$U$24 -> 0 | V8: ='P&L'!$V$24 -> 0 | W8: ='P&L'!$W$24 -> 0 | X8: ='P&L'!$X$24 -> 0 | Y8: ='P&L'!$Y$24 -> 0 | Z8: ='P&L'!$Z$24 -> 0 | AA8: ='P&L'!$AA$24 -> 0 | AB8: ='P&L'!$AB$24 -> 0 | AC8: ='P&L'!$AC$24 -> 0 | AD8: ='P&L'!$AD$24 -> 0 | AE8: ='P&L'!$AE$24 -> 0 | AF8: ='P&L'!$AF$24 -> 0 | AG8: ='P&L'!$AG$24 -> 0 | AH8: ='P&L'!$AH$24 -> 0 | AI8: ='P&L'!$AI$24 -> 0 | AJ8: ='P&L'!$AJ$24 -> 0 | AK8: ='P&L'!$AK$24 -> 0 | AL8: ='P&L'!$AL$24 -> 0 | AN8: =SUM(C8:E8) -> 0 | AO8: =SUM(F8:H8) -> 0 | AP8: =SUM(I8:K8) -> 0 | AQ8: =SUM(L8:N8) -> 0 | AR8: =SUM(O8:Q8) -> 0 | AS8: =SUM(R8:T8) -> 0 | AT8: =SUM(U8:W8) -> 0 | AU8: =SUM(X8:Z8) -> 0 | AV8: =SUM(AA8:AC8) -> 0 | AW8: =SUM(AD8:AF8) -> 0 | AX8: =SUM(AG8:AI8) -> 0 | AY8: =SUM(AJ8:AL8) -> 0 | BA8: =SUM(C8:N8) -> 0 | BB8: =SUM(O8:Z8) -> 0 | BC8: =SUM(AA8:AL8) -> 0
A9: + Depreciation & Amortization | C9: ='P&L'!$C$19 -> 0 | D9: ='P&L'!$D$19 -> 0 | E9: ='P&L'!$E$19 -> 0 | F9: ='P&L'!$F$19 -> 0 | G9: ='P&L'!$G$19 -> 0 | H9: ='P&L'!$H$19 -> 0 | I9: ='P&L'!$I$19 -> 0 | J9: ='P&L'!$J$19 -> 0 | K9: ='P&L'!$K$19 -> 0 | L9: ='P&L'!$L$19 -> 0 | M9: ='P&L'!$M$19 -> 0 | N9: ='P&L'!$N$19 -> 0 | O9: ='P&L'!$O$19 -> 0 | P9: ='P&L'!$P$19 -> 0 | Q9: ='P&L'!$Q$19 -> 0 | R9: ='P&L'!$R$19 -> 0 | S9: ='P&L'!$S$19 -> 0 | T9: ='P&L'!$T$19 -> 0 | U9: ='P&L'!$U$19 -> 0 | V9: ='P&L'!$V$19 -> 0 | W9: ='P&L'!$W$19 -> 0 | X9: ='P&L'!$X$19 -> 0 | Y9: ='P&L'!$Y$19 -> 0 | Z9: ='P&L'!$Z$19 -> 0 | AA9: ='P&L'!$AA$19 -> 0 | AB9: ='P&L'!$AB$19 -> 0 | AC9: ='P&L'!$AC$19 -> 0 | AD9: ='P&L'!$AD$19 -> 0 | AE9: ='P&L'!$AE$19 -> 0 | AF9: ='P&L'!$AF$19 -> 0 | AG9: ='P&L'!$AG$19 -> 0 | AH9: ='P&L'!$AH$19 -> 0 | AI9: ='P&L'!$AI$19 -> 0 | AJ9: ='P&L'!$AJ$19 -> 0 | AK9: ='P&L'!$AK$19 -> 0 | AL9: ='P&L'!$AL$19 -> 0 | AN9: =SUM(C9:E9) -> 0 | AO9: =SUM(F9:H9) -> 0 | AP9: =SUM(I9:K9) -> 0 | AQ9: =SUM(L9:N9) -> 0 | AR9: =SUM(O9:Q9) -> 0 | AS9: =SUM(R9:T9) -> 0 | AT9: =SUM(U9:W9) -> 0 | AU9: =SUM(X9:Z9) -> 0 | AV9: =SUM(AA9:AC9) -> 0 | AW9: =SUM(AD9:AF9) -> 0 | AX9: =SUM(AG9:AI9) -> 0 | AY9: =SUM(AJ9:AL9) -> 0 | BA9: =SUM(C9:N9) -> 0 | BB9: =SUM(O9:Z9) -> 0 | BC9: =SUM(AA9:AL9) -> 0
A10: − Change in Accounts Receivable | C10: =-'Working Capital'!C12 -> 0 | D10: =-'Working Capital'!D12 -> 0 | E10: =-'Working Capital'!E12 -> 0 | F10: =-'Working Capital'!F12 -> 0 | G10: =-'Working Capital'!G12 -> 0 | H10: =-'Working Capital'!H12 -> 0 | I10: =-'Working Capital'!I12 -> 0 | J10: =-'Working Capital'!J12 -> 0 | ... AL10: =-'Working Capital'!AL12 -> 0 | AN10: =SUM(C10:E10) -> 0 | AO10: =SUM(F10:H10) -> 0 | AP10: =SUM(I10:K10) -> 0 | AQ10: =SUM(L10:N10) -> 0 | AR10: =SUM(O10:Q10) -> 0 | AS10: =SUM(R10:T10) -> 0 | AT10: =SUM(U10:W10) -> 0 | AU10: =SUM(X10:Z10) -> 0 | AV10: =SUM(AA10:AC10) -> 0 | AW10: =SUM(AD10:AF10) -> 0 | AX10: =SUM(AG10:AI10) -> 0 | AY10: =SUM(AJ10:AL10) -> 0 | BA10: =SUM(C10:N10) -> 0 | BB10: =SUM(O10:Z10) -> 0 | BC10: =SUM(AA10:AL10) -> 0
A11: − Change in Other Current Assets | C11: =-'Working Capital'!C15 -> 0 | D11: =-'Working Capital'!D15 -> 0 | E11: =-'Working Capital'!E15 -> 0 | F11: =-'Working Capital'!F15 -> 0 | G11: =-'Working Capital'!G15 -> 0 | H11: =-'Working Capital'!H15 -> 0 | I11: =-'Working Capital'!I15 -> 0 | J11: =-'Working Capital'!J15 -> 0 | ... AL11: =-'Working Capital'!AL15 -> 0 | AN11: =SUM(C11:E11) -> 0 | AO11: =SUM(F11:H11) -> 0 | AP11: =SUM(I11:K11) -> 0 | AQ11: =SUM(L11:N11) -> 0 | AR11: =SUM(O11:Q11) -> 0 | AS11: =SUM(R11:T11) -> 0 | AT11: =SUM(U11:W11) -> 0 | AU11: =SUM(X11:Z11) -> 0 | AV11: =SUM(AA11:AC11) -> 0 | AW11: =SUM(AD11:AF11) -> 0 | AX11: =SUM(AG11:AI11) -> 0 | AY11: =SUM(AJ11:AL11) -> 0 | BA11: =SUM(C11:N11) -> 0 | BB11: =SUM(O11:Z11) -> 0 | BC11: =SUM(AA11:AL11) -> 0
A12: + Change in Accounts Payable | C12: ='Working Capital'!C13 -> 0 | D12: ='Working Capital'!D13 -> 0 | E12: ='Working Capital'!E13 -> 0 | F12: ='Working Capital'!F13 -> 0 | G12: ='Working Capital'!G13 -> 0 | H12: ='Working Capital'!H13 -> 0 | I12: ='Working Capital'!I13 -> 0 | J12: ='Working Capital'!J13 -> 0 | ... AL12: ='Working Capital'!AL13 -> 0 | AN12: =SUM(C12:E12) -> 0 | AO12: =SUM(F12:H12) -> 0 | AP12: =SUM(I12:K12) -> 0 | AQ12: =SUM(L12:N12) -> 0 | AR12: =SUM(O12:Q12) -> 0 | AS12: =SUM(R12:T12) -> 0 | AT12: =SUM(U12:W12) -> 0 | AU12: =SUM(X12:Z12) -> 0 | AV12: =SUM(AA12:AC12) -> 0 | AW12: =SUM(AD12:AF12) -> 0 | AX12: =SUM(AG12:AI12) -> 0 | AY12: =SUM(AJ12:AL12) -> 0 | BA12: =SUM(C12:N12) -> 0 | BB12: =SUM(O12:Z12) -> 0 | BC12: =SUM(AA12:AL12) -> 0
A13: + Change in Deferred Revenue | C13: ='Working Capital'!C14 -> 0 | D13: ='Working Capital'!D14 -> 0 | E13: ='Working Capital'!E14 -> 0 | F13: ='Working Capital'!F14 -> 0 | G13: ='Working Capital'!G14 -> 0 | H13: ='Working Capital'!H14 -> 0 | I13: ='Working Capital'!I14 -> 0 | J13: ='Working Capital'!J14 -> 0 | ... AL13: ='Working Capital'!AL14 -> 0 | AN13: =SUM(C13:E13) -> 0 | AO13: =SUM(F13:H13) -> 0 | AP13: =SUM(I13:K13) -> 0 | AQ13: =SUM(L13:N13) -> 0 | AR13: =SUM(O13:Q13) -> 0 | AS13: =SUM(R13:T13) -> 0 | AT13: =SUM(U13:W13) -> 0 | AU13: =SUM(X13:Z13) -> 0 | AV13: =SUM(AA13:AC13) -> 0 | AW13: =SUM(AD13:AF13) -> 0 | AX13: =SUM(AG13:AI13) -> 0 | AY13: =SUM(AJ13:AL13) -> 0 | BA13: =SUM(C13:N13) -> 0 | BB13: =SUM(O13:Z13) -> 0 | BC13: =SUM(AA13:AL13) -> 0
A14: Cash from Operations | C14: =C8+C9+C10+C11+C12+C13 -> 0 | D14: =D8+D9+D10+D11+D12+D13 -> 0 | E14: =E8+E9+E10+E11+E12+E13 -> 0 | F14: =F8+F9+F10+F11+F12+F13 -> 0 | G14: =G8+G9+G10+G11+G12+G13 -> 0 | H14: =H8+H9+H10+H11+H12+H13 -> 0 | I14: =I8+I9+I10+I11+I12+I13 -> 0 | J14: =J8+J9+J10+J11+J12+J13 -> 0 | ... AL14: =AL8+AL9+AL10+AL11+AL12+AL13 -> 0 | AN14: =SUM(C14:E14) -> 0 | AO14: =SUM(F14:H14) -> 0 | AP14: =SUM(I14:K14) -> 0 | AQ14: =SUM(L14:N14) -> 0 | AR14: =SUM(O14:Q14) -> 0 | AS14: =SUM(R14:T14) -> 0 | AT14: =SUM(U14:W14) -> 0 | AU14: =SUM(X14:Z14) -> 0 | AV14: =SUM(AA14:AC14) -> 0 | AW14: =SUM(AD14:AF14) -> 0 | AX14: =SUM(AG14:AI14) -> 0 | AY14: =SUM(AJ14:AL14) -> 0 | BA14: =SUM(C14:N14) -> 0 | BB14: =SUM(O14:Z14) -> 0 | BC14: =SUM(AA14:AL14) -> 0
A16: Cash from Investing
A17: − Capital Expenditures | C17: =-'Working Capital'!C18 -> 0 | D17: =-'Working Capital'!D18 -> 0 | E17: =-'Working Capital'!E18 -> 0 | F17: =-'Working Capital'!F18 -> 0 | G17: =-'Working Capital'!G18 -> 0 | H17: =-'Working Capital'!H18 -> 0 | I17: =-'Working Capital'!I18 -> 0 | J17: =-'Working Capital'!J18 -> 0 | ... AL17: =-'Working Capital'!AL18 -> 0 | AN17: =SUM(C17:E17) -> 0 | AO17: =SUM(F17:H17) -> 0 | AP17: =SUM(I17:K17) -> 0 | AQ17: =SUM(L17:N17) -> 0 | AR17: =SUM(O17:Q17) -> 0 | AS17: =SUM(R17:T17) -> 0 | AT17: =SUM(U17:W17) -> 0 | AU17: =SUM(X17:Z17) -> 0 | AV17: =SUM(AA17:AC17) -> 0 | AW17: =SUM(AD17:AF17) -> 0 | AX17: =SUM(AG17:AI17) -> 0 | AY17: =SUM(AJ17:AL17) -> 0 | BA17: =SUM(C17:N17) -> 0 | BB17: =SUM(O17:Z17) -> 0 | BC17: =SUM(AA17:AL17) -> 0
A18: Cash from Investing | C18: =C17 -> 0 | D18: =D17 -> 0 | E18: =E17 -> 0 | F18: =F17 -> 0 | G18: =G17 -> 0 | H18: =H17 -> 0 | I18: =I17 -> 0 | J18: =J17 -> 0 | ... AL18: =AL17 -> 0 | AN18: =SUM(C18:E18) -> 0 | AO18: =SUM(F18:H18) -> 0 | AP18: =SUM(I18:K18) -> 0 | AQ18: =SUM(L18:N18) -> 0 | AR18: =SUM(O18:Q18) -> 0 | AS18: =SUM(R18:T18) -> 0 | AT18: =SUM(U18:W18) -> 0 | AU18: =SUM(X18:Z18) -> 0 | AV18: =SUM(AA18:AC18) -> 0 | AW18: =SUM(AD18:AF18) -> 0 | AX18: =SUM(AG18:AI18) -> 0 | AY18: =SUM(AJ18:AL18) -> 0 | BA18: =SUM(C18:N18) -> 0 | BB18: =SUM(O18:Z18) -> 0 | BC18: =SUM(AA18:AL18) -> 0
A20: Cash from Financing
A21: + Debt Draw | C21: ='Working Capital'!C23 -> 0 | D21: ='Working Capital'!D23 -> 0 | E21: ='Working Capital'!E23 -> 0 | F21: ='Working Capital'!F23 -> 0 | G21: ='Working Capital'!G23 -> 0 | H21: ='Working Capital'!H23 -> 0 | I21: ='Working Capital'!I23 -> 0 | J21: ='Working Capital'!J23 -> 0 | ... AL21: ='Working Capital'!AL23 -> 0 | AN21: =SUM(C21:E21) -> 0 | AO21: =SUM(F21:H21) -> 0 | AP21: =SUM(I21:K21) -> 0 | AQ21: =SUM(L21:N21) -> 0 | AR21: =SUM(O21:Q21) -> 0 | AS21: =SUM(R21:T21) -> 0 | AT21: =SUM(U21:W21) -> 0 | AU21: =SUM(X21:Z21) -> 0 | AV21: =SUM(AA21:AC21) -> 0 | AW21: =SUM(AD21:AF21) -> 0 | AX21: =SUM(AG21:AI21) -> 0 | AY21: =SUM(AJ21:AL21) -> 0 | BA21: =SUM(C21:N21) -> 0 | BB21: =SUM(O21:Z21) -> 0 | BC21: =SUM(AA21:AL21) -> 0
A22: − Debt Repayment | C22: =-'Working Capital'!C24 -> 0 | D22: =-'Working Capital'!D24 -> 0 | E22: =-'Working Capital'!E24 -> 0 | F22: =-'Working Capital'!F24 -> 0 | G22: =-'Working Capital'!G24 -> 0 | H22: =-'Working Capital'!H24 -> 0 | I22: =-'Working Capital'!I24 -> 0 | J22: =-'Working Capital'!J24 -> 0 | ... AL22: =-'Working Capital'!AL24 -> 0 | AN22: =SUM(C22:E22) -> 0 | AO22: =SUM(F22:H22) -> 0 | AP22: =SUM(I22:K22) -> 0 | AQ22: =SUM(L22:N22) -> 0 | AR22: =SUM(O22:Q22) -> 0 | AS22: =SUM(R22:T22) -> 0 | AT22: =SUM(U22:W22) -> 0 | AU22: =SUM(X22:Z22) -> 0 | AV22: =SUM(AA22:AC22) -> 0 | AW22: =SUM(AD22:AF22) -> 0 | AX22: =SUM(AG22:AI22) -> 0 | AY22: =SUM(AJ22:AL22) -> 0 | BA22: =SUM(C22:N22) -> 0 | BB22: =SUM(O22:Z22) -> 0 | BC22: =SUM(AA22:AL22) -> 0
A23: + Equity Raised | C23: ='Working Capital'!C29 -> 0 | D23: ='Working Capital'!D29 -> 0 | E23: ='Working Capital'!E29 -> 0 | F23: ='Working Capital'!F29 -> 0 | G23: ='Working Capital'!G29 -> 0 | H23: ='Working Capital'!H29 -> 0 | I23: ='Working Capital'!I29 -> 0 | J23: ='Working Capital'!J29 -> 0 | ... AL23: ='Working Capital'!AL29 -> 0 | AN23: =SUM(C23:E23) -> 0 | AO23: =SUM(F23:H23) -> 0 | AP23: =SUM(I23:K23) -> 0 | AQ23: =SUM(L23:N23) -> 0 | AR23: =SUM(O23:Q23) -> 0 | AS23: =SUM(R23:T23) -> 0 | AT23: =SUM(U23:W23) -> 0 | AU23: =SUM(X23:Z23) -> 0 | AV23: =SUM(AA23:AC23) -> 0 | AW23: =SUM(AD23:AF23) -> 0 | AX23: =SUM(AG23:AI23) -> 0 | AY23: =SUM(AJ23:AL23) -> 0 | BA23: =SUM(C23:N23) -> 0 | BB23: =SUM(O23:Z23) -> 0 | BC23: =SUM(AA23:AL23) -> 0
A24: Cash from Financing | C24: =C21+C22+C23 -> 0 | D24: =D21+D22+D23 -> 0 | E24: =E21+E22+E23 -> 0 | F24: =F21+F22+F23 -> 0 | G24: =G21+G22+G23 -> 0 | H24: =H21+H22+H23 -> 0 | I24: =I21+I22+I23 -> 0 | J24: =J21+J22+J23 -> 0 | ... AL24: =AL21+AL22+AL23 -> 0 | AN24: =SUM(C24:E24) -> 0 | AO24: =SUM(F24:H24) -> 0 | AP24: =SUM(I24:K24) -> 0 | AQ24: =SUM(L24:N24) -> 0 | AR24: =SUM(O24:Q24) -> 0 | AS24: =SUM(R24:T24) -> 0 | AT24: =SUM(U24:W24) -> 0 | AU24: =SUM(X24:Z24) -> 0 | AV24: =SUM(AA24:AC24) -> 0 | AW24: =SUM(AD24:AF24) -> 0 | AX24: =SUM(AG24:AI24) -> 0 | AY24: =SUM(AJ24:AL24) -> 0 | BA24: =SUM(C24:N24) -> 0 | BB24: =SUM(O24:Z24) -> 0 | BC24: =SUM(AA24:AL24) -> 0
A26: Net Change in Cash | C26: =C14+C18+C24 -> 0 | D26: =D14+D18+D24 -> 0 | E26: =E14+E18+E24 -> 0 | F26: =F14+F18+F24 -> 0 | G26: =G14+G18+G24 -> 0 | H26: =H14+H18+H24 -> 0 | I26: =I14+I18+I24 -> 0 | J26: =J14+J18+J24 -> 0 | ... AL26: =AL14+AL18+AL24 -> 0 | AN26: =SUM(C26:E26) -> 0 | AO26: =SUM(F26:H26) -> 0 | AP26: =SUM(I26:K26) -> 0 | AQ26: =SUM(L26:N26) -> 0 | AR26: =SUM(O26:Q26) -> 0 | AS26: =SUM(R26:T26) -> 0 | AT26: =SUM(U26:W26) -> 0 | AU26: =SUM(X26:Z26) -> 0 | AV26: =SUM(AA26:AC26) -> 0 | AW26: =SUM(AD26:AF26) -> 0 | AX26: =SUM(AG26:AI26) -> 0 | AY26: =SUM(AJ26:AL26) -> 0 | BA26: =SUM(C26:N26) -> 0 | BB26: =SUM(O26:Z26) -> 0 | BC26: =SUM(AA26:AL26) -> 0
A27: Beginning Cash | B27: Prior month ending cash (or starting cash in month 1) | C27: ='Assumptions'!$F$8 -> 0 | D27: =C28 -> 0 | E27: =D28 -> 0 | F27: =E28 -> 0 | G27: =F28 -> 0 | H27: =G28 -> 0 | I27: =H28 -> 0 | J27: =I28 -> 0 | K27: =J28 -> 0 | ... AL27: =AK28 -> 0 | AN27: =C27 -> 0 | AO27: =F27 -> 0 | AP27: =I27 -> 0 | AQ27: =L27 -> 0 | AR27: =O27 -> 0 | AS27: =R27 -> 0 | AT27: =U27 -> 0 | AU27: =X27 -> 0 | AV27: =AA27 -> 0 | AW27: =AD27 -> 0 | AX27: =AG27 -> 0 | AY27: =AJ27 -> 0 | BA27: =C27 -> 0 | BB27: =O27 -> 0 | BC27: =AA27 -> 0
A28: Ending Cash | B28: Beginning cash + net change in cash | C28: =C27+C26 -> 0 | D28: =D27+D26 -> 0 | E28: =E27+E26 -> 0 | F28: =F27+F26 -> 0 | G28: =G27+G26 -> 0 | H28: =H27+H26 -> 0 | I28: =I27+I26 -> 0 | J28: =J27+J26 -> 0 | ... AL28: =AL27+AL26 -> 0 | AN28: =E28 -> 0 | AO28: =H28 -> 0 | AP28: =K28 -> 0 | AQ28: =N28 -> 0 | AR28: =Q28 -> 0 | AS28: =T28 -> 0 | AT28: =W28 -> 0 | AU28: =Z28 -> 0 | AV28: =AC28 -> 0 | AW28: =AF28 -> 0 | AX28: =AI28 -> 0 | AY28: =AL28 -> 0 | BA28: =N28 -> 0 | BB28: =Z28 -> 0 | BC28: =AL28 -> 0

Sheet Balance Sheet
A1: B2B SaaS + Usage — 3-Year Financial Model — Balance Sheet
A2: Assets = Liabilities + Equity every month, by construction.
A5: Line item | B5: Units / source | C5: Monthly (36 months) | AN5: Quarterly | BA5: Annual
C6: 46023 | D6: 46054 | E6: 46082 | F6: 46113 | G6: 46143 | H6: 46174 | I6: 46204 | J6: 46235 | K6: 46266 | L6: 46296 | M6: 46327 | N6: 46357 | O6: 46388 | P6: 46419 | Q6: 46447 | R6: 46478 | S6: 46508 | T6: 46539 | U6: 46569 | V6: 46600 | W6: 46631 | X6: 46661 | Y6: 46692 | Z6: 46722 | AA6: 46753 | AB6: 46784 | AC6: 46813 | AD6: 46844 | AE6: 46874 | AF6: 46905 | AG6: 46935 | AH6: 46966 | AI6: 46997 | AJ6: 47027 | AK6: 47058 | AL6: 47088 | AN6: Q1 | AO6: Q2 | AP6: Q3 | AQ6: Q4 | AR6: Q5 | AS6: Q6 | AT6: Q7 | AU6: Q8 | AV6: Q9 | AW6: Q10 | AX6: Q11 | AY6: Q12 | BA6: FY1 | BB6: FY2 | BC6: FY3
A7: Assets
A8: Cash & equivalents | B8: Linked from Cash Flow tab | C8: ='Cash Flow'!$C$28 -> 0 | D8: ='Cash Flow'!$D$28 -> 0 | E8: ='Cash Flow'!$E$28 -> 0 | F8: ='Cash Flow'!$F$28 -> 0 | G8: ='Cash Flow'!$G$28 -> 0 | H8: ='Cash Flow'!$H$28 -> 0 | I8: ='Cash Flow'!$I$28 -> 0 | J8: ='Cash Flow'!$J$28 -> 0 | K8: ='Cash Flow'!$K$28 -> 0 | L8: ='Cash Flow'!$L$28 -> 0 | M8: ='Cash Flow'!$M$28 -> 0 | N8: ='Cash Flow'!$N$28 -> 0 | O8: ='Cash Flow'!$O$28 -> 0 | P8: ='Cash Flow'!$P$28 -> 0 | Q8: ='Cash Flow'!$Q$28 -> 0 | R8: ='Cash Flow'!$R$28 -> 0 | S8: ='Cash Flow'!$S$28 -> 0 | T8: ='Cash Flow'!$T$28 -> 0 | U8: ='Cash Flow'!$U$28 -> 0 | V8: ='Cash Flow'!$V$28 -> 0 | W8: ='Cash Flow'!$W$28 -> 0 | X8: ='Cash Flow'!$X$28 -> 0 | Y8: ='Cash Flow'!$Y$28 -> 0 | Z8: ='Cash Flow'!$Z$28 -> 0 | AA8: ='Cash Flow'!$AA$28 -> 0 | AB8: ='Cash Flow'!$AB$28 -> 0 | AC8: ='Cash Flow'!$AC$28 -> 0 | AD8: ='Cash Flow'!$AD$28 -> 0 | AE8: ='Cash Flow'!$AE$28 -> 0 | AF8: ='Cash Flow'!$AF$28 -> 0 | AG8: ='Cash Flow'!$AG$28 -> 0 | AH8: ='Cash Flow'!$AH$28 -> 0 | AI8: ='Cash Flow'!$AI$28 -> 0 | AJ8: ='Cash Flow'!$AJ$28 -> 0 | AK8: ='Cash Flow'!$AK$28 -> 0 | AL8: ='Cash Flow'!$AL$28 -> 0 | AN8: =E8 -> 0 | AO8: =H8 -> 0 | AP8: =K8 -> 0 | AQ8: =N8 -> 0 | AR8: =Q8 -> 0 | AS8: =T8 -> 0 | AT8: =W8 -> 0 | AU8: =Z8 -> 0 | AV8: =AC8 -> 0 | AW8: =AF8 -> 0 | AX8: =AI8 -> 0 | AY8: =AL8 -> 0 | BA8: =N8 -> 0 | BB8: =Z8 -> 0 | BC8: =AL8 -> 0
A9: Accounts Receivable | C9: ='Working Capital'!$C$8 -> 0 | D9: ='Working Capital'!$D$8 -> 0 | E9: ='Working Capital'!$E$8 -> 0 | F9: ='Working Capital'!$F$8 -> 0 | G9: ='Working Capital'!$G$8 -> 0 | H9: ='Working Capital'!$H$8 -> 0 | I9: ='Working Capital'!$I$8 -> 0 | J9: ='Working Capital'!$J$8 -> 0 | K9: ='Working Capital'!$K$8 -> 0 | L9: ='Working Capital'!$L$8 -> 0 | M9: ='Working Capital'!$M$8 -> 0 | N9: ='Working Capital'!$N$8 -> 0 | O9: ='Working Capital'!$O$8 -> 0 | P9: ='Working Capital'!$P$8 -> 0 | Q9: ='Working Capital'!$Q$8 -> 0 | R9: ='Working Capital'!$R$8 -> 0 | S9: ='Working Capital'!$S$8 -> 0 | T9: ='Working Capital'!$T$8 -> 0 | U9: ='Working Capital'!$U$8 -> 0 | V9: ='Working Capital'!$V$8 -> 0 | W9: ='Working Capital'!$W$8 -> 0 | X9: ='Working Capital'!$X$8 -> 0 | Y9: ='Working Capital'!$Y$8 -> 0 | Z9: ='Working Capital'!$Z$8 -> 0 | AA9: ='Working Capital'!$AA$8 -> 0 | AB9: ='Working Capital'!$AB$8 -> 0 | AC9: ='Working Capital'!$AC$8 -> 0 | AD9: ='Working Capital'!$AD$8 -> 0 | AE9: ='Working Capital'!$AE$8 -> 0 | AF9: ='Working Capital'!$AF$8 -> 0 | AG9: ='Working Capital'!$AG$8 -> 0 | AH9: ='Working Capital'!$AH$8 -> 0 | AI9: ='Working Capital'!$AI$8 -> 0 | AJ9: ='Working Capital'!$AJ$8 -> 0 | AK9: ='Working Capital'!$AK$8 -> 0 | AL9: ='Working Capital'!$AL$8 -> 0 | AN9: =E9 -> 0 | AO9: =H9 -> 0 | AP9: =K9 -> 0 | AQ9: =N9 -> 0 | AR9: =Q9 -> 0 | AS9: =T9 -> 0 | AT9: =W9 -> 0 | AU9: =Z9 -> 0 | AV9: =AC9 -> 0 | AW9: =AF9 -> 0 | AX9: =AI9 -> 0 | AY9: =AL9 -> 0 | BA9: =N9 -> 0 | BB9: =Z9 -> 0 | BC9: =AL9 -> 0
A10: Other Current Assets (prepaid, etc.) | B10: Linked from Working Capital tab | C10: ='Working Capital'!C11 -> 0 | D10: ='Working Capital'!D11 -> 0 | E10: ='Working Capital'!E11 -> 0 | F10: ='Working Capital'!F11 -> 0 | G10: ='Working Capital'!G11 -> 0 | H10: ='Working Capital'!H11 -> 0 | I10: ='Working Capital'!I11 -> 0 | J10: ='Working Capital'!J11 -> 0 | ... AL10: ='Working Capital'!AL11 -> 0 | AN10: =E10 -> 0 | AO10: =H10 -> 0 | AP10: =K10 -> 0 | AQ10: =N10 -> 0 | AR10: =Q10 -> 0 | AS10: =T10 -> 0 | AT10: =W10 -> 0 | AU10: =Z10 -> 0 | AV10: =AC10 -> 0 | AW10: =AF10 -> 0 | AX10: =AI10 -> 0 | AY10: =AL10 -> 0 | BA10: =N10 -> 0 | BB10: =Z10 -> 0 | BC10: =AL10 -> 0
A11: Net PP&E | C11: ='Working Capital'!$C$20 -> 0 | D11: ='Working Capital'!$D$20 -> 0 | E11: ='Working Capital'!$E$20 -> 0 | F11: ='Working Capital'!$F$20 -> 0 | G11: ='Working Capital'!$G$20 -> 0 | H11: ='Working Capital'!$H$20 -> 0 | I11: ='Working Capital'!$I$20 -> 0 | J11: ='Working Capital'!$J$20 -> 0 | K11: ='Working Capital'!$K$20 -> 0 | L11: ='Working Capital'!$L$20 -> 0 | M11: ='Working Capital'!$M$20 -> 0 | N11: ='Working Capital'!$N$20 -> 0 | O11: ='Working Capital'!$O$20 -> 0 | P11: ='Working Capital'!$P$20 -> 0 | Q11: ='Working Capital'!$Q$20 -> 0 | R11: ='Working Capital'!$R$20 -> 0 | S11: ='Working Capital'!$S$20 -> 0 | T11: ='Working Capital'!$T$20 -> 0 | U11: ='Working Capital'!$U$20 -> 0 | V11: ='Working Capital'!$V$20 -> 0 | W11: ='Working Capital'!$W$20 -> 0 | X11: ='Working Capital'!$X$20 -> 0 | Y11: ='Working Capital'!$Y$20 -> 0 | Z11: ='Working Capital'!$Z$20 -> 0 | AA11: ='Working Capital'!$AA$20 -> 0 | AB11: ='Working Capital'!$AB$20 -> 0 | AC11: ='Working Capital'!$AC$20 -> 0 | AD11: ='Working Capital'!$AD$20 -> 0 | AE11: ='Working Capital'!$AE$20 -> 0 | AF11: ='Working Capital'!$AF$20 -> 0 | AG11: ='Working Capital'!$AG$20 -> 0 | AH11: ='Working Capital'!$AH$20 -> 0 | AI11: ='Working Capital'!$AI$20 -> 0 | AJ11: ='Working Capital'!$AJ$20 -> 0 | AK11: ='Working Capital'!$AK$20 -> 0 | AL11: ='Working Capital'!$AL$20 -> 0 | AN11: =E11 -> 0 | AO11: =H11 -> 0 | AP11: =K11 -> 0 | AQ11: =N11 -> 0 | AR11: =Q11 -> 0 | AS11: =T11 -> 0 | AT11: =W11 -> 0 | AU11: =Z11 -> 0 | AV11: =AC11 -> 0 | AW11: =AF11 -> 0 | AX11: =AI11 -> 0 | AY11: =AL11 -> 0 | BA11: =N11 -> 0 | BB11: =Z11 -> 0 | BC11: =AL11 -> 0
A12: Total Assets | C12: =C8+C9+C10+C11 -> 0 | D12: =D8+D9+D10+D11 -> 0 | E12: =E8+E9+E10+E11 -> 0 | F12: =F8+F9+F10+F11 -> 0 | G12: =G8+G9+G10+G11 -> 0 | H12: =H8+H9+H10+H11 -> 0 | I12: =I8+I9+I10+I11 -> 0 | J12: =J8+J9+J10+J11 -> 0 | ... AL12: =AL8+AL9+AL10+AL11 -> 0 | AN12: =E12 -> 0 | AO12: =H12 -> 0 | AP12: =K12 -> 0 | AQ12: =N12 -> 0 | AR12: =Q12 -> 0 | AS12: =T12 -> 0 | AT12: =W12 -> 0 | AU12: =Z12 -> 0 | AV12: =AC12 -> 0 | AW12: =AF12 -> 0 | AX12: =AI12 -> 0 | AY12: =AL12 -> 0 | BA12: =N12 -> 0 | BB12: =Z12 -> 0 | BC12: =AL12 -> 0
A14: Liabilities
A15: Accounts Payable | C15: ='Working Capital'!$C$9 -> 0 | D15: ='Working Capital'!$D$9 -> 0 | E15: ='Working Capital'!$E$9 -> 0 | F15: ='Working Capital'!$F$9 -> 0 | G15: ='Working Capital'!$G$9 -> 0 | H15: ='Working Capital'!$H$9 -> 0 | I15: ='Working Capital'!$I$9 -> 0 | J15: ='Working Capital'!$J$9 -> 0 | K15: ='Working Capital'!$K$9 -> 0 | L15: ='Working Capital'!$L$9 -> 0 | M15: ='Working Capital'!$M$9 -> 0 | N15: ='Working Capital'!$N$9 -> 0 | O15: ='Working Capital'!$O$9 -> 0 | P15: ='Working Capital'!$P$9 -> 0 | Q15: ='Working Capital'!$Q$9 -> 0 | R15: ='Working Capital'!$R$9 -> 0 | S15: ='Working Capital'!$S$9 -> 0 | T15: ='Working Capital'!$T$9 -> 0 | U15: ='Working Capital'!$U$9 -> 0 | V15: ='Working Capital'!$V$9 -> 0 | W15: ='Working Capital'!$W$9 -> 0 | X15: ='Working Capital'!$X$9 -> 0 | Y15: ='Working Capital'!$Y$9 -> 0 | Z15: ='Working Capital'!$Z$9 -> 0 | AA15: ='Working Capital'!$AA$9 -> 0 | AB15: ='Working Capital'!$AB$9 -> 0 | AC15: ='Working Capital'!$AC$9 -> 0 | AD15: ='Working Capital'!$AD$9 -> 0 | AE15: ='Working Capital'!$AE$9 -> 0 | AF15: ='Working Capital'!$AF$9 -> 0 | AG15: ='Working Capital'!$AG$9 -> 0 | AH15: ='Working Capital'!$AH$9 -> 0 | AI15: ='Working Capital'!$AI$9 -> 0 | AJ15: ='Working Capital'!$AJ$9 -> 0 | AK15: ='Working Capital'!$AK$9 -> 0 | AL15: ='Working Capital'!$AL$9 -> 0 | AN15: =E15 -> 0 | AO15: =H15 -> 0 | AP15: =K15 -> 0 | AQ15: =N15 -> 0 | AR15: =Q15 -> 0 | AS15: =T15 -> 0 | AT15: =W15 -> 0 | AU15: =Z15 -> 0 | AV15: =AC15 -> 0 | AW15: =AF15 -> 0 | AX15: =AI15 -> 0 | AY15: =AL15 -> 0 | BA15: =N15 -> 0 | BB15: =Z15 -> 0 | BC15: =AL15 -> 0
A16: Deferred Revenue | C16: ='Working Capital'!$C$10 -> 0 | D16: ='Working Capital'!$D$10 -> 0 | E16: ='Working Capital'!$E$10 -> 0 | F16: ='Working Capital'!$F$10 -> 0 | G16: ='Working Capital'!$G$10 -> 0 | H16: ='Working Capital'!$H$10 -> 0 | I16: ='Working Capital'!$I$10 -> 0 | J16: ='Working Capital'!$J$10 -> 0 | K16: ='Working Capital'!$K$10 -> 0 | L16: ='Working Capital'!$L$10 -> 0 | M16: ='Working Capital'!$M$10 -> 0 | N16: ='Working Capital'!$N$10 -> 0 | O16: ='Working Capital'!$O$10 -> 0 | P16: ='Working Capital'!$P$10 -> 0 | Q16: ='Working Capital'!$Q$10 -> 0 | R16: ='Working Capital'!$R$10 -> 0 | S16: ='Working Capital'!$S$10 -> 0 | T16: ='Working Capital'!$T$10 -> 0 | U16: ='Working Capital'!$U$10 -> 0 | V16: ='Working Capital'!$V$10 -> 0 | W16: ='Working Capital'!$W$10 -> 0 | X16: ='Working Capital'!$X$10 -> 0 | Y16: ='Working Capital'!$Y$10 -> 0 | Z16: ='Working Capital'!$Z$10 -> 0 | AA16: ='Working Capital'!$AA$10 -> 0 | AB16: ='Working Capital'!$AB$10 -> 0 | AC16: ='Working Capital'!$AC$10 -> 0 | AD16: ='Working Capital'!$AD$10 -> 0 | AE16: ='Working Capital'!$AE$10 -> 0 | AF16: ='Working Capital'!$AF$10 -> 0 | AG16: ='Working Capital'!$AG$10 -> 0 | AH16: ='Working Capital'!$AH$10 -> 0 | AI16: ='Working Capital'!$AI$10 -> 0 | AJ16: ='Working Capital'!$AJ$10 -> 0 | AK16: ='Working Capital'!$AK$10 -> 0 | AL16: ='Working Capital'!$AL$10 -> 0 | AN16: =E16 -> 0 | AO16: =H16 -> 0 | AP16: =K16 -> 0 | AQ16: =N16 -> 0 | AR16: =Q16 -> 0 | AS16: =T16 -> 0 | AT16: =W16 -> 0 | AU16: =Z16 -> 0 | AV16: =AC16 -> 0 | AW16: =AF16 -> 0 | AX16: =AI16 -> 0 | AY16: =AL16 -> 0 | BA16: =N16 -> 0 | BB16: =Z16 -> 0 | BC16: =AL16 -> 0
A17: Debt | C17: ='Working Capital'!$C$25 -> 0 | D17: ='Working Capital'!$D$25 -> 0 | E17: ='Working Capital'!$E$25 -> 0 | F17: ='Working Capital'!$F$25 -> 0 | G17: ='Working Capital'!$G$25 -> 0 | H17: ='Working Capital'!$H$25 -> 0 | I17: ='Working Capital'!$I$25 -> 0 | J17: ='Working Capital'!$J$25 -> 0 | K17: ='Working Capital'!$K$25 -> 0 | L17: ='Working Capital'!$L$25 -> 0 | M17: ='Working Capital'!$M$25 -> 0 | N17: ='Working Capital'!$N$25 -> 0 | O17: ='Working Capital'!$O$25 -> 0 | P17: ='Working Capital'!$P$25 -> 0 | Q17: ='Working Capital'!$Q$25 -> 0 | R17: ='Working Capital'!$R$25 -> 0 | S17: ='Working Capital'!$S$25 -> 0 | T17: ='Working Capital'!$T$25 -> 0 | U17: ='Working Capital'!$U$25 -> 0 | V17: ='Working Capital'!$V$25 -> 0 | W17: ='Working Capital'!$W$25 -> 0 | X17: ='Working Capital'!$X$25 -> 0 | Y17: ='Working Capital'!$Y$25 -> 0 | Z17: ='Working Capital'!$Z$25 -> 0 | AA17: ='Working Capital'!$AA$25 -> 0 | AB17: ='Working Capital'!$AB$25 -> 0 | AC17: ='Working Capital'!$AC$25 -> 0 | AD17: ='Working Capital'!$AD$25 -> 0 | AE17: ='Working Capital'!$AE$25 -> 0 | AF17: ='Working Capital'!$AF$25 -> 0 | AG17: ='Working Capital'!$AG$25 -> 0 | AH17: ='Working Capital'!$AH$25 -> 0 | AI17: ='Working Capital'!$AI$25 -> 0 | AJ17: ='Working Capital'!$AJ$25 -> 0 | AK17: ='Working Capital'!$AK$25 -> 0 | AL17: ='Working Capital'!$AL$25 -> 0 | AN17: =E17 -> 0 | AO17: =H17 -> 0 | AP17: =K17 -> 0 | AQ17: =N17 -> 0 | AR17: =Q17 -> 0 | AS17: =T17 -> 0 | AT17: =W17 -> 0 | AU17: =Z17 -> 0 | AV17: =AC17 -> 0 | AW17: =AF17 -> 0 | AX17: =AI17 -> 0 | AY17: =AL17 -> 0 | BA17: =N17 -> 0 | BB17: =Z17 -> 0 | BC17: =AL17 -> 0
A18: Total Liabilities | C18: =C15+C16+C17 -> 0 | D18: =D15+D16+D17 -> 0 | E18: =E15+E16+E17 -> 0 | F18: =F15+F16+F17 -> 0 | G18: =G15+G16+G17 -> 0 | H18: =H15+H16+H17 -> 0 | I18: =I15+I16+I17 -> 0 | J18: =J15+J16+J17 -> 0 | ... AL18: =AL15+AL16+AL17 -> 0 | AN18: =E18 -> 0 | AO18: =H18 -> 0 | AP18: =K18 -> 0 | AQ18: =N18 -> 0 | AR18: =Q18 -> 0 | AS18: =T18 -> 0 | AT18: =W18 -> 0 | AU18: =Z18 -> 0 | AV18: =AC18 -> 0 | AW18: =AF18 -> 0 | AX18: =AI18 -> 0 | AY18: =AL18 -> 0 | BA18: =N18 -> 0 | BB18: =Z18 -> 0 | BC18: =AL18 -> 0
A20: Equity
A21: Paid-in Capital | B21: Starting paid-in capital + cumulative equity raised | C21: ='Assumptions'!$F$9+'Working Capital'!C30 -> 0 | D21: ='Assumptions'!$F$9+'Working Capital'!D30 -> 0 | E21: ='Assumptions'!$F$9+'Working Capital'!E30 -> 0 | F21: ='Assumptions'!$F$9+'Working Capital'!F30 -> 0 | G21: ='Assumptions'!$F$9+'Working Capital'!G30 -> 0 | H21: ='Assumptions'!$F$9+'Working Capital'!H30 -> 0 | I21: ='Assumptions'!$F$9+'Working Capital'!I30 -> 0 | J21: ='Assumptions'!$F$9+'Working Capital'!J30 -> 0 | ... AL21: ='Assumptions'!$F$9+'Working Capital'!AL30 -> 0 | AN21: =E21 -> 0 | AO21: =H21 -> 0 | AP21: =K21 -> 0 | AQ21: =N21 -> 0 | AR21: =Q21 -> 0 | AS21: =T21 -> 0 | AT21: =W21 -> 0 | AU21: =Z21 -> 0 | AV21: =AC21 -> 0 | AW21: =AF21 -> 0 | AX21: =AI21 -> 0 | AY21: =AL21 -> 0 | BA21: =N21 -> 0 | BB21: =Z21 -> 0 | BC21: =AL21 -> 0
A22: Retained Earnings | B22: Starting RE (= starting cash − starting paid-in capital) + cumulative Net Income | C22: =('Assumptions'!$F$8-'Assumptions'!$F$9)+'P&L'!C24 -> 0 | D22: =C22+'P&L'!D24 -> 0 | E22: =D22+'P&L'!E24 -> 0 | F22: =E22+'P&L'!F24 -> 0 | G22: =F22+'P&L'!G24 -> 0 | H22: =G22+'P&L'!H24 -> 0 | I22: =H22+'P&L'!I24 -> 0 | J22: =I22+'P&L'!J24 -> 0 | K22: =J22+'P&L'!K24 -> 0 | ... AL22: =AK22+'P&L'!AL24 -> 0 | AN22: =E22 -> 0 | AO22: =H22 -> 0 | AP22: =K22 -> 0 | AQ22: =N22 -> 0 | AR22: =Q22 -> 0 | AS22: =T22 -> 0 | AT22: =W22 -> 0 | AU22: =Z22 -> 0 | AV22: =AC22 -> 0 | AW22: =AF22 -> 0 | AX22: =AI22 -> 0 | AY22: =AL22 -> 0 | BA22: =N22 -> 0 | BB22: =Z22 -> 0 | BC22: =AL22 -> 0
A23: Total Equity | C23: =C21+C22 -> 0 | D23: =D21+D22 -> 0 | E23: =E21+E22 -> 0 | F23: =F21+F22 -> 0 | G23: =G21+G22 -> 0 | H23: =H21+H22 -> 0 | I23: =I21+I22 -> 0 | J23: =J21+J22 -> 0 | ... AL23: =AL21+AL22 -> 0 | AN23: =E23 -> 0 | AO23: =H23 -> 0 | AP23: =K23 -> 0 | AQ23: =N23 -> 0 | AR23: =Q23 -> 0 | AS23: =T23 -> 0 | AT23: =W23 -> 0 | AU23: =Z23 -> 0 | AV23: =AC23 -> 0 | AW23: =AF23 -> 0 | AX23: =AI23 -> 0 | AY23: =AL23 -> 0 | BA23: =N23 -> 0 | BB23: =Z23 -> 0 | BC23: =AL23 -> 0
A24: Total Liabilities + Equity | C24: =C18+C23 -> 0 | D24: =D18+D23 -> 0 | E24: =E18+E23 -> 0 | F24: =F18+F23 -> 0 | G24: =G18+G23 -> 0 | H24: =H18+H23 -> 0 | I24: =I18+I23 -> 0 | J24: =J18+J23 -> 0 | ... AL24: =AL18+AL23 -> 0 | AN24: =E24 -> 0 | AO24: =H24 -> 0 | AP24: =K24 -> 0 | AQ24: =N24 -> 0 | AR24: =Q24 -> 0 | AS24: =T24 -> 0 | AT24: =W24 -> 0 | AU24: =Z24 -> 0 | AV24: =AC24 -> 0 | AW24: =AF24 -> 0 | AX24: =AI24 -> 0 | AY24: =AL24 -> 0 | BA24: =N24 -> 0 | BB24: =Z24 -> 0 | BC24: =AL24 -> 0
A26: Balance check (Assets − Liab&Equity) | B26: Must equal ~0 every month | C26: =C12-C24 -> 0 | D26: =D12-D24 -> 0 | E26: =E12-E24 -> 0 | F26: =F12-F24 -> 0 | G26: =G12-G24 -> 0 | H26: =H12-H24 -> 0 | I26: =I12-I24 -> 0 | J26: =J12-J24 -> 0 | ... AL26: =AL12-AL24 -> 0 | AN26: =E26 -> 0 | AO26: =H26 -> 0 | AP26: =K26 -> 0 | AQ26: =N26 -> 0 | AR26: =Q26 -> 0 | AS26: =T26 -> 0 | AT26: =W26 -> 0 | AU26: =Z26 -> 0 | AV26: =AC26 -> 0 | AW26: =AF26 -> 0 | AX26: =AI26 -> 0 | AY26: =AL26 -> 0 | BA26: =N26 -> 0 | BB26: =Z26 -> 0 | BC26: =AL26 -> 0

Sheet Cash & Runway
A1: B2B SaaS + Usage — 3-Year Financial Model — Cash & Runway
A2: Burn rate and runway — reconciled to the Cash Flow tab.
A5: Line item | B5: Units / source | C5: Monthly (36 months) | AN5: Quarterly | BA5: Annual
C6: 46023 | D6: 46054 | E6: 46082 | F6: 46113 | G6: 46143 | H6: 46174 | I6: 46204 | J6: 46235 | K6: 46266 | L6: 46296 | M6: 46327 | N6: 46357 | O6: 46388 | P6: 46419 | Q6: 46447 | R6: 46478 | S6: 46508 | T6: 46539 | U6: 46569 | V6: 46600 | W6: 46631 | X6: 46661 | Y6: 46692 | Z6: 46722 | AA6: 46753 | AB6: 46784 | AC6: 46813 | AD6: 46844 | AE6: 46874 | AF6: 46905 | AG6: 46935 | AH6: 46966 | AI6: 46997 | AJ6: 47027 | AK6: 47058 | AL6: 47088 | AN6: Q1 | AO6: Q2 | AP6: Q3 | AQ6: Q4 | AR6: Q5 | AS6: Q6 | AT6: Q7 | AU6: Q8 | AV6: Q9 | AW6: Q10 | AX6: Q11 | AY6: Q12 | BA6: FY1 | BB6: FY2 | BC6: FY3
A7: Cash Position
A8: Ending Cash Balance | C8: ='Cash Flow'!$C$28 -> 0 | D8: ='Cash Flow'!$D$28 -> 0 | E8: ='Cash Flow'!$E$28 -> 0 | F8: ='Cash Flow'!$F$28 -> 0 | G8: ='Cash Flow'!$G$28 -> 0 | H8: ='Cash Flow'!$H$28 -> 0 | I8: ='Cash Flow'!$I$28 -> 0 | J8: ='Cash Flow'!$J$28 -> 0 | K8: ='Cash Flow'!$K$28 -> 0 | L8: ='Cash Flow'!$L$28 -> 0 | M8: ='Cash Flow'!$M$28 -> 0 | N8: ='Cash Flow'!$N$28 -> 0 | O8: ='Cash Flow'!$O$28 -> 0 | P8: ='Cash Flow'!$P$28 -> 0 | Q8: ='Cash Flow'!$Q$28 -> 0 | R8: ='Cash Flow'!$R$28 -> 0 | S8: ='Cash Flow'!$S$28 -> 0 | T8: ='Cash Flow'!$T$28 -> 0 | U8: ='Cash Flow'!$U$28 -> 0 | V8: ='Cash Flow'!$V$28 -> 0 | W8: ='Cash Flow'!$W$28 -> 0 | X8: ='Cash Flow'!$X$28 -> 0 | Y8: ='Cash Flow'!$Y$28 -> 0 | Z8: ='Cash Flow'!$Z$28 -> 0 | AA8: ='Cash Flow'!$AA$28 -> 0 | AB8: ='Cash Flow'!$AB$28 -> 0 | AC8: ='Cash Flow'!$AC$28 -> 0 | AD8: ='Cash Flow'!$AD$28 -> 0 | AE8: ='Cash Flow'!$AE$28 -> 0 | AF8: ='Cash Flow'!$AF$28 -> 0 | AG8: ='Cash Flow'!$AG$28 -> 0 | AH8: ='Cash Flow'!$AH$28 -> 0 | AI8: ='Cash Flow'!$AI$28 -> 0 | AJ8: ='Cash Flow'!$AJ$28 -> 0 | AK8: ='Cash Flow'!$AK$28 -> 0 | AL8: ='Cash Flow'!$AL$28 -> 0 | AN8: =E8 -> 0 | AO8: =H8 -> 0 | AP8: =K8 -> 0 | AQ8: =N8 -> 0 | AR8: =Q8 -> 0 | AS8: =T8 -> 0 | AT8: =W8 -> 0 | AU8: =Z8 -> 0 | AV8: =AC8 -> 0 | AW8: =AF8 -> 0 | AX8: =AI8 -> 0 | AY8: =AL8 -> 0 | BA8: =N8 -> 0 | BB8: =Z8 -> 0 | BC8: =AL8 -> 0
A9: Monthly Net Burn (pre-financing) | B9: MAX(0, −(operating + investing cash flow)); excludes debt and equity proceeds | C9: =MAX(0,-('Cash Flow'!C14+'Cash Flow'!C18)) -> 0 | D9: =MAX(0,-('Cash Flow'!D14+'Cash Flow'!D18)) -> 0 | E9: =MAX(0,-('Cash Flow'!E14+'Cash Flow'!E18)) -> 0 | F9: =MAX(0,-('Cash Flow'!F14+'Cash Flow'!F18)) -> 0 | G9: =MAX(0,-('Cash Flow'!G14+'Cash Flow'!G18)) -> 0 | H9: =MAX(0,-('Cash Flow'!H14+'Cash Flow'!H18)) -> 0 | I9: =MAX(0,-('Cash Flow'!I14+'Cash Flow'!I18)) -> 0 | J9: =MAX(0,-('Cash Flow'!J14+'Cash Flow'!J18)) -> 0 | ... AL9: =MAX(0,-('Cash Flow'!AL14+'Cash Flow'!AL18)) -> 0 | AN9: =SUM(C9:E9) -> 0 | AO9: =SUM(F9:H9) -> 0 | AP9: =SUM(I9:K9) -> 0 | AQ9: =SUM(L9:N9) -> 0 | AR9: =SUM(O9:Q9) -> 0 | AS9: =SUM(R9:T9) -> 0 | AT9: =SUM(U9:W9) -> 0 | AU9: =SUM(X9:Z9) -> 0 | AV9: =SUM(AA9:AC9) -> 0 | AW9: =SUM(AD9:AF9) -> 0 | AX9: =SUM(AG9:AI9) -> 0 | AY9: =SUM(AJ9:AL9) -> 0 | BA9: =SUM(C9:N9) -> 0 | BB9: =SUM(O9:Z9) -> 0 | BC9: =SUM(AA9:AL9) -> 0
A10: Trailing 3-Month Avg Burn | C10: =AVERAGE(C9:C9) -> 0 | D10: =AVERAGE(C9:D9) -> 0 | E10: =AVERAGE(C9:E9) -> 0 | F10: =AVERAGE(D9:F9) -> 0 | G10: =AVERAGE(E9:G9) -> 0 | H10: =AVERAGE(F9:H9) -> 0 | I10: =AVERAGE(G9:I9) -> 0 | J10: =AVERAGE(H9:J9) -> 0 | K10: =AVERAGE(I9:K9) -> 0 | L10: =AVERAGE(J9:L9) -> 0 | ... AL10: =AVERAGE(AJ9:AL9) -> 0 | AN10: =AVERAGE(C10:E10) -> 0 | AO10: =AVERAGE(F10:H10) -> 0 | AP10: =AVERAGE(I10:K10) -> 0 | AQ10: =AVERAGE(L10:N10) -> 0 | AR10: =AVERAGE(O10:Q10) -> 0 | AS10: =AVERAGE(R10:T10) -> 0 | AT10: =AVERAGE(U10:W10) -> 0 | AU10: =AVERAGE(X10:Z10) -> 0 | AV10: =AVERAGE(AA10:AC10) -> 0 | AW10: =AVERAGE(AD10:AF10) -> 0 | AX10: =AVERAGE(AG10:AI10) -> 0 | AY10: =AVERAGE(AJ10:AL10) -> 0 | BA10: =AVERAGE(C10:N10) -> 0 | BB10: =AVERAGE(O10:Z10) -> 0 | BC10: =AVERAGE(AA10:AL10) -> 0
A11: Runway (months) | B11: Ending cash ÷ trailing 3-month pre-financing burn; 0 if cash is depleted; 999 if cash-flow positive | C11: =IF(C8<=0,0,IF(C10<=0,999,C8/C10)) -> 0 | D11: =IF(D8<=0,0,IF(D10<=0,999,D8/D10)) -> 0 | E11: =IF(E8<=0,0,IF(E10<=0,999,E8/E10)) -> 0 | F11: =IF(F8<=0,0,IF(F10<=0,999,F8/F10)) -> 0 | G11: =IF(G8<=0,0,IF(G10<=0,999,G8/G10)) -> 0 | H11: =IF(H8<=0,0,IF(H10<=0,999,H8/H10)) -> 0 | I11: =IF(I8<=0,0,IF(I10<=0,999,I8/I10)) -> 0 | J11: =IF(J8<=0,0,IF(J10<=0,999,J8/J10)) -> 0 | ... AL11: =IF(AL8<=0,0,IF(AL10<=0,999,AL8/AL10)) -> 0 | AN11: =E11 -> 0 | AO11: =H11 -> 0 | AP11: =K11 -> 0 | AQ11: =N11 -> 0 | AR11: =Q11 -> 0 | AS11: =T11 -> 0 | AT11: =W11 -> 0 | AU11: =Z11 -> 0 | AV11: =AC11 -> 0 | AW11: =AF11 -> 0 | AX11: =AI11 -> 0 | AY11: =AL11 -> 0 | BA11: =N11 -> 0 | BB11: =Z11 -> 0 | BC11: =AL11 -> 0
A13: Headline
A14: Runway as of final month (36) | C14: =IF(AL8<=0,0,IF(AL10<=0,"Cash-flow positive",AL11)) -> 0

Sheet Scenarios
A1: B2B SaaS + Usage — 3-Year Financial Model — Scenario Comparison
A2: Base/Upside/Downside columns are a fast analytical approximation for side-by-side comparison. The 'Full model' column reflects the detailed 36-month model at the scenario currently selected on the Assumptions tab.
A4: Currently selected scenario: | C4: ='Assumptions'!$C$4 -> 0
A6: KPI | B6: Definition | C6: Base | D6: Upside | E6: Downside | F6: Full model (selected)
A7: Starting ARR (Month 1 run-rate) | B7: Starting customers x starting ARPA x 12 | C7: ='Assumptions'!$C$13*'Assumptions'!$C$21*12 -> 0 | D7: ='Assumptions'!$D$13*'Assumptions'!$D$21*12 -> 0 | E7: ='Assumptions'!$E$13*'Assumptions'!$E$21*12 -> 0 | F7: ='Revenue'!C21 -> 0
A8: Net Revenue Retention (illustrative) | B8: 1 + expansion − contraction − churn (constant-rate approximation) | C8: =1+'Assumptions'!$C$17-'Assumptions'!$C$18-'Assumptions'!$C$16 -> 0 | D8: =1+'Assumptions'!$D$17-'Assumptions'!$D$18-'Assumptions'!$D$16 -> 0 | E8: =1+'Assumptions'!$E$17-'Assumptions'!$E$18-'Assumptions'!$E$16 -> 0 | F8: ='Revenue'!AL31 -> 0
A9: Implied ARR at Month 36 (approx.) | B9: Month-1 ARR compounded at (NRR-1 + new-logo rate) for 35 months — a rough trend estimate, not the detailed model | C9: =('Assumptions'!$C$13*'Assumptions'!$C$21*12)*(1+('Assumptions'!$C$17-'Assumptions'!$C$18-'Assumptions'!$C$16+'Assumptions'!$C$14/'Assumptions'!$C$13))^35 -> 0 | D9: =('Assumptions'!$D$13*'Assumptions'!$D$21*12)*(1+('Assumptions'!$D$17-'Assumptions'!$D$18-'Assumptions'!$D$16+'Assumptions'!$D$14/'Assumptions'!$D$13))^35 -> 0 | E9: =('Assumptions'!$E$13*'Assumptions'!$E$21*12)*(1+('Assumptions'!$E$17-'Assumptions'!$E$18-'Assumptions'!$E$16+'Assumptions'!$E$14/'Assumptions'!$E$13))^35 -> 0 | F9: ='Revenue'!AL21 -> 0
A10: Gross Margin % (illustrative, Month 1) | B10: 1 − variable COGS % − CS people cost ÷ ARR1 | C10: =1-('Assumptions'!$C$27+'Assumptions'!$C$28+'Assumptions'!$C$29)-(('Assumptions'!$C$32*'Assumptions'!$C$34)*12)/('Assumptions'!$C$13*'Assumptions'!$C$21*12) -> 0 | D10: =1-('Assumptions'!$D$27+'Assumptions'!$D$28+'Assumptions'!$D$29)-(('Assumptions'!$D$32*'Assumptions'!$D$34)*12)/('Assumptions'!$D$13*'Assumptions'!$D$21*12) -> 0 | E10: =1-('Assumptions'!$E$27+'Assumptions'!$E$28+'Assumptions'!$E$29)-(('Assumptions'!$E$32*'Assumptions'!$E$34)*12)/('Assumptions'!$E$13*'Assumptions'!$E$21*12) -> 0 | F10: ='COGS & GM'!AL16 -> 0
A11: Month-1 Net Burn (illustrative) | B11: Month-1 headcount cost + variable COGS − Month-1 revenue | C11: =MAX(0,('Assumptions'!$C$32*'Assumptions'!$C$34+'Assumptions'!$C$37*'Assumptions'!$C$39+'Assumptions'!$C$40*'Assumptions'!$C$42+'Assumptions'!$C$45*'Assumptions'!$C$47+'Assumptions'!$C$50*'Assumptions'!$C$52)+(('Assumptions'!$C$13*'Assumptions'!$C$21*12)/12)*(('Assumptions'!$C$27+'Assumptions'!$C$28+'Assumptions'!$C$29))-(('Assumptions'!$C$13*'Assumptions'!$C$21*12)/12)) -> 0 | D11: =MAX(0,('Assumptions'!$D$32*'Assumptions'!$D$34+'Assumptions'!$D$37*'Assumptions'!$D$39+'Assumptions'!$D$40*'Assumptions'!$D$42+'Assumptions'!$D$45*'Assumptions'!$D$47+'Assumptions'!$D$50*'Assumptions'!$D$52)+(('Assumptions'!$D$13*'Assumptions'!$D$21*12)/12)*(('Assumptions'!$D$27+'Assumptions'!$D$28+'Assumptions'!$D$29))-(('Assumptions'!$D$13*'Assumptions'!$D$21*12)/12)) -> 0 | E11: =MAX(0,('Assumptions'!$E$32*'Assumptions'!$E$34+'Assumptions'!$E$37*'Assumptions'!$E$39+'Assumptions'!$E$40*'Assumptions'!$E$42+'Assumptions'!$E$45*'Assumptions'!$E$47+'Assumptions'!$E$50*'Assumptions'!$E$52)+(('Assumptions'!$E$13*'Assumptions'!$E$21*12)/12)*(('Assumptions'!$E$27+'Assumptions'!$E$28+'Assumptions'!$E$29))-(('Assumptions'!$E$13*'Assumptions'!$E$21*12)/12)) -> 0 | F11: ='Cash & Runway'!C9 -> 0
A12: Runway (illustrative, months) | B12: Starting cash ÷ Month-1 net burn | C12: =IFERROR('Assumptions'!$C$8/MAX(1,MAX(0,('Assumptions'!$C$32*'Assumptions'!$C$34+'Assumptions'!$C$37*'Assumptions'!$C$39+'Assumptions'!$C$40*'Assumptions'!$C$42+'Assumptions'!$C$45*'Assumptions'!$C$47+'Assumptions'!$C$50*'Assumptions'!$C$52)+(('Assumptions'!$C$13*'Assumptions'!$C$21*12)/12)*(('Assumptions'!$C$27+'Assumptions'!$C$28+'Assumptions'!$C$29))-(('Assumptions'!$C$13*'Assumptions'!$C$21*12)/12))),999) -> 0 | D12: =IFERROR('Assumptions'!$D$8/MAX(1,MAX(0,('Assumptions'!$D$32*'Assumptions'!$D$34+'Assumptions'!$D$37*'Assumptions'!$D$39+'Assumptions'!$D$40*'Assumptions'!$D$42+'Assumptions'!$D$45*'Assumptions'!$D$47+'Assumptions'!$D$50*'Assumptions'!$D$52)+(('Assumptions'!$D$13*'Assumptions'!$D$21*12)/12)*(('Assumptions'!$D$27+'Assumptions'!$D$28+'Assumptions'!$D$29))-(('Assumptions'!$D$13*'Assumptions'!$D$21*12)/12))),999) -> 0 | E12: =IFERROR('Assumptions'!$E$8/MAX(1,MAX(0,('Assumptions'!$E$32*'Assumptions'!$E$34+'Assumptions'!$E$37*'Assumptions'!$E$39+'Assumptions'!$E$40*'Assumptions'!$E$42+'Assumptions'!$E$45*'Assumptions'!$E$47+'Assumptions'!$E$50*'Assumptions'!$E$52)+(('Assumptions'!$E$13*'Assumptions'!$E$21*12)/12)*(('Assumptions'!$E$27+'Assumptions'!$E$28+'Assumptions'!$E$29))-(('Assumptions'!$E$13*'Assumptions'!$E$21*12)/12))),999) -> 0 | F12: ='Cash & Runway'!AL11 -> 0
A14: Scenario Validity
A15: Selector value is valid (Base/Upside/Downside)? | C15: =IF(ISNUMBER(MATCH('Assumptions'!$C$4,{"Base","Upside","Downside"},0)),"OK","INVALID") -> 0

Sheet Visuals
A1: B2B SaaS + Usage — 3-Year Financial Model — Visuals
A2: ARR, retention, margin, cash, and headcount trends for the B2B SaaS + Usage model.
A4: ARR (Month 36) | D4: Gross Margin % (Month 36) | G4: Net Revenue Retention (Month 36) | J4: Ending Cash (Month 36) | M4: Runway (months) | P4: Total Headcount (Month 36)
A5: ='Revenue'!AL21 -> 0 | D5: ='COGS & GM'!AL16 -> 0 | G5: ='Revenue'!AL31 -> 0 | J5: ='Cash & Runway'!AL8 -> 0 | M5: ='Cash & Runway'!AL11 -> 0 | P5: ='Headcount'!AL22 -> 0

Sheet Checks
A1: B2B SaaS + Usage — 3-Year Financial Model — Checks
A2: Every control below should read PASS. If anything reads FAIL, trace it back through the linked tabs before trusting the outputs.
A4: Check | B4: Description | C4: Metric | D4: Status
A5: Balance Sheet balances | B5: MAX absolute (Assets − Liabilities&Equity) across all 36 months | C5: {=MAX(ABS('Balance Sheet'!C26:AL26))} -> 0 | D5: {=IF(MAX(ABS('Balance Sheet'!C26:AL26))<1.0,"PASS","FAIL")} -> 0
A6: Cash Flow reconciles to Balance Sheet | B6: MAX absolute difference between BS cash and CF ending cash across all 36 months | C6: {=MAX(ABS('Balance Sheet'!C8:AL8-'Cash Flow'!C28:AL28))} -> 0 | D6: {=IF(MAX(ABS('Balance Sheet'!C8:AL8-'Cash Flow'!C28:AL28))<1.0,"PASS","FAIL")} -> 0
A7: Retained Earnings roll-forward | B7: MAX absolute (RE(m) − RE(m−1) − NetIncome(m)) for months 2-36 | C7: {=MAX(ABS('Balance Sheet'!D22:AL22-'Balance Sheet'!C22:AK22-'P&L'!D24:AL24))} -> 0 | D7: {=IF(MAX(ABS('Balance Sheet'!D22:AL22-'Balance Sheet'!C22:AK22-'P&L'!D24:AL24))<1.0,"PASS","FAIL")} -> 0
A8: P&L subtotal integrity | B8: MAX absolute error across Gross Profit / EBITDA / EBIT / EBT / Net Income subtotals | C8: {=MAX(MAX(ABS(('P&L'!C7:AL7-'P&L'!C8:AL8)-'P&L'!C9:AL9)),MAX(ABS(('P&L'!C9:AL9-'P&L'!C16:AL16)-'P&L'!C18:AL18)),MAX(ABS(('P&L'!C18:AL18-'P&L'!C19:AL19)-'P&L'!C20:AL20)),MAX(ABS(('P&L'!C20:AL20-'P&L'!C21:AL21)-'P&L'!C22:AL22)),MAX(ABS(('P&L'!C22:AL22-'P&L'!C23:AL23)-'P&L'!C24:AL24)))} -> 0 | D8: {=IF(MAX(MAX(ABS(('P&L'!C7:AL7-'P&L'!C8:AL8)-'P&L'!C9:AL9)),MAX(ABS(('P&L'!C9:AL9-'P&L'!C16:AL16)-'P&L'!C18:AL18)),MAX(ABS(('P&L'!C18:AL18-'P&L'!C19:AL19)-'P&L'!C20:AL20)),MAX(ABS(('P&L'!C20:AL20-'P&L'!C21:AL21)-'P&L'!C22:AL22)),MAX(ABS(('P&L'!C22:AL22-'P&L'!C23:AL23)-'P&L'!C24:AL24)))<1.0,"PASS","FAIL")} -> 0
A9: Scenario selector validity | B9: Assumptions scenario selector must equal Base, Upside, or Downside | C9: {=IF('Scenarios'!C15="OK",1,0)} -> 0 | D9: {=IF('Scenarios'!C15="OK","PASS","FAIL")} -> 0
A10: No formula errors | B10: Count of #REF!/#DIV0!/#VALUE! etc. across all key schedules (Headcount through Cash & Runway) | C10: {=SUMPRODUCT(--ISERROR('Headcount'!C5:BC260))+SUMPRODUCT(--ISERROR('Revenue'!C5:BC260))+SUMPRODUCT(--ISERROR('COGS & GM'!C5:BC260))+SUMPRODUCT(--ISERROR('Opex'!C5:BC260))+SUMPRODUCT(--ISERROR('Working Capital'!C5:BC260))+SUMPRODUCT(--ISERROR('P&L'!C5:BC260))+SUMPRODUCT(--ISERROR('Balance Sheet'!C5:BC260))+SUMPRODUCT(--ISERROR('Cash Flow'!C5:BC260))+SUMPRODUCT(--ISERROR('Cash & Runway'!C5:BC260))} -> 0 | D10: {=IF((SUMPRODUCT(--ISERROR('Headcount'!C5:BC260))+SUMPRODUCT(--ISERROR('Revenue'!C5:BC260))+SUMPRODUCT(--ISERROR('COGS & GM'!C5:BC260))+SUMPRODUCT(--ISERROR('Opex'!C5:BC260))+SUMPRODUCT(--ISERROR('Working Capital'!C5:BC260))+SUMPRODUCT(--ISERROR('P&L'!C5:BC260))+SUMPRODUCT(--ISERROR('Balance Sheet'!C5:BC260))+SUMPRODUCT(--ISERROR('Cash Flow'!C5:BC260))+SUMPRODUCT(--ISERROR('Cash & Runway'!C5:BC260)))=0,"PASS","FAIL")} -> 0
A12: ALL CHECKS | B12: Overall model integrity status | D12: =IF(AND(D5="PASS",D6="PASS",D7="PASS",D8="PASS",D9="PASS",D10="PASS"),"ALL PASS","REVIEW NEEDED") -> 0
