Workbook

Sheet Read Me
A1: Consumer Subscription — 3-Year Financial Model
A2: 36-month integrated financial model — Read Me
A4: Overview
A5: A 36-month, formula-driven financial model for a consumer subscription business. Start on the Assumptions tab: set Base / Upside / Downside inputs and pick a scenario. Every downstream tab recalculates automatically across acquisition, MAU, paid conversion, revenue, costs, burn, and runway.
A7: How this workbook is organized
A8: Assumptions -> Headcount -> Revenue -> COGS & GM -> Opex -> Working Capital -> P&L -> Balance Sheet -> Cash Flow -> Cash & Runway -> Scenarios -> Visuals -> Checks. Data flows strictly left-to-right through that order: change an assumption, and every downstream tab recalculates automatically (workbook calculation mode is Automatic).
A10: Formatting legend
A11: Blue text on light-blue fill = an input you can edit (Assumptions tab, and scenario selector).
A12: Black text on white = a live formula. Do not hard-code over these cells.
A13: Cells on a light-gray band = a value linked in from another tab.
A15: Color palette
A16: Purple (#7B68EE)
... A35: 36 monthly periods, plus quarterly (12) and annual (3) roll-up columns on each schedule tab. Workbook calculation is set to Automatic — Excel recalculates on every edit. Deterministic, seeded default assumptions are provided so the model is internally consistent out of the box; replace them with your own numbers on the Assumptions tab.

Sheet Assumptions
A1: Consumer Subscription — 3-Year Financial Model — Assumptions
A2: Plain-language inputs. Edit the Base / Upside / Downside columns only — everything else in this workbook is a formula.
A4: Scenario selector: | C4: Base | D4: << Pick Base / Upside / Downside. This one cell drives every formula in the model.
A6: Assumption | B6: Unit | C6: Base | D6: Upside | E6: Downside | F6: Active (used in model) | G6: Notes / definition
A7: Company & Financial
A8: Starting cash balance | B8: $ | C8: 2250000 | D8: 2250000 | E8: 2250000 | F8: =CHOOSE(MATCH('Assumptions'!$C$4,{"Base","Upside","Downside"},0),C8,D8,E8) -> 0 | G8: Cash on hand at the start of month 1.
A9: Starting paid-in capital | B9: $ | C9: 3000000 | D9: 3000000 | E9: 3000000 | F9: =CHOOSE(MATCH('Assumptions'!$C$4,{"Base","Upside","Downside"},0),C9,D9,E9) -> 0 | G9: Cumulative equity raised before the modeled period.
A10: Income tax rate | B10: % | C10: 0 | D10: 0 | E10: 0 | F10: =CHOOSE(MATCH('Assumptions'!$C$4,{"Base","Upside","Downside"},0),C10,D10,E10) -> 0 | G10: Applied only when Earnings Before Tax is positive; no NOL schedule modeled.
A12: Acquisition & Funnel
A13: Starting monthly active users (MAU) | B13: # | C13: 80000 | D13: 90000 | E13: 70000 | F13: =CHOOSE(MATCH('Assumptions'!$C$4,{"Base","Upside","Downside"},0),C13,D13,E13) -> 0 | G13: All active users at the start of month 1, including paid subscribers.
A14: Monthly active-user churn rate | B14: % | C14: 0.08 | D14: 0.06 | E14: 0.105 | F14: =CHOOSE(MATCH('Assumptions'!$C$4,{"Base","Upside","Downside"},0),C14,D14,E14) -> 0 | G14: Share of beginning MAU that goes inactive each month.
A15: Starting paid subscribers | B15: # | C15: 4000 | D15: 4500 | E15: 3500 | F15: =CHOOSE(MATCH('Assumptions'!$C$4,{"Base","Upside","Downside"},0),C15,D15,E15) -> 0 | G15: Active subscribers paying at the start of month 1.
A16: Paid-channel new signups, month 1 | B16: # | C16: 2500 | D16: 3000 | E16: 2000 | F16: =CHOOSE(MATCH('Assumptions'!$C$4,{"Base","Upside","Downside"},0),C16,D16,E16) -> 0 | G16: Users acquired from paid media in month 1.
A17: Paid-channel signups growth, month over month | B17: % | C17: 0.0635 | D17: 0.0943 | E17: 0.0147 | F17: =CHOOSE(MATCH('Assumptions'!$C$4,{"Base","Upside","Downside"},0),C17,D17,E17) -> 0 | G17: Compounding growth in paid-media signups each month.
A18: Paid-channel CAC per new signup | B18: $/user | C18: 28 | D18: 24 | E18: 34 | F18: =CHOOSE(MATCH('Assumptions'!$C$4,{"Base","Upside","Downside"},0),C18,D18,E18) -> 0 | G18: Blended paid-media acquisition cost per new user.
A19: Organic / viral new signups, month 1 | B19: # | C19: 3500 | D19: 4200 | E19: 2800 | F19: =CHOOSE(MATCH('Assumptions'!$C$4,{"Base","Upside","Downside"},0),C19,D19,E19) -> 0 | G19: Users arriving via word-of-mouth, SEO, app-store discovery, and product virality.
A20: Organic / viral signups growth, month over month | B20: % | C20: 0.0279 | D20: 0.0607 | E20: 0.012 | F20: =CHOOSE(MATCH('Assumptions'!$C$4,{"Base","Upside","Downside"},0),C20,D20,E20) -> 0 | G20: Organic signups often scale with awareness and product-market fit.
A21: Organic / viral CAC equivalent per signup | B21: $/user | C21: 4 | D21: 3 | E21: 5.5 | F21: =CHOOSE(MATCH('Assumptions'!$C$4,{"Base","Upside","Downside"},0),C21,D21,E21) -> 0 | G21: Represents community/content/program costs allocated per organic user.
A22: Influencer / referral new signups, month 1 | B22: # | C22: 1200 | D22: 1500 | E22: 900 | F22: =CHOOSE(MATCH('Assumptions'!$C$4,{"Base","Upside","Downside"},0),C22,D22,E22) -> 0 | G22: Users acquired from creators, affiliate partners, and referral loops.
A23: Influencer / referral signups growth, month over month | B23: % | C23: 0.0422 | D23: 0.0625 | E23: 0.0075 | F23: =CHOOSE(MATCH('Assumptions'!$C$4,{"Base","Upside","Downside"},0),C23,D23,E23) -> 0 | G23: Compounding growth in creator and referral-driven acquisition.
A24: Influencer / referral CAC per new signup | B24: $/user | C24: 16 | D24: 13 | E24: 20 | F24: =CHOOSE(MATCH('Assumptions'!$C$4,{"Base","Upside","Downside"},0),C24,D24,E24) -> 0 | G24: Creator fees, referral rewards, and affiliate payouts per acquired user.
A26: Retention & Monetization
A27: Free-to-paid conversion rate | B27: % | C27: 0.025 | D27: 0.032 | E27: 0.018 | F27: =CHOOSE(MATCH('Assumptions'!$C$4,{"Base","Upside","Downside"},0),C27,D27,E27) -> 0 | G27: Share of free MAU that converts to paid each month.
A28: Paid subscriber churn rate | B28: % | C28: 0.045 | D28: 0.032 | E28: 0.06 | F28: =CHOOSE(MATCH('Assumptions'!$C$4,{"Base","Upside","Downside"},0),C28,D28,E28) -> 0 | G28: Monthly churn of beginning paid subscribers.
A29: Plus plan price per subscriber | B29: $/mo | C29: 12 | D29: 13 | E29: 11 | F29: =CHOOSE(MATCH('Assumptions'!$C$4,{"Base","Upside","Downside"},0),C29,D29,E29) -> 0 | G29: Blended realized monthly price for the standard paid tier.
A30: Premium / family plan price per subscriber | B30: $/mo | C30: 24 | D30: 26 | E30: 22 | F30: =CHOOSE(MATCH('Assumptions'!$C$4,{"Base","Upside","Downside"},0),C30,D30,E30) -> 0 | G30: Higher-value tier with more seats/features.
A31: Premium-tier mix, month 1 | B31: % | C31: 0.18 | D31: 0.24 | E31: 0.12 | F31: =CHOOSE(MATCH('Assumptions'!$C$4,{"Base","Upside","Downside"},0),C31,D31,E31) -> 0 | G31: Share of paid subscribers on the higher-value plan at the start of the model.
A32: Premium-tier mix shift, month over month | B32: % | C32: 0.0045 | D32: 0.007 | E32: -0.0006 | F32: =CHOOSE(MATCH('Assumptions'!$C$4,{"Base","Upside","Downside"},0),C32,D32,E32) -> 0 | G32: Monthly change in premium-plan mix, capped inside the model.
A34: COGS & Platform Fees
A35: App-store / platform fee, % of revenue | B35: % | C35: 0.18 | D35: 0.15 | E35: 0.22 | F35: =CHOOSE(MATCH('Assumptions'!$C$4,{"Base","Upside","Downside"},0),C35,D35,E35) -> 0 | G35: Blended app-store take rate / merchant-of-record fee on subscription revenue.
A36: Payment processing fee, % of revenue | B36: % | C36: 0.03 | D36: 0.025 | E36: 0.035 | F36: =CHOOSE(MATCH('Assumptions'!$C$4,{"Base","Upside","Downside"},0),C36,D36,E36) -> 0 | G36: Card and payment-processor fees on direct-web billing.
A37: Hosting & infra cost per MAU | B37: $/MAU/mo | C37: 0.35 | D37: 0.3 | E37: 0.42 | F37: =CHOOSE(MATCH('Assumptions'!$C$4,{"Base","Upside","Downside"},0),C37,D37,E37) -> 0 | G37: Storage, delivery, and core application infrastructure per active user.
A38: AI inference / premium support cost per paid subscriber | B38: $/sub/mo | C38: 1.8 | D38: 1.5 | E38: 2.2 | F38: =CHOOSE(MATCH('Assumptions'!$C$4,{"Base","Upside","Downside"},0),C38,D38,E38) -> 0 | G38: Variable AI feature cost and premium support burden per active paid subscriber.
A40: Headcount — Support / Community Ops (COGS)
A41: Starting Support / Community Ops FTEs | B41: # | C41: 5 | D41: 5 | E41: 5 | F41: =CHOOSE(MATCH('Assumptions'!$C$4,{"Base","Upside","Downside"},0),C41,D41,E41) -> 0 | G41: Customer support, trust & safety, and community operations.
A42: Support / Community Ops net adds per quarter | B42: # | C42: 1 | D42: 1.5 | E42: 0.5 | F42: =CHOOSE(MATCH('Assumptions'!$C$4,{"Base","Upside","Downside"},0),C42,D42,E42) -> 0
A43: Support / Community Ops fully-loaded cost per FTE | B43: $/mo | C43: 7000 | D43: 7000 | E43: 7000 | F43: =CHOOSE(MATCH('Assumptions'!$C$4,{"Base","Upside","Downside"},0),C43,D43,E43) -> 0 | G43: Salary + benefits + payroll tax, monthly.
A45: Headcount — Growth / Marketing (Opex)
A46: Starting Growth / Marketing FTEs | B46: # | C46: 4 | D46: 4 | E46: 4 | F46: =CHOOSE(MATCH('Assumptions'!$C$4,{"Base","Upside","Downside"},0),C46,D46,E46) -> 0 | G46: Performance marketing, lifecycle CRM, and growth analytics.
A47: Growth / Marketing net adds per quarter | B47: # | C47: 1 | D47: 1.5 | E47: 0.5 | F47: =CHOOSE(MATCH('Assumptions'!$C$4,{"Base","Upside","Downside"},0),C47,D47,E47) -> 0
A48: Growth / Marketing fully-loaded cost per FTE | B48: $/mo | C48: 10000 | D48: 10000 | E48: 10000 | F48: =CHOOSE(MATCH('Assumptions'!$C$4,{"Base","Upside","Downside"},0),C48,D48,E48) -> 0
A50: Headcount — Product & Engineering (Opex)
A51: Starting Product / Engineering FTEs | B51: # | C51: 8 | D51: 8 | E51: 8 | F51: =CHOOSE(MATCH('Assumptions'!$C$4,{"Base","Upside","Downside"},0),C51,D51,E51) -> 0 | G51: Engineering, product, design, and data roles building the app.
A52: Product / Engineering net adds per quarter | B52: # | C52: 2 | D52: 2.5 | E52: 1 | F52: =CHOOSE(MATCH('Assumptions'!$C$4,{"Base","Upside","Downside"},0),C52,D52,E52) -> 0
A53: Product / Engineering fully-loaded cost per FTE | B53: $/mo | C53: 15000 | D53: 15000 | E53: 15000 | F53: =CHOOSE(MATCH('Assumptions'!$C$4,{"Base","Upside","Downside"},0),C53,D53,E53) -> 0
A55: Headcount — G&A (Opex)
A56: Starting G&A FTEs | B56: # | C56: 2 | D56: 2 | E56: 2 | F56: =CHOOSE(MATCH('Assumptions'!$C$4,{"Base","Upside","Downside"},0),C56,D56,E56) -> 0 | G56: Finance, HR, legal, and operations.
A57: G&A net adds per quarter | B57: # | C57: 0.5 | D57: 0.5 | E57: 0.25 | F57: =CHOOSE(MATCH('Assumptions'!$C$4,{"Base","Upside","Downside"},0),C57,D57,E57) -> 0
A58: G&A fully-loaded cost per FTE | B58: $/mo | C58: 11000 | D58: 11000 | E58: 11000 | F58: =CHOOSE(MATCH('Assumptions'!$C$4,{"Base","Upside","Downside"},0),C58,D58,E58) -> 0
A60: Marketing / Opex
A61: CRM / analytics / lifecycle tools | B61: $/mo | C61: 10000 | D61: 10000 | E61: 10000 | F61: =CHOOSE(MATCH('Assumptions'!$C$4,{"Base","Upside","Downside"},0),C61,D61,E61) -> 0 | G61: Braze/Iterable, attribution, mobile analytics, and experimentation tooling.
A62: Product software / tools | B62: $/mo | C62: 14000 | D62: 14000 | E62: 14000 | F62: =CHOOSE(MATCH('Assumptions'!$C$4,{"Base","Upside","Downside"},0),C62,D62,E62) -> 0 | G62: Developer tools, observability, data tooling, and collaboration software.
A63: Facilities / admin fixed monthly spend | B63: $/mo | C63: 8000 | D63: 8000 | E63: 8000 | F63: =CHOOSE(MATCH('Assumptions'!$C$4,{"Base","Upside","Downside"},0),C63,D63,E63) -> 0 | G63: Office, insurance, recruiting, audit, and other overhead.
A65: Working Capital & Financing
A66: Days Sales Outstanding (AR) | B66: days | C66: 3 | D66: 2 | E66: 5 | F66: =CHOOSE(MATCH('Assumptions'!$C$4,{"Base","Upside","Downside"},0),C66,D66,E66) -> 0 | G66: Low receivables balance reflecting payment-processor / app-store settlement timing.
A67: Days Payable Outstanding (AP) | B67: days | C67: 25 | D67: 28 | E67: 20 | F67: =CHOOSE(MATCH('Assumptions'!$C$4,{"Base","Upside","Downside"},0),C67,D67,E67) -> 0
A68: Deferred revenue held in advance | B68: mo | C68: 0.3 | D68: 0.4 | E68: 0.2 | F68: =CHOOSE(MATCH('Assumptions'!$C$4,{"Base","Upside","Downside"},0),C68,D68,E68) -> 0 | G68: Reflects modest annual-prepay or app-store cash received before recognition.
A69: Capex, % of revenue | B69: % | C69: 0.015 | D69: 0.012 | E69: 0.02 | F69: =CHOOSE(MATCH('Assumptions'!$C$4,{"Base","Upside","Downside"},0),C69,D69,E69) -> 0 | G69: Capitalized internal tools, office equipment, and small-scale infrastructure.
A70: Useful life of capitalized assets | B70: months | C70: 24 | D70: 24 | E70: 24 | F70: =CHOOSE(MATCH('Assumptions'!$C$4,{"Base","Upside","Downside"},0),C70,D70,E70) -> 0
A71: Other current assets, % of revenue | B71: % | C71: 0.02 | D71: 0.02 | E71: 0.02 | F71: =CHOOSE(MATCH('Assumptions'!$C$4,{"Base","Upside","Downside"},0),C71,D71,E71) -> 0 | G71: Prepaids, deposits, and other small current assets.
A72: Venture debt annual interest rate | B72: % | C72: 0.1 | D72: 0.09 | E72: 0.12 | F72: =CHOOSE(MATCH('Assumptions'!$C$4,{"Base","Upside","Downside"},0),C72,D72,E72) -> 0
A73: Venture debt draw (one-time) | B73: $ | C73: 500000 | D73: 750000 | E73: 350000 | F73: =CHOOSE(MATCH('Assumptions'!$C$4,{"Base","Upside","Downside"},0),C73,D73,E73) -> 0
A74: Venture debt monthly repayment | B74: $/mo | C74: 20000 | D74: 20000 | E74: 15000 | F74: =CHOOSE(MATCH('Assumptions'!$C$4,{"Base","Upside","Downside"},0),C74,D74,E74) -> 0
A75: Growth equity raise (month 6) | B75: $ | C75: 3000000 | D75: 4000000 | E75: 2250000 | F75: =CHOOSE(MATCH('Assumptions'!$C$4,{"Base","Upside","Downside"},0),C75,D75,E75) -> 0
A76: Follow-on equity raise (month 22) | B76: $ | C76: 6000000 | D76: 7500000 | E76: 4500000 | F76: =CHOOSE(MATCH('Assumptions'!$C$4,{"Base","Upside","Downside"},0),C76,D76,E76) -> 0
A79: Tip: start with Base, then stress-test acquisition, conversion, churn, platform fees, and burn in Upside / Downside.

Sheet Headcount
A1: Consumer Subscription — 3-Year Financial Model — Headcount
A2: Fully-loaded FTE ramps by role — flows into COGS or Opex by classification.
A5: Line item | B5: Units / source | C5: Monthly (36 months) | AN5: Quarterly | BA5: Annual
C6: 46023 | D6: 46054 | E6: 46082 | F6: 46113 | G6: 46143 | H6: 46174 | I6: 46204 | J6: 46235 | K6: 46266 | L6: 46296 | M6: 46327 | N6: 46357 | O6: 46388 | P6: 46419 | Q6: 46447 | R6: 46478 | S6: 46508 | T6: 46539 | U6: 46569 | V6: 46600 | W6: 46631 | X6: 46661 | Y6: 46692 | Z6: 46722 | AA6: 46753 | AB6: 46784 | AC6: 46813 | AD6: 46844 | AE6: 46874 | AF6: 46905 | AG6: 46935 | AH6: 46966 | AI6: 46997 | AJ6: 47027 | AK6: 47058 | AL6: 47088 | AN6: Q1 | AO6: Q2 | AP6: Q3 | AQ6: Q4 | AR6: Q5 | AS6: Q6 | AT6: Q7 | AU6: Q8 | AV6: Q9 | AW6: Q10 | AX6: Q11 | AY6: Q12 | BA6: FY1 | BB6: FY2 | BC6: FY3
A7: Cost of Goods Sold headcount (COGS-classified)
A8: Support / Community Ops — headcount (FTE) | B8: Cost of Revenue · start + net adds/qtr ÷ 3 | C8: =ROUND('Assumptions'!$F$41,1) -> 0 | D8: =ROUND(C8+'Assumptions'!$F$42/3,1) -> 0 | E8: =ROUND(D8+'Assumptions'!$F$42/3,1) -> 0 | F8: =ROUND(E8+'Assumptions'!$F$42/3,1) -> 0 | G8: =ROUND(F8+'Assumptions'!$F$42/3,1) -> 0 | H8: =ROUND(G8+'Assumptions'!$F$42/3,1) -> 0 | I8: =ROUND(H8+'Assumptions'!$F$42/3,1) -> 0 | J8: =ROUND(I8+'Assumptions'!$F$42/3,1) -> 0 | K8: =ROUND(J8+'Assumptions'!$F$42/3,1) -> 0 | ... AL8: =ROUND(AK8+'Assumptions'!$F$42/3,1) -> 0 | AN8: =E8 -> 0 | AO8: =H8 -> 0 | AP8: =K8 -> 0 | AQ8: =N8 -> 0 | AR8: =Q8 -> 0 | AS8: =T8 -> 0 | AT8: =W8 -> 0 | AU8: =Z8 -> 0 | AV8: =AC8 -> 0 | AW8: =AF8 -> 0 | AX8: =AI8 -> 0 | AY8: =AL8 -> 0 | BA8: =N8 -> 0 | BB8: =Z8 -> 0 | BC8: =AL8 -> 0
A9: Support / Community Ops — fully-loaded cost | B9: Headcount × monthly fully-loaded cost/FTE | C9: =C8*'Assumptions'!$F$43 -> 0 | D9: =D8*'Assumptions'!$F$43 -> 0 | E9: =E8*'Assumptions'!$F$43 -> 0 | F9: =F8*'Assumptions'!$F$43 -> 0 | G9: =G8*'Assumptions'!$F$43 -> 0 | H9: =H8*'Assumptions'!$F$43 -> 0 | I9: =I8*'Assumptions'!$F$43 -> 0 | J9: =J8*'Assumptions'!$F$43 -> 0 | ... AL9: =AL8*'Assumptions'!$F$43 -> 0 | AN9: =SUM(C9:E9) -> 0 | AO9: =SUM(F9:H9) -> 0 | AP9: =SUM(I9:K9) -> 0 | AQ9: =SUM(L9:N9) -> 0 | AR9: =SUM(O9:Q9) -> 0 | AS9: =SUM(R9:T9) -> 0 | AT9: =SUM(U9:W9) -> 0 | AU9: =SUM(X9:Z9) -> 0 | AV9: =SUM(AA9:AC9) -> 0 | AW9: =SUM(AD9:AF9) -> 0 | AX9: =SUM(AG9:AI9) -> 0 | AY9: =SUM(AJ9:AL9) -> 0 | BA9: =SUM(C9:N9) -> 0 | BB9: =SUM(O9:Z9) -> 0 | BC9: =SUM(AA9:AL9) -> 0
A11: Operating expense headcount (Opex-classified)
A12: Growth / Marketing — headcount (FTE) | B12: Growth & Marketing · start + net adds/qtr ÷ 3 | C12: =ROUND('Assumptions'!$F$46,1) -> 0 | D12: =ROUND(C12+'Assumptions'!$F$47/3,1) -> 0 | E12: =ROUND(D12+'Assumptions'!$F$47/3,1) -> 0 | F12: =ROUND(E12+'Assumptions'!$F$47/3,1) -> 0 | G12: =ROUND(F12+'Assumptions'!$F$47/3,1) -> 0 | H12: =ROUND(G12+'Assumptions'!$F$47/3,1) -> 0 | I12: =ROUND(H12+'Assumptions'!$F$47/3,1) -> 0 | J12: =ROUND(I12+'Assumptions'!$F$47/3,1) -> 0 | K12: =ROUND(J12+'Assumptions'!$F$47/3,1) -> 0 | ... AL12: =ROUND(AK12+'Assumptions'!$F$47/3,1) -> 0 | AN12: =E12 -> 0 | AO12: =H12 -> 0 | AP12: =K12 -> 0 | AQ12: =N12 -> 0 | AR12: =Q12 -> 0 | AS12: =T12 -> 0 | AT12: =W12 -> 0 | AU12: =Z12 -> 0 | AV12: =AC12 -> 0 | AW12: =AF12 -> 0 | AX12: =AI12 -> 0 | AY12: =AL12 -> 0 | BA12: =N12 -> 0 | BB12: =Z12 -> 0 | BC12: =AL12 -> 0
A13: Growth / Marketing — fully-loaded cost | B13: Headcount × monthly fully-loaded cost/FTE | C13: =C12*'Assumptions'!$F$48 -> 0 | D13: =D12*'Assumptions'!$F$48 -> 0 | E13: =E12*'Assumptions'!$F$48 -> 0 | F13: =F12*'Assumptions'!$F$48 -> 0 | G13: =G12*'Assumptions'!$F$48 -> 0 | H13: =H12*'Assumptions'!$F$48 -> 0 | I13: =I12*'Assumptions'!$F$48 -> 0 | J13: =J12*'Assumptions'!$F$48 -> 0 | ... AL13: =AL12*'Assumptions'!$F$48 -> 0 | AN13: =SUM(C13:E13) -> 0 | AO13: =SUM(F13:H13) -> 0 | AP13: =SUM(I13:K13) -> 0 | AQ13: =SUM(L13:N13) -> 0 | AR13: =SUM(O13:Q13) -> 0 | AS13: =SUM(R13:T13) -> 0 | AT13: =SUM(U13:W13) -> 0 | AU13: =SUM(X13:Z13) -> 0 | AV13: =SUM(AA13:AC13) -> 0 | AW13: =SUM(AD13:AF13) -> 0 | AX13: =SUM(AG13:AI13) -> 0 | AY13: =SUM(AJ13:AL13) -> 0 | BA13: =SUM(C13:N13) -> 0 | BB13: =SUM(O13:Z13) -> 0 | BC13: =SUM(AA13:AL13) -> 0
A14: Product / Engineering — headcount (FTE) | B14: Product & Engineering · start + net adds/qtr ÷ 3 | C14: =ROUND('Assumptions'!$F$51,1) -> 0 | D14: =ROUND(C14+'Assumptions'!$F$52/3,1) -> 0 | E14: =ROUND(D14+'Assumptions'!$F$52/3,1) -> 0 | F14: =ROUND(E14+'Assumptions'!$F$52/3,1) -> 0 | G14: =ROUND(F14+'Assumptions'!$F$52/3,1) -> 0 | H14: =ROUND(G14+'Assumptions'!$F$52/3,1) -> 0 | I14: =ROUND(H14+'Assumptions'!$F$52/3,1) -> 0 | J14: =ROUND(I14+'Assumptions'!$F$52/3,1) -> 0 | K14: =ROUND(J14+'Assumptions'!$F$52/3,1) -> 0 | ... AL14: =ROUND(AK14+'Assumptions'!$F$52/3,1) -> 0 | AN14: =E14 -> 0 | AO14: =H14 -> 0 | AP14: =K14 -> 0 | AQ14: =N14 -> 0 | AR14: =Q14 -> 0 | AS14: =T14 -> 0 | AT14: =W14 -> 0 | AU14: =Z14 -> 0 | AV14: =AC14 -> 0 | AW14: =AF14 -> 0 | AX14: =AI14 -> 0 | AY14: =AL14 -> 0 | BA14: =N14 -> 0 | BB14: =Z14 -> 0 | BC14: =AL14 -> 0
A15: Product / Engineering — fully-loaded cost | B15: Headcount × monthly fully-loaded cost/FTE | C15: =C14*'Assumptions'!$F$53 -> 0 | D15: =D14*'Assumptions'!$F$53 -> 0 | E15: =E14*'Assumptions'!$F$53 -> 0 | F15: =F14*'Assumptions'!$F$53 -> 0 | G15: =G14*'Assumptions'!$F$53 -> 0 | H15: =H14*'Assumptions'!$F$53 -> 0 | I15: =I14*'Assumptions'!$F$53 -> 0 | J15: =J14*'Assumptions'!$F$53 -> 0 | ... AL15: =AL14*'Assumptions'!$F$53 -> 0 | AN15: =SUM(C15:E15) -> 0 | AO15: =SUM(F15:H15) -> 0 | AP15: =SUM(I15:K15) -> 0 | AQ15: =SUM(L15:N15) -> 0 | AR15: =SUM(O15:Q15) -> 0 | AS15: =SUM(R15:T15) -> 0 | AT15: =SUM(U15:W15) -> 0 | AU15: =SUM(X15:Z15) -> 0 | AV15: =SUM(AA15:AC15) -> 0 | AW15: =SUM(AD15:AF15) -> 0 | AX15: =SUM(AG15:AI15) -> 0 | AY15: =SUM(AJ15:AL15) -> 0 | BA15: =SUM(C15:N15) -> 0 | BB15: =SUM(O15:Z15) -> 0 | BC15: =SUM(AA15:AL15) -> 0
A16: G&A — headcount (FTE) | B16: General & Administrative · start + net adds/qtr ÷ 3 | C16: =ROUND('Assumptions'!$F$56,1) -> 0 | D16: =ROUND(C16+'Assumptions'!$F$57/3,1) -> 0 | E16: =ROUND(D16+'Assumptions'!$F$57/3,1) -> 0 | F16: =ROUND(E16+'Assumptions'!$F$57/3,1) -> 0 | G16: =ROUND(F16+'Assumptions'!$F$57/3,1) -> 0 | H16: =ROUND(G16+'Assumptions'!$F$57/3,1) -> 0 | I16: =ROUND(H16+'Assumptions'!$F$57/3,1) -> 0 | J16: =ROUND(I16+'Assumptions'!$F$57/3,1) -> 0 | K16: =ROUND(J16+'Assumptions'!$F$57/3,1) -> 0 | ... AL16: =ROUND(AK16+'Assumptions'!$F$57/3,1) -> 0 | AN16: =E16 -> 0 | AO16: =H16 -> 0 | AP16: =K16 -> 0 | AQ16: =N16 -> 0 | AR16: =Q16 -> 0 | AS16: =T16 -> 0 | AT16: =W16 -> 0 | AU16: =Z16 -> 0 | AV16: =AC16 -> 0 | AW16: =AF16 -> 0 | AX16: =AI16 -> 0 | AY16: =AL16 -> 0 | BA16: =N16 -> 0 | BB16: =Z16 -> 0 | BC16: =AL16 -> 0
A17: G&A — fully-loaded cost | B17: Headcount × monthly fully-loaded cost/FTE | C17: =C16*'Assumptions'!$F$58 -> 0 | D17: =D16*'Assumptions'!$F$58 -> 0 | E17: =E16*'Assumptions'!$F$58 -> 0 | F17: =F16*'Assumptions'!$F$58 -> 0 | G17: =G16*'Assumptions'!$F$58 -> 0 | H17: =H16*'Assumptions'!$F$58 -> 0 | I17: =I16*'Assumptions'!$F$58 -> 0 | J17: =J16*'Assumptions'!$F$58 -> 0 | ... AL17: =AL16*'Assumptions'!$F$58 -> 0 | AN17: =SUM(C17:E17) -> 0 | AO17: =SUM(F17:H17) -> 0 | AP17: =SUM(I17:K17) -> 0 | AQ17: =SUM(L17:N17) -> 0 | AR17: =SUM(O17:Q17) -> 0 | AS17: =SUM(R17:T17) -> 0 | AT17: =SUM(U17:W17) -> 0 | AU17: =SUM(X17:Z17) -> 0 | AV17: =SUM(AA17:AC17) -> 0 | AW17: =SUM(AD17:AF17) -> 0 | AX17: =SUM(AG17:AI17) -> 0 | AY17: =SUM(AJ17:AL17) -> 0 | BA17: =SUM(C17:N17) -> 0 | BB17: =SUM(O17:Z17) -> 0 | BC17: =SUM(AA17:AL17) -> 0
A19: Totals
A20: Total headcount (FTE) | B20: Sum of all roles | C20: =C8+C12+C14+C16 -> 0 | D20: =D8+D12+D14+D16 -> 0 | E20: =E8+E12+E14+E16 -> 0 | F20: =F8+F12+F14+F16 -> 0 | G20: =G8+G12+G14+G16 -> 0 | H20: =H8+H12+H14+H16 -> 0 | I20: =I8+I12+I14+I16 -> 0 | J20: =J8+J12+J14+J16 -> 0 | ... AL20: =AL8+AL12+AL14+AL16 -> 0 | AN20: =E20 -> 0 | AO20: =H20 -> 0 | AP20: =K20 -> 0 | AQ20: =N20 -> 0 | AR20: =Q20 -> 0 | AS20: =T20 -> 0 | AT20: =W20 -> 0 | AU20: =Z20 -> 0 | AV20: =AC20 -> 0 | AW20: =AF20 -> 0 | AX20: =AI20 -> 0 | AY20: =AL20 -> 0 | BA20: =N20 -> 0 | BB20: =Z20 -> 0 | BC20: =AL20 -> 0
A21: Total COGS-classified people cost | B21: Feeds COGS & GM tab | C21: =C9 -> 0 | D21: =D9 -> 0 | E21: =E9 -> 0 | F21: =F9 -> 0 | G21: =G9 -> 0 | H21: =H9 -> 0 | I21: =I9 -> 0 | J21: =J9 -> 0 | ... AL21: =AL9 -> 0 | AN21: =SUM(C21:E21) -> 0 | AO21: =SUM(F21:H21) -> 0 | AP21: =SUM(I21:K21) -> 0 | AQ21: =SUM(L21:N21) -> 0 | AR21: =SUM(O21:Q21) -> 0 | AS21: =SUM(R21:T21) -> 0 | AT21: =SUM(U21:W21) -> 0 | AU21: =SUM(X21:Z21) -> 0 | AV21: =SUM(AA21:AC21) -> 0 | AW21: =SUM(AD21:AF21) -> 0 | AX21: =SUM(AG21:AI21) -> 0 | AY21: =SUM(AJ21:AL21) -> 0 | BA21: =SUM(C21:N21) -> 0 | BB21: =SUM(O21:Z21) -> 0 | BC21: =SUM(AA21:AL21) -> 0
A22: Total Opex-classified people cost | B22: Feeds Opex tab | C22: =C13+C15+C17 -> 0 | D22: =D13+D15+D17 -> 0 | E22: =E13+E15+E17 -> 0 | F22: =F13+F15+F17 -> 0 | G22: =G13+G15+G17 -> 0 | H22: =H13+H15+H17 -> 0 | I22: =I13+I15+I17 -> 0 | J22: =J13+J15+J17 -> 0 | ... AL22: =AL13+AL15+AL17 -> 0 | AN22: =SUM(C22:E22) -> 0 | AO22: =SUM(F22:H22) -> 0 | AP22: =SUM(I22:K22) -> 0 | AQ22: =SUM(L22:N22) -> 0 | AR22: =SUM(O22:Q22) -> 0 | AS22: =SUM(R22:T22) -> 0 | AT22: =SUM(U22:W22) -> 0 | AU22: =SUM(X22:Z22) -> 0 | AV22: =SUM(AA22:AC22) -> 0 | AW22: =SUM(AD22:AF22) -> 0 | AX22: =SUM(AG22:AI22) -> 0 | AY22: =SUM(AJ22:AL22) -> 0 | BA22: =SUM(C22:N22) -> 0 | BB22: =SUM(O22:Z22) -> 0 | BC22: =SUM(AA22:AL22) -> 0
A23: General & Administrative people cost | C23: =C17 -> 0 | D23: =D17 -> 0 | E23: =E17 -> 0 | F23: =F17 -> 0 | G23: =G17 -> 0 | H23: =H17 -> 0 | I23: =I17 -> 0 | J23: =J17 -> 0 | ... AL23: =AL17 -> 0 | AN23: =SUM(C23:E23) -> 0 | AO23: =SUM(F23:H23) -> 0 | AP23: =SUM(I23:K23) -> 0 | AQ23: =SUM(L23:N23) -> 0 | AR23: =SUM(O23:Q23) -> 0 | AS23: =SUM(R23:T23) -> 0 | AT23: =SUM(U23:W23) -> 0 | AU23: =SUM(X23:Z23) -> 0 | AV23: =SUM(AA23:AC23) -> 0 | AW23: =SUM(AD23:AF23) -> 0 | AX23: =SUM(AG23:AI23) -> 0 | AY23: =SUM(AJ23:AL23) -> 0 | BA23: =SUM(C23:N23) -> 0 | BB23: =SUM(O23:Z23) -> 0 | BC23: =SUM(AA23:AL23) -> 0
A24: Growth & Marketing people cost | C24: =C13 -> 0 | D24: =D13 -> 0 | E24: =E13 -> 0 | F24: =F13 -> 0 | G24: =G13 -> 0 | H24: =H13 -> 0 | I24: =I13 -> 0 | J24: =J13 -> 0 | ... AL24: =AL13 -> 0 | AN24: =SUM(C24:E24) -> 0 | AO24: =SUM(F24:H24) -> 0 | AP24: =SUM(I24:K24) -> 0 | AQ24: =SUM(L24:N24) -> 0 | AR24: =SUM(O24:Q24) -> 0 | AS24: =SUM(R24:T24) -> 0 | AT24: =SUM(U24:W24) -> 0 | AU24: =SUM(X24:Z24) -> 0 | AV24: =SUM(AA24:AC24) -> 0 | AW24: =SUM(AD24:AF24) -> 0 | AX24: =SUM(AG24:AI24) -> 0 | AY24: =SUM(AJ24:AL24) -> 0 | BA24: =SUM(C24:N24) -> 0 | BB24: =SUM(O24:Z24) -> 0 | BC24: =SUM(AA24:AL24) -> 0
A25: Product & Engineering people cost | C25: =C15 -> 0 | D25: =D15 -> 0 | E25: =E15 -> 0 | F25: =F15 -> 0 | G25: =G15 -> 0 | H25: =H15 -> 0 | I25: =I15 -> 0 | J25: =J15 -> 0 | ... AL25: =AL15 -> 0 | AN25: =SUM(C25:E25) -> 0 | AO25: =SUM(F25:H25) -> 0 | AP25: =SUM(I25:K25) -> 0 | AQ25: =SUM(L25:N25) -> 0 | AR25: =SUM(O25:Q25) -> 0 | AS25: =SUM(R25:T25) -> 0 | AT25: =SUM(U25:W25) -> 0 | AU25: =SUM(X25:Z25) -> 0 | AV25: =SUM(AA25:AC25) -> 0 | AW25: =SUM(AD25:AF25) -> 0 | AX25: =SUM(AG25:AI25) -> 0 | AY25: =SUM(AJ25:AL25) -> 0 | BA25: =SUM(C25:N25) -> 0 | BB25: =SUM(O25:Z25) -> 0 | BC25: =SUM(AA25:AL25) -> 0

Sheet Revenue
A1: Consumer Subscription — 3-Year Financial Model — Revenue
A2: Channel acquisition -> MAU bridge -> free-to-paid conversion -> paid subscriber bridge -> blended ARPU.
A5: Line item | B5: Units / source | C5: Monthly (36 months) | AN5: Quarterly | BA5: Annual
C6: 46023 | D6: 46054 | E6: 46082 | F6: 46113 | G6: 46143 | H6: 46174 | I6: 46204 | J6: 46235 | K6: 46266 | L6: 46296 | M6: 46327 | N6: 46357 | O6: 46388 | P6: 46419 | Q6: 46447 | R6: 46478 | S6: 46508 | T6: 46539 | U6: 46569 | V6: 46600 | W6: 46631 | X6: 46661 | Y6: 46692 | Z6: 46722 | AA6: 46753 | AB6: 46784 | AC6: 46813 | AD6: 46844 | AE6: 46874 | AF6: 46905 | AG6: 46935 | AH6: 46966 | AI6: 46997 | AJ6: 47027 | AK6: 47058 | AL6: 47088 | AN6: Q1 | AO6: Q2 | AP6: Q3 | AQ6: Q4 | AR6: Q5 | AS6: Q6 | AT6: Q7 | AU6: Q8 | AV6: Q9 | AW6: Q10 | AX6: Q11 | AY6: Q12 | BA6: FY1 | BB6: FY2 | BC6: FY3
A7: Acquisition by Channel
A8: Paid new signups | B8: Monthly new users from this channel | C8: ='Assumptions'!$F$16 -> 0 | D8: =C8*(1+'Assumptions'!$F$17) -> 0 | E8: =D8*(1+'Assumptions'!$F$17) -> 0 | F8: =E8*(1+'Assumptions'!$F$17) -> 0 | G8: =F8*(1+'Assumptions'!$F$17) -> 0 | H8: =G8*(1+'Assumptions'!$F$17) -> 0 | I8: =H8*(1+'Assumptions'!$F$17) -> 0 | J8: =I8*(1+'Assumptions'!$F$17) -> 0 | K8: =J8*(1+'Assumptions'!$F$17) -> 0 | ... AL8: =AK8*(1+'Assumptions'!$F$17) -> 0 | AN8: =SUM(C8:E8) -> 0 | AO8: =SUM(F8:H8) -> 0 | AP8: =SUM(I8:K8) -> 0 | AQ8: =SUM(L8:N8) -> 0 | AR8: =SUM(O8:Q8) -> 0 | AS8: =SUM(R8:T8) -> 0 | AT8: =SUM(U8:W8) -> 0 | AU8: =SUM(X8:Z8) -> 0 | AV8: =SUM(AA8:AC8) -> 0 | AW8: =SUM(AD8:AF8) -> 0 | AX8: =SUM(AG8:AI8) -> 0 | AY8: =SUM(AJ8:AL8) -> 0 | BA8: =SUM(C8:N8) -> 0 | BB8: =SUM(O8:Z8) -> 0 | BC8: =SUM(AA8:AL8) -> 0
A9: Paid acquisition spend | B9: New signups × CAC / signup | C9: =C8*'Assumptions'!$F$18 -> 0 | D9: =D8*'Assumptions'!$F$18 -> 0 | E9: =E8*'Assumptions'!$F$18 -> 0 | F9: =F8*'Assumptions'!$F$18 -> 0 | G9: =G8*'Assumptions'!$F$18 -> 0 | H9: =H8*'Assumptions'!$F$18 -> 0 | I9: =I8*'Assumptions'!$F$18 -> 0 | J9: =J8*'Assumptions'!$F$18 -> 0 | ... AL9: =AL8*'Assumptions'!$F$18 -> 0 | AN9: =SUM(C9:E9) -> 0 | AO9: =SUM(F9:H9) -> 0 | AP9: =SUM(I9:K9) -> 0 | AQ9: =SUM(L9:N9) -> 0 | AR9: =SUM(O9:Q9) -> 0 | AS9: =SUM(R9:T9) -> 0 | AT9: =SUM(U9:W9) -> 0 | AU9: =SUM(X9:Z9) -> 0 | AV9: =SUM(AA9:AC9) -> 0 | AW9: =SUM(AD9:AF9) -> 0 | AX9: =SUM(AG9:AI9) -> 0 | AY9: =SUM(AJ9:AL9) -> 0 | BA9: =SUM(C9:N9) -> 0 | BB9: =SUM(O9:Z9) -> 0 | BC9: =SUM(AA9:AL9) -> 0
A10: Organic / Viral new signups | B10: Monthly new users from this channel | C10: ='Assumptions'!$F$19 -> 0 | D10: =C10*(1+'Assumptions'!$F$20) -> 0 | E10: =D10*(1+'Assumptions'!$F$20) -> 0 | F10: =E10*(1+'Assumptions'!$F$20) -> 0 | G10: =F10*(1+'Assumptions'!$F$20) -> 0 | H10: =G10*(1+'Assumptions'!$F$20) -> 0 | I10: =H10*(1+'Assumptions'!$F$20) -> 0 | J10: =I10*(1+'Assumptions'!$F$20) -> 0 | K10: =J10*(1+'Assumptions'!$F$20) -> 0 | ... AL10: =AK10*(1+'Assumptions'!$F$20) -> 0 | AN10: =SUM(C10:E10) -> 0 | AO10: =SUM(F10:H10) -> 0 | AP10: =SUM(I10:K10) -> 0 | AQ10: =SUM(L10:N10) -> 0 | AR10: =SUM(O10:Q10) -> 0 | AS10: =SUM(R10:T10) -> 0 | AT10: =SUM(U10:W10) -> 0 | AU10: =SUM(X10:Z10) -> 0 | AV10: =SUM(AA10:AC10) -> 0 | AW10: =SUM(AD10:AF10) -> 0 | AX10: =SUM(AG10:AI10) -> 0 | AY10: =SUM(AJ10:AL10) -> 0 | BA10: =SUM(C10:N10) -> 0 | BB10: =SUM(O10:Z10) -> 0 | BC10: =SUM(AA10:AL10) -> 0
A11: Organic / Viral acquisition spend | B11: New signups × CAC / signup | C11: =C10*'Assumptions'!$F$21 -> 0 | D11: =D10*'Assumptions'!$F$21 -> 0 | E11: =E10*'Assumptions'!$F$21 -> 0 | F11: =F10*'Assumptions'!$F$21 -> 0 | G11: =G10*'Assumptions'!$F$21 -> 0 | H11: =H10*'Assumptions'!$F$21 -> 0 | I11: =I10*'Assumptions'!$F$21 -> 0 | J11: =J10*'Assumptions'!$F$21 -> 0 | ... AL11: =AL10*'Assumptions'!$F$21 -> 0 | AN11: =SUM(C11:E11) -> 0 | AO11: =SUM(F11:H11) -> 0 | AP11: =SUM(I11:K11) -> 0 | AQ11: =SUM(L11:N11) -> 0 | AR11: =SUM(O11:Q11) -> 0 | AS11: =SUM(R11:T11) -> 0 | AT11: =SUM(U11:W11) -> 0 | AU11: =SUM(X11:Z11) -> 0 | AV11: =SUM(AA11:AC11) -> 0 | AW11: =SUM(AD11:AF11) -> 0 | AX11: =SUM(AG11:AI11) -> 0 | AY11: =SUM(AJ11:AL11) -> 0 | BA11: =SUM(C11:N11) -> 0 | BB11: =SUM(O11:Z11) -> 0 | BC11: =SUM(AA11:AL11) -> 0
A12: Influencer / Referral new signups | B12: Monthly new users from this channel | C12: ='Assumptions'!$F$22 -> 0 | D12: =C12*(1+'Assumptions'!$F$23) -> 0 | E12: =D12*(1+'Assumptions'!$F$23) -> 0 | F12: =E12*(1+'Assumptions'!$F$23) -> 0 | G12: =F12*(1+'Assumptions'!$F$23) -> 0 | H12: =G12*(1+'Assumptions'!$F$23) -> 0 | I12: =H12*(1+'Assumptions'!$F$23) -> 0 | J12: =I12*(1+'Assumptions'!$F$23) -> 0 | K12: =J12*(1+'Assumptions'!$F$23) -> 0 | ... AL12: =AK12*(1+'Assumptions'!$F$23) -> 0 | AN12: =SUM(C12:E12) -> 0 | AO12: =SUM(F12:H12) -> 0 | AP12: =SUM(I12:K12) -> 0 | AQ12: =SUM(L12:N12) -> 0 | AR12: =SUM(O12:Q12) -> 0 | AS12: =SUM(R12:T12) -> 0 | AT12: =SUM(U12:W12) -> 0 | AU12: =SUM(X12:Z12) -> 0 | AV12: =SUM(AA12:AC12) -> 0 | AW12: =SUM(AD12:AF12) -> 0 | AX12: =SUM(AG12:AI12) -> 0 | AY12: =SUM(AJ12:AL12) -> 0 | BA12: =SUM(C12:N12) -> 0 | BB12: =SUM(O12:Z12) -> 0 | BC12: =SUM(AA12:AL12) -> 0
A13: Influencer / Referral acquisition spend | B13: New signups × CAC / signup | C13: =C12*'Assumptions'!$F$24 -> 0 | D13: =D12*'Assumptions'!$F$24 -> 0 | E13: =E12*'Assumptions'!$F$24 -> 0 | F13: =F12*'Assumptions'!$F$24 -> 0 | G13: =G12*'Assumptions'!$F$24 -> 0 | H13: =H12*'Assumptions'!$F$24 -> 0 | I13: =I12*'Assumptions'!$F$24 -> 0 | J13: =J12*'Assumptions'!$F$24 -> 0 | ... AL13: =AL12*'Assumptions'!$F$24 -> 0 | AN13: =SUM(C13:E13) -> 0 | AO13: =SUM(F13:H13) -> 0 | AP13: =SUM(I13:K13) -> 0 | AQ13: =SUM(L13:N13) -> 0 | AR13: =SUM(O13:Q13) -> 0 | AS13: =SUM(R13:T13) -> 0 | AT13: =SUM(U13:W13) -> 0 | AU13: =SUM(X13:Z13) -> 0 | AV13: =SUM(AA13:AC13) -> 0 | AW13: =SUM(AD13:AF13) -> 0 | AX13: =SUM(AG13:AI13) -> 0 | AY13: =SUM(AJ13:AL13) -> 0 | BA13: =SUM(C13:N13) -> 0 | BB13: =SUM(O13:Z13) -> 0 | BC13: =SUM(AA13:AL13) -> 0
A14: Total new signups | B14: Sum of paid, organic / viral, and influencer / referral channels | C14: =C8+C10+C12 -> 0 | D14: =D8+D10+D12 -> 0 | E14: =E8+E10+E12 -> 0 | F14: =F8+F10+F12 -> 0 | G14: =G8+G10+G12 -> 0 | H14: =H8+H10+H12 -> 0 | I14: =I8+I10+I12 -> 0 | J14: =J8+J10+J12 -> 0 | ... AL14: =AL8+AL10+AL12 -> 0 | AN14: =SUM(C14:E14) -> 0 | AO14: =SUM(F14:H14) -> 0 | AP14: =SUM(I14:K14) -> 0 | AQ14: =SUM(L14:N14) -> 0 | AR14: =SUM(O14:Q14) -> 0 | AS14: =SUM(R14:T14) -> 0 | AT14: =SUM(U14:W14) -> 0 | AU14: =SUM(X14:Z14) -> 0 | AV14: =SUM(AA14:AC14) -> 0 | AW14: =SUM(AD14:AF14) -> 0 | AX14: =SUM(AG14:AI14) -> 0 | AY14: =SUM(AJ14:AL14) -> 0 | BA14: =SUM(C14:N14) -> 0 | BB14: =SUM(O14:Z14) -> 0 | BC14: =SUM(AA14:AL14) -> 0
A15: Total acquisition spend | B15: Channel acquisition spend that flows into Growth & Marketing Opex | C15: =C9+C11+C13 -> 0 | D15: =D9+D11+D13 -> 0 | E15: =E9+E11+E13 -> 0 | F15: =F9+F11+F13 -> 0 | G15: =G9+G11+G13 -> 0 | H15: =H9+H11+H13 -> 0 | I15: =I9+I11+I13 -> 0 | J15: =J9+J11+J13 -> 0 | ... AL15: =AL9+AL11+AL13 -> 0 | AN15: =SUM(C15:E15) -> 0 | AO15: =SUM(F15:H15) -> 0 | AP15: =SUM(I15:K15) -> 0 | AQ15: =SUM(L15:N15) -> 0 | AR15: =SUM(O15:Q15) -> 0 | AS15: =SUM(R15:T15) -> 0 | AT15: =SUM(U15:W15) -> 0 | AU15: =SUM(X15:Z15) -> 0 | AV15: =SUM(AA15:AC15) -> 0 | AW15: =SUM(AD15:AF15) -> 0 | AX15: =SUM(AG15:AI15) -> 0 | AY15: =SUM(AJ15:AL15) -> 0 | BA15: =SUM(C15:N15) -> 0 | BB15: =SUM(O15:Z15) -> 0 | BC15: =SUM(AA15:AL15) -> 0
A17: MAU & Paid Subscriber Funnel
A18: Beginning MAU | B18: Prior month ending MAU (or starting MAU in month 1) | C18: ='Assumptions'!$F$13 -> 0 | D18: =C21 -> 0 | E18: =D21 -> 0 | F18: =E21 -> 0 | G18: =F21 -> 0 | H18: =G21 -> 0 | I18: =H21 -> 0 | J18: =I21 -> 0 | K18: =J21 -> 0 | ... AL18: =AK21 -> 0 | AN18: =E18 -> 0 | AO18: =H18 -> 0 | AP18: =K18 -> 0 | AQ18: =N18 -> 0 | AR18: =Q18 -> 0 | AS18: =T18 -> 0 | AT18: =W18 -> 0 | AU18: =Z18 -> 0 | AV18: =AC18 -> 0 | AW18: =AF18 -> 0 | AX18: =AI18 -> 0 | AY18: =AL18 -> 0 | BA18: =N18 -> 0 | BB18: =Z18 -> 0 | BC18: =AL18 -> 0
A19: New signups | B19: Linked from channel acquisition above | C19: =C14 -> 0 | D19: =D14 -> 0 | E19: =E14 -> 0 | F19: =F14 -> 0 | G19: =G14 -> 0 | H19: =H14 -> 0 | I19: =I14 -> 0 | J19: =J14 -> 0 | ... AL19: =AL14 -> 0 | AN19: =SUM(C19:E19) -> 0 | AO19: =SUM(F19:H19) -> 0 | AP19: =SUM(I19:K19) -> 0 | AQ19: =SUM(L19:N19) -> 0 | AR19: =SUM(O19:Q19) -> 0 | AS19: =SUM(R19:T19) -> 0 | AT19: =SUM(U19:W19) -> 0 | AU19: =SUM(X19:Z19) -> 0 | AV19: =SUM(AA19:AC19) -> 0 | AW19: =SUM(AD19:AF19) -> 0 | AX19: =SUM(AG19:AI19) -> 0 | AY19: =SUM(AJ19:AL19) -> 0 | BA19: =SUM(C19:N19) -> 0 | BB19: =SUM(O19:Z19) -> 0 | BC19: =SUM(AA19:AL19) -> 0
A20: Churned / inactive MAU | B20: Beginning MAU × active-user churn rate | C20: =-C18*'Assumptions'!$F$14 -> 0 | D20: =-D18*'Assumptions'!$F$14 -> 0 | E20: =-E18*'Assumptions'!$F$14 -> 0 | F20: =-F18*'Assumptions'!$F$14 -> 0 | G20: =-G18*'Assumptions'!$F$14 -> 0 | H20: =-H18*'Assumptions'!$F$14 -> 0 | I20: =-I18*'Assumptions'!$F$14 -> 0 | J20: =-J18*'Assumptions'!$F$14 -> 0 | ... AL20: =-AL18*'Assumptions'!$F$14 -> 0 | AN20: =SUM(C20:E20) -> 0 | AO20: =SUM(F20:H20) -> 0 | AP20: =SUM(I20:K20) -> 0 | AQ20: =SUM(L20:N20) -> 0 | AR20: =SUM(O20:Q20) -> 0 | AS20: =SUM(R20:T20) -> 0 | AT20: =SUM(U20:W20) -> 0 | AU20: =SUM(X20:Z20) -> 0 | AV20: =SUM(AA20:AC20) -> 0 | AW20: =SUM(AD20:AF20) -> 0 | AX20: =SUM(AG20:AI20) -> 0 | AY20: =SUM(AJ20:AL20) -> 0 | BA20: =SUM(C20:N20) -> 0 | BB20: =SUM(O20:Z20) -> 0 | BC20: =SUM(AA20:AL20) -> 0
A21: Ending MAU | B21: Beginning MAU + new signups − MAU churn | C21: =C18+C19+C20 -> 0 | D21: =D18+D19+D20 -> 0 | E21: =E18+E19+E20 -> 0 | F21: =F18+F19+F20 -> 0 | G21: =G18+G19+G20 -> 0 | H21: =H18+H19+H20 -> 0 | I21: =I18+I19+I20 -> 0 | J21: =J18+J19+J20 -> 0 | ... AL21: =AL18+AL19+AL20 -> 0 | AN21: =E21 -> 0 | AO21: =H21 -> 0 | AP21: =K21 -> 0 | AQ21: =N21 -> 0 | AR21: =Q21 -> 0 | AS21: =T21 -> 0 | AT21: =W21 -> 0 | AU21: =Z21 -> 0 | AV21: =AC21 -> 0 | AW21: =AF21 -> 0 | AX21: =AI21 -> 0 | AY21: =AL21 -> 0 | BA21: =N21 -> 0 | BB21: =Z21 -> 0 | BC21: =AL21 -> 0
A22: Beginning paid subscribers | B22: Prior month ending paid subscribers | C22: ='Assumptions'!$F$15 -> 0 | D22: =C28 -> 0 | E22: =D28 -> 0 | F22: =E28 -> 0 | G22: =F28 -> 0 | H22: =G28 -> 0 | I22: =H28 -> 0 | J22: =I28 -> 0 | K22: =J28 -> 0 | ... AL22: =AK28 -> 0 | AN22: =E22 -> 0 | AO22: =H22 -> 0 | AP22: =K22 -> 0 | AQ22: =N22 -> 0 | AR22: =Q22 -> 0 | AS22: =T22 -> 0 | AT22: =W22 -> 0 | AU22: =Z22 -> 0 | AV22: =AC22 -> 0 | AW22: =AF22 -> 0 | AX22: =AI22 -> 0 | AY22: =AL22 -> 0 | BA22: =N22 -> 0 | BB22: =Z22 -> 0 | BC22: =AL22 -> 0
A23: Churned paid subscribers | B23: Beginning paid subscribers × paid churn | C23: =-C22*'Assumptions'!$F$28 -> 0 | D23: =-D22*'Assumptions'!$F$28 -> 0 | E23: =-E22*'Assumptions'!$F$28 -> 0 | F23: =-F22*'Assumptions'!$F$28 -> 0 | G23: =-G22*'Assumptions'!$F$28 -> 0 | H23: =-H22*'Assumptions'!$F$28 -> 0 | I23: =-I22*'Assumptions'!$F$28 -> 0 | J23: =-J22*'Assumptions'!$F$28 -> 0 | ... AL23: =-AL22*'Assumptions'!$F$28 -> 0 | AN23: =SUM(C23:E23) -> 0 | AO23: =SUM(F23:H23) -> 0 | AP23: =SUM(I23:K23) -> 0 | AQ23: =SUM(L23:N23) -> 0 | AR23: =SUM(O23:Q23) -> 0 | AS23: =SUM(R23:T23) -> 0 | AT23: =SUM(U23:W23) -> 0 | AU23: =SUM(X23:Z23) -> 0 | AV23: =SUM(AA23:AC23) -> 0 | AW23: =SUM(AD23:AF23) -> 0 | AX23: =SUM(AG23:AI23) -> 0 | AY23: =SUM(AJ23:AL23) -> 0 | BA23: =SUM(C23:N23) -> 0 | BB23: =SUM(O23:Z23) -> 0 | BC23: =SUM(AA23:AL23) -> 0
A24: Retained paid before new adds | B24: Beginning paid subscribers net of subscriber churn | C24: =C22+C23 -> 0 | D24: =D22+D23 -> 0 | E24: =E22+E23 -> 0 | F24: =F22+F23 -> 0 | G24: =G22+G23 -> 0 | H24: =H22+H23 -> 0 | I24: =I22+I23 -> 0 | J24: =J22+J23 -> 0 | ... AL24: =AL22+AL23 -> 0 | AN24: =E24 -> 0 | AO24: =H24 -> 0 | AP24: =K24 -> 0 | AQ24: =N24 -> 0 | AR24: =Q24 -> 0 | AS24: =T24 -> 0 | AT24: =W24 -> 0 | AU24: =Z24 -> 0 | AV24: =AC24 -> 0 | AW24: =AF24 -> 0 | AX24: =AI24 -> 0 | AY24: =AL24 -> 0 | BA24: =N24 -> 0 | BB24: =Z24 -> 0 | BC24: =AL24 -> 0
A25: Free MAU available to convert | B25: Ending MAU less retained paid subscribers | C25: =MAX(0,C21-C24) -> 0 | D25: =MAX(0,D21-D24) -> 0 | E25: =MAX(0,E21-E24) -> 0 | F25: =MAX(0,F21-F24) -> 0 | G25: =MAX(0,G21-G24) -> 0 | H25: =MAX(0,H21-H24) -> 0 | I25: =MAX(0,I21-I24) -> 0 | J25: =MAX(0,J21-J24) -> 0 | ... AL25: =MAX(0,AL21-AL24) -> 0 | AN25: =E25 -> 0 | AO25: =H25 -> 0 | AP25: =K25 -> 0 | AQ25: =N25 -> 0 | AR25: =Q25 -> 0 | AS25: =T25 -> 0 | AT25: =W25 -> 0 | AU25: =Z25 -> 0 | AV25: =AC25 -> 0 | AW25: =AF25 -> 0 | AX25: =AI25 -> 0 | AY25: =AL25 -> 0 | BA25: =N25 -> 0 | BB25: =Z25 -> 0 | BC25: =AL25 -> 0
A26: Free-to-paid conversion % | B26: Monthly free-user conversion assumption | C26: ='Assumptions'!$F$27 -> 0 | D26: ='Assumptions'!$F$27 -> 0 | E26: ='Assumptions'!$F$27 -> 0 | F26: ='Assumptions'!$F$27 -> 0 | G26: ='Assumptions'!$F$27 -> 0 | H26: ='Assumptions'!$F$27 -> 0 | I26: ='Assumptions'!$F$27 -> 0 | J26: ='Assumptions'!$F$27 -> 0 | ... AL26: ='Assumptions'!$F$27 -> 0 | AN26: =AVERAGE(C26:E26) -> 0 | AO26: =AVERAGE(F26:H26) -> 0 | AP26: =AVERAGE(I26:K26) -> 0 | AQ26: =AVERAGE(L26:N26) -> 0 | AR26: =AVERAGE(O26:Q26) -> 0 | AS26: =AVERAGE(R26:T26) -> 0 | AT26: =AVERAGE(U26:W26) -> 0 | AU26: =AVERAGE(X26:Z26) -> 0 | AV26: =AVERAGE(AA26:AC26) -> 0 | AW26: =AVERAGE(AD26:AF26) -> 0 | AX26: =AVERAGE(AG26:AI26) -> 0 | AY26: =AVERAGE(AJ26:AL26) -> 0 | BA26: =AVERAGE(C26:N26) -> 0 | BB26: =AVERAGE(O26:Z26) -> 0 | BC26: =AVERAGE(AA26:AL26) -> 0
A27: New paid adds | B27: Free MAU pool × conversion % | C27: =C25*C26 -> 0 | D27: =D25*D26 -> 0 | E27: =E25*E26 -> 0 | F27: =F25*F26 -> 0 | G27: =G25*G26 -> 0 | H27: =H25*H26 -> 0 | I27: =I25*I26 -> 0 | J27: =J25*J26 -> 0 | ... AL27: =AL25*AL26 -> 0 | AN27: =SUM(C27:E27) -> 0 | AO27: =SUM(F27:H27) -> 0 | AP27: =SUM(I27:K27) -> 0 | AQ27: =SUM(L27:N27) -> 0 | AR27: =SUM(O27:Q27) -> 0 | AS27: =SUM(R27:T27) -> 0 | AT27: =SUM(U27:W27) -> 0 | AU27: =SUM(X27:Z27) -> 0 | AV27: =SUM(AA27:AC27) -> 0 | AW27: =SUM(AD27:AF27) -> 0 | AX27: =SUM(AG27:AI27) -> 0 | AY27: =SUM(AJ27:AL27) -> 0 | BA27: =SUM(C27:N27) -> 0 | BB27: =SUM(O27:Z27) -> 0 | BC27: =SUM(AA27:AL27) -> 0
A28: Ending paid subscribers | B28: Retained paid subscribers + new paid adds | C28: =C24+C27 -> 0 | D28: =D24+D27 -> 0 | E28: =E24+E27 -> 0 | F28: =F24+F27 -> 0 | G28: =G24+G27 -> 0 | H28: =H24+H27 -> 0 | I28: =I24+I27 -> 0 | J28: =J24+J27 -> 0 | ... AL28: =AL24+AL27 -> 0 | AN28: =E28 -> 0 | AO28: =H28 -> 0 | AP28: =K28 -> 0 | AQ28: =N28 -> 0 | AR28: =Q28 -> 0 | AS28: =T28 -> 0 | AT28: =W28 -> 0 | AU28: =Z28 -> 0 | AV28: =AC28 -> 0 | AW28: =AF28 -> 0 | AX28: =AI28 -> 0 | AY28: =AL28 -> 0 | BA28: =N28 -> 0 | BB28: =Z28 -> 0 | BC28: =AL28 -> 0
A30: Plans, ARPU & Revenue
A31: Premium-tier subscriber mix | B31: Higher-value plan mix, capped inside the model | C31: ='Assumptions'!$F$31 -> 0 | D31: =MIN(0.50,MAX(0.05,C31+'Assumptions'!$F$32)) -> 0 | E31: =MIN(0.50,MAX(0.05,D31+'Assumptions'!$F$32)) -> 0 | F31: =MIN(0.50,MAX(0.05,E31+'Assumptions'!$F$32)) -> 0 | G31: =MIN(0.50,MAX(0.05,F31+'Assumptions'!$F$32)) -> 0 | H31: =MIN(0.50,MAX(0.05,G31+'Assumptions'!$F$32)) -> 0 | I31: =MIN(0.50,MAX(0.05,H31+'Assumptions'!$F$32)) -> 0 | J31: =MIN(0.50,MAX(0.05,I31+'Assumptions'!$F$32)) -> 0 | K31: =MIN(0.50,MAX(0.05,J31+'Assumptions'!$F$32)) -> 0 | ... AL31: =MIN(0.50,MAX(0.05,AK31+'Assumptions'!$F$32)) -> 0 | AN31: =AVERAGE(C31:E31) -> 0 | AO31: =AVERAGE(F31:H31) -> 0 | AP31: =AVERAGE(I31:K31) -> 0 | AQ31: =AVERAGE(L31:N31) -> 0 | AR31: =AVERAGE(O31:Q31) -> 0 | AS31: =AVERAGE(R31:T31) -> 0 | AT31: =AVERAGE(U31:W31) -> 0 | AU31: =AVERAGE(X31:Z31) -> 0 | AV31: =AVERAGE(AA31:AC31) -> 0 | AW31: =AVERAGE(AD31:AF31) -> 0 | AX31: =AVERAGE(AG31:AI31) -> 0 | AY31: =AVERAGE(AJ31:AL31) -> 0 | BA31: =AVERAGE(C31:N31) -> 0 | BB31: =AVERAGE(O31:Z31) -> 0 | BC31: =AVERAGE(AA31:AL31) -> 0
A32: Blended ARPU | B32: Weighted average of standard and premium plan pricing | C32: ='Assumptions'!$F$29*(1-C31)+'Assumptions'!$F$30*C31 -> 0 | D32: ='Assumptions'!$F$29*(1-D31)+'Assumptions'!$F$30*D31 -> 0 | E32: ='Assumptions'!$F$29*(1-E31)+'Assumptions'!$F$30*E31 -> 0 | F32: ='Assumptions'!$F$29*(1-F31)+'Assumptions'!$F$30*F31 -> 0 | G32: ='Assumptions'!$F$29*(1-G31)+'Assumptions'!$F$30*G31 -> 0 | H32: ='Assumptions'!$F$29*(1-H31)+'Assumptions'!$F$30*H31 -> 0 | I32: ='Assumptions'!$F$29*(1-I31)+'Assumptions'!$F$30*I31 -> 0 | J32: ='Assumptions'!$F$29*(1-J31)+'Assumptions'!$F$30*J31 -> 0 | ... AL32: ='Assumptions'!$F$29*(1-AL31)+'Assumptions'!$F$30*AL31 -> 0 | AN32: =AVERAGE(C32:E32) -> 0 | AO32: =AVERAGE(F32:H32) -> 0 | AP32: =AVERAGE(I32:K32) -> 0 | AQ32: =AVERAGE(L32:N32) -> 0 | AR32: =AVERAGE(O32:Q32) -> 0 | AS32: =AVERAGE(R32:T32) -> 0 | AT32: =AVERAGE(U32:W32) -> 0 | AU32: =AVERAGE(X32:Z32) -> 0 | AV32: =AVERAGE(AA32:AC32) -> 0 | AW32: =AVERAGE(AD32:AF32) -> 0 | AX32: =AVERAGE(AG32:AI32) -> 0 | AY32: =AVERAGE(AJ32:AL32) -> 0 | BA32: =AVERAGE(C32:N32) -> 0 | BB32: =AVERAGE(O32:Z32) -> 0 | BC32: =AVERAGE(AA32:AL32) -> 0
A33: Subscription revenue | B33: Ending paid subscribers × blended ARPU | C33: =C28*C32 -> 0 | D33: =D28*D32 -> 0 | E33: =E28*E32 -> 0 | F33: =F28*F32 -> 0 | G33: =G28*G32 -> 0 | H33: =H28*H32 -> 0 | I33: =I28*I32 -> 0 | J33: =J28*J32 -> 0 | ... AL33: =AL28*AL32 -> 0 | AN33: =SUM(C33:E33) -> 0 | AO33: =SUM(F33:H33) -> 0 | AP33: =SUM(I33:K33) -> 0 | AQ33: =SUM(L33:N33) -> 0 | AR33: =SUM(O33:Q33) -> 0 | AS33: =SUM(R33:T33) -> 0 | AT33: =SUM(U33:W33) -> 0 | AU33: =SUM(X33:Z33) -> 0 | AV33: =SUM(AA33:AC33) -> 0 | AW33: =SUM(AD33:AF33) -> 0 | AX33: =SUM(AG33:AI33) -> 0 | AY33: =SUM(AJ33:AL33) -> 0 | BA33: =SUM(C33:N33) -> 0 | BB33: =SUM(O33:Z33) -> 0 | BC33: =SUM(AA33:AL33) -> 0
A34: Revenue run-rate (monthly revenue x 12) | B34: Illustrative ARR-equivalent for a monthly consumer subscription business | C34: =C33*12 -> 0 | D34: =D33*12 -> 0 | E34: =E33*12 -> 0 | F34: =F33*12 -> 0 | G34: =G33*12 -> 0 | H34: =H33*12 -> 0 | I34: =I33*12 -> 0 | J34: =J33*12 -> 0 | ... AL34: =AL33*12 -> 0 | AN34: =E34 -> 0 | AO34: =H34 -> 0 | AP34: =K34 -> 0 | AQ34: =N34 -> 0 | AR34: =Q34 -> 0 | AS34: =T34 -> 0 | AT34: =W34 -> 0 | AU34: =Z34 -> 0 | AV34: =AC34 -> 0 | AW34: =AF34 -> 0 | AX34: =AI34 -> 0 | AY34: =AL34 -> 0 | BA34: =N34 -> 0 | BB34: =Z34 -> 0 | BC34: =AL34 -> 0
A35: Total Revenue | B35: Subscription revenue only; no ads or IAP modeled | C35: =C33 -> 0 | D35: =D33 -> 0 | E35: =E33 -> 0 | F35: =F33 -> 0 | G35: =G33 -> 0 | H35: =H33 -> 0 | I35: =I33 -> 0 | J35: =J33 -> 0 | ... AL35: =AL33 -> 0 | AN35: =SUM(C35:E35) -> 0 | AO35: =SUM(F35:H35) -> 0 | AP35: =SUM(I35:K35) -> 0 | AQ35: =SUM(L35:N35) -> 0 | AR35: =SUM(O35:Q35) -> 0 | AS35: =SUM(R35:T35) -> 0 | AT35: =SUM(U35:W35) -> 0 | AU35: =SUM(X35:Z35) -> 0 | AV35: =SUM(AA35:AC35) -> 0 | AW35: =SUM(AD35:AF35) -> 0 | AX35: =SUM(AG35:AI35) -> 0 | AY35: =SUM(AJ35:AL35) -> 0 | BA35: =SUM(C35:N35) -> 0 | BB35: =SUM(O35:Z35) -> 0 | BC35: =SUM(AA35:AL35) -> 0
A37: Consumer Subscription KPIs
A38: MAU growth (month over month) | C38: =IFERROR(C21/C18-1,0) -> 0 | D38: =IFERROR(D21/D18-1,0) -> 0 | E38: =IFERROR(E21/E18-1,0) -> 0 | F38: =IFERROR(F21/F18-1,0) -> 0 | G38: =IFERROR(G21/G18-1,0) -> 0 | H38: =IFERROR(H21/H18-1,0) -> 0 | I38: =IFERROR(I21/I18-1,0) -> 0 | J38: =IFERROR(J21/J18-1,0) -> 0 | ... AL38: =IFERROR(AL21/AL18-1,0) -> 0 | AN38: =AVERAGE(C38:E38) -> 0 | AO38: =AVERAGE(F38:H38) -> 0 | AP38: =AVERAGE(I38:K38) -> 0 | AQ38: =AVERAGE(L38:N38) -> 0 | AR38: =AVERAGE(O38:Q38) -> 0 | AS38: =AVERAGE(R38:T38) -> 0 | AT38: =AVERAGE(U38:W38) -> 0 | AU38: =AVERAGE(X38:Z38) -> 0 | AV38: =AVERAGE(AA38:AC38) -> 0 | AW38: =AVERAGE(AD38:AF38) -> 0 | AX38: =AVERAGE(AG38:AI38) -> 0 | AY38: =AVERAGE(AJ38:AL38) -> 0 | BA38: =AVERAGE(C38:N38) -> 0 | BB38: =AVERAGE(O38:Z38) -> 0 | BC38: =AVERAGE(AA38:AL38) -> 0
A39: Paid subscribers as % of MAU | C39: =IFERROR(C28/C21,0) -> 0 | D39: =IFERROR(D28/D21,0) -> 0 | E39: =IFERROR(E28/E21,0) -> 0 | F39: =IFERROR(F28/F21,0) -> 0 | G39: =IFERROR(G28/G21,0) -> 0 | H39: =IFERROR(H28/H21,0) -> 0 | I39: =IFERROR(I28/I21,0) -> 0 | J39: =IFERROR(J28/J21,0) -> 0 | ... AL39: =IFERROR(AL28/AL21,0) -> 0 | AN39: =AVERAGE(C39:E39) -> 0 | AO39: =AVERAGE(F39:H39) -> 0 | AP39: =AVERAGE(I39:K39) -> 0 | AQ39: =AVERAGE(L39:N39) -> 0 | AR39: =AVERAGE(O39:Q39) -> 0 | AS39: =AVERAGE(R39:T39) -> 0 | AT39: =AVERAGE(U39:W39) -> 0 | AU39: =AVERAGE(X39:Z39) -> 0 | AV39: =AVERAGE(AA39:AC39) -> 0 | AW39: =AVERAGE(AD39:AF39) -> 0 | AX39: =AVERAGE(AG39:AI39) -> 0 | AY39: =AVERAGE(AJ39:AL39) -> 0 | BA39: =AVERAGE(C39:N39) -> 0 | BB39: =AVERAGE(O39:Z39) -> 0 | BC39: =AVERAGE(AA39:AL39) -> 0
A40: Free-to-paid conversion % | C40: =IFERROR(C27/C25,0) -> 0 | D40: =IFERROR(D27/D25,0) -> 0 | E40: =IFERROR(E27/E25,0) -> 0 | F40: =IFERROR(F27/F25,0) -> 0 | G40: =IFERROR(G27/G25,0) -> 0 | H40: =IFERROR(H27/H25,0) -> 0 | I40: =IFERROR(I27/I25,0) -> 0 | J40: =IFERROR(J27/J25,0) -> 0 | ... AL40: =IFERROR(AL27/AL25,0) -> 0 | AN40: =AVERAGE(C40:E40) -> 0 | AO40: =AVERAGE(F40:H40) -> 0 | AP40: =AVERAGE(I40:K40) -> 0 | AQ40: =AVERAGE(L40:N40) -> 0 | AR40: =AVERAGE(O40:Q40) -> 0 | AS40: =AVERAGE(R40:T40) -> 0 | AT40: =AVERAGE(U40:W40) -> 0 | AU40: =AVERAGE(X40:Z40) -> 0 | AV40: =AVERAGE(AA40:AC40) -> 0 | AW40: =AVERAGE(AD40:AF40) -> 0 | AX40: =AVERAGE(AG40:AI40) -> 0 | AY40: =AVERAGE(AJ40:AL40) -> 0 | BA40: =AVERAGE(C40:N40) -> 0 | BB40: =AVERAGE(O40:Z40) -> 0 | BC40: =AVERAGE(AA40:AL40) -> 0
A41: Paid retention % | C41: =IFERROR(C24/C22,1) -> 0 | D41: =IFERROR(D24/D22,1) -> 0 | E41: =IFERROR(E24/E22,1) -> 0 | F41: =IFERROR(F24/F22,1) -> 0 | G41: =IFERROR(G24/G22,1) -> 0 | H41: =IFERROR(H24/H22,1) -> 0 | I41: =IFERROR(I24/I22,1) -> 0 | J41: =IFERROR(J24/J22,1) -> 0 | ... AL41: =IFERROR(AL24/AL22,1) -> 0 | AN41: =AVERAGE(C41:E41) -> 0 | AO41: =AVERAGE(F41:H41) -> 0 | AP41: =AVERAGE(I41:K41) -> 0 | AQ41: =AVERAGE(L41:N41) -> 0 | AR41: =AVERAGE(O41:Q41) -> 0 | AS41: =AVERAGE(R41:T41) -> 0 | AT41: =AVERAGE(U41:W41) -> 0 | AU41: =AVERAGE(X41:Z41) -> 0 | AV41: =AVERAGE(AA41:AC41) -> 0 | AW41: =AVERAGE(AD41:AF41) -> 0 | AX41: =AVERAGE(AG41:AI41) -> 0 | AY41: =AVERAGE(AJ41:AL41) -> 0 | BA41: =AVERAGE(C41:N41) -> 0 | BB41: =AVERAGE(O41:Z41) -> 0 | BC41: =AVERAGE(AA41:AL41) -> 0
A42: Paid churn % | C42: =IFERROR(-C23/C22,'Assumptions'!$F$28) -> 0 | D42: =IFERROR(-D23/D22,'Assumptions'!$F$28) -> 0 | E42: =IFERROR(-E23/E22,'Assumptions'!$F$28) -> 0 | F42: =IFERROR(-F23/F22,'Assumptions'!$F$28) -> 0 | G42: =IFERROR(-G23/G22,'Assumptions'!$F$28) -> 0 | H42: =IFERROR(-H23/H22,'Assumptions'!$F$28) -> 0 | I42: =IFERROR(-I23/I22,'Assumptions'!$F$28) -> 0 | J42: =IFERROR(-J23/J22,'Assumptions'!$F$28) -> 0 | ... AL42: =IFERROR(-AL23/AL22,'Assumptions'!$F$28) -> 0 | AN42: =AVERAGE(C42:E42) -> 0 | AO42: =AVERAGE(F42:H42) -> 0 | AP42: =AVERAGE(I42:K42) -> 0 | AQ42: =AVERAGE(L42:N42) -> 0 | AR42: =AVERAGE(O42:Q42) -> 0 | AS42: =AVERAGE(R42:T42) -> 0 | AT42: =AVERAGE(U42:W42) -> 0 | AU42: =AVERAGE(X42:Z42) -> 0 | AV42: =AVERAGE(AA42:AC42) -> 0 | AW42: =AVERAGE(AD42:AF42) -> 0 | AX42: =AVERAGE(AG42:AI42) -> 0 | AY42: =AVERAGE(AJ42:AL42) -> 0 | BA42: =AVERAGE(C42:N42) -> 0 | BB42: =AVERAGE(O42:Z42) -> 0 | BC42: =AVERAGE(AA42:AL42) -> 0
A43: Blended CAC | B43: Total acquisition spend ÷ new paid adds | C43: =IFERROR(C15/MAX(1,C27),0) -> 0 | D43: =IFERROR(D15/MAX(1,D27),0) -> 0 | E43: =IFERROR(E15/MAX(1,E27),0) -> 0 | F43: =IFERROR(F15/MAX(1,F27),0) -> 0 | G43: =IFERROR(G15/MAX(1,G27),0) -> 0 | H43: =IFERROR(H15/MAX(1,H27),0) -> 0 | I43: =IFERROR(I15/MAX(1,I27),0) -> 0 | J43: =IFERROR(J15/MAX(1,J27),0) -> 0 | ... AL43: =IFERROR(AL15/MAX(1,AL27),0) -> 0 | AN43: =AVERAGE(C43:E43) -> 0 | AO43: =AVERAGE(F43:H43) -> 0 | AP43: =AVERAGE(I43:K43) -> 0 | AQ43: =AVERAGE(L43:N43) -> 0 | AR43: =AVERAGE(O43:Q43) -> 0 | AS43: =AVERAGE(R43:T43) -> 0 | AT43: =AVERAGE(U43:W43) -> 0 | AU43: =AVERAGE(X43:Z43) -> 0 | AV43: =AVERAGE(AA43:AC43) -> 0 | AW43: =AVERAGE(AD43:AF43) -> 0 | AX43: =AVERAGE(AG43:AI43) -> 0 | AY43: =AVERAGE(AJ43:AL43) -> 0 | BA43: =AVERAGE(C43:N43) -> 0 | BB43: =AVERAGE(O43:Z43) -> 0 | BC43: =AVERAGE(AA43:AL43) -> 0
A44: Revenue per MAU | C44: =IFERROR(C35/C21,0) -> 0 | D44: =IFERROR(D35/D21,0) -> 0 | E44: =IFERROR(E35/E21,0) -> 0 | F44: =IFERROR(F35/F21,0) -> 0 | G44: =IFERROR(G35/G21,0) -> 0 | H44: =IFERROR(H35/H21,0) -> 0 | I44: =IFERROR(I35/I21,0) -> 0 | J44: =IFERROR(J35/J21,0) -> 0 | ... AL44: =IFERROR(AL35/AL21,0) -> 0 | AN44: =AVERAGE(C44:E44) -> 0 | AO44: =AVERAGE(F44:H44) -> 0 | AP44: =AVERAGE(I44:K44) -> 0 | AQ44: =AVERAGE(L44:N44) -> 0 | AR44: =AVERAGE(O44:Q44) -> 0 | AS44: =AVERAGE(R44:T44) -> 0 | AT44: =AVERAGE(U44:W44) -> 0 | AU44: =AVERAGE(X44:Z44) -> 0 | AV44: =AVERAGE(AA44:AC44) -> 0 | AW44: =AVERAGE(AD44:AF44) -> 0 | AX44: =AVERAGE(AG44:AI44) -> 0 | AY44: =AVERAGE(AJ44:AL44) -> 0 | BA44: =AVERAGE(C44:N44) -> 0 | BB44: =AVERAGE(O44:Z44) -> 0 | BC44: =AVERAGE(AA44:AL44) -> 0

Sheet COGS & GM
A1: Consumer Subscription — 3-Year Financial Model — COGS & GM
A2: App-store / payment fees, hosting, AI inference cost, and Support / Community Ops people cost.
A5: Line item | B5: Units / source | C5: Monthly (36 months) | AN5: Quarterly | BA5: Annual
C6: 46023 | D6: 46054 | E6: 46082 | F6: 46113 | G6: 46143 | H6: 46174 | I6: 46204 | J6: 46235 | K6: 46266 | L6: 46296 | M6: 46327 | N6: 46357 | O6: 46388 | P6: 46419 | Q6: 46447 | R6: 46478 | S6: 46508 | T6: 46539 | U6: 46569 | V6: 46600 | W6: 46631 | X6: 46661 | Y6: 46692 | Z6: 46722 | AA6: 46753 | AB6: 46784 | AC6: 46813 | AD6: 46844 | AE6: 46874 | AF6: 46905 | AG6: 46935 | AH6: 46966 | AI6: 46997 | AJ6: 47027 | AK6: 47058 | AL6: 47088 | AN6: Q1 | AO6: Q2 | AP6: Q3 | AQ6: Q4 | AR6: Q5 | AS6: Q6 | AT6: Q7 | AU6: Q8 | AV6: Q9 | AW6: Q10 | AX6: Q11 | AY6: Q12 | BA6: FY1 | BB6: FY2 | BC6: FY3
A7: COGS Components
A8: App-store / platform fees | C8: ='Revenue'!C35*'Assumptions'!$F$35 -> 0 | D8: ='Revenue'!D35*'Assumptions'!$F$35 -> 0 | E8: ='Revenue'!E35*'Assumptions'!$F$35 -> 0 | F8: ='Revenue'!F35*'Assumptions'!$F$35 -> 0 | G8: ='Revenue'!G35*'Assumptions'!$F$35 -> 0 | H8: ='Revenue'!H35*'Assumptions'!$F$35 -> 0 | I8: ='Revenue'!I35*'Assumptions'!$F$35 -> 0 | J8: ='Revenue'!J35*'Assumptions'!$F$35 -> 0 | ... AL8: ='Revenue'!AL35*'Assumptions'!$F$35 -> 0 | AN8: =SUM(C8:E8) -> 0 | AO8: =SUM(F8:H8) -> 0 | AP8: =SUM(I8:K8) -> 0 | AQ8: =SUM(L8:N8) -> 0 | AR8: =SUM(O8:Q8) -> 0 | AS8: =SUM(R8:T8) -> 0 | AT8: =SUM(U8:W8) -> 0 | AU8: =SUM(X8:Z8) -> 0 | AV8: =SUM(AA8:AC8) -> 0 | AW8: =SUM(AD8:AF8) -> 0 | AX8: =SUM(AG8:AI8) -> 0 | AY8: =SUM(AJ8:AL8) -> 0 | BA8: =SUM(C8:N8) -> 0 | BB8: =SUM(O8:Z8) -> 0 | BC8: =SUM(AA8:AL8) -> 0
A9: Payment processing fees | C9: ='Revenue'!C35*'Assumptions'!$F$36 -> 0 | D9: ='Revenue'!D35*'Assumptions'!$F$36 -> 0 | E9: ='Revenue'!E35*'Assumptions'!$F$36 -> 0 | F9: ='Revenue'!F35*'Assumptions'!$F$36 -> 0 | G9: ='Revenue'!G35*'Assumptions'!$F$36 -> 0 | H9: ='Revenue'!H35*'Assumptions'!$F$36 -> 0 | I9: ='Revenue'!I35*'Assumptions'!$F$36 -> 0 | J9: ='Revenue'!J35*'Assumptions'!$F$36 -> 0 | ... AL9: ='Revenue'!AL35*'Assumptions'!$F$36 -> 0 | AN9: =SUM(C9:E9) -> 0 | AO9: =SUM(F9:H9) -> 0 | AP9: =SUM(I9:K9) -> 0 | AQ9: =SUM(L9:N9) -> 0 | AR9: =SUM(O9:Q9) -> 0 | AS9: =SUM(R9:T9) -> 0 | AT9: =SUM(U9:W9) -> 0 | AU9: =SUM(X9:Z9) -> 0 | AV9: =SUM(AA9:AC9) -> 0 | AW9: =SUM(AD9:AF9) -> 0 | AX9: =SUM(AG9:AI9) -> 0 | AY9: =SUM(AJ9:AL9) -> 0 | BA9: =SUM(C9:N9) -> 0 | BB9: =SUM(O9:Z9) -> 0 | BC9: =SUM(AA9:AL9) -> 0
A10: Hosting & infrastructure | C10: ='Revenue'!C21*'Assumptions'!$F$37 -> 0 | D10: ='Revenue'!D21*'Assumptions'!$F$37 -> 0 | E10: ='Revenue'!E21*'Assumptions'!$F$37 -> 0 | F10: ='Revenue'!F21*'Assumptions'!$F$37 -> 0 | G10: ='Revenue'!G21*'Assumptions'!$F$37 -> 0 | H10: ='Revenue'!H21*'Assumptions'!$F$37 -> 0 | I10: ='Revenue'!I21*'Assumptions'!$F$37 -> 0 | J10: ='Revenue'!J21*'Assumptions'!$F$37 -> 0 | ... AL10: ='Revenue'!AL21*'Assumptions'!$F$37 -> 0 | AN10: =SUM(C10:E10) -> 0 | AO10: =SUM(F10:H10) -> 0 | AP10: =SUM(I10:K10) -> 0 | AQ10: =SUM(L10:N10) -> 0 | AR10: =SUM(O10:Q10) -> 0 | AS10: =SUM(R10:T10) -> 0 | AT10: =SUM(U10:W10) -> 0 | AU10: =SUM(X10:Z10) -> 0 | AV10: =SUM(AA10:AC10) -> 0 | AW10: =SUM(AD10:AF10) -> 0 | AX10: =SUM(AG10:AI10) -> 0 | AY10: =SUM(AJ10:AL10) -> 0 | BA10: =SUM(C10:N10) -> 0 | BB10: =SUM(O10:Z10) -> 0 | BC10: =SUM(AA10:AL10) -> 0
A11: AI inference / premium support | C11: ='Revenue'!C28*'Assumptions'!$F$38 -> 0 | D11: ='Revenue'!D28*'Assumptions'!$F$38 -> 0 | E11: ='Revenue'!E28*'Assumptions'!$F$38 -> 0 | F11: ='Revenue'!F28*'Assumptions'!$F$38 -> 0 | G11: ='Revenue'!G28*'Assumptions'!$F$38 -> 0 | H11: ='Revenue'!H28*'Assumptions'!$F$38 -> 0 | I11: ='Revenue'!I28*'Assumptions'!$F$38 -> 0 | J11: ='Revenue'!J28*'Assumptions'!$F$38 -> 0 | ... AL11: ='Revenue'!AL28*'Assumptions'!$F$38 -> 0 | AN11: =SUM(C11:E11) -> 0 | AO11: =SUM(F11:H11) -> 0 | AP11: =SUM(I11:K11) -> 0 | AQ11: =SUM(L11:N11) -> 0 | AR11: =SUM(O11:Q11) -> 0 | AS11: =SUM(R11:T11) -> 0 | AT11: =SUM(U11:W11) -> 0 | AU11: =SUM(X11:Z11) -> 0 | AV11: =SUM(AA11:AC11) -> 0 | AW11: =SUM(AD11:AF11) -> 0 | AX11: =SUM(AG11:AI11) -> 0 | AY11: =SUM(AJ11:AL11) -> 0 | BA11: =SUM(C11:N11) -> 0 | BB11: =SUM(O11:Z11) -> 0 | BC11: =SUM(AA11:AL11) -> 0
A12: Support / Community Ops people cost | C12: ='Headcount'!$C$21 -> 0 | D12: ='Headcount'!$D$21 -> 0 | E12: ='Headcount'!$E$21 -> 0 | F12: ='Headcount'!$F$21 -> 0 | G12: ='Headcount'!$G$21 -> 0 | H12: ='Headcount'!$H$21 -> 0 | I12: ='Headcount'!$I$21 -> 0 | J12: ='Headcount'!$J$21 -> 0 | K12: ='Headcount'!$K$21 -> 0 | L12: ='Headcount'!$L$21 -> 0 | M12: ='Headcount'!$M$21 -> 0 | N12: ='Headcount'!$N$21 -> 0 | O12: ='Headcount'!$O$21 -> 0 | P12: ='Headcount'!$P$21 -> 0 | Q12: ='Headcount'!$Q$21 -> 0 | R12: ='Headcount'!$R$21 -> 0 | S12: ='Headcount'!$S$21 -> 0 | T12: ='Headcount'!$T$21 -> 0 | U12: ='Headcount'!$U$21 -> 0 | V12: ='Headcount'!$V$21 -> 0 | W12: ='Headcount'!$W$21 -> 0 | X12: ='Headcount'!$X$21 -> 0 | Y12: ='Headcount'!$Y$21 -> 0 | Z12: ='Headcount'!$Z$21 -> 0 | AA12: ='Headcount'!$AA$21 -> 0 | AB12: ='Headcount'!$AB$21 -> 0 | AC12: ='Headcount'!$AC$21 -> 0 | AD12: ='Headcount'!$AD$21 -> 0 | AE12: ='Headcount'!$AE$21 -> 0 | AF12: ='Headcount'!$AF$21 -> 0 | AG12: ='Headcount'!$AG$21 -> 0 | AH12: ='Headcount'!$AH$21 -> 0 | AI12: ='Headcount'!$AI$21 -> 0 | AJ12: ='Headcount'!$AJ$21 -> 0 | AK12: ='Headcount'!$AK$21 -> 0 | AL12: ='Headcount'!$AL$21 -> 0 | AN12: =SUM(C12:E12) -> 0 | AO12: =SUM(F12:H12) -> 0 | AP12: =SUM(I12:K12) -> 0 | AQ12: =SUM(L12:N12) -> 0 | AR12: =SUM(O12:Q12) -> 0 | AS12: =SUM(R12:T12) -> 0 | AT12: =SUM(U12:W12) -> 0 | AU12: =SUM(X12:Z12) -> 0 | AV12: =SUM(AA12:AC12) -> 0 | AW12: =SUM(AD12:AF12) -> 0 | AX12: =SUM(AG12:AI12) -> 0 | AY12: =SUM(AJ12:AL12) -> 0 | BA12: =SUM(C12:N12) -> 0 | BB12: =SUM(O12:Z12) -> 0 | BC12: =SUM(AA12:AL12) -> 0
A13: Total COGS | C13: =C8+C9+C10+C11+C12 -> 0 | D13: =D8+D9+D10+D11+D12 -> 0 | E13: =E8+E9+E10+E11+E12 -> 0 | F13: =F8+F9+F10+F11+F12 -> 0 | G13: =G8+G9+G10+G11+G12 -> 0 | H13: =H8+H9+H10+H11+H12 -> 0 | I13: =I8+I9+I10+I11+I12 -> 0 | J13: =J8+J9+J10+J11+J12 -> 0 | ... AL13: =AL8+AL9+AL10+AL11+AL12 -> 0 | AN13: =SUM(C13:E13) -> 0 | AO13: =SUM(F13:H13) -> 0 | AP13: =SUM(I13:K13) -> 0 | AQ13: =SUM(L13:N13) -> 0 | AR13: =SUM(O13:Q13) -> 0 | AS13: =SUM(R13:T13) -> 0 | AT13: =SUM(U13:W13) -> 0 | AU13: =SUM(X13:Z13) -> 0 | AV13: =SUM(AA13:AC13) -> 0 | AW13: =SUM(AD13:AF13) -> 0 | AX13: =SUM(AG13:AI13) -> 0 | AY13: =SUM(AJ13:AL13) -> 0 | BA13: =SUM(C13:N13) -> 0 | BB13: =SUM(O13:Z13) -> 0 | BC13: =SUM(AA13:AL13) -> 0
A15: Gross Profit & Unit Economics
A16: Gross Profit | C16: ='Revenue'!C35-C13 -> 0 | D16: ='Revenue'!D35-D13 -> 0 | E16: ='Revenue'!E35-E13 -> 0 | F16: ='Revenue'!F35-F13 -> 0 | G16: ='Revenue'!G35-G13 -> 0 | H16: ='Revenue'!H35-H13 -> 0 | I16: ='Revenue'!I35-I13 -> 0 | J16: ='Revenue'!J35-J13 -> 0 | ... AL16: ='Revenue'!AL35-AL13 -> 0 | AN16: =SUM(C16:E16) -> 0 | AO16: =SUM(F16:H16) -> 0 | AP16: =SUM(I16:K16) -> 0 | AQ16: =SUM(L16:N16) -> 0 | AR16: =SUM(O16:Q16) -> 0 | AS16: =SUM(R16:T16) -> 0 | AT16: =SUM(U16:W16) -> 0 | AU16: =SUM(X16:Z16) -> 0 | AV16: =SUM(AA16:AC16) -> 0 | AW16: =SUM(AD16:AF16) -> 0 | AX16: =SUM(AG16:AI16) -> 0 | AY16: =SUM(AJ16:AL16) -> 0 | BA16: =SUM(C16:N16) -> 0 | BB16: =SUM(O16:Z16) -> 0 | BC16: =SUM(AA16:AL16) -> 0
A17: Gross Margin % | C17: =IFERROR(C16/'Revenue'!C35,0) -> 0 | D17: =IFERROR(D16/'Revenue'!D35,0) -> 0 | E17: =IFERROR(E16/'Revenue'!E35,0) -> 0 | F17: =IFERROR(F16/'Revenue'!F35,0) -> 0 | G17: =IFERROR(G16/'Revenue'!G35,0) -> 0 | H17: =IFERROR(H16/'Revenue'!H35,0) -> 0 | I17: =IFERROR(I16/'Revenue'!I35,0) -> 0 | J17: =IFERROR(J16/'Revenue'!J35,0) -> 0 | ... AL17: =IFERROR(AL16/'Revenue'!AL35,0) -> 0 | AN17: =AVERAGE(C17:E17) -> 0 | AO17: =AVERAGE(F17:H17) -> 0 | AP17: =AVERAGE(I17:K17) -> 0 | AQ17: =AVERAGE(L17:N17) -> 0 | AR17: =AVERAGE(O17:Q17) -> 0 | AS17: =AVERAGE(R17:T17) -> 0 | AT17: =AVERAGE(U17:W17) -> 0 | AU17: =AVERAGE(X17:Z17) -> 0 | AV17: =AVERAGE(AA17:AC17) -> 0 | AW17: =AVERAGE(AD17:AF17) -> 0 | AX17: =AVERAGE(AG17:AI17) -> 0 | AY17: =AVERAGE(AJ17:AL17) -> 0 | BA17: =AVERAGE(C17:N17) -> 0 | BB17: =AVERAGE(O17:Z17) -> 0 | BC17: =AVERAGE(AA17:AL17) -> 0
A18: Contribution Margin % | B18: (Gross profit − acquisition spend) ÷ revenue | C18: =IFERROR((C16-'Revenue'!C15)/'Revenue'!C35,0) -> 0 | D18: =IFERROR((D16-'Revenue'!D15)/'Revenue'!D35,0) -> 0 | E18: =IFERROR((E16-'Revenue'!E15)/'Revenue'!E35,0) -> 0 | F18: =IFERROR((F16-'Revenue'!F15)/'Revenue'!F35,0) -> 0 | G18: =IFERROR((G16-'Revenue'!G15)/'Revenue'!G35,0) -> 0 | H18: =IFERROR((H16-'Revenue'!H15)/'Revenue'!H35,0) -> 0 | I18: =IFERROR((I16-'Revenue'!I15)/'Revenue'!I35,0) -> 0 | J18: =IFERROR((J16-'Revenue'!J15)/'Revenue'!J35,0) -> 0 | ... AL18: =IFERROR((AL16-'Revenue'!AL15)/'Revenue'!AL35,0) -> 0 | AN18: =AVERAGE(C18:E18) -> 0 | AO18: =AVERAGE(F18:H18) -> 0 | AP18: =AVERAGE(I18:K18) -> 0 | AQ18: =AVERAGE(L18:N18) -> 0 | AR18: =AVERAGE(O18:Q18) -> 0 | AS18: =AVERAGE(R18:T18) -> 0 | AT18: =AVERAGE(U18:W18) -> 0 | AU18: =AVERAGE(X18:Z18) -> 0 | AV18: =AVERAGE(AA18:AC18) -> 0 | AW18: =AVERAGE(AD18:AF18) -> 0 | AX18: =AVERAGE(AG18:AI18) -> 0 | AY18: =AVERAGE(AJ18:AL18) -> 0 | BA18: =AVERAGE(C18:N18) -> 0 | BB18: =AVERAGE(O18:Z18) -> 0 | BC18: =AVERAGE(AA18:AL18) -> 0
A19: LTV | B19: Blended ARPU × contribution margin % ÷ monthly paid churn | C19: =IF('Revenue'!C42<=0,999,MAX(0,('Revenue'!C32*C18)/'Revenue'!C42)) -> 0 | D19: =IF('Revenue'!D42<=0,999,MAX(0,('Revenue'!D32*D18)/'Revenue'!D42)) -> 0 | E19: =IF('Revenue'!E42<=0,999,MAX(0,('Revenue'!E32*E18)/'Revenue'!E42)) -> 0 | F19: =IF('Revenue'!F42<=0,999,MAX(0,('Revenue'!F32*F18)/'Revenue'!F42)) -> 0 | G19: =IF('Revenue'!G42<=0,999,MAX(0,('Revenue'!G32*G18)/'Revenue'!G42)) -> 0 | H19: =IF('Revenue'!H42<=0,999,MAX(0,('Revenue'!H32*H18)/'Revenue'!H42)) -> 0 | I19: =IF('Revenue'!I42<=0,999,MAX(0,('Revenue'!I32*I18)/'Revenue'!I42)) -> 0 | J19: =IF('Revenue'!J42<=0,999,MAX(0,('Revenue'!J32*J18)/'Revenue'!J42)) -> 0 | ... AL19: =IF('Revenue'!AL42<=0,999,MAX(0,('Revenue'!AL32*AL18)/'Revenue'!AL42)) -> 0 | AN19: =AVERAGE(C19:E19) -> 0 | AO19: =AVERAGE(F19:H19) -> 0 | AP19: =AVERAGE(I19:K19) -> 0 | AQ19: =AVERAGE(L19:N19) -> 0 | AR19: =AVERAGE(O19:Q19) -> 0 | AS19: =AVERAGE(R19:T19) -> 0 | AT19: =AVERAGE(U19:W19) -> 0 | AU19: =AVERAGE(X19:Z19) -> 0 | AV19: =AVERAGE(AA19:AC19) -> 0 | AW19: =AVERAGE(AD19:AF19) -> 0 | AX19: =AVERAGE(AG19:AI19) -> 0 | AY19: =AVERAGE(AJ19:AL19) -> 0 | BA19: =AVERAGE(C19:N19) -> 0 | BB19: =AVERAGE(O19:Z19) -> 0 | BC19: =AVERAGE(AA19:AL19) -> 0
A20: LTV : CAC | C20: =IFERROR(C19/'Revenue'!C43,0) -> 0 | D20: =IFERROR(D19/'Revenue'!D43,0) -> 0 | E20: =IFERROR(E19/'Revenue'!E43,0) -> 0 | F20: =IFERROR(F19/'Revenue'!F43,0) -> 0 | G20: =IFERROR(G19/'Revenue'!G43,0) -> 0 | H20: =IFERROR(H19/'Revenue'!H43,0) -> 0 | I20: =IFERROR(I19/'Revenue'!I43,0) -> 0 | J20: =IFERROR(J19/'Revenue'!J43,0) -> 0 | ... AL20: =IFERROR(AL19/'Revenue'!AL43,0) -> 0 | AN20: =AVERAGE(C20:E20) -> 0 | AO20: =AVERAGE(F20:H20) -> 0 | AP20: =AVERAGE(I20:K20) -> 0 | AQ20: =AVERAGE(L20:N20) -> 0 | AR20: =AVERAGE(O20:Q20) -> 0 | AS20: =AVERAGE(R20:T20) -> 0 | AT20: =AVERAGE(U20:W20) -> 0 | AU20: =AVERAGE(X20:Z20) -> 0 | AV20: =AVERAGE(AA20:AC20) -> 0 | AW20: =AVERAGE(AD20:AF20) -> 0 | AX20: =AVERAGE(AG20:AI20) -> 0 | AY20: =AVERAGE(AJ20:AL20) -> 0 | BA20: =AVERAGE(C20:N20) -> 0 | BB20: =AVERAGE(O20:Z20) -> 0 | BC20: =AVERAGE(AA20:AL20) -> 0
A21: CAC payback (months) | B21: Blended CAC ÷ (ARPU × contribution margin %) | C21: =IF('Revenue'!C32*C18<=0,999,'Revenue'!C43/'Revenue'!C32*C18) -> 0 | D21: =IF('Revenue'!D32*D18<=0,999,'Revenue'!D43/'Revenue'!D32*D18) -> 0 | E21: =IF('Revenue'!E32*E18<=0,999,'Revenue'!E43/'Revenue'!E32*E18) -> 0 | F21: =IF('Revenue'!F32*F18<=0,999,'Revenue'!F43/'Revenue'!F32*F18) -> 0 | G21: =IF('Revenue'!G32*G18<=0,999,'Revenue'!G43/'Revenue'!G32*G18) -> 0 | H21: =IF('Revenue'!H32*H18<=0,999,'Revenue'!H43/'Revenue'!H32*H18) -> 0 | I21: =IF('Revenue'!I32*I18<=0,999,'Revenue'!I43/'Revenue'!I32*I18) -> 0 | J21: =IF('Revenue'!J32*J18<=0,999,'Revenue'!J43/'Revenue'!J32*J18) -> 0 | ... AL21: =IF('Revenue'!AL32*AL18<=0,999,'Revenue'!AL43/'Revenue'!AL32*AL18) -> 0 | AN21: =AVERAGE(C21:E21) -> 0 | AO21: =AVERAGE(F21:H21) -> 0 | AP21: =AVERAGE(I21:K21) -> 0 | AQ21: =AVERAGE(L21:N21) -> 0 | AR21: =AVERAGE(O21:Q21) -> 0 | AS21: =AVERAGE(R21:T21) -> 0 | AT21: =AVERAGE(U21:W21) -> 0 | AU21: =AVERAGE(X21:Z21) -> 0 | AV21: =AVERAGE(AA21:AC21) -> 0 | AW21: =AVERAGE(AD21:AF21) -> 0 | AX21: =AVERAGE(AG21:AI21) -> 0 | AY21: =AVERAGE(AJ21:AL21) -> 0 | BA21: =AVERAGE(C21:N21) -> 0 | BB21: =AVERAGE(O21:Z21) -> 0 | BC21: =AVERAGE(AA21:AL21) -> 0
A22: Runway (months) | B22: Linked from the Cash & Runway tab | C22: =INDEX('Cash & Runway'!$C:$AL,MATCH("Runway (months)",'Cash & Runway'!$A:$A,0),1) -> 0 | D22: =INDEX('Cash & Runway'!$C:$AL,MATCH("Runway (months)",'Cash & Runway'!$A:$A,0),2) -> 0 | E22: =INDEX('Cash & Runway'!$C:$AL,MATCH("Runway (months)",'Cash & Runway'!$A:$A,0),3) -> 0 | F22: =INDEX('Cash & Runway'!$C:$AL,MATCH("Runway (months)",'Cash & Runway'!$A:$A,0),4) -> 0 | G22: =INDEX('Cash & Runway'!$C:$AL,MATCH("Runway (months)",'Cash & Runway'!$A:$A,0),5) -> 0 | H22: =INDEX('Cash & Runway'!$C:$AL,MATCH("Runway (months)",'Cash & Runway'!$A:$A,0),6) -> 0 | I22: =INDEX('Cash & Runway'!$C:$AL,MATCH("Runway (months)",'Cash & Runway'!$A:$A,0),7) -> 0 | J22: =INDEX('Cash & Runway'!$C:$AL,MATCH("Runway (months)",'Cash & Runway'!$A:$A,0),8) -> 0 | K22: =INDEX('Cash & Runway'!$C:$AL,MATCH("Runway (months)",'Cash & Runway'!$A:$A,0),9) -> 0 | L22: =INDEX('Cash & Runway'!$C:$AL,MATCH("Runway (months)",'Cash & Runway'!$A:$A,0),10) -> 0 | M22: =INDEX('Cash & Runway'!$C:$AL,MATCH("Runway (months)",'Cash & Runway'!$A:$A,0),11) -> 0 | N22: =INDEX('Cash & Runway'!$C:$AL,MATCH("Runway (months)",'Cash & Runway'!$A:$A,0),12) -> 0 | O22: =INDEX('Cash & Runway'!$C:$AL,MATCH("Runway (months)",'Cash & Runway'!$A:$A,0),13) -> 0 | P22: =INDEX('Cash & Runway'!$C:$AL,MATCH("Runway (months)",'Cash & Runway'!$A:$A,0),14) -> 0 | Q22: =INDEX('Cash & Runway'!$C:$AL,MATCH("Runway (months)",'Cash & Runway'!$A:$A,0),15) -> 0 | R22: =INDEX('Cash & Runway'!$C:$AL,MATCH("Runway (months)",'Cash & Runway'!$A:$A,0),16) -> 0 | S22: =INDEX('Cash & Runway'!$C:$AL,MATCH("Runway (months)",'Cash & Runway'!$A:$A,0),17) -> 0 | T22: =INDEX('Cash & Runway'!$C:$AL,MATCH("Runway (months)",'Cash & Runway'!$A:$A,0),18) -> 0 | U22: =INDEX('Cash & Runway'!$C:$AL,MATCH("Runway (months)",'Cash & Runway'!$A:$A,0),19) -> 0 | V22: =INDEX('Cash & Runway'!$C:$AL,MATCH("Runway (months)",'Cash & Runway'!$A:$A,0),20) -> 0 | W22: =INDEX('Cash & Runway'!$C:$AL,MATCH("Runway (months)",'Cash & Runway'!$A:$A,0),21) -> 0 | X22: =INDEX('Cash & Runway'!$C:$AL,MATCH("Runway (months)",'Cash & Runway'!$A:$A,0),22) -> 0 | Y22: =INDEX('Cash & Runway'!$C:$AL,MATCH("Runway (months)",'Cash & Runway'!$A:$A,0),23) -> 0 | Z22: =INDEX('Cash & Runway'!$C:$AL,MATCH("Runway (months)",'Cash & Runway'!$A:$A,0),24) -> 0 | AA22: =INDEX('Cash & Runway'!$C:$AL,MATCH("Runway (months)",'Cash & Runway'!$A:$A,0),25) -> 0 | AB22: =INDEX('Cash & Runway'!$C:$AL,MATCH("Runway (months)",'Cash & Runway'!$A:$A,0),26) -> 0 | AC22: =INDEX('Cash & Runway'!$C:$AL,MATCH("Runway (months)",'Cash & Runway'!$A:$A,0),27) -> 0 | AD22: =INDEX('Cash & Runway'!$C:$AL,MATCH("Runway (months)",'Cash & Runway'!$A:$A,0),28) -> 0 | AE22: =INDEX('Cash & Runway'!$C:$AL,MATCH("Runway (months)",'Cash & Runway'!$A:$A,0),29) -> 0 | AF22: =INDEX('Cash & Runway'!$C:$AL,MATCH("Runway (months)",'Cash & Runway'!$A:$A,0),30) -> 0 | AG22: =INDEX('Cash & Runway'!$C:$AL,MATCH("Runway (months)",'Cash & Runway'!$A:$A,0),31) -> 0 | AH22: =INDEX('Cash & Runway'!$C:$AL,MATCH("Runway (months)",'Cash & Runway'!$A:$A,0),32) -> 0 | AI22: =INDEX('Cash & Runway'!$C:$AL,MATCH("Runway (months)",'Cash & Runway'!$A:$A,0),33) -> 0 | AJ22: =INDEX('Cash & Runway'!$C:$AL,MATCH("Runway (months)",'Cash & Runway'!$A:$A,0),34) -> 0 | AK22: =INDEX('Cash & Runway'!$C:$AL,MATCH("Runway (months)",'Cash & Runway'!$A:$A,0),35) -> 0 | AL22: =INDEX('Cash & Runway'!$C:$AL,MATCH("Runway (months)",'Cash & Runway'!$A:$A,0),36) -> 0 | AN22: =E22 -> 0 | AO22: =H22 -> 0 | AP22: =K22 -> 0 | AQ22: =N22 -> 0 | AR22: =Q22 -> 0 | AS22: =T22 -> 0 | AT22: =W22 -> 0 | AU22: =Z22 -> 0 | AV22: =AC22 -> 0 | AW22: =AF22 -> 0 | AX22: =AI22 -> 0 | AY22: =AL22 -> 0 | BA22: =N22 -> 0 | BB22: =Z22 -> 0 | BC22: =AL22 -> 0

Sheet Opex
A1: Consumer Subscription — 3-Year Financial Model — Opex
A2: Operating expenses by department — headcount cost plus program spend.
A5: Line item | B5: Units / source | C5: Monthly (36 months) | AN5: Quarterly | BA5: Annual
C6: 46023 | D6: 46054 | E6: 46082 | F6: 46113 | G6: 46143 | H6: 46174 | I6: 46204 | J6: 46235 | K6: 46266 | L6: 46296 | M6: 46327 | N6: 46357 | O6: 46388 | P6: 46419 | Q6: 46447 | R6: 46478 | S6: 46508 | T6: 46539 | U6: 46569 | V6: 46600 | W6: 46631 | X6: 46661 | Y6: 46692 | Z6: 46722 | AA6: 46753 | AB6: 46784 | AC6: 46813 | AD6: 46844 | AE6: 46874 | AF6: 46905 | AG6: 46935 | AH6: 46966 | AI6: 46997 | AJ6: 47027 | AK6: 47058 | AL6: 47088 | AN6: Q1 | AO6: Q2 | AP6: Q3 | AQ6: Q4 | AR6: Q5 | AS6: Q6 | AT6: Q7 | AU6: Q8 | AV6: Q9 | AW6: Q10 | AX6: Q11 | AY6: Q12 | BA6: FY1 | BB6: FY2 | BC6: FY3
A7: Growth & Marketing
A8: Growth & Marketing — people cost | B8: Linked from Headcount tab | C8: ='Headcount'!$C$24 -> 0 | D8: ='Headcount'!$D$24 -> 0 | E8: ='Headcount'!$E$24 -> 0 | F8: ='Headcount'!$F$24 -> 0 | G8: ='Headcount'!$G$24 -> 0 | H8: ='Headcount'!$H$24 -> 0 | I8: ='Headcount'!$I$24 -> 0 | J8: ='Headcount'!$J$24 -> 0 | K8: ='Headcount'!$K$24 -> 0 | L8: ='Headcount'!$L$24 -> 0 | M8: ='Headcount'!$M$24 -> 0 | N8: ='Headcount'!$N$24 -> 0 | O8: ='Headcount'!$O$24 -> 0 | P8: ='Headcount'!$P$24 -> 0 | Q8: ='Headcount'!$Q$24 -> 0 | R8: ='Headcount'!$R$24 -> 0 | S8: ='Headcount'!$S$24 -> 0 | T8: ='Headcount'!$T$24 -> 0 | U8: ='Headcount'!$U$24 -> 0 | V8: ='Headcount'!$V$24 -> 0 | W8: ='Headcount'!$W$24 -> 0 | X8: ='Headcount'!$X$24 -> 0 | Y8: ='Headcount'!$Y$24 -> 0 | Z8: ='Headcount'!$Z$24 -> 0 | AA8: ='Headcount'!$AA$24 -> 0 | AB8: ='Headcount'!$AB$24 -> 0 | AC8: ='Headcount'!$AC$24 -> 0 | AD8: ='Headcount'!$AD$24 -> 0 | AE8: ='Headcount'!$AE$24 -> 0 | AF8: ='Headcount'!$AF$24 -> 0 | AG8: ='Headcount'!$AG$24 -> 0 | AH8: ='Headcount'!$AH$24 -> 0 | AI8: ='Headcount'!$AI$24 -> 0 | AJ8: ='Headcount'!$AJ$24 -> 0 | AK8: ='Headcount'!$AK$24 -> 0 | AL8: ='Headcount'!$AL$24 -> 0 | AN8: =SUM(C8:E8) -> 0 | AO8: =SUM(F8:H8) -> 0 | AP8: =SUM(I8:K8) -> 0 | AQ8: =SUM(L8:N8) -> 0 | AR8: =SUM(O8:Q8) -> 0 | AS8: =SUM(R8:T8) -> 0 | AT8: =SUM(U8:W8) -> 0 | AU8: =SUM(X8:Z8) -> 0 | AV8: =SUM(AA8:AC8) -> 0 | AW8: =SUM(AD8:AF8) -> 0 | AX8: =SUM(AG8:AI8) -> 0 | AY8: =SUM(AJ8:AL8) -> 0 | BA8: =SUM(C8:N8) -> 0 | BB8: =SUM(O8:Z8) -> 0 | BC8: =SUM(AA8:AL8) -> 0
A9: Paid Acquisition Spend | B9: Linked from Revenue tab: paid signups × CAC | C9: ='Revenue'!$C$9 -> 0 | D9: ='Revenue'!$D$9 -> 0 | E9: ='Revenue'!$E$9 -> 0 | F9: ='Revenue'!$F$9 -> 0 | G9: ='Revenue'!$G$9 -> 0 | H9: ='Revenue'!$H$9 -> 0 | I9: ='Revenue'!$I$9 -> 0 | J9: ='Revenue'!$J$9 -> 0 | K9: ='Revenue'!$K$9 -> 0 | L9: ='Revenue'!$L$9 -> 0 | M9: ='Revenue'!$M$9 -> 0 | N9: ='Revenue'!$N$9 -> 0 | O9: ='Revenue'!$O$9 -> 0 | P9: ='Revenue'!$P$9 -> 0 | Q9: ='Revenue'!$Q$9 -> 0 | R9: ='Revenue'!$R$9 -> 0 | S9: ='Revenue'!$S$9 -> 0 | T9: ='Revenue'!$T$9 -> 0 | U9: ='Revenue'!$U$9 -> 0 | V9: ='Revenue'!$V$9 -> 0 | W9: ='Revenue'!$W$9 -> 0 | X9: ='Revenue'!$X$9 -> 0 | Y9: ='Revenue'!$Y$9 -> 0 | Z9: ='Revenue'!$Z$9 -> 0 | AA9: ='Revenue'!$AA$9 -> 0 | AB9: ='Revenue'!$AB$9 -> 0 | AC9: ='Revenue'!$AC$9 -> 0 | AD9: ='Revenue'!$AD$9 -> 0 | AE9: ='Revenue'!$AE$9 -> 0 | AF9: ='Revenue'!$AF$9 -> 0 | AG9: ='Revenue'!$AG$9 -> 0 | AH9: ='Revenue'!$AH$9 -> 0 | AI9: ='Revenue'!$AI$9 -> 0 | AJ9: ='Revenue'!$AJ$9 -> 0 | AK9: ='Revenue'!$AK$9 -> 0 | AL9: ='Revenue'!$AL$9 -> 0 | AN9: =SUM(C9:E9) -> 0 | AO9: =SUM(F9:H9) -> 0 | AP9: =SUM(I9:K9) -> 0 | AQ9: =SUM(L9:N9) -> 0 | AR9: =SUM(O9:Q9) -> 0 | AS9: =SUM(R9:T9) -> 0 | AT9: =SUM(U9:W9) -> 0 | AU9: =SUM(X9:Z9) -> 0 | AV9: =SUM(AA9:AC9) -> 0 | AW9: =SUM(AD9:AF9) -> 0 | AX9: =SUM(AG9:AI9) -> 0 | AY9: =SUM(AJ9:AL9) -> 0 | BA9: =SUM(C9:N9) -> 0 | BB9: =SUM(O9:Z9) -> 0 | BC9: =SUM(AA9:AL9) -> 0
A10: Organic / Viral Program Spend | B10: Linked from Revenue tab: organic signups × CAC equivalent | C10: ='Revenue'!$C$11 -> 0 | D10: ='Revenue'!$D$11 -> 0 | E10: ='Revenue'!$E$11 -> 0 | F10: ='Revenue'!$F$11 -> 0 | G10: ='Revenue'!$G$11 -> 0 | H10: ='Revenue'!$H$11 -> 0 | I10: ='Revenue'!$I$11 -> 0 | J10: ='Revenue'!$J$11 -> 0 | K10: ='Revenue'!$K$11 -> 0 | L10: ='Revenue'!$L$11 -> 0 | M10: ='Revenue'!$M$11 -> 0 | N10: ='Revenue'!$N$11 -> 0 | O10: ='Revenue'!$O$11 -> 0 | P10: ='Revenue'!$P$11 -> 0 | Q10: ='Revenue'!$Q$11 -> 0 | R10: ='Revenue'!$R$11 -> 0 | S10: ='Revenue'!$S$11 -> 0 | T10: ='Revenue'!$T$11 -> 0 | U10: ='Revenue'!$U$11 -> 0 | V10: ='Revenue'!$V$11 -> 0 | W10: ='Revenue'!$W$11 -> 0 | X10: ='Revenue'!$X$11 -> 0 | Y10: ='Revenue'!$Y$11 -> 0 | Z10: ='Revenue'!$Z$11 -> 0 | AA10: ='Revenue'!$AA$11 -> 0 | AB10: ='Revenue'!$AB$11 -> 0 | AC10: ='Revenue'!$AC$11 -> 0 | AD10: ='Revenue'!$AD$11 -> 0 | AE10: ='Revenue'!$AE$11 -> 0 | AF10: ='Revenue'!$AF$11 -> 0 | AG10: ='Revenue'!$AG$11 -> 0 | AH10: ='Revenue'!$AH$11 -> 0 | AI10: ='Revenue'!$AI$11 -> 0 | AJ10: ='Revenue'!$AJ$11 -> 0 | AK10: ='Revenue'!$AK$11 -> 0 | AL10: ='Revenue'!$AL$11 -> 0 | AN10: =SUM(C10:E10) -> 0 | AO10: =SUM(F10:H10) -> 0 | AP10: =SUM(I10:K10) -> 0 | AQ10: =SUM(L10:N10) -> 0 | AR10: =SUM(O10:Q10) -> 0 | AS10: =SUM(R10:T10) -> 0 | AT10: =SUM(U10:W10) -> 0 | AU10: =SUM(X10:Z10) -> 0 | AV10: =SUM(AA10:AC10) -> 0 | AW10: =SUM(AD10:AF10) -> 0 | AX10: =SUM(AG10:AI10) -> 0 | AY10: =SUM(AJ10:AL10) -> 0 | BA10: =SUM(C10:N10) -> 0 | BB10: =SUM(O10:Z10) -> 0 | BC10: =SUM(AA10:AL10) -> 0
A11: Influencer / Referral Spend | B11: Linked from Revenue tab: referral signups × CAC | C11: ='Revenue'!$C$13 -> 0 | D11: ='Revenue'!$D$13 -> 0 | E11: ='Revenue'!$E$13 -> 0 | F11: ='Revenue'!$F$13 -> 0 | G11: ='Revenue'!$G$13 -> 0 | H11: ='Revenue'!$H$13 -> 0 | I11: ='Revenue'!$I$13 -> 0 | J11: ='Revenue'!$J$13 -> 0 | K11: ='Revenue'!$K$13 -> 0 | L11: ='Revenue'!$L$13 -> 0 | M11: ='Revenue'!$M$13 -> 0 | N11: ='Revenue'!$N$13 -> 0 | O11: ='Revenue'!$O$13 -> 0 | P11: ='Revenue'!$P$13 -> 0 | Q11: ='Revenue'!$Q$13 -> 0 | R11: ='Revenue'!$R$13 -> 0 | S11: ='Revenue'!$S$13 -> 0 | T11: ='Revenue'!$T$13 -> 0 | U11: ='Revenue'!$U$13 -> 0 | V11: ='Revenue'!$V$13 -> 0 | W11: ='Revenue'!$W$13 -> 0 | X11: ='Revenue'!$X$13 -> 0 | Y11: ='Revenue'!$Y$13 -> 0 | Z11: ='Revenue'!$Z$13 -> 0 | AA11: ='Revenue'!$AA$13 -> 0 | AB11: ='Revenue'!$AB$13 -> 0 | AC11: ='Revenue'!$AC$13 -> 0 | AD11: ='Revenue'!$AD$13 -> 0 | AE11: ='Revenue'!$AE$13 -> 0 | AF11: ='Revenue'!$AF$13 -> 0 | AG11: ='Revenue'!$AG$13 -> 0 | AH11: ='Revenue'!$AH$13 -> 0 | AI11: ='Revenue'!$AI$13 -> 0 | AJ11: ='Revenue'!$AJ$13 -> 0 | AK11: ='Revenue'!$AK$13 -> 0 | AL11: ='Revenue'!$AL$13 -> 0 | AN11: =SUM(C11:E11) -> 0 | AO11: =SUM(F11:H11) -> 0 | AP11: =SUM(I11:K11) -> 0 | AQ11: =SUM(L11:N11) -> 0 | AR11: =SUM(O11:Q11) -> 0 | AS11: =SUM(R11:T11) -> 0 | AT11: =SUM(U11:W11) -> 0 | AU11: =SUM(X11:Z11) -> 0 | AV11: =SUM(AA11:AC11) -> 0 | AW11: =SUM(AD11:AF11) -> 0 | AX11: =SUM(AG11:AI11) -> 0 | AY11: =SUM(AJ11:AL11) -> 0 | BA11: =SUM(C11:N11) -> 0 | BB11: =SUM(O11:Z11) -> 0 | BC11: =SUM(AA11:AL11) -> 0
A12: CRM / Analytics / Lifecycle Tools | B12: Fixed monthly | C12: ='Assumptions'!$F$61 -> 0 | D12: ='Assumptions'!$F$61 -> 0 | E12: ='Assumptions'!$F$61 -> 0 | F12: ='Assumptions'!$F$61 -> 0 | G12: ='Assumptions'!$F$61 -> 0 | H12: ='Assumptions'!$F$61 -> 0 | I12: ='Assumptions'!$F$61 -> 0 | J12: ='Assumptions'!$F$61 -> 0 | ... AL12: ='Assumptions'!$F$61 -> 0 | AN12: =SUM(C12:E12) -> 0 | AO12: =SUM(F12:H12) -> 0 | AP12: =SUM(I12:K12) -> 0 | AQ12: =SUM(L12:N12) -> 0 | AR12: =SUM(O12:Q12) -> 0 | AS12: =SUM(R12:T12) -> 0 | AT12: =SUM(U12:W12) -> 0 | AU12: =SUM(X12:Z12) -> 0 | AV12: =SUM(AA12:AC12) -> 0 | AW12: =SUM(AD12:AF12) -> 0 | AX12: =SUM(AG12:AI12) -> 0 | AY12: =SUM(AJ12:AL12) -> 0 | BA12: =SUM(C12:N12) -> 0 | BB12: =SUM(O12:Z12) -> 0 | BC12: =SUM(AA12:AL12) -> 0
A13: Total Growth & Marketing | C13: =C8+C9+C10+C11+C12 -> 0 | D13: =D8+D9+D10+D11+D12 -> 0 | E13: =E8+E9+E10+E11+E12 -> 0 | F13: =F8+F9+F10+F11+F12 -> 0 | G13: =G8+G9+G10+G11+G12 -> 0 | H13: =H8+H9+H10+H11+H12 -> 0 | I13: =I8+I9+I10+I11+I12 -> 0 | J13: =J8+J9+J10+J11+J12 -> 0 | ... AL13: =AL8+AL9+AL10+AL11+AL12 -> 0 | AN13: =SUM(C13:E13) -> 0 | AO13: =SUM(F13:H13) -> 0 | AP13: =SUM(I13:K13) -> 0 | AQ13: =SUM(L13:N13) -> 0 | AR13: =SUM(O13:Q13) -> 0 | AS13: =SUM(R13:T13) -> 0 | AT13: =SUM(U13:W13) -> 0 | AU13: =SUM(X13:Z13) -> 0 | AV13: =SUM(AA13:AC13) -> 0 | AW13: =SUM(AD13:AF13) -> 0 | AX13: =SUM(AG13:AI13) -> 0 | AY13: =SUM(AJ13:AL13) -> 0 | BA13: =SUM(C13:N13) -> 0 | BB13: =SUM(O13:Z13) -> 0 | BC13: =SUM(AA13:AL13) -> 0
A15: Product & Engineering
A16: Product & Engineering — people cost | B16: Linked from Headcount tab | C16: ='Headcount'!$C$25 -> 0 | D16: ='Headcount'!$D$25 -> 0 | E16: ='Headcount'!$E$25 -> 0 | F16: ='Headcount'!$F$25 -> 0 | G16: ='Headcount'!$G$25 -> 0 | H16: ='Headcount'!$H$25 -> 0 | I16: ='Headcount'!$I$25 -> 0 | J16: ='Headcount'!$J$25 -> 0 | K16: ='Headcount'!$K$25 -> 0 | L16: ='Headcount'!$L$25 -> 0 | M16: ='Headcount'!$M$25 -> 0 | N16: ='Headcount'!$N$25 -> 0 | O16: ='Headcount'!$O$25 -> 0 | P16: ='Headcount'!$P$25 -> 0 | Q16: ='Headcount'!$Q$25 -> 0 | R16: ='Headcount'!$R$25 -> 0 | S16: ='Headcount'!$S$25 -> 0 | T16: ='Headcount'!$T$25 -> 0 | U16: ='Headcount'!$U$25 -> 0 | V16: ='Headcount'!$V$25 -> 0 | W16: ='Headcount'!$W$25 -> 0 | X16: ='Headcount'!$X$25 -> 0 | Y16: ='Headcount'!$Y$25 -> 0 | Z16: ='Headcount'!$Z$25 -> 0 | AA16: ='Headcount'!$AA$25 -> 0 | AB16: ='Headcount'!$AB$25 -> 0 | AC16: ='Headcount'!$AC$25 -> 0 | AD16: ='Headcount'!$AD$25 -> 0 | AE16: ='Headcount'!$AE$25 -> 0 | AF16: ='Headcount'!$AF$25 -> 0 | AG16: ='Headcount'!$AG$25 -> 0 | AH16: ='Headcount'!$AH$25 -> 0 | AI16: ='Headcount'!$AI$25 -> 0 | AJ16: ='Headcount'!$AJ$25 -> 0 | AK16: ='Headcount'!$AK$25 -> 0 | AL16: ='Headcount'!$AL$25 -> 0 | AN16: =SUM(C16:E16) -> 0 | AO16: =SUM(F16:H16) -> 0 | AP16: =SUM(I16:K16) -> 0 | AQ16: =SUM(L16:N16) -> 0 | AR16: =SUM(O16:Q16) -> 0 | AS16: =SUM(R16:T16) -> 0 | AT16: =SUM(U16:W16) -> 0 | AU16: =SUM(X16:Z16) -> 0 | AV16: =SUM(AA16:AC16) -> 0 | AW16: =SUM(AD16:AF16) -> 0 | AX16: =SUM(AG16:AI16) -> 0 | AY16: =SUM(AJ16:AL16) -> 0 | BA16: =SUM(C16:N16) -> 0 | BB16: =SUM(O16:Z16) -> 0 | BC16: =SUM(AA16:AL16) -> 0
A17: Product Software & Tools | B17: Fixed monthly | C17: ='Assumptions'!$F$62 -> 0 | D17: ='Assumptions'!$F$62 -> 0 | E17: ='Assumptions'!$F$62 -> 0 | F17: ='Assumptions'!$F$62 -> 0 | G17: ='Assumptions'!$F$62 -> 0 | H17: ='Assumptions'!$F$62 -> 0 | I17: ='Assumptions'!$F$62 -> 0 | J17: ='Assumptions'!$F$62 -> 0 | ... AL17: ='Assumptions'!$F$62 -> 0 | AN17: =SUM(C17:E17) -> 0 | AO17: =SUM(F17:H17) -> 0 | AP17: =SUM(I17:K17) -> 0 | AQ17: =SUM(L17:N17) -> 0 | AR17: =SUM(O17:Q17) -> 0 | AS17: =SUM(R17:T17) -> 0 | AT17: =SUM(U17:W17) -> 0 | AU17: =SUM(X17:Z17) -> 0 | AV17: =SUM(AA17:AC17) -> 0 | AW17: =SUM(AD17:AF17) -> 0 | AX17: =SUM(AG17:AI17) -> 0 | AY17: =SUM(AJ17:AL17) -> 0 | BA17: =SUM(C17:N17) -> 0 | BB17: =SUM(O17:Z17) -> 0 | BC17: =SUM(AA17:AL17) -> 0
A18: Total Product & Engineering | C18: =C16+C17 -> 0 | D18: =D16+D17 -> 0 | E18: =E16+E17 -> 0 | F18: =F16+F17 -> 0 | G18: =G16+G17 -> 0 | H18: =H16+H17 -> 0 | I18: =I16+I17 -> 0 | J18: =J16+J17 -> 0 | ... AL18: =AL16+AL17 -> 0 | AN18: =SUM(C18:E18) -> 0 | AO18: =SUM(F18:H18) -> 0 | AP18: =SUM(I18:K18) -> 0 | AQ18: =SUM(L18:N18) -> 0 | AR18: =SUM(O18:Q18) -> 0 | AS18: =SUM(R18:T18) -> 0 | AT18: =SUM(U18:W18) -> 0 | AU18: =SUM(X18:Z18) -> 0 | AV18: =SUM(AA18:AC18) -> 0 | AW18: =SUM(AD18:AF18) -> 0 | AX18: =SUM(AG18:AI18) -> 0 | AY18: =SUM(AJ18:AL18) -> 0 | BA18: =SUM(C18:N18) -> 0 | BB18: =SUM(O18:Z18) -> 0 | BC18: =SUM(AA18:AL18) -> 0
A20: General & Administrative
A21: General & Administrative — people cost | B21: Linked from Headcount tab | C21: ='Headcount'!$C$23 -> 0 | D21: ='Headcount'!$D$23 -> 0 | E21: ='Headcount'!$E$23 -> 0 | F21: ='Headcount'!$F$23 -> 0 | G21: ='Headcount'!$G$23 -> 0 | H21: ='Headcount'!$H$23 -> 0 | I21: ='Headcount'!$I$23 -> 0 | J21: ='Headcount'!$J$23 -> 0 | K21: ='Headcount'!$K$23 -> 0 | L21: ='Headcount'!$L$23 -> 0 | M21: ='Headcount'!$M$23 -> 0 | N21: ='Headcount'!$N$23 -> 0 | O21: ='Headcount'!$O$23 -> 0 | P21: ='Headcount'!$P$23 -> 0 | Q21: ='Headcount'!$Q$23 -> 0 | R21: ='Headcount'!$R$23 -> 0 | S21: ='Headcount'!$S$23 -> 0 | T21: ='Headcount'!$T$23 -> 0 | U21: ='Headcount'!$U$23 -> 0 | V21: ='Headcount'!$V$23 -> 0 | W21: ='Headcount'!$W$23 -> 0 | X21: ='Headcount'!$X$23 -> 0 | Y21: ='Headcount'!$Y$23 -> 0 | Z21: ='Headcount'!$Z$23 -> 0 | AA21: ='Headcount'!$AA$23 -> 0 | AB21: ='Headcount'!$AB$23 -> 0 | AC21: ='Headcount'!$AC$23 -> 0 | AD21: ='Headcount'!$AD$23 -> 0 | AE21: ='Headcount'!$AE$23 -> 0 | AF21: ='Headcount'!$AF$23 -> 0 | AG21: ='Headcount'!$AG$23 -> 0 | AH21: ='Headcount'!$AH$23 -> 0 | AI21: ='Headcount'!$AI$23 -> 0 | AJ21: ='Headcount'!$AJ$23 -> 0 | AK21: ='Headcount'!$AK$23 -> 0 | AL21: ='Headcount'!$AL$23 -> 0 | AN21: =SUM(C21:E21) -> 0 | AO21: =SUM(F21:H21) -> 0 | AP21: =SUM(I21:K21) -> 0 | AQ21: =SUM(L21:N21) -> 0 | AR21: =SUM(O21:Q21) -> 0 | AS21: =SUM(R21:T21) -> 0 | AT21: =SUM(U21:W21) -> 0 | AU21: =SUM(X21:Z21) -> 0 | AV21: =SUM(AA21:AC21) -> 0 | AW21: =SUM(AD21:AF21) -> 0 | AX21: =SUM(AG21:AI21) -> 0 | AY21: =SUM(AJ21:AL21) -> 0 | BA21: =SUM(C21:N21) -> 0 | BB21: =SUM(O21:Z21) -> 0 | BC21: =SUM(AA21:AL21) -> 0
A22: Facilities & Admin | B22: Fixed monthly | C22: ='Assumptions'!$F$63 -> 0 | D22: ='Assumptions'!$F$63 -> 0 | E22: ='Assumptions'!$F$63 -> 0 | F22: ='Assumptions'!$F$63 -> 0 | G22: ='Assumptions'!$F$63 -> 0 | H22: ='Assumptions'!$F$63 -> 0 | I22: ='Assumptions'!$F$63 -> 0 | J22: ='Assumptions'!$F$63 -> 0 | ... AL22: ='Assumptions'!$F$63 -> 0 | AN22: =SUM(C22:E22) -> 0 | AO22: =SUM(F22:H22) -> 0 | AP22: =SUM(I22:K22) -> 0 | AQ22: =SUM(L22:N22) -> 0 | AR22: =SUM(O22:Q22) -> 0 | AS22: =SUM(R22:T22) -> 0 | AT22: =SUM(U22:W22) -> 0 | AU22: =SUM(X22:Z22) -> 0 | AV22: =SUM(AA22:AC22) -> 0 | AW22: =SUM(AD22:AF22) -> 0 | AX22: =SUM(AG22:AI22) -> 0 | AY22: =SUM(AJ22:AL22) -> 0 | BA22: =SUM(C22:N22) -> 0 | BB22: =SUM(O22:Z22) -> 0 | BC22: =SUM(AA22:AL22) -> 0
A23: Total General & Administrative | C23: =C21+C22 -> 0 | D23: =D21+D22 -> 0 | E23: =E21+E22 -> 0 | F23: =F21+F22 -> 0 | G23: =G21+G22 -> 0 | H23: =H21+H22 -> 0 | I23: =I21+I22 -> 0 | J23: =J21+J22 -> 0 | ... AL23: =AL21+AL22 -> 0 | AN23: =SUM(C23:E23) -> 0 | AO23: =SUM(F23:H23) -> 0 | AP23: =SUM(I23:K23) -> 0 | AQ23: =SUM(L23:N23) -> 0 | AR23: =SUM(O23:Q23) -> 0 | AS23: =SUM(R23:T23) -> 0 | AT23: =SUM(U23:W23) -> 0 | AU23: =SUM(X23:Z23) -> 0 | AV23: =SUM(AA23:AC23) -> 0 | AW23: =SUM(AD23:AF23) -> 0 | AX23: =SUM(AG23:AI23) -> 0 | AY23: =SUM(AJ23:AL23) -> 0 | BA23: =SUM(C23:N23) -> 0 | BB23: =SUM(O23:Z23) -> 0 | BC23: =SUM(AA23:AL23) -> 0
A25: Total Operating Expenses
A26: Total Opex | C26: =C13+C18+C23 -> 0 | D26: =D13+D18+D23 -> 0 | E26: =E13+E18+E23 -> 0 | F26: =F13+F18+F23 -> 0 | G26: =G13+G18+G23 -> 0 | H26: =H13+H18+H23 -> 0 | I26: =I13+I18+I23 -> 0 | J26: =J13+J18+J23 -> 0 | ... AL26: =AL13+AL18+AL23 -> 0 | AN26: =SUM(C26:E26) -> 0 | AO26: =SUM(F26:H26) -> 0 | AP26: =SUM(I26:K26) -> 0 | AQ26: =SUM(L26:N26) -> 0 | AR26: =SUM(O26:Q26) -> 0 | AS26: =SUM(R26:T26) -> 0 | AT26: =SUM(U26:W26) -> 0 | AU26: =SUM(X26:Z26) -> 0 | AV26: =SUM(AA26:AC26) -> 0 | AW26: =SUM(AD26:AF26) -> 0 | AX26: =SUM(AG26:AI26) -> 0 | AY26: =SUM(AJ26:AL26) -> 0 | BA26: =SUM(C26:N26) -> 0 | BB26: =SUM(O26:Z26) -> 0 | BC26: =SUM(AA26:AL26) -> 0

Sheet Working Capital
A1: Consumer Subscription — 3-Year Financial Model — Working Capital
A2: Balance-sheet drivers: receivables, payables, deferred revenue, capex/depreciation, debt & equity financing.
A5: Line item | B5: Units / source | C5: Monthly (36 months) | AN5: Quarterly | BA5: Annual
C6: 46023 | D6: 46054 | E6: 46082 | F6: 46113 | G6: 46143 | H6: 46174 | I6: 46204 | J6: 46235 | K6: 46266 | L6: 46296 | M6: 46327 | N6: 46357 | O6: 46388 | P6: 46419 | Q6: 46447 | R6: 46478 | S6: 46508 | T6: 46539 | U6: 46569 | V6: 46600 | W6: 46631 | X6: 46661 | Y6: 46692 | Z6: 46722 | AA6: 46753 | AB6: 46784 | AC6: 46813 | AD6: 46844 | AE6: 46874 | AF6: 46905 | AG6: 46935 | AH6: 46966 | AI6: 46997 | AJ6: 47027 | AK6: 47058 | AL6: 47088 | AN6: Q1 | AO6: Q2 | AP6: Q3 | AQ6: Q4 | AR6: Q5 | AS6: Q6 | AT6: Q7 | AU6: Q8 | AV6: Q9 | AW6: Q10 | AX6: Q11 | AY6: Q12 | BA6: FY1 | BB6: FY2 | BC6: FY3
A7: Receivables, Payables & Deferred Revenue
A8: Accounts Receivable balance | B8: Revenue × DSO ÷ 30 | C8: ='Revenue'!C35*'Assumptions'!$F$66/30 -> 0 | D8: ='Revenue'!D35*'Assumptions'!$F$66/30 -> 0 | E8: ='Revenue'!E35*'Assumptions'!$F$66/30 -> 0 | F8: ='Revenue'!F35*'Assumptions'!$F$66/30 -> 0 | G8: ='Revenue'!G35*'Assumptions'!$F$66/30 -> 0 | H8: ='Revenue'!H35*'Assumptions'!$F$66/30 -> 0 | I8: ='Revenue'!I35*'Assumptions'!$F$66/30 -> 0 | J8: ='Revenue'!J35*'Assumptions'!$F$66/30 -> 0 | ... AL8: ='Revenue'!AL35*'Assumptions'!$F$66/30 -> 0 | AN8: =E8 -> 0 | AO8: =H8 -> 0 | AP8: =K8 -> 0 | AQ8: =N8 -> 0 | AR8: =Q8 -> 0 | AS8: =T8 -> 0 | AT8: =W8 -> 0 | AU8: =Z8 -> 0 | AV8: =AC8 -> 0 | AW8: =AF8 -> 0 | AX8: =AI8 -> 0 | AY8: =AL8 -> 0 | BA8: =N8 -> 0 | BB8: =Z8 -> 0 | BC8: =AL8 -> 0
A9: Accounts Payable balance | B9: (COGS + Opex) × DPO ÷ 30 | C9: =('COGS & GM'!C13+'Opex'!C26)*'Assumptions'!$F$67/30 -> 0 | D9: =('COGS & GM'!D13+'Opex'!D26)*'Assumptions'!$F$67/30 -> 0 | E9: =('COGS & GM'!E13+'Opex'!E26)*'Assumptions'!$F$67/30 -> 0 | F9: =('COGS & GM'!F13+'Opex'!F26)*'Assumptions'!$F$67/30 -> 0 | G9: =('COGS & GM'!G13+'Opex'!G26)*'Assumptions'!$F$67/30 -> 0 | H9: =('COGS & GM'!H13+'Opex'!H26)*'Assumptions'!$F$67/30 -> 0 | I9: =('COGS & GM'!I13+'Opex'!I26)*'Assumptions'!$F$67/30 -> 0 | J9: =('COGS & GM'!J13+'Opex'!J26)*'Assumptions'!$F$67/30 -> 0 | ... AL9: =('COGS & GM'!AL13+'Opex'!AL26)*'Assumptions'!$F$67/30 -> 0 | AN9: =E9 -> 0 | AO9: =H9 -> 0 | AP9: =K9 -> 0 | AQ9: =N9 -> 0 | AR9: =Q9 -> 0 | AS9: =T9 -> 0 | AT9: =W9 -> 0 | AU9: =Z9 -> 0 | AV9: =AC9 -> 0 | AW9: =AF9 -> 0 | AX9: =AI9 -> 0 | AY9: =AL9 -> 0 | BA9: =N9 -> 0 | BB9: =Z9 -> 0 | BC9: =AL9 -> 0
A10: Deferred Revenue balance | B10: Revenue × months collected in advance | C10: ='Revenue'!C35*'Assumptions'!$F$68 -> 0 | D10: ='Revenue'!D35*'Assumptions'!$F$68 -> 0 | E10: ='Revenue'!E35*'Assumptions'!$F$68 -> 0 | F10: ='Revenue'!F35*'Assumptions'!$F$68 -> 0 | G10: ='Revenue'!G35*'Assumptions'!$F$68 -> 0 | H10: ='Revenue'!H35*'Assumptions'!$F$68 -> 0 | I10: ='Revenue'!I35*'Assumptions'!$F$68 -> 0 | J10: ='Revenue'!J35*'Assumptions'!$F$68 -> 0 | ... AL10: ='Revenue'!AL35*'Assumptions'!$F$68 -> 0 | AN10: =E10 -> 0 | AO10: =H10 -> 0 | AP10: =K10 -> 0 | AQ10: =N10 -> 0 | AR10: =Q10 -> 0 | AS10: =T10 -> 0 | AT10: =W10 -> 0 | AU10: =Z10 -> 0 | AV10: =AC10 -> 0 | AW10: =AF10 -> 0 | AX10: =AI10 -> 0 | AY10: =AL10 -> 0 | BA10: =N10 -> 0 | BB10: =Z10 -> 0 | BC10: =AL10 -> 0
A11: Other Current Assets balance | B11: Revenue × assumption % (prepaid expenses, etc.) | C11: ='Revenue'!C35*'Assumptions'!$F$71 -> 0 | D11: ='Revenue'!D35*'Assumptions'!$F$71 -> 0 | E11: ='Revenue'!E35*'Assumptions'!$F$71 -> 0 | F11: ='Revenue'!F35*'Assumptions'!$F$71 -> 0 | G11: ='Revenue'!G35*'Assumptions'!$F$71 -> 0 | H11: ='Revenue'!H35*'Assumptions'!$F$71 -> 0 | I11: ='Revenue'!I35*'Assumptions'!$F$71 -> 0 | J11: ='Revenue'!J35*'Assumptions'!$F$71 -> 0 | ... AL11: ='Revenue'!AL35*'Assumptions'!$F$71 -> 0 | AN11: =E11 -> 0 | AO11: =H11 -> 0 | AP11: =K11 -> 0 | AQ11: =N11 -> 0 | AR11: =Q11 -> 0 | AS11: =T11 -> 0 | AT11: =W11 -> 0 | AU11: =Z11 -> 0 | AV11: =AC11 -> 0 | AW11: =AF11 -> 0 | AX11: =AI11 -> 0 | AY11: =AL11 -> 0 | BA11: =N11 -> 0 | BB11: =Z11 -> 0 | BC11: =AL11 -> 0
A12: Change in Accounts Receivable | C12: =C8 -> 0 | D12: =D8-C8 -> 0 | E12: =E8-D8 -> 0 | F12: =F8-E8 -> 0 | G12: =G8-F8 -> 0 | H12: =H8-G8 -> 0 | I12: =I8-H8 -> 0 | J12: =J8-I8 -> 0 | K12: =K8-J8 -> 0 | ... AL12: =AL8-AK8 -> 0 | AN12: =SUM(C12:E12) -> 0 | AO12: =SUM(F12:H12) -> 0 | AP12: =SUM(I12:K12) -> 0 | AQ12: =SUM(L12:N12) -> 0 | AR12: =SUM(O12:Q12) -> 0 | AS12: =SUM(R12:T12) -> 0 | AT12: =SUM(U12:W12) -> 0 | AU12: =SUM(X12:Z12) -> 0 | AV12: =SUM(AA12:AC12) -> 0 | AW12: =SUM(AD12:AF12) -> 0 | AX12: =SUM(AG12:AI12) -> 0 | AY12: =SUM(AJ12:AL12) -> 0 | BA12: =SUM(C12:N12) -> 0 | BB12: =SUM(O12:Z12) -> 0 | BC12: =SUM(AA12:AL12) -> 0
A13: Change in Accounts Payable | C13: =C9 -> 0 | D13: =D9-C9 -> 0 | E13: =E9-D9 -> 0 | F13: =F9-E9 -> 0 | G13: =G9-F9 -> 0 | H13: =H9-G9 -> 0 | I13: =I9-H9 -> 0 | J13: =J9-I9 -> 0 | K13: =K9-J9 -> 0 | ... AL13: =AL9-AK9 -> 0 | AN13: =SUM(C13:E13) -> 0 | AO13: =SUM(F13:H13) -> 0 | AP13: =SUM(I13:K13) -> 0 | AQ13: =SUM(L13:N13) -> 0 | AR13: =SUM(O13:Q13) -> 0 | AS13: =SUM(R13:T13) -> 0 | AT13: =SUM(U13:W13) -> 0 | AU13: =SUM(X13:Z13) -> 0 | AV13: =SUM(AA13:AC13) -> 0 | AW13: =SUM(AD13:AF13) -> 0 | AX13: =SUM(AG13:AI13) -> 0 | AY13: =SUM(AJ13:AL13) -> 0 | BA13: =SUM(C13:N13) -> 0 | BB13: =SUM(O13:Z13) -> 0 | BC13: =SUM(AA13:AL13) -> 0
A14: Change in Deferred Revenue | C14: =C10 -> 0 | D14: =D10-C10 -> 0 | E14: =E10-D10 -> 0 | F14: =F10-E10 -> 0 | G14: =G10-F10 -> 0 | H14: =H10-G10 -> 0 | I14: =I10-H10 -> 0 | J14: =J10-I10 -> 0 | K14: =K10-J10 -> 0 | ... AL14: =AL10-AK10 -> 0 | AN14: =SUM(C14:E14) -> 0 | AO14: =SUM(F14:H14) -> 0 | AP14: =SUM(I14:K14) -> 0 | AQ14: =SUM(L14:N14) -> 0 | AR14: =SUM(O14:Q14) -> 0 | AS14: =SUM(R14:T14) -> 0 | AT14: =SUM(U14:W14) -> 0 | AU14: =SUM(X14:Z14) -> 0 | AV14: =SUM(AA14:AC14) -> 0 | AW14: =SUM(AD14:AF14) -> 0 | AX14: =SUM(AG14:AI14) -> 0 | AY14: =SUM(AJ14:AL14) -> 0 | BA14: =SUM(C14:N14) -> 0 | BB14: =SUM(O14:Z14) -> 0 | BC14: =SUM(AA14:AL14) -> 0
A15: Change in Other Current Assets | C15: =C11 -> 0 | D15: =D11-C11 -> 0 | E15: =E11-D11 -> 0 | F15: =F11-E11 -> 0 | G15: =G11-F11 -> 0 | H15: =H11-G11 -> 0 | I15: =I11-H11 -> 0 | J15: =J11-I11 -> 0 | K15: =K11-J11 -> 0 | ... AL15: =AL11-AK11 -> 0 | AN15: =SUM(C15:E15) -> 0 | AO15: =SUM(F15:H15) -> 0 | AP15: =SUM(I15:K15) -> 0 | AQ15: =SUM(L15:N15) -> 0 | AR15: =SUM(O15:Q15) -> 0 | AS15: =SUM(R15:T15) -> 0 | AT15: =SUM(U15:W15) -> 0 | AU15: =SUM(X15:Z15) -> 0 | AV15: =SUM(AA15:AC15) -> 0 | AW15: =SUM(AD15:AF15) -> 0 | AX15: =SUM(AG15:AI15) -> 0 | AY15: =SUM(AJ15:AL15) -> 0 | BA15: =SUM(C15:N15) -> 0 | BB15: =SUM(O15:Z15) -> 0 | BC15: =SUM(AA15:AL15) -> 0
A17: Capex & Depreciation (PP&E)
A18: Capital expenditures | B18: Revenue × capex % of revenue | C18: ='Revenue'!C35*'Assumptions'!$F$69 -> 0 | D18: ='Revenue'!D35*'Assumptions'!$F$69 -> 0 | E18: ='Revenue'!E35*'Assumptions'!$F$69 -> 0 | F18: ='Revenue'!F35*'Assumptions'!$F$69 -> 0 | G18: ='Revenue'!G35*'Assumptions'!$F$69 -> 0 | H18: ='Revenue'!H35*'Assumptions'!$F$69 -> 0 | I18: ='Revenue'!I35*'Assumptions'!$F$69 -> 0 | J18: ='Revenue'!J35*'Assumptions'!$F$69 -> 0 | ... AL18: ='Revenue'!AL35*'Assumptions'!$F$69 -> 0 | AN18: =SUM(C18:E18) -> 0 | AO18: =SUM(F18:H18) -> 0 | AP18: =SUM(I18:K18) -> 0 | AQ18: =SUM(L18:N18) -> 0 | AR18: =SUM(O18:Q18) -> 0 | AS18: =SUM(R18:T18) -> 0 | AT18: =SUM(U18:W18) -> 0 | AU18: =SUM(X18:Z18) -> 0 | AV18: =SUM(AA18:AC18) -> 0 | AW18: =SUM(AD18:AF18) -> 0 | AX18: =SUM(AG18:AI18) -> 0 | AY18: =SUM(AJ18:AL18) -> 0 | BA18: =SUM(C18:N18) -> 0 | BB18: =SUM(O18:Z18) -> 0 | BC18: =SUM(AA18:AL18) -> 0
A19: Depreciation & amortization | B19: Straight-line over useful life; trailing-window formula | C19: =SUM(INDEX('Working Capital'!$C$18:$AL$18,1,MAX(1,1-ROUND('Assumptions'!$F$70,0)+1)):INDEX('Working Capital'!$C$18:$AL$18,1,1))/ROUND('Assumptions'!$F$70,0) -> 0 | D19: =SUM(INDEX('Working Capital'!$C$18:$AL$18,1,MAX(1,2-ROUND('Assumptions'!$F$70,0)+1)):INDEX('Working Capital'!$C$18:$AL$18,1,2))/ROUND('Assumptions'!$F$70,0) -> 0 | E19: =SUM(INDEX('Working Capital'!$C$18:$AL$18,1,MAX(1,3-ROUND('Assumptions'!$F$70,0)+1)):INDEX('Working Capital'!$C$18:$AL$18,1,3))/ROUND('Assumptions'!$F$70,0) -> 0 | F19: =SUM(INDEX('Working Capital'!$C$18:$AL$18,1,MAX(1,4-ROUND('Assumptions'!$F$70,0)+1)):INDEX('Working Capital'!$C$18:$AL$18,1,4))/ROUND('Assumptions'!$F$70,0) -> 0 | G19: =SUM(INDEX('Working Capital'!$C$18:$AL$18,1,MAX(1,5-ROUND('Assumptions'!$F$70,0)+1)):INDEX('Working Capital'!$C$18:$AL$18,1,5))/ROUND('Assumptions'!$F$70,0) -> 0 | H19: =SUM(INDEX('Working Capital'!$C$18:$AL$18,1,MAX(1,6-ROUND('Assumptions'!$F$70,0)+1)):INDEX('Working Capital'!$C$18:$AL$18,1,6))/ROUND('Assumptions'!$F$70,0) -> 0 | I19: =SUM(INDEX('Working Capital'!$C$18:$AL$18,1,MAX(1,7-ROUND('Assumptions'!$F$70,0)+1)):INDEX('Working Capital'!$C$18:$AL$18,1,7))/ROUND('Assumptions'!$F$70,0) -> 0 | J19: =SUM(INDEX('Working Capital'!$C$18:$AL$18,1,MAX(1,8-ROUND('Assumptions'!$F$70,0)+1)):INDEX('Working Capital'!$C$18:$AL$18,1,8))/ROUND('Assumptions'!$F$70,0) -> 0 | K19: =SUM(INDEX('Working Capital'!$C$18:$AL$18,1,MAX(1,9-ROUND('Assumptions'!$F$70,0)+1)):INDEX('Working Capital'!$C$18:$AL$18,1,9))/ROUND('Assumptions'!$F$70,0) -> 0 | L19: =SUM(INDEX('Working Capital'!$C$18:$AL$18,1,MAX(1,10-ROUND('Assumptions'!$F$70,0)+1)):INDEX('Working Capital'!$C$18:$AL$18,1,10))/ROUND('Assumptions'!$F$70,0) -> 0 | M19: =SUM(INDEX('Working Capital'!$C$18:$AL$18,1,MAX(1,11-ROUND('Assumptions'!$F$70,0)+1)):INDEX('Working Capital'!$C$18:$AL$18,1,11))/ROUND('Assumptions'!$F$70,0) -> 0 | N19: =SUM(INDEX('Working Capital'!$C$18:$AL$18,1,MAX(1,12-ROUND('Assumptions'!$F$70,0)+1)):INDEX('Working Capital'!$C$18:$AL$18,1,12))/ROUND('Assumptions'!$F$70,0) -> 0 | O19: =SUM(INDEX('Working Capital'!$C$18:$AL$18,1,MAX(1,13-ROUND('Assumptions'!$F$70,0)+1)):INDEX('Working Capital'!$C$18:$AL$18,1,13))/ROUND('Assumptions'!$F$70,0) -> 0 | P19: =SUM(INDEX('Working Capital'!$C$18:$AL$18,1,MAX(1,14-ROUND('Assumptions'!$F$70,0)+1)):INDEX('Working Capital'!$C$18:$AL$18,1,14))/ROUND('Assumptions'!$F$70,0) -> 0 | Q19: =SUM(INDEX('Working Capital'!$C$18:$AL$18,1,MAX(1,15-ROUND('Assumptions'!$F$70,0)+1)):INDEX('Working Capital'!$C$18:$AL$18,1,15))/ROUND('Assumptions'!$F$70,0) -> 0 | R19: =SUM(INDEX('Working Capital'!$C$18:$AL$18,1,MAX(1,16-ROUND('Assumptions'!$F$70,0)+1)):INDEX('Working Capital'!$C$18:$AL$18,1,16))/ROUND('Assumptions'!$F$70,0) -> 0 | S19: =SUM(INDEX('Working Capital'!$C$18:$AL$18,1,MAX(1,17-ROUND('Assumptions'!$F$70,0)+1)):INDEX('Working Capital'!$C$18:$AL$18,1,17))/ROUND('Assumptions'!$F$70,0) -> 0 | T19: =SUM(INDEX('Working Capital'!$C$18:$AL$18,1,MAX(1,18-ROUND('Assumptions'!$F$70,0)+1)):INDEX('Working Capital'!$C$18:$AL$18,1,18))/ROUND('Assumptions'!$F$70,0) -> 0 | U19: =SUM(INDEX('Working Capital'!$C$18:$AL$18,1,MAX(1,19-ROUND('Assumptions'!$F$70,0)+1)):INDEX('Working Capital'!$C$18:$AL$18,1,19))/ROUND('Assumptions'!$F$70,0) -> 0 | V19: =SUM(INDEX('Working Capital'!$C$18:$AL$18,1,MAX(1,20-ROUND('Assumptions'!$F$70,0)+1)):INDEX('Working Capital'!$C$18:$AL$18,1,20))/ROUND('Assumptions'!$F$70,0) -> 0 | W19: =SUM(INDEX('Working Capital'!$C$18:$AL$18,1,MAX(1,21-ROUND('Assumptions'!$F$70,0)+1)):INDEX('Working Capital'!$C$18:$AL$18,1,21))/ROUND('Assumptions'!$F$70,0) -> 0 | X19: =SUM(INDEX('Working Capital'!$C$18:$AL$18,1,MAX(1,22-ROUND('Assumptions'!$F$70,0)+1)):INDEX('Working Capital'!$C$18:$AL$18,1,22))/ROUND('Assumptions'!$F$70,0) -> 0 | Y19: =SUM(INDEX('Working Capital'!$C$18:$AL$18,1,MAX(1,23-ROUND('Assumptions'!$F$70,0)+1)):INDEX('Working Capital'!$C$18:$AL$18,1,23))/ROUND('Assumptions'!$F$70,0) -> 0 | Z19: =SUM(INDEX('Working Capital'!$C$18:$AL$18,1,MAX(1,24-ROUND('Assumptions'!$F$70,0)+1)):INDEX('Working Capital'!$C$18:$AL$18,1,24))/ROUND('Assumptions'!$F$70,0) -> 0 | AA19: =SUM(INDEX('Working Capital'!$C$18:$AL$18,1,MAX(1,25-ROUND('Assumptions'!$F$70,0)+1)):INDEX('Working Capital'!$C$18:$AL$18,1,25))/ROUND('Assumptions'!$F$70,0) -> 0 | AB19: =SUM(INDEX('Working Capital'!$C$18:$AL$18,1,MAX(1,26-ROUND('Assumptions'!$F$70,0)+1)):INDEX('Working Capital'!$C$18:$AL$18,1,26))/ROUND('Assumptions'!$F$70,0) -> 0 | AC19: =SUM(INDEX('Working Capital'!$C$18:$AL$18,1,MAX(1,27-ROUND('Assumptions'!$F$70,0)+1)):INDEX('Working Capital'!$C$18:$AL$18,1,27))/ROUND('Assumptions'!$F$70,0) -> 0 | AD19: =SUM(INDEX('Working Capital'!$C$18:$AL$18,1,MAX(1,28-ROUND('Assumptions'!$F$70,0)+1)):INDEX('Working Capital'!$C$18:$AL$18,1,28))/ROUND('Assumptions'!$F$70,0) -> 0 | AE19: =SUM(INDEX('Working Capital'!$C$18:$AL$18,1,MAX(1,29-ROUND('Assumptions'!$F$70,0)+1)):INDEX('Working Capital'!$C$18:$AL$18,1,29))/ROUND('Assumptions'!$F$70,0) -> 0 | AF19: =SUM(INDEX('Working Capital'!$C$18:$AL$18,1,MAX(1,30-ROUND('Assumptions'!$F$70,0)+1)):INDEX('Working Capital'!$C$18:$AL$18,1,30))/ROUND('Assumptions'!$F$70,0) -> 0 | AG19: =SUM(INDEX('Working Capital'!$C$18:$AL$18,1,MAX(1,31-ROUND('Assumptions'!$F$70,0)+1)):INDEX('Working Capital'!$C$18:$AL$18,1,31))/ROUND('Assumptions'!$F$70,0) -> 0 | AH19: =SUM(INDEX('Working Capital'!$C$18:$AL$18,1,MAX(1,32-ROUND('Assumptions'!$F$70,0)+1)):INDEX('Working Capital'!$C$18:$AL$18,1,32))/ROUND('Assumptions'!$F$70,0) -> 0 | AI19: =SUM(INDEX('Working Capital'!$C$18:$AL$18,1,MAX(1,33-ROUND('Assumptions'!$F$70,0)+1)):INDEX('Working Capital'!$C$18:$AL$18,1,33))/ROUND('Assumptions'!$F$70,0) -> 0 | AJ19: =SUM(INDEX('Working Capital'!$C$18:$AL$18,1,MAX(1,34-ROUND('Assumptions'!$F$70,0)+1)):INDEX('Working Capital'!$C$18:$AL$18,1,34))/ROUND('Assumptions'!$F$70,0) -> 0 | AK19: =SUM(INDEX('Working Capital'!$C$18:$AL$18,1,MAX(1,35-ROUND('Assumptions'!$F$70,0)+1)):INDEX('Working Capital'!$C$18:$AL$18,1,35))/ROUND('Assumptions'!$F$70,0) -> 0 | AL19: =SUM(INDEX('Working Capital'!$C$18:$AL$18,1,MAX(1,36-ROUND('Assumptions'!$F$70,0)+1)):INDEX('Working Capital'!$C$18:$AL$18,1,36))/ROUND('Assumptions'!$F$70,0) -> 0 | AN19: =SUM(C19:E19) -> 0 | AO19: =SUM(F19:H19) -> 0 | AP19: =SUM(I19:K19) -> 0 | AQ19: =SUM(L19:N19) -> 0 | AR19: =SUM(O19:Q19) -> 0 | AS19: =SUM(R19:T19) -> 0 | AT19: =SUM(U19:W19) -> 0 | AU19: =SUM(X19:Z19) -> 0 | AV19: =SUM(AA19:AC19) -> 0 | AW19: =SUM(AD19:AF19) -> 0 | AX19: =SUM(AG19:AI19) -> 0 | AY19: =SUM(AJ19:AL19) -> 0 | BA19: =SUM(C19:N19) -> 0 | BB19: =SUM(O19:Z19) -> 0 | BC19: =SUM(AA19:AL19) -> 0
A20: Net PP&E balance | C20: =C18-C19 -> 0 | D20: =C20+D18-D19 -> 0 | E20: =D20+E18-E19 -> 0 | F20: =E20+F18-F19 -> 0 | G20: =F20+G18-G19 -> 0 | H20: =G20+H18-H19 -> 0 | I20: =H20+I18-I19 -> 0 | J20: =I20+J18-J19 -> 0 | K20: =J20+K18-K19 -> 0 | ... AL20: =AK20+AL18-AL19 -> 0 | AN20: =E20 -> 0 | AO20: =H20 -> 0 | AP20: =K20 -> 0 | AQ20: =N20 -> 0 | AR20: =Q20 -> 0 | AS20: =T20 -> 0 | AT20: =W20 -> 0 | AU20: =Z20 -> 0 | AV20: =AC20 -> 0 | AW20: =AF20 -> 0 | AX20: =AI20 -> 0 | AY20: =AL20 -> 0 | BA20: =N20 -> 0 | BB20: =Z20 -> 0 | BC20: =AL20 -> 0
A22: Debt Schedule
A23: Debt draw | B23: One-time draw in month 10 | C23: =0 -> 0 | D23: =0 -> 0 | E23: =0 -> 0 | F23: =0 -> 0 | G23: =0 -> 0 | H23: =0 -> 0 | I23: =0 -> 0 | J23: =0 -> 0 | K23: =0 -> 0 | L23: ='Assumptions'!$F$73 -> 0 | M23: =0 -> 0 | N23: =0 -> 0 | O23: =0 -> 0 | P23: =0 -> 0 | Q23: =0 -> 0 | R23: =0 -> 0 | S23: =0 -> 0 | T23: =0 -> 0 | ... AL23: =0 -> 0 | AN23: =SUM(C23:E23) -> 0 | AO23: =SUM(F23:H23) -> 0 | AP23: =SUM(I23:K23) -> 0 | AQ23: =SUM(L23:N23) -> 0 | AR23: =SUM(O23:Q23) -> 0 | AS23: =SUM(R23:T23) -> 0 | AT23: =SUM(U23:W23) -> 0 | AU23: =SUM(X23:Z23) -> 0 | AV23: =SUM(AA23:AC23) -> 0 | AW23: =SUM(AD23:AF23) -> 0 | AX23: =SUM(AG23:AI23) -> 0 | AY23: =SUM(AJ23:AL23) -> 0 | BA23: =SUM(C23:N23) -> 0 | BB23: =SUM(O23:Z23) -> 0 | BC23: =SUM(AA23:AL23) -> 0
A24: Debt repayment | B24: Fixed $/month once balance exists, starting the assumed month | C24: =0 -> 0 | D24: =0 -> 0 | E24: =0 -> 0 | F24: =0 -> 0 | G24: =0 -> 0 | H24: =0 -> 0 | I24: =0 -> 0 | J24: =0 -> 0 | ... T24: =0 -> 0 | U24: =MIN(T25,'Assumptions'!$F$74) -> 0 | V24: =MIN(U25,'Assumptions'!$F$74) -> 0 | W24: =MIN(V25,'Assumptions'!$F$74) -> 0 | X24: =MIN(W25,'Assumptions'!$F$74) -> 0 | Y24: =MIN(X25,'Assumptions'!$F$74) -> 0 | Z24: =MIN(Y25,'Assumptions'!$F$74) -> 0 | AA24: =MIN(Z25,'Assumptions'!$F$74) -> 0 | AB24: =MIN(AA25,'Assumptions'!$F$74) -> 0 | ... AL24: =MIN(AK25,'Assumptions'!$F$74) -> 0 | AN24: =SUM(C24:E24) -> 0 | AO24: =SUM(F24:H24) -> 0 | AP24: =SUM(I24:K24) -> 0 | AQ24: =SUM(L24:N24) -> 0 | AR24: =SUM(O24:Q24) -> 0 | AS24: =SUM(R24:T24) -> 0 | AT24: =SUM(U24:W24) -> 0 | AU24: =SUM(X24:Z24) -> 0 | AV24: =SUM(AA24:AC24) -> 0 | AW24: =SUM(AD24:AF24) -> 0 | AX24: =SUM(AG24:AI24) -> 0 | AY24: =SUM(AJ24:AL24) -> 0 | BA24: =SUM(C24:N24) -> 0 | BB24: =SUM(O24:Z24) -> 0 | BC24: =SUM(AA24:AL24) -> 0
A25: Debt balance (ending) | B25: Prior balance + draw − repayment | C25: =C23-C24 -> 0 | D25: =C25+D23-D24 -> 0 | E25: =D25+E23-E24 -> 0 | F25: =E25+F23-F24 -> 0 | G25: =F25+G23-G24 -> 0 | H25: =G25+H23-H24 -> 0 | I25: =H25+I23-I24 -> 0 | J25: =I25+J23-J24 -> 0 | K25: =J25+K23-K24 -> 0 | ... AL25: =AK25+AL23-AL24 -> 0 | AN25: =E25 -> 0 | AO25: =H25 -> 0 | AP25: =K25 -> 0 | AQ25: =N25 -> 0 | AR25: =Q25 -> 0 | AS25: =T25 -> 0 | AT25: =W25 -> 0 | AU25: =Z25 -> 0 | AV25: =AC25 -> 0 | AW25: =AF25 -> 0 | AX25: =AI25 -> 0 | AY25: =AL25 -> 0 | BA25: =N25 -> 0 | BB25: =Z25 -> 0 | BC25: =AL25 -> 0
A26: Interest expense | B26: Prior month balance × annual rate ÷ 12 | C26: =C23*'Assumptions'!$F$72/12/2 -> 0 | D26: =C25*'Assumptions'!$F$72/12 -> 0 | E26: =D25*'Assumptions'!$F$72/12 -> 0 | F26: =E25*'Assumptions'!$F$72/12 -> 0 | G26: =F25*'Assumptions'!$F$72/12 -> 0 | H26: =G25*'Assumptions'!$F$72/12 -> 0 | I26: =H25*'Assumptions'!$F$72/12 -> 0 | J26: =I25*'Assumptions'!$F$72/12 -> 0 | K26: =J25*'Assumptions'!$F$72/12 -> 0 | ... AL26: =AK25*'Assumptions'!$F$72/12 -> 0 | AN26: =SUM(C26:E26) -> 0 | AO26: =SUM(F26:H26) -> 0 | AP26: =SUM(I26:K26) -> 0 | AQ26: =SUM(L26:N26) -> 0 | AR26: =SUM(O26:Q26) -> 0 | AS26: =SUM(R26:T26) -> 0 | AT26: =SUM(U26:W26) -> 0 | AU26: =SUM(X26:Z26) -> 0 | AV26: =SUM(AA26:AC26) -> 0 | AW26: =SUM(AD26:AF26) -> 0 | AX26: =SUM(AG26:AI26) -> 0 | AY26: =SUM(AJ26:AL26) -> 0 | BA26: =SUM(C26:N26) -> 0 | BB26: =SUM(O26:Z26) -> 0 | BC26: =SUM(AA26:AL26) -> 0
A28: Equity Financing
A29: Equity raised | B29: Growth Equity in month 6; Follow-on Equity in month 22 | C29: =0 -> 0 | D29: =0 -> 0 | E29: =0 -> 0 | F29: =0 -> 0 | G29: =0 -> 0 | H29: ='Assumptions'!$F$75 -> 0 | I29: =0 -> 0 | J29: =0 -> 0 | K29: =0 -> 0 | L29: =0 -> 0 | M29: =0 -> 0 | N29: =0 -> 0 | O29: =0 -> 0 | P29: =0 -> 0 | ... W29: =0 -> 0 | X29: ='Assumptions'!$F$76 -> 0 | Y29: =0 -> 0 | Z29: =0 -> 0 | AA29: =0 -> 0 | AB29: =0 -> 0 | AC29: =0 -> 0 | AD29: =0 -> 0 | AE29: =0 -> 0 | AF29: =0 -> 0 | ... AL29: =0 -> 0 | AN29: =SUM(C29:E29) -> 0 | AO29: =SUM(F29:H29) -> 0 | AP29: =SUM(I29:K29) -> 0 | AQ29: =SUM(L29:N29) -> 0 | AR29: =SUM(O29:Q29) -> 0 | AS29: =SUM(R29:T29) -> 0 | AT29: =SUM(U29:W29) -> 0 | AU29: =SUM(X29:Z29) -> 0 | AV29: =SUM(AA29:AC29) -> 0 | AW29: =SUM(AD29:AF29) -> 0 | AX29: =SUM(AG29:AI29) -> 0 | AY29: =SUM(AJ29:AL29) -> 0 | BA29: =SUM(C29:N29) -> 0 | BB29: =SUM(O29:Z29) -> 0 | BC29: =SUM(AA29:AL29) -> 0
A30: Cumulative paid-in capital | C30: =C29 -> 0 | D30: =C30+D29 -> 0 | E30: =D30+E29 -> 0 | F30: =E30+F29 -> 0 | G30: =F30+G29 -> 0 | H30: =G30+H29 -> 0 | I30: =H30+I29 -> 0 | J30: =I30+J29 -> 0 | K30: =J30+K29 -> 0 | ... AL30: =AK30+AL29 -> 0 | AN30: =E30 -> 0 | AO30: =H30 -> 0 | AP30: =K30 -> 0 | AQ30: =N30 -> 0 | AR30: =Q30 -> 0 | AS30: =T30 -> 0 | AT30: =W30 -> 0 | AU30: =Z30 -> 0 | AV30: =AC30 -> 0 | AW30: =AF30 -> 0 | AX30: =AI30 -> 0 | AY30: =AL30 -> 0 | BA30: =N30 -> 0 | BB30: =Z30 -> 0 | BC30: =AL30 -> 0

Sheet P&L
A1: Consumer Subscription — 3-Year Financial Model — P&L
A2: Integrated income statement — every line links to Revenue, COGS & GM, Opex, or Working Capital.
A5: Line item | B5: Units / source | C5: Monthly (36 months) | AN5: Quarterly | BA5: Annual
C6: 46023 | D6: 46054 | E6: 46082 | F6: 46113 | G6: 46143 | H6: 46174 | I6: 46204 | J6: 46235 | K6: 46266 | L6: 46296 | M6: 46327 | N6: 46357 | O6: 46388 | P6: 46419 | Q6: 46447 | R6: 46478 | S6: 46508 | T6: 46539 | U6: 46569 | V6: 46600 | W6: 46631 | X6: 46661 | Y6: 46692 | Z6: 46722 | AA6: 46753 | AB6: 46784 | AC6: 46813 | AD6: 46844 | AE6: 46874 | AF6: 46905 | AG6: 46935 | AH6: 46966 | AI6: 46997 | AJ6: 47027 | AK6: 47058 | AL6: 47088 | AN6: Q1 | AO6: Q2 | AP6: Q3 | AQ6: Q4 | AR6: Q5 | AS6: Q6 | AT6: Q7 | AU6: Q8 | AV6: Q9 | AW6: Q10 | AX6: Q11 | AY6: Q12 | BA6: FY1 | BB6: FY2 | BC6: FY3
A7: Revenue | C7: ='Revenue'!$C$35 -> 0 | D7: ='Revenue'!$D$35 -> 0 | E7: ='Revenue'!$E$35 -> 0 | F7: ='Revenue'!$F$35 -> 0 | G7: ='Revenue'!$G$35 -> 0 | H7: ='Revenue'!$H$35 -> 0 | I7: ='Revenue'!$I$35 -> 0 | J7: ='Revenue'!$J$35 -> 0 | K7: ='Revenue'!$K$35 -> 0 | L7: ='Revenue'!$L$35 -> 0 | M7: ='Revenue'!$M$35 -> 0 | N7: ='Revenue'!$N$35 -> 0 | O7: ='Revenue'!$O$35 -> 0 | P7: ='Revenue'!$P$35 -> 0 | Q7: ='Revenue'!$Q$35 -> 0 | R7: ='Revenue'!$R$35 -> 0 | S7: ='Revenue'!$S$35 -> 0 | T7: ='Revenue'!$T$35 -> 0 | U7: ='Revenue'!$U$35 -> 0 | V7: ='Revenue'!$V$35 -> 0 | W7: ='Revenue'!$W$35 -> 0 | X7: ='Revenue'!$X$35 -> 0 | Y7: ='Revenue'!$Y$35 -> 0 | Z7: ='Revenue'!$Z$35 -> 0 | AA7: ='Revenue'!$AA$35 -> 0 | AB7: ='Revenue'!$AB$35 -> 0 | AC7: ='Revenue'!$AC$35 -> 0 | AD7: ='Revenue'!$AD$35 -> 0 | AE7: ='Revenue'!$AE$35 -> 0 | AF7: ='Revenue'!$AF$35 -> 0 | AG7: ='Revenue'!$AG$35 -> 0 | AH7: ='Revenue'!$AH$35 -> 0 | AI7: ='Revenue'!$AI$35 -> 0 | AJ7: ='Revenue'!$AJ$35 -> 0 | AK7: ='Revenue'!$AK$35 -> 0 | AL7: ='Revenue'!$AL$35 -> 0 | AN7: =SUM(C7:E7) -> 0 | AO7: =SUM(F7:H7) -> 0 | AP7: =SUM(I7:K7) -> 0 | AQ7: =SUM(L7:N7) -> 0 | AR7: =SUM(O7:Q7) -> 0 | AS7: =SUM(R7:T7) -> 0 | AT7: =SUM(U7:W7) -> 0 | AU7: =SUM(X7:Z7) -> 0 | AV7: =SUM(AA7:AC7) -> 0 | AW7: =SUM(AD7:AF7) -> 0 | AX7: =SUM(AG7:AI7) -> 0 | AY7: =SUM(AJ7:AL7) -> 0 | BA7: =SUM(C7:N7) -> 0 | BB7: =SUM(O7:Z7) -> 0 | BC7: =SUM(AA7:AL7) -> 0
A8: Cost of Goods Sold | C8: ='COGS & GM'!$C$13 -> 0 | D8: ='COGS & GM'!$D$13 -> 0 | E8: ='COGS & GM'!$E$13 -> 0 | F8: ='COGS & GM'!$F$13 -> 0 | G8: ='COGS & GM'!$G$13 -> 0 | H8: ='COGS & GM'!$H$13 -> 0 | I8: ='COGS & GM'!$I$13 -> 0 | J8: ='COGS & GM'!$J$13 -> 0 | K8: ='COGS & GM'!$K$13 -> 0 | L8: ='COGS & GM'!$L$13 -> 0 | M8: ='COGS & GM'!$M$13 -> 0 | N8: ='COGS & GM'!$N$13 -> 0 | O8: ='COGS & GM'!$O$13 -> 0 | P8: ='COGS & GM'!$P$13 -> 0 | Q8: ='COGS & GM'!$Q$13 -> 0 | R8: ='COGS & GM'!$R$13 -> 0 | S8: ='COGS & GM'!$S$13 -> 0 | T8: ='COGS & GM'!$T$13 -> 0 | U8: ='COGS & GM'!$U$13 -> 0 | V8: ='COGS & GM'!$V$13 -> 0 | W8: ='COGS & GM'!$W$13 -> 0 | X8: ='COGS & GM'!$X$13 -> 0 | Y8: ='COGS & GM'!$Y$13 -> 0 | Z8: ='COGS & GM'!$Z$13 -> 0 | AA8: ='COGS & GM'!$AA$13 -> 0 | AB8: ='COGS & GM'!$AB$13 -> 0 | AC8: ='COGS & GM'!$AC$13 -> 0 | AD8: ='COGS & GM'!$AD$13 -> 0 | AE8: ='COGS & GM'!$AE$13 -> 0 | AF8: ='COGS & GM'!$AF$13 -> 0 | AG8: ='COGS & GM'!$AG$13 -> 0 | AH8: ='COGS & GM'!$AH$13 -> 0 | AI8: ='COGS & GM'!$AI$13 -> 0 | AJ8: ='COGS & GM'!$AJ$13 -> 0 | AK8: ='COGS & GM'!$AK$13 -> 0 | AL8: ='COGS & GM'!$AL$13 -> 0 | AN8: =SUM(C8:E8) -> 0 | AO8: =SUM(F8:H8) -> 0 | AP8: =SUM(I8:K8) -> 0 | AQ8: =SUM(L8:N8) -> 0 | AR8: =SUM(O8:Q8) -> 0 | AS8: =SUM(R8:T8) -> 0 | AT8: =SUM(U8:W8) -> 0 | AU8: =SUM(X8:Z8) -> 0 | AV8: =SUM(AA8:AC8) -> 0 | AW8: =SUM(AD8:AF8) -> 0 | AX8: =SUM(AG8:AI8) -> 0 | AY8: =SUM(AJ8:AL8) -> 0 | BA8: =SUM(C8:N8) -> 0 | BB8: =SUM(O8:Z8) -> 0 | BC8: =SUM(AA8:AL8) -> 0
A9: Gross Profit | C9: =C7-C8 -> 0 | D9: =D7-D8 -> 0 | E9: =E7-E8 -> 0 | F9: =F7-F8 -> 0 | G9: =G7-G8 -> 0 | H9: =H7-H8 -> 0 | I9: =I7-I8 -> 0 | J9: =J7-J8 -> 0 | ... AL9: =AL7-AL8 -> 0 | AN9: =SUM(C9:E9) -> 0 | AO9: =SUM(F9:H9) -> 0 | AP9: =SUM(I9:K9) -> 0 | AQ9: =SUM(L9:N9) -> 0 | AR9: =SUM(O9:Q9) -> 0 | AS9: =SUM(R9:T9) -> 0 | AT9: =SUM(U9:W9) -> 0 | AU9: =SUM(X9:Z9) -> 0 | AV9: =SUM(AA9:AC9) -> 0 | AW9: =SUM(AD9:AF9) -> 0 | AX9: =SUM(AG9:AI9) -> 0 | AY9: =SUM(AJ9:AL9) -> 0 | BA9: =SUM(C9:N9) -> 0 | BB9: =SUM(O9:Z9) -> 0 | BC9: =SUM(AA9:AL9) -> 0
A10: Gross Margin % | C10: =IFERROR(C9/C7,0) -> 0 | D10: =IFERROR(D9/D7,0) -> 0 | E10: =IFERROR(E9/E7,0) -> 0 | F10: =IFERROR(F9/F7,0) -> 0 | G10: =IFERROR(G9/G7,0) -> 0 | H10: =IFERROR(H9/H7,0) -> 0 | I10: =IFERROR(I9/I7,0) -> 0 | J10: =IFERROR(J9/J7,0) -> 0 | ... AL10: =IFERROR(AL9/AL7,0) -> 0 | AN10: =AVERAGE(C10:E10) -> 0 | AO10: =AVERAGE(F10:H10) -> 0 | AP10: =AVERAGE(I10:K10) -> 0 | AQ10: =AVERAGE(L10:N10) -> 0 | AR10: =AVERAGE(O10:Q10) -> 0 | AS10: =AVERAGE(R10:T10) -> 0 | AT10: =AVERAGE(U10:W10) -> 0 | AU10: =AVERAGE(X10:Z10) -> 0 | AV10: =AVERAGE(AA10:AC10) -> 0 | AW10: =AVERAGE(AD10:AF10) -> 0 | AX10: =AVERAGE(AG10:AI10) -> 0 | AY10: =AVERAGE(AJ10:AL10) -> 0 | BA10: =AVERAGE(C10:N10) -> 0 | BB10: =AVERAGE(O10:Z10) -> 0 | BC10: =AVERAGE(AA10:AL10) -> 0
A12: Operating Expenses
A13: Growth & Marketing | C13: ='Opex'!$C$13 -> 0 | D13: ='Opex'!$D$13 -> 0 | E13: ='Opex'!$E$13 -> 0 | F13: ='Opex'!$F$13 -> 0 | G13: ='Opex'!$G$13 -> 0 | H13: ='Opex'!$H$13 -> 0 | I13: ='Opex'!$I$13 -> 0 | J13: ='Opex'!$J$13 -> 0 | K13: ='Opex'!$K$13 -> 0 | L13: ='Opex'!$L$13 -> 0 | M13: ='Opex'!$M$13 -> 0 | N13: ='Opex'!$N$13 -> 0 | O13: ='Opex'!$O$13 -> 0 | P13: ='Opex'!$P$13 -> 0 | Q13: ='Opex'!$Q$13 -> 0 | R13: ='Opex'!$R$13 -> 0 | S13: ='Opex'!$S$13 -> 0 | T13: ='Opex'!$T$13 -> 0 | U13: ='Opex'!$U$13 -> 0 | V13: ='Opex'!$V$13 -> 0 | W13: ='Opex'!$W$13 -> 0 | X13: ='Opex'!$X$13 -> 0 | Y13: ='Opex'!$Y$13 -> 0 | Z13: ='Opex'!$Z$13 -> 0 | AA13: ='Opex'!$AA$13 -> 0 | AB13: ='Opex'!$AB$13 -> 0 | AC13: ='Opex'!$AC$13 -> 0 | AD13: ='Opex'!$AD$13 -> 0 | AE13: ='Opex'!$AE$13 -> 0 | AF13: ='Opex'!$AF$13 -> 0 | AG13: ='Opex'!$AG$13 -> 0 | AH13: ='Opex'!$AH$13 -> 0 | AI13: ='Opex'!$AI$13 -> 0 | AJ13: ='Opex'!$AJ$13 -> 0 | AK13: ='Opex'!$AK$13 -> 0 | AL13: ='Opex'!$AL$13 -> 0 | AN13: =SUM(C13:E13) -> 0 | AO13: =SUM(F13:H13) -> 0 | AP13: =SUM(I13:K13) -> 0 | AQ13: =SUM(L13:N13) -> 0 | AR13: =SUM(O13:Q13) -> 0 | AS13: =SUM(R13:T13) -> 0 | AT13: =SUM(U13:W13) -> 0 | AU13: =SUM(X13:Z13) -> 0 | AV13: =SUM(AA13:AC13) -> 0 | AW13: =SUM(AD13:AF13) -> 0 | AX13: =SUM(AG13:AI13) -> 0 | AY13: =SUM(AJ13:AL13) -> 0 | BA13: =SUM(C13:N13) -> 0 | BB13: =SUM(O13:Z13) -> 0 | BC13: =SUM(AA13:AL13) -> 0
A14: Product & Engineering | C14: ='Opex'!$C$18 -> 0 | D14: ='Opex'!$D$18 -> 0 | E14: ='Opex'!$E$18 -> 0 | F14: ='Opex'!$F$18 -> 0 | G14: ='Opex'!$G$18 -> 0 | H14: ='Opex'!$H$18 -> 0 | I14: ='Opex'!$I$18 -> 0 | J14: ='Opex'!$J$18 -> 0 | K14: ='Opex'!$K$18 -> 0 | L14: ='Opex'!$L$18 -> 0 | M14: ='Opex'!$M$18 -> 0 | N14: ='Opex'!$N$18 -> 0 | O14: ='Opex'!$O$18 -> 0 | P14: ='Opex'!$P$18 -> 0 | Q14: ='Opex'!$Q$18 -> 0 | R14: ='Opex'!$R$18 -> 0 | S14: ='Opex'!$S$18 -> 0 | T14: ='Opex'!$T$18 -> 0 | U14: ='Opex'!$U$18 -> 0 | V14: ='Opex'!$V$18 -> 0 | W14: ='Opex'!$W$18 -> 0 | X14: ='Opex'!$X$18 -> 0 | Y14: ='Opex'!$Y$18 -> 0 | Z14: ='Opex'!$Z$18 -> 0 | AA14: ='Opex'!$AA$18 -> 0 | AB14: ='Opex'!$AB$18 -> 0 | AC14: ='Opex'!$AC$18 -> 0 | AD14: ='Opex'!$AD$18 -> 0 | AE14: ='Opex'!$AE$18 -> 0 | AF14: ='Opex'!$AF$18 -> 0 | AG14: ='Opex'!$AG$18 -> 0 | AH14: ='Opex'!$AH$18 -> 0 | AI14: ='Opex'!$AI$18 -> 0 | AJ14: ='Opex'!$AJ$18 -> 0 | AK14: ='Opex'!$AK$18 -> 0 | AL14: ='Opex'!$AL$18 -> 0 | AN14: =SUM(C14:E14) -> 0 | AO14: =SUM(F14:H14) -> 0 | AP14: =SUM(I14:K14) -> 0 | AQ14: =SUM(L14:N14) -> 0 | AR14: =SUM(O14:Q14) -> 0 | AS14: =SUM(R14:T14) -> 0 | AT14: =SUM(U14:W14) -> 0 | AU14: =SUM(X14:Z14) -> 0 | AV14: =SUM(AA14:AC14) -> 0 | AW14: =SUM(AD14:AF14) -> 0 | AX14: =SUM(AG14:AI14) -> 0 | AY14: =SUM(AJ14:AL14) -> 0 | BA14: =SUM(C14:N14) -> 0 | BB14: =SUM(O14:Z14) -> 0 | BC14: =SUM(AA14:AL14) -> 0
A15: General & Administrative | C15: ='Opex'!$C$23 -> 0 | D15: ='Opex'!$D$23 -> 0 | E15: ='Opex'!$E$23 -> 0 | F15: ='Opex'!$F$23 -> 0 | G15: ='Opex'!$G$23 -> 0 | H15: ='Opex'!$H$23 -> 0 | I15: ='Opex'!$I$23 -> 0 | J15: ='Opex'!$J$23 -> 0 | K15: ='Opex'!$K$23 -> 0 | L15: ='Opex'!$L$23 -> 0 | M15: ='Opex'!$M$23 -> 0 | N15: ='Opex'!$N$23 -> 0 | O15: ='Opex'!$O$23 -> 0 | P15: ='Opex'!$P$23 -> 0 | Q15: ='Opex'!$Q$23 -> 0 | R15: ='Opex'!$R$23 -> 0 | S15: ='Opex'!$S$23 -> 0 | T15: ='Opex'!$T$23 -> 0 | U15: ='Opex'!$U$23 -> 0 | V15: ='Opex'!$V$23 -> 0 | W15: ='Opex'!$W$23 -> 0 | X15: ='Opex'!$X$23 -> 0 | Y15: ='Opex'!$Y$23 -> 0 | Z15: ='Opex'!$Z$23 -> 0 | AA15: ='Opex'!$AA$23 -> 0 | AB15: ='Opex'!$AB$23 -> 0 | AC15: ='Opex'!$AC$23 -> 0 | AD15: ='Opex'!$AD$23 -> 0 | AE15: ='Opex'!$AE$23 -> 0 | AF15: ='Opex'!$AF$23 -> 0 | AG15: ='Opex'!$AG$23 -> 0 | AH15: ='Opex'!$AH$23 -> 0 | AI15: ='Opex'!$AI$23 -> 0 | AJ15: ='Opex'!$AJ$23 -> 0 | AK15: ='Opex'!$AK$23 -> 0 | AL15: ='Opex'!$AL$23 -> 0 | AN15: =SUM(C15:E15) -> 0 | AO15: =SUM(F15:H15) -> 0 | AP15: =SUM(I15:K15) -> 0 | AQ15: =SUM(L15:N15) -> 0 | AR15: =SUM(O15:Q15) -> 0 | AS15: =SUM(R15:T15) -> 0 | AT15: =SUM(U15:W15) -> 0 | AU15: =SUM(X15:Z15) -> 0 | AV15: =SUM(AA15:AC15) -> 0 | AW15: =SUM(AD15:AF15) -> 0 | AX15: =SUM(AG15:AI15) -> 0 | AY15: =SUM(AJ15:AL15) -> 0 | BA15: =SUM(C15:N15) -> 0 | BB15: =SUM(O15:Z15) -> 0 | BC15: =SUM(AA15:AL15) -> 0
A16: Total Operating Expenses | C16: =C13+C14+C15 -> 0 | D16: =D13+D14+D15 -> 0 | E16: =E13+E14+E15 -> 0 | F16: =F13+F14+F15 -> 0 | G16: =G13+G14+G15 -> 0 | H16: =H13+H14+H15 -> 0 | I16: =I13+I14+I15 -> 0 | J16: =J13+J14+J15 -> 0 | ... AL16: =AL13+AL14+AL15 -> 0 | AN16: =SUM(C16:E16) -> 0 | AO16: =SUM(F16:H16) -> 0 | AP16: =SUM(I16:K16) -> 0 | AQ16: =SUM(L16:N16) -> 0 | AR16: =SUM(O16:Q16) -> 0 | AS16: =SUM(R16:T16) -> 0 | AT16: =SUM(U16:W16) -> 0 | AU16: =SUM(X16:Z16) -> 0 | AV16: =SUM(AA16:AC16) -> 0 | AW16: =SUM(AD16:AF16) -> 0 | AX16: =SUM(AG16:AI16) -> 0 | AY16: =SUM(AJ16:AL16) -> 0 | BA16: =SUM(C16:N16) -> 0 | BB16: =SUM(O16:Z16) -> 0 | BC16: =SUM(AA16:AL16) -> 0
A18: EBITDA | C18: =C9-C16 -> 0 | D18: =D9-D16 -> 0 | E18: =E9-E16 -> 0 | F18: =F9-F16 -> 0 | G18: =G9-G16 -> 0 | H18: =H9-H16 -> 0 | I18: =I9-I16 -> 0 | J18: =J9-J16 -> 0 | ... AL18: =AL9-AL16 -> 0 | AN18: =SUM(C18:E18) -> 0 | AO18: =SUM(F18:H18) -> 0 | AP18: =SUM(I18:K18) -> 0 | AQ18: =SUM(L18:N18) -> 0 | AR18: =SUM(O18:Q18) -> 0 | AS18: =SUM(R18:T18) -> 0 | AT18: =SUM(U18:W18) -> 0 | AU18: =SUM(X18:Z18) -> 0 | AV18: =SUM(AA18:AC18) -> 0 | AW18: =SUM(AD18:AF18) -> 0 | AX18: =SUM(AG18:AI18) -> 0 | AY18: =SUM(AJ18:AL18) -> 0 | BA18: =SUM(C18:N18) -> 0 | BB18: =SUM(O18:Z18) -> 0 | BC18: =SUM(AA18:AL18) -> 0
A19: Depreciation & Amortization | C19: ='Working Capital'!$C$19 -> 0 | D19: ='Working Capital'!$D$19 -> 0 | E19: ='Working Capital'!$E$19 -> 0 | F19: ='Working Capital'!$F$19 -> 0 | G19: ='Working Capital'!$G$19 -> 0 | H19: ='Working Capital'!$H$19 -> 0 | I19: ='Working Capital'!$I$19 -> 0 | J19: ='Working Capital'!$J$19 -> 0 | K19: ='Working Capital'!$K$19 -> 0 | L19: ='Working Capital'!$L$19 -> 0 | M19: ='Working Capital'!$M$19 -> 0 | N19: ='Working Capital'!$N$19 -> 0 | O19: ='Working Capital'!$O$19 -> 0 | P19: ='Working Capital'!$P$19 -> 0 | Q19: ='Working Capital'!$Q$19 -> 0 | R19: ='Working Capital'!$R$19 -> 0 | S19: ='Working Capital'!$S$19 -> 0 | T19: ='Working Capital'!$T$19 -> 0 | U19: ='Working Capital'!$U$19 -> 0 | V19: ='Working Capital'!$V$19 -> 0 | W19: ='Working Capital'!$W$19 -> 0 | X19: ='Working Capital'!$X$19 -> 0 | Y19: ='Working Capital'!$Y$19 -> 0 | Z19: ='Working Capital'!$Z$19 -> 0 | AA19: ='Working Capital'!$AA$19 -> 0 | AB19: ='Working Capital'!$AB$19 -> 0 | AC19: ='Working Capital'!$AC$19 -> 0 | AD19: ='Working Capital'!$AD$19 -> 0 | AE19: ='Working Capital'!$AE$19 -> 0 | AF19: ='Working Capital'!$AF$19 -> 0 | AG19: ='Working Capital'!$AG$19 -> 0 | AH19: ='Working Capital'!$AH$19 -> 0 | AI19: ='Working Capital'!$AI$19 -> 0 | AJ19: ='Working Capital'!$AJ$19 -> 0 | AK19: ='Working Capital'!$AK$19 -> 0 | AL19: ='Working Capital'!$AL$19 -> 0 | AN19: =SUM(C19:E19) -> 0 | AO19: =SUM(F19:H19) -> 0 | AP19: =SUM(I19:K19) -> 0 | AQ19: =SUM(L19:N19) -> 0 | AR19: =SUM(O19:Q19) -> 0 | AS19: =SUM(R19:T19) -> 0 | AT19: =SUM(U19:W19) -> 0 | AU19: =SUM(X19:Z19) -> 0 | AV19: =SUM(AA19:AC19) -> 0 | AW19: =SUM(AD19:AF19) -> 0 | AX19: =SUM(AG19:AI19) -> 0 | AY19: =SUM(AJ19:AL19) -> 0 | BA19: =SUM(C19:N19) -> 0 | BB19: =SUM(O19:Z19) -> 0 | BC19: =SUM(AA19:AL19) -> 0
A20: EBIT (Operating Income) | C20: =C18-C19 -> 0 | D20: =D18-D19 -> 0 | E20: =E18-E19 -> 0 | F20: =F18-F19 -> 0 | G20: =G18-G19 -> 0 | H20: =H18-H19 -> 0 | I20: =I18-I19 -> 0 | J20: =J18-J19 -> 0 | ... AL20: =AL18-AL19 -> 0 | AN20: =SUM(C20:E20) -> 0 | AO20: =SUM(F20:H20) -> 0 | AP20: =SUM(I20:K20) -> 0 | AQ20: =SUM(L20:N20) -> 0 | AR20: =SUM(O20:Q20) -> 0 | AS20: =SUM(R20:T20) -> 0 | AT20: =SUM(U20:W20) -> 0 | AU20: =SUM(X20:Z20) -> 0 | AV20: =SUM(AA20:AC20) -> 0 | AW20: =SUM(AD20:AF20) -> 0 | AX20: =SUM(AG20:AI20) -> 0 | AY20: =SUM(AJ20:AL20) -> 0 | BA20: =SUM(C20:N20) -> 0 | BB20: =SUM(O20:Z20) -> 0 | BC20: =SUM(AA20:AL20) -> 0
A21: Interest Expense | C21: ='Working Capital'!$C$26 -> 0 | D21: ='Working Capital'!$D$26 -> 0 | E21: ='Working Capital'!$E$26 -> 0 | F21: ='Working Capital'!$F$26 -> 0 | G21: ='Working Capital'!$G$26 -> 0 | H21: ='Working Capital'!$H$26 -> 0 | I21: ='Working Capital'!$I$26 -> 0 | J21: ='Working Capital'!$J$26 -> 0 | K21: ='Working Capital'!$K$26 -> 0 | L21: ='Working Capital'!$L$26 -> 0 | M21: ='Working Capital'!$M$26 -> 0 | N21: ='Working Capital'!$N$26 -> 0 | O21: ='Working Capital'!$O$26 -> 0 | P21: ='Working Capital'!$P$26 -> 0 | Q21: ='Working Capital'!$Q$26 -> 0 | R21: ='Working Capital'!$R$26 -> 0 | S21: ='Working Capital'!$S$26 -> 0 | T21: ='Working Capital'!$T$26 -> 0 | U21: ='Working Capital'!$U$26 -> 0 | V21: ='Working Capital'!$V$26 -> 0 | W21: ='Working Capital'!$W$26 -> 0 | X21: ='Working Capital'!$X$26 -> 0 | Y21: ='Working Capital'!$Y$26 -> 0 | Z21: ='Working Capital'!$Z$26 -> 0 | AA21: ='Working Capital'!$AA$26 -> 0 | AB21: ='Working Capital'!$AB$26 -> 0 | AC21: ='Working Capital'!$AC$26 -> 0 | AD21: ='Working Capital'!$AD$26 -> 0 | AE21: ='Working Capital'!$AE$26 -> 0 | AF21: ='Working Capital'!$AF$26 -> 0 | AG21: ='Working Capital'!$AG$26 -> 0 | AH21: ='Working Capital'!$AH$26 -> 0 | AI21: ='Working Capital'!$AI$26 -> 0 | AJ21: ='Working Capital'!$AJ$26 -> 0 | AK21: ='Working Capital'!$AK$26 -> 0 | AL21: ='Working Capital'!$AL$26 -> 0 | AN21: =SUM(C21:E21) -> 0 | AO21: =SUM(F21:H21) -> 0 | AP21: =SUM(I21:K21) -> 0 | AQ21: =SUM(L21:N21) -> 0 | AR21: =SUM(O21:Q21) -> 0 | AS21: =SUM(R21:T21) -> 0 | AT21: =SUM(U21:W21) -> 0 | AU21: =SUM(X21:Z21) -> 0 | AV21: =SUM(AA21:AC21) -> 0 | AW21: =SUM(AD21:AF21) -> 0 | AX21: =SUM(AG21:AI21) -> 0 | AY21: =SUM(AJ21:AL21) -> 0 | BA21: =SUM(C21:N21) -> 0 | BB21: =SUM(O21:Z21) -> 0 | BC21: =SUM(AA21:AL21) -> 0
A22: Earnings Before Tax | C22: =C20-C21 -> 0 | D22: =D20-D21 -> 0 | E22: =E20-E21 -> 0 | F22: =F20-F21 -> 0 | G22: =G20-G21 -> 0 | H22: =H20-H21 -> 0 | I22: =I20-I21 -> 0 | J22: =J20-J21 -> 0 | ... AL22: =AL20-AL21 -> 0 | AN22: =SUM(C22:E22) -> 0 | AO22: =SUM(F22:H22) -> 0 | AP22: =SUM(I22:K22) -> 0 | AQ22: =SUM(L22:N22) -> 0 | AR22: =SUM(O22:Q22) -> 0 | AS22: =SUM(R22:T22) -> 0 | AT22: =SUM(U22:W22) -> 0 | AU22: =SUM(X22:Z22) -> 0 | AV22: =SUM(AA22:AC22) -> 0 | AW22: =SUM(AD22:AF22) -> 0 | AX22: =SUM(AG22:AI22) -> 0 | AY22: =SUM(AJ22:AL22) -> 0 | BA22: =SUM(C22:N22) -> 0 | BB22: =SUM(O22:Z22) -> 0 | BC22: =SUM(AA22:AL22) -> 0
A23: Income Tax Expense | B23: MAX(0, EBT) × tax rate — no NOL modeling | C23: =MAX(0,C22)*'Assumptions'!$F$10 -> 0 | D23: =MAX(0,D22)*'Assumptions'!$F$10 -> 0 | E23: =MAX(0,E22)*'Assumptions'!$F$10 -> 0 | F23: =MAX(0,F22)*'Assumptions'!$F$10 -> 0 | G23: =MAX(0,G22)*'Assumptions'!$F$10 -> 0 | H23: =MAX(0,H22)*'Assumptions'!$F$10 -> 0 | I23: =MAX(0,I22)*'Assumptions'!$F$10 -> 0 | J23: =MAX(0,J22)*'Assumptions'!$F$10 -> 0 | ... AL23: =MAX(0,AL22)*'Assumptions'!$F$10 -> 0 | AN23: =SUM(C23:E23) -> 0 | AO23: =SUM(F23:H23) -> 0 | AP23: =SUM(I23:K23) -> 0 | AQ23: =SUM(L23:N23) -> 0 | AR23: =SUM(O23:Q23) -> 0 | AS23: =SUM(R23:T23) -> 0 | AT23: =SUM(U23:W23) -> 0 | AU23: =SUM(X23:Z23) -> 0 | AV23: =SUM(AA23:AC23) -> 0 | AW23: =SUM(AD23:AF23) -> 0 | AX23: =SUM(AG23:AI23) -> 0 | AY23: =SUM(AJ23:AL23) -> 0 | BA23: =SUM(C23:N23) -> 0 | BB23: =SUM(O23:Z23) -> 0 | BC23: =SUM(AA23:AL23) -> 0
A24: Net Income | C24: =C22-C23 -> 0 | D24: =D22-D23 -> 0 | E24: =E22-E23 -> 0 | F24: =F22-F23 -> 0 | G24: =G22-G23 -> 0 | H24: =H22-H23 -> 0 | I24: =I22-I23 -> 0 | J24: =J22-J23 -> 0 | ... AL24: =AL22-AL23 -> 0 | AN24: =SUM(C24:E24) -> 0 | AO24: =SUM(F24:H24) -> 0 | AP24: =SUM(I24:K24) -> 0 | AQ24: =SUM(L24:N24) -> 0 | AR24: =SUM(O24:Q24) -> 0 | AS24: =SUM(R24:T24) -> 0 | AT24: =SUM(U24:W24) -> 0 | AU24: =SUM(X24:Z24) -> 0 | AV24: =SUM(AA24:AC24) -> 0 | AW24: =SUM(AD24:AF24) -> 0 | AX24: =SUM(AG24:AI24) -> 0 | AY24: =SUM(AJ24:AL24) -> 0 | BA24: =SUM(C24:N24) -> 0 | BB24: =SUM(O24:Z24) -> 0 | BC24: =SUM(AA24:AL24) -> 0

Sheet Balance Sheet
A1: Consumer Subscription — 3-Year Financial Model — Balance Sheet
A2: Assets = Liabilities + Equity every month, by construction.
A5: Line item | B5: Units / source | C5: Monthly (36 months) | AN5: Quarterly | BA5: Annual
C6: 46023 | D6: 46054 | E6: 46082 | F6: 46113 | G6: 46143 | H6: 46174 | I6: 46204 | J6: 46235 | K6: 46266 | L6: 46296 | M6: 46327 | N6: 46357 | O6: 46388 | P6: 46419 | Q6: 46447 | R6: 46478 | S6: 46508 | T6: 46539 | U6: 46569 | V6: 46600 | W6: 46631 | X6: 46661 | Y6: 46692 | Z6: 46722 | AA6: 46753 | AB6: 46784 | AC6: 46813 | AD6: 46844 | AE6: 46874 | AF6: 46905 | AG6: 46935 | AH6: 46966 | AI6: 46997 | AJ6: 47027 | AK6: 47058 | AL6: 47088 | AN6: Q1 | AO6: Q2 | AP6: Q3 | AQ6: Q4 | AR6: Q5 | AS6: Q6 | AT6: Q7 | AU6: Q8 | AV6: Q9 | AW6: Q10 | AX6: Q11 | AY6: Q12 | BA6: FY1 | BB6: FY2 | BC6: FY3
A7: Assets
A8: Cash & equivalents | B8: Linked from Cash Flow tab | C8: ='Cash Flow'!$C$28 -> 0 | D8: ='Cash Flow'!$D$28 -> 0 | E8: ='Cash Flow'!$E$28 -> 0 | F8: ='Cash Flow'!$F$28 -> 0 | G8: ='Cash Flow'!$G$28 -> 0 | H8: ='Cash Flow'!$H$28 -> 0 | I8: ='Cash Flow'!$I$28 -> 0 | J8: ='Cash Flow'!$J$28 -> 0 | K8: ='Cash Flow'!$K$28 -> 0 | L8: ='Cash Flow'!$L$28 -> 0 | M8: ='Cash Flow'!$M$28 -> 0 | N8: ='Cash Flow'!$N$28 -> 0 | O8: ='Cash Flow'!$O$28 -> 0 | P8: ='Cash Flow'!$P$28 -> 0 | Q8: ='Cash Flow'!$Q$28 -> 0 | R8: ='Cash Flow'!$R$28 -> 0 | S8: ='Cash Flow'!$S$28 -> 0 | T8: ='Cash Flow'!$T$28 -> 0 | U8: ='Cash Flow'!$U$28 -> 0 | V8: ='Cash Flow'!$V$28 -> 0 | W8: ='Cash Flow'!$W$28 -> 0 | X8: ='Cash Flow'!$X$28 -> 0 | Y8: ='Cash Flow'!$Y$28 -> 0 | Z8: ='Cash Flow'!$Z$28 -> 0 | AA8: ='Cash Flow'!$AA$28 -> 0 | AB8: ='Cash Flow'!$AB$28 -> 0 | AC8: ='Cash Flow'!$AC$28 -> 0 | AD8: ='Cash Flow'!$AD$28 -> 0 | AE8: ='Cash Flow'!$AE$28 -> 0 | AF8: ='Cash Flow'!$AF$28 -> 0 | AG8: ='Cash Flow'!$AG$28 -> 0 | AH8: ='Cash Flow'!$AH$28 -> 0 | AI8: ='Cash Flow'!$AI$28 -> 0 | AJ8: ='Cash Flow'!$AJ$28 -> 0 | AK8: ='Cash Flow'!$AK$28 -> 0 | AL8: ='Cash Flow'!$AL$28 -> 0 | AN8: =E8 -> 0 | AO8: =H8 -> 0 | AP8: =K8 -> 0 | AQ8: =N8 -> 0 | AR8: =Q8 -> 0 | AS8: =T8 -> 0 | AT8: =W8 -> 0 | AU8: =Z8 -> 0 | AV8: =AC8 -> 0 | AW8: =AF8 -> 0 | AX8: =AI8 -> 0 | AY8: =AL8 -> 0 | BA8: =N8 -> 0 | BB8: =Z8 -> 0 | BC8: =AL8 -> 0
A9: Accounts Receivable | C9: ='Working Capital'!$C$8 -> 0 | D9: ='Working Capital'!$D$8 -> 0 | E9: ='Working Capital'!$E$8 -> 0 | F9: ='Working Capital'!$F$8 -> 0 | G9: ='Working Capital'!$G$8 -> 0 | H9: ='Working Capital'!$H$8 -> 0 | I9: ='Working Capital'!$I$8 -> 0 | J9: ='Working Capital'!$J$8 -> 0 | K9: ='Working Capital'!$K$8 -> 0 | L9: ='Working Capital'!$L$8 -> 0 | M9: ='Working Capital'!$M$8 -> 0 | N9: ='Working Capital'!$N$8 -> 0 | O9: ='Working Capital'!$O$8 -> 0 | P9: ='Working Capital'!$P$8 -> 0 | Q9: ='Working Capital'!$Q$8 -> 0 | R9: ='Working Capital'!$R$8 -> 0 | S9: ='Working Capital'!$S$8 -> 0 | T9: ='Working Capital'!$T$8 -> 0 | U9: ='Working Capital'!$U$8 -> 0 | V9: ='Working Capital'!$V$8 -> 0 | W9: ='Working Capital'!$W$8 -> 0 | X9: ='Working Capital'!$X$8 -> 0 | Y9: ='Working Capital'!$Y$8 -> 0 | Z9: ='Working Capital'!$Z$8 -> 0 | AA9: ='Working Capital'!$AA$8 -> 0 | AB9: ='Working Capital'!$AB$8 -> 0 | AC9: ='Working Capital'!$AC$8 -> 0 | AD9: ='Working Capital'!$AD$8 -> 0 | AE9: ='Working Capital'!$AE$8 -> 0 | AF9: ='Working Capital'!$AF$8 -> 0 | AG9: ='Working Capital'!$AG$8 -> 0 | AH9: ='Working Capital'!$AH$8 -> 0 | AI9: ='Working Capital'!$AI$8 -> 0 | AJ9: ='Working Capital'!$AJ$8 -> 0 | AK9: ='Working Capital'!$AK$8 -> 0 | AL9: ='Working Capital'!$AL$8 -> 0 | AN9: =E9 -> 0 | AO9: =H9 -> 0 | AP9: =K9 -> 0 | AQ9: =N9 -> 0 | AR9: =Q9 -> 0 | AS9: =T9 -> 0 | AT9: =W9 -> 0 | AU9: =Z9 -> 0 | AV9: =AC9 -> 0 | AW9: =AF9 -> 0 | AX9: =AI9 -> 0 | AY9: =AL9 -> 0 | BA9: =N9 -> 0 | BB9: =Z9 -> 0 | BC9: =AL9 -> 0
A10: Other Current Assets (prepaid, etc.) | B10: Linked from Working Capital tab | C10: ='Working Capital'!C11 -> 0 | D10: ='Working Capital'!D11 -> 0 | E10: ='Working Capital'!E11 -> 0 | F10: ='Working Capital'!F11 -> 0 | G10: ='Working Capital'!G11 -> 0 | H10: ='Working Capital'!H11 -> 0 | I10: ='Working Capital'!I11 -> 0 | J10: ='Working Capital'!J11 -> 0 | ... AL10: ='Working Capital'!AL11 -> 0 | AN10: =E10 -> 0 | AO10: =H10 -> 0 | AP10: =K10 -> 0 | AQ10: =N10 -> 0 | AR10: =Q10 -> 0 | AS10: =T10 -> 0 | AT10: =W10 -> 0 | AU10: =Z10 -> 0 | AV10: =AC10 -> 0 | AW10: =AF10 -> 0 | AX10: =AI10 -> 0 | AY10: =AL10 -> 0 | BA10: =N10 -> 0 | BB10: =Z10 -> 0 | BC10: =AL10 -> 0
A11: Net PP&E | C11: ='Working Capital'!$C$20 -> 0 | D11: ='Working Capital'!$D$20 -> 0 | E11: ='Working Capital'!$E$20 -> 0 | F11: ='Working Capital'!$F$20 -> 0 | G11: ='Working Capital'!$G$20 -> 0 | H11: ='Working Capital'!$H$20 -> 0 | I11: ='Working Capital'!$I$20 -> 0 | J11: ='Working Capital'!$J$20 -> 0 | K11: ='Working Capital'!$K$20 -> 0 | L11: ='Working Capital'!$L$20 -> 0 | M11: ='Working Capital'!$M$20 -> 0 | N11: ='Working Capital'!$N$20 -> 0 | O11: ='Working Capital'!$O$20 -> 0 | P11: ='Working Capital'!$P$20 -> 0 | Q11: ='Working Capital'!$Q$20 -> 0 | R11: ='Working Capital'!$R$20 -> 0 | S11: ='Working Capital'!$S$20 -> 0 | T11: ='Working Capital'!$T$20 -> 0 | U11: ='Working Capital'!$U$20 -> 0 | V11: ='Working Capital'!$V$20 -> 0 | W11: ='Working Capital'!$W$20 -> 0 | X11: ='Working Capital'!$X$20 -> 0 | Y11: ='Working Capital'!$Y$20 -> 0 | Z11: ='Working Capital'!$Z$20 -> 0 | AA11: ='Working Capital'!$AA$20 -> 0 | AB11: ='Working Capital'!$AB$20 -> 0 | AC11: ='Working Capital'!$AC$20 -> 0 | AD11: ='Working Capital'!$AD$20 -> 0 | AE11: ='Working Capital'!$AE$20 -> 0 | AF11: ='Working Capital'!$AF$20 -> 0 | AG11: ='Working Capital'!$AG$20 -> 0 | AH11: ='Working Capital'!$AH$20 -> 0 | AI11: ='Working Capital'!$AI$20 -> 0 | AJ11: ='Working Capital'!$AJ$20 -> 0 | AK11: ='Working Capital'!$AK$20 -> 0 | AL11: ='Working Capital'!$AL$20 -> 0 | AN11: =E11 -> 0 | AO11: =H11 -> 0 | AP11: =K11 -> 0 | AQ11: =N11 -> 0 | AR11: =Q11 -> 0 | AS11: =T11 -> 0 | AT11: =W11 -> 0 | AU11: =Z11 -> 0 | AV11: =AC11 -> 0 | AW11: =AF11 -> 0 | AX11: =AI11 -> 0 | AY11: =AL11 -> 0 | BA11: =N11 -> 0 | BB11: =Z11 -> 0 | BC11: =AL11 -> 0
A12: Total Assets | C12: =C8+C9+C10+C11 -> 0 | D12: =D8+D9+D10+D11 -> 0 | E12: =E8+E9+E10+E11 -> 0 | F12: =F8+F9+F10+F11 -> 0 | G12: =G8+G9+G10+G11 -> 0 | H12: =H8+H9+H10+H11 -> 0 | I12: =I8+I9+I10+I11 -> 0 | J12: =J8+J9+J10+J11 -> 0 | ... AL12: =AL8+AL9+AL10+AL11 -> 0 | AN12: =E12 -> 0 | AO12: =H12 -> 0 | AP12: =K12 -> 0 | AQ12: =N12 -> 0 | AR12: =Q12 -> 0 | AS12: =T12 -> 0 | AT12: =W12 -> 0 | AU12: =Z12 -> 0 | AV12: =AC12 -> 0 | AW12: =AF12 -> 0 | AX12: =AI12 -> 0 | AY12: =AL12 -> 0 | BA12: =N12 -> 0 | BB12: =Z12 -> 0 | BC12: =AL12 -> 0
A14: Liabilities
A15: Accounts Payable | C15: ='Working Capital'!$C$9 -> 0 | D15: ='Working Capital'!$D$9 -> 0 | E15: ='Working Capital'!$E$9 -> 0 | F15: ='Working Capital'!$F$9 -> 0 | G15: ='Working Capital'!$G$9 -> 0 | H15: ='Working Capital'!$H$9 -> 0 | I15: ='Working Capital'!$I$9 -> 0 | J15: ='Working Capital'!$J$9 -> 0 | K15: ='Working Capital'!$K$9 -> 0 | L15: ='Working Capital'!$L$9 -> 0 | M15: ='Working Capital'!$M$9 -> 0 | N15: ='Working Capital'!$N$9 -> 0 | O15: ='Working Capital'!$O$9 -> 0 | P15: ='Working Capital'!$P$9 -> 0 | Q15: ='Working Capital'!$Q$9 -> 0 | R15: ='Working Capital'!$R$9 -> 0 | S15: ='Working Capital'!$S$9 -> 0 | T15: ='Working Capital'!$T$9 -> 0 | U15: ='Working Capital'!$U$9 -> 0 | V15: ='Working Capital'!$V$9 -> 0 | W15: ='Working Capital'!$W$9 -> 0 | X15: ='Working Capital'!$X$9 -> 0 | Y15: ='Working Capital'!$Y$9 -> 0 | Z15: ='Working Capital'!$Z$9 -> 0 | AA15: ='Working Capital'!$AA$9 -> 0 | AB15: ='Working Capital'!$AB$9 -> 0 | AC15: ='Working Capital'!$AC$9 -> 0 | AD15: ='Working Capital'!$AD$9 -> 0 | AE15: ='Working Capital'!$AE$9 -> 0 | AF15: ='Working Capital'!$AF$9 -> 0 | AG15: ='Working Capital'!$AG$9 -> 0 | AH15: ='Working Capital'!$AH$9 -> 0 | AI15: ='Working Capital'!$AI$9 -> 0 | AJ15: ='Working Capital'!$AJ$9 -> 0 | AK15: ='Working Capital'!$AK$9 -> 0 | AL15: ='Working Capital'!$AL$9 -> 0 | AN15: =E15 -> 0 | AO15: =H15 -> 0 | AP15: =K15 -> 0 | AQ15: =N15 -> 0 | AR15: =Q15 -> 0 | AS15: =T15 -> 0 | AT15: =W15 -> 0 | AU15: =Z15 -> 0 | AV15: =AC15 -> 0 | AW15: =AF15 -> 0 | AX15: =AI15 -> 0 | AY15: =AL15 -> 0 | BA15: =N15 -> 0 | BB15: =Z15 -> 0 | BC15: =AL15 -> 0
A16: Deferred Revenue | C16: ='Working Capital'!$C$10 -> 0 | D16: ='Working Capital'!$D$10 -> 0 | E16: ='Working Capital'!$E$10 -> 0 | F16: ='Working Capital'!$F$10 -> 0 | G16: ='Working Capital'!$G$10 -> 0 | H16: ='Working Capital'!$H$10 -> 0 | I16: ='Working Capital'!$I$10 -> 0 | J16: ='Working Capital'!$J$10 -> 0 | K16: ='Working Capital'!$K$10 -> 0 | L16: ='Working Capital'!$L$10 -> 0 | M16: ='Working Capital'!$M$10 -> 0 | N16: ='Working Capital'!$N$10 -> 0 | O16: ='Working Capital'!$O$10 -> 0 | P16: ='Working Capital'!$P$10 -> 0 | Q16: ='Working Capital'!$Q$10 -> 0 | R16: ='Working Capital'!$R$10 -> 0 | S16: ='Working Capital'!$S$10 -> 0 | T16: ='Working Capital'!$T$10 -> 0 | U16: ='Working Capital'!$U$10 -> 0 | V16: ='Working Capital'!$V$10 -> 0 | W16: ='Working Capital'!$W$10 -> 0 | X16: ='Working Capital'!$X$10 -> 0 | Y16: ='Working Capital'!$Y$10 -> 0 | Z16: ='Working Capital'!$Z$10 -> 0 | AA16: ='Working Capital'!$AA$10 -> 0 | AB16: ='Working Capital'!$AB$10 -> 0 | AC16: ='Working Capital'!$AC$10 -> 0 | AD16: ='Working Capital'!$AD$10 -> 0 | AE16: ='Working Capital'!$AE$10 -> 0 | AF16: ='Working Capital'!$AF$10 -> 0 | AG16: ='Working Capital'!$AG$10 -> 0 | AH16: ='Working Capital'!$AH$10 -> 0 | AI16: ='Working Capital'!$AI$10 -> 0 | AJ16: ='Working Capital'!$AJ$10 -> 0 | AK16: ='Working Capital'!$AK$10 -> 0 | AL16: ='Working Capital'!$AL$10 -> 0 | AN16: =E16 -> 0 | AO16: =H16 -> 0 | AP16: =K16 -> 0 | AQ16: =N16 -> 0 | AR16: =Q16 -> 0 | AS16: =T16 -> 0 | AT16: =W16 -> 0 | AU16: =Z16 -> 0 | AV16: =AC16 -> 0 | AW16: =AF16 -> 0 | AX16: =AI16 -> 0 | AY16: =AL16 -> 0 | BA16: =N16 -> 0 | BB16: =Z16 -> 0 | BC16: =AL16 -> 0
A17: Debt | C17: ='Working Capital'!$C$25 -> 0 | D17: ='Working Capital'!$D$25 -> 0 | E17: ='Working Capital'!$E$25 -> 0 | F17: ='Working Capital'!$F$25 -> 0 | G17: ='Working Capital'!$G$25 -> 0 | H17: ='Working Capital'!$H$25 -> 0 | I17: ='Working Capital'!$I$25 -> 0 | J17: ='Working Capital'!$J$25 -> 0 | K17: ='Working Capital'!$K$25 -> 0 | L17: ='Working Capital'!$L$25 -> 0 | M17: ='Working Capital'!$M$25 -> 0 | N17: ='Working Capital'!$N$25 -> 0 | O17: ='Working Capital'!$O$25 -> 0 | P17: ='Working Capital'!$P$25 -> 0 | Q17: ='Working Capital'!$Q$25 -> 0 | R17: ='Working Capital'!$R$25 -> 0 | S17: ='Working Capital'!$S$25 -> 0 | T17: ='Working Capital'!$T$25 -> 0 | U17: ='Working Capital'!$U$25 -> 0 | V17: ='Working Capital'!$V$25 -> 0 | W17: ='Working Capital'!$W$25 -> 0 | X17: ='Working Capital'!$X$25 -> 0 | Y17: ='Working Capital'!$Y$25 -> 0 | Z17: ='Working Capital'!$Z$25 -> 0 | AA17: ='Working Capital'!$AA$25 -> 0 | AB17: ='Working Capital'!$AB$25 -> 0 | AC17: ='Working Capital'!$AC$25 -> 0 | AD17: ='Working Capital'!$AD$25 -> 0 | AE17: ='Working Capital'!$AE$25 -> 0 | AF17: ='Working Capital'!$AF$25 -> 0 | AG17: ='Working Capital'!$AG$25 -> 0 | AH17: ='Working Capital'!$AH$25 -> 0 | AI17: ='Working Capital'!$AI$25 -> 0 | AJ17: ='Working Capital'!$AJ$25 -> 0 | AK17: ='Working Capital'!$AK$25 -> 0 | AL17: ='Working Capital'!$AL$25 -> 0 | AN17: =E17 -> 0 | AO17: =H17 -> 0 | AP17: =K17 -> 0 | AQ17: =N17 -> 0 | AR17: =Q17 -> 0 | AS17: =T17 -> 0 | AT17: =W17 -> 0 | AU17: =Z17 -> 0 | AV17: =AC17 -> 0 | AW17: =AF17 -> 0 | AX17: =AI17 -> 0 | AY17: =AL17 -> 0 | BA17: =N17 -> 0 | BB17: =Z17 -> 0 | BC17: =AL17 -> 0
A18: Total Liabilities | C18: =C15+C16+C17 -> 0 | D18: =D15+D16+D17 -> 0 | E18: =E15+E16+E17 -> 0 | F18: =F15+F16+F17 -> 0 | G18: =G15+G16+G17 -> 0 | H18: =H15+H16+H17 -> 0 | I18: =I15+I16+I17 -> 0 | J18: =J15+J16+J17 -> 0 | ... AL18: =AL15+AL16+AL17 -> 0 | AN18: =E18 -> 0 | AO18: =H18 -> 0 | AP18: =K18 -> 0 | AQ18: =N18 -> 0 | AR18: =Q18 -> 0 | AS18: =T18 -> 0 | AT18: =W18 -> 0 | AU18: =Z18 -> 0 | AV18: =AC18 -> 0 | AW18: =AF18 -> 0 | AX18: =AI18 -> 0 | AY18: =AL18 -> 0 | BA18: =N18 -> 0 | BB18: =Z18 -> 0 | BC18: =AL18 -> 0
A20: Equity
A21: Paid-in Capital | B21: Starting paid-in capital + cumulative equity raised | C21: ='Assumptions'!$F$9+'Working Capital'!C30 -> 0 | D21: ='Assumptions'!$F$9+'Working Capital'!D30 -> 0 | E21: ='Assumptions'!$F$9+'Working Capital'!E30 -> 0 | F21: ='Assumptions'!$F$9+'Working Capital'!F30 -> 0 | G21: ='Assumptions'!$F$9+'Working Capital'!G30 -> 0 | H21: ='Assumptions'!$F$9+'Working Capital'!H30 -> 0 | I21: ='Assumptions'!$F$9+'Working Capital'!I30 -> 0 | J21: ='Assumptions'!$F$9+'Working Capital'!J30 -> 0 | ... AL21: ='Assumptions'!$F$9+'Working Capital'!AL30 -> 0 | AN21: =E21 -> 0 | AO21: =H21 -> 0 | AP21: =K21 -> 0 | AQ21: =N21 -> 0 | AR21: =Q21 -> 0 | AS21: =T21 -> 0 | AT21: =W21 -> 0 | AU21: =Z21 -> 0 | AV21: =AC21 -> 0 | AW21: =AF21 -> 0 | AX21: =AI21 -> 0 | AY21: =AL21 -> 0 | BA21: =N21 -> 0 | BB21: =Z21 -> 0 | BC21: =AL21 -> 0
A22: Retained Earnings | B22: Starting RE (= starting cash − starting paid-in capital) + cumulative Net Income | C22: =('Assumptions'!$F$8-'Assumptions'!$F$9)+'P&L'!C24 -> 0 | D22: =C22+'P&L'!D24 -> 0 | E22: =D22+'P&L'!E24 -> 0 | F22: =E22+'P&L'!F24 -> 0 | G22: =F22+'P&L'!G24 -> 0 | H22: =G22+'P&L'!H24 -> 0 | I22: =H22+'P&L'!I24 -> 0 | J22: =I22+'P&L'!J24 -> 0 | K22: =J22+'P&L'!K24 -> 0 | ... AL22: =AK22+'P&L'!AL24 -> 0 | AN22: =E22 -> 0 | AO22: =H22 -> 0 | AP22: =K22 -> 0 | AQ22: =N22 -> 0 | AR22: =Q22 -> 0 | AS22: =T22 -> 0 | AT22: =W22 -> 0 | AU22: =Z22 -> 0 | AV22: =AC22 -> 0 | AW22: =AF22 -> 0 | AX22: =AI22 -> 0 | AY22: =AL22 -> 0 | BA22: =N22 -> 0 | BB22: =Z22 -> 0 | BC22: =AL22 -> 0
A23: Total Equity | C23: =C21+C22 -> 0 | D23: =D21+D22 -> 0 | E23: =E21+E22 -> 0 | F23: =F21+F22 -> 0 | G23: =G21+G22 -> 0 | H23: =H21+H22 -> 0 | I23: =I21+I22 -> 0 | J23: =J21+J22 -> 0 | ... AL23: =AL21+AL22 -> 0 | AN23: =E23 -> 0 | AO23: =H23 -> 0 | AP23: =K23 -> 0 | AQ23: =N23 -> 0 | AR23: =Q23 -> 0 | AS23: =T23 -> 0 | AT23: =W23 -> 0 | AU23: =Z23 -> 0 | AV23: =AC23 -> 0 | AW23: =AF23 -> 0 | AX23: =AI23 -> 0 | AY23: =AL23 -> 0 | BA23: =N23 -> 0 | BB23: =Z23 -> 0 | BC23: =AL23 -> 0
A24: Total Liabilities + Equity | C24: =C18+C23 -> 0 | D24: =D18+D23 -> 0 | E24: =E18+E23 -> 0 | F24: =F18+F23 -> 0 | G24: =G18+G23 -> 0 | H24: =H18+H23 -> 0 | I24: =I18+I23 -> 0 | J24: =J18+J23 -> 0 | ... AL24: =AL18+AL23 -> 0 | AN24: =E24 -> 0 | AO24: =H24 -> 0 | AP24: =K24 -> 0 | AQ24: =N24 -> 0 | AR24: =Q24 -> 0 | AS24: =T24 -> 0 | AT24: =W24 -> 0 | AU24: =Z24 -> 0 | AV24: =AC24 -> 0 | AW24: =AF24 -> 0 | AX24: =AI24 -> 0 | AY24: =AL24 -> 0 | BA24: =N24 -> 0 | BB24: =Z24 -> 0 | BC24: =AL24 -> 0
A26: Balance check (Assets − Liab&Equity) | B26: Must equal ~0 every month | C26: =C12-C24 -> 0 | D26: =D12-D24 -> 0 | E26: =E12-E24 -> 0 | F26: =F12-F24 -> 0 | G26: =G12-G24 -> 0 | H26: =H12-H24 -> 0 | I26: =I12-I24 -> 0 | J26: =J12-J24 -> 0 | ... AL26: =AL12-AL24 -> 0 | AN26: =E26 -> 0 | AO26: =H26 -> 0 | AP26: =K26 -> 0 | AQ26: =N26 -> 0 | AR26: =Q26 -> 0 | AS26: =T26 -> 0 | AT26: =W26 -> 0 | AU26: =Z26 -> 0 | AV26: =AC26 -> 0 | AW26: =AF26 -> 0 | AX26: =AI26 -> 0 | AY26: =AL26 -> 0 | BA26: =N26 -> 0 | BB26: =Z26 -> 0 | BC26: =AL26 -> 0

Sheet Cash Flow
A1: Consumer Subscription — 3-Year Financial Model — Cash Flow
A2: Indirect method — Net Income reconciled to the change in cash.
A5: Line item | B5: Units / source | C5: Monthly (36 months) | AN5: Quarterly | BA5: Annual
C6: 46023 | D6: 46054 | E6: 46082 | F6: 46113 | G6: 46143 | H6: 46174 | I6: 46204 | J6: 46235 | K6: 46266 | L6: 46296 | M6: 46327 | N6: 46357 | O6: 46388 | P6: 46419 | Q6: 46447 | R6: 46478 | S6: 46508 | T6: 46539 | U6: 46569 | V6: 46600 | W6: 46631 | X6: 46661 | Y6: 46692 | Z6: 46722 | AA6: 46753 | AB6: 46784 | AC6: 46813 | AD6: 46844 | AE6: 46874 | AF6: 46905 | AG6: 46935 | AH6: 46966 | AI6: 46997 | AJ6: 47027 | AK6: 47058 | AL6: 47088 | AN6: Q1 | AO6: Q2 | AP6: Q3 | AQ6: Q4 | AR6: Q5 | AS6: Q6 | AT6: Q7 | AU6: Q8 | AV6: Q9 | AW6: Q10 | AX6: Q11 | AY6: Q12 | BA6: FY1 | BB6: FY2 | BC6: FY3
A7: Cash from Operations
A8: Net Income | C8: ='P&L'!$C$24 -> 0 | D8: ='P&L'!$D$24 -> 0 | E8: ='P&L'!$E$24 -> 0 | F8: ='P&L'!$F$24 -> 0 | G8: ='P&L'!$G$24 -> 0 | H8: ='P&L'!$H$24 -> 0 | I8: ='P&L'!$I$24 -> 0 | J8: ='P&L'!$J$24 -> 0 | K8: ='P&L'!$K$24 -> 0 | L8: ='P&L'!$L$24 -> 0 | M8: ='P&L'!$M$24 -> 0 | N8: ='P&L'!$N$24 -> 0 | O8: ='P&L'!$O$24 -> 0 | P8: ='P&L'!$P$24 -> 0 | Q8: ='P&L'!$Q$24 -> 0 | R8: ='P&L'!$R$24 -> 0 | S8: ='P&L'!$S$24 -> 0 | T8: ='P&L'!$T$24 -> 0 | U8: ='P&L'!$U$24 -> 0 | V8: ='P&L'!$V$24 -> 0 | W8: ='P&L'!$W$24 -> 0 | X8: ='P&L'!$X$24 -> 0 | Y8: ='P&L'!$Y$24 -> 0 | Z8: ='P&L'!$Z$24 -> 0 | AA8: ='P&L'!$AA$24 -> 0 | AB8: ='P&L'!$AB$24 -> 0 | AC8: ='P&L'!$AC$24 -> 0 | AD8: ='P&L'!$AD$24 -> 0 | AE8: ='P&L'!$AE$24 -> 0 | AF8: ='P&L'!$AF$24 -> 0 | AG8: ='P&L'!$AG$24 -> 0 | AH8: ='P&L'!$AH$24 -> 0 | AI8: ='P&L'!$AI$24 -> 0 | AJ8: ='P&L'!$AJ$24 -> 0 | AK8: ='P&L'!$AK$24 -> 0 | AL8: ='P&L'!$AL$24 -> 0 | AN8: =SUM(C8:E8) -> 0 | AO8: =SUM(F8:H8) -> 0 | AP8: =SUM(I8:K8) -> 0 | AQ8: =SUM(L8:N8) -> 0 | AR8: =SUM(O8:Q8) -> 0 | AS8: =SUM(R8:T8) -> 0 | AT8: =SUM(U8:W8) -> 0 | AU8: =SUM(X8:Z8) -> 0 | AV8: =SUM(AA8:AC8) -> 0 | AW8: =SUM(AD8:AF8) -> 0 | AX8: =SUM(AG8:AI8) -> 0 | AY8: =SUM(AJ8:AL8) -> 0 | BA8: =SUM(C8:N8) -> 0 | BB8: =SUM(O8:Z8) -> 0 | BC8: =SUM(AA8:AL8) -> 0
A9: + Depreciation & Amortization | C9: ='P&L'!$C$19 -> 0 | D9: ='P&L'!$D$19 -> 0 | E9: ='P&L'!$E$19 -> 0 | F9: ='P&L'!$F$19 -> 0 | G9: ='P&L'!$G$19 -> 0 | H9: ='P&L'!$H$19 -> 0 | I9: ='P&L'!$I$19 -> 0 | J9: ='P&L'!$J$19 -> 0 | K9: ='P&L'!$K$19 -> 0 | L9: ='P&L'!$L$19 -> 0 | M9: ='P&L'!$M$19 -> 0 | N9: ='P&L'!$N$19 -> 0 | O9: ='P&L'!$O$19 -> 0 | P9: ='P&L'!$P$19 -> 0 | Q9: ='P&L'!$Q$19 -> 0 | R9: ='P&L'!$R$19 -> 0 | S9: ='P&L'!$S$19 -> 0 | T9: ='P&L'!$T$19 -> 0 | U9: ='P&L'!$U$19 -> 0 | V9: ='P&L'!$V$19 -> 0 | W9: ='P&L'!$W$19 -> 0 | X9: ='P&L'!$X$19 -> 0 | Y9: ='P&L'!$Y$19 -> 0 | Z9: ='P&L'!$Z$19 -> 0 | AA9: ='P&L'!$AA$19 -> 0 | AB9: ='P&L'!$AB$19 -> 0 | AC9: ='P&L'!$AC$19 -> 0 | AD9: ='P&L'!$AD$19 -> 0 | AE9: ='P&L'!$AE$19 -> 0 | AF9: ='P&L'!$AF$19 -> 0 | AG9: ='P&L'!$AG$19 -> 0 | AH9: ='P&L'!$AH$19 -> 0 | AI9: ='P&L'!$AI$19 -> 0 | AJ9: ='P&L'!$AJ$19 -> 0 | AK9: ='P&L'!$AK$19 -> 0 | AL9: ='P&L'!$AL$19 -> 0 | AN9: =SUM(C9:E9) -> 0 | AO9: =SUM(F9:H9) -> 0 | AP9: =SUM(I9:K9) -> 0 | AQ9: =SUM(L9:N9) -> 0 | AR9: =SUM(O9:Q9) -> 0 | AS9: =SUM(R9:T9) -> 0 | AT9: =SUM(U9:W9) -> 0 | AU9: =SUM(X9:Z9) -> 0 | AV9: =SUM(AA9:AC9) -> 0 | AW9: =SUM(AD9:AF9) -> 0 | AX9: =SUM(AG9:AI9) -> 0 | AY9: =SUM(AJ9:AL9) -> 0 | BA9: =SUM(C9:N9) -> 0 | BB9: =SUM(O9:Z9) -> 0 | BC9: =SUM(AA9:AL9) -> 0
A10: − Change in Accounts Receivable | C10: =-'Working Capital'!C12 -> 0 | D10: =-'Working Capital'!D12 -> 0 | E10: =-'Working Capital'!E12 -> 0 | F10: =-'Working Capital'!F12 -> 0 | G10: =-'Working Capital'!G12 -> 0 | H10: =-'Working Capital'!H12 -> 0 | I10: =-'Working Capital'!I12 -> 0 | J10: =-'Working Capital'!J12 -> 0 | ... AL10: =-'Working Capital'!AL12 -> 0 | AN10: =SUM(C10:E10) -> 0 | AO10: =SUM(F10:H10) -> 0 | AP10: =SUM(I10:K10) -> 0 | AQ10: =SUM(L10:N10) -> 0 | AR10: =SUM(O10:Q10) -> 0 | AS10: =SUM(R10:T10) -> 0 | AT10: =SUM(U10:W10) -> 0 | AU10: =SUM(X10:Z10) -> 0 | AV10: =SUM(AA10:AC10) -> 0 | AW10: =SUM(AD10:AF10) -> 0 | AX10: =SUM(AG10:AI10) -> 0 | AY10: =SUM(AJ10:AL10) -> 0 | BA10: =SUM(C10:N10) -> 0 | BB10: =SUM(O10:Z10) -> 0 | BC10: =SUM(AA10:AL10) -> 0
A11: − Change in Other Current Assets | C11: =-'Working Capital'!C15 -> 0 | D11: =-'Working Capital'!D15 -> 0 | E11: =-'Working Capital'!E15 -> 0 | F11: =-'Working Capital'!F15 -> 0 | G11: =-'Working Capital'!G15 -> 0 | H11: =-'Working Capital'!H15 -> 0 | I11: =-'Working Capital'!I15 -> 0 | J11: =-'Working Capital'!J15 -> 0 | ... AL11: =-'Working Capital'!AL15 -> 0 | AN11: =SUM(C11:E11) -> 0 | AO11: =SUM(F11:H11) -> 0 | AP11: =SUM(I11:K11) -> 0 | AQ11: =SUM(L11:N11) -> 0 | AR11: =SUM(O11:Q11) -> 0 | AS11: =SUM(R11:T11) -> 0 | AT11: =SUM(U11:W11) -> 0 | AU11: =SUM(X11:Z11) -> 0 | AV11: =SUM(AA11:AC11) -> 0 | AW11: =SUM(AD11:AF11) -> 0 | AX11: =SUM(AG11:AI11) -> 0 | AY11: =SUM(AJ11:AL11) -> 0 | BA11: =SUM(C11:N11) -> 0 | BB11: =SUM(O11:Z11) -> 0 | BC11: =SUM(AA11:AL11) -> 0
A12: + Change in Accounts Payable | C12: ='Working Capital'!C13 -> 0 | D12: ='Working Capital'!D13 -> 0 | E12: ='Working Capital'!E13 -> 0 | F12: ='Working Capital'!F13 -> 0 | G12: ='Working Capital'!G13 -> 0 | H12: ='Working Capital'!H13 -> 0 | I12: ='Working Capital'!I13 -> 0 | J12: ='Working Capital'!J13 -> 0 | ... AL12: ='Working Capital'!AL13 -> 0 | AN12: =SUM(C12:E12) -> 0 | AO12: =SUM(F12:H12) -> 0 | AP12: =SUM(I12:K12) -> 0 | AQ12: =SUM(L12:N12) -> 0 | AR12: =SUM(O12:Q12) -> 0 | AS12: =SUM(R12:T12) -> 0 | AT12: =SUM(U12:W12) -> 0 | AU12: =SUM(X12:Z12) -> 0 | AV12: =SUM(AA12:AC12) -> 0 | AW12: =SUM(AD12:AF12) -> 0 | AX12: =SUM(AG12:AI12) -> 0 | AY12: =SUM(AJ12:AL12) -> 0 | BA12: =SUM(C12:N12) -> 0 | BB12: =SUM(O12:Z12) -> 0 | BC12: =SUM(AA12:AL12) -> 0
A13: + Change in Deferred Revenue | C13: ='Working Capital'!C14 -> 0 | D13: ='Working Capital'!D14 -> 0 | E13: ='Working Capital'!E14 -> 0 | F13: ='Working Capital'!F14 -> 0 | G13: ='Working Capital'!G14 -> 0 | H13: ='Working Capital'!H14 -> 0 | I13: ='Working Capital'!I14 -> 0 | J13: ='Working Capital'!J14 -> 0 | ... AL13: ='Working Capital'!AL14 -> 0 | AN13: =SUM(C13:E13) -> 0 | AO13: =SUM(F13:H13) -> 0 | AP13: =SUM(I13:K13) -> 0 | AQ13: =SUM(L13:N13) -> 0 | AR13: =SUM(O13:Q13) -> 0 | AS13: =SUM(R13:T13) -> 0 | AT13: =SUM(U13:W13) -> 0 | AU13: =SUM(X13:Z13) -> 0 | AV13: =SUM(AA13:AC13) -> 0 | AW13: =SUM(AD13:AF13) -> 0 | AX13: =SUM(AG13:AI13) -> 0 | AY13: =SUM(AJ13:AL13) -> 0 | BA13: =SUM(C13:N13) -> 0 | BB13: =SUM(O13:Z13) -> 0 | BC13: =SUM(AA13:AL13) -> 0
A14: Cash from Operations | C14: =C8+C9+C10+C11+C12+C13 -> 0 | D14: =D8+D9+D10+D11+D12+D13 -> 0 | E14: =E8+E9+E10+E11+E12+E13 -> 0 | F14: =F8+F9+F10+F11+F12+F13 -> 0 | G14: =G8+G9+G10+G11+G12+G13 -> 0 | H14: =H8+H9+H10+H11+H12+H13 -> 0 | I14: =I8+I9+I10+I11+I12+I13 -> 0 | J14: =J8+J9+J10+J11+J12+J13 -> 0 | ... AL14: =AL8+AL9+AL10+AL11+AL12+AL13 -> 0 | AN14: =SUM(C14:E14) -> 0 | AO14: =SUM(F14:H14) -> 0 | AP14: =SUM(I14:K14) -> 0 | AQ14: =SUM(L14:N14) -> 0 | AR14: =SUM(O14:Q14) -> 0 | AS14: =SUM(R14:T14) -> 0 | AT14: =SUM(U14:W14) -> 0 | AU14: =SUM(X14:Z14) -> 0 | AV14: =SUM(AA14:AC14) -> 0 | AW14: =SUM(AD14:AF14) -> 0 | AX14: =SUM(AG14:AI14) -> 0 | AY14: =SUM(AJ14:AL14) -> 0 | BA14: =SUM(C14:N14) -> 0 | BB14: =SUM(O14:Z14) -> 0 | BC14: =SUM(AA14:AL14) -> 0
A16: Cash from Investing
A17: − Capital Expenditures | C17: =-'Working Capital'!C18 -> 0 | D17: =-'Working Capital'!D18 -> 0 | E17: =-'Working Capital'!E18 -> 0 | F17: =-'Working Capital'!F18 -> 0 | G17: =-'Working Capital'!G18 -> 0 | H17: =-'Working Capital'!H18 -> 0 | I17: =-'Working Capital'!I18 -> 0 | J17: =-'Working Capital'!J18 -> 0 | ... AL17: =-'Working Capital'!AL18 -> 0 | AN17: =SUM(C17:E17) -> 0 | AO17: =SUM(F17:H17) -> 0 | AP17: =SUM(I17:K17) -> 0 | AQ17: =SUM(L17:N17) -> 0 | AR17: =SUM(O17:Q17) -> 0 | AS17: =SUM(R17:T17) -> 0 | AT17: =SUM(U17:W17) -> 0 | AU17: =SUM(X17:Z17) -> 0 | AV17: =SUM(AA17:AC17) -> 0 | AW17: =SUM(AD17:AF17) -> 0 | AX17: =SUM(AG17:AI17) -> 0 | AY17: =SUM(AJ17:AL17) -> 0 | BA17: =SUM(C17:N17) -> 0 | BB17: =SUM(O17:Z17) -> 0 | BC17: =SUM(AA17:AL17) -> 0
A18: Cash from Investing | C18: =C17 -> 0 | D18: =D17 -> 0 | E18: =E17 -> 0 | F18: =F17 -> 0 | G18: =G17 -> 0 | H18: =H17 -> 0 | I18: =I17 -> 0 | J18: =J17 -> 0 | ... AL18: =AL17 -> 0 | AN18: =SUM(C18:E18) -> 0 | AO18: =SUM(F18:H18) -> 0 | AP18: =SUM(I18:K18) -> 0 | AQ18: =SUM(L18:N18) -> 0 | AR18: =SUM(O18:Q18) -> 0 | AS18: =SUM(R18:T18) -> 0 | AT18: =SUM(U18:W18) -> 0 | AU18: =SUM(X18:Z18) -> 0 | AV18: =SUM(AA18:AC18) -> 0 | AW18: =SUM(AD18:AF18) -> 0 | AX18: =SUM(AG18:AI18) -> 0 | AY18: =SUM(AJ18:AL18) -> 0 | BA18: =SUM(C18:N18) -> 0 | BB18: =SUM(O18:Z18) -> 0 | BC18: =SUM(AA18:AL18) -> 0
A20: Cash from Financing
A21: + Debt Draw | C21: ='Working Capital'!C23 -> 0 | D21: ='Working Capital'!D23 -> 0 | E21: ='Working Capital'!E23 -> 0 | F21: ='Working Capital'!F23 -> 0 | G21: ='Working Capital'!G23 -> 0 | H21: ='Working Capital'!H23 -> 0 | I21: ='Working Capital'!I23 -> 0 | J21: ='Working Capital'!J23 -> 0 | ... AL21: ='Working Capital'!AL23 -> 0 | AN21: =SUM(C21:E21) -> 0 | AO21: =SUM(F21:H21) -> 0 | AP21: =SUM(I21:K21) -> 0 | AQ21: =SUM(L21:N21) -> 0 | AR21: =SUM(O21:Q21) -> 0 | AS21: =SUM(R21:T21) -> 0 | AT21: =SUM(U21:W21) -> 0 | AU21: =SUM(X21:Z21) -> 0 | AV21: =SUM(AA21:AC21) -> 0 | AW21: =SUM(AD21:AF21) -> 0 | AX21: =SUM(AG21:AI21) -> 0 | AY21: =SUM(AJ21:AL21) -> 0 | BA21: =SUM(C21:N21) -> 0 | BB21: =SUM(O21:Z21) -> 0 | BC21: =SUM(AA21:AL21) -> 0
A22: − Debt Repayment | C22: =-'Working Capital'!C24 -> 0 | D22: =-'Working Capital'!D24 -> 0 | E22: =-'Working Capital'!E24 -> 0 | F22: =-'Working Capital'!F24 -> 0 | G22: =-'Working Capital'!G24 -> 0 | H22: =-'Working Capital'!H24 -> 0 | I22: =-'Working Capital'!I24 -> 0 | J22: =-'Working Capital'!J24 -> 0 | ... AL22: =-'Working Capital'!AL24 -> 0 | AN22: =SUM(C22:E22) -> 0 | AO22: =SUM(F22:H22) -> 0 | AP22: =SUM(I22:K22) -> 0 | AQ22: =SUM(L22:N22) -> 0 | AR22: =SUM(O22:Q22) -> 0 | AS22: =SUM(R22:T22) -> 0 | AT22: =SUM(U22:W22) -> 0 | AU22: =SUM(X22:Z22) -> 0 | AV22: =SUM(AA22:AC22) -> 0 | AW22: =SUM(AD22:AF22) -> 0 | AX22: =SUM(AG22:AI22) -> 0 | AY22: =SUM(AJ22:AL22) -> 0 | BA22: =SUM(C22:N22) -> 0 | BB22: =SUM(O22:Z22) -> 0 | BC22: =SUM(AA22:AL22) -> 0
A23: + Equity Raised | C23: ='Working Capital'!C29 -> 0 | D23: ='Working Capital'!D29 -> 0 | E23: ='Working Capital'!E29 -> 0 | F23: ='Working Capital'!F29 -> 0 | G23: ='Working Capital'!G29 -> 0 | H23: ='Working Capital'!H29 -> 0 | I23: ='Working Capital'!I29 -> 0 | J23: ='Working Capital'!J29 -> 0 | ... AL23: ='Working Capital'!AL29 -> 0 | AN23: =SUM(C23:E23) -> 0 | AO23: =SUM(F23:H23) -> 0 | AP23: =SUM(I23:K23) -> 0 | AQ23: =SUM(L23:N23) -> 0 | AR23: =SUM(O23:Q23) -> 0 | AS23: =SUM(R23:T23) -> 0 | AT23: =SUM(U23:W23) -> 0 | AU23: =SUM(X23:Z23) -> 0 | AV23: =SUM(AA23:AC23) -> 0 | AW23: =SUM(AD23:AF23) -> 0 | AX23: =SUM(AG23:AI23) -> 0 | AY23: =SUM(AJ23:AL23) -> 0 | BA23: =SUM(C23:N23) -> 0 | BB23: =SUM(O23:Z23) -> 0 | BC23: =SUM(AA23:AL23) -> 0
A24: Cash from Financing | C24: =C21+C22+C23 -> 0 | D24: =D21+D22+D23 -> 0 | E24: =E21+E22+E23 -> 0 | F24: =F21+F22+F23 -> 0 | G24: =G21+G22+G23 -> 0 | H24: =H21+H22+H23 -> 0 | I24: =I21+I22+I23 -> 0 | J24: =J21+J22+J23 -> 0 | ... AL24: =AL21+AL22+AL23 -> 0 | AN24: =SUM(C24:E24) -> 0 | AO24: =SUM(F24:H24) -> 0 | AP24: =SUM(I24:K24) -> 0 | AQ24: =SUM(L24:N24) -> 0 | AR24: =SUM(O24:Q24) -> 0 | AS24: =SUM(R24:T24) -> 0 | AT24: =SUM(U24:W24) -> 0 | AU24: =SUM(X24:Z24) -> 0 | AV24: =SUM(AA24:AC24) -> 0 | AW24: =SUM(AD24:AF24) -> 0 | AX24: =SUM(AG24:AI24) -> 0 | AY24: =SUM(AJ24:AL24) -> 0 | BA24: =SUM(C24:N24) -> 0 | BB24: =SUM(O24:Z24) -> 0 | BC24: =SUM(AA24:AL24) -> 0
A26: Net Change in Cash | C26: =C14+C18+C24 -> 0 | D26: =D14+D18+D24 -> 0 | E26: =E14+E18+E24 -> 0 | F26: =F14+F18+F24 -> 0 | G26: =G14+G18+G24 -> 0 | H26: =H14+H18+H24 -> 0 | I26: =I14+I18+I24 -> 0 | J26: =J14+J18+J24 -> 0 | ... AL26: =AL14+AL18+AL24 -> 0 | AN26: =SUM(C26:E26) -> 0 | AO26: =SUM(F26:H26) -> 0 | AP26: =SUM(I26:K26) -> 0 | AQ26: =SUM(L26:N26) -> 0 | AR26: =SUM(O26:Q26) -> 0 | AS26: =SUM(R26:T26) -> 0 | AT26: =SUM(U26:W26) -> 0 | AU26: =SUM(X26:Z26) -> 0 | AV26: =SUM(AA26:AC26) -> 0 | AW26: =SUM(AD26:AF26) -> 0 | AX26: =SUM(AG26:AI26) -> 0 | AY26: =SUM(AJ26:AL26) -> 0 | BA26: =SUM(C26:N26) -> 0 | BB26: =SUM(O26:Z26) -> 0 | BC26: =SUM(AA26:AL26) -> 0
A27: Beginning Cash | B27: Prior month ending cash (or starting cash in month 1) | C27: ='Assumptions'!$F$8 -> 0 | D27: =C28 -> 0 | E27: =D28 -> 0 | F27: =E28 -> 0 | G27: =F28 -> 0 | H27: =G28 -> 0 | I27: =H28 -> 0 | J27: =I28 -> 0 | K27: =J28 -> 0 | ... AL27: =AK28 -> 0 | AN27: =C27 -> 0 | AO27: =F27 -> 0 | AP27: =I27 -> 0 | AQ27: =L27 -> 0 | AR27: =O27 -> 0 | AS27: =R27 -> 0 | AT27: =U27 -> 0 | AU27: =X27 -> 0 | AV27: =AA27 -> 0 | AW27: =AD27 -> 0 | AX27: =AG27 -> 0 | AY27: =AJ27 -> 0 | BA27: =C27 -> 0 | BB27: =O27 -> 0 | BC27: =AA27 -> 0
A28: Ending Cash | B28: Beginning cash + net change in cash | C28: =C27+C26 -> 0 | D28: =D27+D26 -> 0 | E28: =E27+E26 -> 0 | F28: =F27+F26 -> 0 | G28: =G27+G26 -> 0 | H28: =H27+H26 -> 0 | I28: =I27+I26 -> 0 | J28: =J27+J26 -> 0 | ... AL28: =AL27+AL26 -> 0 | AN28: =E28 -> 0 | AO28: =H28 -> 0 | AP28: =K28 -> 0 | AQ28: =N28 -> 0 | AR28: =Q28 -> 0 | AS28: =T28 -> 0 | AT28: =W28 -> 0 | AU28: =Z28 -> 0 | AV28: =AC28 -> 0 | AW28: =AF28 -> 0 | AX28: =AI28 -> 0 | AY28: =AL28 -> 0 | BA28: =N28 -> 0 | BB28: =Z28 -> 0 | BC28: =AL28 -> 0

Sheet Cash & Runway
A1: Consumer Subscription — 3-Year Financial Model — Cash & Runway
A2: Burn rate and runway — reconciled to the Cash Flow tab.
A5: Line item | B5: Units / source | C5: Monthly (36 months) | AN5: Quarterly | BA5: Annual
C6: 46023 | D6: 46054 | E6: 46082 | F6: 46113 | G6: 46143 | H6: 46174 | I6: 46204 | J6: 46235 | K6: 46266 | L6: 46296 | M6: 46327 | N6: 46357 | O6: 46388 | P6: 46419 | Q6: 46447 | R6: 46478 | S6: 46508 | T6: 46539 | U6: 46569 | V6: 46600 | W6: 46631 | X6: 46661 | Y6: 46692 | Z6: 46722 | AA6: 46753 | AB6: 46784 | AC6: 46813 | AD6: 46844 | AE6: 46874 | AF6: 46905 | AG6: 46935 | AH6: 46966 | AI6: 46997 | AJ6: 47027 | AK6: 47058 | AL6: 47088 | AN6: Q1 | AO6: Q2 | AP6: Q3 | AQ6: Q4 | AR6: Q5 | AS6: Q6 | AT6: Q7 | AU6: Q8 | AV6: Q9 | AW6: Q10 | AX6: Q11 | AY6: Q12 | BA6: FY1 | BB6: FY2 | BC6: FY3
A7: Cash Position
A8: Ending Cash Balance | C8: ='Cash Flow'!$C$28 -> 0 | D8: ='Cash Flow'!$D$28 -> 0 | E8: ='Cash Flow'!$E$28 -> 0 | F8: ='Cash Flow'!$F$28 -> 0 | G8: ='Cash Flow'!$G$28 -> 0 | H8: ='Cash Flow'!$H$28 -> 0 | I8: ='Cash Flow'!$I$28 -> 0 | J8: ='Cash Flow'!$J$28 -> 0 | K8: ='Cash Flow'!$K$28 -> 0 | L8: ='Cash Flow'!$L$28 -> 0 | M8: ='Cash Flow'!$M$28 -> 0 | N8: ='Cash Flow'!$N$28 -> 0 | O8: ='Cash Flow'!$O$28 -> 0 | P8: ='Cash Flow'!$P$28 -> 0 | Q8: ='Cash Flow'!$Q$28 -> 0 | R8: ='Cash Flow'!$R$28 -> 0 | S8: ='Cash Flow'!$S$28 -> 0 | T8: ='Cash Flow'!$T$28 -> 0 | U8: ='Cash Flow'!$U$28 -> 0 | V8: ='Cash Flow'!$V$28 -> 0 | W8: ='Cash Flow'!$W$28 -> 0 | X8: ='Cash Flow'!$X$28 -> 0 | Y8: ='Cash Flow'!$Y$28 -> 0 | Z8: ='Cash Flow'!$Z$28 -> 0 | AA8: ='Cash Flow'!$AA$28 -> 0 | AB8: ='Cash Flow'!$AB$28 -> 0 | AC8: ='Cash Flow'!$AC$28 -> 0 | AD8: ='Cash Flow'!$AD$28 -> 0 | AE8: ='Cash Flow'!$AE$28 -> 0 | AF8: ='Cash Flow'!$AF$28 -> 0 | AG8: ='Cash Flow'!$AG$28 -> 0 | AH8: ='Cash Flow'!$AH$28 -> 0 | AI8: ='Cash Flow'!$AI$28 -> 0 | AJ8: ='Cash Flow'!$AJ$28 -> 0 | AK8: ='Cash Flow'!$AK$28 -> 0 | AL8: ='Cash Flow'!$AL$28 -> 0 | AN8: =E8 -> 0 | AO8: =H8 -> 0 | AP8: =K8 -> 0 | AQ8: =N8 -> 0 | AR8: =Q8 -> 0 | AS8: =T8 -> 0 | AT8: =W8 -> 0 | AU8: =Z8 -> 0 | AV8: =AC8 -> 0 | AW8: =AF8 -> 0 | AX8: =AI8 -> 0 | AY8: =AL8 -> 0 | BA8: =N8 -> 0 | BB8: =Z8 -> 0 | BC8: =AL8 -> 0
A9: Monthly Net Burn (pre-financing) | B9: MAX(0, −(operating + investing cash flow)); excludes debt and equity proceeds | C9: =MAX(0,-('Cash Flow'!C14+'Cash Flow'!C18)) -> 0 | D9: =MAX(0,-('Cash Flow'!D14+'Cash Flow'!D18)) -> 0 | E9: =MAX(0,-('Cash Flow'!E14+'Cash Flow'!E18)) -> 0 | F9: =MAX(0,-('Cash Flow'!F14+'Cash Flow'!F18)) -> 0 | G9: =MAX(0,-('Cash Flow'!G14+'Cash Flow'!G18)) -> 0 | H9: =MAX(0,-('Cash Flow'!H14+'Cash Flow'!H18)) -> 0 | I9: =MAX(0,-('Cash Flow'!I14+'Cash Flow'!I18)) -> 0 | J9: =MAX(0,-('Cash Flow'!J14+'Cash Flow'!J18)) -> 0 | ... AL9: =MAX(0,-('Cash Flow'!AL14+'Cash Flow'!AL18)) -> 0 | AN9: =SUM(C9:E9) -> 0 | AO9: =SUM(F9:H9) -> 0 | AP9: =SUM(I9:K9) -> 0 | AQ9: =SUM(L9:N9) -> 0 | AR9: =SUM(O9:Q9) -> 0 | AS9: =SUM(R9:T9) -> 0 | AT9: =SUM(U9:W9) -> 0 | AU9: =SUM(X9:Z9) -> 0 | AV9: =SUM(AA9:AC9) -> 0 | AW9: =SUM(AD9:AF9) -> 0 | AX9: =SUM(AG9:AI9) -> 0 | AY9: =SUM(AJ9:AL9) -> 0 | BA9: =SUM(C9:N9) -> 0 | BB9: =SUM(O9:Z9) -> 0 | BC9: =SUM(AA9:AL9) -> 0
A10: Trailing 3-Month Avg Burn | C10: =AVERAGE(C9:C9) -> 0 | D10: =AVERAGE(C9:D9) -> 0 | E10: =AVERAGE(C9:E9) -> 0 | F10: =AVERAGE(D9:F9) -> 0 | G10: =AVERAGE(E9:G9) -> 0 | H10: =AVERAGE(F9:H9) -> 0 | I10: =AVERAGE(G9:I9) -> 0 | J10: =AVERAGE(H9:J9) -> 0 | K10: =AVERAGE(I9:K9) -> 0 | L10: =AVERAGE(J9:L9) -> 0 | ... AL10: =AVERAGE(AJ9:AL9) -> 0 | AN10: =AVERAGE(C10:E10) -> 0 | AO10: =AVERAGE(F10:H10) -> 0 | AP10: =AVERAGE(I10:K10) -> 0 | AQ10: =AVERAGE(L10:N10) -> 0 | AR10: =AVERAGE(O10:Q10) -> 0 | AS10: =AVERAGE(R10:T10) -> 0 | AT10: =AVERAGE(U10:W10) -> 0 | AU10: =AVERAGE(X10:Z10) -> 0 | AV10: =AVERAGE(AA10:AC10) -> 0 | AW10: =AVERAGE(AD10:AF10) -> 0 | AX10: =AVERAGE(AG10:AI10) -> 0 | AY10: =AVERAGE(AJ10:AL10) -> 0 | BA10: =AVERAGE(C10:N10) -> 0 | BB10: =AVERAGE(O10:Z10) -> 0 | BC10: =AVERAGE(AA10:AL10) -> 0
A11: Runway (months) | B11: Ending cash ÷ trailing 3-month pre-financing burn; 0 if cash is depleted; 999 if cash-flow positive | C11: =IF(C8<=0,0,IF(C10<=0,999,C8/C10)) -> 0 | D11: =IF(D8<=0,0,IF(D10<=0,999,D8/D10)) -> 0 | E11: =IF(E8<=0,0,IF(E10<=0,999,E8/E10)) -> 0 | F11: =IF(F8<=0,0,IF(F10<=0,999,F8/F10)) -> 0 | G11: =IF(G8<=0,0,IF(G10<=0,999,G8/G10)) -> 0 | H11: =IF(H8<=0,0,IF(H10<=0,999,H8/H10)) -> 0 | I11: =IF(I8<=0,0,IF(I10<=0,999,I8/I10)) -> 0 | J11: =IF(J8<=0,0,IF(J10<=0,999,J8/J10)) -> 0 | ... AL11: =IF(AL8<=0,0,IF(AL10<=0,999,AL8/AL10)) -> 0 | AN11: =E11 -> 0 | AO11: =H11 -> 0 | AP11: =K11 -> 0 | AQ11: =N11 -> 0 | AR11: =Q11 -> 0 | AS11: =T11 -> 0 | AT11: =W11 -> 0 | AU11: =Z11 -> 0 | AV11: =AC11 -> 0 | AW11: =AF11 -> 0 | AX11: =AI11 -> 0 | AY11: =AL11 -> 0 | BA11: =N11 -> 0 | BB11: =Z11 -> 0 | BC11: =AL11 -> 0
A13: Headline
A14: Runway as of final month (36) | C14: =IF(AL8<=0,0,IF(AL10<=0,"Cash-flow positive",AL11)) -> 0

Sheet Scenarios
A1: Consumer Subscription — 3-Year Financial Model — Scenario Comparison
A2: Base/Upside/Downside columns are a fast analytical approximation for side-by-side comparison. The 'Full model' column reflects the detailed 36-month model at the scenario currently selected on the Assumptions tab.
A4: Currently selected scenario: | C4: ='Assumptions'!$C$4 -> 0
A6: KPI | B6: Definition | C6: Base | D6: Upside | E6: Downside | F6: Full model (selected)
A7: Revenue run-rate (Month 1 x 12) | B7: Month-1 subscription revenue annualized as a simple ARR-equivalent headline. | C7: =((('Assumptions'!$C$15*(1-'Assumptions'!$C$28))+((MAX(0,('Assumptions'!$C$13+('Assumptions'!$C$16+'Assumptions'!$C$19+'Assumptions'!$C$22)-'Assumptions'!$C$13*'Assumptions'!$C$14)-('Assumptions'!$C$15*(1-'Assumptions'!$C$28))))*'Assumptions'!$C$27))*('Assumptions'!$C$29*(1-'Assumptions'!$C$31)+'Assumptions'!$C$30*'Assumptions'!$C$31))*12 -> 0 | D7: =((('Assumptions'!$D$15*(1-'Assumptions'!$D$28))+((MAX(0,('Assumptions'!$D$13+('Assumptions'!$D$16+'Assumptions'!$D$19+'Assumptions'!$D$22)-'Assumptions'!$D$13*'Assumptions'!$D$14)-('Assumptions'!$D$15*(1-'Assumptions'!$D$28))))*'Assumptions'!$D$27))*('Assumptions'!$D$29*(1-'Assumptions'!$D$31)+'Assumptions'!$D$30*'Assumptions'!$D$31))*12 -> 0 | E7: =((('Assumptions'!$E$15*(1-'Assumptions'!$E$28))+((MAX(0,('Assumptions'!$E$13+('Assumptions'!$E$16+'Assumptions'!$E$19+'Assumptions'!$E$22)-'Assumptions'!$E$13*'Assumptions'!$E$14)-('Assumptions'!$E$15*(1-'Assumptions'!$E$28))))*'Assumptions'!$E$27))*('Assumptions'!$E$29*(1-'Assumptions'!$E$31)+'Assumptions'!$E$30*'Assumptions'!$E$31))*12 -> 0 | F7: ='Revenue'!C35*12 -> 0
A8: Paid retention % (illustrative) | B8: 1 − monthly paid subscriber churn rate. | C8: =1-'Assumptions'!$C$28 -> 0 | D8: =1-'Assumptions'!$D$28 -> 0 | E8: =1-'Assumptions'!$E$28 -> 0 | F8: ='Revenue'!C41 -> 0
A9: Implied Revenue at Month 36 (approx.) | B9: Month-1 revenue compounded at an illustrative blended paid-user growth trend for 35 more months. | C9: =((('Assumptions'!$C$15*(1-'Assumptions'!$C$28))+((MAX(0,('Assumptions'!$C$13+('Assumptions'!$C$16+'Assumptions'!$C$19+'Assumptions'!$C$22)-'Assumptions'!$C$13*'Assumptions'!$C$14)-('Assumptions'!$C$15*(1-'Assumptions'!$C$28))))*'Assumptions'!$C$27))*('Assumptions'!$C$29*(1-'Assumptions'!$C$31)+'Assumptions'!$C$30*'Assumptions'!$C$31))*(1+(('Assumptions'!$C$17+'Assumptions'!$C$20+'Assumptions'!$C$23)/3)+'Assumptions'!$C$27*0.35-'Assumptions'!$C$28+'Assumptions'!$C$32*0.5)^35 -> 0 | D9: =((('Assumptions'!$D$15*(1-'Assumptions'!$D$28))+((MAX(0,('Assumptions'!$D$13+('Assumptions'!$D$16+'Assumptions'!$D$19+'Assumptions'!$D$22)-'Assumptions'!$D$13*'Assumptions'!$D$14)-('Assumptions'!$D$15*(1-'Assumptions'!$D$28))))*'Assumptions'!$D$27))*('Assumptions'!$D$29*(1-'Assumptions'!$D$31)+'Assumptions'!$D$30*'Assumptions'!$D$31))*(1+(('Assumptions'!$D$17+'Assumptions'!$D$20+'Assumptions'!$D$23)/3)+'Assumptions'!$D$27*0.35-'Assumptions'!$D$28+'Assumptions'!$D$32*0.5)^35 -> 0 | E9: =((('Assumptions'!$E$15*(1-'Assumptions'!$E$28))+((MAX(0,('Assumptions'!$E$13+('Assumptions'!$E$16+'Assumptions'!$E$19+'Assumptions'!$E$22)-'Assumptions'!$E$13*'Assumptions'!$E$14)-('Assumptions'!$E$15*(1-'Assumptions'!$E$28))))*'Assumptions'!$E$27))*('Assumptions'!$E$29*(1-'Assumptions'!$E$31)+'Assumptions'!$E$30*'Assumptions'!$E$31))*(1+(('Assumptions'!$E$17+'Assumptions'!$E$20+'Assumptions'!$E$23)/3)+'Assumptions'!$E$27*0.35-'Assumptions'!$E$28+'Assumptions'!$E$32*0.5)^35 -> 0 | F9: ='Revenue'!AL35 -> 0
A10: Gross Margin % (illustrative, Month 1) | B10: Month-1 revenue less platform fees, hosting, AI inference, and support people cost. | C10: =IFERROR((((('Assumptions'!$C$15*(1-'Assumptions'!$C$28))+((MAX(0,('Assumptions'!$C$13+('Assumptions'!$C$16+'Assumptions'!$C$19+'Assumptions'!$C$22)-'Assumptions'!$C$13*'Assumptions'!$C$14)-('Assumptions'!$C$15*(1-'Assumptions'!$C$28))))*'Assumptions'!$C$27))*('Assumptions'!$C$29*(1-'Assumptions'!$C$31)+'Assumptions'!$C$30*'Assumptions'!$C$31))-(((('Assumptions'!$C$15*(1-'Assumptions'!$C$28))+((MAX(0,('Assumptions'!$C$13+('Assumptions'!$C$16+'Assumptions'!$C$19+'Assumptions'!$C$22)-'Assumptions'!$C$13*'Assumptions'!$C$14)-('Assumptions'!$C$15*(1-'Assumptions'!$C$28))))*'Assumptions'!$C$27))*('Assumptions'!$C$29*(1-'Assumptions'!$C$31)+'Assumptions'!$C$30*'Assumptions'!$C$31))*('Assumptions'!$C$35+'Assumptions'!$C$36)+('Assumptions'!$C$13+('Assumptions'!$C$16+'Assumptions'!$C$19+'Assumptions'!$C$22)-'Assumptions'!$C$13*'Assumptions'!$C$14)*'Assumptions'!$C$37+(('Assumptions'!$C$15*(1-'Assumptions'!$C$28))+((MAX(0,('Assumptions'!$C$13+('Assumptions'!$C$16+'Assumptions'!$C$19+'Assumptions'!$C$22)-'Assumptions'!$C$13*'Assumptions'!$C$14)-('Assumptions'!$C$15*(1-'Assumptions'!$C$28))))*'Assumptions'!$C$27))*'Assumptions'!$C$38+('Assumptions'!$C$41*'Assumptions'!$C$43)))/((('Assumptions'!$C$15*(1-'Assumptions'!$C$28))+((MAX(0,('Assumptions'!$C$13+('Assumptions'!$C$16+'Assumptions'!$C$19+'Assumptions'!$C$22)-'Assumptions'!$C$13*'Assumptions'!$C$14)-('Assumptions'!$C$15*(1-'Assumptions'!$C$28))))*'Assumptions'!$C$27))*('Assumptions'!$C$29*(1-'Assumptions'!$C$31)+'Assumptions'!$C$30*'Assumptions'!$C$31)),0) -> 0 | D10: =IFERROR((((('Assumptions'!$D$15*(1-'Assumptions'!$D$28))+((MAX(0,('Assumptions'!$D$13+('Assumptions'!$D$16+'Assumptions'!$D$19+'Assumptions'!$D$22)-'Assumptions'!$D$13*'Assumptions'!$D$14)-('Assumptions'!$D$15*(1-'Assumptions'!$D$28))))*'Assumptions'!$D$27))*('Assumptions'!$D$29*(1-'Assumptions'!$D$31)+'Assumptions'!$D$30*'Assumptions'!$D$31))-(((('Assumptions'!$D$15*(1-'Assumptions'!$D$28))+((MAX(0,('Assumptions'!$D$13+('Assumptions'!$D$16+'Assumptions'!$D$19+'Assumptions'!$D$22)-'Assumptions'!$D$13*'Assumptions'!$D$14)-('Assumptions'!$D$15*(1-'Assumptions'!$D$28))))*'Assumptions'!$D$27))*('Assumptions'!$D$29*(1-'Assumptions'!$D$31)+'Assumptions'!$D$30*'Assumptions'!$D$31))*('Assumptions'!$D$35+'Assumptions'!$D$36)+('Assumptions'!$D$13+('Assumptions'!$D$16+'Assumptions'!$D$19+'Assumptions'!$D$22)-'Assumptions'!$D$13*'Assumptions'!$D$14)*'Assumptions'!$D$37+(('Assumptions'!$D$15*(1-'Assumptions'!$D$28))+((MAX(0,('Assumptions'!$D$13+('Assumptions'!$D$16+'Assumptions'!$D$19+'Assumptions'!$D$22)-'Assumptions'!$D$13*'Assumptions'!$D$14)-('Assumptions'!$D$15*(1-'Assumptions'!$D$28))))*'Assumptions'!$D$27))*'Assumptions'!$D$38+('Assumptions'!$D$41*'Assumptions'!$D$43)))/((('Assumptions'!$D$15*(1-'Assumptions'!$D$28))+((MAX(0,('Assumptions'!$D$13+('Assumptions'!$D$16+'Assumptions'!$D$19+'Assumptions'!$D$22)-'Assumptions'!$D$13*'Assumptions'!$D$14)-('Assumptions'!$D$15*(1-'Assumptions'!$D$28))))*'Assumptions'!$D$27))*('Assumptions'!$D$29*(1-'Assumptions'!$D$31)+'Assumptions'!$D$30*'Assumptions'!$D$31)),0) -> 0 | E10: =IFERROR((((('Assumptions'!$E$15*(1-'Assumptions'!$E$28))+((MAX(0,('Assumptions'!$E$13+('Assumptions'!$E$16+'Assumptions'!$E$19+'Assumptions'!$E$22)-'Assumptions'!$E$13*'Assumptions'!$E$14)-('Assumptions'!$E$15*(1-'Assumptions'!$E$28))))*'Assumptions'!$E$27))*('Assumptions'!$E$29*(1-'Assumptions'!$E$31)+'Assumptions'!$E$30*'Assumptions'!$E$31))-(((('Assumptions'!$E$15*(1-'Assumptions'!$E$28))+((MAX(0,('Assumptions'!$E$13+('Assumptions'!$E$16+'Assumptions'!$E$19+'Assumptions'!$E$22)-'Assumptions'!$E$13*'Assumptions'!$E$14)-('Assumptions'!$E$15*(1-'Assumptions'!$E$28))))*'Assumptions'!$E$27))*('Assumptions'!$E$29*(1-'Assumptions'!$E$31)+'Assumptions'!$E$30*'Assumptions'!$E$31))*('Assumptions'!$E$35+'Assumptions'!$E$36)+('Assumptions'!$E$13+('Assumptions'!$E$16+'Assumptions'!$E$19+'Assumptions'!$E$22)-'Assumptions'!$E$13*'Assumptions'!$E$14)*'Assumptions'!$E$37+(('Assumptions'!$E$15*(1-'Assumptions'!$E$28))+((MAX(0,('Assumptions'!$E$13+('Assumptions'!$E$16+'Assumptions'!$E$19+'Assumptions'!$E$22)-'Assumptions'!$E$13*'Assumptions'!$E$14)-('Assumptions'!$E$15*(1-'Assumptions'!$E$28))))*'Assumptions'!$E$27))*'Assumptions'!$E$38+('Assumptions'!$E$41*'Assumptions'!$E$43)))/((('Assumptions'!$E$15*(1-'Assumptions'!$E$28))+((MAX(0,('Assumptions'!$E$13+('Assumptions'!$E$16+'Assumptions'!$E$19+'Assumptions'!$E$22)-'Assumptions'!$E$13*'Assumptions'!$E$14)-('Assumptions'!$E$15*(1-'Assumptions'!$E$28))))*'Assumptions'!$E$27))*('Assumptions'!$E$29*(1-'Assumptions'!$E$31)+'Assumptions'!$E$30*'Assumptions'!$E$31)),0) -> 0 | F10: ='COGS & GM'!C17 -> 0
A11: Month-1 Net Burn (illustrative) | B11: Month-1 COGS + Opex less revenue; floored at zero. | C11: =MAX(0,(((('Assumptions'!$C$15*(1-'Assumptions'!$C$28))+((MAX(0,('Assumptions'!$C$13+('Assumptions'!$C$16+'Assumptions'!$C$19+'Assumptions'!$C$22)-'Assumptions'!$C$13*'Assumptions'!$C$14)-('Assumptions'!$C$15*(1-'Assumptions'!$C$28))))*'Assumptions'!$C$27))*('Assumptions'!$C$29*(1-'Assumptions'!$C$31)+'Assumptions'!$C$30*'Assumptions'!$C$31))*('Assumptions'!$C$35+'Assumptions'!$C$36)+('Assumptions'!$C$13+('Assumptions'!$C$16+'Assumptions'!$C$19+'Assumptions'!$C$22)-'Assumptions'!$C$13*'Assumptions'!$C$14)*'Assumptions'!$C$37+(('Assumptions'!$C$15*(1-'Assumptions'!$C$28))+((MAX(0,('Assumptions'!$C$13+('Assumptions'!$C$16+'Assumptions'!$C$19+'Assumptions'!$C$22)-'Assumptions'!$C$13*'Assumptions'!$C$14)-('Assumptions'!$C$15*(1-'Assumptions'!$C$28))))*'Assumptions'!$C$27))*'Assumptions'!$C$38+('Assumptions'!$C$41*'Assumptions'!$C$43))+('Assumptions'!$C$46*'Assumptions'!$C$48+'Assumptions'!$C$51*'Assumptions'!$C$53+'Assumptions'!$C$56*'Assumptions'!$C$58)+((('Assumptions'!$C$16*'Assumptions'!$C$18+'Assumptions'!$C$19*'Assumptions'!$C$21+'Assumptions'!$C$22*'Assumptions'!$C$24))+'Assumptions'!$C$61+'Assumptions'!$C$62+'Assumptions'!$C$63)-((('Assumptions'!$C$15*(1-'Assumptions'!$C$28))+((MAX(0,('Assumptions'!$C$13+('Assumptions'!$C$16+'Assumptions'!$C$19+'Assumptions'!$C$22)-'Assumptions'!$C$13*'Assumptions'!$C$14)-('Assumptions'!$C$15*(1-'Assumptions'!$C$28))))*'Assumptions'!$C$27))*('Assumptions'!$C$29*(1-'Assumptions'!$C$31)+'Assumptions'!$C$30*'Assumptions'!$C$31))) -> 0 | D11: =MAX(0,(((('Assumptions'!$D$15*(1-'Assumptions'!$D$28))+((MAX(0,('Assumptions'!$D$13+('Assumptions'!$D$16+'Assumptions'!$D$19+'Assumptions'!$D$22)-'Assumptions'!$D$13*'Assumptions'!$D$14)-('Assumptions'!$D$15*(1-'Assumptions'!$D$28))))*'Assumptions'!$D$27))*('Assumptions'!$D$29*(1-'Assumptions'!$D$31)+'Assumptions'!$D$30*'Assumptions'!$D$31))*('Assumptions'!$D$35+'Assumptions'!$D$36)+('Assumptions'!$D$13+('Assumptions'!$D$16+'Assumptions'!$D$19+'Assumptions'!$D$22)-'Assumptions'!$D$13*'Assumptions'!$D$14)*'Assumptions'!$D$37+(('Assumptions'!$D$15*(1-'Assumptions'!$D$28))+((MAX(0,('Assumptions'!$D$13+('Assumptions'!$D$16+'Assumptions'!$D$19+'Assumptions'!$D$22)-'Assumptions'!$D$13*'Assumptions'!$D$14)-('Assumptions'!$D$15*(1-'Assumptions'!$D$28))))*'Assumptions'!$D$27))*'Assumptions'!$D$38+('Assumptions'!$D$41*'Assumptions'!$D$43))+('Assumptions'!$D$46*'Assumptions'!$D$48+'Assumptions'!$D$51*'Assumptions'!$D$53+'Assumptions'!$D$56*'Assumptions'!$D$58)+((('Assumptions'!$D$16*'Assumptions'!$D$18+'Assumptions'!$D$19*'Assumptions'!$D$21+'Assumptions'!$D$22*'Assumptions'!$D$24))+'Assumptions'!$D$61+'Assumptions'!$D$62+'Assumptions'!$D$63)-((('Assumptions'!$D$15*(1-'Assumptions'!$D$28))+((MAX(0,('Assumptions'!$D$13+('Assumptions'!$D$16+'Assumptions'!$D$19+'Assumptions'!$D$22)-'Assumptions'!$D$13*'Assumptions'!$D$14)-('Assumptions'!$D$15*(1-'Assumptions'!$D$28))))*'Assumptions'!$D$27))*('Assumptions'!$D$29*(1-'Assumptions'!$D$31)+'Assumptions'!$D$30*'Assumptions'!$D$31))) -> 0 | E11: =MAX(0,(((('Assumptions'!$E$15*(1-'Assumptions'!$E$28))+((MAX(0,('Assumptions'!$E$13+('Assumptions'!$E$16+'Assumptions'!$E$19+'Assumptions'!$E$22)-'Assumptions'!$E$13*'Assumptions'!$E$14)-('Assumptions'!$E$15*(1-'Assumptions'!$E$28))))*'Assumptions'!$E$27))*('Assumptions'!$E$29*(1-'Assumptions'!$E$31)+'Assumptions'!$E$30*'Assumptions'!$E$31))*('Assumptions'!$E$35+'Assumptions'!$E$36)+('Assumptions'!$E$13+('Assumptions'!$E$16+'Assumptions'!$E$19+'Assumptions'!$E$22)-'Assumptions'!$E$13*'Assumptions'!$E$14)*'Assumptions'!$E$37+(('Assumptions'!$E$15*(1-'Assumptions'!$E$28))+((MAX(0,('Assumptions'!$E$13+('Assumptions'!$E$16+'Assumptions'!$E$19+'Assumptions'!$E$22)-'Assumptions'!$E$13*'Assumptions'!$E$14)-('Assumptions'!$E$15*(1-'Assumptions'!$E$28))))*'Assumptions'!$E$27))*'Assumptions'!$E$38+('Assumptions'!$E$41*'Assumptions'!$E$43))+('Assumptions'!$E$46*'Assumptions'!$E$48+'Assumptions'!$E$51*'Assumptions'!$E$53+'Assumptions'!$E$56*'Assumptions'!$E$58)+((('Assumptions'!$E$16*'Assumptions'!$E$18+'Assumptions'!$E$19*'Assumptions'!$E$21+'Assumptions'!$E$22*'Assumptions'!$E$24))+'Assumptions'!$E$61+'Assumptions'!$E$62+'Assumptions'!$E$63)-((('Assumptions'!$E$15*(1-'Assumptions'!$E$28))+((MAX(0,('Assumptions'!$E$13+('Assumptions'!$E$16+'Assumptions'!$E$19+'Assumptions'!$E$22)-'Assumptions'!$E$13*'Assumptions'!$E$14)-('Assumptions'!$E$15*(1-'Assumptions'!$E$28))))*'Assumptions'!$E$27))*('Assumptions'!$E$29*(1-'Assumptions'!$E$31)+'Assumptions'!$E$30*'Assumptions'!$E$31))) -> 0 | F11: ='Cash & Runway'!C9 -> 0
A12: Runway (illustrative, months) | B12: Starting cash divided by illustrative month-1 net burn. | C12: =IFERROR('Assumptions'!$C$8/MAX(1,MAX(0,(((('Assumptions'!$C$15*(1-'Assumptions'!$C$28))+((MAX(0,('Assumptions'!$C$13+('Assumptions'!$C$16+'Assumptions'!$C$19+'Assumptions'!$C$22)-'Assumptions'!$C$13*'Assumptions'!$C$14)-('Assumptions'!$C$15*(1-'Assumptions'!$C$28))))*'Assumptions'!$C$27))*('Assumptions'!$C$29*(1-'Assumptions'!$C$31)+'Assumptions'!$C$30*'Assumptions'!$C$31))*('Assumptions'!$C$35+'Assumptions'!$C$36)+('Assumptions'!$C$13+('Assumptions'!$C$16+'Assumptions'!$C$19+'Assumptions'!$C$22)-'Assumptions'!$C$13*'Assumptions'!$C$14)*'Assumptions'!$C$37+(('Assumptions'!$C$15*(1-'Assumptions'!$C$28))+((MAX(0,('Assumptions'!$C$13+('Assumptions'!$C$16+'Assumptions'!$C$19+'Assumptions'!$C$22)-'Assumptions'!$C$13*'Assumptions'!$C$14)-('Assumptions'!$C$15*(1-'Assumptions'!$C$28))))*'Assumptions'!$C$27))*'Assumptions'!$C$38+('Assumptions'!$C$41*'Assumptions'!$C$43))+('Assumptions'!$C$46*'Assumptions'!$C$48+'Assumptions'!$C$51*'Assumptions'!$C$53+'Assumptions'!$C$56*'Assumptions'!$C$58)+((('Assumptions'!$C$16*'Assumptions'!$C$18+'Assumptions'!$C$19*'Assumptions'!$C$21+'Assumptions'!$C$22*'Assumptions'!$C$24))+'Assumptions'!$C$61+'Assumptions'!$C$62+'Assumptions'!$C$63)-((('Assumptions'!$C$15*(1-'Assumptions'!$C$28))+((MAX(0,('Assumptions'!$C$13+('Assumptions'!$C$16+'Assumptions'!$C$19+'Assumptions'!$C$22)-'Assumptions'!$C$13*'Assumptions'!$C$14)-('Assumptions'!$C$15*(1-'Assumptions'!$C$28))))*'Assumptions'!$C$27))*('Assumptions'!$C$29*(1-'Assumptions'!$C$31)+'Assumptions'!$C$30*'Assumptions'!$C$31)))),999) -> 0 | D12: =IFERROR('Assumptions'!$D$8/MAX(1,MAX(0,(((('Assumptions'!$D$15*(1-'Assumptions'!$D$28))+((MAX(0,('Assumptions'!$D$13+('Assumptions'!$D$16+'Assumptions'!$D$19+'Assumptions'!$D$22)-'Assumptions'!$D$13*'Assumptions'!$D$14)-('Assumptions'!$D$15*(1-'Assumptions'!$D$28))))*'Assumptions'!$D$27))*('Assumptions'!$D$29*(1-'Assumptions'!$D$31)+'Assumptions'!$D$30*'Assumptions'!$D$31))*('Assumptions'!$D$35+'Assumptions'!$D$36)+('Assumptions'!$D$13+('Assumptions'!$D$16+'Assumptions'!$D$19+'Assumptions'!$D$22)-'Assumptions'!$D$13*'Assumptions'!$D$14)*'Assumptions'!$D$37+(('Assumptions'!$D$15*(1-'Assumptions'!$D$28))+((MAX(0,('Assumptions'!$D$13+('Assumptions'!$D$16+'Assumptions'!$D$19+'Assumptions'!$D$22)-'Assumptions'!$D$13*'Assumptions'!$D$14)-('Assumptions'!$D$15*(1-'Assumptions'!$D$28))))*'Assumptions'!$D$27))*'Assumptions'!$D$38+('Assumptions'!$D$41*'Assumptions'!$D$43))+('Assumptions'!$D$46*'Assumptions'!$D$48+'Assumptions'!$D$51*'Assumptions'!$D$53+'Assumptions'!$D$56*'Assumptions'!$D$58)+((('Assumptions'!$D$16*'Assumptions'!$D$18+'Assumptions'!$D$19*'Assumptions'!$D$21+'Assumptions'!$D$22*'Assumptions'!$D$24))+'Assumptions'!$D$61+'Assumptions'!$D$62+'Assumptions'!$D$63)-((('Assumptions'!$D$15*(1-'Assumptions'!$D$28))+((MAX(0,('Assumptions'!$D$13+('Assumptions'!$D$16+'Assumptions'!$D$19+'Assumptions'!$D$22)-'Assumptions'!$D$13*'Assumptions'!$D$14)-('Assumptions'!$D$15*(1-'Assumptions'!$D$28))))*'Assumptions'!$D$27))*('Assumptions'!$D$29*(1-'Assumptions'!$D$31)+'Assumptions'!$D$30*'Assumptions'!$D$31)))),999) -> 0 | E12: =IFERROR('Assumptions'!$E$8/MAX(1,MAX(0,(((('Assumptions'!$E$15*(1-'Assumptions'!$E$28))+((MAX(0,('Assumptions'!$E$13+('Assumptions'!$E$16+'Assumptions'!$E$19+'Assumptions'!$E$22)-'Assumptions'!$E$13*'Assumptions'!$E$14)-('Assumptions'!$E$15*(1-'Assumptions'!$E$28))))*'Assumptions'!$E$27))*('Assumptions'!$E$29*(1-'Assumptions'!$E$31)+'Assumptions'!$E$30*'Assumptions'!$E$31))*('Assumptions'!$E$35+'Assumptions'!$E$36)+('Assumptions'!$E$13+('Assumptions'!$E$16+'Assumptions'!$E$19+'Assumptions'!$E$22)-'Assumptions'!$E$13*'Assumptions'!$E$14)*'Assumptions'!$E$37+(('Assumptions'!$E$15*(1-'Assumptions'!$E$28))+((MAX(0,('Assumptions'!$E$13+('Assumptions'!$E$16+'Assumptions'!$E$19+'Assumptions'!$E$22)-'Assumptions'!$E$13*'Assumptions'!$E$14)-('Assumptions'!$E$15*(1-'Assumptions'!$E$28))))*'Assumptions'!$E$27))*'Assumptions'!$E$38+('Assumptions'!$E$41*'Assumptions'!$E$43))+('Assumptions'!$E$46*'Assumptions'!$E$48+'Assumptions'!$E$51*'Assumptions'!$E$53+'Assumptions'!$E$56*'Assumptions'!$E$58)+((('Assumptions'!$E$16*'Assumptions'!$E$18+'Assumptions'!$E$19*'Assumptions'!$E$21+'Assumptions'!$E$22*'Assumptions'!$E$24))+'Assumptions'!$E$61+'Assumptions'!$E$62+'Assumptions'!$E$63)-((('Assumptions'!$E$15*(1-'Assumptions'!$E$28))+((MAX(0,('Assumptions'!$E$13+('Assumptions'!$E$16+'Assumptions'!$E$19+'Assumptions'!$E$22)-'Assumptions'!$E$13*'Assumptions'!$E$14)-('Assumptions'!$E$15*(1-'Assumptions'!$E$28))))*'Assumptions'!$E$27))*('Assumptions'!$E$29*(1-'Assumptions'!$E$31)+'Assumptions'!$E$30*'Assumptions'!$E$31)))),999) -> 0 | F12: ='Cash & Runway'!AL11 -> 0
A14: Scenario Validity
A15: Selector value is valid (Base/Upside/Downside)? | C15: =IF(ISNUMBER(MATCH('Assumptions'!$C$4,{"Base","Upside","Downside"},0)),"OK","INVALID") -> 0

Sheet Visuals
A1: Consumer Subscription — 3-Year Financial Model — Visuals
A2: MAU, paid conversion, unit economics, cash, headcount, and scenario trends for the Consumer Subscription model.
A4: MAU (Month 36) | D4: Paid Subs (Month 36) | G4: Revenue (Month 36) | J4: Gross Margin % (Month 36) | M4: LTV : CAC (Month 36) | P4: Runway (months)
A5: ='Revenue'!AL21 -> 0 | D5: ='Revenue'!AL28 -> 0 | G5: ='Revenue'!AL35 -> 0 | J5: ='COGS & GM'!AL17 -> 0 | M5: ='COGS & GM'!AL20 -> 0 | P5: ='Cash & Runway'!AL11 -> 0

Sheet Checks
A1: Consumer Subscription — 3-Year Financial Model — Checks
A2: Every control below should read PASS. If anything reads FAIL, trace it back through the linked tabs before trusting the outputs.
A4: Check | B4: Description | C4: Metric | D4: Status
A5: Balance Sheet balances | B5: MAX absolute (Assets − Liabilities&Equity) across all 36 months | C5: {=MAX(ABS('Balance Sheet'!C26:AL26))} -> 0 | D5: {=IF(MAX(ABS('Balance Sheet'!C26:AL26))<1.0,"PASS","FAIL")} -> 0
A6: Cash Flow reconciles to Balance Sheet | B6: MAX absolute difference between BS cash and CF ending cash across all 36 months | C6: {=MAX(ABS('Balance Sheet'!C8:AL8-'Cash Flow'!C28:AL28))} -> 0 | D6: {=IF(MAX(ABS('Balance Sheet'!C8:AL8-'Cash Flow'!C28:AL28))<1.0,"PASS","FAIL")} -> 0
A7: Retained Earnings roll-forward | B7: MAX absolute (RE(m) − RE(m−1) − NetIncome(m)) for months 2-36 | C7: {=MAX(ABS('Balance Sheet'!D22:AL22-'Balance Sheet'!C22:AK22-'P&L'!D24:AL24))} -> 0 | D7: {=IF(MAX(ABS('Balance Sheet'!D22:AL22-'Balance Sheet'!C22:AK22-'P&L'!D24:AL24))<1.0,"PASS","FAIL")} -> 0
A8: P&L subtotal integrity | B8: MAX absolute error across Gross Profit / EBITDA / EBIT / EBT / Net Income subtotals | C8: {=MAX(MAX(ABS(('P&L'!C7:AL7-'P&L'!C8:AL8)-'P&L'!C9:AL9)),MAX(ABS(('P&L'!C9:AL9-'P&L'!C16:AL16)-'P&L'!C18:AL18)),MAX(ABS(('P&L'!C18:AL18-'P&L'!C19:AL19)-'P&L'!C20:AL20)),MAX(ABS(('P&L'!C20:AL20-'P&L'!C21:AL21)-'P&L'!C22:AL22)),MAX(ABS(('P&L'!C22:AL22-'P&L'!C23:AL23)-'P&L'!C24:AL24)))} -> 0 | D8: {=IF(MAX(MAX(ABS(('P&L'!C7:AL7-'P&L'!C8:AL8)-'P&L'!C9:AL9)),MAX(ABS(('P&L'!C9:AL9-'P&L'!C16:AL16)-'P&L'!C18:AL18)),MAX(ABS(('P&L'!C18:AL18-'P&L'!C19:AL19)-'P&L'!C20:AL20)),MAX(ABS(('P&L'!C20:AL20-'P&L'!C21:AL21)-'P&L'!C22:AL22)),MAX(ABS(('P&L'!C22:AL22-'P&L'!C23:AL23)-'P&L'!C24:AL24)))<1.0,"PASS","FAIL")} -> 0
A9: Scenario selector validity | B9: Assumptions scenario selector must equal Base, Upside, or Downside | C9: {=IF('Scenarios'!C15="OK",1,0)} -> 0 | D9: {=IF('Scenarios'!C15="OK","PASS","FAIL")} -> 0
A10: No formula errors | B10: Count of #REF!/#DIV0!/#VALUE! etc. across all key schedules (Headcount through Cash & Runway) | C10: {=SUMPRODUCT(--ISERROR('Headcount'!C5:BC260))+SUMPRODUCT(--ISERROR('Revenue'!C5:BC260))+SUMPRODUCT(--ISERROR('COGS & GM'!C5:BC260))+SUMPRODUCT(--ISERROR('Opex'!C5:BC260))+SUMPRODUCT(--ISERROR('Working Capital'!C5:BC260))+SUMPRODUCT(--ISERROR('P&L'!C5:BC260))+SUMPRODUCT(--ISERROR('Balance Sheet'!C5:BC260))+SUMPRODUCT(--ISERROR('Cash Flow'!C5:BC260))+SUMPRODUCT(--ISERROR('Cash & Runway'!C5:BC260))} -> 0 | D10: {=IF((SUMPRODUCT(--ISERROR('Headcount'!C5:BC260))+SUMPRODUCT(--ISERROR('Revenue'!C5:BC260))+SUMPRODUCT(--ISERROR('COGS & GM'!C5:BC260))+SUMPRODUCT(--ISERROR('Opex'!C5:BC260))+SUMPRODUCT(--ISERROR('Working Capital'!C5:BC260))+SUMPRODUCT(--ISERROR('P&L'!C5:BC260))+SUMPRODUCT(--ISERROR('Balance Sheet'!C5:BC260))+SUMPRODUCT(--ISERROR('Cash Flow'!C5:BC260))+SUMPRODUCT(--ISERROR('Cash & Runway'!C5:BC260)))=0,"PASS","FAIL")} -> 0
A12: ALL CHECKS | B12: Overall model integrity status | D12: =IF(AND(D5="PASS",D6="PASS",D7="PASS",D8="PASS",D9="PASS",D10="PASS"),"ALL PASS","REVIEW NEEDED") -> 0
